Workbook
Name _1: #REF!
Name _2: #REF!
Name _3: #REF!
Name _4: #REF!
Name _5: #REF!
Name a: #REF!
Name Accounts: #REF!
Name Activity_Reports: #REF!
Name ADM: #REF!
Name Application: [6]!Table6[Application]
Name B: #REF!
Name back: #REF!
Name Calendar: #REF!
Name Catalogue_xls: #REF!
Name CompanyCode: [11]CompanyCode!$A$2:$A$5
Name Contractingdiv: #REF!
Name corporate_affairs: #REF!
Name CTY: '[12]0.CTY'!$D:$D
Name Data_Values: '[16]Single Measure Analysis'!$B$29:$M$30
Name DATA13: '[17]2.1Raw material_details'!#REF!
Name DATA14: '[17]2.1Raw material_details'!#REF!
Name DATA15: '[17]2.1Raw material_details'!#REF!
Name DATA16: '[17]2.1Raw material_details'!#REF!
Name DATA17: '[17]2.1Raw material_details'!#REF!
Name DATA18: '[17]2.1Raw material_details'!#REF!
Name DATA19: '[17]2.1Raw material_details'!#REF!
Name DATA20: '[17]2.1Raw material_details'!#REF!
Name DATA21: '[17]2.1Raw material_details'!#REF!
Name DATA22: '[17]2.1Raw material_details'!#REF!
Name DATA23: '[17]2.1Raw material_details'!#REF!
Name DATA24: '[17]2.1Raw material_details'!#REF!
Name DATA25: '[17]2.1Raw material_details'!#REF!
Name DATA26: '[17]2.1Raw material_details'!#REF!
Name DATA27: '[17]2.1Raw material_details'!#REF!
Name DATA28: '[17]2.1Raw material_details'!#REF!
Name DATA29: '[17]2.1Raw material_details'!#REF!
Name DATA30: '[17]2.1Raw material_details'!#REF!
Name DATA31: '[17]2.1Raw material_details'!#REF!
Name DATA32: '[17]2.1Raw material_details'!#REF!
Name DATA33: '[17]2.1Raw material_details'!#REF!
Name DATA34: '[17]2.1Raw material_details'!#REF!
Name DATA35: '[17]2.1Raw material_details'!#REF!
Name DATA36: '[17]2.1Raw material_details'!#REF!
Name DATA37: '[17]2.1Raw material_details'!#REF!
Name Date_of_separation: #REF!
Name DeptCode: #REF!
Name dinhbien2021: #REF!
Name DivisionCode: #REF!
Name dow: #REF!
Name DT: #REF!
Name ERP: #REF!
Name Excise: #REF!
Name Expectations: #REF!
Name EXR: [19]Asm.!$B$2
Name EXR: #REF!
Name fdg: [20]!MeasureList
Name Finanacialsys: #REF!
Name Financialsys: #REF!
Name GENERAL: #REF!,#REF!,#REF!,#REF!,#REF!,#REF!,#REF!
Name GrossUp: #REF!

Sheet Timeline & PIC
B1: DUY TAN GROUP
B2: =IF(B3="EN","Schedule Annual Plan 2025","Lịch lập NGÂN SÁCH năm 2026") -> Lịch lập NGÂN SÁCH năm 2026 | D2: =IF(B3="EN","Start:","Bắt đầu:") -> Bắt đầu: | E2: 45915
B3: ='[28]Overview-BC Tongquan'!B2 -> VN | D3: =IF(B3="EN","Finish:","Kết thúc:") -> Kết thúc: | E3: =G22 -> 45990 | G3: =E3-E2 -> 75
D4: =IF(B3="en","SENDER","Đơn vị gửi") -> Đơn vị gửi | E4: =IF(B3="EN","RECEIVER","Đơn vị nhận") -> Đơn vị nhận | G4: Deadline | H4: THÁNG 09 | AM4: THÁNG 10 | BR4: THÁNG 11
B5: No. | C5: =IF(B3="EN","PROCESS","TRÌNH TỰ THỰC HIỆN") -> TRÌNH TỰ THỰC HIỆN | F5: Thời gian | H5: 1 | I5: 2 | J5: 3 | K5: 4 | L5: 5 | M5: 6 | N5: 7 | O5: 8 | P5: 9 | Q5: 10 | R5: 11 | S5: 12 | T5: 13 | U5: 14 | V5: 15 | W5: 16 | X5: 17 | Y5: 18 | Z5: 19 | AA5: 20 | AB5: 21 | AC5: 22 | AD5: 23 | AE5: 24 | AF5: 25 | AG5: 26 | AH5: 27 | AI5: 28 | AJ5: 29 | AK5: 30 | AL5: 31 | AM5: 1 | AN5: 2 | AO5: 3 | AP5: 4 | AQ5: 5 | AR5: 6 | AS5: 7 | AT5: 8 | AU5: 9 | AV5: 10 | AW5: 11 | AX5: 12 | AY5: 13 | AZ5: 14 | BA5: 15 | BB5: 16 | BC5: 17 | BD5: 18 | BE5: 19 | BF5: 20 | BG5: 21 | BH5: 22 | BI5: 23 | BJ5: 24 | BK5: 25 | BL5: 26 | BM5: 27 | BN5: 28 | BO5: 29 | BP5: 30 | BQ5: 31 | BR5: 1 | BS5: =BR5+1 -> 2 | BT5: =BS5+1 -> 3 | BU5: =BT5+1 -> 4 | BV5: =BU5+1 -> 5 | BW5: =BV5+1 -> 6 | BX5: =BW5+1 -> 7 | BY5: =BX5+1 -> 8 | BZ5: =BY5+1 -> 9 | ... CT5: =CS5+1 -> 29 | CU5: 30
F6: (Ngày) | H6: M | I6: T | J6: W | K6: TH | L6: F | M6: Sa | N6: Su | O6: M | P6: T | Q6: W | R6: TH | S6: F | T6: Sa | U6: Su | V6: M | W6: T | X6: W | Y6: TH | Z6: F | AA6: Sa | AB6: Su | AC6: M | AD6: T | AE6: W | AF6: TH | AG6: F | AH6: Sa | AI6: Su | AJ6: M | AK6: T | AL6: W | AM6: TH | AN6: F | AO6: Sa | AP6: Su | AQ6: M | AR6: T | AS6: W | AT6: TH | AU6: F | AV6: Sa | AW6: Su | AX6: M | AY6: T | AZ6: W | BA6: TH | BB6: F | BC6: Sa | BD6: Su | BE6: M | BF6: T | BG6: W | BH6: TH | BI6: F | BJ6: Sa | BK6: Su | BL6: M | BM6: T | BN6: W | BO6: TH | BP6: F | BQ6: Sa | BR6: Su | BS6: M | BT6: T | BU6: W | BV6: TH | BW6: F | BX6: Sa | BY6: Su | BZ6: M | CA6: T | CB6: W | CC6: TH | CD6: F | CE6: Sa | CF6: Su | CG6: M | CH6: T | CI6: W | CJ6: TH | CK6: F | CL6: Sa | CM6: Su | CN6: M | CO6: T | CP6: W | CQ6: TH | CR6: F | CS6: Sa | CT6: Su | CU6: M
B7: 1 | C7: Khởi động | D7: GĐTC holding | E7: =IF(B3="EN","All","Tất cả") -> Tất cả | G7: =E2 -> 45915
B8: 2 | C8: Kế hoạch Doanh thu / Sản lượng | D8: =IF(B3="EN","Sales team","Phòng kinh doanh") -> Phòng kinh doanh | E8: =IF(B3="EN","Acct.","Kế toán") -> Kế toán | F8: 15 | G8: =F8+$G$7 -> 45930
B9: 3 | C9: Kế hoạch giá cả nguyên vật liệu | D9: =IF(B2="EN","Supply chain","Chuỗi cung ứng") -> Chuỗi cung ứng | E9: =E8 -> Kế toán | F9: 15 | G9: =F9+$G$7 -> 45930
B10: =B9+1 -> 4 | C10: Kế hoạch chi phí vận chuyển, cước xuất khẩu,... | D10: =IF(B3="EN","Supply chain","Chuổi cung ứng") -> Chuổi cung ứng | E10: =E9 -> Kế toán | F10: 15 | G10: =F10+$G$7 -> 45930
B11: =B10+1 -> 5 | C11: Kế hoạch sản xuất | D11: =IF(B3="EN","Production","Bộ phận sản xuất") -> Bộ phận sản xuất | E11: =E10 -> Kế toán | F11: 20 | G11: =F11+$G$7 -> 45935
B12: =B11+1 -> 6 | C12: Kế hoạch biến phí sản xuất | D12: =E12 -> Kế toán | E12: =E11 -> Kế toán | F12: 20 | G12: =F12+$G$7 -> 45935
B13: =B12+1 -> 7 | C13: Kế hoạch nhân sự (số lượng nhân sự, quỹ lương, chi phí đào tạo,...) | D13: =IF(B3="EN","HR","Phòng nhân sự") -> Phòng nhân sự | E13: =E12 -> Kế toán | F13: 30 | G13: =F13+$G$7 -> 45945
B14: =B13+1 -> 8 | C14: Ngân sách đầu tư | D14: =E7 -> Tất cả | E14: =E13 -> Kế toán | F14: 30 | G14: =F14+$G$7 -> 45945
B15: =B14+1 -> 9 | C15: Ngân sách chi phí sản xuất (không bao gồm lương) | D15: =D11 -> Bộ phận sản xuất | E15: =E14 -> Kế toán | F15: 30 | G15: =F15+$G$7 -> 45945
B16: =B15+1 -> 10 | C16: Ngân sách chi phí bán hàng & chí phí quản lý (không bao gồm lương) | D16: =D14 -> Tất cả | E16: =E15 -> Kế toán | F16: 30 | G16: =F16+$G$7 -> 45945
B17: =B16+1 -> 11 | C17: Tổng hợp kết quả ngân sách mỗi công ty | D17: Kế toán quản trị | E17: KTT/GĐTC | F17: 45 | G17: =F17+$G$7 -> 45960
B18: 12 | C18: Trình bày kết quả ngân sách của mỗi công ty đến TGĐ (Bottom up) | D18: KTT/GĐTC | E18: TGĐ | F18: 50 | G18: =F18+$G$7 -> 45965
B19: 13 | C19: Trình bày kết quả ngân sách của mỗi công ty đến TGĐ (Top down) | D19: KTT/GĐTC | E19: TGĐ | F19: 55 | G19: =F19+$G$7 -> 45970
B20: 14 | C20: Trình bày kết quả ngân sách của mỗi công ty đến TGĐ (Chính thức) | D20: KTT/GĐTC | E20: TGĐ | F20: 62 | G20: =F20+$G$7 -> 45977
B21: 15 | C21: Hợp nhất ngân sách cho toàn bộ DT Group | D21: KTQT holding | E21: GĐTC holding | F21: 70 | G21: =F21+$G$7 -> 45985
B22: 16 | C22: Trình bày kết quả ngân sách hợp nhất cho toàn bộ DT Group | D22: GĐTC holding | E22: TGĐ | F22: 75 | G22: =F22+$G$7 -> 45990

Sheet Thongtin
B2: STT | C2: Nội dung | D2: Nguồn cung cấp dữ liệu | E2: Nguồn thông tin liên quan | F2: Thời gian cần dữ liệu | H2: STT | I2: Màu sheet | J2: Thông tin
B3: 1 | C3: Ban hành Nhóm-Loại NVL Trạm thu mua | D3: GĐĐH Trạm - DTR | E3: 1. BGĐ DTR 2. Phòng cung ứng DTR | F3: 45940 | H3: 1 | J3: Kết quả kinh doanh tổng hợp
B4: 2 | C4: Ban hành Sản lượng Trạm thu mua | D4: GĐĐH Trạm - DTR | E4: 1. BGĐ DTR 2. Phòng cung ứng DTR | F4: 45940 | H4: 2 | J4: Kết quả kinh doanh PET và HD
B5: 3 | C5: Ban hành đơn giá MUA từng loại NVL | D5: GĐĐH Trạm - DTR | E5: 1. Phòng cung ứng DTR đề xuất KH năm 2026 (Dữ liệu theo từng tháng) 2. KTT các trạm cung cấp đơn giá bình quân thực tế mua theo từng tháng ( Dữ liệu năm 2023-2024-2025) 3. Đơn giá BGĐ-DTR duyệt mua trong năm 2025 (Dữ liệu theo từng tháng) | F5: 45940 | H5: 3 | J5: Kết quả kinh doanh PET và HD
B6: 4 | C6: Ban hành đơn giá BÁN từng loại thành phẩm | D6: GĐĐH Trạm - DTR | E6: 1. BGĐ DTR 2. Phòng cung ứng DTR | F6: 45940 | H6: 4 | J6: Ban hành Định mức về Công suất MMTB - Định mức về CP phục vụ sản xuất - Định biên Nhân sự
B7: 5 | C7: Kế hoạch đầu tư CAPEX tại Trạm => Ảnh hưởng đến Sản phẩm và TCKT Trạm cung cấp đến DTR | D7: GĐĐH Trạm - DTR | E7: 1. BGĐ DTR 2. Phòng kỹ thuật DTR 3. Phòng mua hàng DTR | F7: 45940 | H7: 5 | J7: Ban hành sản lượng - đơn giá - Cơ cấu về: NVL - Thành phẩm - Hao hụt - Bán hàng
H8: 6 | J8: Nhóm Chi phí:CP Sản xuất - CP Bán hàng - CP Quản lý (Công thức từ: Định mức - Lương - PB_TSCD - PB_CPTT - nhóm NVL - Phát sinh trực tiếp)
H9: 7 | J9: Cập nhật TSCĐ - CPTT năm trước chuyển sang và Capex 2026
H10: 8 | I10: … | J10: Thông tin khác

Sheet KH hanh dong
A3: KẾ HOẠCH KINH DOANH 2026
A4: Nguồn yêu cầu: GĐTC-DTR
A5: STT | B5: Nhóm công việc | C5: Kế hoạch hành động | D5: Người thực hiện | E5: Thời gian hoàn thành tính toán và xác lập mục tiêu 2026 | F5: Hiện trạng / vướng mắt / giải pháp (tại thời điểm tháng 10/2025) | G5: Mục tiêu 2026 (rolling hàng tháng) | U5: KHNS 2026 | V5: Thực hiện 2025 | W5: Tăng/giảm vs KHNS 2026
G6: Đánh giá KQ đạt được (cập nhật đến thời điểm báo cáo) | H6: Mục tiêu T1 | I6: Mục tiêu T2 | J6: Mục tiêu T3 | K6: Mục tiêu T4 | L6: Mục tiêu T5 | M6: Mục tiêu T6 | N6: Mục tiêu T7 | O6: Mục tiêu T8 | P6: Mục tiêu T9 | Q6: Mục tiêu T10 | R6: Mục tiêu T11 | S6: Mục tiêu T12 | T6: Dự báo KQ 2026 | W6: Theo số tiền phát sinh | X6: Theo mức độ hoạt động | Y6: %
A7: A | B7: HOẠT ĐỘNG MUA HÀNG
A8: 1 | B8: Đáp ứng sản lượng mua cho Trạm | C8: Lập mục tiêu sản lượng mua để Trạm đạt hòa vốn và có lãi.
C9: Xây dựng các trạm vệ tinh để tăng lượng chai về Trạm.
C10: Phát triển thêm các NCC liên kết ở tỉnh.
C11: Đàm phán tăng sản lượng mua từ các NCC đang giao dịch.
A12: 2 | B12: Cải thiện dịch vụ khách hàng | C12: Cải thiện thời gian nhận hàng
C13: Thanh toán trong ngày và cuối tuần
A14: B | B14: HOẠT ĐỘNG BÁN HÀNG
A15: 1 | B15: Giá bán về DTR | C15: Áp dụng cơ cấu giá mới từ Tháng 9/2025
A16: 2 | B16: Kiểm soát tồn kho thành phẩm | C16: Lập KH giao hàng về DTR hàng ngày, ngày cuối tháng không để tồn kho và xuất hóa đơn 100%
A17: 3 | B17: Chi phí thuê xe vận chuyển | C17: - Đàm phán giảm giá, đề nghị NCC sử dụng phương tiện vận chuyển hiệu quả. - Tìm NCC mới cạnh tranh.
A18: C | B18: HOẠT ĐỘNG CẢI TIẾN CHI PHÍ
A19: I | B19: Chi phí nguyên vật liệu
A20: 1 | B20: Kiểm soát lượng mua, giá mua | C20: - Lập mục tiêu tồn kho tối thiểu 10 ngày sản xuất và phối hợp P.Cung ứng lập KH mua hàng theo tuần. - Kiểm soát giá mua tương ứng với từng mức chất lượng chai.
A21: 2 | B21: Kiểm soát chất lượng NVL, hao hụt | C21: Kiểm soát chất lượng chai (tỷ lệ chai nguyên liệu - Chai xá/xô tuyển, thành phần chai sau phân loại, tỷ lệ tạp chất).
A22: 3 | B22: Kiểm soát định mức vật tư sản xuất (hóa chất, dây đai, vật tư kỹ thuật …) | C22: - Thống kê và thực hiện cải tiến tiêu hao. - Mua tập trung tại P.Mua hàng DTR.
A23: 4 | B23: Xử lý phế liệu, phó sản thu hồi | C23: Phân loại phế liệu thành 2 nhóm: - Nhóm hàng hóa (nhãn, bao jumbo, kim loại,…): tìm đơn vị thu mua giá cao - Nhóm rác thải công nghiệp (bùn, hỗn hợp tạp chất): thuê thu gom
A24: II | B24: Chi phí nhân công
A25: 1 | B25: Định mức NCTT | C25: - Kiểm soát định mức NCTT theo chuyền/công đoạn. - Thực hiện tiêu chuẩn hóa/tự động hóa MMTB để giảm nhân công, tăng năng suất. - Tăng số lượng lao động thời vụ. - Tính toán phương án trả lương/ thưởng theo sản lượng.
A26: 2 | B26: Năng suất lao động | C26: - Lập mục tiêu tăng thời gian sản xuất từ 8 giờ/ngày -> 12 giờ -> 16 giờ -> 24 giờ.
A27: III | B27: Chi phí sản xuất chung
A28: 1 | B28: Chi phí điện | C28: - Phối hợp kỹ thuật bảo trì MMTB đảm bảo hoạt động liên tục -> tăng hiệu quả sử dụng điện và tăng năng suất lao động.
A29: 2 | B29: Chi phí xe nâng | C29: - Chuyển dần xe nâng dầu từ DTR về các Trạm (các xe của trạm sửa chữa nhiều sẽ thanh lý)
A30: 3 | B30: Chi phí khấu hao TSCĐ, CCDC, chi phí phân bổ khác | C30: - Thống kê, đánh giá lại hiệu quả sử dụng tất cả TS. - Tách chi phí khấu hao/phân bổ không phục vụ trực tiếp hoạt động để đánh giá hiệu quả KD thực của trạm.
A31: 4 | B31: Chi phí thuê xưởng | C31: - Tìm vị trí và đề xuất phương án di dời nhà máy để giảm tiền thu, tăng hiệu quả thu mua.
A32: IV | B32: Chi phí quản lý
A33: 1 | B33: Chi phí lương (gồm gián tiếp SX) | C33: Soát xét định biên và kế hoạch tuyển dụng, lập mục tiêu giảm định biên đến cuối 2026
A34: 2 | B34: Chi phí theo mục phí (ngoài chi phí lương) | C34: - Lập danh mục chi phí dịch vụ thuê/mua trả tiền định kỳ (nhóm dịch vụ/phòng ban quản lý, tên NCC, hợp đồng mới nhất, tiền trả định kỳ tháng/quý/năm, thời hạn công nợ) -> đàm phán từng NC giảm giá và tìm NCC mới cạnh tranh - XD định mức chi phí cho các khoản mục có thể xác lập định mức - Phân tích chi phí, nguyên nhân tăng/giảm và giải pháp cải tiến.
A35: V | B35: Mục tiêu lợi nhuận
A36: 1 | B36: Lợi nhuận kế hoạch đến cuối năm 2026 | C36: Sau khi đánh giá, xác lập các mục tiêu bên trên, tính toán lợi nhuận kế hoạch đến cuối năm 2026

Sheet KQKD Tong hop
B3: MỤC TIÊU KẾT QUẢ KINH DOANH NĂM 2026 | S3: ĐVT: Triệu đồng
B4: STT | C4: Mục phí | D4: Thực tế năm 2023 | E4: Thực tế năm 2024 | F4: KQKD 2025 | G4: T1 | H4: T2 | I4: T3 | J4: T4 | K4: T5 | L4: T6 | M4: T7 | N4: T8 | O4: T9 | P4: T10 | Q4: T11 | R4: T12 | S4: Kế hoạch 2026 | U4: KQKD 2025 | V4: KH 2026 | X4: KQKD 2025 | Y4: KH 2026
B5: 1 | C5: SẢN LƯỢNG BÁN (TẤN) | D5: ='KQKD PET'!D5 -> 5652770.5 | E5: ='KQKD PET'!E5 -> 4895018.4 | F5: ='KQKD PET'!F5 -> 5879799 | G5: =G6+G7+G8 -> 533700 | H5: =H6+H7+H8 -> 400275 | I5: =I6+I7+I8 -> 578175 | J5: =J6+J7+J8 -> 622650 | K5: =K6+K7+K8 -> 622650 | L5: =L6+L7+L8 -> 622650 | M5: =M6+M7+M8 -> 622650 | N5: =N6+N7+N8 -> 622650 | ... R5: =R6+R7+R8 -> 622650 | S5: =SUM(G5:R5) -> 7116000 | V5: =S5/F5 -> 1.2102455
B6: 1.1 | C6: Chai PET | D6: ='KQKD PET'!D6 -> 5652770.5 | E6: ='KQKD PET'!E6 -> 4895018.4 | F6: ='KQKD PET'!F6 -> 5879799 | G6: ='KQKD PET'!G6+'KQKD HD'!F6 -> 533700 | H6: ='KQKD PET'!H6+'KQKD HD'!G6 -> 400275 | I6: ='KQKD PET'!I6+'KQKD HD'!H6 -> 578175 | J6: ='KQKD PET'!J6+'KQKD HD'!I6 -> 622650 | K6: ='KQKD PET'!K6+'KQKD HD'!J6 -> 622650 | L6: ='KQKD PET'!L6+'KQKD HD'!K6 -> 622650 | M6: ='KQKD PET'!M6+'KQKD HD'!L6 -> 622650 | N6: ='KQKD PET'!N6+'KQKD HD'!M6 -> 622650 | ... R6: ='KQKD PET'!R6+'KQKD HD'!Q6 -> 622650 | S6: =SUM(G6:R6) -> 7116000 | U6: =S6/F6 -> 1.2102455 | V6: =S6/F6 -> 1.2102455
B7: 1.2 | C7: Vảy PET | D7: ='KQKD PET'!D7 -> 0 | E7: ='KQKD PET'!E7 -> 0 | F7: ='KQKD PET'!F7 -> 0 | G7: ='KQKD PET'!G7+'KQKD HD'!F7 -> 0 | H7: ='KQKD PET'!H7+'KQKD HD'!G7 -> 0 | I7: ='KQKD PET'!I7+'KQKD HD'!H7 -> 0 | J7: ='KQKD PET'!J7+'KQKD HD'!I7 -> 0 | K7: ='KQKD PET'!K7+'KQKD HD'!J7 -> 0 | L7: ='KQKD PET'!L7+'KQKD HD'!K7 -> 0 | M7: ='KQKD PET'!M7+'KQKD HD'!L7 -> 0 | N7: ='KQKD PET'!N7+'KQKD HD'!M7 -> 0 | ... R7: ='KQKD PET'!R7+'KQKD HD'!Q7 -> 0 | S7: =SUM(G7:R7) -> 0
B8: 1.3 | C8: Vảy HD | D8: ='KQKD PET'!D8 -> 0 | E8: ='KQKD PET'!E8 -> 0 | F8: ='KQKD PET'!F8 -> 0 | G8: ='KQKD PET'!G8+'KQKD HD'!F8 -> 0 | H8: ='KQKD PET'!H8+'KQKD HD'!G8 -> 0 | I8: ='KQKD PET'!I8+'KQKD HD'!H8 -> 0 | J8: ='KQKD PET'!J8+'KQKD HD'!I8 -> 0 | K8: ='KQKD PET'!K8+'KQKD HD'!J8 -> 0 | L8: ='KQKD PET'!L8+'KQKD HD'!K8 -> 0 | M8: ='KQKD PET'!M8+'KQKD HD'!L8 -> 0 | N8: ='KQKD PET'!N8+'KQKD HD'!M8 -> 0 | ... R8: ='KQKD PET'!R8+'KQKD HD'!Q8 -> 0 | S8: =SUM(G8:R8) -> 0
B9: 2 | C9: DOANH THU | D9: ='KQKD PET'!D9 -> 78915665269 | E9: ='KQKD PET'!E9 -> 74523104085 | F9: ='KQKD PET'!F9 -> 97725917198 | G9: =G10+G11+G12+G13 -> 7469550000 | H9: =H10+H11+H12+H13 -> 5602162500 | I9: =I10+I11+I12+I13 -> 8092012500 | J9: =J10+J11+J12+J13 -> 8714475000 | K9: =K10+K11+K12+K13 -> 8714475000 | L9: =L10+L11+L12+L13 -> 8714475000 | M9: =M10+M11+M12+M13 -> 8714475000 | N9: =N10+N11+N12+N13 -> 8714475000 | ... R9: =R10+R11+R12+R13 -> 8714475000 | S9: =SUM(G9:R9) -> 99594000000 | U9: =F9/F$9 -> 1 | V9: =S9/S$9 -> 1 | X9: =F9/F5 -> 16620.622 | Y9: =S9/S5 -> 13995.784 | Z9: =Y9-X9 -> -2624.838
B10: 2.1 | C10: Chai PET | D10: ='KQKD PET'!D10 -> 78915665269 | E10: ='KQKD PET'!E10 -> 74523104085 | F10: ='KQKD PET'!F10 -> 97725917198 | G10: ='KQKD PET'!G10+'KQKD HD'!F10 -> 7469550000 | H10: ='KQKD PET'!H10+'KQKD HD'!G10 -> 5602162500 | I10: ='KQKD PET'!I10+'KQKD HD'!H10 -> 8092012500 | J10: ='KQKD PET'!J10+'KQKD HD'!I10 -> 8714475000 | K10: ='KQKD PET'!K10+'KQKD HD'!J10 -> 8714475000 | L10: ='KQKD PET'!L10+'KQKD HD'!K10 -> 8714475000 | M10: ='KQKD PET'!M10+'KQKD HD'!L10 -> 8714475000 | N10: ='KQKD PET'!N10+'KQKD HD'!M10 -> 8714475000 | ... R10: ='KQKD PET'!R10+'KQKD HD'!Q10 -> 8714475000 | S10: =SUM(G10:R10) -> 99594000000 | U10: =F10/F$9 -> 1 | V10: =S10/S$9 -> 1
B11: 2.2 | C11: Vảy PET | D11: ='KQKD PET'!D11 -> 0 | E11: ='KQKD PET'!E11 -> 0 | F11: ='KQKD PET'!F11 -> 0 | G11: ='KQKD PET'!G11+'KQKD HD'!F11 -> 0 | H11: ='KQKD PET'!H11+'KQKD HD'!G11 -> 0 | I11: ='KQKD PET'!I11+'KQKD HD'!H11 -> 0 | J11: ='KQKD PET'!J11+'KQKD HD'!I11 -> 0 | K11: ='KQKD PET'!K11+'KQKD HD'!J11 -> 0 | L11: ='KQKD PET'!L11+'KQKD HD'!K11 -> 0 | M11: ='KQKD PET'!M11+'KQKD HD'!L11 -> 0 | N11: ='KQKD PET'!N11+'KQKD HD'!M11 -> 0 | ... R11: ='KQKD PET'!R11+'KQKD HD'!Q11 -> 0 | S11: =SUM(G11:R11) -> 0 | U11: =F11/F$9 -> 0 | V11: =S11/S$9 -> 0
B12: 2.3 | C12: Vảy HD | D12: ='KQKD PET'!D12 -> 0 | E12: ='KQKD PET'!E12 -> 0 | F12: ='KQKD PET'!F12 -> 0 | G12: ='KQKD PET'!G12+'KQKD HD'!F12 -> 0 | H12: ='KQKD PET'!H12+'KQKD HD'!G12 -> 0 | I12: ='KQKD PET'!I12+'KQKD HD'!H12 -> 0 | J12: ='KQKD PET'!J12+'KQKD HD'!I12 -> 0 | K12: ='KQKD PET'!K12+'KQKD HD'!J12 -> 0 | L12: ='KQKD PET'!L12+'KQKD HD'!K12 -> 0 | M12: ='KQKD PET'!M12+'KQKD HD'!L12 -> 0 | N12: ='KQKD PET'!N12+'KQKD HD'!M12 -> 0 | ... R12: ='KQKD PET'!R12+'KQKD HD'!Q12 -> 0 | S12: =SUM(G12:R12) -> 0 | U12: =F12/F$9 -> 0 | V12: =S12/S$9 -> 0
B13: 2.4 | C13: Khác | D13: ='KQKD PET'!D13 -> 0 | E13: ='KQKD PET'!E13 -> 0 | F13: ='KQKD PET'!F13 -> 0 | G13: ='KQKD PET'!G13+'KQKD HD'!F13 -> 0 | H13: ='KQKD PET'!H13+'KQKD HD'!G13 -> 0 | I13: ='KQKD PET'!I13+'KQKD HD'!H13 -> 0 | J13: ='KQKD PET'!J13+'KQKD HD'!I13 -> 0 | K13: ='KQKD PET'!K13+'KQKD HD'!J13 -> 0 | L13: ='KQKD PET'!L13+'KQKD HD'!K13 -> 0 | M13: ='KQKD PET'!M13+'KQKD HD'!L13 -> 0 | N13: ='KQKD PET'!N13+'KQKD HD'!M13 -> 0 | ... R13: ='KQKD PET'!R13+'KQKD HD'!Q13 -> 0 | S13: =SUM(G13:R13) -> 0 | U13: =F13/F$9 -> 0 | V13: =S13/S$9 -> 0
B14: 3 | C14: BIẾN PHÍ | D14: ='KQKD PET'!D14 -> 7.4913898e+10 | E14: ='KQKD PET'!E14 -> 70945682854 | F14: ='KQKD PET'!F14 -> 8.7040525e+10 | G14: =G15+G23 -> 6.6989855e+09 | H14: =H15+H23 -> 5.1345336e+09 | I14: =I15+I23 -> 7.2126164e+09 | J14: =J15+J23 -> 7.7629387e+09 | K14: =K15+K23 -> 7.7380763e+09 | L14: =L15+L23 -> 7.7567254e+09 | M14: =M15+M23 -> 7.7882538e+09 | N14: =N15+N23 -> 7.8002203e+09 | ... R14: =R15+R23 -> 7.7463711e+09 | S14: =SUM(G14:R14) -> 8.8930411e+10 | U14: =F14/F$9 -> 0.89065959 | V14: =S14/S$9 -> 0.89292941
B15: 3.1 | C15: BIẾN PHÍ SẢN XUẤT | D15: ='KQKD PET'!D15 -> 7.3435299e+10 | E15: ='KQKD PET'!E15 -> 69651631026 | F15: ='KQKD PET'!F15 -> 8.5723904e+10 | G15: =G16+G20+G21+G22 -> 6.5846212e+09 | H15: =H16+H20+H21+H22 -> 5.0487604e+09 | I15: =I16+I20+I21+I22 -> 7.0887217e+09 | J15: =J16+J20+J21+J22 -> 7.6295137e+09 | K15: =K16+K20+K21+K22 -> 7.6046513e+09 | L15: =L16+L20+L21+L22 -> 7.6233004e+09 | M15: =M16+M20+M21+M22 -> 7.6548288e+09 | N15: =N16+N20+N21+N22 -> 7.6667953e+09 | ... R15: =R16+R20+R21+R22 -> 7.6129461e+09 | S15: =SUM(G15:R15) -> 8.7405554e+10 | U15: =F15/F$9 -> 0.877187 | V15: =S15/S$9 -> 0.87761868
B16: 3.1.1 | C16: Nguyên vật liệu chính (nhựa, gồm hao hụt) | D16: ='KQKD PET'!D16 -> 66674046263 | E16: ='KQKD PET'!E16 -> 64023356129 | F16: ='KQKD PET'!F16 -> 79307026326 | G16: ='KQKD PET'!G16+'KQKD HD'!F16 -> 6000000000 | H16: ='KQKD PET'!H16+'KQKD HD'!G16 -> 4500000000 | I16: ='KQKD PET'!I16+'KQKD HD'!H16 -> 6500000000 | J16: ='KQKD PET'!J16+'KQKD HD'!I16 -> 7000000000 | K16: ='KQKD PET'!K16+'KQKD HD'!J16 -> 7000000000 | L16: ='KQKD PET'!L16+'KQKD HD'!K16 -> 7000000000 | M16: ='KQKD PET'!M16+'KQKD HD'!L16 -> 7000000000 | N16: ='KQKD PET'!N16+'KQKD HD'!M16 -> 7000000000 | ... R16: ='KQKD PET'!R16+'KQKD HD'!Q16 -> 7000000000 | S16: =SUM(G16:R16) -> 80000000000 | U16: =F16/F$9 -> 0.81152501 | V16: =S16/S$9 -> 0.80326124
B17: 3.1.2 | C17: Trong đó: i/ Hao hụt CĐ phân loại chai | D17: ='KQKD PET'!D17 -> 4304680024 | E17: ='KQKD PET'!E17 -> 5823164953 | F17: ='KQKD PET'!F17 -> 8362915901 | G17: ='KQKD PET'!G17+'KQKD HD'!F17 -> 663000000 | H17: ='KQKD PET'!H17+'KQKD HD'!G17 -> 497250000 | I17: ='KQKD PET'!I17+'KQKD HD'!H17 -> 718250000 | J17: ='KQKD PET'!J17+'KQKD HD'!I17 -> 773500000 | K17: ='KQKD PET'!K17+'KQKD HD'!J17 -> 773500000 | L17: ='KQKD PET'!L17+'KQKD HD'!K17 -> 773500000 | M17: ='KQKD PET'!M17+'KQKD HD'!L17 -> 773500000 | N17: ='KQKD PET'!N17+'KQKD HD'!M17 -> 773500000 | ... R17: ='KQKD PET'!R17+'KQKD HD'!Q17 -> 773500000 | S17: =SUM(G17:R17) -> 8840000000 | U17: =F17/F$9 -> 0.08557521 | V17: =S17/S$9 -> 0.088760367
C18: ii/ Hao hụt CĐ băm vảy | D18: ='KQKD PET'!D18 -> 0 | E18: ='KQKD PET'!E18 -> 0 | F18: ='KQKD PET'!F18 -> 0 | G18: ='KQKD PET'!G18+'KQKD HD'!F18 -> 0 | H18: ='KQKD PET'!H18+'KQKD HD'!G18 -> 0 | I18: ='KQKD PET'!I18+'KQKD HD'!H18 -> 0 | J18: ='KQKD PET'!J18+'KQKD HD'!I18 -> 0 | K18: ='KQKD PET'!K18+'KQKD HD'!J18 -> 0 | L18: ='KQKD PET'!L18+'KQKD HD'!K18 -> 0 | M18: ='KQKD PET'!M18+'KQKD HD'!L18 -> 0 | N18: ='KQKD PET'!N18+'KQKD HD'!M18 -> 0 | ... R18: ='KQKD PET'!R18+'KQKD HD'!Q18 -> 0 | S18: =SUM(G18:R18) -> 0 | U18: =F18/F$9 -> 0 | V18: =S18/S$9 -> 0
B19: 3.1.3 | C19: % chi phí nguyên liệu/doanh thu | D19: ='KQKD PET'!D19 -> 0.8448772 | E19: ='KQKD PET'!E19 -> 0.85910748 | F19: ='KQKD PET'!F19 -> 0.81152501 | G19: =G16/G9 -> 0.80326124 | H19: =H16/H9 -> 0.80326124 | I19: =I16/I9 -> 0.80326124 | J19: =J16/J9 -> 0.80326124 | K19: =K16/K9 -> 0.80326124 | L19: =L16/L9 -> 0.80326124 | M19: =M16/M9 -> 0.80326124 | N19: =N16/N9 -> 0.80326124 | ... S19: =S16/S9 -> 0.80326124 | U19: =F19/F$9 -> 8.3040921e-12 | V19: =S19/S$9 -> 8.0653578e-12
B20: 3.1.4 | C20: Nguyên vật liệu phụ | D20: ='KQKD PET'!D20 -> 630817585 | E20: ='KQKD PET'!E20 -> 620417107 | F20: ='KQKD PET'!F20 -> 5.6441463e+08 | G20: ='KQKD PET'!G20+'KQKD HD'!F20 -> 1.2915839e+08 | H20: ='KQKD PET'!H20+'KQKD HD'!G20 -> 96868796 | I20: ='KQKD PET'!I20+'KQKD HD'!H20 -> 1.3992159e+08 | J20: ='KQKD PET'!J20+'KQKD HD'!I20 -> 1.5068479e+08 | K20: ='KQKD PET'!K20+'KQKD HD'!J20 -> 1.5068479e+08 | L20: ='KQKD PET'!L20+'KQKD HD'!K20 -> 1.5068479e+08 | M20: ='KQKD PET'!M20+'KQKD HD'!L20 -> 1.5068479e+08 | N20: ='KQKD PET'!N20+'KQKD HD'!M20 -> 1.5068479e+08 | ... R20: ='KQKD PET'!R20+'KQKD HD'!Q20 -> 1.5068479e+08 | S20: =SUM(G20:R20) -> 1.7221119e+09 | U20: =F20/F$9 -> 0.0057754857 | V20: =S20/S$9 -> 0.017291322
B21: 3.1.5 | C21: Điện sản xuất | D21: ='KQKD PET'!D21 -> 326356700 | E21: ='KQKD PET'!E21 -> 377182809 | F21: ='KQKD PET'!F21 -> 453250096 | G21: ='KQKD PET'!G21+'KQKD HD'!F21 -> 45584274 | H21: ='KQKD PET'!H21+'KQKD HD'!G21 -> 34188205 | I21: ='KQKD PET'!I21+'KQKD HD'!H21 -> 49382963 | J21: ='KQKD PET'!J21+'KQKD HD'!I21 -> 53181653 | K21: ='KQKD PET'!K21+'KQKD HD'!J21 -> 53181653 | L21: ='KQKD PET'!L21+'KQKD HD'!K21 -> 53181653 | M21: ='KQKD PET'!M21+'KQKD HD'!L21 -> 53181653 | N21: ='KQKD PET'!N21+'KQKD HD'!M21 -> 53181653 | ... R21: ='KQKD PET'!R21+'KQKD HD'!Q21 -> 53181653 | S21: =SUM(G21:R21) -> 6.0779032e+08 | U21: =F21/F$9 -> 0.0046379723 | V21: =S21/S$9 -> 0.00610268
B22: 3.1.6 | C22: Nhân công trực tiếp | D22: ='KQKD PET'!D22 -> 5.8040781e+09 | E22: ='KQKD PET'!E22 -> 4630674981 | F22: ='KQKD PET'!F22 -> 5.3992128e+09 | G22: ='KQKD PET'!G22+'KQKD HD'!F22 -> 4.0987858e+08 | H22: ='KQKD PET'!H22+'KQKD HD'!G22 -> 4.177034e+08 | I22: ='KQKD PET'!I22+'KQKD HD'!H22 -> 3.9941719e+08 | J22: ='KQKD PET'!J22+'KQKD HD'!I22 -> 4.256473e+08 | K22: ='KQKD PET'!K22+'KQKD HD'!J22 -> 4.0078483e+08 | L22: ='KQKD PET'!L22+'KQKD HD'!K22 -> 4.1943392e+08 | M22: ='KQKD PET'!M22+'KQKD HD'!L22 -> 4.5096237e+08 | N22: ='KQKD PET'!N22+'KQKD HD'!M22 -> 4.6292885e+08 | ... R22: ='KQKD PET'!R22+'KQKD HD'!Q22 -> 4.0907969e+08 | S22: =SUM(G22:R22) -> 5.0756521e+09 | U22: =F22/F$9 -> 0.055248525 | V22: =S22/S$9 -> 0.050963433
B23: 3.2 | C23: BIẾN PHÍ BÁN HÀNG | D23: ='KQKD PET'!D23 -> 1478599034 | E23: ='KQKD PET'!E23 -> 1294051828 | F23: ='KQKD PET'!F23 -> 1.3166214e+09 | G23: =G24 -> 1.1436429e+08 | H23: =H24 -> 85773214 | I23: =I24 -> 1.2389464e+08 | J23: =J24 -> 133425000 | K23: =K24 -> 133425000 | L23: =L24 -> 133425000 | M23: =M24 -> 133425000 | N23: =N24 -> 133425000 | ... R23: =R24 -> 133425000 | S23: =SUM(G23:R23) -> 1.5248571e+09 | U23: =F23/F$9 -> 0.013472592 | V23: =S23/S$9 -> 0.015310733
C24: Chi phí vận chuyển | D24: ='KQKD PET'!D24 -> 1478599034 | E24: ='KQKD PET'!E24 -> 1294051828 | F24: ='KQKD PET'!F24 -> 1.3166214e+09 | G24: ='KQKD PET'!G24+'KQKD HD'!F24 -> 1.1436429e+08 | H24: ='KQKD PET'!H24+'KQKD HD'!G24 -> 85773214 | I24: ='KQKD PET'!I24+'KQKD HD'!H24 -> 1.2389464e+08 | J24: ='KQKD PET'!J24+'KQKD HD'!I24 -> 133425000 | K24: ='KQKD PET'!K24+'KQKD HD'!J24 -> 133425000 | L24: ='KQKD PET'!L24+'KQKD HD'!K24 -> 133425000 | M24: ='KQKD PET'!M24+'KQKD HD'!L24 -> 133425000 | N24: ='KQKD PET'!N24+'KQKD HD'!M24 -> 133425000 | ... R24: ='KQKD PET'!R24+'KQKD HD'!Q24 -> 133425000 | S24: =SUM(G24:R24) -> 1.5248571e+09 | U24: =F24/F$9 -> 0.013472592 | V24: =S24/S$9 -> 0.015310733
B25: 4 | C25: LÃI SAU BIẾN PHÍ | D25: ='KQKD PET'!D25 -> 4.0017676e+09 | E25: ='KQKD PET'!E25 -> 3577421231 | F25: ='KQKD PET'!F25 -> 1.0685392e+10 | G25: =G9-G14 -> 7.7056447e+08 | H25: =H9-H14 -> 4.6762888e+08 | I25: =I9-I14 -> 8.7939612e+08 | J25: =J9-J14 -> 9.5153625e+08 | K25: =K9-K14 -> 9.7639873e+08 | L25: =L9-L14 -> 9.5774963e+08 | M25: =M9-M14 -> 9.2622118e+08 | N25: =N9-N14 -> 9.1425471e+08 | ... R25: =R9-R14 -> 9.6810387e+08 | S25: =SUM(G25:R25) -> 1.0663589e+10 | U25: =F25/F$9 -> 0.10934041 | V25: =S25/S$9 -> 0.10707059
B26: 4.1 | C26: % lãi biến phí/doanh thu | D26: ='KQKD PET'!D26 -> 0.05070942 | E26: ='KQKD PET'!E26 -> 0.04800419 | F26: ='KQKD PET'!F26 -> 0.013472592 | G26: =G25/G9 -> 0.10316076 | H26: =H25/H9 -> 0.083472924 | I26: =I25/I9 -> 0.10867459 | J26: =J25/J9 -> 0.10919031 | K26: =K25/K9 -> 0.11204332 | L26: =L25/L9 -> 0.10990331 | M26: =M25/M9 -> 0.10628537 | N26: =N25/N9 -> 0.1049122 | ... S26: =S25/S9 -> 0.10707059 | U26: =F26/F$9 -> 1.37861e-13 | V26: =S26/S$9 -> 1.0750707e-12
B27: 5 | C27: CHI PHÍ SẢN XUẤT CHUNG | D27: ='KQKD PET'!D27 -> 2.0941578e+09 | E27: ='KQKD PET'!E27 -> 2385196776 | F27: ='KQKD PET'!F27 -> 4.2048304e+09 | G27: =G28+G29+G30 -> 5.2485398e+08 | H27: =H28+H29+H30 -> 5.3468413e+08 | I27: =I28+I29+I30 -> 4.9822558e+08 | J27: =J28+J29+J30 -> 5.1694045e+08 | K27: =K28+K29+K30 -> 4.9801716e+08 | L27: =L28+L29+L30 -> 5.2597207e+08 | M27: =M28+M29+M30 -> 5.063536e+08 | N27: =N28+N29+N30 -> 5.1191977e+08 | ... R27: =R28+R29+R30 -> 5.1098676e+08 | S27: =SUM(G27:R27) -> 6.138579e+09 | U27: =F27/F$9 -> 0.043026768 | V27: =S27/S$9 -> 0.061636032
B28: 5.1 | C28: Lương gián tiếp Sản xuất | D28: ='KQKD PET'!D28 -> 3.1517286e+08 | E28: ='KQKD PET'!E28 -> 220439144 | F28: ='KQKD PET'!F28 -> 1.0162315e+09 | G28: ='KQKD PET'!G28+'KQKD HD'!F28 -> 2.0140792e+08 | H28: ='KQKD PET'!H28+'KQKD HD'!G28 -> 2.2291481e+08 | I28: ='KQKD PET'!I28+'KQKD HD'!H28 -> 1.9174351e+08 | J28: ='KQKD PET'!J28+'KQKD HD'!I28 -> 2.0729541e+08 | K28: ='KQKD PET'!K28+'KQKD HD'!J28 -> 197959424 | L28: ='KQKD PET'!L28+'KQKD HD'!K28 -> 2.0561971e+08 | M28: ='KQKD PET'!M28+'KQKD HD'!L28 -> 2.0558595e+08 | N28: ='KQKD PET'!N28+'KQKD HD'!M28 -> 2.0680673e+08 | ... R28: ='KQKD PET'!R28+'KQKD HD'!Q28 -> 2.0131325e+08 | S28: =SUM(G28:R28) -> 2.4550487e+09 | U28: =F28/F$9 -> 0.010398792 | V28: =S28/S$9 -> 0.024650568
B29: 5.2 | C29: Chi phí thuê xưởng | D29: ='KQKD PET'!D29 -> 1118310000 | E29: ='KQKD PET'!E29 -> 1557000000 | F29: ='KQKD PET'!F29 -> 1800000000 | G29: ='KQKD PET'!G29+'KQKD HD'!F29 -> 150000000 | H29: ='KQKD PET'!H29+'KQKD HD'!G29 -> 150000000 | I29: ='KQKD PET'!I29+'KQKD HD'!H29 -> 150000000 | J29: ='KQKD PET'!J29+'KQKD HD'!I29 -> 150000000 | K29: ='KQKD PET'!K29+'KQKD HD'!J29 -> 150000000 | L29: ='KQKD PET'!L29+'KQKD HD'!K29 -> 150000000 | M29: ='KQKD PET'!M29+'KQKD HD'!L29 -> 150000000 | N29: ='KQKD PET'!N29+'KQKD HD'!M29 -> 150000000 | ... R29: ='KQKD PET'!R29+'KQKD HD'!Q29 -> 150000000 | S29: =SUM(G29:R29) -> 1800000000 | U29: =F29/F$9 -> 0.01841886 | V29: =S29/S$9 -> 0.018073378
B30: 5.3 | C30: Chi phí sản xuất (Ngoài lương, BOM, thuê xưởng, khấu hao) | D30: ='KQKD PET'!D30 -> 660674936 | E30: ='KQKD PET'!E30 -> 607757632 | F30: ='KQKD PET'!F30 -> 1.3885989e+09 | G30: ='KQKD PET'!G30+'KQKD HD'!F30 -> 1.7344606e+08 | H30: ='KQKD PET'!H30+'KQKD HD'!G30 -> 1.6176933e+08 | I30: ='KQKD PET'!I30+'KQKD HD'!H30 -> 1.5648207e+08 | J30: ='KQKD PET'!J30+'KQKD HD'!I30 -> 1.5964503e+08 | K30: ='KQKD PET'!K30+'KQKD HD'!J30 -> 1.5005774e+08 | L30: ='KQKD PET'!L30+'KQKD HD'!K30 -> 1.7035236e+08 | M30: ='KQKD PET'!M30+'KQKD HD'!L30 -> 1.5076764e+08 | N30: ='KQKD PET'!N30+'KQKD HD'!M30 -> 1.5511304e+08 | ... R30: ='KQKD PET'!R30+'KQKD HD'!Q30 -> 1.5967352e+08 | S30: =SUM(G30:R30) -> 1.8835303e+09 | U30: =F30/F$9 -> 0.014209116 | V30: =S30/S$9 -> 0.018912086
B31: 6 | C31: CHI PHÍ KHẤU HAO | D31: ='KQKD PET'!D31 -> 1036408270 | E31: ='KQKD PET'!E31 -> 1382050356 | F31: ='KQKD PET'!F31 -> 1.9084998e+09 | G31: ='KQKD PET'!G31+'KQKD HD'!F31 -> 81327530 | H31: ='KQKD PET'!H31+'KQKD HD'!G31 -> 81327530 | I31: ='KQKD PET'!I31+'KQKD HD'!H31 -> 81327530 | J31: ='KQKD PET'!J31+'KQKD HD'!I31 -> 81327530 | K31: ='KQKD PET'!K31+'KQKD HD'!J31 -> 81327530 | L31: ='KQKD PET'!L31+'KQKD HD'!K31 -> 81327530 | M31: ='KQKD PET'!M31+'KQKD HD'!L31 -> 81327530 | N31: ='KQKD PET'!N31+'KQKD HD'!M31 -> 81327530 | ... R31: ='KQKD PET'!R31+'KQKD HD'!Q31 -> 81327530 | S31: =SUM(G31:R31) -> 9.7593036e+08 | U31: =F31/F$9 -> 0.019529106 | V31: =S31/S$9 -> 0.0097990879
B32: 7 | C32: LỢI NHUẬN GỘP | D32: ='KQKD PET'!D32 -> 871201538 | E32: ='KQKD PET'!E32 -> -189825901 | F32: ='KQKD PET'!F32 -> 4.5720617e+09 | G32: =G25-G27-G31 -> 1.6438296e+08 | H32: =H25-H27-H31 -> -1.4838278e+08 | I32: =I25-I27-I31 -> 2.9984301e+08 | J32: =J25-J27-J31 -> 3.5326827e+08 | K32: =K25-K27-K31 -> 3.9705403e+08 | L32: =L25-L27-L31 -> 3.5045003e+08 | M32: =M25-M27-M31 -> 3.3854005e+08 | N32: =N25-N27-N31 -> 3.2100741e+08 | ... R32: =R25-R27-R31 -> 3.7578957e+08 | S32: =SUM(G32:R32) -> 3.5490792e+09 | U32: =F32/F$9 -> 0.046784536 | V32: =S32/S$9 -> 0.035635472
B33: 7.1 | C33: % lãi gộp/doanh thu | D33: ='KQKD PET'!D33 -> 0.011039653 | E33: ='KQKD PET'!E33 -> -0.0025472087 | F33: ='KQKD PET'!F33 -> 0.046784536 | G33: =G32/G9 -> 0.022007077 | H33: =H32/H9 -> -0.026486697 | I33: =I32/I9 -> 0.037054195 | J33: =J32/J9 -> 0.040538102 | K33: =K32/K9 -> 0.045562588 | L33: =L32/L9 -> 0.040214704 | M33: =M32/M9 -> 0.038848015 | N33: =N32/N9 -> 0.036836116 | ... S33: =S32/S9 -> 0.035635472 | U33: =F33/F$9 -> 4.7873213e-13 | V33: =S33/S$9 -> 3.5780742e-13
B34: 8 | C34: CHI PHÍ BÁN HÀNG & MKT & R&D | D34: ='KQKD PET'!D34 -> 0 | E34: ='KQKD PET'!E34 -> 0 | F34: ='KQKD PET'!F34 -> 0 | G34: =G35+G36+G37 -> 0 | H34: =H35+H36+H37 -> 0 | I34: =I35+I36+I37 -> 0 | J34: =J35+J36+J37 -> 0 | K34: =K35+K36+K37 -> 0 | L34: =L35+L36+L37 -> 0 | M34: =M35+M36+M37 -> 0 | N34: =N35+N36+N37 -> 0 | ... R34: =R35+R36+R37 -> 0 | S34: =SUM(G34:R34) -> 0 | U34: =F34/F$9 -> 0 | V34: =S34/S$9 -> 0
B35: 8.1 | C35: Lương | D35: ='KQKD PET'!D35 -> 0 | E35: ='KQKD PET'!E35 -> 0 | F35: ='KQKD PET'!F35 -> 0 | G35: ='KQKD PET'!G35+'KQKD HD'!F35 -> 0 | H35: ='KQKD PET'!H35+'KQKD HD'!G35 -> 0 | I35: ='KQKD PET'!I35+'KQKD HD'!H35 -> 0 | J35: ='KQKD PET'!J35+'KQKD HD'!I35 -> 0 | K35: ='KQKD PET'!K35+'KQKD HD'!J35 -> 0 | L35: ='KQKD PET'!L35+'KQKD HD'!K35 -> 0 | M35: ='KQKD PET'!M35+'KQKD HD'!L35 -> 0 | N35: ='KQKD PET'!N35+'KQKD HD'!M35 -> 0 | ... R35: ='KQKD PET'!R35+'KQKD HD'!Q35 -> 0 | S35: =SUM(G35:R35) -> 0 | U35: =F35/F$9 -> 0 | V35: =S35/S$9 -> 0
B36: 8.2 | C36: Chi phí bán hàng (ngoài lương, khấu hao) | D36: ='KQKD PET'!D36 -> 0 | E36: ='KQKD PET'!E36 -> 0 | F36: ='KQKD PET'!F36 -> 0 | G36: ='KQKD PET'!G36+'KQKD HD'!F36 -> 0 | H36: ='KQKD PET'!H36+'KQKD HD'!G36 -> 0 | I36: ='KQKD PET'!I36+'KQKD HD'!H36 -> 0 | J36: ='KQKD PET'!J36+'KQKD HD'!I36 -> 0 | K36: ='KQKD PET'!K36+'KQKD HD'!J36 -> 0 | L36: ='KQKD PET'!L36+'KQKD HD'!K36 -> 0 | M36: ='KQKD PET'!M36+'KQKD HD'!L36 -> 0 | N36: ='KQKD PET'!N36+'KQKD HD'!M36 -> 0 | ... R36: ='KQKD PET'!R36+'KQKD HD'!Q36 -> 0 | S36: =SUM(G36:R36) -> 0 | U36: =F36/F$9 -> 0 | V36: =S36/S$9 -> 0
B37: 83 | C37: Khấu hao tài sản | D37: ='KQKD PET'!D37 -> 0 | E37: ='KQKD PET'!E37 -> 0 | F37: ='KQKD PET'!F37 -> 0 | G37: ='KQKD PET'!G37+'KQKD HD'!F37 -> 0 | H37: ='KQKD PET'!H37+'KQKD HD'!G37 -> 0 | I37: ='KQKD PET'!I37+'KQKD HD'!H37 -> 0 | J37: ='KQKD PET'!J37+'KQKD HD'!I37 -> 0 | K37: ='KQKD PET'!K37+'KQKD HD'!J37 -> 0 | L37: ='KQKD PET'!L37+'KQKD HD'!K37 -> 0 | M37: ='KQKD PET'!M37+'KQKD HD'!L37 -> 0 | N37: ='KQKD PET'!N37+'KQKD HD'!M37 -> 0 | ... R37: ='KQKD PET'!R37+'KQKD HD'!Q37 -> 0 | S37: =SUM(G37:R37) -> 0 | U37: =F37/F$9 -> 0 | V37: =S37/S$9 -> 0
B38: 9 | C38: CHI PHÍ QUẢN LÝ | D38: ='KQKD PET'!D38 -> 1414416772 | E38: ='KQKD PET'!E38 -> 2036034770 | F38: ='KQKD PET'!F38 -> 3.891071e+09 | G38: =G39+G40+G41 -> 4.7153661e+08 | H38: =H39+H40+H41 -> 4.996212e+08 | I38: =I39+I40+I41 -> 4.3800101e+08 | J38: =J39+J40+J41 -> 4.4143001e+08 | K38: =K39+K40+K41 -> 4.4099057e+08 | L38: =L39+L40+L41 -> 4.3789178e+08 | M38: =M39+M40+M41 -> 4.3766534e+08 | N38: =N39+N40+N41 -> 4.9357986e+08 | ... R38: =R39+R40+R41 -> 4.4120512e+08 | S38: =SUM(G38:R38) -> 5.4138202e+09 | U38: =F38/F$9 -> 0.039816162 | V38: =S38/S$9 -> 0.054358899
B39: 9.1 | C39: Lương | D39: ='KQKD PET'!D39 -> 1124385437 | E39: ='KQKD PET'!E39 -> 1412576558 | F39: ='KQKD PET'!F39 -> 2.8990944e+09 | G39: ='KQKD PET'!G39+'KQKD HD'!F39 -> 323945534 | H39: ='KQKD PET'!H39+'KQKD HD'!G39 -> 362007174 | I39: ='KQKD PET'!I39+'KQKD HD'!H39 -> 317132791 | J39: ='KQKD PET'!J39+'KQKD HD'!I39 -> 325999646 | K39: ='KQKD PET'!K39+'KQKD HD'!J39 -> 321392926 | L39: ='KQKD PET'!L39+'KQKD HD'!K39 -> 325999646 | M39: ='KQKD PET'!M39+'KQKD HD'!L39 -> 323044028 | N39: ='KQKD PET'!N39+'KQKD HD'!M39 -> 323044028 | ... R39: ='KQKD PET'!R39+'KQKD HD'!Q39 -> 323044028 | S39: =SUM(G39:R39) -> 3918100515 | U39: =F39/F$9 -> 0.029665563 | V39: =S39/S$9 -> 0.039340729
B40: 9.2 | C40: Chi phí quản lý (ngoài lương, khấu hao) | D40: ='KQKD PET'!D40 -> 290031335 | E40: ='KQKD PET'!E40 -> 609710270 | F40: ='KQKD PET'!F40 -> 902118544 | G40: ='KQKD PET'!G40+'KQKD HD'!F40 -> 1.3693526e+08 | H40: ='KQKD PET'!H40+'KQKD HD'!G40 -> 1.2695821e+08 | I40: ='KQKD PET'!I40+'KQKD HD'!H40 -> 1.102124e+08 | J40: ='KQKD PET'!J40+'KQKD HD'!I40 -> 1.0477454e+08 | K40: ='KQKD PET'!K40+'KQKD HD'!J40 -> 1.0894183e+08 | L40: ='KQKD PET'!L40+'KQKD HD'!K40 -> 1.0123631e+08 | M40: ='KQKD PET'!M40+'KQKD HD'!L40 -> 1.039655e+08 | N40: ='KQKD PET'!N40+'KQKD HD'!M40 -> 1.5988002e+08 | ... R40: ='KQKD PET'!R40+'KQKD HD'!Q40 -> 1.0750528e+08 | S40: =SUM(G40:R40) -> 1.3678499e+09 | U40: =F40/F$9 -> 0.0092311085 | V40: =S40/S$9 -> 0.01373426
B41: 9.3 | C41: Khấu hao tài sản | D41: ='KQKD PET'!D41 -> 0 | E41: ='KQKD PET'!E41 -> 13747942 | F41: ='KQKD PET'!F41 -> 89858023 | G41: ='KQKD PET'!G41+'KQKD HD'!F41 -> 10655817 | H41: ='KQKD PET'!H41+'KQKD HD'!G41 -> 10655817 | I41: ='KQKD PET'!I41+'KQKD HD'!H41 -> 10655817 | J41: ='KQKD PET'!J41+'KQKD HD'!I41 -> 10655817 | K41: ='KQKD PET'!K41+'KQKD HD'!J41 -> 10655817 | L41: ='KQKD PET'!L41+'KQKD HD'!K41 -> 10655817 | M41: ='KQKD PET'!M41+'KQKD HD'!L41 -> 10655817 | N41: ='KQKD PET'!N41+'KQKD HD'!M41 -> 10655817 | ... R41: ='KQKD PET'!R41+'KQKD HD'!Q41 -> 10655817 | S41: =SUM(G41:R41) -> 1.278698e+08 | U41: =F41/F$9 -> 0.0009194902 | V41: =S41/S$9 -> 0.0012839107
B42: 10 | C42: DOANH THU/CHI PHÍ KHÁC | D42: ='KQKD PET'!D42 -> 114814093 | E42: ='KQKD PET'!E42 -> -59489094 | F42: ='KQKD PET'!F42 -> 283673552 | G42: ='KQKD PET'!G42+'KQKD HD'!F42 -> 0 | H42: ='KQKD PET'!H42+'KQKD HD'!G42 -> 0 | I42: ='KQKD PET'!I42+'KQKD HD'!H42 -> 0 | J42: ='KQKD PET'!J42+'KQKD HD'!I42 -> 0 | K42: ='KQKD PET'!K42+'KQKD HD'!J42 -> 0 | L42: ='KQKD PET'!L42+'KQKD HD'!K42 -> 0 | M42: ='KQKD PET'!M42+'KQKD HD'!L42 -> 0 | N42: ='KQKD PET'!N42+'KQKD HD'!M42 -> 0 | ... R42: ='KQKD PET'!R42+'KQKD HD'!Q42 -> 0 | S42: =SUM(G42:R42) -> 0 | U42: =F42/F$9 -> 0.0029027464 | V42: =S42/S$9 -> 0
B43: 11 | C43: LỢI NHUẬN THUẦN TỪ HOẠT ĐỘNG KINH DOANH | D43: ='KQKD PET'!D43 -> -428401141 | E43: ='KQKD PET'!E43 -> -2285349765 | F43: ='KQKD PET'!F43 -> 9.6466433e+08 | G43: =G32-G34-G38+G42 -> -3.0715365e+08 | H43: =H32-H34-H38+H42 -> -6.4800398e+08 | I43: =I32-I34-I38+I42 -> -1.38158e+08 | J43: =J32-J34-J38+J42 -> -88161731 | K43: =K32-K34-K38+K42 -> -43936535 | L43: =L32-L34-L38+L42 -> -87441746 | M43: =M32-M34-M38+M42 -> -99125290 | N43: =N32-N34-N38+N42 -> -1.7257245e+08 | ... R43: =R32-R34-R38+R42 -> -65415549 | S43: =SUM(G43:R43) -> -1.864741e+09 | U43: =F43/F$9 -> 0.0098711207 | V43: =S43/S$9 -> -0.018723427
B44: 12 | C44: DOANH THU TÀI CHÍNH | D44: ='KQKD PET'!D44 -> 4823037 | E44: ='KQKD PET'!E44 -> 438643 | F44: ='KQKD PET'!F44 -> 6026805 | G44: ='KQKD PET'!G44+'KQKD HD'!F44 -> 60000 | H44: ='KQKD PET'!H44+'KQKD HD'!G44 -> 60000 | I44: ='KQKD PET'!I44+'KQKD HD'!H44 -> 60000 | J44: ='KQKD PET'!J44+'KQKD HD'!I44 -> 60000 | K44: ='KQKD PET'!K44+'KQKD HD'!J44 -> 60000 | L44: ='KQKD PET'!L44+'KQKD HD'!K44 -> 60000 | M44: ='KQKD PET'!M44+'KQKD HD'!L44 -> 60000 | N44: ='KQKD PET'!N44+'KQKD HD'!M44 -> 60000 | ... R44: ='KQKD PET'!R44+'KQKD HD'!Q44 -> 60000 | S44: =SUM(G44:R44) -> 720000 | U44: =F44/F$9 -> 6.1670488e-05 | V44: =S44/S$9 -> 7.2293512e-06
B45: 13 | C45: CHI PHÍ TÀI CHÍNH | D45: ='KQKD PET'!D45 -> 0 | E45: ='KQKD PET'!E45 -> 0 | F45: ='KQKD PET'!F45 -> 0 | G45: ='KQKD PET'!G45+'KQKD HD'!F45 -> 0 | H45: ='KQKD PET'!H45+'KQKD HD'!G45 -> 0 | I45: ='KQKD PET'!I45+'KQKD HD'!H45 -> 0 | J45: ='KQKD PET'!J45+'KQKD HD'!I45 -> 0 | K45: ='KQKD PET'!K45+'KQKD HD'!J45 -> 0 | L45: ='KQKD PET'!L45+'KQKD HD'!K45 -> 0 | M45: ='KQKD PET'!M45+'KQKD HD'!L45 -> 0 | N45: ='KQKD PET'!N45+'KQKD HD'!M45 -> 0 | ... R45: ='KQKD PET'!R45+'KQKD HD'!Q45 -> 0 | S45: =SUM(G45:R45) -> 0 | U45: =F45/F$9 -> 0 | V45: =S45/S$9 -> 0
B46: 13.1 | C46: Trong đó: chi phí lãi vay | D46: ='KQKD PET'!D46 -> 0 | E46: ='KQKD PET'!E46 -> 0 | F46: ='KQKD PET'!F46 -> 0 | G46: ='KQKD PET'!G46+'KQKD HD'!F46 -> 0 | H46: ='KQKD PET'!H46+'KQKD HD'!G46 -> 0 | I46: ='KQKD PET'!I46+'KQKD HD'!H46 -> 0 | J46: ='KQKD PET'!J46+'KQKD HD'!I46 -> 0 | K46: ='KQKD PET'!K46+'KQKD HD'!J46 -> 0 | L46: ='KQKD PET'!L46+'KQKD HD'!K46 -> 0 | M46: ='KQKD PET'!M46+'KQKD HD'!L46 -> 0 | N46: ='KQKD PET'!N46+'KQKD HD'!M46 -> 0 | ... R46: ='KQKD PET'!R46+'KQKD HD'!Q46 -> 0 | S46: =SUM(G46:R46) -> 0 | U46: =F46/F$9 -> 0 | V46: =S46/S$9 -> 0
B47: 14 | C47: LỢI NHUẬN TRƯỚC THUẾ | D47: ='KQKD PET'!D47 -> -423578104 | E47: ='KQKD PET'!E47 -> -2284911122 | F47: ='KQKD PET'!F47 -> 9.7069113e+08 | G47: =G43+G44-G45 -> -3.0709365e+08 | H47: =H43+H44-H45 -> -6.4794398e+08 | I47: =I43+I44-I45 -> -1.38098e+08 | J47: =J43+J44-J45 -> -88101731 | K47: =K43+K44-K45 -> -43876535 | L47: =L43+L44-L45 -> -87381746 | M47: =M43+M44-M45 -> -99065290 | N47: =N43+N44-N45 -> -1.7251245e+08 | ... R47: =R43+R44-R45 -> -65355549 | S47: =SUM(G47:R47) -> -1.864021e+09 | U47: =F47/F$9 -> 0.0099327912 | V47: =S47/S$9 -> -0.018716198
B48: 15 | C48: THUẾ TNDN | D48: ='KQKD PET'!D48 -> 0 | E48: ='KQKD PET'!E48 -> 0 | F48: ='KQKD PET'!F48 -> 0 | S48: =SUM(G48:R48) -> 0 | U48: =F48/F$9 -> 0 | V48: =S48/S$9 -> 0
B49: 16 | C49: LỢI NHUẬN SAU THUẾ | D49: ='KQKD PET'!D49 -> -423578104 | E49: ='KQKD PET'!E49 -> -2284911122 | F49: ='KQKD PET'!F49 -> 9.7069113e+08 | G49: =G47-G48 -> -3.0709365e+08 | H49: =H47-H48 -> -6.4794398e+08 | I49: =I47-I48 -> -1.38098e+08 | J49: =J47-J48 -> -88101731 | K49: =K47-K48 -> -43876535 | L49: =L47-L48 -> -87381746 | M49: =M47-M48 -> -99065290 | N49: =N47-N48 -> -1.7251245e+08 | ... R49: =R47-R48 -> -65355549 | S49: =SUM(G49:R49) -> -1.864021e+09 | U49: =F49/F$9 -> 0.0099327912 | V49: =S49/S$9 -> -0.018716198
B50: 16.1 | C50: % LNST/doanh thu | D50: ='KQKD PET'!D50 -> -0.0053674781 | E50: ='KQKD PET'!E50 -> -0.030660439 | F50: ='KQKD PET'!F50 -> 0.0099327912 | G50: =G49/G9 -> -0.041112738 | H50: =H49/H9 -> -0.11565962 | I50: =I49/I9 -> -0.017065964 | J50: =J49/J9 -> -0.010109815 | K50: =K49/K9 -> -0.0050349029 | L50: =L49/L9 -> -0.010027196 | M50: =M49/M9 -> -0.011367901 | N50: =N49/N9 -> -0.019796081 | ... S50: =S49/S9 -> -0.018716198 | U50: =F50/F$9 -> 1.0163927e-13 | V50: =S50/S$9 -> -1.8792495e-13
B51: 17 | C51: Khấu hao tài sản | D51: ='KQKD PET'!D51 -> 1036408270 | E51: ='KQKD PET'!E51 -> 1395798298 | F51: ='KQKD PET'!F51 -> 1.9983578e+09 | G51: ='KQKD PET'!G51+'KQKD HD'!F51 -> 91983346 | H51: ='KQKD PET'!H51+'KQKD HD'!G51 -> 91983346 | I51: ='KQKD PET'!I51+'KQKD HD'!H51 -> 91983346 | J51: ='KQKD PET'!J51+'KQKD HD'!I51 -> 91983346 | K51: ='KQKD PET'!K51+'KQKD HD'!J51 -> 91983346 | L51: ='KQKD PET'!L51+'KQKD HD'!K51 -> 91983346 | M51: ='KQKD PET'!M51+'KQKD HD'!L51 -> 91983346 | N51: ='KQKD PET'!N51+'KQKD HD'!M51 -> 91983346 | ... R51: ='KQKD PET'!R51+'KQKD HD'!Q51 -> 91983346 | S51: =SUM(G51:R51) -> 1.1038002e+09 | U51: =F51/F$9 -> 0.020448596 | V51: =S51/S$9 -> 0.011082999
B52: 18 | C52: LỢI NHUẬN KHÔNG BAO GỒM KHẤU HAO, LÃI VAY | D52: ='KQKD PET'!D52 -> 612830166 | E52: ='KQKD PET'!E52 -> -889112824 | F52: ='KQKD PET'!F52 -> 2.9690489e+09 | G52: =G49+G51 -> -2.151103e+08 | H52: =H49+H51 -> -5.5596063e+08 | I52: =I49+I51 -> -46114651 | J52: =J49+J51 -> 3881615.2 | K52: =K49+K51 -> 48106811 | L52: =L49+L51 -> 4601600.8 | M52: =M49+M51 -> -7081943.6 | N52: =N49+N51 -> -80529104 | ... R52: =R49+R51 -> 26627797 | S52: =SUM(G52:R52) -> -7.6022086e+08 | U52: =F52/F$9 -> 0.030381387 | V52: =S52/S$9 -> -0.0076331993
B53: 18.1 | C53: % LN không gồm khấu hao/doanh thu | D53: ='KQKD PET'!D53 -> 0.0077656339 | E53: ='KQKD PET'!E53 -> -0.0119307 | F53: ='KQKD PET'!F53 -> 0.030381387 | G53: =G52/G9 -> -0.028798295 | H53: =H52/H9 -> -0.099240362 | I53: =I52/I9 -> -0.0056987864 | J53: =J52/J9 -> 0.00044542158 | K53: =K52/K9 -> 0.0055203338 | L53: =L52/L9 -> 0.00052804108 | M53: =M52/M9 -> -0.0008126644 | N53: =N52/N9 -> -0.009240844 | ... S53: =S52/S9 -> -0.0076331993 | U53: =F53/F$9 -> 3.1088362e-13 | V53: =S53/S$9 -> -7.6643165e-14
U54: =F54/F$9 -> 0 | V54: =S54/S$9 -> 0
B56: 1. Hòa vốn (Bao gồm khấu hao) | D56: =D4 -> Thực tế năm 2023 | E56: =E4 -> Thực tế năm 2024 | F56: =F4 -> KQKD 2025 | G56: =G4 -> T1 | H56: =H4 -> T2 | I56: =I4 -> T3 | J56: =J4 -> T4 | K56: =K4 -> T5 | ... S56: =S4 -> Kế hoạch 2026
B57: Sản lượng NVL hòa vốn (tấn) | D57: =D$58*(1+(D$17+D$18)/D$16) -> 6834600.4 | E57: =E$58*(1+(E$17+E$18)/E$16) -> 8662919.1 | F57: =IFERROR(F$58*(1+(F$17+F$18)/F$16),0) -> 6085582.8 | G57: =G$58*(1+(G$17+G$18)/G$16) -> 828918.76 | H57: =H$58*(1+(H$17+H$18)/H$16) -> 1060466.6 | I57: =I$58*(1+(I$17+I$18)/I$16) -> 742935.04 | J57: =J$58*(1+(J$17+J$18)/J$16) -> 755517.31 | K57: =K$58*(1+(K$17+K$18)/K$16) -> 722567.21 | L57: =L$58*(1+(L$17+L$18)/L$16) -> 754581.89 | M57: =M$58*(1+(M$17+M$18)/M$16) -> 765452.93 | N57: =N$58*(1+(N$17+N$18)/N$16) -> 821969.74 | ... S57: =S$58*(1+(S$17+S$18)/S$16) -> 9284195.8
B58: Sản lượng thành phẩm hòa vốn (tấn) | D58: =(D$27+D$31+D$34+D$38)/(D$25/D$5) -> 6420099.2 | E58: =(E$27+E$31+E$34+E$38)/(E$25/E$5) -> 7940684 | F58: =IFERROR((F$27+F$31+F$34+F$38)/(F$25/F$5),0) -> 5505073.5 | G58: =(G$27+G$31+G$34+G$38)/(G$25/G$5) -> 746437.43 | H58: =(H$27+H$31+H$34+H$38)/(H$25/H$5) -> 954945.17 | I58: =(I$27+I$31+I$34+I$38)/(I$25/I$5) -> 669009.49 | J58: =(J$27+J$31+J$34+J$38)/(J$25/J$5) -> 680339.76 | K58: =(K$27+K$31+K$34+K$38)/(K$25/K$5) -> 650668.35 | L58: =(L$27+L$31+L$34+L$38)/(L$25/L$5) -> 679497.43 | M58: =(M$27+M$31+M$34+M$38)/(M$25/M$5) -> 689286.74 | N58: =(N$27+N$31+N$34+N$38)/(N$25/N$5) -> 740179.87 | ... S58: =(S$27+S$31+S$34+S$38)/(S$25/S$5) -> 8360374.4
B59: Doanh thu hòa vốn (triệu đồng) | D59: =D$58*(D$9/D$5) -> 8.9627979e+10 | E59: =E$58*(E$9/E$5) -> 1.2089115e+11 | F59: =IFERROR(F$58*(F$9/F$5),0) -> 9.1497746e+10 | G59: =G$58*(G$9/G$5) -> 1.0446977e+10 | H59: =H$58*(H$9/H$5) -> 1.3365206e+10 | I59: =I$58*(I$9/I$5) -> 9.3633125e+09 | J59: =J$58*(J$9/J$5) -> 9.5218885e+09 | K59: =K$58*(K$9/K$5) -> 9.1066138e+09 | L59: =L$58*(L$9/L$5) -> 9.5100993e+09 | M59: =M$58*(M$9/M$5) -> 9.6471085e+09 | N59: =N$58*(N$9/N$5) -> 1.0359398e+10 | ... S59: =S$58*(S$9/S$5) -> 1.1701e+11
B60: 2. Hòa vốn (Không bao gồm khấu hao) | D60: =D56 -> Thực tế năm 2023 | E60: =E56 -> Thực tế năm 2024 | F60: =F56 -> KQKD 2025 | G60: =G56 -> T1 | H60: =H56 -> T2 | I60: =I56 -> T3 | J60: =J56 -> T4 | K60: =K56 -> T5 | ... S60: =S56 -> Kế hoạch 2026
B61: Sản lượng NVL hòa vốn (tấn) | D61: =D$62*(1+(D$17+D$18)/D$16) -> 5276082.7 | E61: =E$62*(1+(E$17+E$18)/E$16) -> 6579324.4 | F61: =IFERROR(F$62*(1+(F$17+F$18)/F$16),0) -> 4870000.6 | G61: =G$62*(1+(G$17+G$18)/G$16) -> 758170.47 | H61: =H$62*(1+(H$17+H$18)/H$16) -> 973031.7 | I61: =I$62*(1+(I$17+I$18)/I$16) -> 675776.3 | J61: =J$62*(1+(J$17+J$18)/J$16) -> 688675.77 | K61: =K$62*(1+(K$17+K$18)/K$16) -> 657427.69 | L61: =L$62*(1+(L$17+L$18)/L$16) -> 688173.99 | M61: =M$62*(1+(M$17+M$18)/M$16) -> 696784.51 | N61: =N$62*(1+(N$17+N$18)/N$16) -> 752402.54 | ... S61: =S$62*(1+(S$17+S$18)/S$16) -> 8466217.9
B62: Sản lượng thành phẩm hòa vốn (tấn) | D62: =(D$27+D$31+D$34+D$38-D51)/(D$25/D$5) -> 4956101.6 | E62: =(E$27+E$31+E$34+E$38-E51)/(E$25/E$5) -> 6030800.4 | F62: =IFERROR((F$27+F$31+F$34+F$38-F51)/(F$25/F$5),0) -> 4405446.8 | G62: =(G$27+G$31+G$34+G$38-G51)/(G$25/G$5) -> 682728.92 | H62: =(H$27+H$31+H$34+H$38-H51)/(H$25/H$5) -> 876210.44 | I62: =(I$27+I$31+I$34+I$38-I51)/(I$25/I$5) -> 608533.37 | J62: =(J$27+J$31+J$34+J$38-J51)/(J$25/J$5) -> 620149.28 | K62: =(K$27+K$31+K$34+K$38-K51)/(K$25/K$5) -> 592010.52 | L62: =(L$27+L$31+L$34+L$38-L51)/(L$25/L$5) -> 619697.42 | M62: =(M$27+M$31+M$34+M$38-M51)/(M$25/M$5) -> 627451.15 | N62: =(N$27+N$31+N$34+N$38-N51)/(N$25/N$5) -> 677534.93 | ... S62: =(S$27+S$31+S$34+S$38-S51)/(S$25/S$5) -> 7623789.2
B63: Doanh thu hòa vốn (triệu đồng) | D63: =D$62*(D$9/D$5) -> 6.9189799e+10 | E63: =E$62*(E$9/E$5) -> 9.1814561e+10 | F63: =IFERROR(F$62*(F$9/F$5),0) -> 7.3221267e+10 | G63: =G$62*(G$9/G$5) -> 9.5553266e+09 | H63: =H$62*(H$9/H$5) -> 1.2263252e+10 | I63: =I$62*(I$9/I$5) -> 8.5169016e+09 | J63: =J$62*(J$9/J$5) -> 8.6794754e+09 | K63: =K$62*(K$9/K$5) -> 8.2856515e+09 | L63: =L$62*(L$9/L$5) -> 8.6731514e+09 | M63: =M$62*(M$9/M$5) -> 8.7816709e+09 | N63: =N$62*(N$9/N$5) -> 9.4826326e+09 | ... S63: =S$62*(S$9/S$5) -> 1.0670091e+11

Sheet KQKD PET
B3: MỤC TIÊU KẾT QUẢ KINH DOANH NĂM 2026 | S3: ĐVT: Triệu đồng
B4: STT | C4: Mục phí | D4: Thực tế năm 2023 | E4: Thực tế năm 2024 | F4: KQKD 2025 | G4: T1 | H4: T2 | I4: T3 | J4: T4 | K4: T5 | L4: T6 | M4: T7 | N4: T8 | O4: T9 | P4: T10 | Q4: T11 | R4: T12 | S4: Kế hoạch 2026 | U4: Kiểm tra lại các sheet chi phí
B5: 1 | C5: SẢN LƯỢNG BÁN (TẤN) | D5: =D6+D7+D8 -> 5652770.5 | E5: =E6+E7+E8 -> 4895018.4 | F5: =F6+F7+F8 -> 5879799 | G5: =G6+G7+G8 -> 533700 | H5: =H6+H7+H8 -> 400275 | I5: =I6+I7+I8 -> 578175 | J5: =J6+J7+J8 -> 622650 | K5: =K6+K7+K8 -> 622650 | ... R5: =R6+R7+R8 -> 622650 | S5: =SUM(G5:R5) -> 7116000 | U5: ='3.Thanh pham'!$T$136+'3.Thanh pham'!$T$97 -> 7116000
B6: 1.1 | C6: Chai PET | D6: ='4.Doanh thu'!AJ22 -> 5652770.5 | E6: ='4.Doanh thu'!AH22 -> 4895018.4 | F6: ='4.Doanh thu'!AF22 -> 5879799 | G6: ='4.Doanh thu'!F22 -> 533700 | H6: ='4.Doanh thu'!G22 -> 400275 | I6: ='4.Doanh thu'!H22 -> 578175 | J6: ='4.Doanh thu'!I22 -> 622650 | K6: ='4.Doanh thu'!J22 -> 622650 | L6: ='4.Doanh thu'!K22 -> 622650 | M6: ='4.Doanh thu'!L22 -> 622650 | N6: ='4.Doanh thu'!M22 -> 622650 | ... R6: ='4.Doanh thu'!Q22 -> 622650 | S6: =SUM(G6:R6) -> 7116000
B7: 1.2 | C7: Vảy PET | D7: ='4.Doanh thu'!AJ80 -> 0 | E7: ='4.Doanh thu'!AH80 -> 0 | F7: ='4.Doanh thu'!AF80 -> 0 | G7: ='4.Doanh thu'!F80 -> 0 | H7: ='4.Doanh thu'!G80 -> 0 | I7: ='4.Doanh thu'!H80 -> 0 | J7: ='4.Doanh thu'!I80 -> 0 | K7: ='4.Doanh thu'!J80 -> 0 | L7: ='4.Doanh thu'!K80 -> 0 | M7: ='4.Doanh thu'!L80 -> 0 | N7: ='4.Doanh thu'!M80 -> 0 | ... R7: ='4.Doanh thu'!Q80 -> 0 | S7: =SUM(G7:R7) -> 0
B8: 1.3 | C8: Vảy HD | S8: =SUM(G8:R8) -> 0
B9: 2 | C9: DOANH THU | D9: =D10+D11+D12+D13 -> 78915665269 | E9: =E10+E11+E12+E13 -> 74523104085 | F9: =F10+F11+F12+F13 -> 97725917198 | G9: =G10+G11+G12+G13 -> 7469550000 | H9: =H10+H11+H12+H13 -> 5602162500 | I9: =I10+I11+I12+I13 -> 8092012500 | J9: =J10+J11+J12+J13 -> 8714475000 | K9: =K10+K11+K12+K13 -> 8714475000 | ... R9: =R10+R11+R12+R13 -> 8714475000 | S9: =SUM(G9:R9) -> 99594000000 | U9: ='4.Doanh thu'!$R$60+'4.Doanh thu'!$R$119 -> 99594000000
B10: 2.1 | C10: Chai PET | D10: ='4.Doanh thu'!AJ60 -> 78915665269 | E10: ='4.Doanh thu'!AH60 -> 74523104085 | F10: ='4.Doanh thu'!AF60 -> 97725917198 | G10: ='4.Doanh thu'!F60 -> 7469550000 | H10: ='4.Doanh thu'!G60 -> 5602162500 | I10: ='4.Doanh thu'!H60 -> 8092012500 | J10: ='4.Doanh thu'!I60 -> 8714475000 | K10: ='4.Doanh thu'!J60 -> 8714475000 | L10: ='4.Doanh thu'!K60 -> 8714475000 | M10: ='4.Doanh thu'!L60 -> 8714475000 | N10: ='4.Doanh thu'!M60 -> 8714475000 | ... R10: ='4.Doanh thu'!Q60 -> 8714475000 | S10: =SUM(G10:R10) -> 99594000000
B11: 2.2 | C11: Vảy PET | D11: ='4.Doanh thu'!AJ119 -> 0 | E11: ='4.Doanh thu'!AH119 -> 0 | F11: ='4.Doanh thu'!AF119 -> 0 | G11: ='4.Doanh thu'!F119 -> 0 | H11: ='4.Doanh thu'!G119 -> 0 | I11: ='4.Doanh thu'!H119 -> 0 | J11: ='4.Doanh thu'!I119 -> 0 | K11: ='4.Doanh thu'!J119 -> 0 | L11: ='4.Doanh thu'!K119 -> 0 | M11: ='4.Doanh thu'!L119 -> 0 | N11: ='4.Doanh thu'!M119 -> 0 | ... R11: ='4.Doanh thu'!Q119 -> 0 | S11: =SUM(G11:R11) -> 0
B12: 2.3 | C12: Vảy HD | S12: =SUM(G12:R12) -> 0
B13: 2.4 | C13: Khác | S13: =SUM(G13:R13) -> 0
B14: 3 | C14: BIẾN PHÍ | D14: =D15+D23 -> 7.4913898e+10 | E14: =E15+E23 -> 70945682854 | F14: =F15+F23 -> 8.7040525e+10 | G14: =G15+G23 -> 6.6989855e+09 | H14: =H15+H23 -> 5.1345336e+09 | I14: =I15+I23 -> 7.2126164e+09 | J14: =J15+J23 -> 7.7629387e+09 | K14: =K15+K23 -> 7.7380763e+09 | ... R14: =R15+R23 -> 7.7463711e+09 | S14: =SUM(G14:R14) -> 8.8930411e+10
B15: 3.1 | C15: BIẾN PHÍ SẢN XUẤT | D15: =D16+D20+D21+D22 -> 7.3435299e+10 | E15: =E16+E20+E21+E22 -> 69651631026 | F15: =F16+F20+F21+F22 -> 8.5723904e+10 | G15: =G16+G20+G21+G22 -> 6.5846212e+09 | H15: =H16+H20+H21+H22 -> 5.0487604e+09 | I15: =I16+I20+I21+I22 -> 7.0887217e+09 | J15: =J16+J20+J21+J22 -> 7.6295137e+09 | K15: =K16+K20+K21+K22 -> 7.6046513e+09 | ... R15: =R16+R20+R21+R22 -> 7.6129461e+09 | S15: =SUM(G15:R15) -> 8.7405554e+10
B16: 3.1.1 | C16: Nguyên vật liệu chính (nhựa, gồm hao hụt) | D16: =65387977661-414619518-4421623024+792534516+1021205404+3891200+D17 -> 66674046263 | E16: =58200191176+E17 -> 64023356129 | F16: =57301760425+13642350000+F17 -> 79307026326 | G16: ='1.NVL Chai'!H42 -> 6000000000 | H16: ='1.NVL Chai'!I42 -> 4500000000 | I16: ='1.NVL Chai'!J42 -> 6500000000 | J16: ='1.NVL Chai'!K42 -> 7000000000 | K16: ='1.NVL Chai'!L42 -> 7000000000 | L16: ='1.NVL Chai'!M42 -> 7000000000 | M16: ='1.NVL Chai'!N42 -> 7000000000 | N16: ='1.NVL Chai'!O42 -> 7000000000 | ... R16: ='1.NVL Chai'!S42 -> 7000000000 | S16: =SUM(G16:R16) -> 80000000000 | U16: ='3.Thanh pham'!T198 -> 80000000000
B17: 3.1.2 | C17: Trong đó: i/ Hao hụt CĐ phân loại chai | D17: =4421623024+172191089-312083318+201538626-178589397 -> 4304680024 | E17: 5823164953 | F17: =6555265901+1807650000 -> 8362915901 | G17: =SUM('3.Thanh pham'!H$187:H$189)*'1.NVL Chai'!H$34 -> 663000000 | H17: =SUM('3.Thanh pham'!I$187:I$189)*'1.NVL Chai'!I$34 -> 497250000 | I17: =SUM('3.Thanh pham'!J$187:J$189)*'1.NVL Chai'!J$34 -> 718250000 | J17: =SUM('3.Thanh pham'!K$187:K$189)*'1.NVL Chai'!K$34 -> 773500000 | K17: =SUM('3.Thanh pham'!L$187:L$189)*'1.NVL Chai'!L$34 -> 773500000 | L17: =SUM('3.Thanh pham'!M$187:M$189)*'1.NVL Chai'!M$34 -> 773500000 | M17: =SUM('3.Thanh pham'!N$187:N$189)*'1.NVL Chai'!N$34 -> 773500000 | N17: =SUM('3.Thanh pham'!O$187:O$189)*'1.NVL Chai'!O$34 -> 773500000 | ... R17: =SUM('3.Thanh pham'!S$187:S$189)*'1.NVL Chai'!S$34 -> 773500000 | S17: =SUM(G17:R17) -> 8840000000 | U17: ='3.Thanh pham'!T196 -> 8840000000
C18: ii/ Hao hụt CĐ băm vảy | G18: =('3.Thanh pham'!H$190*'1.NVL Chai'!H$34) -> 0 | H18: =('3.Thanh pham'!I$190*'1.NVL Chai'!I$34) -> 0 | I18: =('3.Thanh pham'!J$190*'1.NVL Chai'!J$34) -> 0 | J18: =('3.Thanh pham'!K$190*'1.NVL Chai'!K$34) -> 0 | K18: =('3.Thanh pham'!L$190*'1.NVL Chai'!L$34) -> 0 | L18: =('3.Thanh pham'!M$190*'1.NVL Chai'!M$34) -> 0 | M18: =('3.Thanh pham'!N$190*'1.NVL Chai'!N$34) -> 0 | N18: =('3.Thanh pham'!O$190*'1.NVL Chai'!O$34) -> 0 | ... R18: =('3.Thanh pham'!S$190*'1.NVL Chai'!S$34) -> 0 | S18: =SUM(G18:R18) -> 0 | U18: =U17-S17-S18 -> 0
B19: 3.1.3 | C19: % chi phí nguyên liệu/doanh thu | D19: =D16/D9 -> 0.8448772 | E19: =E16/E9 -> 0.85910748 | F19: =IFERROR(F16/$F$9,0) -> 0.81152501 | G19: =G16/G9 -> 0.80326124 | H19: =H16/H9 -> 0.80326124 | I19: =I16/I9 -> 0.80326124 | J19: =J16/J9 -> 0.80326124 | K19: =K16/K9 -> 0.80326124 | L19: =L16/L9 -> 0.80326124 | M19: =M16/M9 -> 0.80326124 | N19: =N16/N9 -> 0.80326124 | ... S19: =S16/S9 -> 0.80326124
B20: 3.1.4 | C20: Nguyên vật liệu phụ | D20: =SUM(CPSX!AO19:AO25) -> 630817585 | E20: =SUM(CPSX!AM19:AM25) -> 620417107 | F20: =SUM(CPSX!AK19:AK25) -> 5.6441463e+08 | G20: =SUM(CPSX!K19:K25) -> 1.2915839e+08 | H20: =SUM(CPSX!L19:L25) -> 96868796 | I20: =SUM(CPSX!M19:M25) -> 1.3992159e+08 | J20: =SUM(CPSX!N19:N25) -> 1.5068479e+08 | K20: =SUM(CPSX!O19:O25) -> 1.5068479e+08 | L20: =SUM(CPSX!P19:P25) -> 1.5068479e+08 | M20: =SUM(CPSX!Q19:Q25) -> 1.5068479e+08 | N20: =SUM(CPSX!R19:R25) -> 1.5068479e+08 | ... R20: =SUM(CPSX!V19:V25) -> 1.5068479e+08 | S20: =SUM(G20:R20) -> 1.7221119e+09 | U20: =SUM(CPSX!W19:W25) -> 1.7221119e+09
B21: 3.1.5 | C21: Điện sản xuất | D21: =CPSX!AO$18 -> 326356700 | E21: =CPSX!AM$18 -> 377182809 | F21: =CPSX!AK$18 -> 453250096 | G21: =CPSX!K$18 -> 45584274 | H21: =CPSX!L$18 -> 34188205 | I21: =CPSX!M$18 -> 49382963 | J21: =CPSX!N$18 -> 53181653 | K21: =CPSX!O$18 -> 53181653 | L21: =CPSX!P$18 -> 53181653 | M21: =CPSX!Q$18 -> 53181653 | N21: =CPSX!R$18 -> 53181653 | ... R21: =CPSX!V$18 -> 53181653 | S21: =SUM(G21:R21) -> 6.0779032e+08 | U21: =CPSX!W18 -> 6.0779032e+08
B22: 3.1.6 | C22: Nhân công trực tiếp | D22: =SUM(CPSX!AO6:AO16) -> 5.8040781e+09 | E22: =SUM(CPSX!AM6:AM16) -> 4630674981 | F22: =SUM(CPSX!AK6:AK16) -> 5.3992128e+09 | G22: =SUM(CPSX!K6:K16) -> 4.0987858e+08 | H22: =SUM(CPSX!L6:L16) -> 4.177034e+08 | I22: =SUM(CPSX!M6:M16) -> 3.9941719e+08 | J22: =SUM(CPSX!N6:N16) -> 4.256473e+08 | K22: =SUM(CPSX!O6:O16) -> 4.0078483e+08 | L22: =SUM(CPSX!P6:P16) -> 4.1943392e+08 | M22: =SUM(CPSX!Q6:Q16) -> 4.5096237e+08 | N22: =SUM(CPSX!R6:R16) -> 4.6292885e+08 | ... R22: =SUM(CPSX!V6:V16) -> 4.0907969e+08 | S22: =SUM(G22:R22) -> 5.0756521e+09 | U22: =SUM(CPSX!W6:W16) -> 5.0756521e+09
B23: 3.2 | C23: BIẾN PHÍ BÁN HÀNG | D23: =D24 -> 1478599034 | E23: =E24 -> 1294051828 | F23: =F24 -> 1.3166214e+09 | G23: =G24 -> 1.1436429e+08 | H23: =H24 -> 85773214 | I23: =I24 -> 1.2389464e+08 | J23: =J24 -> 133425000 | K23: =K24 -> 133425000 | ... R23: =R24 -> 133425000 | S23: =SUM(G23:R23) -> 1.5248571e+09 | U23: =CPBH!W8 -> 1.5248571e+09
C24: Chi phí vận chuyển | D24: =CPBH!AO$8 -> 1478599034 | E24: =CPBH!AM$8 -> 1294051828 | F24: =CPBH!AK$8 -> 1.3166214e+09 | G24: =CPBH!K$8 -> 1.1436429e+08 | H24: =CPBH!L$8 -> 85773214 | I24: =CPBH!M$8 -> 1.2389464e+08 | J24: =CPBH!N$8 -> 133425000 | K24: =CPBH!O$8 -> 133425000 | L24: =CPBH!P$8 -> 133425000 | M24: =CPBH!Q$8 -> 133425000 | N24: =CPBH!R$8 -> 133425000 | ... R24: =CPBH!V$8 -> 133425000 | S24: =SUM(G24:R24) -> 1.5248571e+09
B25: 4 | C25: LÃI SAU BIẾN PHÍ | D25: =D9-D14 -> 4.0017676e+09 | E25: =E9-E14 -> 3577421231 | F25: =F9-F14 -> 1.0685392e+10 | G25: =G9-G14 -> 7.7056447e+08 | H25: =H9-H14 -> 4.6762888e+08 | I25: =I9-I14 -> 8.7939612e+08 | J25: =J9-J14 -> 9.5153625e+08 | K25: =K9-K14 -> 9.7639873e+08 | ... R25: =R9-R14 -> 9.6810387e+08 | S25: =SUM(G25:R25) -> 1.0663589e+10
B26: 4.1 | C26: % lãi biến phí/doanh thu | D26: =D25/D9 -> 0.05070942 | E26: =E25/E9 -> 0.04800419 | F26: =IFERROR(F23/$F$9,0) -> 0.013472592 | G26: =G25/G9 -> 0.10316076 | H26: =H25/H9 -> 0.083472924 | I26: =I25/I9 -> 0.10867459 | J26: =J25/J9 -> 0.10919031 | K26: =K25/K9 -> 0.11204332 | L26: =L25/L9 -> 0.10990331 | M26: =M25/M9 -> 0.10628537 | N26: =N25/N9 -> 0.1049122 | ... S26: =S25/S9 -> 0.10707059
B27: 5 | C27: CHI PHÍ SẢN XUẤT CHUNG | D27: =D28+D29+D30 -> 2.0941578e+09 | E27: =E28+E29+E30 -> 2385196776 | F27: =F28+F29+F30 -> 4.2048304e+09 | G27: =G28+G29+G30 -> 5.2485398e+08 | H27: =H28+H29+H30 -> 5.3468413e+08 | I27: =I28+I29+I30 -> 4.9822558e+08 | J27: =J28+J29+J30 -> 5.1694045e+08 | K27: =K28+K29+K30 -> 4.9801716e+08 | ... R27: =R28+R29+R30 -> 5.1098676e+08 | S27: =SUM(G27:R27) -> 6.138579e+09
B28: 5.1 | C28: Lương gián tiếp Sản xuất | D28: =SUM(CPSX!AO$72:AO$81) -> 3.1517286e+08 | E28: =SUM(CPSX!AM$72:AM$81) -> 220439144 | F28: =SUM(CPSX!AK$72:AK$81) -> 1.0162315e+09 | G28: =SUM(CPSX!K$72:K$81) -> 2.0140792e+08 | H28: =SUM(CPSX!L$72:L$81) -> 2.2291481e+08 | I28: =SUM(CPSX!M$72:M$81) -> 1.9174351e+08 | J28: =SUM(CPSX!N$72:N$81) -> 2.0729541e+08 | K28: =SUM(CPSX!O$72:O$81) -> 197959424 | L28: =SUM(CPSX!P$72:P$81) -> 2.0561971e+08 | M28: =SUM(CPSX!Q$72:Q$81) -> 2.0558595e+08 | N28: =SUM(CPSX!R$72:R$81) -> 2.0680673e+08 | ... R28: =SUM(CPSX!V$72:V$81) -> 2.0131325e+08 | S28: =SUM(G28:R28) -> 2.4550487e+09
B29: 5.2 | C29: Chi phí thuê xưởng | D29: =CPSX!AO$88 -> 1118310000 | E29: =CPSX!AM$88 -> 1557000000 | F29: =CPSX!AK$88 -> 1800000000 | G29: =CPSX!K$88 -> 150000000 | H29: =CPSX!L$88 -> 150000000 | I29: =CPSX!M$88 -> 150000000 | J29: =CPSX!N$88 -> 150000000 | K29: =CPSX!O$88 -> 150000000 | L29: =CPSX!P$88 -> 150000000 | M29: =CPSX!Q$88 -> 150000000 | N29: =CPSX!R$88 -> 150000000 | ... R29: =CPSX!V$88 -> 150000000 | S29: =SUM(G29:R29) -> 1800000000
B30: 5.3 | C30: Chi phí sản xuất (Ngoài lương, BOM, thuê xưởng, khấu hao) | D30: =CPSX!AO17+SUM(CPSX!AO82:AO87)+SUM(CPSX!AO89:AO98) -> 660674936 | E30: =CPSX!AM17+SUM(CPSX!AM82:AM87)+SUM(CPSX!AM89:AM98) -> 607757632 | F30: =CPSX!AK17+SUM(CPSX!AK82:AK87)+SUM(CPSX!AK89:AK98) -> 1.3885989e+09 | G30: =CPSX!K17+SUM(CPSX!K82:K87)+SUM(CPSX!K89:K98) -> 1.7344606e+08 | H30: =CPSX!L17+SUM(CPSX!L82:L87)+SUM(CPSX!L89:L98) -> 1.6176933e+08 | I30: =CPSX!M17+SUM(CPSX!M82:M87)+SUM(CPSX!M89:M98) -> 1.5648207e+08 | J30: =CPSX!N17+SUM(CPSX!N82:N87)+SUM(CPSX!N89:N98) -> 1.5964503e+08 | K30: =CPSX!O17+SUM(CPSX!O82:O87)+SUM(CPSX!O89:O98) -> 1.5005774e+08 | L30: =CPSX!P17+SUM(CPSX!P82:P87)+SUM(CPSX!P89:P98) -> 1.7035236e+08 | M30: =CPSX!Q17+SUM(CPSX!Q82:Q87)+SUM(CPSX!Q89:Q98) -> 1.5076764e+08 | N30: =CPSX!R17+SUM(CPSX!R82:R87)+SUM(CPSX!R89:R98) -> 1.5511304e+08 | ... R30: =CPSX!V17+SUM(CPSX!V82:V87)+SUM(CPSX!V89:V98) -> 1.5967352e+08 | S30: =SUM(G30:R30) -> 1.8835303e+09
B31: 6 | C31: CHI PHÍ KHẤU HAO | D31: =CPSX!AO99 -> 1036408270 | E31: =CPSX!AM99 -> 1382050356 | F31: =CPSX!AK99 -> 1.9084998e+09 | G31: =SUM(CPSX!K100:K104) -> 81327530 | H31: =SUM(CPSX!L100:L104) -> 81327530 | I31: =SUM(CPSX!M100:M104) -> 81327530 | J31: =SUM(CPSX!N100:N104) -> 81327530 | K31: =SUM(CPSX!O100:O104) -> 81327530 | L31: =SUM(CPSX!P100:P104) -> 81327530 | M31: =SUM(CPSX!Q100:Q104) -> 81327530 | N31: =SUM(CPSX!R100:R104) -> 81327530 | ... R31: =SUM(CPSX!V100:V104) -> 81327530 | S31: =SUM(G31:R31) -> 9.7593036e+08
B32: 7 | C32: LỢI NHUẬN GỘP | D32: =D25-D27-D31 -> 871201538 | E32: =E25-E27-E31 -> -189825901 | F32: =F25-F27-F31 -> 4.5720617e+09 | G32: =G25-G27-G31 -> 1.6438296e+08 | H32: =H25-H27-H31 -> -1.4838278e+08 | I32: =I25-I27-I31 -> 2.9984301e+08 | J32: =J25-J27-J31 -> 3.5326827e+08 | K32: =K25-K27-K31 -> 3.9705403e+08 | ... R32: =R25-R27-R31 -> 3.7578957e+08 | S32: =SUM(G32:R32) -> 3.5490792e+09
B33: 7.1 | C33: % lãi gộp/doanh thu | D33: =D32/D9 -> 0.011039653 | E33: =E32/E9 -> -0.0025472087 | F33: =F32/F9 -> 0.046784536 | G33: =G32/G9 -> 0.022007077 | H33: =H32/H9 -> -0.026486697 | I33: =I32/I9 -> 0.037054195 | J33: =J32/J9 -> 0.040538102 | K33: =K32/K9 -> 0.045562588 | ... S33: =S32/S9 -> 0.035635472
B34: 8 | C34: CHI PHÍ BÁN HÀNG & MKT & R&D | D34: =D35+D36+D37 -> 0 | E34: =E35+E36+E37 -> 0 | F34: =F35+F36+F37 -> 0 | G34: =G35+G36+G37 -> 0 | H34: =H35+H36+H37 -> 0 | I34: =I35+I36+I37 -> 0 | J34: =J35+J36+J37 -> 0 | K34: =K35+K36+K37 -> 0 | ... R34: =R35+R36+R37 -> 0 | S34: =SUM(G34:R34) -> 0
B35: 8.1 | C35: Lương | S35: =SUM(G35:R35) -> 0
B36: 8.2 | C36: Chi phí bán hàng (ngoài lương, khấu hao) | S36: =SUM(G36:R36) -> 0
B37: 8.3 | C37: Khấu hao tài sản | S37: =SUM(G37:R37) -> 0
B38: 9 | C38: CHI PHÍ QUẢN LÝ | D38: =D39+D40+D41 -> 1414416772 | E38: =E39+E40+E41 -> 2036034770 | F38: =F39+F40+F41 -> 3.891071e+09 | G38: =G39+G40+G41 -> 4.7153661e+08 | H38: =H39+H40+H41 -> 4.996212e+08 | I38: =I39+I40+I41 -> 4.3800101e+08 | J38: =J39+J40+J41 -> 4.4143001e+08 | K38: =K39+K40+K41 -> 4.4099057e+08 | ... R38: =R39+R40+R41 -> 4.4120512e+08 | S38: =SUM(G38:R38) -> 5.4138202e+09
B39: 9.1 | C39: Lương | D39: =SUM(CPQL!AO5:AO14) -> 1124385437 | E39: =SUM(CPQL!AM5:AM14) -> 1412576558 | F39: =SUM(CPQL!AK5:AK14) -> 2.8990944e+09 | G39: =SUM(CPQL!K5:K14) -> 323945534 | H39: =SUM(CPQL!L5:L14) -> 362007174 | I39: =SUM(CPQL!M5:M14) -> 317132791 | J39: =SUM(CPQL!N5:N14) -> 325999646 | K39: =SUM(CPQL!O5:O14) -> 321392926 | L39: =SUM(CPQL!P5:P14) -> 325999646 | M39: =SUM(CPQL!Q5:Q14) -> 323044028 | N39: =SUM(CPQL!R5:R14) -> 323044028 | ... R39: =SUM(CPQL!V5:V14) -> 323044028 | S39: =SUM(G39:R39) -> 3918100515
B40: 9.2 | C40: Chi phí quản lý (ngoài lương, khấu hao) | D40: =SUM(CPQL!AO15:AO62) -> 290031335 | E40: =SUM(CPQL!AM15:AM62) -> 609710270 | F40: =SUM(CPQL!AK15:AK62) -> 902118544 | G40: =SUM(CPQL!K15:K62) -> 1.3693526e+08 | H40: =SUM(CPQL!L15:L62) -> 1.2695821e+08 | I40: =SUM(CPQL!M15:M62) -> 1.102124e+08 | J40: =SUM(CPQL!N15:N62) -> 1.0477454e+08 | K40: =SUM(CPQL!O15:O62) -> 1.0894183e+08 | L40: =SUM(CPQL!P15:P62) -> 1.0123631e+08 | M40: =SUM(CPQL!Q15:Q62) -> 1.039655e+08 | N40: =SUM(CPQL!R15:R62) -> 1.5988002e+08 | ... R40: =SUM(CPQL!V15:V62) -> 1.0750528e+08 | S40: =SUM(G40:R40) -> 1.3678499e+09
B41: 9.3 | C41: Khấu hao tài sản | D41: =CPQL!AO63 -> 0 | E41: =CPQL!AM63 -> 13747942 | F41: =CPQL!AK63 -> 89858023 | G41: =CPQL!K63 -> 10655817 | H41: =CPQL!L63 -> 10655817 | I41: =CPQL!M63 -> 10655817 | J41: =CPQL!N63 -> 10655817 | K41: =CPQL!O63 -> 10655817 | L41: =CPQL!P63 -> 10655817 | M41: =CPQL!Q63 -> 10655817 | N41: =CPQL!R63 -> 10655817 | ... R41: =CPQL!V63 -> 10655817 | S41: =SUM(G41:R41) -> 1.278698e+08
B42: 10 | C42: DOANH THU/CHI PHÍ KHÁC | D42: 114814093 | E42: =4158777-63647871 -> -59489094 | F42: 283673552 | S42: =SUM(G42:R42) -> 0 | U42: <= Nhập số liệu
B43: 11 | C43: LỢI NHUẬN THUẦN TỪ HOẠT ĐỘNG KINH DOANH | D43: =D32-D34-D38+D42 -> -428401141 | E43: =E32-E34-E38+E42 -> -2285349765 | F43: =F32-F34-F38+F42 -> 9.6466433e+08 | G43: =G32-G34-G38+G42 -> -3.0715365e+08 | H43: =H32-H34-H38+H42 -> -6.4800398e+08 | I43: =I32-I34-I38+I42 -> -1.38158e+08 | J43: =J32-J34-J38+J42 -> -88161731 | K43: =K32-K34-K38+K42 -> -43936535 | ... R43: =R32-R34-R38+R42 -> -65415549 | S43: =SUM(G43:R43) -> -1.864741e+09
B44: 12 | C44: DOANH THU TÀI CHÍNH | D44: 4823037 | E44: =438643 -> 438643 | F44: 6026805 | G44: 60000 | H44: 60000 | I44: 60000 | J44: 60000 | K44: 60000 | L44: 60000 | M44: 60000 | N44: 60000 | O44: 60000 | P44: 60000 | Q44: 60000 | R44: 60000 | S44: =SUM(G44:R44) -> 720000 | U44: <= Nhập số liệu
B45: 13 | C45: CHI PHÍ TÀI CHÍNH | S45: =SUM(G45:R45) -> 0 | U45: <= Nhập số liệu
B46: 13.1 | C46: Trong đó: chi phí lãi vay | S46: =SUM(G46:R46) -> 0
B47: 14 | C47: LỢI NHUẬN TRƯỚC THUẾ | D47: =D43+D44-D45 -> -423578104 | E47: =E43+E44-E45 -> -2284911122 | F47: =F43+F44-F45 -> 9.7069113e+08 | G47: =G43+G44-G45 -> -3.0709365e+08 | H47: =H43+H44-H45 -> -6.4794398e+08 | I47: =I43+I44-I45 -> -1.38098e+08 | J47: =J43+J44-J45 -> -88101731 | K47: =K43+K44-K45 -> -43876535 | ... R47: =R43+R44-R45 -> -65355549 | S47: =SUM(G47:R47) -> -1.864021e+09
B48: 15 | C48: THUẾ TNDN | S48: =SUM(G48:R48) -> 0 | U48: <= Nhập số liệu
B49: 16 | C49: LỢI NHUẬN SAU THUẾ | D49: =D47-D48 -> -423578104 | E49: =E47-E48 -> -2284911122 | F49: =F47-F48 -> 9.7069113e+08 | G49: =G47-G48 -> -3.0709365e+08 | H49: =H47-H48 -> -6.4794398e+08 | I49: =I47-I48 -> -1.38098e+08 | J49: =J47-J48 -> -88101731 | K49: =K47-K48 -> -43876535 | ... R49: =R47-R48 -> -65355549 | S49: =SUM(G49:R49) -> -1.864021e+09
B50: 16.1 | C50: % LNST/doanh thu | D50: =D49/D9 -> -0.0053674781 | E50: =E49/E9 -> -0.030660439 | F50: =F49/F9 -> 0.0099327912 | G50: =G49/G9 -> -0.041112738 | H50: =H49/H9 -> -0.11565962 | I50: =I49/I9 -> -0.017065964 | J50: =J49/J9 -> -0.010109815 | K50: =K49/K9 -> -0.0050349029 | ... S50: =S49/S9 -> -0.018716198
B51: 17 | C51: Khấu hao tài sản | D51: =D31+D41+D37 -> 1036408270 | E51: =E31+E41+E37 -> 1395798298 | F51: =F31+F41+F37 -> 1.9983578e+09 | G51: =G31+G41+G37 -> 91983346 | H51: =H31+H41+H37 -> 91983346 | I51: =I31+I41+I37 -> 91983346 | J51: =J31+J41+J37 -> 91983346 | K51: =K31+K41+K37 -> 91983346 | ... S51: =S31+S41+S37 -> 1.1038002e+09
B52: 18 | C52: LỢI NHUẬN KHÔNG BAO GỒM KHẤU HAO, LÃI VAY | D52: =D49+D51 -> 612830166 | E52: =E49+E51 -> -889112824 | F52: =F49+F51 -> 2.9690489e+09 | G52: =G49+G51 -> -2.151103e+08 | H52: =H49+H51 -> -5.5596063e+08 | I52: =I49+I51 -> -46114651 | J52: =J49+J51 -> 3881615.2 | K52: =K49+K51 -> 48106811 | ... R52: =R49+R51 -> 26627797 | S52: =SUM(G52:R52) -> -7.6022086e+08
B53: 18.1 | C53: % LN không gồm khấu hao/doanh thu | D53: =D52/D9 -> 0.0077656339 | E53: =E52/E9 -> -0.0119307 | F53: =F52/F9 -> 0.030381387 | G53: =G52/G9 -> -0.028798295 | H53: =H52/H9 -> -0.099240362 | I53: =I52/I9 -> -0.0056987864 | J53: =J52/J9 -> 0.00044542158 | K53: =K52/K9 -> 0.0055203338 | ... S53: =S52/S9 -> -0.0076331993
B56: 1. Hòa vốn (Bao gồm khấu hao) | D56: =D4 -> Thực tế năm 2023 | E56: =E4 -> Thực tế năm 2024 | F56: =F4 -> KQKD 2025 | G56: =G4 -> T1 | H56: =H4 -> T2 | I56: =I4 -> T3 | J56: =J4 -> T4 | K56: =K4 -> T5 | ... S56: =S4 -> Kế hoạch 2026
B57: Sản lượng NVL hòa vốn (tấn) | D57: =D$58*(1+(D$17+D$18)/D$16) -> 6834600.4 | E57: =E$58*(1+(E$17+E$18)/E$16) -> 8662919.1 | F57: =IFERROR(F$58*(1+(F$17+F$18)/F$16),0) -> 6085582.8 | G57: =G$58*(1+(G$17+G$18)/G$16) -> 828918.76 | H57: =H$58*(1+(H$17+H$18)/H$16) -> 1060466.6 | I57: =I$58*(1+(I$17+I$18)/I$16) -> 742935.04 | J57: =J$58*(1+(J$17+J$18)/J$16) -> 755517.31 | K57: =K$58*(1+(K$17+K$18)/K$16) -> 722567.21 | L57: =L$58*(1+(L$17+L$18)/L$16) -> 754581.89 | M57: =M$58*(1+(M$17+M$18)/M$16) -> 765452.93 | N57: =N$58*(1+(N$17+N$18)/N$16) -> 821969.74 | ... S57: =S$58*(1+(S$17+S$18)/S$16) -> 9284195.8
B58: Sản lượng thành phẩm hòa vốn (tấn) | D58: =(D$27+D$31+D$34+D$38)/(D$25/D$5) -> 6420099.2 | E58: =(E$27+E$31+E$34+E$38)/(E$25/E$5) -> 7940684 | F58: =IFERROR((F$27+F$31+F$34+F$38)/(F$25/F$5),0) -> 5505073.5 | G58: =(G$27+G$31+G$34+G$38)/(G$25/G$5) -> 746437.43 | H58: =(H$27+H$31+H$34+H$38)/(H$25/H$5) -> 954945.17 | I58: =(I$27+I$31+I$34+I$38)/(I$25/I$5) -> 669009.49 | J58: =(J$27+J$31+J$34+J$38)/(J$25/J$5) -> 680339.76 | K58: =(K$27+K$31+K$34+K$38)/(K$25/K$5) -> 650668.35 | L58: =(L$27+L$31+L$34+L$38)/(L$25/L$5) -> 679497.43 | M58: =(M$27+M$31+M$34+M$38)/(M$25/M$5) -> 689286.74 | N58: =(N$27+N$31+N$34+N$38)/(N$25/N$5) -> 740179.87 | ... S58: =(S$27+S$31+S$34+S$38)/(S$25/S$5) -> 8360374.4
B59: Doanh thu hòa vốn (triệu đồng) | D59: =D$58*(D$9/D$5) -> 8.9627979e+10 | E59: =E$58*(E$9/E$5) -> 1.2089115e+11 | F59: =IFERROR(F$58*(F$9/F$5),0) -> 9.1497746e+10 | G59: =G$58*(G$9/G$5) -> 1.0446977e+10 | H59: =H$58*(H$9/H$5) -> 1.3365206e+10 | I59: =I$58*(I$9/I$5) -> 9.3633125e+09 | J59: =J$58*(J$9/J$5) -> 9.5218885e+09 | K59: =K$58*(K$9/K$5) -> 9.1066138e+09 | L59: =L$58*(L$9/L$5) -> 9.5100993e+09 | M59: =M$58*(M$9/M$5) -> 9.6471085e+09 | N59: =N$58*(N$9/N$5) -> 1.0359398e+10 | ... S59: =S$58*(S$9/S$5) -> 1.1701e+11
B60: 2. Hòa vốn (Không bao gồm khấu hao) | D60: =D56 -> Thực tế năm 2023 | E60: =E56 -> Thực tế năm 2024 | F60: =F56 -> KQKD 2025 | G60: =G56 -> T1 | H60: =H56 -> T2 | I60: =I56 -> T3 | J60: =J56 -> T4 | K60: =K56 -> T5 | ... S60: =S56 -> Kế hoạch 2026
B61: Sản lượng NVL hòa vốn (tấn) | D61: =D$62*(1+(D$17+D$18)/D$16) -> 5276082.7 | E61: =E$62*(1+(E$17+E$18)/E$16) -> 6579324.4 | F61: =IFERROR(F$62*(1+(F$17+F$18)/F$16),0) -> 4870000.6 | G61: =G$62*(1+(G$17+G$18)/G$16) -> 758170.47 | H61: =H$62*(1+(H$17+H$18)/H$16) -> 973031.7 | I61: =I$62*(1+(I$17+I$18)/I$16) -> 675776.3 | J61: =J$62*(1+(J$17+J$18)/J$16) -> 688675.77 | K61: =K$62*(1+(K$17+K$18)/K$16) -> 657427.69 | L61: =L$62*(1+(L$17+L$18)/L$16) -> 688173.99 | M61: =M$62*(1+(M$17+M$18)/M$16) -> 696784.51 | N61: =N$62*(1+(N$17+N$18)/N$16) -> 752402.54 | ... S61: =S$62*(1+(S$17+S$18)/S$16) -> 8466217.9
B62: Sản lượng thành phẩm hòa vốn (tấn) | D62: =(D$27+D$31+D$34+D$38-D51)/(D$25/D$5) -> 4956101.6 | E62: =(E$27+E$31+E$34+E$38-E51)/(E$25/E$5) -> 6030800.4 | F62: =IFERROR((F$27+F$31+F$34+F$38-F51)/(F$25/F$5),0) -> 4405446.8 | G62: =(G$27+G$31+G$34+G$38-G51)/(G$25/G$5) -> 682728.92 | H62: =(H$27+H$31+H$34+H$38-H51)/(H$25/H$5) -> 876210.44 | I62: =(I$27+I$31+I$34+I$38-I51)/(I$25/I$5) -> 608533.37 | J62: =(J$27+J$31+J$34+J$38-J51)/(J$25/J$5) -> 620149.28 | K62: =(K$27+K$31+K$34+K$38-K51)/(K$25/K$5) -> 592010.52 | L62: =(L$27+L$31+L$34+L$38-L51)/(L$25/L$5) -> 619697.42 | M62: =(M$27+M$31+M$34+M$38-M51)/(M$25/M$5) -> 627451.15 | N62: =(N$27+N$31+N$34+N$38-N51)/(N$25/N$5) -> 677534.93 | ... S62: =(S$27+S$31+S$34+S$38-S51)/(S$25/S$5) -> 7623789.2
B63: Doanh thu hòa vốn (triệu đồng) | D63: =D$62*(D$9/D$5) -> 6.9189799e+10 | E63: =E$62*(E$9/E$5) -> 9.1814561e+10 | F63: =IFERROR(F$62*(F$9/F$5),0) -> 7.3221267e+10 | G63: =G$62*(G$9/G$5) -> 9.5553266e+09 | H63: =H$62*(H$9/H$5) -> 1.2263252e+10 | I63: =I$62*(I$9/I$5) -> 8.5169016e+09 | J63: =J$62*(J$9/J$5) -> 8.6794754e+09 | K63: =K$62*(K$9/K$5) -> 8.2856515e+09 | L63: =L$62*(L$9/L$5) -> 8.6731514e+09 | M63: =M$62*(M$9/M$5) -> 8.7816709e+09 | N63: =N$62*(N$9/N$5) -> 9.4826326e+09 | ... S63: =S$62*(S$9/S$5) -> 1.0670091e+11
F65: =S9/S5 -> 13995.784

Sheet KQKD HD
B3: MỤC TIÊU KẾT QUẢ KINH DOANH NĂM 2026 | R3: ĐVT: Triệu đồng
B4: STT | C4: Mục phí | D4: Thực tế năm 2024 | E4: KQKD 2025 | F4: T1 | G4: T2 | H4: T3 | I4: T4 | J4: T5 | K4: T6 | L4: T7 | M4: T8 | N4: T9 | O4: T10 | P4: T11 | Q4: T12 | R4: Kế hoạch 2026
B5: 1 | C5: SẢN LƯỢNG BÁN (TẤN) | E5: =E6+E7+E8 -> 0 | F5: =F6+F7+F8 -> 0 | G5: =G6+G7+G8 -> 0 | H5: =H6+H7+H8 -> 0 | I5: =I6+I7+I8 -> 0 | J5: =J6+J7+J8 -> 0 | K5: =K6+K7+K8 -> 0 | L5: =L6+L7+L8 -> 0 | ... Q5: =Q6+Q7+Q8 -> 0 | R5: =SUM(F5:Q5) -> 0
B6: 1.1 | C6: Chai PET | R6: =SUM(F6:Q6) -> 0
B7: 1.2 | C7: Vảy PET | R7: =SUM(F7:Q7) -> 0
B8: 1.3 | C8: Vảy HD | F8: ='4.Doanh thu'!F123 -> 0 | G8: ='4.Doanh thu'!G123 -> 0 | H8: ='4.Doanh thu'!H123 -> 0 | I8: ='4.Doanh thu'!I123 -> 0 | J8: ='4.Doanh thu'!J123 -> 0 | K8: ='4.Doanh thu'!K123 -> 0 | L8: ='4.Doanh thu'!L123 -> 0 | M8: ='4.Doanh thu'!M123 -> 0 | ... Q8: ='4.Doanh thu'!Q123 -> 0 | R8: =SUM(F8:Q8) -> 0
B9: 2 | C9: DOANH THU | E9: =E10+E11+E12+E13 -> 0 | F9: =F10+F11+F12+F13 -> 0 | G9: =G10+G11+G12+G13 -> 0 | H9: =H10+H11+H12+H13 -> 0 | I9: =I10+I11+I12+I13 -> 0 | J9: =J10+J11+J12+J13 -> 0 | K9: =K10+K11+K12+K13 -> 0 | L9: =L10+L11+L12+L13 -> 0 | ... Q9: =Q10+Q11+Q12+Q13 -> 0 | R9: =SUM(F9:Q9) -> 0
B10: 2.1 | C10: Chai PET | R10: =SUM(F10:Q10) -> 0
B11: 2.2 | C11: Vảy PET | R11: =SUM(F11:Q11) -> 0
B12: 2.3 | C12: Vảy HD | F12: ='4.Doanh thu'!F125 -> 0 | G12: ='4.Doanh thu'!G125 -> 0 | H12: ='4.Doanh thu'!H125 -> 0 | I12: ='4.Doanh thu'!I125 -> 0 | J12: ='4.Doanh thu'!J125 -> 0 | K12: ='4.Doanh thu'!K125 -> 0 | L12: ='4.Doanh thu'!L125 -> 0 | M12: ='4.Doanh thu'!M125 -> 0 | ... Q12: ='4.Doanh thu'!Q125 -> 0 | R12: =SUM(F12:Q12) -> 0
B13: 2.4 | C13: Khác | R13: =SUM(F13:Q13) -> 0
B14: 3 | C14: BIẾN PHÍ | E14: =E15+E23 -> 0 | F14: =F15+F23 -> 0 | G14: =G15+G23 -> 0 | H14: =H15+H23 -> 0 | I14: =I15+I23 -> 0 | J14: =J15+J23 -> 0 | K14: =K15+K23 -> 0 | L14: =L15+L23 -> 0 | ... Q14: =Q15+Q23 -> 0 | R14: =SUM(F14:Q14) -> 0
B15: 3.1 | C15: BIẾN PHÍ SẢN XUẤT | E15: =E16+E20+E21+E22 -> 0 | F15: =F16+F20+F21+F22 -> 0 | G15: =G16+G20+G21+G22 -> 0 | H15: =H16+H20+H21+H22 -> 0 | I15: =I16+I20+I21+I22 -> 0 | J15: =J16+J20+J21+J22 -> 0 | K15: =K16+K20+K21+K22 -> 0 | L15: =L16+L20+L21+L22 -> 0 | ... Q15: =Q16+Q20+Q21+Q22 -> 0 | R15: =SUM(F15:Q15) -> 0
B16: 3.1.1 | C16: Nguyên vật liệu chính (nhựa, gồm hao hụt) | F16: ='1.NVL Chai'!H21 -> 0 | G16: ='1.NVL Chai'!I21 -> 0 | H16: ='1.NVL Chai'!J21 -> 0 | I16: ='1.NVL Chai'!K21 -> 0 | J16: ='1.NVL Chai'!L21 -> 0 | K16: ='1.NVL Chai'!M21 -> 0 | L16: ='1.NVL Chai'!N21 -> 0 | M16: ='1.NVL Chai'!O21 -> 0 | ... Q16: ='1.NVL Chai'!S21 -> 0 | R16: =SUM(F16:Q16) -> 0
B17: 3.1.2 | C17: Trong đó: i/ Hao hụt CĐ phân loại chai | R17: =SUM(F17:Q17) -> 0
C18: ii/ Hao hụt CĐ băm vảy | F18: ='1.NVL Chai'!H21*'2.Hao hut & % chai '!F48 -> 0 | G18: ='1.NVL Chai'!I21*'2.Hao hut & % chai '!G48 -> 0 | H18: ='1.NVL Chai'!J21*'2.Hao hut & % chai '!H48 -> 0 | I18: ='1.NVL Chai'!K21*'2.Hao hut & % chai '!I48 -> 0 | J18: ='1.NVL Chai'!L21*'2.Hao hut & % chai '!J48 -> 0 | K18: ='1.NVL Chai'!M21*'2.Hao hut & % chai '!K48 -> 0 | L18: ='1.NVL Chai'!N21*'2.Hao hut & % chai '!L48 -> 0 | M18: ='1.NVL Chai'!O21*'2.Hao hut & % chai '!M48 -> 0 | ... Q18: ='1.NVL Chai'!S21*'2.Hao hut & % chai '!Q48 -> 0 | R18: =SUM(F18:Q18) -> 0
B19: 3.1.3 | C19: % chi phí nguyên liệu/doanh thu | E19: =IFERROR(E18/E$9,0) -> 0 | F19: =IFERROR(F18/F$9,0) -> 0 | G19: =IFERROR(G18/G$9,0) -> 0 | H19: =IFERROR(H18/H$9,0) -> 0 | I19: =IFERROR(I18/I$9,0) -> 0 | J19: =IFERROR(J18/J$9,0) -> 0 | K19: =IFERROR(K18/K$9,0) -> 0 | L19: =IFERROR(L18/L$9,0) -> 0 | ... R19: =IFERROR(R18/R$9,0) -> 0
B20: 3.1.4 | C20: Nguyên vật liệu phụ | R20: =SUM(F20:Q20) -> 0
B21: 3.1.5 | C21: Điện sản xuất | R21: =SUM(F21:Q21) -> 0
B22: 3.1.6 | C22: Nhân công trực tiếp | F22: =Luong_HCNS!G62 -> 0 | G22: =Luong_HCNS!H62 -> 0 | H22: =Luong_HCNS!I62 -> 0 | I22: =Luong_HCNS!J62 -> 0 | J22: =Luong_HCNS!K62 -> 0 | K22: =Luong_HCNS!L62 -> 0 | L22: =Luong_HCNS!M62 -> 0 | M22: =Luong_HCNS!N62 -> 0 | ... Q22: =Luong_HCNS!R62 -> 0 | R22: =SUM(F22:Q22) -> 0
B23: 3.2 | C23: BIẾN PHÍ BÁN HÀNG | E23: =E24 -> 0 | F23: =F24 -> 0 | G23: =G24 -> 0 | H23: =H24 -> 0 | I23: =I24 -> 0 | J23: =J24 -> 0 | K23: =K24 -> 0 | L23: =L24 -> 0 | ... Q23: =Q24 -> 0 | R23: =SUM(F23:Q23) -> 0
C24: Chi phí vận chuyển | F24: ='3.Thanh pham'!H141*'Dinh muc'!$G$48 -> 0 | G24: ='3.Thanh pham'!I141*'Dinh muc'!$G$48 -> 0 | H24: ='3.Thanh pham'!J141*'Dinh muc'!$G$48 -> 0 | I24: ='3.Thanh pham'!K141*'Dinh muc'!$G$48 -> 0 | J24: ='3.Thanh pham'!L141*'Dinh muc'!$G$48 -> 0 | K24: ='3.Thanh pham'!M141*'Dinh muc'!$G$48 -> 0 | L24: ='3.Thanh pham'!N141*'Dinh muc'!$G$48 -> 0 | M24: ='3.Thanh pham'!O141*'Dinh muc'!$G$48 -> 0 | ... Q24: ='3.Thanh pham'!S141*'Dinh muc'!$G$48 -> 0 | R24: =SUM(F24:Q24) -> 0
B25: 4 | C25: LÃI SAU BIẾN PHÍ | E25: =E9-E14 -> 0 | F25: =F9-F14 -> 0 | G25: =G9-G14 -> 0 | H25: =H9-H14 -> 0 | I25: =I9-I14 -> 0 | J25: =J9-J14 -> 0 | K25: =K9-K14 -> 0 | L25: =L9-L14 -> 0 | ... Q25: =Q9-Q14 -> 0 | R25: =SUM(F25:Q25) -> 0
B26: 4.1 | C26: % lãi biến phí/doanh thu | E26: =IFERROR(E25/E$9,0) -> 0 | F26: =IFERROR(F25/F$9,0) -> 0 | G26: =IFERROR(G25/G$9,0) -> 0 | H26: =IFERROR(H25/H$9,0) -> 0 | I26: =IFERROR(I25/I$9,0) -> 0 | J26: =IFERROR(J25/J$9,0) -> 0 | K26: =IFERROR(K25/K$9,0) -> 0 | L26: =IFERROR(L25/L$9,0) -> 0 | ... R26: =IFERROR(R25/R$9,0) -> 0
B27: 5 | C27: CHI PHÍ SẢN XUẤT CHUNG | E27: =E28+E29+E30 -> 0 | F27: =F28+F29+F30 -> 0 | G27: =G28+G29+G30 -> 0 | H27: =H28+H29+H30 -> 0 | I27: =I28+I29+I30 -> 0 | J27: =J28+J29+J30 -> 0 | K27: =K28+K29+K30 -> 0 | L27: =L28+L29+L30 -> 0 | ... Q27: =Q28+Q29+Q30 -> 0 | R27: =SUM(F27:Q27) -> 0
B28: 5.1 | C28: Lương gián tiếp Sản xuất | F28: =Luong_HCNS!G61 -> 0 | G28: =Luong_HCNS!H61 -> 0 | H28: =Luong_HCNS!I61 -> 0 | I28: =Luong_HCNS!J61 -> 0 | J28: =Luong_HCNS!K61 -> 0 | K28: =Luong_HCNS!L61 -> 0 | L28: =Luong_HCNS!M61 -> 0 | M28: =Luong_HCNS!N61 -> 0 | ... Q28: =Luong_HCNS!R61 -> 0 | R28: =SUM(F28:Q28) -> 0
B29: 5.2 | C29: Chi phí thuê xưởng | R29: =SUM(F29:Q29) -> 0
B30: 5.3 | C30: Chi phí sản xuất (Ngoài lương, BOM, thuê xưởng, khấu hao) | R30: =SUM(F30:Q30) -> 0
B31: 6 | C31: CHI PHÍ KHẤU HAO | R31: =SUM(F31:Q31) -> 0
B32: 7 | C32: LỢI NHUẬN GỘP | E32: =E25-E27-E31 -> 0 | F32: =F25-F27-F31 -> 0 | G32: =G25-G27-G31 -> 0 | H32: =H25-H27-H31 -> 0 | I32: =I25-I27-I31 -> 0 | J32: =J25-J27-J31 -> 0 | K32: =K25-K27-K31 -> 0 | L32: =L25-L27-L31 -> 0 | ... Q32: =Q25-Q27-Q31 -> 0 | R32: =SUM(F32:Q32) -> 0
B33: 7.1 | C33: % lãi gộp/doanh thu | E33: =IFERROR(E32/E$9,0) -> 0 | F33: =IFERROR(F32/F$9,0) -> 0 | G33: =IFERROR(G32/G$9,0) -> 0 | H33: =IFERROR(H32/H$9,0) -> 0 | I33: =IFERROR(I32/I$9,0) -> 0 | J33: =IFERROR(J32/J$9,0) -> 0 | K33: =IFERROR(K32/K$9,0) -> 0 | L33: =IFERROR(L32/L$9,0) -> 0 | ... R33: =IFERROR(R32/R$9,0) -> 0
B34: 8 | C34: CHI PHÍ BÁN HÀNG & MKT & R&D | E34: =E35+E36+E37 -> 0 | F34: =F35+F36+F37 -> 0 | G34: =G35+G36+G37 -> 0 | H34: =H35+H36+H37 -> 0 | I34: =I35+I36+I37 -> 0 | J34: =J35+J36+J37 -> 0 | K34: =K35+K36+K37 -> 0 | L34: =L35+L36+L37 -> 0 | ... Q34: =Q35+Q36+Q37 -> 0 | R34: =SUM(F34:Q34) -> 0
B35: 8.1 | C35: Lương | R35: =SUM(F35:Q35) -> 0
B36: 8.2 | C36: Chi phí bán hàng (ngoài lương, khấu hao) | R36: =SUM(F36:Q36) -> 0
B37: 83 | C37: Khấu hao tài sản | R37: =SUM(F37:Q37) -> 0
B38: 9 | C38: CHI PHÍ QUẢN LÝ | E38: =E39+E40+E41 -> 0 | F38: =F39+F40+F41 -> 0 | G38: =G39+G40+G41 -> 0 | H38: =H39+H40+H41 -> 0 | I38: =I39+I40+I41 -> 0 | J38: =J39+J40+J41 -> 0 | K38: =K39+K40+K41 -> 0 | L38: =L39+L40+L41 -> 0 | ... Q38: =Q39+Q40+Q41 -> 0 | R38: =SUM(F38:Q38) -> 0
B39: 9.1 | C39: Lương | R39: =SUM(F39:Q39) -> 0
B40: 9.2 | C40: Chi phí quản lý (ngoài lương, khấu hao) | R40: =SUM(F40:Q40) -> 0
B41: 9.3 | C41: Khấu hao tài sản | R41: =SUM(F41:Q41) -> 0
B42: 10 | C42: DOANH THU/CHI PHÍ KHÁC | R42: =SUM(F42:Q42) -> 0
B43: 11 | C43: LỢI NHUẬN THUẦN TỪ HOẠT ĐỘNG KINH DOANH | E43: =E32-E34-E38+E42 -> 0 | F43: =F32-F34-F38+F42 -> 0 | G43: =G32-G34-G38+G42 -> 0 | H43: =H32-H34-H38+H42 -> 0 | I43: =I32-I34-I38+I42 -> 0 | J43: =J32-J34-J38+J42 -> 0 | K43: =K32-K34-K38+K42 -> 0 | L43: =L32-L34-L38+L42 -> 0 | ... Q43: =Q32-Q34-Q38+Q42 -> 0 | R43: =SUM(F43:Q43) -> 0
B44: 12 | C44: DOANH THU TÀI CHÍNH | R44: =SUM(F44:Q44) -> 0
B45: 13 | C45: CHI PHÍ TÀI CHÍNH | R45: =SUM(F45:Q45) -> 0
B46: 13.1 | C46: Trong đó: chi phí lãi vay | R46: =SUM(F46:Q46) -> 0
B47: 14 | C47: LỢI NHUẬN TRƯỚC THUẾ | E47: =E43+E44-E45 -> 0 | F47: =F43+F44-F45 -> 0 | G47: =G43+G44-G45 -> 0 | H47: =H43+H44-H45 -> 0 | I47: =I43+I44-I45 -> 0 | J47: =J43+J44-J45 -> 0 | K47: =K43+K44-K45 -> 0 | L47: =L43+L44-L45 -> 0 | ... Q47: =Q43+Q44-Q45 -> 0 | R47: =SUM(F47:Q47) -> 0
B48: 15 | C48: THUẾ TNDN | R48: =SUM(F48:Q48) -> 0
B49: 16 | C49: LỢI NHUẬN SAU THUẾ | E49: =E47-E48 -> 0 | F49: =F47-F48 -> 0 | G49: =G47-G48 -> 0 | H49: =H47-H48 -> 0 | I49: =I47-I48 -> 0 | J49: =J47-J48 -> 0 | K49: =K47-K48 -> 0 | L49: =L47-L48 -> 0 | ... Q49: =Q47-Q48 -> 0 | R49: =SUM(F49:Q49) -> 0
B50: 16.1 | C50: % LNST/doanh thu | E50: =IFERROR(E49/E$9,0) -> 0 | F50: =IFERROR(F49/F$9,0) -> 0 | G50: =IFERROR(G49/G$9,0) -> 0 | H50: =IFERROR(H49/H$9,0) -> 0 | I50: =IFERROR(I49/I$9,0) -> 0 | J50: =IFERROR(J49/J$9,0) -> 0 | K50: =IFERROR(K49/K$9,0) -> 0 | L50: =IFERROR(L49/L$9,0) -> 0 | ... R50: =IFERROR(R49/R$9,0) -> 0
B51: 17 | C51: Khấu hao tài sản | E51: =E31+E37+E41 -> 0 | F51: =F31+F37+F41 -> 0 | G51: =G31+G37+G41 -> 0 | H51: =H31+H37+H41 -> 0 | I51: =I31+I37+I41 -> 0 | J51: =J31+J37+J41 -> 0 | K51: =K31+K37+K41 -> 0 | L51: =L31+L37+L41 -> 0 | ... Q51: =Q31+Q37+Q41 -> 0 | R51: =SUM(F51:Q51) -> 0
B52: 18 | C52: LỢI NHUẬN KHÔNG BAO GỒM KHẤU HAO, LÃI VAY | E52: =E49+E51 -> 0 | F52: =F49+F51 -> 0 | G52: =G49+G51 -> 0 | H52: =H49+H51 -> 0 | I52: =I49+I51 -> 0 | J52: =J49+J51 -> 0 | K52: =K49+K51 -> 0 | L52: =L49+L51 -> 0 | ... Q52: =Q49+Q51 -> 0 | R52: =SUM(F52:Q52) -> 0
B53: 18.1 | C53: % LN không gồm khấu hao/doanh thu | E53: =IFERROR(E52/E$9,0) -> 0 | F53: =IFERROR(F52/F$9,0) -> 0 | G53: =IFERROR(G52/G$9,0) -> 0 | H53: =IFERROR(H52/H$9,0) -> 0 | I53: =IFERROR(I52/I$9,0) -> 0 | J53: =IFERROR(J52/J$9,0) -> 0 | K53: =IFERROR(K52/K$9,0) -> 0 | L53: =IFERROR(L52/L$9,0) -> 0 | ... R53: =IFERROR(R52/R$9,0) -> 0

Sheet Cong suat
B3: CÔNG SUẤT
B4: I - CÔNG SUẤT CHUYỀN LỰA CHAI - CHAI XÁ TRÒN
B5: STT | C5: Công đoạn sản xuất | D5: Cấp liệu | E5: Lồng tách tạp chất | F5: Lựa phân loại chai | G5: Tách nhãn | H5: Lựa phân loại chai sau tách nhãn | I5: Ép kiện | J5: Xử lý phó sản, nắp, cổ chai | K5: Công suất thành phẩm cả chuyền
B6: 1 | C6: Năng suất THIẾT KẾ (Kg NVL đầu vào / giờ) | D6: 1100 | F6: =D6 -> 1100 | G6: 800-1000 | H6: 1000 | I6: 1000 | K6: 1200
B7: 2 | C7: Năng suất ĐỊNH MỨC (Kg NVL đầu vào / giờ) | D7: 1100 | F7: =D7 -> 1100 | G7: 800 | H7: 1000 | I7: 1000 | K7: =E15 -> 990
B8: 3 | C8: Định mức nhân công (Số NV / Ca8) | D8: 2 | F8: 4 | G8: 1 | H8: 4 | I8: 1 | K8: =SUM(D8:J8) -> 12
C9: Diễn giải | D9: 1 NV kéo bao 1 NV đổ bao | E9: Xếp phía sau trước máy ép kiện | F9: 2 NV phân loại chai tạp, bì tạp 1 NV phân loại chai B6, B2.2 1 NV phân loại chai viền nhôm, các tạp còn lại | G9: 1 NV kỹ thuật vận hành chung (vận hành chung cho 2 chuyền) | H9: 1 NV phân loại chai B4, B5 1 NV phân loại chai B6, B2.2 và chai sót nhãn 1 NV thu gom bao thành phẩm 1 NV thay bao rác | I9: 1 NV ép kiện thành phẩm, phế liệu, phó sản, lái xe nâng
B11: STT | C11: Chỉ tiêu định mức | D11: ĐVT | E11: ĐM 1 giờ | F11: ĐM 1 Ca8 | G11: ĐM 1 Ca12 | H11: ĐM 2 Ca8 | I11: ĐM 2 Ca12
B12: 1 | C12: Tổng nhân sự: | D12: Người | E12: =K8 -> 12 | F12: =$E12 -> 12 | G12: =$F12*1.5 -> 18 | H12: =$F12*2 -> 24 | I12: =$G12*2 -> 36
B13: 2 | C13: Định mức NVL đầu vào: | D13: kg/giờ | E13: =D7 -> 1100 | F13: =$E13*8 -> 8800 | G13: =$F13*1.5 -> 13200 | H13: =$F13*2 -> 17600 | I13: =$G13*2 -> 26400
B14: 3 | C14: Hao hụt: | D14: ='2.Hao hut & % chai '!R8 -> 0.1 | E14: =E13*$D$14 -> 110 | F14: =$E14*8 -> 880 | G14: =$E14*12 -> 1320 | H14: =$F14*2 -> 1760 | I14: =$G14*2 -> 2640
B15: 4 | C15: Định mức thành phẩm: | D15: kg/giờ | E15: =E13-E14 -> 990 | F15: =$E15*8 -> 7920 | G15: =$F15*1.5 -> 11880 | H15: =$F15*2 -> 15840 | I15: =$G15*2 -> 23760
B16: 5 | C16: Định mức thành phẩm/người: | D16: kg/giờ/người | E16: =E15/K8 -> 82.5 | F16: =$E16*8 -> 660 | G16: =$F16*1.5 -> 990 | H16: =$F16*2 -> 1320 | I16: =$G16*2 -> 1980
B18: II - CÔNG SUẤT CHUYỀN LỰA CHAI - CHAI ÉP KIỆN
B19: STT | C19: Công đoạn sản xuất | D19: Cấp liệu | E19: Phá kiện (thủ công bằng tay) | F19: Lựa phân loại chai | G19: Tách nhãn | H19: Lựa phân loại chai sau tách nhãn | I19: Ép kiện | J19: Xử lý phó sản, nắp, cổ chai | K19: Công suất thành phẩm cả chuyền
B20: 1 | C20: Năng suất THIẾT KẾ (Kg NVL đầu vào / giờ) | D20: 1000 | E20: 1000 | F20: 1000 | G20: 1500 | H20: 1000 | I20: 1000 | K20: =D20 -> 1000
B21: 2 | C21: Năng suất ĐỊNH MỨC (Kg NVL đầu vào / giờ) | D21: 1000 | E21: 1000 | F21: 1000 | G21: 800 | H21: 1000 | I21: 1000 | K21: =E29 -> 870
B22: 3 | C22: Định mức nhân công (Số NV / Ca8) | D22: 1 | E22: 2 | F22: 5 | G22: 0 | H22: 4 | I22: 1 | K22: =SUM(D22:J22) -> 13
C23: Diễn giải | D23: 1 NV xe nâng | E23: 2 NV cắt kiện | F23: 2 NV phân loại chai tạp, bì tạp 2 NV phân loại chai B6, B2.2 1 NV phân loại chai viền nhôm, các tạp còn lại | G23: Máy tách nhãn | H23: 1 NV phân loại chai B4, B5 1 NV phân loại chai B6, B2.2 và chai sót nhãn 1 NV thu gom bao thành phẩm 1 NV thay bao rác | I23: 1 NV ép kiện thành phẩm, phế liệu, phó sản
B25: STT | C25: Chỉ tiêu định mức | D25: ĐVT | E25: ĐM 1 giờ | F25: ĐM 1 Ca8 | G25: ĐM 1 Ca12 | H25: ĐM 2 Ca8 | I25: ĐM 2 Ca12
B26: 1 | C26: Tổng nhân sự: | D26: Người | E26: =K22 -> 13 | F26: =$E26 -> 13 | G26: =$F26*1.5 -> 19.5 | H26: =$F26*2 -> 26 | I26: =$G26*2 -> 39
B27: 2 | C27: Định mức NVL đầu vào: | D27: kg/giờ | E27: =D21 -> 1000 | F27: =$E27*8 -> 8000 | G27: =$F27*1.5 -> 12000 | H27: =$F27*2 -> 16000 | I27: =$G27*2 -> 24000
B28: 3 | C28: Hao hụt: | D28: ='2.Hao hut & % chai '!R14 -> 0.13 | E28: =E27*$D$28 -> 130 | F28: =$E28*8 -> 1040 | G28: =$F28*1.5 -> 1560 | H28: =$F28*2 -> 2080 | I28: =$G28*2 -> 3120
B29: 4 | C29: Định mức thành phẩm: | D29: kg/giờ | E29: =E27-E28 -> 870 | F29: =$E29*8 -> 6960 | G29: =$F29*1.5 -> 10440 | H29: =$F29*2 -> 13920 | I29: =$G29*2 -> 20880
B30: 5 | C30: Định mức thành phẩm/người: | D30: kg/giờ/người | E30: =E29/K22 -> 66.923077 | F30: =$E30*8 -> 535.38462 | G30: =$F30*1.5 -> 803.07692 | H30: =$F30*2 -> 1070.7692 | I30: =$G30*2 -> 1606.1538
B32: III - CÔNG SUẤT CHUYỀN LỰA CHAI - CHAI TUYỂN XÔ
B33: STT | C33: Công đoạn sản xuất | D33: Cấp liệu | E33: Lồng tách tạp chất | F33: Lựa phân loại chai | G33: Tách nhãn | H33: Lựa phân loại chai sau tách nhãn | I33: Ép kiện | J33: Công suất thành phẩm cả chuyền
B34: 1 | C34: Năng suất THIẾT KẾ (Kg NVL đầu vào / giờ) | E34: 1500 | F34: 1500 | G34: 800-1000 | H34: 1000 | I34: 1400 | J34: 1300
B35: 2 | C35: Năng suất ĐỊNH MỨC (Kg NVL đầu vào / giờ) | E35: 1300 | F35: 1300 | G35: 900 | H35: 900 | I35: 1300 | J35: 1222
B36: 3 | C36: Định mức nhân công (Số NV / Ca8) | D36: 1 | E36: 1 | F36: 4 | H36: 4 | I36: 1 | J36: =SUM(D36:I36) -> 11
C37: Diễn giải | D37: 1 NV cấp liệu | E37: 1 NV thay bao, đóng gói chai B6 | F37: 2 NV phân loại chai tạp chất, 2 NV phân loại chai B6 | H37: 2 NV phân loại chai B4, B5 2 NV phân loại chai B2.2 và chai còn lại | I37: 1 NV ép kiện thành phẩm, phế liệu, phó sản
B39: STT | C39: Chỉ tiêu định mức | D39: ĐVT | E39: ĐM 1 giờ | F39: ĐM 1 Ca8 | G39: ĐM 1 Ca12 | H39: ĐM 2 Ca8 | I39: ĐM 2 Ca12
B40: 1 | C40: Tổng nhân sự: | D40: Người | E40: =J36 -> 11 | F40: =$E40 -> 11 | G40: =$F40*1.5 -> 16.5 | H40: =$F40*2 -> 22 | I40: =$G40*2 -> 33
B41: 2 | C41: Định mức NVL đầu vào: | D41: kg/giờ | E41: =$E$35 -> 1300 | F41: =$E41*8 -> 10400 | G41: =$F41*1.5 -> 15600 | H41: =$F41*2 -> 20800 | I41: =$G41*2 -> 31200
B42: 3 | C42: Hao hụt: | D42: ='2.Hao hut & % chai '!R20 -> 0.06 | E42: =E41*$D$42 -> 78 | F42: =$E42*8 -> 624 | G42: =$E42*12 -> 936 | H42: =$F42*2 -> 1248 | I42: =$G42*2 -> 1872
B43: 4 | C43: Định mức thành phẩm: | D43: kg/giờ | E43: =E41-E42 -> 1222 | F43: =$E43*8 -> 9776 | G43: =$F43*1.5 -> 14664 | H43: =$F43*2 -> 19552 | I43: =$G43*2 -> 29328
B44: 5 | C44: Định mức thành phẩm/người: | D44: kg/giờ/người | E44: =E43/J36 -> 111.09091 | F44: =$E44*8 -> 888.72727 | G44: =$F44*1.5 -> 1333.0909 | H44: =$F44*2 -> 1777.4545 | I44: =$G44*2 -> 2666.1818
B46: VI - CÔNG SUẤT MÁY VÀ NĂNG SUẤT LAO ĐỘNG MỤC TIÊU
B47: 1 | C47: CHUYỀN LỰA CHAI - CHAI XÁ TRÒN | E47: Định mức | F47: T1 | G47: T2 | H47: T3 | I47: T4 | J47: T5 | K47: T6 | L47: T7 | M47: T8 | N47: T9 | O47: T10 | P47: T11 | Q47: T12 | R47: Kế hoạch 2026
B48: a | C48: Số nhân sự/ chuyền/ ca | D48: Người | E48: =E12 -> 12 | F48: =E48 -> 12 | G48: =F48 -> 12 | H48: =G48 -> 12 | I48: =H48 -> 12 | J48: =E48 -> 12 | K48: =J48 -> 12 | L48: =K48 -> 12 | M48: =L48 -> 12 | N48: =M48 -> 12 | O48: =N48 -> 12 | P48: =O48 -> 12 | Q48: =P48 -> 12
B49: b | C49: Công suất/ chuyền | D49: kg/giờ | E49: =E15 -> 990 | F49: =E49 -> 990 | G49: =F49 -> 990 | H49: =G49 -> 990 | I49: =H49 -> 990 | J49: =E49 -> 990 | K49: =J49 -> 990 | L49: =K49 -> 990 | M49: =L49 -> 990 | N49: =M49 -> 990 | O49: =N49 -> 990 | P49: =O49 -> 990 | Q49: =P49 -> 990
B50: c | C50: Năng suất lao động | D50: kg/giờ/người | E50: =E49/E48 -> 82.5 | F50: =E50 -> 82.5 | G50: =F50 -> 82.5 | H50: =G50 -> 82.5 | I50: =H50 -> 82.5 | J50: =J49/J48 -> 82.5 | K50: =K49/K48 -> 82.5 | L50: =L49/L48 -> 82.5 | M50: =M49/M48 -> 82.5 | N50: =N49/N48 -> 82.5 | O50: =O49/O48 -> 82.5 | P50: =P49/P48 -> 82.5 | Q50: =Q49/Q48 -> 82.5
B51: 2 | C51: CHUYỀN LỰA CHAI - CHAI ÉP KIỆN
B52: a | C52: Số nhân sự/ chuyền/ ca | D52: Người | E52: =E26 -> 13 | F52: =E52 -> 13 | G52: =F52 -> 13 | H52: =G52 -> 13 | I52: =H52 -> 13 | J52: =E52 -> 13 | K52: =J52 -> 13 | L52: =K52 -> 13 | M52: =L52 -> 13 | N52: =M52 -> 13 | O52: =N52 -> 13 | P52: =O52 -> 13 | Q52: =P52 -> 13
B53: b | C53: Công suất/chuyền (kg thành phẩm/ giờ) | D53: kg/giờ | E53: =E29 -> 870 | F53: =E53 -> 870 | G53: =F53 -> 870 | H53: =G53 -> 870 | I53: =H53 -> 870 | J53: =E53 -> 870 | K53: =J53 -> 870 | L53: =K53 -> 870 | M53: =L53 -> 870 | N53: =M53 -> 870 | O53: =N53 -> 870 | P53: =O53 -> 870 | Q53: =P53 -> 870
B54: c | C54: Năng suất lao động (kg thành phẩm/ người/ giờ): | D54: kg/giờ/người | E54: =E53/E52 -> 66.923077 | F54: =E54 -> 66.923077 | G54: =F54 -> 66.923077 | H54: =G54 -> 66.923077 | I54: =H54 -> 66.923077 | J54: =J53/J52 -> 66.923077 | K54: =K53/K52 -> 66.923077 | L54: =L53/L52 -> 66.923077 | M54: =M53/M52 -> 66.923077 | N54: =N53/N52 -> 66.923077 | O54: =O53/O52 -> 66.923077 | P54: =P53/P52 -> 66.923077 | Q54: =Q53/Q52 -> 66.923077
B55: 3 | C55: CHUYỀN LỰA CHAI - CHAI TUYỂN XÔ (có thể xử lý chạy trên chuyền chai tròn hoặc ép kiện)
B56: a | C56: Số nhân sự/ chuyền/ ca | D56: Người | E56: =E40 -> 11 | F56: =E56 -> 11 | G56: =F56 -> 11 | H56: =G56 -> 11 | I56: =H56 -> 11 | J56: =E56 -> 11 | K56: =J56 -> 11 | L56: =K56 -> 11 | M56: =L56 -> 11 | N56: =M56 -> 11 | O56: =N56 -> 11 | P56: =O56 -> 11 | Q56: =P56 -> 11
B57: b | C57: Công suất/chuyền (kg thành phẩm/ giờ) | D57: kg/giờ | E57: =E43 -> 1222 | F57: =E57 -> 1222 | G57: =F57 -> 1222 | H57: =G57 -> 1222 | I57: =H57 -> 1222 | J57: =E57 -> 1222 | K57: =J57 -> 1222 | L57: =K57 -> 1222 | M57: =L57 -> 1222 | N57: =M57 -> 1222 | O57: =N57 -> 1222 | P57: =O57 -> 1222 | Q57: =P57 -> 1222
B58: c | C58: Năng suất lao động (kg thành phẩm/ người/ giờ): | D58: kg/giờ/người | E58: =E57/E56 -> 111.09091 | F58: =E58 -> 111.09091 | G58: =F58 -> 111.09091 | H58: =G58 -> 111.09091 | I58: =H58 -> 111.09091 | J58: =J57/J56 -> 111.09091 | K58: =K57/K56 -> 111.09091 | L58: =L57/L56 -> 111.09091 | M58: =M57/M56 -> 111.09091 | N58: =N57/N56 -> 111.09091 | O58: =O57/O56 -> 111.09091 | P58: =P57/P56 -> 111.09091 | Q58: =Q57/Q56 -> 111.09091
B60: VII - TỔNG CÔNG SUẤT MÁY PET và NĂNG SUẤT LAO ĐỘNG
B61: i | C61: Tổng công suất PET/giờ | D61: kg/giờ | E61: Định mức | F61: T1 | G61: T2 | H61: T3 | I61: T4 | J61: T5 | K61: T6 | L61: T7 | M61: T8 | N61: T9 | O61: T10 | P61: T11 | Q61: T12 | R61: Kế hoạch 2026
B62: 1 | C62: Công suất máy - Tính trên NVL đầu vào | D62: Tấn/giờ | E62: =$E$13+$E$27*80%+$E$41*20% -> 2160 | F62: =$E$13+$E$27*80%+$E$41*20% -> 2160 | G62: =$E$13+$E$27*80%+$E$41*20% -> 2160 | H62: =$E$13+$E$27*80%+$E$41*20% -> 2160 | I62: =$E$13+$E$27*80%+$E$41*20% -> 2160 | J62: =$E$13+$E$27*80%+$E$41*20% -> 2160 | K62: =$E$13+$E$27*80%+$E$41*20% -> 2160 | L62: =$E$13+$E$27*80%+$E$41*20% -> 2160 | ... Q62: =$E$13+$E$27*80%+$E$41*20% -> 2160
B63: 2 | C63: Công suất máy - Tính trên Thành phẩm SX | D63: Tấn/giờ | E63: =$E$49+$E$53*80%+$E$57*20% -> 1930.4 | F63: =$E$49+$E$53*80%+$E$57*20% -> 1930.4 | G63: =$E$49+$E$53*80%+$E$57*20% -> 1930.4 | H63: =$E$49+$E$53*80%+$E$57*20% -> 1930.4 | I63: =$E$49+$E$53*80%+$E$57*20% -> 1930.4 | J63: =$E$49+$E$53*80%+$E$57*20% -> 1930.4 | K63: =$E$49+$E$53*80%+$E$57*20% -> 1930.4 | L63: =$E$49+$E$53*80%+$E$57*20% -> 1930.4 | ... Q63: =$E$49+$E$53*80%+$E$57*20% -> 1930.4
B64: ii | C64: Tổng công suất PET/tháng (8hx3cax30 ngày) | D64: kg/tháng | E64: Định mức | J64: T5 | K64: T6 | L64: T7 | M64: T8 | N64: T9 | O64: T10 | P64: T11 | Q64: T12
B65: 1 | C65: Công suất máy - Tính trên NVL đầu vào | D65: Tấn/tháng | E65: =E62*8*3*30 -> 1555200 | F65: =F62*8*3*30 -> 1555200 | G65: =G62*8*3*30 -> 1555200 | H65: =H62*8*3*30 -> 1555200 | I65: =I62*8*3*30 -> 1555200 | J65: =J62*8*3*30 -> 1555200 | K65: =K62*8*3*30 -> 1555200 | L65: =L62*8*3*30 -> 1555200 | ... Q65: =Q62*8*3*30 -> 1555200
B66: 2 | C66: Công suất máy - Tính trên Thành phẩm SX | D66: Tấn/tháng | E66: =E63*8*3*30 -> 1389888 | F66: =F63*8*3*30 -> 1389888 | G66: =G63*8*3*30 -> 1389888 | H66: =H63*8*3*30 -> 1389888 | I66: =I63*8*3*30 -> 1389888 | J66: =J63*8*3*30 -> 1389888 | K66: =K63*8*3*30 -> 1389888 | L66: =L63*8*3*30 -> 1389888 | ... Q66: =Q63*8*3*30 -> 1389888
B67: iii | C67: Năng suất lao động (CNTT) | E67: Định mức | F67: T1 | G67: T2 | H67: T3 | I67: T4 | J67: T5 | K67: T6 | L67: T7 | M67: T8 | N67: T9 | O67: T10 | P67: T11 | Q67: T12
B68: 1 | C68: Năng suất lao động - Tấn/người/ngày | D68: Tấn/người/ngày | E68: =E69/30 -> 627.77236 | F68: =F69/30 -> 627.77236 | G68: =G69/30 -> 627.77236 | H68: =H69/30 -> 627.77236 | I68: =I69/30 -> 627.77236 | J68: =J69/30 -> 627.77236 | K68: =K69/30 -> 627.77236 | L68: =L69/30 -> 627.77236 | ... Q68: =Q69/30 -> 627.77236
B69: 2 | C69: Năng suất lao động - Tấn/người/tháng | D69: Tấn/người/tháng | E69: =E66/(E48+E52*80%+E56*20%)/3 -> 18833.171 | F69: =F66/(F48+F52*80%+F56*20%)/3 -> 18833.171 | G69: =G66/(G48+G52*80%+G56*20%)/3 -> 18833.171 | H69: =H66/(H48+H52*80%+H56*20%)/3 -> 18833.171 | I69: =I66/(I48+I52*80%+I56*20%)/3 -> 18833.171 | J69: =J66/(J48+J52*80%+J56*20%)/3 -> 18833.171 | K69: =K66/(K48+K52*80%+K56*20%)/3 -> 18833.171 | L69: =L66/(L48+L52*80%+L56*20%)/3 -> 18833.171 | ... Q69: =Q66/(Q48+Q52*80%+Q56*20%)/3 -> 18833.171
B71: VIII - CÔNG SUẤT CHUYỀN BĂM VẢY PET
B72: STT | C72: Công đoạn sản xuất | D72: Cấp liệu | E72: XXX | F72: XXX | G72: XXX | H72: XXX | I72: XXX | J72: XXX | K72: Công suất thành phẩm cả chuyền
B73: 1 | C73: Năng suất THIẾT KẾ (Kg NVL đầu vào / giờ)
B74: 2 | C74: Năng suất ĐỊNH MỨC (Kg NVL đầu vào / giờ)
B75: 3 | C75: Định mức nhân công (Số NV / Ca8)
C76: Diễn giải
B78: STT | C78: Chỉ tiêu định mức | D78: ĐVT | E78: ĐM 1 giờ | F78: ĐM 1 Ca8 | G78: ĐM 1 Ca12 | H78: ĐM 2 Ca8 | I78: ĐM 2 Ca12
B79: 1 | C79: Tổng nhân sự: | D79: Người | E79: =K75 -> 0 | F79: =$E79 -> 0 | G79: =$F79*1.5 -> 0 | H79: =$F79*2 -> 0 | I79: =$G79*2 -> 0
B80: 2 | C80: Định mức NVL đầu vào: | D80: kg/giờ | E80: =D74 -> 0 | F80: =$E80*8 -> 0 | G80: =$F80*1.5 -> 0 | H80: =$F80*2 -> 0 | I80: =$G80*2 -> 0
B81: 3 | C81: Hao hụt: | D81: ='2.Hao hut & % chai '!R27 -> 0 | E81: =E80*$D$28 -> 0 | F81: =$E81*8 -> 0 | G81: =$F81*1.5 -> 0 | H81: =$F81*2 -> 0 | I81: =$G81*2 -> 0
B82: 4 | C82: Định mức thành phẩm: | D82: kg/giờ | E82: =E80-E81 -> 0 | F82: =$E82*8 -> 0 | G82: =$F82*1.5 -> 0 | H82: =$F82*2 -> 0 | I82: =$G82*2 -> 0
B83: 5 | C83: Định mức thành phẩm/người: | D83: kg/giờ/người | E83: =IFERROR(E82/K75,0) -> 0 | F83: =$E83*8 -> 0 | G83: =$F83*1.5 -> 0 | H83: =$F83*2 -> 0 | I83: =$G83*2 -> 0

Sheet Dinh muc
B3: ĐỊNH MỨC CHI PHÍ
B4: I - ĐỊNH MỨC TIÊU HAO VẬT TƯ - PHÂN LOẠI CHAI PET
B5: STT | C5: Mục phí | D5: ĐVT | E5: Định mức | F5: Đơn giá | G5: Chi phí/1kg thành phẩm | H5: Diễn giải
C6: Công suất lựa chai | E6: =('Cong suat'!E29+'Cong suat'!E15)/2 -> 930
B7: 1 | C7: Chi phí nhân công trực tiếp (giờ công lao động) | E7: =E8+E9 -> 13 | F7: =(E8*F8+E9*F9)/E7 -> 50500 | G7: =G8+G9 -> 705.91398
B8: a | C8: LĐ định biên | D8: Giờ công/ca 8 | E8: ='Cong suat'!$K$22*75% -> 9.75 | F8: =(350000+50000+42000)/8 -> 55250 | G8: =E8*F8/E6 -> 579.23387 | H8: 75% định biên, trong tuần tăng ca 4.5h
B9: b | C9: LĐ thời vụ | D9: Giờ công/ca 8 | E9: ='Cong suat'!$K$22*25% -> 3.25 | F9: =(250000+40000)/8 -> 36250 | G9: =E9*F9/E6 -> 126.68011 | H9: 25% thời vụ, trong tuần tăng ca 4.5h
B10: c | C10: Tiền ăn giữa Ca | D10: Đồng/người/ngày công | F10: =25000*1.05 -> 26250
B11: 2 | C11: Điện sản xuất | D11: Kw/1chuyền/1giờ hoạt động | E11: =18071/3/26/7 -> 33.09707 | F11: 2400 | G11: =E11*F11/E6 -> 85.411793 | H11: (1 giờ sản xuất 875 kg thành phẩm)
B12: 3 | C12: Dao tách nhãn chai PET | D12: Bộ | E12: =1/2000000*(('Cong suat'!$E$13+'Cong suat'!$E$27)/2) -> 0.000525 | F12: =150000000+10000000 -> 160000000 | G12: =E12*F12/$E$6 -> 90.322581 | H12: Công suất thiết kế: 2000 tấn chai PET-B0
B13: 4 | C13: Dây đai | E13: =0.3 -> 0.3 | F13: 51000 | G13: =E13*F13/230 -> 66.521739 | H13: (1 kg = 500m)
B14: 5 | C14: Bao jumbo
B15: 6 | C15: Hóa chất
B16: 7 | C16: Chi phí xử lý nhãn chai PET | D16: Kg | E16: 1 | F16: 300 | G16: =(('Cong suat'!$E$28+'Cong suat'!$E$14)*50%)*F16/$E$6 -> 38.709677
B17: 8 | C17: Dầu xe nâng | D17: Lít/giờ hoạt động | E17: 0.8 | F17: 18000 | G17: =E17*F17/E6*3 -> 46.451613 | H17: (1 giờ vận chuyển 1.100kg x 3 chiếc)
B18: 9 | C18: Chi phí vận chuyển | D18: Chuyến/7 tấn | E18: 1 | F18: 1500000 | G18: =F18/7000 -> 214.28571 | H18: (1 chuyến1,5 triệu đồng, 7 tấn/chuyến)
B20: II - ĐỊNH MỨC TIÊU HAO VẬT TƯ - BĂM VẢY PET
B21: STT | C21: Mục phí | D21: ĐVT | E21: ĐM 1 giờ | F21: Đơn giá | G21: Chi phí/1kg thành phẩm | H21: Diễn giải
C22: Công suất băm PET | E22: ='Cong suat'!$E$82 -> 0
B23: 1 | C23: Chi phí nhân công trực tiếp
B24: a | C24: LĐ định biên | D24: Giờ công/ca 8
B25: b | C25: LĐ thời vụ | D25: Giờ công/ca 8
B26: c | C26: Tiền ăn giữa Ca | D26: Đồng/người
B27: 2 | C27: Điện sản xuất | D27: Kw/1chuyền/1giờ hoạt động | E27: 65 | F27: 2100 | G27: =E27*F27/$G$7 -> 193.36634
B28: 3 | C28: Dao băm vảy PET | E28: =1/150000*'Cong suat'!$E$80 -> 0 | F28: 51000000 | G28: =E28*F28/$E$22 -> #DIV/0! | H28: Công suất thiết kế: 150 tấn
B29: 4 | C29: Dây đai
B30: 5 | C30: Bao jumbo | E30: =E22/400 -> 0 | F30: 71000 | G30: =E30*F30/$E$22 -> #DIV/0!
B31: 6 | C31: Hóa chất
B32: 7 | C32: Chi phí xử lý nước thải, môi trường | E32: 3 | F32: 11000 | G32: =E32*F32/$E$22 -> #DIV/0! | H32: Xử lý: nhãn, bùn, nước thải, hóa chất xử lý hồ XLNT
B33: 8 | C33: Dầu xe nâng | E33: =30/10 -> 3 | F33: 18000 | G33: =E33*F33/1100 -> 49.090909
B34: 9 | C34: Chi phí vận chuyển | D34: Chuyến | E34: 10000 | F34: 3200000 | G34: =F34/E34 -> 320
B36: III - ĐỊNH MỨC TIÊU HAO VẬT TƯ - BĂM VẢY HD
B37: STT | C37: Mục phí | D37: ĐVT | E37: Định mức | F37: Đơn giá | G37: Chi phí/1kg thành phẩm | H37: Diễn giải
C38: Công suất băm HD
B39: 1 | C39: Chi phí nhân công trực tiếp
B40: a | C40: LĐ định biên
B41: b | C41: LĐ thời vụ
B42: c | C42: Tiền ăn giữa Ca
B43: 2 | C43: Điện sản xuất
B44: 3 | C44: Dao băm vảy HD
B45: 4 | C45: Dây đai
B46: 5 | C46: Bao jumbo
B47: 6 | C47: Hóa chất
B48: 7 | C48: Chi phí xử lý nước thải, môi trường
B49: 8 | C49: Dầu xe nâng
B50: 9 | C50: Chi phí vận chuyển | D50: Chuyến | E50: 10000 | F50: 3200000 | G50: =F50/E50 -> 320
H54: Ngày …
C55: Duyệt | D55: Xem xét | E55: Xem xét | G55: Xem xét | H55: Người lập
C56: GĐĐH DTR | D56: GĐTC DTR | E56: GĐ các trạm | G56: Trưởng Trạm | H56: Kế toán trưởng

Sheet Dinh bien_HCNS
B1: #VALUE!
B3: ĐINH BIÊN NHÂN SỰ - PET | T3: ĐVT: người
B4: STT | C4: Phòng ban | D4: Tài khoản | E4: KQKD 2023 | F4: KQKD 2024 | G4: KQKD 2025 | H4: T1 | I4: T2 | J4: T3 | K4: T4 | L4: T5 | M4: T6 | N4: T7 | O4: T8 | P4: T9 | Q4: T10 | R4: T11 | S4: T12 | T4: Kế hoạch 2026
B5: 1 | C5: Ban giám đốc | D5: 642 | E5: =SUM(E6:E8) -> 1 | F5: =SUM(F6:F8) -> 2 | G5: =SUM(G6:G8) -> 2 | H5: =SUM(H6:H8) -> 3 | I5: =SUM(I6:I8) -> 3 | J5: =SUM(J6:J8) -> 3 | K5: =SUM(K6:K8) -> 3 | L5: =SUM(L6:L8) -> 3 | ... T5: =SUM(T6:T8) -> 3
B6: 1.1 | C6: Giám đốc Trạm | F6: 1 | G6: 1 | H6: 1 | I6: 1 | J6: 1 | K6: 1 | L6: 1 | M6: 1 | N6: 1 | O6: 1 | P6: 1 | Q6: 1 | R6: 1 | S6: 1 | T6: 1
B7: 1.2 | C7: Trưởng trạm thu mua | E7: 1 | F7: 1 | G7: 1 | H7: 1 | I7: 1 | J7: 1 | K7: 1 | L7: 1 | M7: 1 | N7: 1 | O7: 1 | P7: 1 | Q7: 1 | R7: 1 | S7: 1 | T7: 1
B8: 1.3 | C8: Giám đốc đại diện pháp luật | H8: 1 | I8: 1 | J8: 1 | K8: 1 | L8: 1 | M8: 1 | N8: 1 | O8: 1 | P8: 1 | Q8: 1 | R8: 1 | S8: 1 | T8: 1
B9: 2 | C9: Phòng Hành chánh nhân sự | D9: 642 | E9: =SUM(E10:E16) -> 0 | F9: =SUM(F10:F16) -> 0 | G9: =SUM(G10:G16) -> 2 | H9: =SUM(H10:H16) -> 2 | I9: =SUM(I10:I16) -> 2 | J9: =SUM(J10:J16) -> 2 | K9: =SUM(K10:K16) -> 2 | L9: =SUM(L10:L16) -> 2 | ... T9: =SUM(T10:T16) -> 2
B10: 2.1 | C10: Trưởng phòng nhân sự
B11: 2.1 | C11: Nhân viên hành chính | G11: 1 | H11: 1 | I11: 1 | J11: 1 | K11: 1 | L11: 1 | M11: 1 | N11: 1 | O11: 1 | P11: 1 | Q11: 1 | R11: 1 | S11: 1 | T11: 1
B12: 2.3 | C12: Nhân viên nhân sự
B13: 2.4 | C13: Tuyển dụng
B14: 2.2 | C14: Nhân viên tạp vụ (Lao động thuê ngoài) | G14: 1 | H14: 1 | I14: 1 | J14: 1 | K14: 1 | L14: 1 | M14: 1 | N14: 1 | O14: 1 | P14: 1 | Q14: 1 | R14: 1 | S14: 1 | T14: 1
B15: 2.6 | C15: Bảo vệ
B16: 2.7 | C16: Nhân viên chăm sóc cây xanh
B17: 3 | C17: Phòng Kế toán | D17: 642 | E17: =SUM(E18:E21) -> 3 | F17: =SUM(F18:F21) -> 3 | G17: =SUM(G18:G21) -> 3 | H17: =SUM(H18:H21) -> 3 | I17: =SUM(I18:I21) -> 3 | J17: =SUM(J18:J21) -> 3 | K17: =SUM(K18:K21) -> 3 | L17: =SUM(L18:L21) -> 3 | ... T17: =SUM(T18:T21) -> 3
B18: 3.1 | C18: Kế toán trưởng | E18: 1 | F18: 1 | G18: 1 | H18: 1 | I18: 1 | J18: 1 | K18: 1 | L18: 1 | M18: 1 | N18: 1 | O18: 1 | P18: 1 | Q18: 1 | R18: 1 | S18: 1 | T18: 1
B19: 3.2 | C19: Kế toán tổng hợp | E19: 1 | F19: 1 | G19: 1 | H19: 1 | I19: 1 | J19: 1 | K19: 1 | L19: 1 | M19: 1 | N19: 1 | O19: 1 | P19: 1 | Q19: 1 | R19: 1 | S19: 1 | T19: 1
B20: 3.3 | C20: Kế toán kho | E20: 1 | F20: 1 | G20: 1 | H20: 1 | I20: 1 | J20: 1 | K20: 1 | L20: 1 | M20: 1 | N20: 1 | O20: 1 | P20: 1 | Q20: 1 | R20: 1 | S20: 1 | T20: 1
B21: 3.4 | C21: Kế toán viên
B22: 4 | C22: Phòng Mua hàng | D22: 642 | E22: =E23 -> 0 | F22: =F23 -> 0 | G22: =G23 -> 0 | H22: =H23 -> 0 | I22: =I23 -> 0 | J22: =J23 -> 0 | K22: =K23 -> 0 | L22: =L23 -> 0 | ... T22: =T23 -> 0
B23: 4.1 | C23: Nhân viên mua hàng
B24: 5 | C24: Ban dự án XDCB | D24: 642 | E24: =E25 -> 0 | F24: =F25 -> 0 | G24: =G25 -> 0 | H24: =H25 -> 0 | I24: =I25 -> 0 | J24: =J25 -> 0 | K24: =K25 -> 0 | L24: =L25 -> 0 | ... S24: =S25 -> 0
B25: 5.1 | C25: Nhân viên
B26: 6 | C26: Phòng Quản Trị Hệ Thống | D26: 642 | E26: =E27 -> 0 | F26: =F27 -> 0 | G26: =G27 -> 0 | H26: =H27 -> 0 | I26: =I27 -> 0 | J26: =J27 -> 0 | K26: =K27 -> 0 | L26: =L27 -> 0 | ... S26: =S27 -> 0
B27: 6.1 | C27: Nhân viên quản trị hệ thống
B28: 7 | C28: Phòng 5S & an toàn | D28: 642 | E28: =SUM(E29:E30) -> 0 | F28: =SUM(F29:F30) -> 0 | G28: =SUM(G29:G30) -> 0 | H28: =SUM(H29:H30) -> 0 | I28: =SUM(I29:I30) -> 0 | J28: =SUM(J29:J30) -> 0 | K28: =SUM(K29:K30) -> 0 | L28: =SUM(L29:L30) -> 0 | ... T28: =SUM(T29:T30) -> 0
B29: 7.1 | C29: Nhân viên 5S & an toàn
B30: 7.2 | C30: Lao động thuê ngoài
B31: 8 | C31: Phòng Cung ứng | D31: 642 | E31: =E32 -> 0 | F31: =F32 -> 0 | G31: =G32 -> 0 | H31: =H32 -> 0 | I31: =I32 -> 0 | J31: =J32 -> 0 | K31: =K32 -> 0 | L31: =L32 -> 0 | ... S31: =S32 -> 0
B32: 8.1 | C32: Nhân viên
B33: 9 | C33: Phòng mua XNK | D33: 642 | E33: =E34 -> 0 | F33: =F34 -> 0 | G33: =G34 -> 0 | H33: =H34 -> 0 | I33: =I34 -> 0 | J33: =J34 -> 0 | K33: =K34 -> 0 | L33: =L34 -> 0 | ... S33: =S34 -> 0
B34: 9.1 | C34: Nhân viên
B35: 10 | C35: Tư Vấn Dịch Vụ | D35: 642 | E35: =E36 -> 0 | F35: =F36 -> 0 | G35: =G36 -> 0 | H35: =H36 -> 0 | I35: =I36 -> 0 | J35: =J36 -> 0 | K35: =K36 -> 0 | L35: =L36 -> 0 | ... S35: =S36 -> 0
B36: 10.1 | C36: Nhân viên
B37: 11 | C37: Phòng Nghiên Cứu & Phát Triển | D37: 627 | E37: =E38 -> 0 | F37: =F38 -> 0 | G37: =G38 -> 0 | H37: =H38 -> 0 | I37: =I38 -> 0 | J37: =J38 -> 0 | K37: =K38 -> 0 | L37: =L38 -> 0 | ... S37: =S38 -> 0
B38: 11.1 | C38: Nhân viên
B39: 4 | C39: Phòng Kiểm soát chất lượng | D39: 627 | E39: =SUM(E40:E42) -> 1 | F39: =SUM(F40:F42) -> 1 | G39: =SUM(G40:G42) -> 2 | H39: =SUM(H40:H42) -> 3 | I39: =SUM(I40:I42) -> 3 | J39: =SUM(J40:J42) -> 3 | K39: =SUM(K40:K42) -> 3 | L39: =SUM(L40:L42) -> 3 | ... T39: =SUM(T40:T42) -> 3
B40: 4.1 | C40: Tổ trưởng Kiểm soát chất lượng | G40: 1 | H40: 1 | I40: 1 | J40: 1 | K40: 1 | L40: 1 | M40: 1 | N40: 1 | O40: 1 | P40: 1 | Q40: 1 | R40: 1 | S40: 1 | T40: 1
B41: 4.2 | C41: Kiểm soát NVL | E41: 1 | F41: 1 | G41: 1 | H41: 1 | I41: 1 | J41: 1 | K41: 1 | L41: 1 | M41: 1 | N41: 1 | O41: 1 | P41: 1 | Q41: 1 | R41: 1 | S41: 1 | T41: =IFERROR(AVERAGEA(H41:S41),0) -> 1
B42: 4.3 | C42: Kiểm soát thành phẩm ( Lao động thuê ngoài) | H42: 1 | I42: 1 | J42: 1 | K42: 1 | L42: 1 | M42: 1 | N42: 1 | O42: 1 | P42: 1 | Q42: 1 | R42: 1 | S42: 1 | T42: =IFERROR(AVERAGEA(H42:S42),0) -> 1
B43: 5 | C43: Phòng Kỹ thuật | D43: 627 | E43: =SUM(E44:E50) -> 0 | F43: =SUM(F44:F50) -> 0 | G43: =SUM(G44:G50) -> 3 | H43: =SUM(H44:H50) -> 3 | I43: =SUM(I44:I50) -> 3 | J43: =SUM(J44:J50) -> 3 | K43: =SUM(K44:K50) -> 3 | L43: =SUM(L44:L50) -> 3 | ... T43: =SUM(T44:T50) -> 3
B44: 13.1 | C44: Quản lý kỹ thuật | T44: =IFERROR(AVERAGEA(H44:S44),0) -> 0
B45: 13.2 | C45: Tổ trưởng vận hành máy | T45: =IFERROR(AVERAGEA(H45:S45),0) -> 0
B46: 13.3 | C46: Tổ trưởng kỹ thuật nước và môi trường | T46: =IFERROR(AVERAGEA(H46:S46),0) -> 0
B47: 5.1 | C47: Nhân viên vận hành máy | G47: 2 | H47: 1 | I47: 1 | J47: 1 | K47: 1 | L47: 1 | M47: 1 | N47: 1 | O47: 1 | P47: 1 | Q47: 1 | R47: 1 | S47: 1 | T47: =IFERROR(AVERAGEA(H47:S47),0) -> 1
B48: 5.2 | C48: Nhân viên bảo trì | G48: 1 | H48: 2 | I48: 2 | J48: 2 | K48: 2 | L48: 2 | M48: 2 | N48: 2 | O48: 2 | P48: 2 | Q48: 2 | R48: 2 | S48: 2 | T48: =IFERROR(AVERAGEA(H48:S48),0) -> 2
B49: 13.6 | C49: Nhân viên xử lý nước thải (24/24) | T49: =IFERROR(AVERAGEA(H49:S49),0) -> 0
B50: 13.7 | C50: Nhân viên thống kê kỹ thuật | T50: =IFERROR(AVERAGEA(H50:S50),0) -> 0
B51: 6 | C51: Phòng Sản xuất | E51: =E52+E57+E64 -> 51 | F51: =F52+F57+F64 -> 42 | G51: =G52+G57+G64 -> 40 | H51: =H52+H57+H64 -> 41 | I51: =I52+I57+I64 -> 41 | J51: =J52+J57+J64 -> 41 | K51: =K52+K57+K64 -> 41 | L51: =L52+L57+L64 -> 41 | ... T51: =T52+T57+T64 -> 39
B52: 6.1 | C52: Quản lý sản xuất | D52: 627 | E52: =SUM(E53:E56) -> 1 | F52: =SUM(F53:F56) -> 1 | G52: =SUM(G53:G56) -> 2 | H52: =SUM(H53:H56) -> 2 | I52: =SUM(I53:I56) -> 2 | J52: =SUM(J53:J56) -> 2 | K52: =SUM(K53:K56) -> 2 | L52: =SUM(L53:L56) -> 2 | ... T52: =SUM(T53:T56) -> 2
B53: 6.1.1 | C53: Trưởng phòng sản xuất | G53: 1 | H53: 1 | I53: 1 | J53: 1 | K53: 1 | L53: 1 | M53: 1 | N53: 1 | O53: 1 | P53: 1 | Q53: 1 | R53: 1 | S53: 1 | T53: =IFERROR(AVERAGEA(H53:S53),0) -> 1
B54: 14.1.2 | C54: Giám sát sản xuất | T54: =IFERROR(AVERAGEA(H54:S54),0) -> 0
B55: 6.1.2 | C55: Tổ trưởng sản xuất | E55: 1 | F55: 1 | G55: 1 | H55: 1 | I55: 1 | J55: 1 | K55: 1 | L55: 1 | M55: 1 | N55: 1 | O55: 1 | P55: 1 | Q55: 1 | R55: 1 | S55: 1 | T55: =IFERROR(AVERAGEA(H55:S55),0) -> 1
B56: 14.1.4 | C56: Nhân viên thống kê sản xuất | V56: Chi tiết phân bổ Công nhân trực tiếp SX
B57: 6.2 | C57: Công nhân trực tiếp sản xuất - Phân loại | D57: 622 | E57: =SUM(E58:E63) -> 50 | F57: =SUM(F58:F63) -> 41 | G57: =SUM(G58:G63) -> 38 | H57: =SUM(H58:H63) -> 39 | I57: =SUM(I58:I63) -> 39 | J57: =SUM(J58:J63) -> 39 | K57: =SUM(K58:K63) -> 39 | L57: =SUM(L58:L63) -> 39 | ... T57: =SUM(T58:T63) -> 37 | V57: Công nhân trực tiếp sản xuất - Phân loại
B58: 6.2.1 | C58: Nhân viên phân loại | E58: 37 | F58: 26 | G58: 12 | H58: =27-H59-H60-H62-H70-H61 -> 14 | I58: =27-I59-I60-I62-I70-I61 -> 14 | J58: =27-J59-J60-J62-J70-J61 -> 14 | K58: =27-K59-K60-K62-K70-K61 -> 14 | L58: =27-L59-L60-L62-L70-L61 -> 14 | M58: =27-M59-M60-M62-M70-M61 -> 14 | N58: =27-N59-N60-N62-N70-N61 -> 14 | O58: =27-O59-O60-O62-O70-O61 -> 14 | ... S58: =27-S59-S60-S62-S70-S61 -> 14 | T58: =25-T59-T60-T62-T70-T61 -> 12 | V58: SX chai PET - Chuyền phân loại
B59: 6.2.2 | C59: Nhân viên sản xuất chung | E59: 3 | F59: 3 | G59: 3 | H59: 3 | I59: 3 | J59: 3 | K59: 3 | L59: 3 | M59: 3 | N59: 3 | O59: 3 | P59: 3 | Q59: 3 | R59: 3 | S59: 3 | T59: 3 | V59: Công đoạn 1: Cấp liệu
B60: 6.2.3 | C60: Nhân viên ép kiện | E60: 2 | F60: 2 | G60: 2 | H60: 2 | I60: 2 | J60: 2 | K60: 2 | L60: 2 | M60: 2 | N60: 2 | O60: 2 | P60: 2 | Q60: 2 | R60: 2 | S60: 2 | T60: 2 | V60: Công đoạn 2: Phân loại chai
B61: 6.2.4 | C61: Nhân viên lái xe nâng | E61: 3 | F61: 3 | G61: 3 | H61: 3 | I61: 3 | J61: 3 | K61: 3 | L61: 3 | M61: 3 | N61: 3 | O61: 3 | P61: 3 | Q61: 3 | R61: 3 | S61: 3 | T61: 3 | V61: Công đoạn 3: Tách nhãn
B62: 6.2.5 | C62: Nhân viên Nhập - Xuất hàng | E62: 5 | F62: 5 | G62: 5 | H62: 5 | I62: 5 | J62: 5 | K62: 5 | L62: 5 | M62: 5 | N62: 5 | O62: 5 | P62: 5 | Q62: 5 | R62: 5 | S62: 5 | T62: =IFERROR(AVERAGEA(H62:S62),0) -> 5 | V62: Nhân viên xử lý nắp, cổ chai,…
B63: 6.2.6 | C63: Lao động thuê ngoài | F63: 2 | G63: 13 | H63: 12 | I63: 12 | J63: 12 | K63: 12 | L63: 12 | M63: 12 | N63: 12 | O63: 12 | P63: 12 | Q63: 12 | R63: 12 | S63: 12 | T63: 12 | V63: Công đoạn 4: Rework (B6.2+chai còn nhãn)
B64: 14.3 | C64: Công nhân trực tiếp sản xuất - Băm vảy PET | D64: 622 | G64: =G65+G66 -> 0 | H64: =H65+H66 -> 0 | I64: =I65+I66 -> 0 | J64: =J65+J66 -> 0 | K64: =K65+K66 -> 0 | L64: =L65+L66 -> 0 | M64: =M65+M66 -> 0 | N64: =N65+N66 -> 0 | ... S64: =S65+S66 -> 0 | V64: Công đoạn 5: Ép kiện và lưu kho
B65: 14.3.1 | C65: Nhân viên băm vảy | V65: Sản xuất chung
B66: 14.3.2 | C66: Lao động thuê ngoài | V66: Nhân viên lái xe nâng
B67: 8 | C67: Phòng Kho vận | D67: 627 | E67: =SUM(E68:E71) -> 0 | F67: =SUM(F68:F71) -> 1 | G67: =SUM(G68:G71) -> 1 | H67: =SUM(H68:H71) -> 1 | I67: =SUM(I68:I71) -> 1 | J67: =SUM(J68:J71) -> 1 | K67: =SUM(K68:K71) -> 1 | L67: =SUM(L68:L71) -> 1 | ... T67: =SUM(T68:T71) -> 1 | V67: Nhân viên kéo bao, bì tạp
B68: 8.1 | C68: Thủ kho | E68: 0 | F68: 1 | G68: 1 | H68: 1 | I68: 1 | J68: 1 | K68: 1 | L68: 1 | M68: 1 | N68: 1 | O68: 1 | P68: 1 | Q68: 1 | R68: 1 | S68: 1 | T68: =IFERROR(AVERAGEA(H68:S68),0) -> 1 | V68: Nhân viên ghi số liệu
B69: 15.2 | C69: Tổ Trưởng Kho - Xuất nhập | T69: =IFERROR(AVERAGEA(H69:S69),0) -> 0 | V69: Xử lý phó sản
B70: 15.3 | C70: Nhân Viên Lái Xe Nâng | H70: 0 | I70: 0 | J70: 0 | K70: 0 | L70: 0 | M70: 0 | N70: 0 | O70: 0 | P70: 0 | Q70: 0 | R70: 0 | S70: 0 | T70: =IFERROR(AVERAGEA(H70:S70),0) -> 0
B71: 15.5 | C71: Lao động thuê ngoài
B72: 16 | C72: Trạm cấp 2 - Kiên Giang | D72: 642 | E72: =E73 -> 0 | F72: =F73 -> 0 | G72: =G73 -> 0 | H72: =H73 -> 0 | I72: =I73 -> 0 | J72: =J73 -> 0 | K72: =K73 -> 0 | L72: =L73 -> 0 | ... S72: =S73 -> 0 | T72: =IFERROR(AVERAGEA(H72:S72),0) -> 0
B73: 16.1 | C73: Nhân viên | T73: =IFERROR(AVERAGEA(H73:S73),0) -> 0
B74: 17 | C74: Trạm cấp 2 - Cà Mau | D74: 642 | E74: =E75 -> 0 | F74: =F75 -> 0 | G74: =G75 -> 0 | H74: =H75 -> 0 | I74: =I75 -> 0 | J74: =J75 -> 0 | K74: =K75 -> 0 | L74: =L75 -> 0 | ... S74: =S75 -> 0 | T74: =IFERROR(AVERAGEA(H74:S74),0) -> 0
B75: 17.1 | C75: Nhân viên | T75: =IFERROR(AVERAGEA(H75:S75),0) -> 0
B76: 18 | C76: Trạm cấp 2 - Gia Lai | D76: 642 | E76: =E77 -> 0 | F76: =F77 -> 0 | G76: =G77 -> 0 | H76: =H77 -> 0 | I76: =I77 -> 0 | J76: =J77 -> 0 | K76: =K77 -> 0 | L76: =L77 -> 0 | ... S76: =S77 -> 0 | T76: =IFERROR(AVERAGEA(H76:S76),0) -> 0
B77: 18.1 | C77: Nhân viên | T77: =IFERROR(AVERAGEA(H77:S77),0) -> 0
C78: TỔNG NHÂN SỰ | E78: =E5+E9+E17+E22+E24+E26+E28+E31+E33+E35+E37+E39+E43+E51+E67 -> 56 | F78: =F5+F9+F17+F22+F24+F26+F28+F31+F33+F35+F37+F39+F43+F51+F67 -> 49 | G78: =G5+G9+G17+G22+G24+G26+G28+G31+G33+G35+G37+G39+G43+G51+G67 -> 53 | H78: =H5+H9+H17+H22+H24+H26+H28+H31+H33+H35+H37+H39+H43+H51+H67 -> 56 | I78: =I5+I9+I17+I22+I24+I26+I28+I31+I33+I35+I37+I39+I43+I51+I67 -> 56 | J78: =J5+J9+J17+J22+J24+J26+J28+J31+J33+J35+J37+J39+J43+J51+J67 -> 56 | K78: =K5+K9+K17+K22+K24+K26+K28+K31+K33+K35+K37+K39+K43+K51+K67 -> 56 | L78: =L5+L9+L17+L22+L24+L26+L28+L31+L33+L35+L37+L39+L43+L51+L67 -> 56 | ... T78: =T5+T9+T17+T22+T24+T26+T28+T31+T33+T35+T37+T39+T43+T51+T67 -> 54
C79: Nhân sự thuộc ĐỊNH BIÊN | E79: =E78-E80 -> 56 | F79: =F78-F80 -> 47 | G79: =G78-G80 -> 39 | H79: =H78-H80 -> 42 | I79: =I78-I80 -> 42 | J79: =J78-J80 -> 42 | K79: =K78-K80 -> 42 | L79: =L78-L80 -> 42 | ... T79: =T78-T80 -> 40
C80: Lao động thuê ngoài | E80: =E63+E71+E14 -> 0 | F80: =F63+F71+F14 -> 2 | G80: =G63+G71+G14 -> 14 | H80: =H63+H71+H14+H42 -> 14 | I80: =I63+I71+I14+I42 -> 14 | J80: =J63+J71+J14+J42 -> 14 | K80: =K63+K71+K14+K42 -> 14 | L80: =L63+L71+L14+L42 -> 14 | M80: =M63+M71+M14+M42 -> 14 | N80: =N63+N71+N14+N42 -> 14 | O80: =O63+O71+O14+O42 -> 14 | ... T80: =T63+T71+T14+T42 -> 14
B82: II - ĐỊNH BIÊN - HD
B83: 19 | C83: XƯỞNG SẢN XUẤT | D83: =D4 -> Tài khoản | E83: KQKD 2023 | F83: KQKD 2024 | G83: =G4 -> KQKD 2025 | H83: =H4 -> T1 | I83: =I4 -> T2 | J83: =J4 -> T3 | K83: =K4 -> T4 | L83: =L4 -> T5 | M83: =M4 -> T6 | N83: =N4 -> T7 | ... T83: =T4 -> Kế hoạch 2026
B84: 19.1 | C84: Quản lý sản xuất | D84: 627 | T84: =IFERROR(AVERAGEA(H84:S84),0) -> 0
B85: 19.1.1 | C85: Trưởng ca sản xuất (theo ca sx) | T85: =IFERROR(AVERAGEA(H85:S85),0) -> 0
B86: 19.2 | C86: Công nhân trực tiếp sản xuất | D86: 622 | T86: =IFERROR(AVERAGEA(H86:S86),0) -> 0
C87: TỔNG: | H87: =H85+H86 -> 0 | I87: =I85+I86 -> 0 | J87: =J85+J86 -> 0 | K87: =K85+K86 -> 0 | L87: =L85+L86 -> 0 | M87: =M85+M86 -> 0 | N87: =N85+N86 -> 0 | O87: =O85+O86 -> 0 | ... S87: =S85+S86 -> 0 | T87: =IFERROR(AVERAGEA(H87:S87),0) -> 0

Sheet LUONG
B3: BẢNG LƯƠNG TỪ HCNS | F3: =SUBTOTAL(9,F5:F208) -> 50405987 | G3: =SUBTOTAL(9,G5:G208) -> 86833987 | H3: =SUBTOTAL(9,H5:H208) -> 48781987 | I3: =SUBTOTAL(9,I5:I208) -> 49453987 | J3: =SUBTOTAL(9,J5:J208) -> 51133987 | K3: =SUBTOTAL(9,K5:K208) -> 49453987 | L3: =SUBTOTAL(9,L5:L208) -> 49229987 | M3: =SUBTOTAL(9,M5:M208) -> 49229987 | ... Q3: =SUBTOTAL(9,Q5:Q208) -> 49229987
B4: Phòng ban | C4: Mã tài khoản (Mã Chi phí_L4) | D4: Tên tài khoản (Cost elements 2) | E4: Chi Phí_L5 (Cost Group 2) | F4: T1 | G4: T2 | H4: T3 | I4: T4 | J4: T5 | K4: T6 | L4: T7 | M4: T8 | N4: T9 | O4: T10 | P4: T11 | Q4: T12 | R4: Kế hoạch 2026
B5: Ban giám đốc | D5: Số lượng nhân sự | F5: ='Dinh bien_HCNS'!H5 -> 3 | G5: ='Dinh bien_HCNS'!I5 -> 3 | H5: ='Dinh bien_HCNS'!J5 -> 3 | I5: ='Dinh bien_HCNS'!K5 -> 3 | J5: ='Dinh bien_HCNS'!L5 -> 3 | K5: ='Dinh bien_HCNS'!M5 -> 3 | L5: ='Dinh bien_HCNS'!N5 -> 3 | M5: ='Dinh bien_HCNS'!O5 -> 3 | ... R5: ='Dinh bien_HCNS'!T5 -> 3
B6: Ban giám đốc | D6: ADM_Lương Khối Quản Lý | F6: =SUM(F8:F16) -> 219959680 | G6: =SUM(G8:G16) -> 238357680 | H6: =SUM(H8:H16) -> 219275680 | I6: =SUM(I8:I16) -> 219527680 | J6: =SUM(J8:J16) -> 220307680 | K6: =SUM(K8:K16) -> 219527680 | L6: =SUM(L8:L16) -> 219443680 | M6: =SUM(M8:M16) -> 219443680 | ... R6: =SUM(R8:R16) -> 2654134160
B7: Ban giám đốc | D7: Chi phí lương TB/1 Người | F7: =IFERROR(SUM(F8:F15)/F5,0) -> 73319893 | G7: =IFERROR(SUM(G8:G15)/G5,0) -> 79452560 | H7: =IFERROR(SUM(H8:H15)/H5,0) -> 73091893 | I7: =IFERROR(SUM(I8:I15)/I5,0) -> 73175893 | J7: =IFERROR(SUM(J8:J15)/J5,0) -> 73435893 | K7: =IFERROR(SUM(K8:K15)/K5,0) -> 73175893 | L7: =IFERROR(SUM(L8:L15)/L5,0) -> 73147893 | M7: =IFERROR(SUM(M8:M15)/M5,0) -> 73147893 | ... Q7: =IFERROR(SUM(Q8:Q15)/Q5,0) -> 73147893 | R7: =AVERAGEA(F7:Q7) -> 73725949
B8: Ban giám đốc | C8: 6421002604 | D8: Chi phí lương chính - Gián tiếp | E8: Salary and Wages - Direct | F8: 159236000 | G8: 159236000 | H8: 159236000 | I8: 159236000 | J8: 159236000 | K8: 159236000 | L8: 159236000 | M8: 159236000 | N8: 159236000 | O8: 159236000 | P8: 159236000 | Q8: 159236000 | R8: =SUM(F8:Q8) -> 1910832000
B9: Ban giám đốc | C9: 6421002605 | D9: Chi phí lương T13, phép năm - Gián tiếp | E9: Salary and Wages - Support | F9: 12566600 | G9: 12566600 | H9: 12566600 | I9: 12566600 | J9: 12566600 | K9: 12566600 | L9: 12566600 | M9: 12566600 | N9: 12566600 | O9: 12566600 | P9: 12566600 | Q9: 12566600 | R9: =SUM(F9:Q9) -> 150799200
B10: Ban giám đốc | C10: 6421002802 | D10: Chi phí khen thưởng - Gián tiếp | E10: Employee Welfare | F10: 600000 | G10: 0 | H10: 0 | I10: 0 | J10: 1200000 | K10: 0 | L10: 0 | M10: 0 | N10: 600000 | O10: 0 | P10: 0 | Q10: 0 | R10: =SUM(F10:Q10) -> 2400000
B11: Ban giám đốc | C11: 6421002806 | D11: Thưởng danh hiệu | E11: Salary and Wages - Support | F11: 17064120 | G11: 17064120 | H11: 17064120 | I11: 17064120 | J11: 17064120 | K11: 17064120 | L11: 17064120 | M11: 17064120 | N11: 17064120 | O11: 17064120 | P11: 17064120 | Q11: 17064120 | R11: =SUM(F11:Q11) -> 204769440
B12: Ban giám đốc | C12: 6421007202 | D12: Chi phí khen thưởng, bồi dưỡng khác | E12: Employee Welfare | G12: 19250000 | R12: =SUM(F12:Q12) -> 19250000
B13: Ban giám đốc | C13: 6421003202 | D13: Tiền ăn giữa ca - Gián tiếp | E13: Employee Welfare | F13: 2100000 | G13: 1848000 | H13: 2016000 | I13: 2268000 | J13: 1848000 | K13: 2268000 | L13: 2184000 | M13: 2184000 | N13: 2100000 | O13: 2100000 | P13: 2268000 | Q13: 2184000 | R13: =SUM(F13:Q13) -> 25368000
B14: Ban giám đốc | C14: 6421002603 | D14: Phụ cấp ca đêm - Gián tiếp | E14: Salary and Wages - Support | R14: =SUM(F14:Q14) -> 0
B15: Ban giám đốc | C15: 6421003401 | D15: BHXH, BHYT, KPCĐ, BHTN - Gián tiếp | E15: Employee Welfare | F15: 28392960 | G15: 28392960 | H15: 28392960 | I15: 28392960 | J15: 28392960 | K15: 28392960 | L15: 28392960 | M15: 28392960 | N15: 28392960 | O15: 28392960 | P15: 28392960 | Q15: 28392960 | R15: =SUM(F15:Q15) -> 340715520
B16: Ban giám đốc | C16: 6421002703 | D16: Chi phí lương ngoài giờ - Gián tiếp | E16: Salary and Wages - Support | R16: =SUM(F16:Q16) -> 0
B17: Phòng Hành chánh nhân sự | D17: Số lượng nhân sự | F17: ='Dinh bien_HCNS'!H9 -> 2 | G17: ='Dinh bien_HCNS'!I9 -> 2 | H17: ='Dinh bien_HCNS'!J9 -> 2 | I17: ='Dinh bien_HCNS'!K9 -> 2 | J17: ='Dinh bien_HCNS'!L9 -> 2 | K17: ='Dinh bien_HCNS'!M9 -> 2 | L17: ='Dinh bien_HCNS'!N9 -> 2 | M17: ='Dinh bien_HCNS'!O9 -> 2 | ... R17: ='Dinh bien_HCNS'!T9 -> 2
B18: Phòng Hành chánh nhân sự | D18: ADM_Lương Khối Quản Lý | F18: =SUM(F20:F28) -> 27239400 | G18: =SUM(G20:G28) -> 26518323 | H18: =SUM(H20:H28) -> 25799554 | I18: =SUM(I20:I28) -> 28148323 | J18: =SUM(J20:J28) -> 26004477 | K18: =SUM(K20:K28) -> 28148323 | L18: =SUM(L20:L28) -> 27365400 | M18: =SUM(M20:M28) -> 27365400 | ... R18: =SUM(R20:R28) -> 326381723
B19: Phòng Hành chánh nhân sự | D19: Chi phí lương TB/1 Người | F19: =IFERROR(SUM(F20:F27)/F17,0) -> 13619700 | G19: =IFERROR(SUM(G20:G27)/G17,0) -> 13259162 | H19: =IFERROR(SUM(H20:H27)/H17,0) -> 12899777 | I19: =IFERROR(SUM(I20:I27)/I17,0) -> 14074162 | J19: =IFERROR(SUM(J20:J27)/J17,0) -> 13002238 | K19: =IFERROR(SUM(K20:K27)/K17,0) -> 14074162 | L19: =IFERROR(SUM(L20:L27)/L17,0) -> 13682700 | M19: =IFERROR(SUM(M20:M27)/M17,0) -> 13682700 | ... Q19: =IFERROR(SUM(Q20:Q27)/Q17,0) -> 13682700 | R19: =AVERAGEA(F19:Q19) -> 13599238
B20: Phòng Hành chánh nhân sự | C20: 6421002604 | D20: Chi phí lương chính - Gián tiếp | E20: Salary and Wages - Direct | F20: =13880000+6750000 -> 20630000 | G20: =14336923+5940000 -> 20276923 | H20: =12966154+6480000 -> 19446154 | I20: =14336923+7290000 -> 21626923 | J20: =13423077+5940000 -> 19363077 | K20: =14336923+7290000 -> 21626923 | L20: =13880000+7020000 -> 20900000 | M20: =13880000+7020000 -> 20900000 | N20: =14336923+6750000 -> 21086923 | O20: =13423077+6750000 -> 20173077 | P20: =14336923+7290000 -> 21626923 | Q20: =13880000+7020000 -> 20900000 | R20: =SUM(F20:Q20) -> 248556923
B21: Phòng Hành chánh nhân sự | C21: 6421002605 | D21: Chi phí lương T13, phép năm - Gián tiếp | E21: Salary and Wages - Support | F21: 940500 | G21: 940500 | H21: 940500 | I21: 940500 | J21: 940500 | K21: 940500 | L21: 940500 | M21: 940500 | N21: 940500 | O21: 940500 | P21: 940500 | Q21: 940500 | R21: =SUM(F21:Q21) -> 11286000
B22: Phòng Hành chánh nhân sự | C22: 6421002802 | D22: Chi phí khen thưởng - Gián tiếp | E22: Employee Welfare | F22: 200000 | G22: 0 | H22: 0 | I22: 0 | J22: 400000 | K22: 0 | L22: 0 | M22: 0 | N22: 200000 | O22: 0 | P22: 0 | Q22: 0 | R22: =SUM(F22:Q22) -> 800000
B23: Phòng Hành chánh nhân sự | C23: 6421002806 | D23: Thưởng danh hiệu | E23: Salary and Wages - Support | F23: 1277100 | G23: 1277100 | H23: 1277100 | I23: 1277100 | J23: 1277100 | K23: 1277100 | L23: 1277100 | M23: 1277100 | N23: 1277100 | O23: 1277100 | P23: 1277100 | Q23: 1277100 | R23: =SUM(F23:Q23) -> 15325200
B24: Phòng Hành chánh nhân sự | C24: 6421007202 | D24: Chi phí khen thưởng, bồi dưỡng khác | E24: Employee Welfare | R24: =SUM(F24:Q24) -> 0
B25: Phòng Hành chánh nhân sự | C25: 6421003202 | D25: Tiền ăn giữa ca - Gián tiếp | E25: Employee Welfare | F25: =700000*2 -> 1400000 | G25: =616000*2 -> 1232000 | H25: =672000*2 -> 1344000 | I25: =756000*2 -> 1512000 | J25: =616000*2 -> 1232000 | K25: =756000*2 -> 1512000 | L25: =728000*2 -> 1456000 | M25: =728000*2 -> 1456000 | N25: =700000*2 -> 1400000 | O25: =700000*2 -> 1400000 | P25: =756000*2 -> 1512000 | Q25: =728000*2 -> 1456000 | R25: =SUM(F25:Q25) -> 16912000
B26: Phòng Hành chánh nhân sự | C26: 6421002603 | D26: Phụ cấp ca đêm - Gián tiếp | E26: Salary and Wages - Support | R26: =SUM(F26:Q26) -> 0
B27: Phòng Hành chánh nhân sự | C27: 6421003401 | D27: BHXH, BHYT, KPCĐ, BHTN - Gián tiếp | E27: Employee Welfare | F27: 2791800 | G27: 2791800 | H27: 2791800 | I27: 2791800 | J27: 2791800 | K27: 2791800 | L27: 2791800 | M27: 2791800 | N27: 2791800 | O27: 2791800 | P27: 2791800 | Q27: 2791800 | R27: =SUM(F27:Q27) -> 33501600
B28: Phòng Hành chánh nhân sự | C28: 6421002703 | D28: Chi phí lương ngoài giờ - Gián tiếp | E28: Salary and Wages - Support | R28: =SUM(F28:Q28) -> 0
B29: Phòng Kế toán | D29: Số lượng nhân sự | F29: ='Dinh bien_HCNS'!H17 -> 3 | G29: ='Dinh bien_HCNS'!I17 -> 3 | H29: ='Dinh bien_HCNS'!J17 -> 3 | I29: ='Dinh bien_HCNS'!K17 -> 3 | J29: ='Dinh bien_HCNS'!L17 -> 3 | K29: ='Dinh bien_HCNS'!M17 -> 3 | L29: ='Dinh bien_HCNS'!N17 -> 3 | M29: ='Dinh bien_HCNS'!O17 -> 3 | ... R29: ='Dinh bien_HCNS'!T17 -> 3
B30: Phòng Kế toán | D30: ADM_Lương Khối Quản Lý | F30: =SUM(F32:F40) -> 76746454 | G30: =SUM(G32:G40) -> 97131171 | H30: =SUM(H32:H40) -> 72057557 | I30: =SUM(I32:I40) -> 78323643 | J30: =SUM(J32:J40) -> 75080769 | K30: =SUM(K32:K40) -> 78323643 | L30: =SUM(L32:L40) -> 76234948 | M30: =SUM(M32:M40) -> 76234948 | ... R30: =SUM(R32:R40) -> 937584632
B31: Phòng Kế toán | D31: Chi phí lương TB/1 Người | F31: =IFERROR(SUM(F32:F39)/F29,0) -> 25582151 | G31: =IFERROR(SUM(G32:G39)/G29,0) -> 32377057 | H31: =IFERROR(SUM(H32:H39)/H29,0) -> 24019186 | I31: =IFERROR(SUM(I32:I39)/I29,0) -> 26107881 | J31: =IFERROR(SUM(J32:J39)/J29,0) -> 25026923 | K31: =IFERROR(SUM(K32:K39)/K29,0) -> 26107881 | L31: =IFERROR(SUM(L32:L39)/L29,0) -> 25411649 | M31: =IFERROR(SUM(M32:M39)/M29,0) -> 25411649 | ... Q31: =IFERROR(SUM(Q32:Q39)/Q29,0) -> 25411649 | R31: =AVERAGEA(F31:Q31) -> 26044018
B32: Phòng Kế toán | C32: 6421002604 | D32: Chi phí lương chính - Gián tiếp | E32: Salary and Wages - Direct | F32: 52117584 | G32: 54104301 | H32: 48112687 | I32: 54126773 | J32: 50103899 | K32: 54126773 | L32: 52122078 | M32: 52122078 | N32: 54117785 | O32: 50117383 | P32: 54126773 | Q32: 52122078 | R32: =SUM(F32:Q32) -> 627420192
B33: Phòng Kế toán | C33: 6421002605 | D33: Chi phí lương T13, phép năm - Gián tiếp | E33: Salary and Wages - Support | F33: 4117081 | G33: 4117081 | H33: 4117081 | I33: 4117081 | J33: 4117081 | K33: 4117081 | L33: 4117081 | M33: 4117081 | N33: 4117081 | O33: 4117081 | P33: 4117081 | Q33: 4117081 | R33: =SUM(F33:Q33) -> 49404972
B34: Phòng Kế toán | C34: 6421002802 | D34: Chi phí khen thưởng - Gián tiếp | E34: Employee Welfare | F34: 600000 | G34: 0 | H34: 0 | I34: 0 | J34: 1200000 | K34: 0 | L34: 0 | M34: 0 | N34: 600000 | O34: 0 | P34: 0 | Q34: 0 | R34: =SUM(F34:Q34) -> 2400000
B35: Phòng Kế toán | C35: 6421002806 | D35: Thưởng danh hiệu | E35: Salary and Wages - Support | F35: 5590562 | G35: 5590562 | H35: 5590562 | I35: 5590562 | J35: 5590562 | K35: 5590562 | L35: 5590562 | M35: 5590562 | N35: 5590562 | O35: 5590562 | P35: 5590562 | Q35: 5590562 | R35: =SUM(F35:Q35) -> 67086744
B36: Phòng Kế toán | C36: 6421007202 | D36: Chi phí khen thưởng, bồi dưỡng khác | E36: Employee Welfare | G36: 19250000 | R36: =SUM(F36:Q36) -> 19250000
B37: Phòng Kế toán | C37: 6421003202 | D37: Tiền ăn giữa ca - Gián tiếp | E37: Employee Welfare | F37: 2100000 | G37: 1848000 | H37: 2016000 | I37: 2268000 | J37: 1848000 | K37: 2268000 | L37: 2184000 | M37: 2184000 | N37: 2100000 | O37: 2100000 | P37: 2268000 | Q37: 2184000 | R37: =SUM(F37:Q37) -> 25368000
B38: Phòng Kế toán | C38: 6421002603 | D38: Phụ cấp ca đêm - Gián tiếp | E38: Salary and Wages - Support | R38: =SUM(F38:Q38) -> 0
B39: Phòng Kế toán | C39: 6421003401 | D39: BHXH, BHYT, KPCĐ, BHTN - Gián tiếp | E39: Employee Welfare | F39: 12221227 | G39: 12221227 | H39: 12221227 | I39: 12221227 | J39: 12221227 | K39: 12221227 | L39: 12221227 | M39: 12221227 | N39: 12221227 | O39: 12221227 | P39: 12221227 | Q39: 12221227 | R39: =SUM(F39:Q39) -> 146654724
B40: Phòng Kế toán | C40: 6421002703 | D40: Chi phí lương ngoài giờ - Gián tiếp | E40: Salary and Wages - Support | R40: =SUM(F40:Q40) -> 0
B41: Phòng Mua hàng | D41: Số lượng nhân sự | F41: ='Dinh bien_HCNS'!H22 -> 0 | G41: ='Dinh bien_HCNS'!I22 -> 0 | H41: ='Dinh bien_HCNS'!J22 -> 0 | I41: ='Dinh bien_HCNS'!K22 -> 0 | J41: ='Dinh bien_HCNS'!L22 -> 0 | K41: ='Dinh bien_HCNS'!M22 -> 0 | L41: ='Dinh bien_HCNS'!N22 -> 0 | M41: ='Dinh bien_HCNS'!O22 -> 0 | ... R41: ='Dinh bien_HCNS'!T22 -> 0
B42: Phòng Mua hàng | D42: ADM_Lương Khối Quản Lý | F42: =SUM(F44:F51) -> 0 | G42: =SUM(G44:G51) -> 0 | H42: =SUM(H44:H51) -> 0 | I42: =SUM(I44:I51) -> 0 | J42: =SUM(J44:J51) -> 0 | K42: =SUM(K44:K51) -> 0 | L42: =SUM(L44:L51) -> 0 | M42: =SUM(M44:M51) -> 0 | ... Q42: =SUM(Q44:Q51) -> 0 | R42: =SUM(F42:Q42) -> 0
B43: Phòng Mua hàng | D43: Chi phí lương TB/1 Người | F43: =IFERROR(SUM(F44:F51)/F41,0) -> 0 | G43: =IFERROR(SUM(G44:G51)/G41,0) -> 0 | H43: =IFERROR(SUM(H44:H51)/H41,0) -> 0 | I43: =IFERROR(SUM(I44:I51)/I41,0) -> 0 | J43: =IFERROR(SUM(J44:J51)/J41,0) -> 0 | K43: =IFERROR(SUM(K44:K51)/K41,0) -> 0 | L43: =IFERROR(SUM(L44:L51)/L41,0) -> 0 | M43: =IFERROR(SUM(M44:M51)/M41,0) -> 0 | ... Q43: =IFERROR(SUM(Q44:Q51)/Q41,0) -> 0 | R43: =AVERAGEA(F43:Q43) -> 0
B44: Phòng Mua hàng | C44: 6421002604 | D44: Chi phí lương chính - Gián tiếp | E44: Salary and Wages - Direct | R44: =SUM(F44:Q44) -> 0
B45: Phòng Mua hàng | C45: 6421002605 | D45: Chi phí lương T13, phép năm - Gián tiếp | E45: Salary and Wages - Support | R45: =SUM(F45:Q45) -> 0
B46: Phòng Mua hàng | C46: 6421002802 | D46: Chi phí khen thưởng - Gián tiếp | E46: Employee Welfare | R46: =SUM(F46:Q46) -> 0
B47: Phòng Mua hàng | C47: 6421002806 | D47: Thưởng danh hiệu | E47: Salary and Wages - Support | R47: =SUM(F47:Q47) -> 0
B48: Phòng Mua hàng | C48: 6421007202 | D48: Chi phí khen thưởng, bồi dưỡng khác | E48: Employee Welfare | R48: =SUM(F48:Q48) -> 0
B49: Phòng Mua hàng | C49: 6421003202 | D49: Tiền ăn giữa ca - Gián tiếp | E49: Employee Welfare | R49: =SUM(F49:Q49) -> 0
B50: Phòng Mua hàng | C50: 6421002603 | D50: Phụ cấp ca đêm - Gián tiếp | E50: Salary and Wages - Support | R50: =SUM(F50:Q50) -> 0
B51: Phòng Mua hàng | C51: 6421003401 | D51: BHXH, BHYT, KPCĐ, BHTN - Gián tiếp | E51: Employee Welfare | R51: =SUM(F51:Q51) -> 0
B52: Phòng Mua hàng | C52: 6421002703 | D52: Chi phí lương ngoài giờ - Gián tiếp | E52: Salary and Wages - Support | R52: =SUM(F52:Q52) -> 0
B53: Ban dự án XDCB | D53: Số lượng nhân sự
B54: Ban dự án XDCB | D54: ADM_Lương Khối Quản Lý | F54: =SUM(F56:F63) -> 0 | G54: =SUM(G56:G63) -> 0 | H54: =SUM(H56:H63) -> 0 | I54: =SUM(I56:I63) -> 0 | J54: =SUM(J56:J63) -> 0 | K54: =SUM(K56:K63) -> 0 | L54: =SUM(L56:L63) -> 0 | M54: =SUM(M56:M63) -> 0 | ... Q54: =SUM(Q56:Q63) -> 0 | R54: =SUM(F54:Q54) -> 0
B55: Ban dự án XDCB | D55: Chi phí lương TB/1 Người | F55: =IFERROR(SUM(F56:F63)/F53,0) -> 0 | G55: =IFERROR(SUM(G56:G63)/G53,0) -> 0 | H55: =IFERROR(SUM(H56:H63)/H53,0) -> 0 | I55: =IFERROR(SUM(I56:I63)/I53,0) -> 0 | J55: =IFERROR(SUM(J56:J63)/J53,0) -> 0 | K55: =IFERROR(SUM(K56:K63)/K53,0) -> 0 | L55: =IFERROR(SUM(L56:L63)/L53,0) -> 0 | M55: =IFERROR(SUM(M56:M63)/M53,0) -> 0 | ... Q55: =IFERROR(SUM(Q56:Q63)/Q53,0) -> 0 | R55: =AVERAGEA(F55:Q55) -> 0
B56: Ban dự án XDCB | C56: 6421002604 | D56: Chi phí lương chính - Gián tiếp | E56: Salary and Wages - Direct | R56: =SUM(F56:Q56) -> 0
B57: Ban dự án XDCB | C57: 6421002605 | D57: Chi phí lương T13, phép năm - Gián tiếp | E57: Salary and Wages - Support | R57: =SUM(F57:Q57) -> 0
B58: Ban dự án XDCB | C58: 6421002802 | D58: Chi phí khen thưởng - Gián tiếp | E58: Employee Welfare | R58: =SUM(F58:Q58) -> 0
B59: Ban dự án XDCB | C59: 6421002806 | D59: Thưởng danh hiệu | E59: Salary and Wages - Support | R59: =SUM(F59:Q59) -> 0
B60: Ban dự án XDCB | C60: 6421007202 | D60: Chi phí khen thưởng, bồi dưỡng khác | E60: Employee Welfare | R60: =SUM(F60:Q60) -> 0
B61: Ban dự án XDCB | C61: 6421003202 | D61: Tiền ăn giữa ca - Gián tiếp | E61: Employee Welfare | R61: =SUM(F61:Q61) -> 0
B62: Ban dự án XDCB | C62: 6421002603 | D62: Phụ cấp ca đêm - Gián tiếp | E62: Salary and Wages - Support | R62: =SUM(F62:Q62) -> 0
B63: Ban dự án XDCB | C63: 6421003401 | D63: BHXH, BHYT, KPCĐ, BHTN - Gián tiếp | E63: Employee Welfare | R63: =SUM(F63:Q63) -> 0
B64: Ban dự án XDCB | C64: 6421002703 | D64: Chi phí lương ngoài giờ - Gián tiếp | E64: Salary and Wages - Support | R64: =SUM(F64:Q64) -> 0
B65: Phòng Quản Trị Hệ Thống | D65: Số lượng nhân sự
B66: Phòng Quản Trị Hệ Thống | D66: ADM_Lương Khối Quản Lý | F66: =SUM(F68:F75) -> 0 | G66: =SUM(G68:G75) -> 0 | H66: =SUM(H68:H75) -> 0 | I66: =SUM(I68:I75) -> 0 | J66: =SUM(J68:J75) -> 0 | K66: =SUM(K68:K75) -> 0 | L66: =SUM(L68:L75) -> 0 | M66: =SUM(M68:M75) -> 0 | ... Q66: =SUM(Q68:Q75) -> 0 | R66: =SUM(F66:Q66) -> 0
B67: Phòng Quản Trị Hệ Thống | D67: Chi phí lương TB/1 Người | F67: =IFERROR(SUM(F68:F75)/F65,0) -> 0 | G67: =IFERROR(SUM(G68:G75)/G65,0) -> 0 | H67: =IFERROR(SUM(H68:H75)/H65,0) -> 0 | I67: =IFERROR(SUM(I68:I75)/I65,0) -> 0 | J67: =IFERROR(SUM(J68:J75)/J65,0) -> 0 | K67: =IFERROR(SUM(K68:K75)/K65,0) -> 0 | L67: =IFERROR(SUM(L68:L75)/L65,0) -> 0 | M67: =IFERROR(SUM(M68:M75)/M65,0) -> 0 | ... Q67: =IFERROR(SUM(Q68:Q75)/Q65,0) -> 0 | R67: =AVERAGEA(F67:Q67) -> 0
B68: Phòng Quản Trị Hệ Thống | C68: 6421002604 | D68: Chi phí lương chính - Gián tiếp | E68: Salary and Wages - Direct | R68: =SUM(F68:Q68) -> 0
B69: Phòng Quản Trị Hệ Thống | C69: 6421002605 | D69: Chi phí lương T13, phép năm - Gián tiếp | E69: Salary and Wages - Support | R69: =SUM(F69:Q69) -> 0
B70: Phòng Quản Trị Hệ Thống | C70: 6421002802 | D70: Chi phí khen thưởng - Gián tiếp | E70: Employee Welfare | R70: =SUM(F70:Q70) -> 0
B71: Phòng Quản Trị Hệ Thống | C71: 6421002806 | D71: Thưởng danh hiệu | E71: Salary and Wages - Support | R71: =SUM(F71:Q71) -> 0
B72: Phòng Quản Trị Hệ Thống | C72: 6421007202 | D72: Chi phí khen thưởng, bồi dưỡng khác | E72: Employee Welfare | R72: =SUM(F72:Q72) -> 0
B73: Phòng Quản Trị Hệ Thống | C73: 6421003202 | D73: Tiền ăn giữa ca - Gián tiếp | E73: Employee Welfare | R73: =SUM(F73:Q73) -> 0
B74: Phòng Quản Trị Hệ Thống | C74: 6421002603 | D74: Phụ cấp ca đêm - Gián tiếp | E74: Salary and Wages - Support | R74: =SUM(F74:Q74) -> 0
B75: Phòng Quản Trị Hệ Thống | C75: 6421003401 | D75: BHXH, BHYT, KPCĐ, BHTN - Gián tiếp | E75: Employee Welfare | R75: =SUM(F75:Q75) -> 0
B76: Phòng Quản Trị Hệ Thống | C76: 6421002703 | D76: Chi phí lương ngoài giờ - Gián tiếp | E76: Salary and Wages - Support | R76: =SUM(F76:Q76) -> 0
B77: Phòng 5S & an toàn | D77: Số lượng nhân sự
B78: Phòng 5S & an toàn | D78: ADM_Lương Khối Quản Lý | F78: =SUM(F80:F87) -> 0 | G78: =SUM(G80:G87) -> 0 | H78: =SUM(H80:H87) -> 0 | I78: =SUM(I80:I87) -> 0 | J78: =SUM(J80:J87) -> 0 | K78: =SUM(K80:K87) -> 0 | L78: =SUM(L80:L87) -> 0 | M78: =SUM(M80:M87) -> 0 | ... Q78: =SUM(Q80:Q87) -> 0 | R78: =SUM(F78:Q78) -> 0
B79: Phòng 5S & an toàn | D79: Chi phí lương TB/1 Người | F79: =IFERROR(SUM(F80:F87)/F77,0) -> 0 | G79: =IFERROR(SUM(G80:G87)/G77,0) -> 0 | H79: =IFERROR(SUM(H80:H87)/H77,0) -> 0 | I79: =IFERROR(SUM(I80:I87)/I77,0) -> 0 | J79: =IFERROR(SUM(J80:J87)/J77,0) -> 0 | K79: =IFERROR(SUM(K80:K87)/K77,0) -> 0 | L79: =IFERROR(SUM(L80:L87)/L77,0) -> 0 | M79: =IFERROR(SUM(M80:M87)/M77,0) -> 0 | ... Q79: =IFERROR(SUM(Q80:Q87)/Q77,0) -> 0 | R79: =AVERAGEA(F79:Q79) -> 0
B80: Phòng 5S & an toàn | C80: 6421002604 | D80: Chi phí lương chính - Gián tiếp | E80: Salary and Wages - Direct | R80: =SUM(F80:Q80) -> 0
B81: Phòng 5S & an toàn | C81: 6421002605 | D81: Chi phí lương T13, phép năm - Gián tiếp | E81: Salary and Wages - Support | R81: =SUM(F81:Q81) -> 0
B82: Phòng 5S & an toàn | C82: 6421002802 | D82: Chi phí khen thưởng - Gián tiếp | E82: Employee Welfare | R82: =SUM(F82:Q82) -> 0
B83: Phòng 5S & an toàn | C83: 6421002806 | D83: Thưởng danh hiệu | E83: Salary and Wages - Support | R83: =SUM(F83:Q83) -> 0
B84: Phòng 5S & an toàn | C84: 6421007202 | D84: Chi phí khen thưởng, bồi dưỡng khác | E84: Employee Welfare | R84: =SUM(F84:Q84) -> 0
B85: Phòng 5S & an toàn | C85: 6421003202 | D85: Tiền ăn giữa ca - Gián tiếp | E85: Employee Welfare | R85: =SUM(F85:Q85) -> 0
B86: Phòng 5S & an toàn | C86: 6421002603 | D86: Phụ cấp ca đêm - Gián tiếp | E86: Salary and Wages - Support | R86: =SUM(F86:Q86) -> 0
B87: Phòng 5S & an toàn | C87: 6421003401 | D87: BHXH, BHYT, KPCĐ, BHTN - Gián tiếp | E87: Employee Welfare | R87: =SUM(F87:Q87) -> 0
B88: Phòng 5S & an toàn | C88: 6421002703 | D88: Chi phí lương ngoài giờ - Gián tiếp | E88: Salary and Wages - Support | R88: =SUM(F88:Q88) -> 0
B89: Phòng Cung ứng | D89: Số lượng nhân sự
B90: Phòng Cung ứng | D90: ADM_Lương Khối Quản Lý | F90: =SUM(F92:F99) -> 0 | G90: =SUM(G92:G99) -> 0 | H90: =SUM(H92:H99) -> 0 | I90: =SUM(I92:I99) -> 0 | J90: =SUM(J92:J99) -> 0 | K90: =SUM(K92:K99) -> 0 | L90: =SUM(L92:L99) -> 0 | M90: =SUM(M92:M99) -> 0 | ... Q90: =SUM(Q92:Q99) -> 0 | R90: =SUM(F90:Q90) -> 0
B91: Phòng Cung ứng | D91: Chi phí lương TB/1 Người | F91: =IFERROR(SUM(F92:F99)/F89,0) -> 0 | G91: =IFERROR(SUM(G92:G99)/G89,0) -> 0 | H91: =IFERROR(SUM(H92:H99)/H89,0) -> 0 | I91: =IFERROR(SUM(I92:I99)/I89,0) -> 0 | J91: =IFERROR(SUM(J92:J99)/J89,0) -> 0 | K91: =IFERROR(SUM(K92:K99)/K89,0) -> 0 | L91: =IFERROR(SUM(L92:L99)/L89,0) -> 0 | M91: =IFERROR(SUM(M92:M99)/M89,0) -> 0 | ... Q91: =IFERROR(SUM(Q92:Q99)/Q89,0) -> 0 | R91: =AVERAGEA(F91:Q91) -> 0
B92: Phòng Cung ứng | C92: 6421002604 | D92: Chi phí lương chính - Gián tiếp | E92: Salary and Wages - Direct | R92: =SUM(F92:Q92) -> 0
B93: Phòng Cung ứng | C93: 6421002605 | D93: Chi phí lương T13, phép năm - Gián tiếp | E93: Salary and Wages - Support | R93: =SUM(F93:Q93) -> 0
B94: Phòng Cung ứng | C94: 6421002802 | D94: Chi phí khen thưởng - Gián tiếp | E94: Employee Welfare | R94: =SUM(F94:Q94) -> 0
B95: Phòng Cung ứng | C95: 6421002806 | D95: Thưởng danh hiệu | E95: Salary and Wages - Support | R95: =SUM(F95:Q95) -> 0
B96: Phòng Cung ứng | C96: 6421007202 | D96: Chi phí khen thưởng, bồi dưỡng khác | E96: Employee Welfare | R96: =SUM(F96:Q96) -> 0
B97: Phòng Cung ứng | C97: 6421003202 | D97: Tiền ăn giữa ca - Gián tiếp | E97: Employee Welfare | R97: =SUM(F97:Q97) -> 0
B98: Phòng Cung ứng | C98: 6421002603 | D98: Phụ cấp ca đêm - Gián tiếp | E98: Salary and Wages - Support | R98: =SUM(F98:Q98) -> 0
B99: Phòng Cung ứng | C99: 6421003401 | D99: BHXH, BHYT, KPCĐ, BHTN - Gián tiếp | E99: Employee Welfare | R99: =SUM(F99:Q99) -> 0
B100: Phòng Cung ứng | C100: 6421002703 | D100: Chi phí lương ngoài giờ - Gián tiếp | E100: Salary and Wages - Support | R100: =SUM(F100:Q100) -> 0
B101: Phòng mua XNK | D101: Số lượng nhân sự
B102: Phòng mua XNK | D102: ADM_Lương Khối Quản Lý | F102: =SUM(F104:F111) -> 0 | G102: =SUM(G104:G111) -> 0 | H102: =SUM(H104:H111) -> 0 | I102: =SUM(I104:I111) -> 0 | J102: =SUM(J104:J111) -> 0 | K102: =SUM(K104:K111) -> 0 | L102: =SUM(L104:L111) -> 0 | M102: =SUM(M104:M111) -> 0 | ... Q102: =SUM(Q104:Q111) -> 0 | R102: =SUM(F102:Q102) -> 0
...

Sheet Luong_HCNS
B1: #VALUE!
B3: I - CHI PHÍ LƯƠNG - PET | S3: ĐVT: Triệu đồng
B4: STT | C4: Phòng ban | D4: Phân loại | E4: Lương BQ/người/ tháng | F4: KHNS 2025 đã duyệt | G4: T1 | H4: T2 | I4: T3 | J4: T4 | K4: T5 | L4: T6 | M4: T7 | N4: T8 | O4: T9 | P4: T10 | Q4: T11 | R4: T12 | S4: Mục tiêu 2026
B5: I | C5: BAN GIÁM ĐỐC (642) | F5: =F6+F7 -> 60000000 | G5: =G6+G7 -> 60000000 | H5: =H6+H7 -> 60000000 | I5: =I6+I7 -> 60000000 | J5: =J6+J7 -> 60000000 | K5: =K6+K7 -> 60000000 | L5: =L6+L7 -> 60000000 | M5: =M6+M7 -> 60000000 | ... R5: =R6+R7 -> 60000000 | S5: =SUM(G5:R5) -> 720000000
B6: 1 | C6: Giám đốc | D6: Định phí | E6: 60000000 | F6: =$E6*'Dinh bien_HCNS'!G6 -> 60000000 | G6: =$E6*'Dinh bien_HCNS'!H6 -> 60000000 | H6: =$E6*'Dinh bien_HCNS'!I6 -> 60000000 | I6: =$E6*'Dinh bien_HCNS'!J6 -> 60000000 | J6: =$E6*'Dinh bien_HCNS'!K6 -> 60000000 | K6: =$E6*'Dinh bien_HCNS'!L6 -> 60000000 | L6: =$E6*'Dinh bien_HCNS'!M6 -> 60000000 | M6: =$E6*'Dinh bien_HCNS'!N6 -> 60000000 | ... R6: =$E6*'Dinh bien_HCNS'!S6 -> 60000000 | S6: =SUM(G6:R6) -> 720000000
B7: 2 | C7: Phó giám đốc | D7: Định phí | F7: =$E7*'Dinh bien_HCNS'!G7 -> 0 | G7: =$E7*'Dinh bien_HCNS'!H7 -> 0 | H7: =$E7*'Dinh bien_HCNS'!I7 -> 0 | I7: =$E7*'Dinh bien_HCNS'!J7 -> 0 | J7: =$E7*'Dinh bien_HCNS'!K7 -> 0 | K7: =$E7*'Dinh bien_HCNS'!L7 -> 0 | L7: =$E7*'Dinh bien_HCNS'!M7 -> 0 | M7: =$E7*'Dinh bien_HCNS'!N7 -> 0 | ... R7: =$E7*'Dinh bien_HCNS'!S7 -> 0 | S7: =SUM(G7:R7) -> 0
B8: II | C8: VĂN PHÒNG GIÁM ĐỐC (642) | F8: =F9+F10+F11 -> #REF! | G8: =G9+G10+G11 -> #REF! | H8: =H9+H10+H11 -> #REF! | I8: =I9+I10+I11 -> #REF! | J8: =J9+J10+J11 -> #REF! | K8: =K9+K10+K11 -> #REF! | L8: =L9+L10+L11 -> #REF! | M8: =M9+M10+M11 -> #REF! | ... R8: =R9+R10+R11 -> #REF! | S8: =SUM(G8:R8) -> #REF!
B9: 1 | C9: Trợ lý giám đốc | D9: Định phí | F9: =$E9*'Dinh bien_HCNS'!#REF! -> #REF! | G9: =$E9*'Dinh bien_HCNS'!#REF! -> #REF! | H9: =$E9*'Dinh bien_HCNS'!#REF! -> #REF! | I9: =$E9*'Dinh bien_HCNS'!#REF! -> #REF! | J9: =$E9*'Dinh bien_HCNS'!#REF! -> #REF! | K9: =$E9*'Dinh bien_HCNS'!#REF! -> #REF! | L9: =$E9*'Dinh bien_HCNS'!#REF! -> #REF! | M9: =$E9*'Dinh bien_HCNS'!#REF! -> #REF! | ... R9: =$E9*'Dinh bien_HCNS'!#REF! -> #REF! | S9: =SUM(G9:R9) -> #REF!
B10: 2 | C10: Quản trị hệ thống | D10: Định phí | F10: =$E10*'Dinh bien_HCNS'!#REF! -> #REF! | G10: =$E10*'Dinh bien_HCNS'!#REF! -> #REF! | H10: =$E10*'Dinh bien_HCNS'!#REF! -> #REF! | I10: =$E10*'Dinh bien_HCNS'!#REF! -> #REF! | J10: =$E10*'Dinh bien_HCNS'!#REF! -> #REF! | K10: =$E10*'Dinh bien_HCNS'!#REF! -> #REF! | L10: =$E10*'Dinh bien_HCNS'!#REF! -> #REF! | M10: =$E10*'Dinh bien_HCNS'!#REF! -> #REF! | ... R10: =$E10*'Dinh bien_HCNS'!#REF! -> #REF! | S10: =SUM(G10:R10) -> #REF!
B11: 3 | C11: Ban An Toàn và 5S | D11: Định phí | E11: 14157445 | F11: =$E11*'Dinh bien_HCNS'!#REF! -> #REF! | G11: =$E11*'Dinh bien_HCNS'!#REF! -> #REF! | H11: =$E11*'Dinh bien_HCNS'!#REF! -> #REF! | I11: =$E11*'Dinh bien_HCNS'!#REF! -> #REF! | J11: =$E11*'Dinh bien_HCNS'!#REF! -> #REF! | K11: =$E11*'Dinh bien_HCNS'!#REF! -> #REF! | L11: =$E11*'Dinh bien_HCNS'!#REF! -> #REF! | M11: =$E11*'Dinh bien_HCNS'!#REF! -> #REF! | ... R11: =$E11*'Dinh bien_HCNS'!#REF! -> #REF! | S11: =SUM(G11:R11) -> #REF!
B12: III | C12: CUNG ỨNG (642) | F12: =F13 -> 0 | G12: =G13 -> 0 | H12: =H13 -> 0 | I12: =I13 -> 0 | J12: =J13 -> 0 | K12: =K13 -> 0 | L12: =L13 -> 0 | M12: =M13 -> 0 | ... R12: =R13 -> 0 | S12: =SUM(G12:R12) -> 0
B13: 1 | C13: Nhân viên mua hàng | D13: Định phí | E13: 13102591 | F13: =$E13*'Dinh bien_HCNS'!G77 -> 0 | G13: =$E13*'Dinh bien_HCNS'!H77 -> 0 | H13: =$E13*'Dinh bien_HCNS'!I77 -> 0 | I13: =$E13*'Dinh bien_HCNS'!J77 -> 0 | J13: =$E13*'Dinh bien_HCNS'!K77 -> 0 | K13: =$E13*'Dinh bien_HCNS'!L77 -> 0 | L13: =$E13*'Dinh bien_HCNS'!M77 -> 0 | M13: =$E13*'Dinh bien_HCNS'!N77 -> 0 | ... R13: =$E13*'Dinh bien_HCNS'!S77 -> 0 | S13: =SUM(G13:R13) -> 0
B14: IV | C14: HÀNH CHÍNH NHÂN SỰ (642) | F14: =F15+F16+F17+F18+F19+F20 -> 10000000 | G14: =G15+G16+G17+G18+G19+G20 -> 10000000 | H14: =H15+H16+H17+H18+H19+H20 -> 10000000 | I14: =I15+I16+I17+I18+I19+I20 -> 10000000 | J14: =J15+J16+J17+J18+J19+J20 -> 10000000 | K14: =K15+K16+K17+K18+K19+K20 -> 10000000 | L14: =L15+L16+L17+L18+L19+L20 -> 10000000 | M14: =M15+M16+M17+M18+M19+M20 -> 10000000 | ... R14: =R15+R16+R17+R18+R19+R20 -> 10000000 | S14: =SUM(G14:R14) -> 120000000
B15: 1 | C15: Hành chính | D15: Định phí | E15: 8000000 | F15: =$E15*'Dinh bien_HCNS'!G10 -> 0 | G15: =$E15*'Dinh bien_HCNS'!H10 -> 0 | H15: =$E15*'Dinh bien_HCNS'!I10 -> 0 | I15: =$E15*'Dinh bien_HCNS'!J10 -> 0 | J15: =$E15*'Dinh bien_HCNS'!K10 -> 0 | K15: =$E15*'Dinh bien_HCNS'!L10 -> 0 | L15: =$E15*'Dinh bien_HCNS'!M10 -> 0 | M15: =$E15*'Dinh bien_HCNS'!N10 -> 0 | ... R15: =$E15*'Dinh bien_HCNS'!S10 -> 0 | S15: =SUM(G15:R15) -> 0
B16: 2 | C16: Nhân sự | D16: Định phí | E16: 10000000 | F16: =$E16*'Dinh bien_HCNS'!G11 -> 10000000 | G16: =$E16*'Dinh bien_HCNS'!H11 -> 10000000 | H16: =$E16*'Dinh bien_HCNS'!I11 -> 10000000 | I16: =$E16*'Dinh bien_HCNS'!J11 -> 10000000 | J16: =$E16*'Dinh bien_HCNS'!K11 -> 10000000 | K16: =$E16*'Dinh bien_HCNS'!L11 -> 10000000 | L16: =$E16*'Dinh bien_HCNS'!M11 -> 10000000 | M16: =$E16*'Dinh bien_HCNS'!N11 -> 10000000 | ... R16: =$E16*'Dinh bien_HCNS'!S11 -> 10000000 | S16: =SUM(G16:R16) -> 120000000
B17: 3 | C17: Tuyển dụng | D17: Định phí | F17: =$E17*'Dinh bien_HCNS'!G12 -> 0 | G17: =$E17*'Dinh bien_HCNS'!H12 -> 0 | H17: =$E17*'Dinh bien_HCNS'!I12 -> 0 | I17: =$E17*'Dinh bien_HCNS'!J12 -> 0 | J17: =$E17*'Dinh bien_HCNS'!K12 -> 0 | K17: =$E17*'Dinh bien_HCNS'!L12 -> 0 | L17: =$E17*'Dinh bien_HCNS'!M12 -> 0 | M17: =$E17*'Dinh bien_HCNS'!N12 -> 0 | ... R17: =$E17*'Dinh bien_HCNS'!S12 -> 0 | S17: =SUM(G17:R17) -> 0
B18: 4 | C18: Tạp vụ | D18: Định phí | E18: 7000000 | F18: =$E18*'Dinh bien_HCNS'!G13 -> 0 | G18: =$E18*'Dinh bien_HCNS'!H13 -> 0 | H18: =$E18*'Dinh bien_HCNS'!I13 -> 0 | I18: =$E18*'Dinh bien_HCNS'!J13 -> 0 | J18: =$E18*'Dinh bien_HCNS'!K13 -> 0 | K18: =$E18*'Dinh bien_HCNS'!L13 -> 0 | L18: =$E18*'Dinh bien_HCNS'!M13 -> 0 | M18: =$E18*'Dinh bien_HCNS'!N13 -> 0 | ... R18: =$E18*'Dinh bien_HCNS'!S13 -> 0 | S18: =SUM(G18:R18) -> 0
B19: 5 | C19: Bảo vệ | D19: Định phí | F19: =$E19*'Dinh bien_HCNS'!G14 -> 0 | G19: =$E19*'Dinh bien_HCNS'!H14 -> 0 | H19: =$E19*'Dinh bien_HCNS'!I14 -> 0 | I19: =$E19*'Dinh bien_HCNS'!J14 -> 0 | J19: =$E19*'Dinh bien_HCNS'!K14 -> 0 | K19: =$E19*'Dinh bien_HCNS'!L14 -> 0 | L19: =$E19*'Dinh bien_HCNS'!M14 -> 0 | M19: =$E19*'Dinh bien_HCNS'!N14 -> 0 | ... R19: =$E19*'Dinh bien_HCNS'!S14 -> 0 | S19: =SUM(G19:R19) -> 0
B20: 6 | C20: Chăm sóc cây xanh | D20: Định phí | F20: =$E20*'Dinh bien_HCNS'!G16 -> 0 | G20: =$E20*'Dinh bien_HCNS'!H16 -> 0 | H20: =$E20*'Dinh bien_HCNS'!I16 -> 0 | I20: =$E20*'Dinh bien_HCNS'!J16 -> 0 | J20: =$E20*'Dinh bien_HCNS'!K16 -> 0 | K20: =$E20*'Dinh bien_HCNS'!L16 -> 0 | L20: =$E20*'Dinh bien_HCNS'!M16 -> 0 | M20: =$E20*'Dinh bien_HCNS'!N16 -> 0 | ... R20: =$E20*'Dinh bien_HCNS'!S16 -> 0 | S20: =SUM(G20:R20) -> 0
B21: V | C21: KẾ TOÁN (642) | F21: =F22+F23+F24 -> 40000000 | G21: =G22+G23+G24 -> 12000000 | H21: =H22+H23+H24 -> 12000000 | I21: =I22+I23+I24 -> 40000000 | J21: =J22+J23+J24 -> 40000000 | K21: =K22+K23+K24 -> 40000000 | L21: =L22+L23+L24 -> 40000000 | M21: =M22+M23+M24 -> 40000000 | ... R21: =R22+R23+R24 -> 40000000 | S21: =SUM(G21:R21) -> 424000000
B22: 1 | C22: Kế toán trưởng | D22: Định phí | E22: 28000000 | F22: =$E22*'Dinh bien_HCNS'!G18 -> 28000000 | I22: =$E22*'Dinh bien_HCNS'!J18 -> 28000000 | J22: =$E22*'Dinh bien_HCNS'!K18 -> 28000000 | K22: =$E22*'Dinh bien_HCNS'!L18 -> 28000000 | L22: =$E22*'Dinh bien_HCNS'!M18 -> 28000000 | M22: =$E22*'Dinh bien_HCNS'!N18 -> 28000000 | N22: =$E22*'Dinh bien_HCNS'!O18 -> 28000000 | O22: =$E22*'Dinh bien_HCNS'!P18 -> 28000000 | P22: =$E22*'Dinh bien_HCNS'!Q18 -> 28000000 | ... R22: =$E22*'Dinh bien_HCNS'!S18 -> 28000000 | S22: =SUM(G22:R22) -> 280000000
B23: 2 | C23: Kế toán tổng hợp | D23: Định phí | E23: 12000000 | F23: =$E23*'Dinh bien_HCNS'!G19 -> 12000000 | G23: =$E23*'Dinh bien_HCNS'!H19 -> 12000000 | H23: =$E23*'Dinh bien_HCNS'!I19 -> 12000000 | I23: =$E23*'Dinh bien_HCNS'!J19 -> 12000000 | J23: =$E23*'Dinh bien_HCNS'!K19 -> 12000000 | K23: =$E23*'Dinh bien_HCNS'!L19 -> 12000000 | L23: =$E23*'Dinh bien_HCNS'!M19 -> 12000000 | M23: =$E23*'Dinh bien_HCNS'!N19 -> 12000000 | ... R23: =$E23*'Dinh bien_HCNS'!S19 -> 12000000 | S23: =SUM(G23:R23) -> 144000000
B24: 3 | C24: Kế toán kho | D24: Định phí | E24: 10000000 | F24: =$E24*'Dinh bien_HCNS'!G21 -> 0 | G24: =$E24*'Dinh bien_HCNS'!H21 -> 0 | H24: =$E24*'Dinh bien_HCNS'!I21 -> 0 | I24: =$E24*'Dinh bien_HCNS'!J21 -> 0 | J24: =$E24*'Dinh bien_HCNS'!K21 -> 0 | K24: =$E24*'Dinh bien_HCNS'!L21 -> 0 | L24: =$E24*'Dinh bien_HCNS'!M21 -> 0 | M24: =$E24*'Dinh bien_HCNS'!N21 -> 0 | ... R24: =$E24*'Dinh bien_HCNS'!S21 -> 0 | S24: =SUM(G24:R24) -> 0
B25: VI | C25: XƯỞNG SẢN XUẤT | F25: =F26+F31+F32+F35 -> 43836365 | G25: =G26+G31+G32+G35 -> 4.2057532e+08 | H25: =H26+H31+H32+H35 -> 3.2638875e+08 | I25: =I26+I31+I32+I35 -> 4.5197085e+08 | J25: =J26+J31+J32+J35 -> 4.8336637e+08 | K25: =K26+K31+K32+K35 -> 4.8336637e+08 | L25: =L26+L31+L32+L35 -> 4.8336637e+08 | M25: =M26+M31+M32+M35 -> 4.8336637e+08 | ... S25: =S26+S31+S32+S35 -> 5.5492323e+09
B26: 1 | C26: Quản lý sản xuất (627) | F26: =F27+F28+F29+F30 -> 30000000 | G26: =G27+G28+G29+G30 -> 30000000 | H26: =H27+H28+H29+H30 -> 30000000 | I26: =I27+I28+I29+I30 -> 30000000 | J26: =J27+J28+J29+J30 -> 30000000 | K26: =K27+K28+K29+K30 -> 30000000 | L26: =L27+L28+L29+L30 -> 30000000 | M26: =M27+M28+M29+M30 -> 30000000 | ... R26: =R27+R28+R29+R30 -> 30000000 | S26: =SUM(G26:R26) -> 360000000
B27: a | C27: Trưởng phòng sản xuất | D27: Định phí | E27: 20000000 | F27: =$E27*'Dinh bien_HCNS'!G53 -> 20000000 | G27: =$E27*'Dinh bien_HCNS'!H53 -> 20000000 | H27: =$E27*'Dinh bien_HCNS'!I53 -> 20000000 | I27: =$E27*'Dinh bien_HCNS'!J53 -> 20000000 | J27: =$E27*'Dinh bien_HCNS'!K53 -> 20000000 | K27: =$E27*'Dinh bien_HCNS'!L53 -> 20000000 | L27: =$E27*'Dinh bien_HCNS'!M53 -> 20000000 | M27: =$E27*'Dinh bien_HCNS'!N53 -> 20000000 | ... R27: =$E27*'Dinh bien_HCNS'!S53 -> 20000000 | S27: =SUM(G27:R27) -> 240000000
B28: b | C28: Phó phòng sản xuất | D28: Định phí | F28: =$E28*'Dinh bien_HCNS'!G54 -> 0 | G28: =$E28*'Dinh bien_HCNS'!H54 -> 0 | H28: =$E28*'Dinh bien_HCNS'!I54 -> 0 | I28: =$E28*'Dinh bien_HCNS'!J54 -> 0 | J28: =$E28*'Dinh bien_HCNS'!K54 -> 0 | K28: =$E28*'Dinh bien_HCNS'!L54 -> 0 | L28: =$E28*'Dinh bien_HCNS'!M54 -> 0 | M28: =$E28*'Dinh bien_HCNS'!N54 -> 0 | ... R28: =$E28*'Dinh bien_HCNS'!S54 -> 0 | S28: =SUM(G28:R28) -> 0
B29: c | C29: Trưởng ca sản xuất (theo ca sx) | D29: Định phí | E29: 10000000 | F29: =$E29*'Dinh bien_HCNS'!G55 -> 10000000 | G29: =$E29*'Dinh bien_HCNS'!H55 -> 10000000 | H29: =$E29*'Dinh bien_HCNS'!I55 -> 10000000 | I29: =$E29*'Dinh bien_HCNS'!J55 -> 10000000 | J29: =$E29*'Dinh bien_HCNS'!K55 -> 10000000 | K29: =$E29*'Dinh bien_HCNS'!L55 -> 10000000 | L29: =$E29*'Dinh bien_HCNS'!M55 -> 10000000 | M29: =$E29*'Dinh bien_HCNS'!N55 -> 10000000 | ... R29: =$E29*'Dinh bien_HCNS'!S55 -> 10000000 | S29: =SUM(G29:R29) -> 120000000
B30: d | C30: Thống kê sản xuất | D30: Định phí | F30: =$E30*'Dinh bien_HCNS'!G56 -> 0 | G30: =$E30*'Dinh bien_HCNS'!H56 -> 0 | H30: =$E30*'Dinh bien_HCNS'!I56 -> 0 | I30: =$E30*'Dinh bien_HCNS'!J56 -> 0 | J30: =$E30*'Dinh bien_HCNS'!K56 -> 0 | K30: =$E30*'Dinh bien_HCNS'!L56 -> 0 | L30: =$E30*'Dinh bien_HCNS'!M56 -> 0 | M30: =$E30*'Dinh bien_HCNS'!N56 -> 0 | ... R30: =$E30*'Dinh bien_HCNS'!S56 -> 0 | S30: =SUM(G30:R30) -> 0
B31: 2 | C31: Bộ phận kho (627) | D31: Định phí | E31: 13829034 | F31: =$E31*'Dinh bien_HCNS'!G67 -> 13829034 | G31: =$E31*'Dinh bien_HCNS'!H67 -> 13829034 | H31: =$E31*'Dinh bien_HCNS'!I67 -> 13829034 | I31: =$E31*'Dinh bien_HCNS'!J67 -> 13829034 | J31: =$E31*'Dinh bien_HCNS'!K67 -> 13829034 | K31: =$E31*'Dinh bien_HCNS'!L67 -> 13829034 | L31: =$E31*'Dinh bien_HCNS'!M67 -> 13829034 | M31: =$E31*'Dinh bien_HCNS'!N67 -> 13829034 | ... R31: =$E31*'Dinh bien_HCNS'!S67 -> 13829034 | S31: =SUM(G31:R31) -> 165948414
B32: 3 | C32: Công nhân trực tiếp sản xuất (622) | D32: Biến phí | E32: =E33+E34 -> 705.91398 | F32: =F33+F34 -> 7330.8468 | G32: =G33+G34 -> 3.7674629e+08 | H32: =H33+H34 -> 2.8255972e+08 | I32: =I33+I34 -> 4.0814181e+08 | J32: =J33+J34 -> 4.3953734e+08 | K32: =K33+K34 -> 4.3953734e+08 | L32: =L33+L34 -> 4.3953734e+08 | ... R32: =R33+R34 -> 4.3953734e+08 | S32: =SUM(G32:R32) -> 5.0232839e+09
B33: a | C33: Lao động định biên | D33: Đồng/kg | E33: ='Dinh muc'!$G$8 -> 579.23387 | F33: =$E33*'Dinh bien_HCNS'!G58 -> 6950.8065 | G33: =$E$33*'3.Thanh pham'!H$78 -> 3.0913712e+08 | H33: =$E$33*'3.Thanh pham'!I$78 -> 2.3185284e+08 | I33: =$E$33*'3.Thanh pham'!J$78 -> 3.3489854e+08 | J33: =$E$33*'3.Thanh pham'!K$78 -> 3.6065997e+08 | K33: =$E$33*'3.Thanh pham'!L$78 -> 3.6065997e+08 | L33: =$E$33*'3.Thanh pham'!M$78 -> 3.6065997e+08 | M33: =$E$33*'3.Thanh pham'!N$78 -> 3.6065997e+08 | N33: =$E$33*'3.Thanh pham'!O$78 -> 3.6065997e+08 | ... R33: =$E$33*'3.Thanh pham'!S$78 -> 3.6065997e+08 | S33: =SUM(G33:R33) -> 4.1218282e+09
B34: b | C34: Lao động thuê ngoài | D34: Đồng/kg | E34: ='Dinh muc'!$G$9 -> 126.68011 | F34: =$E34*'Dinh bien_HCNS'!G59 -> 380.04032 | G34: =$E$34*'3.Thanh pham'!H$78 -> 67609173 | H34: =$E$34*'3.Thanh pham'!I$78 -> 50706880 | I34: =$E$34*'3.Thanh pham'!J$78 -> 73243271 | J34: =$E$34*'3.Thanh pham'!K$78 -> 78877369 | K34: =$E$34*'3.Thanh pham'!L$78 -> 78877369 | L34: =$E$34*'3.Thanh pham'!M$78 -> 78877369 | M34: =$E$34*'3.Thanh pham'!N$78 -> 78877369 | N34: =$E$34*'3.Thanh pham'!O$78 -> 78877369 | ... R34: =$E$34*'3.Thanh pham'!S$78 -> 78877369 | S34: =SUM(G34:R34) -> 9.0145565e+08
B35: 4 | C35: Công nhân trực tiếp sản xuất - Băm vảy | E35: =E36+E37 -> 18083854 | F35: =F36+F37 -> 0 | G35: =G36+G37 -> 0 | H35: =H36+H37 -> 0 | I35: =I36+I37 -> 0 | J35: =J36+J37 -> 0 | K35: =K36+K37 -> 0 | L35: =L36+L37 -> 0 | ... R35: =R36+R37 -> 0 | S35: =SUM(G35:R35) -> 0
B36: a | C36: Lao động định biên | E36: 11083854 | F36: =$E36*'Dinh bien_HCNS'!G65 -> 0 | G36: =$E36*'Dinh bien_HCNS'!H65 -> 0 | H36: =$E36*'Dinh bien_HCNS'!I65 -> 0 | I36: =$E36*'Dinh bien_HCNS'!J65 -> 0 | J36: =$E36*'Dinh bien_HCNS'!K65 -> 0 | K36: =$E36*'Dinh bien_HCNS'!L65 -> 0 | L36: =$E36*'Dinh bien_HCNS'!M65 -> 0 | M36: =$E36*'Dinh bien_HCNS'!N65 -> 0 | ... R36: =$E36*'Dinh bien_HCNS'!S65 -> 0 | S36: =SUM(G36:R36) -> 0
B37: b | C37: Lao động thuê ngoài | E37: 7000000 | F37: =$E37*'Dinh bien_HCNS'!G66 -> 0 | G37: =$E37*'Dinh bien_HCNS'!H66 -> 0 | H37: =$E37*'Dinh bien_HCNS'!I66 -> 0 | I37: =$E37*'Dinh bien_HCNS'!J66 -> 0 | J37: =$E37*'Dinh bien_HCNS'!K66 -> 0 | K37: =$E37*'Dinh bien_HCNS'!L66 -> 0 | L37: =$E37*'Dinh bien_HCNS'!M66 -> 0 | M37: =$E37*'Dinh bien_HCNS'!N66 -> 0 | ... R37: =$E37*'Dinh bien_HCNS'!S66 -> 0 | S37: =SUM(G37:R37) -> 0
B38: VII | C38: KỸ THUẬT (627) | F38: =SUM(F39:F45) -> 21000000 | G38: =SUM(G39:G45) -> 21000000 | H38: =SUM(H39:H45) -> 21000000 | I38: =SUM(I39:I45) -> 21000000 | J38: =SUM(J39:J45) -> 21000000 | K38: =SUM(K39:K45) -> 21000000 | L38: =SUM(L39:L45) -> 21000000 | M38: =SUM(M39:M45) -> 21000000 | ... R38: =SUM(R39:R45) -> 21000000 | S38: =SUM(G38:R38) -> 252000000
B39: 1 | C39: Văn phòng kỹ thuật | D39: Định phí | F39: =$E39*'Dinh bien_HCNS'!G44 -> 0 | G39: =$E39*'Dinh bien_HCNS'!H44 -> 0 | H39: =$E39*'Dinh bien_HCNS'!I44 -> 0 | I39: =$E39*'Dinh bien_HCNS'!J44 -> 0 | J39: =$E39*'Dinh bien_HCNS'!K44 -> 0 | K39: =$E39*'Dinh bien_HCNS'!L44 -> 0 | L39: =$E39*'Dinh bien_HCNS'!M44 -> 0 | M39: =$E39*'Dinh bien_HCNS'!N44 -> 0 | ... R39: =$E39*'Dinh bien_HCNS'!S44 -> 0 | S39: =SUM(G39:R39) -> 0
B40: 2 | C40: Bảo trì MMTB, thay dao | D40: Định phí | E40: 7000000 | F40: =$E40*'Dinh bien_HCNS'!G45 -> 0 | G40: =$E40*'Dinh bien_HCNS'!H45 -> 0 | H40: =$E40*'Dinh bien_HCNS'!I45 -> 0 | I40: =$E40*'Dinh bien_HCNS'!J45 -> 0 | J40: =$E40*'Dinh bien_HCNS'!K45 -> 0 | K40: =$E40*'Dinh bien_HCNS'!L45 -> 0 | L40: =$E40*'Dinh bien_HCNS'!M45 -> 0 | M40: =$E40*'Dinh bien_HCNS'!N45 -> 0 | ... R40: =$E40*'Dinh bien_HCNS'!S45 -> 0 | S40: =SUM(G40:R40) -> 0
B41: 3 | C41: Vận hành MMTB (theo ca sx) | D41: Biến phí | E41: 10000000 | F41: =$E41*'Dinh bien_HCNS'!G46 -> 0 | G41: =$E41*'Dinh bien_HCNS'!H46 -> 0 | H41: =$E41*'Dinh bien_HCNS'!I46 -> 0 | I41: =$E41*'Dinh bien_HCNS'!J46 -> 0 | J41: =$E41*'Dinh bien_HCNS'!K46 -> 0 | K41: =$E41*'Dinh bien_HCNS'!L46 -> 0 | L41: =$E41*'Dinh bien_HCNS'!M46 -> 0 | M41: =$E41*'Dinh bien_HCNS'!N46 -> 0 | ... R41: =$E41*'Dinh bien_HCNS'!S46 -> 0 | S41: =SUM(G41:R41) -> 0
B42: 4 | C42: Tự động hóa | D42: Định phí | E42: 7000000 | F42: =$E42*'Dinh bien_HCNS'!G47 -> 14000000 | G42: =$E42*'Dinh bien_HCNS'!H47 -> 7000000 | H42: =$E42*'Dinh bien_HCNS'!I47 -> 7000000 | I42: =$E42*'Dinh bien_HCNS'!J47 -> 7000000 | J42: =$E42*'Dinh bien_HCNS'!K47 -> 7000000 | K42: =$E42*'Dinh bien_HCNS'!L47 -> 7000000 | L42: =$E42*'Dinh bien_HCNS'!M47 -> 7000000 | M42: =$E42*'Dinh bien_HCNS'!N47 -> 7000000 | ... R42: =$E42*'Dinh bien_HCNS'!S47 -> 7000000 | S42: =SUM(G42:R42) -> 84000000
B43: 5 | C43: Điện, nước sản xuất | D43: Định phí | E43: 7000000 | F43: =$E43*'Dinh bien_HCNS'!G48 -> 7000000 | G43: =$E43*'Dinh bien_HCNS'!H48 -> 14000000 | H43: =$E43*'Dinh bien_HCNS'!I48 -> 14000000 | I43: =$E43*'Dinh bien_HCNS'!J48 -> 14000000 | J43: =$E43*'Dinh bien_HCNS'!K48 -> 14000000 | K43: =$E43*'Dinh bien_HCNS'!L48 -> 14000000 | L43: =$E43*'Dinh bien_HCNS'!M48 -> 14000000 | M43: =$E43*'Dinh bien_HCNS'!N48 -> 14000000 | ... R43: =$E43*'Dinh bien_HCNS'!S48 -> 14000000 | S43: =SUM(G43:R43) -> 168000000
B44: 6 | C44: Xử lý nước thải | D44: Định phí | E44: 10000000 | F44: =$E44*'Dinh bien_HCNS'!G49 -> 0 | G44: =$E44*'Dinh bien_HCNS'!H49 -> 0 | H44: =$E44*'Dinh bien_HCNS'!I49 -> 0 | I44: =$E44*'Dinh bien_HCNS'!J49 -> 0 | J44: =$E44*'Dinh bien_HCNS'!K49 -> 0 | K44: =$E44*'Dinh bien_HCNS'!L49 -> 0 | L44: =$E44*'Dinh bien_HCNS'!M49 -> 0 | M44: =$E44*'Dinh bien_HCNS'!N49 -> 0 | ... R44: =$E44*'Dinh bien_HCNS'!S49 -> 0 | S44: =SUM(G44:R44) -> 0
B45: 7 | C45: Thống kê kỹ thuật | D45: Định phí | E45: 7000000 | F45: =$E45*'Dinh bien_HCNS'!G50 -> 0 | G45: =$E45*'Dinh bien_HCNS'!H50 -> 0 | H45: =$E45*'Dinh bien_HCNS'!I50 -> 0 | I45: =$E45*'Dinh bien_HCNS'!J50 -> 0 | J45: =$E45*'Dinh bien_HCNS'!K50 -> 0 | K45: =$E45*'Dinh bien_HCNS'!L50 -> 0 | L45: =$E45*'Dinh bien_HCNS'!M50 -> 0 | M45: =$E45*'Dinh bien_HCNS'!N50 -> 0 | ... R45: =$E45*'Dinh bien_HCNS'!S50 -> 0 | S45: =SUM(G45:R45) -> 0
B46: VIII | C46: KIỂM SOÁT CHẤT LƯỢNG (627) | F46: =F47+F48 -> 5000000 | G46: =G47+G48 -> 11500000 | H46: =H47+H48 -> 11500000 | I46: =I47+I48 -> 11500000 | J46: =J47+J48 -> 11500000 | K46: =K47+K48 -> 11500000 | L46: =L47+L48 -> 11500000 | M46: =M47+M48 -> 11500000 | ... R46: =R47+R48 -> 11500000 | S46: =SUM(G46:R46) -> 138000000
B47: 1 | C47: Kiểm soát NVL | D47: Định phí | E47: 5000000 | F47: =$E47*'Dinh bien_HCNS'!G41 -> 5000000 | G47: =$E47*'Dinh bien_HCNS'!H41 -> 5000000 | H47: =$E47*'Dinh bien_HCNS'!I41 -> 5000000 | I47: =$E47*'Dinh bien_HCNS'!J41 -> 5000000 | J47: =$E47*'Dinh bien_HCNS'!K41 -> 5000000 | K47: =$E47*'Dinh bien_HCNS'!L41 -> 5000000 | L47: =$E47*'Dinh bien_HCNS'!M41 -> 5000000 | M47: =$E47*'Dinh bien_HCNS'!N41 -> 5000000 | ... R47: =$E47*'Dinh bien_HCNS'!S41 -> 5000000 | S47: =SUM(G47:R47) -> 60000000
B48: 2 | C48: Kiểm soát thành phẩm | D48: Định phí | E48: 6500000 | F48: =$E48*'Dinh bien_HCNS'!G42 -> 0 | G48: =$E48*'Dinh bien_HCNS'!H42 -> 6500000 | H48: =$E48*'Dinh bien_HCNS'!I42 -> 6500000 | I48: =$E48*'Dinh bien_HCNS'!J42 -> 6500000 | J48: =$E48*'Dinh bien_HCNS'!K42 -> 6500000 | K48: =$E48*'Dinh bien_HCNS'!L42 -> 6500000 | L48: =$E48*'Dinh bien_HCNS'!M42 -> 6500000 | M48: =$E48*'Dinh bien_HCNS'!N42 -> 6500000 | ... R48: =$E48*'Dinh bien_HCNS'!S42 -> 6500000 | S48: =SUM(G48:R48) -> 78000000
C49: TỔNG: | F49: =F5+F8+F12+F14+F21+F25+F38+F46 -> #REF! | G49: =G5+G8+G12+G14+G21+G25+G38+G46 -> #REF! | H49: =H5+H8+H12+H14+H21+H25+H38+H46 -> #REF! | I49: =I5+I8+I12+I14+I21+I25+I38+I46 -> #REF! | J49: =J5+J8+J12+J14+J21+J25+J38+J46 -> #REF! | K49: =K5+K8+K12+K14+K21+K25+K38+K46 -> #REF! | L49: =L5+L8+L12+L14+L21+L25+L38+L46 -> #REF! | M49: =M5+M8+M12+M14+M21+M25+M38+M46 -> #REF! | ... R49: =R5+R8+R12+R14+R21+R25+R38+R46 -> #REF! | S49: =SUM(G49:R49) -> #REF!
C50: Trong đó: Định phí | F50: =F49-F51 -> #REF! | G50: =G49-G51 -> #REF! | H50: =H49-H51 -> #REF! | I50: =I49-I51 -> #REF! | J50: =J49-J51 -> #REF! | K50: =K49-K51 -> #REF! | L50: =L49-L51 -> #REF! | M50: =M49-M51 -> #REF! | ... R50: =R49-R51 -> #REF! | S50: =SUM(G50:R50) -> #REF!
C51: Biến phí | F51: =F29+F31+F32+F41 -> 23836365 | G51: =G29+G31+G32+G41 -> 4.0057532e+08 | H51: =H29+H31+H32+H41 -> 3.0638875e+08 | I51: =I29+I31+I32+I41 -> 4.3197085e+08 | J51: =J29+J31+J32+J41 -> 4.6336637e+08 | K51: =K29+K31+K32+K41 -> 4.6336637e+08 | L51: =L29+L31+L32+L41 -> 4.6336637e+08 | M51: =M29+M31+M32+M41 -> 4.6336637e+08 | ... R51: =R29+R31+R32+R41 -> 4.6336637e+08 | S51: =SUM(G51:R51) -> 5.3092323e+09
C53: TỔNG: | F53: =F49 -> #REF! | G53: =G49 -> #REF! | H53: =H49 -> #REF! | I53: =I49 -> #REF! | J53: =J49 -> #REF! | K53: =K49 -> #REF! | L53: =L49 -> #REF! | M53: =M49 -> #REF! | ... S53: =S49 -> #REF!
C54: Trong đó: 622 | F54: =F32+F35 -> 7330.8468 | G54: =G32+G35 -> 3.7674629e+08 | H54: =H32+H35 -> 2.8255972e+08 | I54: =I32+I35 -> 4.0814181e+08 | J54: =J32+J35 -> 4.3953734e+08 | K54: =K32+K35 -> 4.3953734e+08 | L54: =L32+L35 -> 4.3953734e+08 | M54: =M32+M35 -> 4.3953734e+08 | ... S54: =S32+S35 -> 5.0232839e+09
C55: 627 | F55: =F26+F31+F38+F46 -> 69829034 | G55: =G26+G31+G38+G46 -> 76329034 | H55: =H26+H31+H38+H46 -> 76329034 | I55: =I26+I31+I38+I46 -> 76329034 | J55: =J26+J31+J38+J46 -> 76329034 | K55: =K26+K31+K38+K46 -> 76329034 | L55: =L26+L31+L38+L46 -> 76329034 | M55: =M26+M31+M38+M46 -> 76329034 | ... S55: =S26+S31+S38+S46 -> 915948414 | U55: =K55-J55 -> 0
C56: 642 | F56: =F5+F8+F12+F14+F21 -> #REF! | G56: =G5+G8+G12+G14+G21 -> #REF! | H56: =H5+H8+H12+H14+H21 -> #REF! | I56: =I5+I8+I12+I14+I21 -> #REF! | J56: =J5+J8+J12+J14+J21 -> #REF! | K56: =K5+K8+K12+K14+K21 -> #REF! | L56: =L5+L8+L12+L14+L21 -> #REF! | M56: =M5+M8+M12+M14+M21 -> #REF! | ... S56: =S5+S8+S12+S14+S21 -> #REF!
B58: II - CHI PHÍ LƯƠNG - HD
B59: VI | C59: XƯỞNG SẢN XUẤT | D59: =D4 -> Phân loại | E59: =E4 -> Lương BQ/người/ tháng | F59: =F4 -> KHNS 2025 đã duyệt | G59: =G4 -> T1 | H59: =H4 -> T2 | I59: =I4 -> T3 | J59: =J4 -> T4 | K59: =K4 -> T5 | ... S59: =S4 -> Mục tiêu 2026
B60: 1 | C60: Quản lý sản xuất (627)
C61: Trưởng ca sản xuất (theo ca sx) | D61: Định phí | E61: 15000000 | F61: =$E61*'Dinh bien_HCNS'!G94 -> 0 | G61: =$E61*'Dinh bien_HCNS'!H85 -> 0 | H61: =$E61*'Dinh bien_HCNS'!I85 -> 0 | I61: =$E61*'Dinh bien_HCNS'!J85 -> 0 | J61: =$E61*'Dinh bien_HCNS'!K85 -> 0 | K61: =$E61*'Dinh bien_HCNS'!L85 -> 0 | L61: =$E61*'Dinh bien_HCNS'!M85 -> 0 | M61: =$E61*'Dinh bien_HCNS'!N85 -> 0 | N61: =$E61*'Dinh bien_HCNS'!O85 -> 0 | ... R61: =$E61*'Dinh bien_HCNS'!S85 -> 0 | S61: =SUM(G61:R61) -> 0
B62: 2 | C62: Công nhân trực tiếp sản xuất (622) | D62: Biến phí | E62: 12000000 | G62: =$E62*'Dinh bien_HCNS'!H86 -> 0 | H62: =$E62*'Dinh bien_HCNS'!I86 -> 0 | I62: =$E62*'Dinh bien_HCNS'!J86 -> 0 | J62: =$E62*'Dinh bien_HCNS'!K86 -> 0 | K62: =$E62*'Dinh bien_HCNS'!L86 -> 0 | L62: =$E62*'Dinh bien_HCNS'!M86 -> 0 | M62: =$E62*'Dinh bien_HCNS'!N86 -> 0 | N62: =$E62*'Dinh bien_HCNS'!O86 -> 0 | ... R62: =$E62*'Dinh bien_HCNS'!S86 -> 0 | S62: =SUM(G62:R62) -> 0
C63: TỔNG: | G63: =G61+G62 -> 0 | H63: =H61+H62 -> 0 | I63: =I61+I62 -> 0 | J63: =J61+J62 -> 0 | K63: =K61+K62 -> 0 | L63: =L61+L62 -> 0 | M63: =M61+M62 -> 0 | N63: =N61+N62 -> 0 | ... R63: =R61+R62 -> 0 | S63: =SUM(G63:R63) -> 0

Sheet 4.Doanh thu
B3: DOANH THU
B4: I - DOANH THU CHAI PET
B5: 1. Sản lượng bán chai
B6: STT | C6: Thành phẩm (chai sau phân loại) | D6: ĐVT | E6: Tỷ lệ | F6: T1 | G6: T2 | H6: T3 | I6: T4 | J6: T5 | K6: T6 | L6: T7 | M6: T8 | N6: T9 | O6: T10 | P6: T11 | Q6: T12 | R6: Kế hoạch 2026 | T6: T1 | U6: T2 | V6: T3 | W6: T4 | X6: T5 | Y6: T6 | Z6: T7 | AA6: T8 | AB6: T9 | AC6: T10 | AD6: T11 | AE6: T12 | AF6: KQKD 2025 | AH6: KQKD 2024 | AJ6: KQKD 2023 | AL6: +/- 2026 sv 2025 | AM6: +/- %
B7: 1 | C7: Chai PET B1 | D7: Tấn | E7: =R7/$R$22 -> 0.53175942 | F7: ='3.Thanh pham'!H82 -> 283800 | G7: ='3.Thanh pham'!I82 -> 212850 | H7: ='3.Thanh pham'!J82 -> 307450 | I7: ='3.Thanh pham'!K82 -> 331100 | J7: ='3.Thanh pham'!L82 -> 331100 | K7: ='3.Thanh pham'!M82 -> 331100 | L7: ='3.Thanh pham'!N82 -> 331100 | M7: ='3.Thanh pham'!O82 -> 331100 | ... Q7: ='3.Thanh pham'!S82 -> 331100 | R7: =SUM(F7:Q7) -> 3784000 | T7: 121846 | U7: 99642 | V7: 105984 | W7: 3981 | X7: 130504 | Y7: 324765 | Z7: 469064 | AA7: 443912 | AB7: 349932 | AC7: 228250 | AD7: 228250 | AE7: 228250 | AF7: =SUM(T7:AE7) -> 2734380 | AH7: 1895177 | AJ7: 2890702.5 | AL7: =IFERROR(R7-AF7,0) -> 1049620 | AM7: =IFERROR((R7/AF7)-1,0) -> 0.38386033
B8: 2 | C8: Chai PET B1 Không Phân Loại | D8: Tấn | E8: =R8/$R$22 -> 0 | F8: ='3.Thanh pham'!H83 -> 0 | G8: ='3.Thanh pham'!I83 -> 0 | H8: ='3.Thanh pham'!J83 -> 0 | I8: ='3.Thanh pham'!K83 -> 0 | J8: ='3.Thanh pham'!L83 -> 0 | K8: ='3.Thanh pham'!M83 -> 0 | L8: ='3.Thanh pham'!N83 -> 0 | M8: ='3.Thanh pham'!O83 -> 0 | ... Q8: ='3.Thanh pham'!S83 -> 0 | R8: =SUM(F8:Q8) -> 0 | AB8: 21565 | AF8: =SUM(T8:AE8) -> 21565 | AH8: 742255 | AL8: =IFERROR(R8-AF8,0) -> -21565 | AM8: =IFERROR((R8/AF8)-1,0) -> -1
B9: 3 | C9: Chai PET B1.3 | D9: Tấn | E9: =R9/$R$22 -> 0 | F9: ='3.Thanh pham'!H84 -> 0 | G9: ='3.Thanh pham'!I84 -> 0 | H9: ='3.Thanh pham'!J84 -> 0 | I9: ='3.Thanh pham'!K84 -> 0 | J9: ='3.Thanh pham'!L84 -> 0 | K9: ='3.Thanh pham'!M84 -> 0 | L9: ='3.Thanh pham'!N84 -> 0 | M9: ='3.Thanh pham'!O84 -> 0 | ... Q9: ='3.Thanh pham'!S84 -> 0 | R9: =SUM(F9:Q9) -> 0 | U9: 114280 | V9: 194340 | W9: 246148 | X9: 119501 | AF9: =SUM(T9:AE9) -> 674269 | AL9: =IFERROR(R9-AF9,0) -> -674269 | AM9: =IFERROR((R9/AF9)-1,0) -> -1
B10: 4 | C10: Chai PET B2.1 | D10: Tấn | E10: =R10/$R$22 -> 0 | F10: ='3.Thanh pham'!H85 -> 0 | G10: ='3.Thanh pham'!I85 -> 0 | H10: ='3.Thanh pham'!J85 -> 0 | I10: ='3.Thanh pham'!K85 -> 0 | J10: ='3.Thanh pham'!L85 -> 0 | K10: ='3.Thanh pham'!M85 -> 0 | L10: ='3.Thanh pham'!N85 -> 0 | M10: ='3.Thanh pham'!O85 -> 0 | ... Q10: ='3.Thanh pham'!S85 -> 0 | R10: =SUM(F10:Q10) -> 0 | U10: 85 | AF10: =SUM(T10:AE10) -> 85 | AJ10: 138350.5 | AL10: =IFERROR(R10-AF10,0) -> -85 | AM10: =IFERROR((R10/AF10)-1,0) -> -1
B11: 5 | C11: Chai PET B2.2 | D11: Tấn | E11: =R11/$R$22 -> 0.11410905 | F11: ='3.Thanh pham'!H86 -> 60900 | G11: ='3.Thanh pham'!I86 -> 45675 | H11: ='3.Thanh pham'!J86 -> 65975 | I11: ='3.Thanh pham'!K86 -> 71050 | J11: ='3.Thanh pham'!L86 -> 71050 | K11: ='3.Thanh pham'!M86 -> 71050 | L11: ='3.Thanh pham'!N86 -> 71050 | M11: ='3.Thanh pham'!O86 -> 71050 | ... Q11: ='3.Thanh pham'!S86 -> 71050 | R11: =SUM(F11:Q11) -> 812000 | T11: 29025 | U11: 45312 | V11: 50403 | W11: 31944 | X11: 57137 | Y11: 57210 | Z11: 42086 | AA11: 51729 | AB11: 40991 | AC11: 55750 | AD11: 55750 | AE11: 55750 | AF11: =SUM(T11:AE11) -> 573087 | AH11: 635827 | AJ11: 565953 | AL11: =IFERROR(R11-AF11,0) -> 238913 | AM11: =IFERROR((R11/AF11)-1,0) -> 0.41688784
B12: 6 | C12: Chai PET B3 | D12: Tấn | E12: =R12/$R$22 -> 0 | F12: ='3.Thanh pham'!H87 -> 0 | G12: ='3.Thanh pham'!I87 -> 0 | H12: ='3.Thanh pham'!J87 -> 0 | I12: ='3.Thanh pham'!K87 -> 0 | J12: ='3.Thanh pham'!L87 -> 0 | K12: ='3.Thanh pham'!M87 -> 0 | L12: ='3.Thanh pham'!N87 -> 0 | M12: ='3.Thanh pham'!O87 -> 0 | ... Q12: ='3.Thanh pham'!S87 -> 0 | R12: =SUM(F12:Q12) -> 0 | U12: 15709 | AF12: =SUM(T12:AE12) -> 15709 | AH12: 50758 | AJ12: 623305.5 | AL12: =IFERROR(R12-AF12,0) -> -15709 | AM12: =IFERROR((R12/AF12)-1,0) -> -1
B13: 7 | C13: Chai PET B4 | D13: Tấn | E13: =R13/$R$22 -> 0.016863406 | F13: ='3.Thanh pham'!H88 -> 9000 | G13: ='3.Thanh pham'!I88 -> 6750 | H13: ='3.Thanh pham'!J88 -> 9750 | I13: ='3.Thanh pham'!K88 -> 10500 | J13: ='3.Thanh pham'!L88 -> 10500 | K13: ='3.Thanh pham'!M88 -> 10500 | L13: ='3.Thanh pham'!N88 -> 10500 | M13: ='3.Thanh pham'!O88 -> 10500 | ... Q13: ='3.Thanh pham'!S88 -> 10500 | R13: =SUM(F13:Q13) -> 120000 | T13: 3805 | U13: 6542 | V13: 5850 | W13: 7817 | X13: 12348 | Y13: 6870 | Z13: 13717 | AA13: 13559 | AB13: 10573 | AC13: 7500 | AD13: 7500 | AE13: 7500 | AF13: =SUM(T13:AE13) -> 103581 | AH13: 85204 | AJ13: 86157 | AL13: =IFERROR(R13-AF13,0) -> 16419 | AM13: =IFERROR((R13/AF13)-1,0) -> 0.15851363
B14: 8 | C14: Chai PET B5 | D14: Tấn | E14: =R14/$R$22 -> 0.022484542 | F14: ='3.Thanh pham'!H89 -> 12000 | G14: ='3.Thanh pham'!I89 -> 9000 | H14: ='3.Thanh pham'!J89 -> 13000 | I14: ='3.Thanh pham'!K89 -> 14000 | J14: ='3.Thanh pham'!L89 -> 14000 | K14: ='3.Thanh pham'!M89 -> 14000 | L14: ='3.Thanh pham'!N89 -> 14000 | M14: ='3.Thanh pham'!O89 -> 14000 | ... Q14: ='3.Thanh pham'!S89 -> 14000 | R14: =SUM(F14:Q14) -> 160000 | T14: 6975 | U14: 8759 | V14: 4910 | W14: 15092 | X14: 11240 | Y14: 8710 | Z14: 17048 | AA14: 18066 | AB14: 13542 | AC14: 10000 | AD14: 10000 | AE14: 10000 | AF14: =SUM(T14:AE14) -> 134342 | AH14: 127968 | AJ14: 151214 | AL14: =IFERROR(R14-AF14,0) -> 25658 | AM14: =IFERROR((R14/AF14)-1,0) -> 0.19099016
B15: 9 | C15: Chai PET B6.1 | D15: Tấn | E15: =R15/$R$22 -> 0 | F15: ='3.Thanh pham'!H90 -> 0 | G15: ='3.Thanh pham'!I90 -> 0 | H15: ='3.Thanh pham'!J90 -> 0 | I15: ='3.Thanh pham'!K90 -> 0 | J15: ='3.Thanh pham'!L90 -> 0 | K15: ='3.Thanh pham'!M90 -> 0 | L15: ='3.Thanh pham'!N90 -> 0 | M15: ='3.Thanh pham'!O90 -> 0 | ... Q15: ='3.Thanh pham'!S90 -> 0 | R15: =SUM(F15:Q15) -> 0 | AF15: =SUM(T15:AE15) -> 0 | AH15: 11776 | AL15: =IFERROR(R15-AF15,0) -> 0 | AM15: =IFERROR((R15/AF15)-1,0) -> 0
B16: 10 | C16: Chai PET B6.2 | D16: Tấn | E16: =R16/$R$22 -> 0.2698145 | F16: ='3.Thanh pham'!H91 -> 144000 | G16: ='3.Thanh pham'!I91 -> 108000 | H16: ='3.Thanh pham'!J91 -> 156000 | I16: ='3.Thanh pham'!K91 -> 168000 | J16: ='3.Thanh pham'!L91 -> 168000 | K16: ='3.Thanh pham'!M91 -> 168000 | L16: ='3.Thanh pham'!N91 -> 168000 | M16: ='3.Thanh pham'!O91 -> 168000 | ... Q16: ='3.Thanh pham'!S91 -> 168000 | R16: =SUM(F16:Q16) -> 1920000 | T16: 73417 | U16: 7620 | V16: 88130 | W16: 200401 | X16: 104534 | Y16: 108010 | Z16: 164167 | AA16: 174065 | AB16: 145925 | AC16: 120000 | AD16: 120000 | AE16: 120000 | AF16: =SUM(T16:AE16) -> 1426269 | AH16: 1151193 | AJ16: 981342 | AL16: =IFERROR(R16-AF16,0) -> 493731 | AM16: =IFERROR((R16/AF16)-1,0) -> 0.34616962
B17: 11 | C17: Chai PET B7.1 | D17: Tấn | E17: =R17/$R$22 -> 0 | F17: ='3.Thanh pham'!H92 -> 0 | G17: ='3.Thanh pham'!I92 -> 0 | H17: ='3.Thanh pham'!J92 -> 0 | I17: ='3.Thanh pham'!K92 -> 0 | J17: ='3.Thanh pham'!L92 -> 0 | K17: ='3.Thanh pham'!M92 -> 0 | L17: ='3.Thanh pham'!N92 -> 0 | M17: ='3.Thanh pham'!O92 -> 0 | ... Q17: ='3.Thanh pham'!S92 -> 0 | R17: =SUM(F17:Q17) -> 0 | AF17: =SUM(T17:AE17) -> 0 | AL17: =IFERROR(R17-AF17,0) -> 0 | AM17: =IFERROR((R17/AF17)-1,0) -> 0
B18: 12 | C18: Chai PET B7.2 | D18: Tấn | E18: =R18/$R$22 -> 0 | F18: ='3.Thanh pham'!H93 -> 0 | G18: ='3.Thanh pham'!I93 -> 0 | H18: ='3.Thanh pham'!J93 -> 0 | I18: ='3.Thanh pham'!K93 -> 0 | J18: ='3.Thanh pham'!L93 -> 0 | K18: ='3.Thanh pham'!M93 -> 0 | L18: ='3.Thanh pham'!N93 -> 0 | M18: ='3.Thanh pham'!O93 -> 0 | ... Q18: ='3.Thanh pham'!S93 -> 0 | R18: =SUM(F18:Q18) -> 0 | V18: 3650 | AA18: 3386 | AB18: 1364 | AF18: =SUM(T18:AE18) -> 8400 | AL18: =IFERROR(R18-AF18,0) -> -8400 | AM18: =IFERROR((R18/AF18)-1,0) -> -1
B19: 13 | C19: Cổ Chai PET | D19: Tấn | E19: =R19/$R$22 -> 0.011242271 | F19: ='3.Thanh pham'!H94 -> 6000 | G19: ='3.Thanh pham'!I94 -> 4500 | H19: ='3.Thanh pham'!J94 -> 6500 | I19: ='3.Thanh pham'!K94 -> 7000 | J19: ='3.Thanh pham'!L94 -> 7000 | K19: ='3.Thanh pham'!M94 -> 7000 | L19: ='3.Thanh pham'!N94 -> 7000 | M19: ='3.Thanh pham'!O94 -> 7000 | ... Q19: ='3.Thanh pham'!S94 -> 7000 | R19: =SUM(F19:Q19) -> 80000 | AF19: =SUM(T19:AE19) -> 0 | AL19: =IFERROR(R19-AF19,0) -> 80000 | AM19: =IFERROR((R19/AF19)-1,0) -> 0
B20: 14 | C20: Nắp HD ép các màu | D20: Tấn | E20: =R20/$R$22 -> 0.033726813 | F20: ='3.Thanh pham'!H95 -> 18000 | G20: ='3.Thanh pham'!I95 -> 13500 | H20: ='3.Thanh pham'!J95 -> 19500 | I20: ='3.Thanh pham'!K95 -> 21000 | J20: ='3.Thanh pham'!L95 -> 21000 | K20: ='3.Thanh pham'!M95 -> 21000 | L20: ='3.Thanh pham'!N95 -> 21000 | M20: ='3.Thanh pham'!O95 -> 21000 | ... Q20: ='3.Thanh pham'!S95 -> 21000 | R20: =SUM(F20:Q20) -> 240000 | T20: 7010 | U20: 12644 | V20: 20860 | W20: 14520 | X20: 32092 | Y20: 3380 | Z20: 12888 | AA20: 6982 | AB20: 6454 | AC20: 20000 | AD20: 20000 | AE20: 20000 | AF20: =SUM(T20:AE20) -> 176830 | AH20: 177804 | AJ20: 130416 | AL20: =IFERROR(R20-AF20,0) -> 63170 | AM20: =IFERROR((R20/AF20)-1,0) -> 0.35723576
B21: 15 | C21: Khác | D21: Tấn | E21: =R21/$R$22 -> 0 | F21: ='3.Thanh pham'!H96 -> 0 | G21: ='3.Thanh pham'!I96 -> 0 | H21: ='3.Thanh pham'!J96 -> 0 | I21: ='3.Thanh pham'!K96 -> 0 | J21: ='3.Thanh pham'!L96 -> 0 | K21: ='3.Thanh pham'!M96 -> 0 | L21: ='3.Thanh pham'!N96 -> 0 | M21: ='3.Thanh pham'!O96 -> 0 | ... Q21: ='3.Thanh pham'!S96 -> 0 | R21: =SUM(F21:Q21) -> 0 | V21: 1860 | Y21: 1490 | AB21: 7932 | AF21: =SUM(T21:AE21) -> 11282 | AH21: 17056.4 | AJ21: 85330 | AL21: =IFERROR(R21-AF21,0) -> -11282 | AM21: =IFERROR((R21/AF21)-1,0) -> -1
C22: TỔNG: | E22: =SUM(E7:E21) -> 1 | F22: =SUM(F7:F21) -> 533700 | G22: =SUM(G7:G21) -> 400275 | H22: =SUM(H7:H21) -> 578175 | I22: =SUM(I7:I21) -> 622650 | J22: =SUM(J7:J21) -> 622650 | K22: =SUM(K7:K21) -> 622650 | L22: =SUM(L7:L21) -> 622650 | ... Q22: =SUM(Q7:Q21) -> 622650 | R22: =SUM(F22:Q22) -> 7116000 | T22: =SUM(T7:T21) -> 242078 | U22: =SUM(U7:U21) -> 310593 | V22: =SUM(V7:V21) -> 475987 | W22: =SUM(W7:W21) -> 519903 | X22: =SUM(X7:X21) -> 467356 | Y22: =SUM(Y7:Y21) -> 510435 | Z22: =SUM(Z7:Z21) -> 718970 | AA22: =SUM(AA7:AA21) -> 711699 | ... AE22: =SUM(AE7:AE21) -> 441500 | AF22: =SUM(T22:AE22) -> 5879799 | AH22: =SUM(AH7:AH21) -> 4895018.4 | AJ22: =SUM(AJ7:AJ21) -> 5652770.5 | AL22: =IFERROR(R22-AF22,0) -> 1236201 | AM22: =IFERROR((R22/AF22)-1,0) -> 0.21024545
B24: 2. Giá bán chai
B25: STT | C25: Thành phẩm (chai sau phân loại) | D25: ĐVT | E25: Tỷ lệ | F25: T1 | G25: T2 | H25: T3 | I25: T4 | J25: T5 | K25: T6 | L25: T7 | M25: T8 | N25: T9 | O25: T10 | P25: T11 | Q25: T12 | R25: Kế hoạch 2026 | T25: T1 | U25: T2 | V25: T3 | W25: T4 | X25: T5 | Y25: T6 | Z25: T7 | AA25: T8 | AB25: T9 | AC25: T10 | AD25: T11 | AE25: T12 | AF25: KQKD 2025 | AH25: KQKD 2024 | AJ25: KQKD 2023 | AL25: +/- 2026 sv 2025 | AM25: +/- % | AO25: Nhóm chai PET | AP25: Thành phần chai PET sau phân loại | AQ25: Đơn giá PET-B0 | AR25: Hao hụt | AT25: GAP (đảm bảo chi phí và lợi nhuận) | AU25: Đơn giá bán theo công thức
B26: 1 | C26: Chai PET B1 | D26: Đồng/kg | F26: =$AU$27 -> 15000 | G26: =$AU$27 -> 15000 | H26: =$AU$27 -> 15000 | I26: =$AU$27 -> 15000 | J26: =$AU$27 -> 15000 | K26: =$AU$27 -> 15000 | L26: =$AU$27 -> 15000 | M26: =$AU$27 -> 15000 | ... Q26: =$AU$27 -> 15000 | R26: =IFERROR(AVERAGEA(F26:Q26),0) -> 15000 | T26: =IFERROR(T45/T7,0) -> 17452.912 | U26: =IFERROR(U45/U7,0) -> 16241.454 | V26: =IFERROR(V45/V7,0) -> 17309.09 | W26: =IFERROR(W45/W7,0) -> 18573.574 | X26: =IFERROR(X45/X7,0) -> 18390.797 | Y26: =IFERROR(Y45/Y7,0) -> 18717.792 | Z26: =IFERROR(Z45/Z7,0) -> 19089.519 | AA26: =IFERROR(AA45/AA7,0) -> 17673.184 | AB26: =IFERROR(AB45/AB7,0) -> 15658.951 | AC26: 15000 | AD26: 15000 | AE26: 15000 | AF26: =IFERROR(AVERAGEA(T26:AE26),0) -> 17008.939 | AH26: =IFERROR(AH45/AH7,0) -> 17331.591 | AJ26: =IFERROR(AJ45/AJ7,0) -> 16510.254 | AL26: =IFERROR(R26-AF26,0) -> -2008.9394 | AM26: =IFERROR((R26/AF26)-1,0) -> -0.1181108 | AR26: Tỷ lệ | AS26: Quy ra tiền
B27: 2 | C27: Chai PET B1 Không Phân Loại | D27: Đồng/kg | F27: =$AU$27 -> 15000 | G27: =$AU$27 -> 15000 | H27: =$AU$27 -> 15000 | I27: =$AU$27 -> 15000 | J27: =$AU$27 -> 15000 | K27: =$AU$27 -> 15000 | L27: =$AU$27 -> 15000 | M27: =$AU$27 -> 15000 | ... Q27: =$AU$27 -> 15000 | R27: =IFERROR(AVERAGEA(F27:Q27),0) -> 15000 | T27: =IFERROR(T46/T8,0) -> 0 | U27: =IFERROR(U46/U8,0) -> 0 | V27: =IFERROR(V46/V8,0) -> 0 | W27: =IFERROR(W46/W8,0) -> 0 | X27: =IFERROR(X46/X8,0) -> 0 | Y27: =IFERROR(Y46/Y8,0) -> 0 | Z27: =IFERROR(Z46/Z8,0) -> 0 | AA27: =IFERROR(AA46/AA8,0) -> 0 | AB27: =IFERROR(AB46/AB8,0) -> 15000 | AF27: =IFERROR(AVERAGEA(AB27),0) -> 15000 | AH27: =IFERROR(AH46/AH8,0) -> 16477.287 | AJ27: =IFERROR(AJ46/AJ8,0) -> 0 | AL27: =IFERROR(R27-AF27,0) -> 0 | AM27: =IFERROR((R27/AF27)-1,0) -> 0 | AO27: Chai PET nhóm 1 | AP27: B1.1 + B1.2 + B1.3 + B2.1 + B3 | AQ27: ='1.NVL Chai'!T34 -> 10000 | AR27: 0.11 | AS27: =AQ27*AR27 -> 1100 | AT27: =3500+500 -> 4000 | AU27: 15000
B28: 3 | C28: Chai PET B1.3 | D28: Đồng/kg | F28: =$AU$27 -> 15000 | G28: =$AU$27 -> 15000 | H28: =$AU$27 -> 15000 | I28: =$AU$27 -> 15000 | J28: =$AU$27 -> 15000 | K28: =$AU$27 -> 15000 | L28: =$AU$27 -> 15000 | M28: =$AU$27 -> 15000 | ... Q28: =$AU$27 -> 15000 | R28: =IFERROR(AVERAGEA(F28:Q28),0) -> 15000 | T28: =IFERROR(T47/T9,0) -> 0 | U28: =IFERROR(U47/U9,0) -> 17030 | V28: =IFERROR(V47/V9,0) -> 18393.594 | W28: =IFERROR(W47/W9,0) -> 19816.996 | X28: =IFERROR(X47/X9,0) -> 18689.691 | Y28: =IFERROR(Y47/Y9,0) -> 0 | Z28: =IFERROR(Z47/Z9,0) -> 0 | AA28: =IFERROR(AA47/AA9,0) -> 0 | AB28: =IFERROR(AB47/AB9,0) -> 0 | AF28: =IFERROR(AVERAGEA(U28:X28),0) -> 18482.57 | AH28: =IFERROR(AH47/AH9,0) -> 0 | AJ28: =IFERROR(AJ47/AJ9,0) -> 0 | AL28: =IFERROR(R28-AF28,0) -> -3482.5701 | AM28: =IFERROR((R28/AF28)-1,0) -> -0.18842456 | AO28: Chai PET nhóm 2 | AP28: B4 + B5 | AQ28: =$AQ$27 -> 10000 | AR28: 0.11 | AS28: =AQ28*AR28 -> 1100 | AT28: =500+500 -> 1000 | AU28: 12000
B29: 4 | C29: Chai PET B2.1 | D29: Đồng/kg | F29: =$AU$27 -> 15000 | G29: =$AU$27 -> 15000 | H29: =$AU$27 -> 15000 | I29: =$AU$27 -> 15000 | J29: =$AU$27 -> 15000 | K29: =$AU$27 -> 15000 | L29: =$AU$27 -> 15000 | M29: =$AU$27 -> 15000 | ... Q29: =$AU$27 -> 15000 | R29: =IFERROR(AVERAGEA(F29:Q29),0) -> 15000 | T29: =IFERROR(T48/T10,0) -> 0 | U29: =IFERROR(U48/U10,0) -> 16394 | V29: =IFERROR(V48/V10,0) -> 0 | W29: =IFERROR(W48/W10,0) -> 0 | X29: =IFERROR(X48/X10,0) -> 0 | Y29: =IFERROR(Y48/Y10,0) -> 0 | Z29: =IFERROR(Z48/Z10,0) -> 0 | AA29: =IFERROR(AA48/AA10,0) -> 0 | AB29: =IFERROR(AB48/AB10,0) -> 0 | AF29: =IFERROR(AVERAGEA(U29),0) -> 16394 | AH29: =IFERROR(AH48/AH10,0) -> 0 | AJ29: =IFERROR(AJ48/AJ10,0) -> 10461.233 | AL29: =IFERROR(R29-AF29,0) -> -1394 | AM29: =IFERROR((R29/AF29)-1,0) -> -0.085031109 | AO29: Chai PET nhóm 3 | AP29: B2.2 + B6.1 + B6.2 | AQ29: =$AQ$27 -> 10000 | AR29: 0.11 | AS29: =AQ29*AR29 -> 1100 | AT29: =2000+500 -> 2500 | AU29: 13500
B30: 5 | C30: Chai PET B2.2 | D30: Đồng/kg | F30: =$AU$29 -> 13500 | G30: =$AU$29 -> 13500 | H30: =$AU$29 -> 13500 | I30: =$AU$29 -> 13500 | J30: =$AU$29 -> 13500 | K30: =$AU$29 -> 13500 | L30: =$AU$29 -> 13500 | M30: =$AU$29 -> 13500 | ... Q30: =$AU$29 -> 13500 | R30: =IFERROR(AVERAGEA(F30:Q30),0) -> 13500 | T30: =IFERROR(T49/T11,0) -> 15550.956 | U30: =IFERROR(U49/U11,0) -> 17030 | V30: =IFERROR(V49/V11,0) -> 17306.878 | W30: =IFERROR(W49/W11,0) -> 18571.168 | X30: =IFERROR(X49/X11,0) -> 18561.238 | Y30: =IFERROR(Y49/Y11,0) -> 18704.085 | Z30: =IFERROR(Z49/Z11,0) -> 19006.941 | AA30: =IFERROR(AA49/AA11,0) -> 17246.76 | AB30: =IFERROR(AB49/AB11,0) -> 14013.82 | AC30: 13500 | AD30: 13500 | AE30: 13500 | AF30: =IFERROR(AVERAGEA(T30:AE30),0) -> 16374.321 | AH30: =IFERROR(AH49/AH11,0) -> 13372.586 | AJ30: =IFERROR(AJ49/AJ11,0) -> 10177.679 | AL30: =IFERROR(R30-AF30,0) -> -2874.3206 | AM30: =IFERROR((R30/AF30)-1,0) -> -0.17553831 | AO30: Chai PET nhóm 4 | AP30: Nắp HD ép, cổ chai, PP (Quai) | AQ30: =$AQ$27 -> 10000 | AR30: 0.11 | AS30: =AQ30*AR30 -> 1100 | AT30: =-5000+500 -> -4500 | AU30: 8100
B31: 6 | C31: Chai PET B3 | D31: Đồng/kg | F31: =$AU$27 -> 15000 | G31: =$AU$27 -> 15000 | H31: =$AU$27 -> 15000 | I31: =$AU$27 -> 15000 | J31: =$AU$27 -> 15000 | K31: =$AU$27 -> 15000 | L31: =$AU$27 -> 15000 | M31: =$AU$27 -> 15000 | ... Q31: =$AU$27 -> 15000 | R31: =IFERROR(AVERAGEA(F31:Q31),0) -> 15000 | T31: =IFERROR(T50/T12,0) -> 0 | U31: =IFERROR(U50/U12,0) -> 17030 | V31: =IFERROR(V50/V12,0) -> 0 | W31: =IFERROR(W50/W12,0) -> 0 | X31: =IFERROR(X50/X12,0) -> 0 | Y31: =IFERROR(Y50/Y12,0) -> 0 | Z31: =IFERROR(Z50/Z12,0) -> 0 | AA31: =IFERROR(AA50/AA12,0) -> 0 | AB31: =IFERROR(AB50/AB12,0) -> 0 | AF31: =IFERROR(AVERAGEA(U31),0) -> 17030 | AH31: =IFERROR(AH50/AH12,0) -> 16152.902 | AJ31: =IFERROR(AJ50/AJ12,0) -> 15598.827 | AL31: =IFERROR(R31-AF31,0) -> -2030 | AM31: =IFERROR((R31/AF31)-1,0) -> -0.11920141 | AO31: Chai PET nhóm 5 | AP31: B7.2 | AQ31: =$AQ$27 -> 10000 | AR31: 0.11 | AS31: =AQ31*AR31 -> 1100 | AT31: -3500 | AU31: 9000
B32: 7 | C32: Chai PET B4 | D32: Đồng/kg | F32: =$AU$28 -> 12000 | G32: =$AU$28 -> 12000 | H32: =$AU$28 -> 12000 | I32: =$AU$28 -> 12000 | J32: =$AU$28 -> 12000 | K32: =$AU$28 -> 12000 | L32: =$AU$28 -> 12000 | M32: =$AU$28 -> 12000 | ... Q32: =$AU$28 -> 12000 | R32: =IFERROR(AVERAGEA(F32:Q32),0) -> 12000 | T32: =IFERROR(T51/T13,0) -> 14300 | U32: =IFERROR(U51/U13,0) -> 17030 | V32: =IFERROR(V51/V13,0) -> 16390.376 | W32: =IFERROR(W51/W13,0) -> 17906.045 | X32: =IFERROR(X51/X13,0) -> 18686.429 | Y32: =IFERROR(Y51/Y13,0) -> 18543.188 | Z32: =IFERROR(Z51/Z13,0) -> 18907.35 | AA32: =IFERROR(AA51/AA13,0) -> 17575.213 | AB32: =IFERROR(AB51/AB13,0) -> 12575.144 | AC32: 12000 | AD32: 12000 | AE32: 12000 | AF32: =IFERROR(AVERAGEA(T32:AE32),0) -> 15659.479 | AH32: =IFERROR(AH51/AH13,0) -> 13157.399 | AJ32: =IFERROR(AJ51/AJ13,0) -> 10009.366 | AL32: =IFERROR(R32-AF32,0) -> -3659.4787 | AM32: =IFERROR((R32/AF32)-1,0) -> -0.23369097 | AR32: 0.14
B33: 8 | C33: Chai PET B5 | D33: Đồng/kg | F33: =$AU$28 -> 12000 | G33: =$AU$28 -> 12000 | H33: =$AU$28 -> 12000 | I33: =$AU$28 -> 12000 | J33: =$AU$28 -> 12000 | K33: =$AU$28 -> 12000 | L33: =$AU$28 -> 12000 | M33: =$AU$28 -> 12000 | ... Q33: =$AU$28 -> 12000 | R33: =IFERROR(AVERAGEA(F33:Q33),0) -> 12000 | T33: =IFERROR(T52/T14,0) -> 15611.183 | U33: =IFERROR(U52/U14,0) -> 17030 | V33: =IFERROR(V52/V14,0) -> 17030 | W33: =IFERROR(W52/W14,0) -> 18210.019 | X33: =IFERROR(X52/X14,0) -> 18609.057 | Y33: =IFERROR(Y52/Y14,0) -> 18563.444 | Z33: =IFERROR(Z52/Z14,0) -> 18855.973 | AA33: =IFERROR(AA52/AA14,0) -> 17545.251 | AB33: =IFERROR(AB52/AB14,0) -> 12710.161 | AC33: 12000 | AD33: 12000 | AE33: 12000 | AF33: =IFERROR(AVERAGEA(T33:AE33),0) -> 15847.091 | AH33: =IFERROR(AH52/AH14,0) -> 13209.104 | AJ33: =IFERROR(AJ52/AJ14,0) -> 10940.26 | AL33: =IFERROR(R33-AF33,0) -> -3847.0907 | AM33: =IFERROR((R33/AF33)-1,0) -> -0.24276322
B34: 9 | C34: Chai PET B6.1 | D34: Đồng/kg | F34: =$AU$29 -> 13500 | G34: =$AU$29 -> 13500 | H34: =$AU$29 -> 13500 | I34: =$AU$29 -> 13500 | J34: =$AU$29 -> 13500 | K34: =$AU$29 -> 13500 | L34: =$AU$29 -> 13500 | M34: =$AU$29 -> 13500 | ... Q34: =$AU$29 -> 13500 | R34: =IFERROR(AVERAGEA(F34:Q34),0) -> 13500 | T34: =IFERROR(T53/T15,0) -> 0 | U34: =IFERROR(U53/U15,0) -> 0 | V34: =IFERROR(V53/V15,0) -> 0 | W34: =IFERROR(W53/W15,0) -> 0 | X34: =IFERROR(X53/X15,0) -> 0 | Y34: =IFERROR(Y53/Y15,0) -> 0 | Z34: =IFERROR(Z53/Z15,0) -> 0 | AA34: =IFERROR(AA53/AA15,0) -> 0 | AB34: =IFERROR(AB53/AB15,0) -> 0 | AF34: =IFERROR(AVERAGEA(T34:AE34),0) -> 0 | AH34: =IFERROR(AH53/AH15,0) -> 13000 | AJ34: =IFERROR(AJ53/AJ15,0) -> 0 | AL34: =IFERROR(R34-AF34,0) -> 13500 | AM34: =IFERROR((R34/AF34)-1,0) -> 0
B35: 10 | C35: Chai PET B6.2 | D35: Đồng/kg | F35: =$AU$29 -> 13500 | G35: =$AU$29 -> 13500 | H35: =$AU$29 -> 13500 | I35: =$AU$29 -> 13500 | J35: =$AU$29 -> 13500 | K35: =$AU$29 -> 13500 | L35: =$AU$29 -> 13500 | M35: =$AU$29 -> 13500 | ... Q35: =$AU$29 -> 13500 | R35: =IFERROR(AVERAGEA(F35:Q35),0) -> 13500 | T35: =IFERROR(T54/T16,0) -> 13000 | U35: =IFERROR(U54/U16,0) -> 16842.539 | V35: =IFERROR(V54/V16,0) -> 17030 | W35: =IFERROR(W54/W16,0) -> 17911.564 | X35: =IFERROR(X54/X16,0) -> 18496.188 | Y35: =IFERROR(Y54/Y16,0) -> 18724.562 | Z35: =IFERROR(Z54/Z16,0) -> 19058.443 | AA35: =IFERROR(AA54/AA16,0) -> 17415.845 | AB35: =IFERROR(AB54/AB16,0) -> 14015.001 | AC35: =AC30 -> 13500 | AD35: =AD30 -> 13500 | AE35: =AE30 -> 13500 | AF35: =IFERROR(AVERAGEA(T35:AE35),0) -> 16082.845 | AH35: =IFERROR(AH54/AH16,0) -> 12714.655 | AJ35: =IFERROR(AJ54/AJ16,0) -> 9213.7358 | AL35: =IFERROR(R35-AF35,0) -> -2582.8452 | AM35: =IFERROR((R35/AF35)-1,0) -> -0.16059628
B36: 11 | C36: Chai PET B7.1 | D36: Đồng/kg | F36: =$AU$31 -> 9000 | G36: =$AU$31 -> 9000 | H36: =$AU$31 -> 9000 | I36: =$AU$31 -> 9000 | J36: =$AU$31 -> 9000 | K36: =$AU$31 -> 9000 | L36: =$AU$31 -> 9000 | M36: =$AU$31 -> 9000 | ... Q36: =$AU$31 -> 9000 | R36: =IFERROR(AVERAGEA(F36:Q36),0) -> 9000 | T36: =IFERROR(T55/T17,0) -> 0 | U36: =IFERROR(U55/U17,0) -> 0 | V36: =IFERROR(V55/V17,0) -> 0 | W36: =IFERROR(W55/W17,0) -> 0 | X36: =IFERROR(X55/X17,0) -> 0 | Y36: =IFERROR(Y55/Y17,0) -> 0 | Z36: =IFERROR(Z55/Z17,0) -> 0 | AA36: =IFERROR(AA55/AA17,0) -> 0 | AB36: =IFERROR(AB55/AB17,0) -> 0 | AF36: =IFERROR(AVERAGEA(T36:AE36),0) -> 0 | AH36: =IFERROR(AH55/AH17,0) -> 0 | AJ36: =IFERROR(AJ55/AJ17,0) -> 0 | AL36: =IFERROR(R36-AF36,0) -> 9000 | AM36: =IFERROR((R36/AF36)-1,0) -> 0
B37: 12 | C37: Chai PET B7.2 | D37: Đồng/kg | F37: =$AU$31 -> 9000 | G37: =$AU$31 -> 9000 | H37: =$AU$31 -> 9000 | I37: =$AU$31 -> 9000 | J37: =$AU$31 -> 9000 | K37: =$AU$31 -> 9000 | L37: =$AU$31 -> 9000 | M37: =$AU$31 -> 9000 | ... Q37: =$AU$31 -> 9000 | R37: =IFERROR(AVERAGEA(F37:Q37),0) -> 9000 | T37: =IFERROR(T56/T18,0) -> 0 | U37: =IFERROR(U56/U18,0) -> 0 | V37: =IFERROR(V56/V18,0) -> 8000 | W37: =IFERROR(W56/W18,0) -> 0 | X37: =IFERROR(X56/X18,0) -> 0 | Y37: =IFERROR(Y56/Y18,0) -> 0 | Z37: =IFERROR(Z56/Z18,0) -> 0 | AA37: =IFERROR(AA56/AA18,0) -> 8000 | AB37: =IFERROR(AB56/AB18,0) -> 9000 | AF37: =IFERROR(AVERAGEA(V37,AA37,AB37),0) -> 8333.3333 | AH37: =IFERROR(AH56/AH18,0) -> 0 | AJ37: =IFERROR(AJ56/AJ18,0) -> 0 | AL37: =IFERROR(R37-AF37,0) -> 666.66667 | AM37: =IFERROR((R37/AF37)-1,0) -> 0.08
B38: 13 | C38: Cổ Chai PET | D38: Đồng/kg | F38: =$AU$30 -> 8100 | G38: =$AU$30 -> 8100 | H38: =$AU$30 -> 8100 | I38: =$AU$30 -> 8100 | J38: =$AU$30 -> 8100 | K38: =$AU$30 -> 8100 | L38: =$AU$30 -> 8100 | M38: =$AU$30 -> 8100 | ... Q38: =$AU$30 -> 8100 | R38: =IFERROR(AVERAGEA(F38:Q38),0) -> 8100 | T38: =IFERROR(T57/T19,0) -> 0 | U38: =IFERROR(U57/U19,0) -> 0 | V38: =IFERROR(V57/V19,0) -> 0 | W38: =IFERROR(W57/W19,0) -> 0 | X38: =IFERROR(X57/X19,0) -> 0 | Y38: =IFERROR(Y57/Y19,0) -> 0 | Z38: =IFERROR(Z57/Z19,0) -> 0 | AA38: =IFERROR(AA57/AA19,0) -> 0 | AB38: =IFERROR(AB57/AB19,0) -> 0 | AF38: =IFERROR(AVERAGEA(T38:AE38),0) -> 0 | AH38: =IFERROR(AH57/AH19,0) -> 0 | AJ38: =IFERROR(AJ57/AJ19,0) -> 0 | AL38: =IFERROR(R38-AF38,0) -> 8100 | AM38: =IFERROR((R38/AF38)-1,0) -> 0
B39: 14 | C39: Nắp HD ép các màu | D39: Đồng/kg | F39: =$AU$30 -> 8100 | G39: =$AU$30 -> 8100 | H39: =$AU$30 -> 8100 | I39: =$AU$30 -> 8100 | J39: =$AU$30 -> 8100 | K39: =$AU$30 -> 8100 | L39: =$AU$30 -> 8100 | M39: =$AU$30 -> 8100 | ... Q39: =$AU$30 -> 8100 | R39: =IFERROR(AVERAGEA(F39:Q39),0) -> 8100 | T39: =IFERROR(T58/T20,0) -> 14300 | U39: =IFERROR(U58/U20,0) -> 1500 | V39: =IFERROR(V58/V20,0) -> 3806.3279 | W39: =IFERROR(W58/W20,0) -> 10000 | X39: =IFERROR(X58/X20,0) -> 10000 | Y39: =IFERROR(Y58/Y20,0) -> 10000 | Z39: =IFERROR(Z58/Z20,0) -> 10000 | AA39: =IFERROR(AA58/AA20,0) -> 10070.61 | AB39: =IFERROR(AB58/AB20,0) -> 7000 | AC39: 6500 | AD39: 6500 | AE39: 6500 | AF39: =IFERROR(AVERAGEA(T39:AE39),0) -> 8014.7448 | AH39: =IFERROR(AH58/AH20,0) -> 13293.252 | AJ39: =IFERROR(AJ58/AJ20,0) -> 12710.274 | AL39: =IFERROR(R39-AF39,0) -> 85.255163 | AM39: =IFERROR((R39/AF39)-1,0) -> 0.01063729
B40: 15 | C40: Khác | D40: Đồng/kg | F40: =$AU$30 -> 8100 | G40: =$AU$30 -> 8100 | H40: =$AU$30 -> 8100 | I40: =$AU$30 -> 8100 | J40: =$AU$30 -> 8100 | K40: =$AU$30 -> 8100 | L40: =$AU$30 -> 8100 | M40: =$AU$30 -> 8100 | ... Q40: =$AU$30 -> 8100 | R40: =IFERROR(AVERAGEA(F40:Q40),0) -> 8100 | T40: =IFERROR(T59/T21,0) -> 0 | U40: =IFERROR(U59/U21,0) -> 0 | V40: =IFERROR(V59/V21,0) -> 9071 | W40: =IFERROR(W59/W21,0) -> 0 | X40: =IFERROR(X59/X21,0) -> 0 | Y40: =IFERROR(Y59/Y21,0) -> 14200 | Z40: =IFERROR(Z59/Z21,0) -> 0 | AA40: =IFERROR(AA59/AA21,0) -> 0 | AB40: =IFERROR(AB59/AB21,0) -> 2888.1745 | AF40: =IFERROR(AVERAGEA(V40,Y40,AB40),0) -> 8719.7248 | AH40: =IFERROR(AH59/AH21,0) -> 9302.9235 | AJ40: =IFERROR(AJ59/AJ21,0) -> 12223.671 | AL40: =IFERROR(R40-AF40,0) -> -619.72483 | AM40: =IFERROR((R40/AF40)-1,0) -> -0.071071604
C41: Giá bán Trung bình | F41: =F60/F22 -> 13995.784 | G41: =G60/G22 -> 13995.784 | H41: =H60/H22 -> 13995.784 | I41: =I60/I22 -> 13995.784 | J41: =J60/J22 -> 13995.784 | K41: =K60/K22 -> 13995.784 | L41: =L60/L22 -> 13995.784 | M41: =M60/M22 -> 13995.784 | ... R41: =R60/R22 -> 13995.784 | T41: =T60/T22 -> 15680.473 | U41: =U60/U22 -> 16140.038 | V41: =V60/V22 -> 16990.471 | W41: =W60/W22 -> 18646.912 | X41: =X60/X22 -> 17948.521 | Y41: =Y60/Y22 -> 18641.789 | Z41: =Z60/Z22 -> 18905.641 | AA41: =AA60/AA22 -> 17453.532 | ... AF41: =AF60/AF22 -> 16620.622 | AH41: =AH60/AH22 -> 15224.275 | AJ41: =AJ60/AJ22 -> 13960.529 | AL41: =IFERROR(R41-AF41,0) -> -2624.838 | AM41: =IFERROR((R41/AF41)-1,0) -> -0.15792658
B43: 3. Doanh thu chai
B44: STT | C44: Thành phẩm (chai sau phân loại) | D44: ĐVT | E44: Tỷ lệ | F44: T1 | G44: T2 | H44: T3 | I44: T4 | J44: T5 | K44: T6 | L44: T7 | M44: T8 | N44: T9 | O44: T10 | P44: T11 | Q44: T12 | R44: Kế hoạch 2026 | T44: T1 | U44: T2 | V44: T3 | W44: T4 | X44: T5 | Y44: T6 | Z44: T7 | AA44: T8 | AB44: T9 | AC44: T10 | AD44: T11 | AE44: T12 | AF44: KQKD 2025 | AH44: KQKD 2024 | AJ44: KQKD 2023 | AL44: +/- 2026 sv 2025 | AM44: +/- %
B45: 1 | C45: Chai PET B1 | D45: Triệu đ | E45: =R45/$R$60 -> 0.56991385 | F45: =F7*F26 -> 4257000000 | G45: =G7*G26 -> 3192750000 | H45: =H7*H26 -> 4611750000 | I45: =I7*I26 -> 4966500000 | J45: =J7*J26 -> 4966500000 | K45: =K7*K26 -> 4966500000 | L45: =L7*L26 -> 4966500000 | M45: =M7*M26 -> 4966500000 | ... Q45: =Q7*Q26 -> 4966500000 | R45: =SUM(F45:Q45) -> 56760000000 | T45: 2126567480 | U45: 1618330982 | V45: 1834486565 | W45: 73941400 | X45: 2400072512 | Y45: 6078883751 | Z45: 8954206262 | AA45: 7845338365 | AB45: 5479567900 | AC45: =AC7*AC26 -> 3423750000 | AD45: =AD7*AD26 -> 3423750000 | AE45: =AE7*AE26 -> 3423750000 | AF45: =SUM(T45:AE45) -> 46682645217 | AH45: =32687184700+159248000 -> 32846432700 | AJ45: =44166623800+3559610000 -> 47726233800 | AL45: =IFERROR(R45-AF45,0) -> 10077354783 | AM45: =IFERROR((R45/AF45)-1,0) -> 0.2158694
B46: 2 | C46: Chai PET B1 Không Phân Loại | D46: Triệu đ | E46: =R46/$R$60 -> 0 | F46: =F8*F27 -> 0 | G46: =G8*G27 -> 0 | H46: =H8*H27 -> 0 | I46: =I8*I27 -> 0 | J46: =J8*J27 -> 0 | K46: =K8*K27 -> 0 | L46: =L8*L27 -> 0 | M46: =M8*M27 -> 0 | ... Q46: =Q8*Q27 -> 0 | R46: =SUM(F46:Q46) -> 0 | AB46: 323475000 | AC46: =AC8*AC27 -> 0 | AD46: =AD8*AD27 -> 0 | AE46: =AE8*AE27 -> 0 | AF46: =SUM(T46:AE46) -> 323475000 | AH46: 12230348500 | AL46: =IFERROR(R46-AF46,0) -> -323475000 | AM46: =IFERROR((R46/AF46)-1,0) -> -1
B47: 3 | C47: Chai PET B1.3 | D47: Triệu đ | E47: =R47/$R$60 -> 0 | F47: =F9*F28 -> 0 | G47: =G9*G28 -> 0 | H47: =H9*H28 -> 0 | I47: =I9*I28 -> 0 | J47: =J9*J28 -> 0 | K47: =K9*K28 -> 0 | L47: =L9*L28 -> 0 | M47: =M9*M28 -> 0 | ... Q47: =Q9*Q28 -> 0 | R47: =SUM(F47:Q47) -> 0 | U47: 1946188400 | V47: 3574611014 | W47: 4877913934 | X47: 2233436740 | AC47: =AC9*AC28 -> 0 | AD47: =AD9*AD28 -> 0 | AE47: =AE9*AE28 -> 0 | AF47: =SUM(T47:AE47) -> 12632150088 | AL47: =IFERROR(R47-AF47,0) -> -12632150088 | AM47: =IFERROR((R47/AF47)-1,0) -> -1
B48: 4 | C48: Chai PET B2.1 | D48: Triệu đ | E48: =R48/$R$60 -> 0 | F48: =F10*F29 -> 0 | G48: =G10*G29 -> 0 | H48: =H10*H29 -> 0 | I48: =I10*I29 -> 0 | J48: =J10*J29 -> 0 | K48: =K10*K29 -> 0 | L48: =L10*L29 -> 0 | M48: =M10*M29 -> 0 | ... Q48: =Q10*Q29 -> 0 | R48: =SUM(F48:Q48) -> 0 | U48: 1393490 | AC48: =AC10*AC29 -> 0 | AD48: =AD10*AD29 -> 0 | AE48: =AE10*AE29 -> 0 | AF48: =SUM(T48:AE48) -> 1393490 | AJ48: 1447316750 | AL48: =IFERROR(R48-AF48,0) -> -1393490 | AM48: =IFERROR((R48/AF48)-1,0) -> -1
B49: 5 | C49: Chai PET B2.2 | D49: Triệu đ | E49: =R49/$R$60 -> 0.11006687 | F49: =F11*F30 -> 822150000 | G49: =G11*G30 -> 616612500 | H49: =H11*H30 -> 890662500 | I49: =I11*I30 -> 959175000 | J49: =J11*J30 -> 959175000 | K49: =K11*K30 -> 959175000 | L49: =L11*L30 -> 959175000 | M49: =M11*M30 -> 959175000 | ... Q49: =Q11*Q30 -> 959175000 | R49: =SUM(F49:Q49) -> 10962000000 | T49: 451366500 | U49: 771663360 | V49: 872318550 | W49: 593237400 | X49: 1060533472 | Y49: 1070060700 | Z49: 799926136 | AA49: 892157663 | AB49: 574440500 | AC49: =AC11*AC30 -> 752625000 | AD49: =AD11*AD30 -> 752625000 | AE49: =AE11*AE30 -> 752625000 | AF49: =SUM(T49:AE49) -> 9343579281 | AH49: 8502651000 | AJ49: 5760087865 | AL49: =IFERROR(R49-AF49,0) -> 1618420719 | AM49: =IFERROR((R49/AF49)-1,0) -> 0.17321207
B50: 6 | C50: Chai PET B3 | D50: Triệu đ | E50: =R50/$R$60 -> 0 | F50: =F12*F31 -> 0 | G50: =G12*G31 -> 0 | H50: =H12*H31 -> 0 | I50: =I12*I31 -> 0 | J50: =J12*J31 -> 0 | K50: =K12*K31 -> 0 | L50: =L12*L31 -> 0 | M50: =M12*M31 -> 0 | ... Q50: =Q12*Q31 -> 0 | R50: =SUM(F50:Q50) -> 0 | U50: 267524270 | AC50: =AC12*AC31 -> 0 | AD50: =AD12*AD31 -> 0 | AE50: =AE12*AE31 -> 0 | AF50: =SUM(T50:AE50) -> 267524270 | AH50: 819889000 | AJ50: 9722834500 | AL50: =IFERROR(R50-AF50,0) -> -267524270 | AM50: =IFERROR((R50/AF50)-1,0) -> -1
B51: 7 | C51: Chai PET B4 | D51: Triệu đ | E51: =R51/$R$60 -> 0.014458702 | F51: =F13*F32 -> 108000000 | G51: =G13*G32 -> 81000000 | H51: =H13*H32 -> 117000000 | I51: =I13*I32 -> 126000000 | J51: =J13*J32 -> 126000000 | K51: =K13*K32 -> 126000000 | L51: =L13*L32 -> 126000000 | M51: =M13*M32 -> 126000000 | ... Q51: =Q13*Q32 -> 126000000 | R51: =SUM(F51:Q51) -> 1440000000 | T51: 54411500 | U51: 111410260 | V51: 95883700 | W51: 139971550 | X51: 230740020 | Y51: 127391700 | Z51: 259352118 | AA51: 238302319 | AB51: 132957000 | AC51: =AC13*AC32 -> 90000000 | AD51: =AD13*AD32 -> 90000000 | AE51: =AE13*AE32 -> 90000000 | AF51: =SUM(T51:AE51) -> 1660420167 | AH51: 1121063000 | AJ51: 862376983 | AL51: =IFERROR(R51-AF51,0) -> -220420167 | AM51: =IFERROR((R51/AF51)-1,0) -> -0.13274963
B52: 8 | C52: Chai PET B5 | D52: Triệu đ | E52: =R52/$R$60 -> 0.01927827 | F52: =F14*F33 -> 144000000 | G52: =G14*G33 -> 108000000 | H52: =H14*H33 -> 156000000 | I52: =I14*I33 -> 168000000 | J52: =J14*J33 -> 168000000 | K52: =K14*K33 -> 168000000 | L52: =L14*L33 -> 168000000 | M52: =M14*M33 -> 168000000 | ... Q52: =Q14*Q33 -> 168000000 | R52: =SUM(F52:Q52) -> 1920000000 | T52: 108888000 | U52: 149165770 | V52: 83617300 | W52: 274825600 | X52: 209165800 | Y52: 161687600 | Z52: 321456635 | AA52: 316972509 | AB52: 172121000 | AC52: =AC14*AC33 -> 120000000 | AD52: =AD14*AD33 -> 120000000 | AE52: =AE14*AE33 -> 120000000 | AF52: =SUM(T52:AE52) -> 2157900214 | AH52: 1690342600 | AJ52: 1654320500 | AL52: =IFERROR(R52-AF52,0) -> -237900214 | AM52: =IFERROR((R52/AF52)-1,0) -> -0.11024616
B53: 9 | C53: Chai PET B6.1 | D53: Triệu đ | E53: =R53/$R$60 -> 0 | F53: =F15*F34 -> 0 | G53: =G15*G34 -> 0 | H53: =H15*H34 -> 0 | I53: =I15*I34 -> 0 | J53: =J15*J34 -> 0 | K53: =K15*K34 -> 0 | L53: =L15*L34 -> 0 | M53: =M15*M34 -> 0 | ... Q53: =Q15*Q34 -> 0 | R53: =SUM(F53:Q53) -> 0 | AC53: =AC15*AC34 -> 0 | AD53: =AD15*AD34 -> 0 | AE53: =AE15*AE34 -> 0 | AF53: =SUM(T53:AE53) -> 0 | AH53: 153088000 | AL53: =IFERROR(R53-AF53,0) -> 0 | AM53: =IFERROR((R53/AF53)-1,0) -> 0
B54: 10 | C54: Chai PET B6.2 | D54: Triệu đ | E54: =R54/$R$60 -> 0.26025664 | F54: =F16*F35 -> 1944000000 | G54: =G16*G35 -> 1458000000 | H54: =H16*H35 -> 2106000000 | I54: =I16*I35 -> 2268000000 | J54: =J16*J35 -> 2268000000 | K54: =K16*K35 -> 2268000000 | L54: =L16*L35 -> 2268000000 | M54: =M16*M35 -> 2268000000 | ... Q54: =Q16*Q35 -> 2268000000 | R54: =SUM(F54:Q54) -> 25920000000 | T54: 954421000 | U54: 128340144 | V54: 1500853900 | W54: 3589495430 | X54: 1933480560 | Y54: 2022439900 | Z54: 3128767403 | AA54: 3031489074 | AB54: 2045139000 | AC54: =AC16*AC35 -> 1620000000 | AD54: =AD16*AD35 -> 1620000000 | AE54: =AE16*AE35 -> 1620000000 | AF54: =SUM(T54:AE54) -> 23194426411 | AH54: 14637021500 | AJ54: 9041825897 | AL54: =IFERROR(R54-AF54,0) -> 2725573589 | AM54: =IFERROR((R54/AF54)-1,0) -> 0.11750985
B55: 11 | C55: Chai PET B7.1 | D55: Triệu đ | E55: =R55/$R$60 -> 0 | F55: =F17*F36 -> 0 | G55: =G17*G36 -> 0 | H55: =H17*H36 -> 0 | I55: =I17*I36 -> 0 | J55: =J17*J36 -> 0 | K55: =K17*K36 -> 0 | L55: =L17*L36 -> 0 | M55: =M17*M36 -> 0 | ... Q55: =Q17*Q36 -> 0 | R55: =SUM(F55:Q55) -> 0 | AC55: =AC17*AC36 -> 0 | AD55: =AD17*AD36 -> 0 | AE55: =AE17*AE36 -> 0 | AF55: =SUM(T55:AE55) -> 0 | AL55: =IFERROR(R55-AF55,0) -> 0 | AM55: =IFERROR((R55/AF55)-1,0) -> 0
B56: 12 | C56: Chai PET B7.2 | D56: Triệu đ | E56: =R56/$R$60 -> 0 | F56: =F18*F37 -> 0 | G56: =G18*G37 -> 0 | H56: =H18*H37 -> 0 | I56: =I18*I37 -> 0 | J56: =J18*J37 -> 0 | K56: =K18*K37 -> 0 | L56: =L18*L37 -> 0 | M56: =M18*M37 -> 0 | ... Q56: =Q18*Q37 -> 0 | R56: =SUM(F56:Q56) -> 0 | V56: 29200000 | AA56: 27088000 | AB56: 12276000 | AC56: =AC18*AC37 -> 0 | AD56: =AD18*AD37 -> 0 | AE56: =AE18*AE37 -> 0 | AF56: =SUM(T56:AE56) -> 68564000 | AL56: =IFERROR(R56-AF56,0) -> -68564000 | AM56: =IFERROR((R56/AF56)-1,0) -> -1
B57: 13 | C57: Cổ Chai PET | D57: Triệu đ | E57: =R57/$R$60 -> 0.006506416 | F57: =F19*F38 -> 48600000 | G57: =G19*G38 -> 36450000 | H57: =H19*H38 -> 52650000 | I57: =I19*I38 -> 56700000 | J57: =J19*J38 -> 56700000 | K57: =K19*K38 -> 56700000 | L57: =L19*L38 -> 56700000 | M57: =M19*M38 -> 56700000 | ... Q57: =Q19*Q38 -> 56700000 | R57: =SUM(F57:Q57) -> 648000000 | AC57: =AC19*AC38 -> 0 | AD57: =AD19*AD38 -> 0 | AE57: =AE19*AE38 -> 0 | AF57: =SUM(T57:AE57) -> 0 | AL57: =IFERROR(R57-AF57,0) -> 648000000 | AM57: =IFERROR((R57/AF57)-1,0) -> 0
B58: 14 | C58: Nắp HD ép các màu | D58: Triệu đ | E58: =R58/$R$60 -> 0.019519248 | F58: =F20*F39 -> 145800000 | G58: =G20*G39 -> 109350000 | H58: =H20*H39 -> 157950000 | I58: =I20*I39 -> 170100000 | J58: =J20*J39 -> 170100000 | K58: =K20*K39 -> 170100000 | L58: =L20*L39 -> 170100000 | M58: =M20*M39 -> 170100000 | ... Q58: =Q20*Q39 -> 170100000 | R58: =SUM(F58:Q58) -> 1944000000 | T58: 100243000 | U58: 18966000 | V58: 79400000 | W58: 145200000 | X58: 320920000 | Y58: 33800000 | Z58: 128880000 | AA58: 70313000 | AB58: 45178000 | AC58: =AC20*AC39 -> 130000000 | AD58: =AD20*AD39 -> 130000000 | AE58: =AE20*AE39 -> 130000000 | AF58: =SUM(T58:AE58) -> 1332900000 | AH58: 2363593400 | AJ58: 1657623109 | AL58: =IFERROR(R58-AF58,0) -> 611100000 | AM58: =IFERROR((R58/AF58)-1,0) -> 0.458474
B59: 15 | C59: Khác | D59: Triệu đ | E59: =R59/$R$60 -> 0 | F59: =F21*F40 -> 0 | G59: =G21*G40 -> 0 | H59: =H21*H40 -> 0 | I59: =I21*I40 -> 0 | J59: =J21*J40 -> 0 | K59: =K21*K40 -> 0 | L59: =L21*L40 -> 0 | M59: =M21*M40 -> 0 | ... Q59: =Q21*Q40 -> 0 | R59: =SUM(F59:Q59) -> 0 | V59: 16872060 | Y59: 21158000 | AB59: 22909000 | AC59: =AC21*AC40 -> 0 | AD59: =AD21*AD40 -> 0 | AE59: =AE21*AE40 -> 0 | AF59: =SUM(T59:AE59) -> 60939060 | AH59: =320056785-159248000-2134400 -> 158674385 | AJ59: =4602655865-3559610000 -> 1043045865 | AL59: =IFERROR(R59-AF59,0) -> -60939060 | AM59: =IFERROR((R59/AF59)-1,0) -> -1
C60: TỔNG: | E60: =SUM(E45:E59) -> 1 | F60: =SUM(F45:F59) -> 7469550000 | G60: =SUM(G45:G59) -> 5602162500 | H60: =SUM(H45:H59) -> 8092012500 | I60: =SUM(I45:I59) -> 8714475000 | J60: =SUM(J45:J59) -> 8714475000 | K60: =SUM(K45:K59) -> 8714475000 | L60: =SUM(L45:L59) -> 8714475000 | ... Q60: =SUM(Q45:Q59) -> 8714475000 | R60: =SUM(F60:Q60) -> 99594000000 | T60: =SUM(T45:T59) -> 3795897480 | U60: =SUM(U45:U59) -> 5012982676 | V60: =SUM(V45:V59) -> 8087243089 | W60: =SUM(W45:W59) -> 9694585314 | X60: =SUM(X45:X59) -> 8388349104 | Y60: =SUM(Y45:Y59) -> 9515421651 | Z60: =SUM(Z45:Z59) -> 13592588554 | AA60: =SUM(AA45:AA59) -> 12421660930 | ... AE60: =SUM(AE45:AE59) -> 6136375000 | AF60: =SUM(T60:AE60) -> 97725917198 | AH60: =SUM(AH45:AH59) -> 74523104085 | AJ60: =SUM(AJ45:AJ59) -> 78915665269 | AL60: =IFERROR(R60-AF60,0) -> 1868082802 | AM60: =IFERROR((R60/AF60)-1,0) -> 0.019115531
B62: II - DOANH THU VẢY PET
B63: 1. Sản lượng vảy
B64: STT | C64: Thành phẩm (Vảy PET sau khi băm) | D64: ĐVT | E64: Tỷ lệ | F64: T1 | G64: T2 | H64: T3 | I64: T4 | J64: T5 | K64: T6 | L64: T7 | M64: T8 | N64: T9 | O64: T10 | P64: T11 | Q64: T12 | R64: Kế hoạch 2026 | T64: T1 | U64: T2 | V64: T3 | W64: T4 | X64: T5 | Y64: T6 | Z64: T7 | AA64: T8 | AB64: T9 | AC64: T10 | AD64: T11 | AE64: T12 | AF64: KQKD 2025 | AH64: KQKD 2024 | AJ64: KQKD 2023 | AL64: +/- 2026 sv 2025 | AM64: +/- %
B65: 1 | C65: Vảy PET B1 | D65: Tấn | F65: ='3.Thanh pham'!H121 -> 0 | G65: ='3.Thanh pham'!I121 -> 0 | H65: ='3.Thanh pham'!J121 -> 0 | I65: ='3.Thanh pham'!K121 -> 0 | J65: ='3.Thanh pham'!L121 -> 0 | K65: ='3.Thanh pham'!M121 -> 0 | L65: ='3.Thanh pham'!N121 -> 0 | M65: ='3.Thanh pham'!O121 -> 0 | ... Q65: ='3.Thanh pham'!S121 -> 0 | R65: =SUM(F65:Q65) -> 0 | AL65: =IFERROR(R65-AF65,0) -> 0 | AM65: =IFERROR((R65/AF65)-1,0) -> 0
B66: 2 | C66: Vảy PET B1 Không Phân Loại | D66: Tấn | F66: ='3.Thanh pham'!H122 -> 0 | G66: ='3.Thanh pham'!I122 -> 0 | H66: ='3.Thanh pham'!J122 -> 0 | I66: ='3.Thanh pham'!K122 -> 0 | J66: ='3.Thanh pham'!L122 -> 0 | K66: ='3.Thanh pham'!M122 -> 0 | L66: ='3.Thanh pham'!N122 -> 0 | M66: ='3.Thanh pham'!O122 -> 0 | ... Q66: ='3.Thanh pham'!S122 -> 0 | R66: =SUM(F66:Q66) -> 0 | AL66: =IFERROR(R66-AF66,0) -> 0 | AM66: =IFERROR((R66/AF66)-1,0) -> 0
B67: 3 | C67: Vảy PET B1.3 | D67: Tấn | F67: ='3.Thanh pham'!H123 -> 0 | G67: ='3.Thanh pham'!I123 -> 0 | H67: ='3.Thanh pham'!J123 -> 0 | I67: ='3.Thanh pham'!K123 -> 0 | J67: ='3.Thanh pham'!L123 -> 0 | K67: ='3.Thanh pham'!M123 -> 0 | L67: ='3.Thanh pham'!N123 -> 0 | M67: ='3.Thanh pham'!O123 -> 0 | ... Q67: ='3.Thanh pham'!S123 -> 0 | R67: =SUM(F67:Q67) -> 0 | AL67: =IFERROR(R67-AF67,0) -> 0 | AM67: =IFERROR((R67/AF67)-1,0) -> 0
B68: 4 | C68: Vảy PET B2.1 | D68: Tấn | F68: ='3.Thanh pham'!H124 -> 0 | G68: ='3.Thanh pham'!I124 -> 0 | H68: ='3.Thanh pham'!J124 -> 0 | I68: ='3.Thanh pham'!K124 -> 0 | J68: ='3.Thanh pham'!L124 -> 0 | K68: ='3.Thanh pham'!M124 -> 0 | L68: ='3.Thanh pham'!N124 -> 0 | M68: ='3.Thanh pham'!O124 -> 0 | ... Q68: ='3.Thanh pham'!S124 -> 0 | R68: =SUM(F68:Q68) -> 0 | AL68: =IFERROR(R68-AF68,0) -> 0 | AM68: =IFERROR((R68/AF68)-1,0) -> 0
B69: 5 | C69: Vảy PET B2.2 | D69: Tấn | F69: ='3.Thanh pham'!H125 -> 0 | G69: ='3.Thanh pham'!I125 -> 0 | H69: ='3.Thanh pham'!J125 -> 0 | I69: ='3.Thanh pham'!K125 -> 0 | J69: ='3.Thanh pham'!L125 -> 0 | K69: ='3.Thanh pham'!M125 -> 0 | L69: ='3.Thanh pham'!N125 -> 0 | M69: ='3.Thanh pham'!O125 -> 0 | ... Q69: ='3.Thanh pham'!S125 -> 0 | R69: =SUM(F69:Q69) -> 0 | AL69: =IFERROR(R69-AF69,0) -> 0 | AM69: =IFERROR((R69/AF69)-1,0) -> 0
B70: 6 | C70: Vảy PET B3 | D70: Tấn | F70: ='3.Thanh pham'!H126 -> 0 | G70: ='3.Thanh pham'!I126 -> 0 | H70: ='3.Thanh pham'!J126 -> 0 | I70: ='3.Thanh pham'!K126 -> 0 | J70: ='3.Thanh pham'!L126 -> 0 | K70: ='3.Thanh pham'!M126 -> 0 | L70: ='3.Thanh pham'!N126 -> 0 | M70: ='3.Thanh pham'!O126 -> 0 | ... Q70: ='3.Thanh pham'!S126 -> 0 | R70: =SUM(F70:Q70) -> 0 | AL70: =IFERROR(R70-AF70,0) -> 0 | AM70: =IFERROR((R70/AF70)-1,0) -> 0
B71: 7 | C71: Vảy PET B4 | D71: Tấn | F71: ='3.Thanh pham'!H127 -> 0 | G71: ='3.Thanh pham'!I127 -> 0 | H71: ='3.Thanh pham'!J127 -> 0 | I71: ='3.Thanh pham'!K127 -> 0 | J71: ='3.Thanh pham'!L127 -> 0 | K71: ='3.Thanh pham'!M127 -> 0 | L71: ='3.Thanh pham'!N127 -> 0 | M71: ='3.Thanh pham'!O127 -> 0 | ... Q71: ='3.Thanh pham'!S127 -> 0 | R71: =SUM(F71:Q71) -> 0 | AL71: =IFERROR(R71-AF71,0) -> 0 | AM71: =IFERROR((R71/AF71)-1,0) -> 0
B72: 8 | C72: Vảy PET B5 | D72: Tấn | F72: ='3.Thanh pham'!H128 -> 0 | G72: ='3.Thanh pham'!I128 -> 0 | H72: ='3.Thanh pham'!J128 -> 0 | I72: ='3.Thanh pham'!K128 -> 0 | J72: ='3.Thanh pham'!L128 -> 0 | K72: ='3.Thanh pham'!M128 -> 0 | L72: ='3.Thanh pham'!N128 -> 0 | M72: ='3.Thanh pham'!O128 -> 0 | ... Q72: ='3.Thanh pham'!S128 -> 0 | R72: =SUM(F72:Q72) -> 0 | AL72: =IFERROR(R72-AF72,0) -> 0 | AM72: =IFERROR((R72/AF72)-1,0) -> 0
B73: 9 | C73: Vảy PET B6.1 | D73: Tấn | F73: ='3.Thanh pham'!H129 -> 0 | G73: ='3.Thanh pham'!I129 -> 0 | H73: ='3.Thanh pham'!J129 -> 0 | I73: ='3.Thanh pham'!K129 -> 0 | J73: ='3.Thanh pham'!L129 -> 0 | K73: ='3.Thanh pham'!M129 -> 0 | L73: ='3.Thanh pham'!N129 -> 0 | M73: ='3.Thanh pham'!O129 -> 0 | ... Q73: ='3.Thanh pham'!S129 -> 0 | R73: =SUM(F73:Q73) -> 0 | AL73: =IFERROR(R73-AF73,0) -> 0 | AM73: =IFERROR((R73/AF73)-1,0) -> 0
B74: 10 | C74: Vảy PET B6.2 | D74: Tấn | F74: ='3.Thanh pham'!H130 -> 0 | G74: ='3.Thanh pham'!I130 -> 0 | H74: ='3.Thanh pham'!J130 -> 0 | I74: ='3.Thanh pham'!K130 -> 0 | J74: ='3.Thanh pham'!L130 -> 0 | K74: ='3.Thanh pham'!M130 -> 0 | L74: ='3.Thanh pham'!N130 -> 0 | M74: ='3.Thanh pham'!O130 -> 0 | ... Q74: ='3.Thanh pham'!S130 -> 0 | AL74: =IFERROR(R74-AF74,0) -> 0 | AM74: =IFERROR((R74/AF74)-1,0) -> 0
B75: 11 | C75: Vảy PET B7.1 | D75: Tấn | F75: ='3.Thanh pham'!H131 -> 0 | G75: ='3.Thanh pham'!I131 -> 0 | H75: ='3.Thanh pham'!J131 -> 0 | I75: ='3.Thanh pham'!K131 -> 0 | J75: ='3.Thanh pham'!L131 -> 0 | K75: ='3.Thanh pham'!M131 -> 0 | L75: ='3.Thanh pham'!N131 -> 0 | M75: ='3.Thanh pham'!O131 -> 0 | ... Q75: ='3.Thanh pham'!S131 -> 0 | AL75: =IFERROR(R75-AF75,0) -> 0 | AM75: =IFERROR((R75/AF75)-1,0) -> 0
B76: 12 | C76: Vảy PET B7.2 | D76: Tấn | F76: ='3.Thanh pham'!H132 -> 0 | G76: ='3.Thanh pham'!I132 -> 0 | H76: ='3.Thanh pham'!J132 -> 0 | I76: ='3.Thanh pham'!K132 -> 0 | J76: ='3.Thanh pham'!L132 -> 0 | K76: ='3.Thanh pham'!M132 -> 0 | L76: ='3.Thanh pham'!N132 -> 0 | M76: ='3.Thanh pham'!O132 -> 0 | ... Q76: ='3.Thanh pham'!S132 -> 0 | R76: =SUM(F76:Q76) -> 0 | AL76: =IFERROR(R76-AF76,0) -> 0 | AM76: =IFERROR((R76/AF76)-1,0) -> 0
