Workbook

Sheet Timeline & PIC
B1: DUY TAN GROUP
B2: =IF(B3="EN","Schedule Annual Plan 2025","Lịch lập NGÂN SÁCH năm 2026") -> Lịch lập NGÂN SÁCH năm 2026 | D2: =IF(B3="EN","Start:","Bắt đầu:") -> Bắt đầu: | E2: 45915
B3: VN | D3: =IF(B3="EN","Finish:","Kết thúc:") -> Kết thúc: | E3: =G22 -> 45990 | G3: =E3-E2 -> 75
D4: =IF(B3="en","SENDER","Đơn vị gửi") -> Đơn vị gửi | E4: =IF(B3="EN","RECEIVER","Đơn vị nhận") -> Đơn vị nhận | G4: Deadline | H4: THÁNG 09 | AM4: THÁNG 10 | BR4: THÁNG 11
B5: No. | C5: =IF(B3="EN","PROCESS","TRÌNH TỰ THỰC HIỆN") -> TRÌNH TỰ THỰC HIỆN | F5: Thời gian | H5: 1 | I5: 2 | J5: 3 | K5: 4 | L5: 5 | M5: 6 | N5: 7 | O5: 8 | P5: 9 | Q5: 10 | R5: 11 | S5: 12 | T5: 13 | U5: 14 | V5: 15 | W5: 16 | X5: 17 | Y5: 18 | Z5: 19 | AA5: 20 | AB5: 21 | AC5: 22 | AD5: 23 | AE5: 24 | AF5: 25 | AG5: 26 | AH5: 27 | AI5: 28 | AJ5: 29 | AK5: 30 | AL5: 31 | AM5: 1 | AN5: 2 | AO5: 3 | AP5: 4 | AQ5: 5 | AR5: 6 | AS5: 7 | AT5: 8 | AU5: 9 | AV5: 10 | AW5: 11 | AX5: 12 | AY5: 13 | AZ5: 14 | BA5: 15 | BB5: 16 | BC5: 17 | BD5: 18 | BE5: 19 | BF5: 20 | BG5: 21 | BH5: 22 | BI5: 23 | BJ5: 24 | BK5: 25 | BL5: 26 | BM5: 27 | BN5: 28 | BO5: 29 | BP5: 30 | BQ5: 31 | BR5: 1 | BS5: =BR5+1 -> 2 | BT5: =BS5+1 -> 3 | BU5: =BT5+1 -> 4 | BV5: =BU5+1 -> 5 | BW5: =BV5+1 -> 6 | BX5: =BW5+1 -> 7 | BY5: =BX5+1 -> 8 | BZ5: =BY5+1 -> 9 | ... CT5: =CS5+1 -> 29 | CU5: 30
F6: (Ngày) | H6: M | I6: T | J6: W | K6: TH | L6: F | M6: Sa | N6: Su | O6: M | P6: T | Q6: W | R6: TH | S6: F | T6: Sa | U6: Su | V6: M | W6: T | X6: W | Y6: TH | Z6: F | AA6: Sa | AB6: Su | AC6: M | AD6: T | AE6: W | AF6: TH | AG6: F | AH6: Sa | AI6: Su | AJ6: M | AK6: T | AL6: W | AM6: TH | AN6: F | AO6: Sa | AP6: Su | AQ6: M | AR6: T | AS6: W | AT6: TH | AU6: F | AV6: Sa | AW6: Su | AX6: M | AY6: T | AZ6: W | BA6: TH | BB6: F | BC6: Sa | BD6: Su | BE6: M | BF6: T | BG6: W | BH6: TH | BI6: F | BJ6: Sa | BK6: Su | BL6: M | BM6: T | BN6: W | BO6: TH | BP6: F | BQ6: Sa | BR6: Su | BS6: M | BT6: T | BU6: W | BV6: TH | BW6: F | BX6: Sa | BY6: Su | BZ6: M | CA6: T | CB6: W | CC6: TH | CD6: F | CE6: Sa | CF6: Su | CG6: M | CH6: T | CI6: W | CJ6: TH | CK6: F | CL6: Sa | CM6: Su | CN6: M | CO6: T | CP6: W | CQ6: TH | CR6: F | CS6: Sa | CT6: Su | CU6: M
B7: 1 | C7: Khởi động | D7: GĐTC holding | E7: =IF(B3="EN","All","Tất cả") -> Tất cả | G7: =E2 -> 45915
B8: 2 | C8: Kế hoạch Doanh thu / Sản lượng | D8: =IF(B3="EN","Sales team","Phòng kinh doanh") -> Phòng kinh doanh | E8: =IF(B3="EN","Acct.","Kế toán") -> Kế toán | F8: 15 | G8: =F8+$G$7 -> 45930
B9: 3 | C9: Kế hoạch giá cả nguyên vật liệu | D9: =IF(B2="EN","Supply chain","Chuỗi cung ứng") -> Chuỗi cung ứng | E9: =E8 -> Kế toán | F9: 15 | G9: =F9+$G$7 -> 45930
B10: =B9+1 -> 4 | C10: Kế hoạch chi phí vận chuyển, cước xuất khẩu,... | D10: =IF(B3="EN","Supply chain","Chuổi cung ứng") -> Chuổi cung ứng | E10: =E9 -> Kế toán | F10: 15 | G10: =F10+$G$7 -> 45930
B11: =B10+1 -> 5 | C11: Kế hoạch sản xuất | D11: =IF(B3="EN","Production","Bộ phận sản xuất") -> Bộ phận sản xuất | E11: =E10 -> Kế toán | F11: 20 | G11: =F11+$G$7 -> 45935
B12: =B11+1 -> 6 | C12: Kế hoạch biến phí sản xuất | D12: =E12 -> Kế toán | E12: =E11 -> Kế toán | F12: 20 | G12: =F12+$G$7 -> 45935
B13: =B12+1 -> 7 | C13: Kế hoạch nhân sự (số lượng nhân sự, quỹ lương, chi phí đào tạo,...) | D13: =IF(B3="EN","HR","Phòng nhân sự") -> Phòng nhân sự | E13: =E12 -> Kế toán | F13: 30 | G13: =F13+$G$7 -> 45945
B14: =B13+1 -> 8 | C14: Ngân sách đầu tư | D14: =E7 -> Tất cả | E14: =E13 -> Kế toán | F14: 30 | G14: =F14+$G$7 -> 45945
B15: =B14+1 -> 9 | C15: Ngân sách chi phí sản xuất (không bao gồm lương) | D15: =D11 -> Bộ phận sản xuất | E15: =E14 -> Kế toán | F15: 30 | G15: =F15+$G$7 -> 45945
B16: =B15+1 -> 10 | C16: Ngân sách chi phí bán hàng & chí phí quản lý (không bao gồm lương) | D16: =D14 -> Tất cả | E16: =E15 -> Kế toán | F16: 30 | G16: =F16+$G$7 -> 45945
B17: =B16+1 -> 11 | C17: Tổng hợp kết quả ngân sách mỗi công ty | D17: Kế toán quản trị | E17: KTT/GĐTC | F17: 45 | G17: =F17+$G$7 -> 45960
B18: 12 | C18: Trình bày kết quả ngân sách của mỗi công ty đến TGĐ (Bottom up) | D18: KTT/GĐTC | E18: TGĐ | F18: 50 | G18: =F18+$G$7 -> 45965
B19: 13 | C19: Trình bày kết quả ngân sách của mỗi công ty đến TGĐ (Top down) | D19: KTT/GĐTC | E19: TGĐ | F19: 55 | G19: =F19+$G$7 -> 45970
B20: 14 | C20: Trình bày kết quả ngân sách của mỗi công ty đến TGĐ (Chính thức) | D20: KTT/GĐTC | E20: TGĐ | F20: 62 | G20: =F20+$G$7 -> 45977
B21: 15 | C21: Hợp nhất ngân sách cho toàn bộ DT Group | D21: KTQT holding | E21: GĐTC holding | F21: 70 | G21: =F21+$G$7 -> 45985
B22: 16 | C22: Trình bày kết quả ngân sách hợp nhất cho toàn bộ DT Group | D22: GĐTC holding | E22: TGĐ | F22: 75 | G22: =F22+$G$7 -> 45990

Sheet Thongtin
B2: STT | C2: Nội dung | D2: Nguồn cung cấp dữ liệu | E2: Nguồn thông tin liên quan | F2: Thời gian cần dữ liệu | H2: STT | I2: Màu sheet | J2: Thông tin
B3: 1 | C3: Ban hành Nhóm-Loại NVL Trạm thu mua | D3: GĐĐH Trạm - DTR | E3: 1. BGĐ DTR 2. Phòng cung ứng DTR | F3: 45940 | H3: 1 | J3: Kết quả kinh doanh tổng hợp
B4: 2 | C4: Ban hành Sản lượng Trạm thu mua | D4: GĐĐH Trạm - DTR | E4: 1. BGĐ DTR 2. Phòng cung ứng DTR | F4: 45940 | H4: 2 | J4: Kết quả kinh doanh PET và HD
B5: 3 | C5: Ban hành đơn giá MUA từng loại NVL | D5: GĐĐH Trạm - DTR | E5: 1. Phòng cung ứng DTR đề xuất KH năm 2026 (Dữ liệu theo từng tháng) 2. KTT các trạm cung cấp đơn giá bình quân thực tế mua theo từng tháng ( Dữ liệu năm 2023-2024-2025) 3. Đơn giá BGĐ-DTR duyệt mua trong năm 2025 (Dữ liệu theo từng tháng) | F5: 45940 | H5: 3 | J5: Kết quả kinh doanh PET và HD
B6: 4 | C6: Ban hành đơn giá BÁN từng loại thành phẩm | D6: GĐĐH Trạm - DTR | E6: 1. BGĐ DTR 2. Phòng cung ứng DTR | F6: 45940 | H6: 4 | J6: Ban hành Định mức về Công suất MMTB - Định mức về CP phục vụ sản xuất - Định biên Nhân sự
B7: 5 | C7: Kế hoạch đầu tư CAPEX tại Trạm => Ảnh hưởng đến Sản phẩm và TCKT Trạm cung cấp đến DTR | D7: GĐĐH Trạm - DTR | E7: 1. BGĐ DTR 2. Phòng kỹ thuật DTR 3. Phòng mua hàng DTR | F7: 45940 | H7: 5 | J7: Ban hành sản lượng - đơn giá - Cơ cấu về: NVL - Thành phẩm - Hao hụt - Bán hàng
H8: 6 | J8: Nhóm Chi phí:CP Sản xuất - CP Bán hàng - CP Quản lý (Công thức từ: Định mức - Lương - PB_TSCD - PB_CPTT - nhóm NVL - Phát sinh trực tiếp)
H9: 7 | J9: Cập nhật TSCĐ - CPTT năm trước chuyển sang và Capex 2026
H10: 8 | I10: … | J10: Thông tin khác

Sheet KH hanh dong
A3: KẾ HOẠCH KINH DOANH 2026
A4: Nguồn yêu cầu: GĐTC-DTR
A5: STT | B5: Nhóm công việc | C5: Kế hoạch hành động | D5: Người thực hiện | E5: Thời gian hoàn thành tính toán và xác lập mục tiêu 2026 | F5: Hiện trạng / vướng mắt / giải pháp (tại thời điểm tháng 10/2025) | G5: Mục tiêu 2026 (rolling hàng tháng) | U5: KHNS 2026 | V5: Thực hiện 2025 | W5: Tăng/giảm vs KHNS 2026
G6: Đánh giá KQ đạt được (cập nhật đến thời điểm báo cáo) | H6: Mục tiêu T1 | I6: Mục tiêu T2 | J6: Mục tiêu T3 | K6: Mục tiêu T4 | L6: Mục tiêu T5 | M6: Mục tiêu T6 | N6: Mục tiêu T7 | O6: Mục tiêu T8 | P6: Mục tiêu T9 | Q6: Mục tiêu T10 | R6: Mục tiêu T11 | S6: Mục tiêu T12 | T6: Dự báo KQ 2026 | W6: Theo số tiền phát sinh | X6: Theo mức độ hoạt động | Y6: %
A7: A | B7: HOẠT ĐỘNG MUA HÀNG
A8: 1 | B8: Đáp ứng sản lượng mua cho Trạm | C8: Lập mục tiêu sản lượng mua để Trạm đạt hòa vốn và có lãi.
C9: Xây dựng các trạm vệ tinh để tăng lượng chai về Trạm.
C10: Phát triển thêm các NCC liên kết ở tỉnh.
C11: Đàm phán tăng sản lượng mua từ các NCC đang giao dịch.
A12: 2 | B12: Cải thiện dịch vụ khách hàng | C12: Cải thiện thời gian nhận hàng
C13: Thanh toán trong ngày và cuối tuần
A14: B | B14: HOẠT ĐỘNG BÁN HÀNG
A15: 1 | B15: Giá bán về DTR | C15: Áp dụng cơ cấu giá mới từ Tháng 9/2025
A16: 2 | B16: Kiểm soát tồn kho thành phẩm | C16: Lập KH giao hàng về DTR hàng ngày, ngày cuối tháng không để tồn kho và xuất hóa đơn 100%
A17: 3 | B17: Chi phí thuê xe vận chuyển | C17: - Đàm phán giảm giá, đề nghị NCC sử dụng phương tiện vận chuyển hiệu quả. - Tìm NCC mới cạnh tranh.
A18: C | B18: HOẠT ĐỘNG CẢI TIẾN CHI PHÍ
A19: I | B19: Chi phí nguyên vật liệu
A20: 1 | B20: Kiểm soát lượng mua, giá mua | C20: - Lập mục tiêu tồn kho tối thiểu 10 ngày sản xuất và phối hợp P.Cung ứng lập KH mua hàng theo tuần. - Kiểm soát giá mua tương ứng với từng mức chất lượng chai.
A21: 2 | B21: Kiểm soát chất lượng NVL, hao hụt | C21: Kiểm soát chất lượng chai (tỷ lệ chai nguyên liệu - Chai xá/xô tuyển, thành phần chai sau phân loại, tỷ lệ tạp chất).
A22: 3 | B22: Kiểm soát định mức vật tư sản xuất (hóa chất, dây đai, vật tư kỹ thuật …) | C22: - Thống kê và thực hiện cải tiến tiêu hao. - Mua tập trung tại P.Mua hàng DTR.
A23: 4 | B23: Xử lý phế liệu, phó sản thu hồi | C23: Phân loại phế liệu thành 2 nhóm: - Nhóm hàng hóa (nhãn, bao jumbo, kim loại,…): tìm đơn vị thu mua giá cao - Nhóm rác thải công nghiệp (bùn, hỗn hợp tạp chất): thuê thu gom
A24: II | B24: Chi phí nhân công
A25: 1 | B25: Định mức NCTT | C25: - Kiểm soát định mức NCTT theo chuyền/công đoạn. - Thực hiện tiêu chuẩn hóa/tự động hóa MMTB để giảm nhân công, tăng năng suất. - Tăng số lượng lao động thời vụ. - Tính toán phương án trả lương/ thưởng theo sản lượng.
A26: 2 | B26: Năng suất lao động | C26: - Lập mục tiêu tăng thời gian sản xuất từ 8 giờ/ngày -> 12 giờ -> 16 giờ -> 24 giờ.
A27: III | B27: Chi phí sản xuất chung
A28: 1 | B28: Chi phí điện | C28: - Phối hợp kỹ thuật bảo trì MMTB đảm bảo hoạt động liên tục -> tăng hiệu quả sử dụng điện và tăng năng suất lao động.
A29: 2 | B29: Chi phí xe nâng | C29: - Chuyển dần xe nâng dầu từ DTR về các Trạm (các xe của trạm sửa chữa nhiều sẽ thanh lý)
A30: 3 | B30: Chi phí khấu hao TSCĐ, CCDC, chi phí phân bổ khác | C30: - Thống kê, đánh giá lại hiệu quả sử dụng tất cả TS. - Tách chi phí khấu hao/phân bổ không phục vụ trực tiếp hoạt động để đánh giá hiệu quả KD thực của trạm.
A31: 4 | B31: Chi phí thuê xưởng | C31: - Tìm vị trí và đề xuất phương án di dời nhà máy để giảm tiền thu, tăng hiệu quả thu mua.
A32: IV | B32: Chi phí quản lý
A33: 1 | B33: Chi phí lương (gồm gián tiếp SX) | C33: Soát xét định biên và kế hoạch tuyển dụng, lập mục tiêu giảm định biên đến cuối 2026
A34: 2 | B34: Chi phí theo mục phí (ngoài chi phí lương) | C34: - Lập danh mục chi phí dịch vụ thuê/mua trả tiền định kỳ (nhóm dịch vụ/phòng ban quản lý, tên NCC, hợp đồng mới nhất, tiền trả định kỳ tháng/quý/năm, thời hạn công nợ) -> đàm phán từng NC giảm giá và tìm NCC mới cạnh tranh - XD định mức chi phí cho các khoản mục có thể xác lập định mức - Phân tích chi phí, nguyên nhân tăng/giảm và giải pháp cải tiến.
A35: V | B35: Mục tiêu lợi nhuận
A36: 1 | B36: Lợi nhuận kế hoạch đến cuối năm 2026 | C36: Sau khi đánh giá, xác lập các mục tiêu bên trên, tính toán lợi nhuận kế hoạch đến cuối năm 2026

Sheet KDKD DAY DAI
B3: MỤC TIÊU KẾT QUẢ KINH DOANH NĂM 2026 | S3: ĐVT: Triệu đồng
B4: STT | C4: Mục phí | D4: Thực tế năm 2023 | E4: Thực tế năm 2024 | F4: KQKD 2025 | G4: T1 | H4: T2 | I4: T3 | J4: T4 | K4: T5 | L4: T6 | M4: T7 | N4: T8 | O4: T9 | P4: T10 | Q4: T11 | R4: T12 | S4: KH 2026 | U4: Kiểm tra lại các sheet chi phí
B5: 1 | C5: SẢN LƯỢNG BÁN (TẤN) | D5: =D6+D7+D8 -> 0 | E5: =E6+E7+E8 -> 0 | F5: =F6+F7+F8 -> 0 | G5: =G6+G7+G8 -> 0 | H5: =H6+H7+H8 -> 0 | I5: =I6+I7+I8 -> 0 | J5: =J6+J7+J8 -> 0 | K5: =K6+K7+K8 -> 0 | ... R5: =R6+R7+R8 -> 0 | S5: =SUM(G5:R5) -> 0
B6: 1.1 | C6: Dây Đai PET | G6: ='KH DAY DAI'!E23 -> 0 | H6: ='KH DAY DAI'!F23 -> 0 | I6: ='KH DAY DAI'!G23 -> 0 | J6: ='KH DAY DAI'!H23 -> 0 | K6: ='KH DAY DAI'!I23 -> 0 | L6: ='KH DAY DAI'!J23 -> 0 | M6: ='KH DAY DAI'!K23 -> 0 | N6: ='KH DAY DAI'!L23 -> 0 | ... R6: ='KH DAY DAI'!P23 -> 0 | S6: =SUM(G6:R6) -> 0
B7: 1.2 | S7: =SUM(G7:R7) -> 0
B8: 1.3 | S8: =SUM(G8:R8) -> 0
B9: 2 | C9: DOANH THU | D9: =D10+D11+D12+D13 -> 0 | E9: =E10+E11+E12+E13 -> 0 | F9: =F10+F11+F12+F13 -> 0 | G9: =G10+G11+G12+G13 -> 0 | H9: =H10+H11+H12+H13 -> 0 | I9: =I10+I11+I12+I13 -> 0 | J9: =J10+J11+J12+J13 -> 0 | K9: =K10+K11+K12+K13 -> 0 | ... R9: =R10+R11+R12+R13 -> 0 | S9: =SUM(G9:R9) -> 0
B10: 2.1 | C10: Dây Đai PET | G10: ='KH DAY DAI'!E24 -> 0 | H10: ='KH DAY DAI'!F24 -> 0 | I10: ='KH DAY DAI'!G24 -> 0 | J10: ='KH DAY DAI'!H24 -> 0 | K10: ='KH DAY DAI'!I24 -> 0 | L10: ='KH DAY DAI'!J24 -> 0 | M10: ='KH DAY DAI'!K24 -> 0 | N10: ='KH DAY DAI'!L24 -> 0 | ... R10: ='KH DAY DAI'!P24 -> 0 | S10: =SUM(G10:R10) -> 0
B11: 2.2
B12: 2.3
B13: 2.4 | C13: Khác | S13: =SUM(G13:R13) -> 0
B14: 3 | C14: BIẾN PHÍ | D14: =D15+D23 -> 0 | E14: =E15+E23 -> 0 | G14: =G15+G23 -> 0 | H14: =H15+H23 -> 0 | I14: =I15+I23 -> 0 | J14: =J15+J23 -> 0 | K14: =K15+K23 -> 0 | L14: =L15+L23 -> 0 | M14: =M15+M23 -> 0 | N14: =N15+N23 -> 0 | ... R14: =R15+R23 -> 0 | S14: =SUM(G14:R14) -> 0
B15: 3.1 | C15: BIẾN PHÍ SẢN XUẤT | D15: =D16+D20+D21+D22 -> 0 | E15: =E16+E20+E21+E22 -> 0 | G15: =G16+G20+G21+G22 -> 0 | H15: =H16+H20+H21+H22 -> 0 | I15: =I16+I20+I21+I22 -> 0 | J15: =J16+J20+J21+J22 -> 0 | K15: =K16+K20+K21+K22 -> 0 | L15: =L16+L20+L21+L22 -> 0 | M15: =M16+M20+M21+M22 -> 0 | N15: =N16+N20+N21+N22 -> 0 | ... R15: =R16+R20+R21+R22 -> 0 | S15: =SUM(G15:R15) -> 0
B16: 3.1.1 | C16: Nguyên vật liệu chính (nhựa, gồm hao hụt) | G16: =SUM('KH DAY DAI'!E25:E26,'KH DAY DAI'!E33) -> 0 | H16: =SUM('KH DAY DAI'!F25:F26,'KH DAY DAI'!F33) -> 0 | I16: =SUM('KH DAY DAI'!G25:G26,'KH DAY DAI'!G33) -> 0 | J16: =SUM('KH DAY DAI'!H25:H26,'KH DAY DAI'!H33) -> 0 | K16: =SUM('KH DAY DAI'!I25:I26,'KH DAY DAI'!I33) -> 0 | L16: =SUM('KH DAY DAI'!J25:J26,'KH DAY DAI'!J33) -> 0 | M16: =SUM('KH DAY DAI'!K25:K26,'KH DAY DAI'!K33) -> 0 | N16: =SUM('KH DAY DAI'!L25:L26,'KH DAY DAI'!L33) -> 0 | ... R16: =SUM('KH DAY DAI'!P25:P26,'KH DAY DAI'!P33) -> 0 | S16: =SUM(G16:R16) -> 0
B17: 3.1.2 | C17: Trong đó: i/ Hao hụt CĐ phân loại chai | G17: =SUM('KH DAY DAI'!E26,'KH DAY DAI'!E33) -> 0 | H17: =SUM('KH DAY DAI'!F26,'KH DAY DAI'!F33) -> 0 | I17: =SUM('KH DAY DAI'!G26,'KH DAY DAI'!G33) -> 0 | J17: =SUM('KH DAY DAI'!H26,'KH DAY DAI'!H33) -> 0 | K17: =SUM('KH DAY DAI'!I26,'KH DAY DAI'!I33) -> 0 | L17: =SUM('KH DAY DAI'!J26,'KH DAY DAI'!J33) -> 0 | M17: =SUM('KH DAY DAI'!K26,'KH DAY DAI'!K33) -> 0 | N17: =SUM('KH DAY DAI'!L26,'KH DAY DAI'!L33) -> 0 | ... R17: =SUM('KH DAY DAI'!P26,'KH DAY DAI'!P33) -> 0 | S17: =SUM(G17:R17) -> 0
C18: ii/ Hao hụt CĐ băm vảy | S18: =SUM(G18:R18) -> 0
B19: 3.1.3 | C19: % chi phí nguyên liệu/doanh thu | D19: =IFERROR(D16/$F$9,0) -> 0 | E19: =IFERROR(E16/$F$9,0) -> 0 | F19: =IFERROR(F16/$F$9,0) -> 0 | G19: =G16/G9 -> #DIV/0! | H19: =H16/H9 -> #DIV/0! | I19: =I16/I9 -> #DIV/0! | J19: =J16/J9 -> #DIV/0! | K19: =K16/K9 -> #DIV/0! | L19: =L16/L9 -> #DIV/0! | M19: =M16/M9 -> #DIV/0! | N19: =N16/N9 -> #DIV/0! | ... S19: =S16/S9 -> #DIV/0!
B20: 3.1.4 | C20: Nguyên vật liệu phụ | G20: ='KH DAY DAI'!E27 -> 0 | H20: ='KH DAY DAI'!F27 -> 0 | I20: ='KH DAY DAI'!G27 -> 0 | J20: ='KH DAY DAI'!H27 -> 0 | K20: ='KH DAY DAI'!I27 -> 0 | L20: ='KH DAY DAI'!J27 -> 0 | M20: ='KH DAY DAI'!K27 -> 0 | N20: ='KH DAY DAI'!L27 -> 0 | ... R20: ='KH DAY DAI'!P27 -> 0 | S20: =SUM(G20:R20) -> 0
B21: 3.1.5 | C21: Điện sản xuất | G21: ='KH DAY DAI'!E28 -> 0 | H21: ='KH DAY DAI'!F28 -> 0 | I21: ='KH DAY DAI'!G28 -> 0 | J21: ='KH DAY DAI'!H28 -> 0 | K21: ='KH DAY DAI'!I28 -> 0 | L21: ='KH DAY DAI'!J28 -> 0 | M21: ='KH DAY DAI'!K28 -> 0 | N21: ='KH DAY DAI'!L28 -> 0 | ... R21: ='KH DAY DAI'!P28 -> 0 | S21: =SUM(G21:R21) -> 0
B22: 3.1.6 | C22: Nhân công trực tiếp | G22: ='KH DAY DAI'!E29 -> 0 | H22: ='KH DAY DAI'!F29 -> 0 | I22: ='KH DAY DAI'!G29 -> 0 | J22: ='KH DAY DAI'!H29 -> 0 | K22: ='KH DAY DAI'!I29 -> 0 | L22: ='KH DAY DAI'!J29 -> 0 | M22: ='KH DAY DAI'!K29 -> 0 | N22: ='KH DAY DAI'!L29 -> 0 | ... R22: ='KH DAY DAI'!P29 -> 0 | S22: =SUM(G22:R22) -> 0
B23: 3.2 | C23: BIẾN PHÍ BÁN HÀNG | D23: =D24 -> 0 | E23: =E24 -> 0 | F23: =F24 -> 0 | G23: =G24 -> 0 | H23: =H24 -> 0 | I23: =I24 -> 0 | J23: =J24 -> 0 | K23: =K24 -> 0 | ... R23: =R24 -> 0 | S23: =SUM(G23:R23) -> 0
C24: Chi phí vận chuyển | G24: ='KH DAY DAI'!E36 -> 0 | H24: ='KH DAY DAI'!F36 -> 0 | I24: ='KH DAY DAI'!G36 -> 0 | J24: ='KH DAY DAI'!H36 -> 0 | K24: ='KH DAY DAI'!I36 -> 0 | L24: ='KH DAY DAI'!J36 -> 0 | M24: ='KH DAY DAI'!K36 -> 0 | N24: ='KH DAY DAI'!L36 -> 0 | ... R24: ='KH DAY DAI'!P36 -> 0 | S24: =SUM(G24:R24) -> 0
B25: 4 | C25: LÃI SAU BIẾN PHÍ | D25: =D9-D14 -> 0 | E25: =E9-E14 -> 0 | F25: =F9-F14 -> 0 | G25: =G9-G14 -> 0 | H25: =H9-H14 -> 0 | I25: =I9-I14 -> 0 | J25: =J9-J14 -> 0 | K25: =K9-K14 -> 0 | ... R25: =R9-R14 -> 0 | S25: =SUM(G25:R25) -> 0
B26: 4.1 | C26: % lãi biến phí/doanh thu | D26: =IFERROR(D23/$F$9,0) -> 0 | E26: =IFERROR(E23/$F$9,0) -> 0 | F26: =IFERROR(F23/$F$9,0) -> 0 | G26: =G25/G9 -> #DIV/0! | H26: =H25/H9 -> #DIV/0! | I26: =I25/I9 -> #DIV/0! | J26: =J25/J9 -> #DIV/0! | K26: =K25/K9 -> #DIV/0! | L26: =L25/L9 -> #DIV/0! | M26: =M25/M9 -> #DIV/0! | N26: =N25/N9 -> #DIV/0! | ... S26: =S25/S9 -> #DIV/0!
B27: 5 | C27: CHI PHÍ SẢN XUẤT CHUNG | D27: =D28+D29+D30 -> 0 | E27: =E28+E29+E30 -> 0 | F27: =F28+F29+F30 -> 0 | G27: =G28+G29+G30 -> 0 | H27: =H28+H29+H30 -> 0 | I27: =I28+I29+I30 -> 0 | J27: =J28+J29+J30 -> 0 | K27: =K28+K29+K30 -> 0 | ... R27: =R28+R29+R30 -> 0 | S27: =SUM(G27:R27) -> 0
B28: 5.1 | C28: Lương gián tiếp Sản xuất | G28: ='KH DAY DAI'!E31 -> 0 | H28: ='KH DAY DAI'!F31 -> 0 | I28: ='KH DAY DAI'!G31 -> 0 | J28: ='KH DAY DAI'!H31 -> 0 | K28: ='KH DAY DAI'!I31 -> 0 | L28: ='KH DAY DAI'!J31 -> 0 | M28: ='KH DAY DAI'!K31 -> 0 | N28: ='KH DAY DAI'!L31 -> 0 | ... R28: ='KH DAY DAI'!P31 -> 0 | S28: =SUM(G28:R28) -> 0
B29: 5.2 | C29: Chi phí thuê xưởng | S29: =SUM(G29:R29) -> 0
B30: 5.3 | C30: Chi phí sản xuất (Ngoài lương, BOM, thuê xưởng, khấu hao) | G30: =SUM('KH DAY DAI'!E30) -> 0 | H30: =SUM('KH DAY DAI'!F30) -> 0 | I30: =SUM('KH DAY DAI'!G30) -> 0 | J30: =SUM('KH DAY DAI'!H30) -> 0 | K30: =SUM('KH DAY DAI'!I30) -> 0 | L30: =SUM('KH DAY DAI'!J30) -> 0 | M30: =SUM('KH DAY DAI'!K30) -> 0 | N30: =SUM('KH DAY DAI'!L30) -> 0 | ... R30: =SUM('KH DAY DAI'!P30) -> 0 | S30: =SUM(G30:R30) -> 0
B31: 6 | C31: CHI PHÍ KHẤU HAO, CCDC | G31: ='KH DAY DAI'!E32 -> 0 | H31: ='KH DAY DAI'!F32 -> 0 | I31: ='KH DAY DAI'!G32 -> 0 | J31: ='KH DAY DAI'!H32 -> 0 | K31: ='KH DAY DAI'!I32 -> 0 | L31: ='KH DAY DAI'!J32 -> 0 | M31: ='KH DAY DAI'!K32 -> 0 | N31: ='KH DAY DAI'!L32 -> 0 | ... R31: ='KH DAY DAI'!P32 -> 0 | S31: =SUM(G31:R31) -> 0
B32: 7 | C32: LỢI NHUẬN GỘP | D32: =D25-D27-D31 -> 0 | E32: =E25-E27-E31 -> 0 | F32: =F25-F27-F31 -> 0 | G32: =G25-G27-G31 -> 0 | H32: =H25-H27-H31 -> 0 | I32: =I25-I27-I31 -> 0 | J32: =J25-J27-J31 -> 0 | K32: =K25-K27-K31 -> 0 | ... R32: =R25-R27-R31 -> 0 | S32: =SUM(G32:R32) -> 0
B33: 7.1 | C33: % lãi gộp/doanh thu | D33: =IFERROR(D30/$F$9,0) -> 0 | E33: =IFERROR(E30/$F$9,0) -> 0 | F33: =IFERROR(F30/$F$9,0) -> 0 | G33: =G32/G9 -> #DIV/0! | H33: =H32/H9 -> #DIV/0! | I33: =I32/I9 -> #DIV/0! | J33: =J32/J9 -> #DIV/0! | K33: =K32/K9 -> #DIV/0! | L33: =L32/L9 -> #DIV/0! | M33: =M32/M9 -> #DIV/0! | N33: =N32/N9 -> #DIV/0! | ... S33: =S32/S9 -> #DIV/0!
B34: 8 | C34: CHI PHÍ BÁN HÀNG & MKT & R&D | D34: =D35+D36+D37 -> 0 | E34: =E35+E36+E37 -> 0 | F34: =F35+F36+F37 -> 0 | G34: =G35+G36+G37 -> 0 | H34: =H35+H36+H37 -> 0 | I34: =I35+I36+I37 -> 0 | J34: =J35+J36+J37 -> 0 | K34: =K35+K36+K37 -> 0 | ... R34: =R35+R36+R37 -> 0 | S34: =SUM(G34:R34) -> 0
B35: 8.1 | C35: Lương | S35: =SUM(G35:R35) -> 0
B36: 8.2 | C36: Chi phí bán hàng (ngoài lương, khấu hao) | G36: =SUM('KH DAY DAI'!E34:E35) -> 0 | H36: =SUM('KH DAY DAI'!F34:F35) -> 0 | I36: =SUM('KH DAY DAI'!G34:G35) -> 0 | J36: =SUM('KH DAY DAI'!H34:H35) -> 0 | K36: =SUM('KH DAY DAI'!I34:I35) -> 0 | L36: =SUM('KH DAY DAI'!J34:J35) -> 0 | M36: =SUM('KH DAY DAI'!K34:K35) -> 0 | N36: =SUM('KH DAY DAI'!L34:L35) -> 0 | ... R36: =SUM('KH DAY DAI'!P34:P35) -> 0 | S36: =SUM(G36:R36) -> 0
B37: 8.3 | C37: Khấu hao tài sản | S37: =SUM(G37:R37) -> 0
B38: 9 | C38: CHI PHÍ QUẢN LÝ | D38: =D39+D40+D41 -> 0 | E38: =E39+E40+E41 -> 0 | F38: =F39+F40+F41 -> 0 | G38: =G39+G40+G41 -> 0 | H38: =H39+H40+H41 -> 0 | I38: =I39+I40+I41 -> 0 | J38: =J39+J40+J41 -> 0 | K38: =K39+K40+K41 -> 0 | ... R38: =R39+R40+R41 -> 0 | S38: =SUM(G38:R38) -> 0
B39: 9.1 | C39: Lương | S39: =SUM(G39:R39) -> 0
B40: 9.2 | C40: Chi phí quản lý (ngoài lương, khấu hao) | S40: =SUM(G40:R40) -> 0
B41: 9.3 | C41: Khấu hao tài sản | S41: =SUM(G41:R41) -> 0
B42: 10 | C42: DOANH THU/CHI PHÍ KHÁC | S42: =SUM(G42:R42) -> 0 | U42: <= Nhập số liệu
B43: 11 | C43: LỢI NHUẬN THUẦN TỪ HOẠT ĐỘNG KINH DOANH | D43: =D32-D34-D38+D42 -> 0 | E43: =E32-E34-E38+E42 -> 0 | F43: =F32-F34-F38+F42 -> 0 | G43: =G32-G34-G38+G42 -> 0 | H43: =H32-H34-H38+H42 -> 0 | I43: =I32-I34-I38+I42 -> 0 | J43: =J32-J34-J38+J42 -> 0 | K43: =K32-K34-K38+K42 -> 0 | ... R43: =R32-R34-R38+R42 -> 0 | S43: =SUM(G43:R43) -> 0 | T43: =S9-S14-S27-S34-S31 -> 0
B44: 12 | C44: DOANH THU TÀI CHÍNH | S44: =SUM(G44:R44) -> 0 | U44: <= Nhập số liệu
B45: 13 | C45: CHI PHÍ TÀI CHÍNH | S45: =SUM(G45:R45) -> 0 | U45: <= Nhập số liệu
B46: 13.1 | C46: Trong đó: chi phí lãi vay | S46: =SUM(G46:R46) -> 0
B47: 14 | C47: LỢI NHUẬN TRƯỚC THUẾ | D47: =D43+D44-D45 -> 0 | E47: =E43+E44-E45 -> 0 | F47: =F43+F44-F45 -> 0 | G47: =G43+G44-G45 -> 0 | H47: =H43+H44-H45 -> 0 | I47: =I43+I44-I45 -> 0 | J47: =J43+J44-J45 -> 0 | K47: =K43+K44-K45 -> 0 | ... R47: =R43+R44-R45 -> 0 | S47: =SUM(G47:R47) -> 0
B48: 15 | C48: THUẾ TNDN | S48: =SUM(G48:R48) -> 0 | U48: <= Nhập số liệu
B49: 16 | C49: LỢI NHUẬN SAU THUẾ | D49: =D47-D48 -> 0 | E49: =E47-E48 -> 0 | F49: =F47-F48 -> 0 | G49: =G47-G48 -> 0 | H49: =H47-H48 -> 0 | I49: =I47-I48 -> 0 | J49: =J47-J48 -> 0 | K49: =K47-K48 -> 0 | ... R49: =R47-R48 -> 0 | S49: =SUM(G49:R49) -> 0
B50: 16.1 | C50: % LNST/doanh thu | D50: =IFERROR(D47/$F$9,0) -> 0 | E50: =IFERROR(E47/$F$9,0) -> 0 | F50: =IFERROR(F47/$F$9,0) -> 0 | G50: =G49/G9 -> #DIV/0! | H50: =H49/H9 -> #DIV/0! | I50: =I49/I9 -> #DIV/0! | J50: =J49/J9 -> #DIV/0! | K50: =K49/K9 -> #DIV/0! | L50: =L49/L9 -> #DIV/0! | M50: =M49/M9 -> #DIV/0! | N50: =N49/N9 -> #DIV/0! | ... S50: =S49/S9 -> #DIV/0!
B51: 17 | C51: Khấu hao tài sản | G51: =G31 -> 0 | H51: =H31 -> 0 | I51: =I31 -> 0 | J51: =J31 -> 0 | K51: =K31 -> 0 | L51: =L31 -> 0 | M51: =M31 -> 0 | N51: =N31 -> 0 | ... R51: =R31 -> 0 | S51: =SUM(G51:R51) -> 0
B52: 18 | C52: LỢI NHUẬN KHÔNG BAO GỒM KHẤU HAO, LÃI VAY | D52: =D49+D51 -> 0 | E52: =E49+E51 -> 0 | F52: =F49+F51 -> 0 | G52: =G49+G51 -> 0 | H52: =H49+H51 -> 0 | I52: =I49+I51 -> 0 | J52: =J49+J51 -> 0 | K52: =K49+K51 -> 0 | ... R52: =R49+R51 -> 0 | S52: =SUM(G52:R52) -> 0
B53: 18.1 | C53: % LN không gồm khấu hao/doanh thu | D53: =IFERROR(D50/$F$9,0) -> 0 | E53: =IFERROR(E50/$F$9,0) -> 0 | F53: =IFERROR(F50/$F$9,0) -> 0 | G53: =G52/G9 -> #DIV/0! | H53: =H52/H9 -> #DIV/0! | I53: =I52/I9 -> #DIV/0! | J53: =J52/J9 -> #DIV/0! | K53: =K52/K9 -> #DIV/0! | L53: =L52/L9 -> #DIV/0! | M53: =M52/M9 -> #DIV/0! | N53: =N52/N9 -> #DIV/0! | ... S53: =S52/S9 -> #DIV/0!
B56: 1. Hòa vốn (Bao gồm khấu hao) | D56: =D4 -> Thực tế năm 2023 | E56: =E4 -> Thực tế năm 2024 | F56: =F4 -> KQKD 2025 | G56: =G4 -> T1 | H56: =H4 -> T2 | I56: =I4 -> T3 | J56: =J4 -> T4 | K56: =K4 -> T5 | ... S56: =S4 -> KH 2026
B57: Sản lượng NVL hòa vốn (tấn) | D57: =IFERROR(D$58*(1+(D$17+D$18)/D$16),0) -> 0 | E57: =IFERROR(E$58*(1+(E$17+E$18)/E$16),0) -> 0 | F57: =IFERROR(F$58*(1+(F$17+F$18)/F$16),0) -> 0 | G57: =G$58*(1+(G$17+G$18)/G$16) -> #DIV/0! | H57: =H$58*(1+(H$17+H$18)/H$16) -> #DIV/0! | I57: =I$58*(1+(I$17+I$18)/I$16) -> #DIV/0! | J57: =J$58*(1+(J$17+J$18)/J$16) -> #DIV/0! | K57: =K$58*(1+(K$17+K$18)/K$16) -> #DIV/0! | L57: =L$58*(1+(L$17+L$18)/L$16) -> #DIV/0! | M57: =M$58*(1+(M$17+M$18)/M$16) -> #DIV/0! | N57: =N$58*(1+(N$17+N$18)/N$16) -> #DIV/0! | ... S57: =S$58*(1+(S$17+S$18)/S$16) -> #DIV/0!
B58: Sản lượng thành phẩm hòa vốn (tấn) | D58: =IFERROR((D$27+D$31+D$34+D$38)/(D$25/D$5),0) -> 0 | E58: =IFERROR((E$27+E$31+E$34+E$38)/(E$25/E$5),0) -> 0 | F58: =IFERROR((F$27+F$31+F$34+F$38)/(F$25/F$5),0) -> 0 | G58: =(G$27+G$31+G$34+G$38)/(G$25/G$5) -> #DIV/0! | H58: =(H$27+H$31+H$34+H$38)/(H$25/H$5) -> #DIV/0! | I58: =(I$27+I$31+I$34+I$38)/(I$25/I$5) -> #DIV/0! | J58: =(J$27+J$31+J$34+J$38)/(J$25/J$5) -> #DIV/0! | K58: =(K$27+K$31+K$34+K$38)/(K$25/K$5) -> #DIV/0! | L58: =(L$27+L$31+L$34+L$38)/(L$25/L$5) -> #DIV/0! | M58: =(M$27+M$31+M$34+M$38)/(M$25/M$5) -> #DIV/0! | N58: =(N$27+N$31+N$34+N$38)/(N$25/N$5) -> #DIV/0! | ... S58: =(S$27+S$31+S$34+S$38)/(S$25/S$5) -> #DIV/0!
B59: Doanh thu hòa vốn (triệu đồng) | D59: =IFERROR(D$58*(D$9/D$5),0) -> 0 | E59: =IFERROR(E$58*(E$9/E$5),0) -> 0 | F59: =IFERROR(F$58*(F$9/F$5),0) -> 0 | G59: =G$58*(G$9/G$5) -> #DIV/0! | H59: =H$58*(H$9/H$5) -> #DIV/0! | I59: =I$58*(I$9/I$5) -> #DIV/0! | J59: =J$58*(J$9/J$5) -> #DIV/0! | K59: =K$58*(K$9/K$5) -> #DIV/0! | L59: =L$58*(L$9/L$5) -> #DIV/0! | M59: =M$58*(M$9/M$5) -> #DIV/0! | N59: =N$58*(N$9/N$5) -> #DIV/0! | ... S59: =S$58*(S$9/S$5) -> #DIV/0!
B60: 2. Hòa vốn (Không bao gồm khấu hao) | D60: =D56 -> Thực tế năm 2023 | E60: =E56 -> Thực tế năm 2024 | F60: =F56 -> KQKD 2025 | G60: =G56 -> T1 | H60: =H56 -> T2 | I60: =I56 -> T3 | J60: =J56 -> T4 | K60: =K56 -> T5 | ... S60: =S56 -> KH 2026
B61: Sản lượng NVL hòa vốn (tấn) | D61: =IFERROR(D$62*(1+(D$17+D$18)/D$16),0) -> 0 | E61: =IFERROR(E$62*(1+(E$17+E$18)/E$16),0) -> 0 | F61: =IFERROR(F$62*(1+(F$17+F$18)/F$16),0) -> 0 | G61: =G$62*(1+(G$17+G$18)/G$16) -> #DIV/0! | H61: =H$62*(1+(H$17+H$18)/H$16) -> #DIV/0! | I61: =I$62*(1+(I$17+I$18)/I$16) -> #DIV/0! | J61: =J$62*(1+(J$17+J$18)/J$16) -> #DIV/0! | K61: =K$62*(1+(K$17+K$18)/K$16) -> #DIV/0! | L61: =L$62*(1+(L$17+L$18)/L$16) -> #DIV/0! | M61: =M$62*(1+(M$17+M$18)/M$16) -> #DIV/0! | N61: =N$62*(1+(N$17+N$18)/N$16) -> #DIV/0! | ... S61: =S$62*(1+(S$17+S$18)/S$16) -> #DIV/0!
B62: Sản lượng thành phẩm hòa vốn (tấn) | D62: =IFERROR((D$27+D$31+D$34+D$38-D51)/(D$25/D$5),0) -> 0 | E62: =IFERROR((E$27+E$31+E$34+E$38-E51)/(E$25/E$5),0) -> 0 | F62: =IFERROR((F$27+F$31+F$34+F$38-F51)/(F$25/F$5),0) -> 0 | G62: =(G$27+G$31+G$34+G$38-G51)/(G$25/G$5) -> #DIV/0! | H62: =(H$27+H$31+H$34+H$38-H51)/(H$25/H$5) -> #DIV/0! | I62: =(I$27+I$31+I$34+I$38-I51)/(I$25/I$5) -> #DIV/0! | J62: =(J$27+J$31+J$34+J$38-J51)/(J$25/J$5) -> #DIV/0! | K62: =(K$27+K$31+K$34+K$38-K51)/(K$25/K$5) -> #DIV/0! | L62: =(L$27+L$31+L$34+L$38-L51)/(L$25/L$5) -> #DIV/0! | M62: =(M$27+M$31+M$34+M$38-M51)/(M$25/M$5) -> #DIV/0! | N62: =(N$27+N$31+N$34+N$38-N51)/(N$25/N$5) -> #DIV/0! | ... S62: =(S$27+S$31+S$34+S$38-S51)/(S$25/S$5) -> #DIV/0!
B63: Doanh thu hòa vốn (triệu đồng) | D63: =IFERROR(D$62*(D$9/D$5),0) -> 0 | E63: =IFERROR(E$62*(E$9/E$5),0) -> 0 | F63: =IFERROR(F$62*(F$9/F$5),0) -> 0 | G63: =G$62*(G$9/G$5) -> #DIV/0! | H63: =H$62*(H$9/H$5) -> #DIV/0! | I63: =I$62*(I$9/I$5) -> #DIV/0! | J63: =J$62*(J$9/J$5) -> #DIV/0! | K63: =K$62*(K$9/K$5) -> #DIV/0! | L63: =L$62*(L$9/L$5) -> #DIV/0! | M63: =M$62*(M$9/M$5) -> #DIV/0! | N63: =N$62*(N$9/N$5) -> #DIV/0! | ... S63: =S$62*(S$9/S$5) -> #DIV/0!

Sheet KH DAY DAI
B2: 1. Dây đai
B4: STT | C4: Nội dung | D4: Tỷ lệ | E4: 1 | F4: =+E4+1 -> 2 | G4: =+F4+1 -> 3 | H4: =+G4+1 -> 4 | I4: =+H4+1 -> 5 | J4: =+I4+1 -> 6 | K4: =+J4+1 -> 7 | L4: =+K4+1 -> 8 | M4: =+L4+1 -> 9 | ... P4: =+O4+1 -> 12
B5: 1 | C5: Sản lượng sản xuất (tấn) | E5: =300*16*30/10^3 -> 144 | F5: =300*16*30/10^3 -> 144 | G5: =300*16*30/10^3 -> 144 | H5: =300*16*30/10^3 -> 144 | I5: =300*16*30/10^3 -> 144 | J5: =300*16*30/10^3 -> 144 | K5: =300*16*30/10^3 -> 144 | L5: =300*16*30/10^3 -> 144 | ... P5: =300*16*30/10^3 -> 144 | Q5: =400 -> 400
B6: 2 | C6: Giá bán | E6: 19000 | F6: 19000 | G6: 19000 | H6: 19000 | I6: 19000 | J6: 19000 | K6: 19000 | L6: 19000 | M6: 19000 | N6: 19000 | O6: 19000 | P6: 19000
B7: 3 | C7: Giá vốn (bao gồm CP hoa hồng) | E7: =SUM(E8,E12:E21) -> 17207.846 | F7: =SUM(F8,F12:F21) -> 17207.846 | G7: =SUM(G8,G12:G21) -> 17207.846 | H7: =SUM(H8,H12:H21) -> 17207.846 | I7: =SUM(I8,I12:I21) -> 17207.846 | J7: =SUM(J8,J12:J21) -> 17207.846 | K7: =SUM(K8,K12:K21) -> 17207.846 | L7: =SUM(L8,L12:L21) -> 17207.846 | ... P7: =SUM(P8,P12:P21) -> 17207.846
B8: 3.1 | C8: Chi phí nguyên vật liệu | E8: =+SUM(E9:E11) -> 8840 | F8: =+SUM(F9:F11) -> 8840 | G8: =+SUM(G9:G11) -> 8840 | H8: =+SUM(H9:H11) -> 8840 | I8: =+SUM(I9:I11) -> 8840 | J8: =+SUM(J9:J11) -> 8840 | K8: =+SUM(K9:K11) -> 8840 | L8: =+SUM(L9:L11) -> 8840 | ... P8: =+SUM(P9:P11) -> 8840
C9: Phó Sản PET GC Dây Đai | D9: 0.5 | E9: =8000*$D9 -> 4000 | F9: =8000*$D9 -> 4000 | G9: =8000*$D9 -> 4000 | H9: =8000*$D9 -> 4000 | I9: =8000*$D9 -> 4000 | J9: =8000*$D9 -> 4000 | K9: =8000*$D9 -> 4000 | L9: =8000*$D9 -> 4000 | ... P9: =8000*$D9 -> 4000
C10: Phó Sản PET Đầu Keo | D10: 0.35 | E10: 2800 | F10: 2800 | G10: 2800 | H10: 2800 | I10: 2800 | J10: 2800 | K10: 2800 | L10: 2800 | M10: 2800 | N10: 2800 | O10: 2800 | P10: 2800
C11: Vảy PET B4_A3 | D11: 0.15 | E11: 2040 | F11: 2040 | G11: 2040 | H11: 2040 | I11: 2040 | J11: 2040 | K11: 2040 | L11: 2040 | M11: 2040 | N11: 2040 | O11: 2040 | P11: 2040
B12: 3.2 | C12: Phó sản, hao hụt | E12: 365.39084 | F12: 365.39084 | G12: 365.39084 | H12: 365.39084 | I12: 365.39084 | J12: 365.39084 | K12: 365.39084 | L12: 365.39084 | M12: 365.39084 | N12: 365.39084 | O12: 365.39084 | P12: 365.39084
B13: 3.3 | C13: Hóa chất rửa vảy | E13: 36.24378 | F13: 36.24378 | G13: 36.24378 | H13: 36.24378 | I13: 36.24378 | J13: 36.24378 | K13: 36.24378 | L13: 36.24378 | M13: 36.24378 | N13: 36.24378 | O13: 36.24378 | P13: 36.24378
B14: 3.4 | C14: Điện, nước | E14: 212.12234 | F14: 212.12234 | G14: 212.12234 | H14: 212.12234 | I14: 212.12234 | J14: 212.12234 | K14: 212.12234 | L14: 212.12234 | M14: 212.12234 | N14: 212.12234 | O14: 212.12234 | P14: 212.12234
B15: 3.5 | C15: Nhân công trực tiếp | E15: 240.68287 | F15: 240.68287 | G15: 240.68287 | H15: 240.68287 | I15: 240.68287 | J15: 240.68287 | K15: 240.68287 | L15: 240.68287 | M15: 240.68287 | N15: 240.68287 | O15: 240.68287 | P15: 240.68287 | Q15: =48000*2 -> 96000 | R15: =Q15/Q5 -> 240
B16: 3.6 | C16: Vật tư phân xưởng | E16: 58.638979 | F16: 58.638979 | G16: 58.638979 | H16: 58.638979 | I16: 58.638979 | J16: 58.638979 | K16: 58.638979 | L16: 58.638979 | M16: 58.638979 | N16: 58.638979 | O16: 58.638979 | P16: 58.638979
B17: 3.7 | C17: Lương gián tiếp sx | E17: 217.51578 | F17: 217.51578 | G17: 217.51578 | H17: 217.51578 | I17: 217.51578 | J17: 217.51578 | K17: 217.51578 | L17: 217.51578 | M17: 217.51578 | N17: 217.51578 | O17: 217.51578 | P17: 217.51578
B18: 3.8 | C18: Khấu hao | E18: 421.56543 | F18: 421.56543 | G18: 421.56543 | H18: 421.56543 | I18: 421.56543 | J18: 421.56543 | K18: 421.56543 | L18: 421.56543 | M18: 421.56543 | N18: 421.56543 | O18: 421.56543 | P18: 421.56543 | Q18: =6200000000/12/12 -> 43055556 | R18: =Q18/E5 -> 298996.91
C19: Tỷ lệ hao hụt nguyên liệu gia công | D19: 0.04 | E19: =+SUM(E9:E18)*$D19 -> 415.6864 | F19: =+SUM(F9:F18)*$D19 -> 415.6864 | G19: =+SUM(G9:G18)*$D19 -> 415.6864 | H19: =+SUM(H9:H18)*$D19 -> 415.6864 | I19: =+SUM(I9:I18)*$D19 -> 415.6864 | J19: =+SUM(J9:J18)*$D19 -> 415.6864 | K19: =+SUM(K9:K18)*$D19 -> 415.6864 | L19: =+SUM(L9:L18)*$D19 -> 415.6864 | ... P19: =+SUM(P9:P18)*$D19 -> 415.6864
C20: Chi phí gia công | E20: 5000 | F20: 5000 | G20: 5000 | H20: 5000 | I20: 5000 | J20: 5000 | K20: 5000 | L20: 5000 | M20: 5000 | N20: 5000 | O20: 5000 | P20: 5000
C21: Chi phí hoa hồng | D21: =E21/E$6 -> 0.073684211 | E21: =(E6-5000)*10% -> 1400 | F21: =(F6-5000)*10% -> 1400 | G21: =(G6-5000)*10% -> 1400 | H21: =(H6-5000)*10% -> 1400 | I21: =(I6-5000)*10% -> 1400 | J21: =(J6-5000)*10% -> 1400 | K21: =(K6-5000)*10% -> 1400 | L21: =(L6-5000)*10% -> 1400 | ... P21: =(P6-5000)*10% -> 1400
C23: Thành Phẩm Bán
C24: Doanh thu
C25: CP NVL
C26: Hao hụt
C27: Hóa chất
C28: Điện, nước
C29: Nhân công trực tiếp
C30: Vật tư phân xưởng
C31: Lương gián tiếp sx
C32: Khấu hao
C33: Tỷ lệ hao hụt nguyên liệu gia công
C34: Chi phí gia công
... C42: Vảy B4_A3
C43: Phó Sản PET Đầu Keo | D43: 0.15
C44: HH 4%

Sheet Cong suat
B3: CÔNG SUẤT
B4: I - CÔNG SUẤT CHUYỀN LỰA CHAI - CHAI XÁ TRÒN | E4: SX Chai B1.1 | F4: Loại B2.2, B4, B5, B6.2 | H4: Loại kim loại, chai còn nhãn
B5: STT | C5: Công đoạn sản xuất | D5: Cấp liệu | E5: Lồng tách tạp chất | F5: Lựa phân loại chai | G5: Tách nhãn | H5: Lựa phân loại chai sau tách nhãn | I5: Ép kiện | J5: Xử lý phó sản, nắp, cổ chai | K5: Công suất thành phẩm cả chuyền
B6: 1 | C6: Năng suất THIẾT KẾ (Kg NVL đầu vào / giờ) | D6: 1500 | E6: 1500 | F6: 1500 | G6: 1.100-1.500 | H6: 1100 | I6: 1400 | K6: =D6*(100%-$D$14) -> 1335
B7: 2 | C7: Năng suất ĐỊNH MỨC (Kg NVL đầu vào / giờ) | D7: 1400 | E7: 1200 | F7: 1200 | G7: =D7*95% -> 1330 | H7: =D7*90% -> 1260 | I7: 1300 | K7: =E15 -> 1246
B8: 3 | C8: Định mức nhân công (Số NV / Ca8) | D8: 2 | E8: 2 | F8: =4+1 -> 5 | G8: 1 | H8: =5 -> 5 | I8: =1 -> 1 | J8: 2 | K8: =SUM(D8:J8) -> 18
C9: Diễn giải
B11: STT | C11: Chỉ tiêu định mức | D11: ĐVT | E11: ĐM 1 giờ | F11: ĐM 1 Ca8 | G11: ĐM 1 Ca12 | H11: ĐM 2 Ca8 | I11: ĐM 2 Ca12
B12: 1 | C12: Tổng nhân sự: | D12: Người | E12: =K8 -> 18 | F12: =$E12 -> 18 | G12: =$F12*1.5 -> 27 | H12: =$F12*2 -> 36 | I12: =$G12*2 -> 54
B13: 2 | C13: Định mức NVL đầu vào: | D13: kg/giờ | E13: =D7 -> 1400 | F13: =$E13*8 -> 11200 | G13: =$F13*1.5 -> 16800 | H13: =$F13*2 -> 22400 | I13: =$G13*2 -> 33600
B14: 3 | C14: Hao hụt: | D14: ='2.Hao hut & % chai '!$N$8 -> 0.11 | E14: =E13*$D$14 -> 154 | F14: =$E14*8 -> 1232 | G14: =$E14*12 -> 1848 | H14: =$F14*2 -> 2464 | I14: =$G14*2 -> 3696
B15: 4 | C15: Định mức thành phẩm: | D15: kg/giờ | E15: =E13-E14 -> 1246 | F15: =$E15*8 -> 9968 | G15: =$F15*1.5 -> 14952 | H15: =$F15*2 -> 19936 | I15: =$G15*2 -> 29904
B16: 5 | C16: Định mức thành phẩm/người: | D16: kg/giờ/người | E16: =E15/K8 -> 69.222222 | F16: =$E16*8 -> 553.77778 | G16: =$F16*1.5 -> 830.66667 | H16: =$F16*2 -> 1107.5556 | I16: =$G16*2 -> 1661.3333
B18: II - CÔNG SUẤT CHUYỀN LỰA CHAI - CHAI ÉP KIỆN
B19: STT | C19: Công đoạn sản xuất | D19: Cấp liệu | E19: Phá kiện (thủ công bằng tay) | F19: Lựa phân loại chai | G19: Tách nhãn | H19: Lựa phân loại chai sau tách nhãn | I19: Ép kiện | J19: Xử lý phó sản, nắp, cổ chai | K19: Công suất thành phẩm cả chuyền
B20: 1 | C20: Năng suất THIẾT KẾ (Kg NVL đầu vào / giờ) | D20: 1500 | F20: 1500 | G20: 1.100-1.500 | H20: 1100 | I20: 1400 | K20: =D20*(100%-$D$14) -> 1335
B21: 2 | C21: Năng suất ĐỊNH MỨC (Kg NVL đầu vào / giờ) | D21: 1400 | E21: =D21 -> 1400 | F21: =E21 -> 1400 | G21: =F21 -> 1400 | H21: =G21 -> 1400 | I21: 1300 | K21: =E29 -> 1218
B22: 3 | C22: Định mức nhân công (Số NV / Ca8) | D22: 2 | E22: 2 | F22: =3+1+1 -> 5 | G22: 1 | H22: 6 | I22: =1+1 -> 2 | J22: 2 | K22: =SUM(D22:J22) -> 20
C23: Diễn giải
B25: STT | C25: Chỉ tiêu định mức | D25: ĐVT | E25: ĐM 1 giờ | F25: ĐM 1 Ca8 | G25: ĐM 1 Ca12 | H25: ĐM 2 Ca8 | I25: ĐM 2 Ca12
B26: 1 | C26: Tổng nhân sự: | D26: Người | E26: =K22 -> 20 | F26: =$E26 -> 20 | G26: =$F26*1.5 -> 30 | H26: =$F26*2 -> 40 | I26: =$G26*2 -> 60
B27: 2 | C27: Định mức NVL đầu vào: | D27: kg/giờ | E27: =G21 -> 1400 | F27: =$E27*8 -> 11200 | G27: =$F27*1.5 -> 16800 | H27: =$F27*2 -> 22400 | I27: =$G27*2 -> 33600
B28: 3 | C28: Hao hụt: | D28: ='2.Hao hut & % chai '!$N$14 -> 0.13 | E28: =E27*$D$28 -> 182 | F28: =$E28*8 -> 1456 | G28: =$F28*1.5 -> 2184 | H28: =$F28*2 -> 2912 | I28: =$G28*2 -> 4368
B29: 4 | C29: Định mức thành phẩm: | D29: kg/giờ | E29: =E27-E28 -> 1218 | F29: =$E29*8 -> 9744 | G29: =$F29*1.5 -> 14616 | H29: =$F29*2 -> 19488 | I29: =$G29*2 -> 29232
B30: 5 | C30: Định mức thành phẩm/người: | D30: kg/giờ/người | E30: =E29/K22 -> 60.9 | F30: =$E30*8 -> 487.2 | G30: =$F30*1.5 -> 730.8 | H30: =$F30*2 -> 974.4 | I30: =$G30*2 -> 1461.6
B32: III - CÔNG SUẤT CHUYỀN LỰA CHAI - CHAI TUYỂN XÔ
B33: STT | C33: Công đoạn sản xuất | D33: Cấp liệu | E33: Lồng tách tạp chất | F33: Lựa phân loại chai | G33: Tách nhãn | H33: Lựa phân loại chai sau tách nhãn | I33: Ép kiện | J33: Xử lý phó sản, nắp, cổ chai | K33: Công suất thành phẩm cả chuyền
B34: 1 | C34: Năng suất THIẾT KẾ (Kg NVL đầu vào / giờ) | D34: 2000 | E34: 2000 | F34: 1500 | G34: 1.000-1.500 | H34: 1000 | I34: 1400 | K34: 1300
B35: 2 | C35: Năng suất ĐỊNH MỨC (Kg NVL đầu vào / giờ) | D35: 2000 | E35: 2000 | F35: 1500 | G35: 1000 | H35: 900 | I35: 1300 | K35: =E43 -> 1926
B36: 3 | C36: Định mức nhân công (Số NV / Ca8) | D36: 2 | F36: 2 | G36: 1 | H36: 2 | I36: 2 | J36: 2 | K36: =SUM(D36:J36) -> 11
C37: Diễn giải
B39: STT | C39: Chỉ tiêu định mức | D39: ĐVT | E39: ĐM 1 giờ | F39: ĐM 1 Ca8 | G39: ĐM 1 Ca12 | H39: ĐM 2 Ca8 | I39: ĐM 2 Ca12
B40: 1 | C40: Tổng nhân sự: | D40: Người | E40: =K36 -> 11 | F40: =$E40 -> 11 | G40: =$F40*1.5 -> 16.5 | H40: =$F40*2 -> 22 | I40: =$G40*2 -> 33
B41: 2 | C41: Định mức NVL đầu vào: | D41: kg/giờ | E41: =$E$35 -> 2000 | F41: =$E41*8 -> 16000 | G41: =$F41*1.5 -> 24000 | H41: =$F41*2 -> 32000 | I41: =$G41*2 -> 48000
B42: 3 | C42: Hao hụt: | D42: ='2.Hao hut & % chai '!$G$20 -> 0.037 | E42: =E41*$D$42 -> 74 | F42: =$E42*8 -> 592 | G42: =$E42*12 -> 888 | H42: =$F42*2 -> 1184 | I42: =$G42*2 -> 1776
B43: 4 | C43: Định mức thành phẩm: | D43: kg/giờ | E43: =E41-E42 -> 1926 | F43: =$E43*8 -> 15408 | G43: =$F43*1.5 -> 23112 | H43: =$F43*2 -> 30816 | I43: =$G43*2 -> 46224
B44: 5 | C44: Định mức thành phẩm/người: | D44: kg/giờ/người | E44: =E43/K36 -> 175.09091 | F44: =$E44*8 -> 1400.7273 | G44: =$F44*1.5 -> 2101.0909 | H44: =$F44*2 -> 2801.4545 | I44: =$G44*2 -> 4202.1818
B46: VI - CÔNG SUẤT MÁY VÀ NĂNG SUẤT LAO ĐỘNG MỤC TIÊU
B47: 1 | C47: CHUYỀN LỰA CHAI - CHAI XÁ TRÒN | E47: Định mức | F47: T1 | G47: T2 | H47: T3 | I47: T4 | J47: T5 | K47: T6 | L47: T7 | M47: T8 | N47: T9 | O47: T10 | P47: T11 | Q47: T12 | R47: Mục tiêu 2026
B48: a | C48: Số nhân sự/ chuyền/ ca | D48: Người | E48: =E12 -> 18 | F48: =E48 -> 18 | G48: =F48 -> 18 | H48: =G48 -> 18 | I48: =H48 -> 18 | J48: =E48 -> 18 | K48: =J48 -> 18 | L48: =K48 -> 18 | M48: =L48 -> 18 | N48: =M48 -> 18 | O48: =N48 -> 18 | P48: =O48 -> 18 | Q48: =P48 -> 18
B49: b | C49: Công suất/ chuyền | D49: kg/giờ | E49: =E15 -> 1246 | F49: =E49 -> 1246 | G49: =F49 -> 1246 | H49: =G49 -> 1246 | I49: =H49 -> 1246 | J49: =E49 -> 1246 | K49: =J49 -> 1246 | L49: =K49 -> 1246 | M49: =L49 -> 1246 | N49: =M49 -> 1246 | O49: =N49 -> 1246 | P49: =O49 -> 1246 | Q49: =P49 -> 1246
B50: c | C50: Năng suất lao động | D50: kg/giờ/người | E50: =E49/E48 -> 69.222222 | F50: =E50 -> 69.222222 | G50: =F50 -> 69.222222 | H50: =G50 -> 69.222222 | I50: =H50 -> 69.222222 | J50: =J49/J48 -> 69.222222 | K50: =K49/K48 -> 69.222222 | L50: =L49/L48 -> 69.222222 | M50: =M49/M48 -> 69.222222 | N50: =N49/N48 -> 69.222222 | O50: =O49/O48 -> 69.222222 | P50: =P49/P48 -> 69.222222 | Q50: =Q49/Q48 -> 69.222222
B51: 2 | C51: CHUYỀN LỰA CHAI - CHAI ÉP KIỆN | F51: =E51 -> 0 | G51: =F51 -> 0 | H51: =G51 -> 0 | I51: =H51 -> 0
B52: a | C52: Số nhân sự/ chuyền/ ca | D52: Người | E52: =E26 -> 20 | F52: =E52 -> 20 | G52: =F52 -> 20 | H52: =G52 -> 20 | I52: =H52 -> 20 | J52: =E52 -> 20 | K52: =J52 -> 20 | L52: =K52 -> 20 | M52: =L52 -> 20 | N52: =M52 -> 20 | O52: =N52 -> 20 | P52: =O52 -> 20 | Q52: =P52 -> 20
B53: b | C53: Công suất/chuyền (kg thành phẩm/ giờ) | D53: kg/giờ | E53: =E29 -> 1218 | F53: =E53 -> 1218 | G53: =F53 -> 1218 | H53: =G53 -> 1218 | I53: =H53 -> 1218 | J53: =E53 -> 1218 | K53: =J53 -> 1218 | L53: =K53 -> 1218 | M53: =L53 -> 1218 | N53: =M53 -> 1218 | O53: =N53 -> 1218 | P53: =O53 -> 1218 | Q53: =P53 -> 1218
B54: c | C54: Năng suất lao động (kg thành phẩm/ người/ giờ): | D54: kg/giờ/người | E54: =E53/E52 -> 60.9 | F54: =E54 -> 60.9 | G54: =F54 -> 60.9 | H54: =G54 -> 60.9 | I54: =H54 -> 60.9 | J54: =J53/J52 -> 60.9 | K54: =K53/K52 -> 60.9 | L54: =L53/L52 -> 60.9 | M54: =M53/M52 -> 60.9 | N54: =N53/N52 -> 60.9 | O54: =O53/O52 -> 60.9 | P54: =P53/P52 -> 60.9 | Q54: =Q53/Q52 -> 60.9
B55: 3 | C55: CHUYỀN LỰA CHAI - CHAI TUYỂN XÔ (có thể xử lý chạy trên chuyền chai tròn hoặc ép kiện) | F55: =E55 -> 0 | G55: =F55 -> 0 | H55: =G55 -> 0 | I55: =H55 -> 0
B56: a | C56: Số nhân sự/ chuyền/ ca | D56: Người | E56: =E40 -> 11 | F56: =E56 -> 11 | G56: =F56 -> 11 | H56: =G56 -> 11 | I56: =H56 -> 11 | J56: =E56 -> 11 | K56: =J56 -> 11 | L56: =K56 -> 11 | M56: =L56 -> 11 | N56: =M56 -> 11 | O56: =N56 -> 11 | P56: =O56 -> 11 | Q56: =P56 -> 11
B57: b | C57: Công suất/chuyền (kg thành phẩm/ giờ) | D57: kg/giờ | E57: =E43 -> 1926 | F57: =E57 -> 1926 | G57: =F57 -> 1926 | H57: =G57 -> 1926 | I57: =H57 -> 1926 | J57: =E57 -> 1926 | K57: =J57 -> 1926 | L57: =K57 -> 1926 | M57: =L57 -> 1926 | N57: =M57 -> 1926 | O57: =N57 -> 1926 | P57: =O57 -> 1926 | Q57: =P57 -> 1926
B58: c | C58: Năng suất lao động (kg thành phẩm/ người/ giờ): | D58: kg/giờ/người | E58: =E57/E56 -> 175.09091 | F58: =E58 -> 175.09091 | G58: =F58 -> 175.09091 | H58: =G58 -> 175.09091 | I58: =H58 -> 175.09091 | J58: =J57/J56 -> 175.09091 | K58: =K57/K56 -> 175.09091 | L58: =L57/L56 -> 175.09091 | M58: =M57/M56 -> 175.09091 | N58: =N57/N56 -> 175.09091 | O58: =O57/O56 -> 175.09091 | P58: =P57/P56 -> 175.09091 | Q58: =Q57/Q56 -> 175.09091
B60: VII - TỔNG CÔNG SUẤT MÁY PET và NĂNG SUẤT LAO ĐỘNG
B61: i | C61: Tổng công suất PET/giờ | D61: kg/giờ | E61: Định mức | F61: T1 | G61: T2 | H61: T3 | I61: T4 | J61: T5 | K61: T6 | L61: T7 | M61: T8 | N61: T9 | O61: T10 | P61: T11 | Q61: T12 | R61: Mục tiêu 2026
B62: 1 | C62: Công suất máy - Tính trên NVL đầu vào | D62: Tấn/giờ | E62: =$E$13+$E$27*90%+$E$41*10% -> 2860 | F62: =$E$13+$E$27*95%+$E$41*5% -> 2830 | G62: =$E$13+$E$27*95%+$E$41*5% -> 2830 | H62: =$E$13+$E$27*95%+$E$41*5% -> 2830 | I62: =$E$13+$E$27*95%+$E$41*5% -> 2830 | J62: =$E$13+$E$27*95%+$E$41*5% -> 2830 | K62: =$E$13+$E$27*95%+$E$41*5% -> 2830 | L62: =$E$13+$E$27*95%+$E$41*5% -> 2830 | M62: =$E$13+$E$27*95%+$E$41*5% -> 2830 | ... Q62: =$E$13+$E$27*95%+$E$41*5% -> 2830
B63: 2 | C63: Công suất máy - Tính trên Thành phẩm SX | D63: Tấn/giờ | E63: =$E$49+$E$53*80%+$E$57*20% -> 2605.6 | F63: =$E$49+$E$53*80%+$E$57*20% -> 2605.6 | G63: =$E$49+$E$53*80%+$E$57*20% -> 2605.6 | H63: =$E$49+$E$53*80%+$E$57*20% -> 2605.6 | I63: =$E$49+$E$53*80%+$E$57*20% -> 2605.6 | J63: =$E$49+$E$53*80%+$E$57*20% -> 2605.6 | K63: =$E$49+$E$53*80%+$E$57*20% -> 2605.6 | L63: =$E$49+$E$53*80%+$E$57*20% -> 2605.6 | ... Q63: =$E$49+$E$53*80%+$E$57*20% -> 2605.6
B64: ii | C64: Tổng công suất PET/tháng (8hx4cax30 ngày) | D64: kg/tháng | E64: Định mức | J64: T5 | K64: T6 | L64: T7 | M64: T8 | N64: T9 | O64: T10 | P64: T11 | Q64: T12
B65: 1 | C65: Công suất máy - Tính trên NVL đầu vào | D65: Tấn/tháng | E65: =E62*7*2*30 -> 1201200 | F65: =F62*7*2*30 -> 1188600 | G65: =G62*7*2*30 -> 1188600 | H65: =H62*7*2*30 -> 1188600 | I65: =I62*7*2*30 -> 1188600 | J65: =J62*7*2*30 -> 1188600 | K65: =K62*7*2*30 -> 1188600 | L65: =L62*7*2*30 -> 1188600 | ... Q65: =Q62*7*2*30 -> 1188600
B66: 2 | C66: Công suất máy - Tính trên Thành phẩm SX | D66: Tấn/tháng | E66: =E63*7*2*30 -> 1094352 | F66: =F63*7*2*30 -> 1094352 | G66: =G63*7*2*30 -> 1094352 | H66: =H63*7*2*30 -> 1094352 | I66: =I63*7*2*30 -> 1094352 | J66: =J63*7*2*30 -> 1094352 | K66: =K63*7*2*30 -> 1094352 | L66: =L63*7*2*30 -> 1094352 | ... Q66: =Q63*7*2*30 -> 1094352
B67: iii | C67: Năng suất lao động (CNTT) | E67: Định mức | J67: T5 | K67: T6 | L67: T7 | M67: T8 | N67: T9 | O67: T10 | P67: T11 | Q67: T12
B68: 1 | C68: Năng suất lao động - Tấn/người/ngày | D68: Tấn/người/ngày | E68: =E69/30 -> 251.92265 | F68: =F69/30 -> 251.92265 | G68: =G69/30 -> 251.92265 | H68: =H69/30 -> 251.92265 | I68: =I69/30 -> 251.92265 | J68: =J69/30 -> 251.92265 | K68: =K69/30 -> 251.92265 | L68: =L69/30 -> 251.92265 | ... Q68: =Q69/30 -> 251.92265
B69: 2 | C69: Năng suất lao động - Tấn/người/tháng | D69: Tấn/người/tháng | E69: =E66/(E48+E52*80%+E56*20%)/4 -> 7557.6796 | F69: =F66/(F48+F52*80%+F56*20%)/4 -> 7557.6796 | G69: =G66/(G48+G52*80%+G56*20%)/4 -> 7557.6796 | H69: =H66/(H48+H52*80%+H56*20%)/4 -> 7557.6796 | I69: =I66/(I48+I52*80%+I56*20%)/4 -> 7557.6796 | J69: =J66/(J48+J52*80%+J56*20%)/4 -> 7557.6796 | K69: =K66/(K48+K52*80%+K56*20%)/4 -> 7557.6796 | L69: =L66/(L48+L52*80%+L56*20%)/4 -> 7557.6796 | ... Q69: =Q66/(Q48+Q52*80%+Q56*20%)/4 -> 7557.6796
B71: IX - CÔNG SUẤT CHUYỀN BĂM PET FS (B6.2)
B72: STT | C72: Công đoạn sản xuất | D72: Cấp liệu | E72: XXX | F72: XXX | G72: XXX | H72: XXX | I72: Đóng gói, cân TP | J72: XXX | K72: Công suất thành phẩm cả chuyền
B73: 1 | C73: Năng suất THIẾT KẾ (Kg NVL đầu vào / giờ) | D73: 7000 | K73: =D73*(100%-$D$97) -> 6580
B74: 2 | C74: Năng suất ĐỊNH MỨC (Kg NVL đầu vào / giờ) | D74: 700 | E74: =D74 -> 700 | F74: =E74 -> 700 | G74: =F74 -> 700 | H74: =G74 -> 700 | I74: 1300 | K74: =D74*(100%-$D$81) -> 630
B75: 3 | C75: Định mức nhân công (Số NV / Ca8) | D75: 1 | F75: 1 | I75: 1 | K75: =SUM(D75:J75) -> 3
C76: Diễn giải
B78: STT | C78: Chỉ tiêu định mức | D78: ĐVT | E78: ĐM 1 giờ | F78: ĐM 1 Ca8 | G78: ĐM 1 Ca12 | H78: ĐM 2 Ca8 | I78: ĐM 2 Ca12
B79: 1 | C79: Tổng nhân sự: | D79: Người | E79: =K75 -> 3 | F79: =$E79 -> 3 | G79: =$F79*1.5 -> 4.5 | H79: =$F79*2 -> 6 | I79: =$G79*2 -> 9
B80: 2 | C80: Định mức NVL đầu vào: | D80: kg/giờ | E80: =D74 -> 700 | F80: =$E80*8 -> 5600 | G80: =$F80*1.5 -> 8400 | H80: =$F80*2 -> 11200 | I80: =$G80*2 -> 16800
B81: 3 | C81: Hao hụt: | D81: ='2.Hao hut & % chai '!H43 -> 0.1 | E81: =E80*D81 -> 70 | F81: =$E81*8 -> 560 | G81: =$F81*1.5 -> 840 | H81: =$F81*2 -> 1120 | I81: =$G81*2 -> 1680
B82: 4 | C82: Định mức thành phẩm: | D82: kg/giờ | E82: =E80-E81 -> 630 | F82: =$E82*8 -> 5040 | G82: =$F82*1.5 -> 7560 | H82: =$F82*2 -> 10080 | I82: =$G82*2 -> 15120
B83: 5 | C83: Định mức thành phẩm/người: | D83: kg/giờ/người | E83: =E82/K75 -> 210 | F83: =$E83*8 -> 1680 | G83: =$F83*1.5 -> 2520 | H83: =$F83*2 -> 3360 | I83: =$G83*2 -> 5040
B87: IX - CÔNG SUẤT CHUYỀN BĂM HDPE
B88: STT | C88: Công đoạn sản xuất | D88: Cấp liệu | E88: XXX | F88: XXX | G88: XXX | H88: XXX | I88: Đóng gói, cân TP | J88: XXX | K88: Công suất thành phẩm cả chuyền
B89: 1 | C89: Năng suất THIẾT KẾ (Kg NVL đầu vào / giờ) | D89: 1500 | K89: =D89*(100%-$D$97) -> 1410
B90: 2 | C90: Năng suất ĐỊNH MỨC (Kg NVL đầu vào / giờ) | D90: 1500 | E90: =D90 -> 1500 | F90: =E90 -> 1500 | G90: =F90 -> 1500 | H90: =G90 -> 1500 | I90: 1300 | K90: =D90*(100%-$D$97) -> 1410
B91: 3 | C91: Định mức nhân công (Số NV / Ca8) | D91: 1 | F91: 1 | I91: 1 | K91: =SUM(D91:J91) -> 3
C92: Diễn giải
B94: STT | C94: Chỉ tiêu định mức | D94: ĐVT | E94: ĐM 1 giờ | F94: ĐM 1 Ca8 | G94: ĐM 1 Ca12 | H94: ĐM 2 Ca8 | I94: ĐM 2 Ca12
B95: 1 | C95: Tổng nhân sự: | D95: Người | E95: =K91 -> 3 | F95: =$E95 -> 3 | G95: =$F95*1.5 -> 4.5 | H95: =$F95*2 -> 6 | I95: =$G95*2 -> 9
B96: 2 | C96: Định mức NVL đầu vào: | D96: kg/giờ | E96: =D90 -> 1500 | F96: =$E96*8 -> 12000 | G96: =$F96*1.5 -> 18000 | H96: =$F96*2 -> 24000 | I96: =$G96*2 -> 36000
B97: 3 | C97: Hao hụt: | D97: ='2.Hao hut & % chai '!H27 -> 0.06 | E97: =E96*D97 -> 90 | F97: =$E97*8 -> 720 | G97: =$F97*1.5 -> 1080 | H97: =$F97*2 -> 1440 | I97: =$G97*2 -> 2160
B98: 4 | C98: Định mức thành phẩm: | D98: kg/giờ | E98: =E96-E97 -> 1410 | F98: =$E98*8 -> 11280 | G98: =$F98*1.5 -> 16920 | H98: =$F98*2 -> 22560 | I98: =$G98*2 -> 33840
B99: 5 | C99: Định mức thành phẩm/người: | D99: kg/giờ/người | E99: =E98/K91 -> 470 | F99: =$E99*8 -> 3760 | G99: =$F99*1.5 -> 5640 | H99: =$F99*2 -> 7520 | I99: =$G99*2 -> 11280
B102: IX - CÔNG SUẤT CHUYỀN DÂY ĐAI
B103: STT | C103: Công đoạn sản xuất | D103: Cấp liệu | E103: XXX | F103: XXX | G103: XXX | H103: XXX | I103: Đóng gói, cân TP | J103: XXX | K103: Công suất thành phẩm cả chuyền
B104: 1 | C104: Năng suất THIẾT KẾ (Kg NVL đầu vào / giờ) | D104: 300 | K104: =D104*(100%-$D$97) -> 282
B105: 2 | C105: Năng suất ĐỊNH MỨC (Kg NVL đầu vào / giờ) | D105: 300 | K105: =D105*(100%-$D$97) -> 282
C106: Định mức Kỹ thuật vận hành (Số NV / Ca12) | D106: 1 | K106: =SUM(D106:J106) -> 1
B107: 3 | C107: Định mức nhân công (Số NV / Ca12) | D107: 2 | K107: =SUM(D107:J107) -> 2
C108: Diễn giải
B110: STT | C110: Chỉ tiêu định mức | D110: ĐVT | E110: ĐM 1 giờ | F110: ĐM 1 Ca8 | G110: ĐM 1 Ca12 | H110: ĐM 2 Ca8 | I110: ĐM 2 Ca12
B111: 1 | C111: Tổng nhân sự: | D111: Người | E111: 3 | F111: =$E111 -> 3 | G111: =$F111*1.5 -> 4.5 | H111: =$F111*2 -> 6 | I111: =$G111*2 -> 9
B112: 2 | C112: Định mức NVL đầu vào: | D112: kg/giờ | E112: =D105 -> 300 | F112: =$E112*8 -> 2400 | G112: =$F112*1.5 -> 3600 | H112: =$F112*2 -> 4800 | I112: =$G112*2 -> 7200
B113: 3 | C113: Hao hụt: | D113: ='2.Hao hut & % chai '!T172 -> 0.04 | E113: =E112*$D$28 -> 39 | F113: =$E113*8 -> 312 | G113: =$F113*1.5 -> 468 | H113: =$F113*2 -> 624 | I113: =$G113*2 -> 936
B114: 4 | C114: Định mức thành phẩm: | D114: kg/giờ | E114: =E112-E113 -> 261 | F114: =$E114*8 -> 2088 | G114: =$F114*1.5 -> 3132 | H114: =$F114*2 -> 4176 | I114: =$G114*2 -> 6264
B115: 5 | C115: Định mức thành phẩm/người: | D115: kg/giờ/người | E115: =E114/K107 -> 130.5 | F115: =$E115*8 -> 1044 | G115: =$F115*1.5 -> 1566 | H115: =$F115*2 -> 2088 | I115: =$G115*2 -> 3132
B117: VIII - CÔNG SUẤT CHUYỀN BĂM VẢY PET
B118: STT | C118: Công đoạn sản xuất | D118: Cấp liệu | E118: XXX | F118: XXX | G118: XXX | H118: XXX | I118: Đóng gói, cân TP | J118: XXX | K118: Công suất thành phẩm cả chuyền
B119: 1 | C119: Năng suất THIẾT KẾ (Kg NVL đầu vào / giờ) | D119: 2000 | F119: 1500 | G119: 1.100-1.500 | K119: =D119*(100%-$D$97) -> 1880
...

Sheet Dinh muc
B3: ĐỊNH MỨC CHI PHÍ
B4: I - ĐỊNH MỨC TIÊU HAO VẬT TƯ - PHÂN LOẠI CHAI PET
B5: STT | C5: Mục phí | D5: ĐVT | E5: Định mức | F5: Đơn giá | G5: Chi phí/1kg thành phẩm | H5: Diễn giải
C6: Công suất lựa chai | E6: =('Cong suat'!E29+'Cong suat'!E15)/2 -> 1232
B7: 1 | C7: Chi phí nhân công trực tiếp (giờ công lao động) | E7: =E8+E9 -> 128
B8: a | C8: LĐ định biên | D8: Giờ công/ca 8 | E8: =7*8 -> 56 | G8: =E8*F8/E6 -> 0
B9: b | C9: LĐ thời vụ | D9: Giờ công/ca 8 | E9: =9*8 -> 72 | F9: =260000/8 -> 32500 | G9: =E9*F9/E6 -> 1899.3506
B10: c | C10: Tiền ăn giữa Ca | D10: Đồng/người/ngày công | E10: =E7/8 -> 16 | F10: =25000 -> 25000 | G10: =(E10*F10)/($E$6*8) -> 40.584416
B11: 2 | C11: Điện sản xuất | D11: Kw/1chuyền/1giờ hoạt động | E11: 40 | F11: =ROUND(2100*1.05,-1) -> 2210 | G11: =E11*F11/E6 -> 71.753247
B12: 3 | C12: Dao tách nhãn chai PET | D12: Tấn/Bộ | E12: =1700000 -> 1700000 | F12: 165000000 | G12: =F12/(E12*87%) -> 111.56187 | H12: Anh Quân chốt định mức băm: 1500 tấn chai PET-B0
B13: 4 | C13: Dây đai | D13: Kg/tấn | E13: =1.1*50% -> 0.55 | F13: 51000 | G13: =E13*F13/(1000*87%)+1 -> 33.241379 | H13: Chuyển Băm 80%, CP dây đai tái sử dụng lại được 2 lần
B14: 5 | C14: Bao jumbo
B15: 6 | C15: Hóa chất
B16: 7 | C16: Chi phí xử lý nhãn chai PET | D16: Kg | E16: 1 | F16: 300 | G16: =(6.5%*1000)*F16/870 -> 22.413793
B17: 8 | C17: Dầu xe nâng | D17: Lít/giờ hoạt động | E17: =2.5*85% -> 2.125 | F17: 18000 | G17: =E17*F17/1100 -> 34.772727 | H17: Bình quân 1 h: 2.5 lít, hiệu suất sử dụng: 85%
B18: 9 | C18: Chi phí vận chuyển | D18: Chuyến/9 tấn | E18: 1 | F18: 3200000 | G18: =F18/9000 -> 355.55556
B20: II - ĐỊNH MỨC TIÊU HAO VẬT TƯ - BĂM VẢY PET - CHUYỀN FS (B6.2)
B21: STT | C21: Mục phí | D21: ĐVT | E21: ĐM 1 giờ | F21: Đơn giá | G21: Chi phí/1kg thành phẩm | H21: Diễn giải
C22: Công suất băm PET | E22: ='Cong suat'!E82 -> 630
B23: 1 | C23: Chi phí nhân công trực tiếp | E23: =SUM(E24:E25) -> 24
B24: a | C24: LĐ định biên | D24: Giờ công/ca 8 | E24: =3*8 -> 24
B25: b | C25: LĐ thời vụ | D25: Giờ công/ca 8
B26: c | C26: Tiền ăn giữa Ca | D26: Đồng/người/ngày công | E26: =E23/8 -> 3 | F26: =25000 -> 25000 | G26: =(E26*F26)/($E$22*8) -> 14.880952
B27: 2 | C27: Điện sản xuất | D27: Kw/h | E27: 70 | F27: =ROUND(2100*1.05,-1) -> 2210 | G27: =E27*F27/$E$22 -> 245.55556
B28: 3 | C28: Dao băm vảy PET | D28: Tấn/Bộ | E28: 200000 | F28: 44000000 | G28: =F28/(E28*90%) -> 244.44444 | H28: Công suất thiết kế: 200 tấn
B29: 4 | C29: Dây đai
B30: 5 | C30: Bao jumbo | D30: Cái/Kg | E30: 350 | F30: 75000 | G30: =F30/(E30*2*0.9) -> 119.04762 | H30: 1 cái sử dụng được 2 lần
B31: 6 | C31: Hóa chất
B32: 7 | C32: Chi phí xử lý bùn, nước thải | G32: =SUM(G33:G35) -> 269.52381 | H32: Xử lý: nhãn, bùn, nước thải, hóa chất xử lý hồ XLNT
B33: 7.1 | C33: Chi phí nước sản xuất | D33: m3/h | E33: 3 | F33: 11500 | G33: =E33*F33/$E$22 -> 54.761905
C34: Chi phí xử lý nước thải | D34: m3/h | E34: =E33*80% -> 2.4 | F34: 9500 | G34: =E34*F34/$E$22 -> 36.190476
C35: Chi phí xử lý bùn | E35: ='Cong suat'!D90*5% -> 75 | F35: 1500 | G35: =E35*F35/$E$22 -> 178.57143
B36: 8 | C36: Dầu xe nâng | E36: =2.5*60% -> 1.5 | F36: 18000 | G36: =E36*F36/1100 -> 24.545455 | H36: Bình quân 1 h: 2.5 lít, hiệu suất sử dụng: 60%
B37: 9 | C37: Chi phí vận chuyển | D37: Chuyến | E37: 10000 | F37: 3200000 | G37: =F37/E37 -> 320
B39: III - ĐỊNH MỨC TIÊU HAO VẬT TƯ - BĂM VẢY PET Tu chuyen HD
B40: STT | C40: Mục phí | D40: ĐVT | E40: Định mức | F40: Đơn giá | G40: Chi phí/1kg thành phẩm | H40: Diễn giải
C41: Công suất băm HD | E41: ='Cong suat'!K90 -> 1410
B42: 1 | C42: Chi phí nhân công trực tiếp | E42: 3 | F42: 50320
B43: a | C43: LĐ định biên | D43: h | E43: =3*8 -> 24 | F43: 50320 | G43: =(E43*F43)/($E$41*8) -> 107.06383
B44: b | C44: LĐ thời vụ | D44: h
B45: c | C45: Tiền ăn giữa Ca | D45: Đồng/người/ngày công | E45: 3 | F45: =25000 -> 25000 | G45: =E45*F45/($E$41*8) -> 6.6489362
B46: 2 | C46: Điện sản xuất | D46: Kw/h | E46: =250*70% -> 175 | F46: =ROUND(2100*1.05,-1) -> 2210 | G46: =E46*F46/$E$41 -> 274.29078
B47: 3 | C47: Dao băm vảy HD | D47: Tấn/Bộ | E47: 300000 | F47: 70000000 | G47: =F47/(E47*94%) -> 248.22695
B48: 4 | C48: Dây đai
B49: 5 | C49: Bao jumbo | D49: Cái/Kg | E49: 350 | F49: 75000 | G49: =F49/(E49*2*94%) -> 113.98176 | H49: 1 cái sử dụng được 2 lần
B50: 6 | C50: Hóa chất
B51: 7.1 | C51: Chi phí nước sản xuất | D51: m3/h | E51: 3 | F51: 11500 | G51: =E51*F51/$E$41 -> 24.468085
B52: 7 | C52: Chi phí xử lý nước thải, môi trường | D52: m3/h | E52: =E51*80% -> 2.4 | F52: 11500 | G52: =E52*F52/$E$41 -> 19.574468
C53: Chi phí xử lý bùn | E53: ='Cong suat'!D90*3% -> 45 | F53: 1500 | G53: =E53*F53/$E$41 -> 47.87234
B54: 8 | C54: Dầu xe nâng | E54: =2.5*60% -> 1.5 | F54: 18000 | G54: =E54*F54/1100 -> 24.545455
B55: 9 | C55: Chi phí vận chuyển | D55: Chuyến | E55: 10000 | F55: 3200000 | G55: =F55/E55 -> 320
H59: Ngày …
C60: Duyệt | D60: Xem xét | E60: Xem xét | G60: Xem xét | H60: Người lập
C61: GĐĐH DTR | D61: GĐTC DTR | E61: GĐ các trạm | G61: Trưởng Trạm | H61: Kế toán trưởng

Sheet Dinh muc (2)
B3: ĐỊNH MỨC CHI PHÍ
B4: I - ĐỊNH MỨC TIÊU HAO VẬT TƯ - PHÂN LOẠI CHAI PET
B5: STT | C5: Mục phí | D5: ĐVT | E5: Định mức | F5: Đơn giá | G5: Chi phí/1kg thành phẩm | H5: Diễn giải
C6: Công suất lựa chai | E6: =('Cong suat'!E29+'Cong suat'!E15)/2 -> 1232
B7: 1 | C7: Chi phí nhân công trực tiếp (giờ công lao động) | E7: =E8+E9 -> 16 | F7: =(E8*F8+E9*F9)/E7 -> 18281.25 | G7: =G8+G9 -> 237.41883
B8: a | C8: LĐ định biên | D8: Giờ công/ca 8 | E8: 7 | G8: =E8*F8/E6 -> 0
B9: b | C9: LĐ thời vụ | D9: Giờ công/ca 8 | E9: 9 | F9: =260000/8 -> 32500 | G9: =E9*F9/E6 -> 237.41883
B10: c | C10: Tiền ăn giữa Ca | D10: Đồng/người/ngày công | E10: =E7 -> 16 | F10: =25000/8 -> 3125 | G10: =E10*F10/$E$6 -> 40.584416
B11: 2 | C11: Điện sản xuất | D11: Kw/1chuyền/1giờ hoạt động | E11: 40 | F11: =ROUND(2100*1.05,-1) -> 2210 | G11: =E11*F11/E6 -> 71.753247
B12: 3 | C12: Dao tách nhãn chai PET | D12: Tấn/Bộ | E12: =1/1700000*(('Cong suat'!$E$13+'Cong suat'!$E$21)/2) -> 0.00082352941 | F12: 165000000 | G12: =E12*F12/$E$6 -> 110.29412 | H12: Anh Quân chốt định mức băm: 1500 tấn chai PET-B0 | I12: Tăng Dm dao tách nhãn 1500 -> 1700
B13: 4 | C13: Dây đai | E13: =0.3*50% -> 0.15 | F13: 51000 | G13: =E13*F13/230 -> 33.26087 | H13: Chuyển Băm 80%, CP dây đai tái sử dụng lại được 2 lần
B14: 5 | C14: Bao jumbo
B15: 6 | C15: Hóa chất
B16: 7 | C16: Chi phí xử lý nhãn chai PET | D16: Kg | E16: =SUM('Cong suat'!E13,'Cong suat'!E27)/2*6.5% -> 91 | F16: 300 | G16: =E16*F16/$E$6 -> 22.159091
B17: 8 | C17: Dầu xe nâng | D17: Lít/giờ hoạt động | E17: =2.5*85% -> 2.125 | F17: 18000 | G17: =E17*F17/1100 -> 34.772727 | H17: Bình quân 1 h: 2.5 lít, hiệu suất sử dụng: 85%
B18: 9 | C18: Chi phí vận chuyển | D18: Chuyến/9 tấn | E18: 1 | F18: 3200000 | G18: =F18/9000 -> 355.55556
B20: II - ĐỊNH MỨC TIÊU HAO VẬT TƯ - BĂM VẢY PET
B21: STT | C21: Mục phí | D21: ĐVT | E21: ĐM 1 giờ | F21: Đơn giá | G21: Chi phí/1kg thành phẩm | H21: Diễn giải
C22: Công suất băm PET | E22: ='Cong suat'!$E$98 -> 1410
B23: 1 | C23: Chi phí nhân công trực tiếp
B24: a | C24: LĐ định biên | D24: Giờ công/ca 8 | E24: 3
B25: b | C25: LĐ thời vụ | D25: Giờ công/ca 8
B26: c | C26: Tiền ăn giữa Ca | D26: Đồng/người | E26: =E23 -> 0 | F26: =25000/8 -> 3125 | G26: =E26*F26/$E$22 -> 0
B27: 2 | C27: Điện sản xuất | D27: Kw/1chuyền/1giờ hoạt động | E27: 70 | F27: =ROUND(2100*1.05,-1) -> 2210 | G27: =E27*F27/$E$22 -> 109.71631
B28: 3 | C28: Dao băm vảy PET | E28: =1/200000*'Cong suat'!$E$96 -> 0.0075 | F28: 44000000 | G28: =E28*F28/$E$22 -> 234.04255 | H28: Công suất thiết kế: 200 tấn
B29: 4 | C29: Dây đai
B30: 5 | C30: Bao jumbo | E30: =E22/350*50% -> 2.0142857 | F30: 71000 | G30: =E30*F30/$E$22 -> 101.42857
B31: 6 | C31: Hóa chất
B32: 7 | C32: Chi phí xử lý bùn, nước thải | G32: =SUM(G33:G35) -> 120.42553 | H32: Xử lý: nhãn, bùn, nước thải, hóa chất xử lý hồ XLNT
B33: 7.1 | C33: Chi phí nước sản xuất | E33: 3 | F33: 11500 | G33: =E33*F33/$E$22 -> 24.468085
C34: Chi phí xử lý nước thải | E34: =E33*80% -> 2.4 | F34: 9500 | G34: =E34*F34/$E$22 -> 16.170213
C35: Chi phí xử lý bùn | E35: ='Cong suat'!D90*5% -> 75 | F35: 1500 | G35: =E35*F35/$E$22 -> 79.787234
B36: 8 | C36: Dầu xe nâng | E36: =2.5*60% -> 1.5 | F36: 18000 | G36: =E36*F36/1100 -> 24.545455 | H36: Bình quân 1 h: 2.5 lít, hiệu suất sử dụng: 60%
B37: 9 | C37: Chi phí vận chuyển | D37: Chuyến | E37: 10000 | F37: 3200000 | G37: =F37/E37 -> 320
B39: III - ĐỊNH MỨC TIÊU HAO VẬT TƯ - BĂM VẢY PET Tu chuyen HD
B40: STT | C40: Mục phí | D40: ĐVT | E40: Định mức | F40: Đơn giá | G40: Chi phí/1kg thành phẩm | H40: Diễn giải
C41: Công suất băm HD | E41: ='Cong suat'!K90 -> 1410
B42: 1 | C42: Chi phí nhân công trực tiếp | E42: 3 | F42: 50320
B43: a | C43: LĐ định biên | E43: 3 | F43: 50320 | G43: =E43*F43/$E$41 -> 107.06383
B44: b | C44: LĐ thời vụ
B45: c | C45: Tiền ăn giữa Ca | E45: 3 | F45: =25000/8 -> 3125 | G45: =E45*F45/$E$41 -> 6.6489362
B46: 2 | C46: Điện sản xuất | E46: =250*75% -> 187.5 | F46: =ROUND(2100*1.05,-1) -> 2210 | G46: =E46*F46/$E$41 -> 293.88298
B47: 3 | C47: Dao băm vảy HD | E47: =1/300000*'Cong suat'!D89 -> 0.005 | F47: 70000000 | G47: =E47*F47/$E$41 -> 248.22695
B48: 4 | C48: Dây đai
B49: 5 | C49: Bao jumbo | E49: =1/350*E41*50% -> 2.0142857 | F49: 75000 | G49: =E49*F49/$E$41 -> 107.14286
B50: 6 | C50: Hóa chất
B51: 7.1 | C51: Chi phí nước sản xuất | E51: 3 | F51: 11500 | G51: =E51*F51/$E$41 -> 24.468085
B52: 7 | C52: Chi phí xử lý nước thải, môi trường | E52: =E51*80% -> 2.4 | F52: 11500 | G52: =E52*F52/$E$41 -> 19.574468
C53: Chi phí xử lý bùn | E53: ='Cong suat'!D90*3% -> 45 | F53: 1500 | G53: =E53*F53/$E$41 -> 47.87234
B54: 8 | C54: Dầu xe nâng | E54: =2.5*60% -> 1.5 | F54: 18000 | G54: =E54*F54/1100 -> 24.545455
B55: 9 | C55: Chi phí vận chuyển | D55: Chuyến | E55: 10000 | F55: 3200000 | G55: =F55/E55 -> 320
H59: Ngày …
C60: Duyệt | D60: Xem xét | E60: Xem xét | G60: Xem xét | H60: Người lập
C61: GĐĐH DTR | D61: GĐTC DTR | E61: GĐ các trạm | G61: Trưởng Trạm | H61: Kế toán trưởng

Sheet Dinh bien_HCNS
B1: #VALUE!
B3: I - ĐINH BIÊN NHÂN SỰ - PET | R3: ĐVT: người
B4: STT | C4: Phòng ban | D4: Tài khoản | E4: KQKD 2025 | F4: T1 | G4: T2 | H4: T3 | I4: T4 | J4: T5 | K4: T6 | L4: T7 | M4: T8 | N4: T9 | O4: T10 | P4: T11 | Q4: T12 | R4: KH 2026
B5: 1 | C5: Ban giám đốc | D5: 642 | E5: =E6+E7 -> 2 | F5: =SUM(F6:F7) -> 2 | G5: =SUM(G6:G7) -> 2 | H5: =SUM(H6:H7) -> 2 | I5: =SUM(I6:I7) -> 2 | J5: =SUM(J6:J7) -> 2 | K5: =SUM(K6:K7) -> 2 | L5: =SUM(L6:L7) -> 2 | M5: =SUM(M6:M7) -> 2 | ... Q5: =SUM(Q6:Q7) -> 2 | R5: =R6+R7 -> 2
B6: 1.1 | C6: Giám đốc Trạm | E6: 1 | F6: 1 | G6: 1 | H6: 1 | I6: 1 | J6: 1 | K6: 1 | L6: 1 | M6: 1 | N6: 1 | O6: 1 | P6: 1 | Q6: 1 | R6: =Q6 -> 1
B7: 1.2 | C7: Trưởng trạm thu mua | E7: 1 | F7: 1 | G7: 1 | H7: 1 | I7: 1 | J7: 1 | K7: 1 | L7: 1 | M7: 1 | N7: 1 | O7: 1 | P7: 1 | Q7: 1 | R7: =Q7 -> 1
B8: 2 | C8: Phòng Hành chánh nhân sự | D8: 642 | E8: =E9+E11+E12+E13+E14+E15 -> 2 | F8: =SUM(F9:F15) -> 2 | G8: =SUM(G9:G15) -> 2 | H8: =SUM(H9:H15) -> 2 | I8: =SUM(I9:I15) -> 2 | J8: =SUM(J9:J15) -> 2 | K8: =SUM(K9:K15) -> 2 | L8: =SUM(L9:L15) -> 2 | M8: =SUM(M9:M15) -> 2 | ... R8: =SUM(R9:R15) -> 2
B9: 2.1 | C9: Trưởng phòng nhân sự | E9: 1 | F9: 1 | G9: 1 | H9: 1 | I9: 1 | J9: 1 | K9: 1 | L9: 1 | M9: 1 | N9: 1 | O9: 1 | P9: 1 | Q9: 1 | R9: =Q9 -> 1
B10: 2.1 | C10: Nhân viên hành chính | R10: =Q10 -> 0
B11: 2.2 | C11: Nhân viên nhân sự | R11: =Q11 -> 0
B12: 2.3 | C12: Tuyển dụng | R12: =Q12 -> 0
B13: 2.4 | C13: Nhân viên tạp vụ | E13: 1 | F13: 1 | G13: 1 | H13: 1 | I13: 1 | J13: 1 | K13: 1 | L13: 1 | M13: 1 | N13: 1 | O13: 1 | P13: 1 | Q13: 1 | R13: =Q13 -> 1
B14: 2.5 | C14: Bảo vệ | R14: =Q14 -> 0
B15: 2.6 | C15: Nhân viên chăm sóc cây xanh | R15: =Q15 -> 0
B16: 3 | C16: Phòng Kế toán | D16: 642 | E16: =SUM(E17:E20) -> 3 | F16: =SUM(F17:F20) -> 3 | G16: =SUM(G17:G20) -> 3 | H16: =SUM(H17:H20) -> 3 | I16: =SUM(I17:I20) -> 3 | J16: =SUM(J17:J20) -> 3 | K16: =SUM(K17:K20) -> 3 | L16: =SUM(L17:L20) -> 3 | ... R16: =SUM(R17:R20) -> 3
B17: 3.1 | C17: Kế toán trưởng | E17: 1 | F17: 1 | G17: 1 | H17: 1 | I17: 1 | J17: 1 | K17: 1 | L17: 1 | M17: 1 | N17: 1 | O17: 1 | P17: 1 | Q17: 1 | R17: =Q17 -> 1
B18: 3.2 | C18: Kế toán tổng hợp | E18: 1 | F18: 1 | G18: 1 | H18: 1 | I18: 1 | J18: 1 | K18: 1 | L18: 1 | M18: 1 | N18: 1 | O18: 1 | P18: 1 | Q18: 1 | R18: =Q18 -> 1
B19: 3.3 | C19: Kế toán kho | R19: =Q19 -> 0
B20: 3.4 | C20: Kế toán viên | E20: 1 | F20: 1 | G20: 1 | H20: 1 | I20: 1 | J20: 1 | K20: 1 | L20: 1 | M20: 1 | N20: 1 | O20: 1 | P20: 1 | Q20: 1 | R20: =Q20 -> 1
B21: 4 | C21: Phòng Mua hàng | D21: 642 | E21: =E22 -> 1 | F21: =F22 -> 1 | G21: =G22 -> 1 | H21: =H22 -> 1 | I21: =I22 -> 1 | J21: =J22 -> 1 | K21: =K22 -> 1 | L21: =L22 -> 1 | ... R21: =R22 -> 1
B22: 4.1 | C22: Nhân viên mua hàng | E22: 1 | F22: 1 | G22: 1 | H22: 1 | I22: 1 | J22: 1 | K22: 1 | L22: 1 | M22: 1 | N22: 1 | O22: 1 | P22: 1 | Q22: 1 | R22: =Q22 -> 1
B23: 5 | C23: Ban dự án XDCB | D23: 642 | E23: =E24 -> 0 | F23: =F24 -> 0 | G23: =G24 -> 0 | H23: =H24 -> 0 | I23: =I24 -> 0 | J23: =J24 -> 0 | K23: =K24 -> 0 | L23: =L24 -> 0 | ... Q23: =Q24 -> 0
B24: 5.1 | C24: Nhân viên
B25: 6 | C25: Phòng Quản Trị Hệ Thống | D25: 642 | E25: =E26 -> 0 | F25: =F26 -> 0 | G25: =G26 -> 0 | H25: =H26 -> 0 | I25: =I26 -> 0 | J25: =J26 -> 0 | K25: =K26 -> 0 | L25: =L26 -> 0 | ... Q25: =Q26 -> 0
B26: 6.1 | C26: Nhân viên quản trị hệ thống
B27: 7 | C27: Phòng 5S & an toàn | D27: 642 | E27: =SUM(E28:E30) -> 5 | F27: =SUM(F28:F30) -> 5 | G27: =SUM(G28:G30) -> 5 | H27: =SUM(H28:H30) -> 5 | I27: =SUM(I28:I30) -> 5 | J27: =SUM(J28:J30) -> 5 | K27: =SUM(K28:K30) -> 5 | L27: =SUM(L28:L30) -> 5 | ... R27: =SUM(R28:R30) -> 5
B28: 7.1 | C28: Nhân viên 5S & an toàn | E28: 1 | F28: 1 | G28: 1 | H28: 1 | I28: 1 | J28: 1 | K28: 1 | L28: 1 | M28: 1 | N28: 1 | O28: 1 | P28: 1 | Q28: 1 | R28: =Q28 -> 1
B29: 7.2 | C29: Nhân viên XLNT | E29: 3 | F29: 3 | G29: 3 | H29: 3 | I29: 3 | J29: 3 | K29: 3 | L29: 3 | M29: 3 | N29: 3 | O29: 3 | P29: 3 | Q29: 3 | R29: 3
B30: 7.3 | C30: Lao động thuê ngoài: 5S 2 xưởng | E30: 1 | F30: 1 | G30: 1 | H30: 1 | I30: 1 | J30: 1 | K30: 1 | L30: 1 | M30: 1 | N30: 1 | O30: 1 | P30: 1 | Q30: 1 | R30: 1
B31: 8 | C31: Phòng Cung ứng | D31: 642 | E31: =E32 -> 0 | F31: =F32 -> 0 | G31: =G32 -> 0 | H31: =H32 -> 0 | I31: =I32 -> 0 | J31: =J32 -> 0 | K31: =K32 -> 0 | L31: =L32 -> 0 | ... Q31: =Q32 -> 0 | R31: =Q31 -> 0
B32: 8.1 | C32: Nhân viên | R32: =Q32 -> 0
B33: 9 | C33: Phòng mua XNK | D33: 642 | E33: =E34 -> 0 | F33: =F34 -> 0 | G33: =G34 -> 0 | H33: =H34 -> 0 | I33: =I34 -> 0 | J33: =J34 -> 0 | K33: =K34 -> 0 | L33: =L34 -> 0 | ... Q33: =Q34 -> 0 | R33: =Q33 -> 0
B34: 9.1 | C34: Nhân viên mua hàng | R34: =Q34 -> 0
B35: 10 | C35: Tư Vấn Dịch Vụ | D35: 642 | E35: =E36 -> 0 | F35: =F36 -> 0 | G35: =G36 -> 0 | H35: =H36 -> 0 | I35: =I36 -> 0 | J35: =J36 -> 0 | K35: =K36 -> 0 | L35: =L36 -> 0 | ... Q35: =Q36 -> 0 | R35: =Q35 -> 0
B36: 10.1 | C36: Nhân viên | R36: =Q36 -> 0
B37: 11 | C37: Phòng Nghiên Cứu & Phát Triển | D37: 627 | E37: =E38 -> 0 | F37: =F38 -> 0 | G37: =G38 -> 0 | H37: =H38 -> 0 | I37: =I38 -> 0 | J37: =J38 -> 0 | K37: =K38 -> 0 | L37: =L38 -> 0 | ... Q37: =Q38 -> 0 | R37: =Q37 -> 0
B38: 11.1 | C38: Nhân viên | R38: =Q38 -> 0
B39: 12 | C39: Phòng Kiểm soát chất lượng | D39: 627 | E39: =E41+E42 -> 2 | F39: =SUM(F40:F42) -> 2 | G39: =SUM(G40:G42) -> 2 | H39: =SUM(H40:H42) -> 2 | I39: =SUM(I40:I42) -> 2 | J39: =SUM(J40:J42) -> 2 | K39: =SUM(K40:K42) -> 2 | L39: =SUM(L40:L42) -> 2 | M39: =SUM(M40:M42) -> 2 | ... R39: =SUM(R40:R42) -> 2
B40: 12.1 | C40: Tổ trưởng Kiểm soát chất lượng
B41: 12.2 | C41: Kiểm soát NVL | E41: 1 | F41: 1 | G41: 1 | H41: 1 | I41: 1 | J41: 1 | K41: 1 | L41: 1 | M41: 1 | N41: 1 | O41: 1 | P41: 1 | Q41: 1 | R41: 1
B42: 12.3 | C42: Kiểm soát thành phẩm | E42: 1 | F42: 1 | G42: 1 | H42: 1 | I42: 1 | J42: 1 | K42: 1 | L42: 1 | M42: 1 | N42: 1 | O42: 1 | P42: 1 | Q42: 1 | R42: 1
B43: 13 | C43: Phòng Kỹ thuật | D43: 627 | E43: =SUM(E44:E50) -> 6 | F43: =SUM(F44:F50) -> 6 | G43: =SUM(G44:G50) -> 6 | H43: =SUM(H44:H50) -> 6 | I43: =SUM(I44:I50) -> 6 | J43: =SUM(J44:J50) -> 6 | K43: =SUM(K44:K50) -> 6 | L43: =SUM(L44:L50) -> 6 | ... R43: =SUM(R44:R50) -> 6
B44: 13.1 | C44: Quản lý kỹ thuật | R44: =Q44 -> 0
B45: 13.2 | C45: Tổ trưởng vận hành máy | E45: 1 | F45: 1 | G45: 1 | H45: 1 | I45: 1 | J45: 1 | K45: 1 | L45: 1 | M45: 1 | N45: 1 | O45: 1 | P45: 1 | Q45: 1 | R45: 1
B46: 13.3 | C46: Tổ trưởng kỹ thuật nước và môi trường
B47: 13.3 | C47: Nhân viên vận hành máy | E47: 3 | F47: 3 | G47: 3 | H47: 3 | I47: 3 | J47: 3 | K47: 3 | L47: 3 | M47: 3 | N47: 3 | O47: 3 | P47: 3 | Q47: 3 | R47: 3
B48: 13.4 | C48: Nhân viên bảo trì | E48: 2 | F48: 2 | G48: 2 | H48: 2 | I48: 2 | J48: 2 | K48: 2 | L48: 2 | M48: 2 | N48: 2 | O48: 2 | P48: 2 | Q48: 2 | R48: 2
B49: 13.5 | C49: Nhân viên xử lý nước thải (24/24)
B50: 13.6 | C50: Nhân viên thống kê kỹ thuật | R50: =Q50 -> 0
B51: 14 | C51: Phòng Sản xuất | E51: =E52+E57+E63 -> 75 | F51: =F52+F57+F63 -> 66 | G51: =G52+G57+G63 -> 66 | H51: =H52+H57+H63 -> 66 | I51: =I52+I57+I63 -> 66 | J51: =J52+J57+J63 -> 66 | K51: =K52+K57+K63 -> 66 | L51: =L52+L57+L63 -> 66 | ... R51: =R52+R57+R63 -> 66
B52: 14.1 | C52: Bộ phận quản lý sản xuất | D52: 627 | E52: =E53+E54+E55+E56 -> 2 | F52: =SUM(F53:F56) -> 2 | G52: =SUM(G53:G56) -> 2 | H52: =SUM(H53:H56) -> 2 | I52: =SUM(I53:I56) -> 2 | J52: =SUM(J53:J56) -> 2 | K52: =SUM(K53:K56) -> 2 | L52: =SUM(L53:L56) -> 2 | M52: =SUM(M53:M56) -> 2 | ... R52: =SUM(R53:R56) -> 2
B53: 14.1.1 | C53: Trưởng phòng sản xuất | E53: 1 | F53: 1 | G53: 1 | H53: 1 | I53: 1 | J53: 1 | K53: 1 | L53: 1 | M53: 1 | N53: 1 | O53: 1 | P53: 1 | Q53: 1 | R53: =Q53 -> 1
B54: 14.1.2 | C54: Giám sát sản xuất | R54: =Q54 -> 0
B55: 14.1.3 | C55: Tổ trưởng sản xuất | R55: =Q55 -> 0
B56: 14.1.4 | C56: Nhân viên thống kê sản xuất | E56: 1 | F56: 1 | G56: 1 | H56: 1 | I56: 1 | J56: 1 | K56: 1 | L56: 1 | M56: 1 | N56: 1 | O56: 1 | P56: 1 | Q56: 1 | R56: =Q56 -> 1 | T56: Chi tiết phân bổ Công nhân trực tiếp SX
B57: 14.2 | C57: Công nhân trực tiếp sản xuất - Phân loại | D57: 622 | E57: =SUM(E58:E62) -> 70 | F57: =SUM(F58:F62) -> 58 | G57: =SUM(G58:G62) -> 58 | H57: =SUM(H58:H62) -> 58 | I57: =SUM(I58:I62) -> 58 | J57: =SUM(J58:J62) -> 58 | K57: =SUM(K58:K62) -> 58 | L57: =SUM(L58:L62) -> 58 | ... R57: =SUM(R58:R62) -> 58 | T57: Công nhân trực tiếp sản xuất - Phân loại
B58: 14.2.1 | C58: Nhân viên phân loại | E58: 16 | F58: =22-F64-F60-F61 -> 13 | G58: =22-G64-G60-G61 -> 13 | H58: =22-H64-H60-H61 -> 13 | I58: =22-I64-I60-I61 -> 13 | J58: =22-J64-J60-J61 -> 13 | K58: =22-K64-K60-K61 -> 13 | L58: =22-L64-L60-L61 -> 13 | M58: =22-M64-M60-M61 -> 13 | ... Q58: =22-Q64-Q60-Q61 -> 13 | R58: =Q58 -> 13 | T58: SX chai PET - Chuyền phân loại
B59: 14.2.2 | C59: Nhân viên sản xuất chung | T59: Công đoạn 1: Cấp liệu
B60: 14.2.3 | C60: Nhân viên ép kiện | E60: 2 | F60: 2 | G60: 2 | H60: 2 | I60: 2 | J60: 2 | K60: 2 | L60: 2 | M60: 2 | N60: 2 | O60: 2 | P60: 2 | Q60: 2 | R60: =Q60 -> 2 | T60: Công đoạn 2: Phân loại chai
B61: 14.2.4 | C61: Nhân viên lái xe nâng | E61: 1 | F61: 1 | G61: 1 | H61: 1 | I61: 1 | J61: 1 | K61: 1 | L61: 1 | M61: 1 | N61: 1 | O61: 1 | P61: 1 | Q61: 1 | R61: =Q61 -> 1 | T61: Công đoạn 3: Tách nhãn
B62: 14.2.4 | C62: Lao động thuê ngoài | E62: =54-E73-E30 -> 51 | F62: 42 | G62: 42 | H62: 42 | I62: 42 | J62: 42 | K62: 42 | L62: 42 | M62: 42 | N62: 42 | O62: 42 | P62: 42 | Q62: 42 | R62: 42 | T62: Công đoạn 4: Rework (B6.2+chai còn nhãn)
B63: 14.3 | C63: Công nhân trực tiếp sản xuất - Băm vảy PET | D63: 622 | E63: =E64+E67 -> 3 | F63: =F64+F67 -> 6 | G63: =G64+G67 -> 6 | H63: =H64+H67 -> 6 | I63: =I64+I67 -> 6 | J63: =J64+J67 -> 6 | K63: =K64+K67 -> 6 | L63: =L64+L67 -> 6 | ... Q63: =Q64+Q67 -> 6 | R63: =Q63 -> 6 | T63: Công đoạn 5: Ép kiện
B64: 14.3.1 | C64: Nhân viên băm vảy | E64: 3 | F64: 6 | G64: 6 | H64: 6 | I64: 6 | J64: 6 | K64: 6 | L64: 6 | M64: 6 | N64: 6 | O64: 6 | P64: 6 | Q64: 6 | R64: =Q64 -> 6 | T64: Sản xuất chung
B65: 14.3.2 | T65: Nhân viên lái xe nâng
B66: 14.3.3 | T66: Nhân viên kéo bao, bì tạp
B67: 14.3.4 | C67: Lao động thuê ngoài | T67: Nhân viên ghi số liệu
B68: 15 | C68: Phòng Kho vận | D68: 627 | E68: =SUM(E69:E73) -> 6 | F68: =SUM(F69:F73) -> 6 | G68: =SUM(G69:G73) -> 6 | H68: =SUM(H69:H73) -> 6 | I68: =SUM(I69:I73) -> 6 | J68: =SUM(J69:J73) -> 6 | K68: =SUM(K69:K73) -> 6 | L68: =SUM(L69:L73) -> 6 | ... R68: =SUM(R69:R73) -> 6 | T68: Xử lý phó sản
B69: 15.1 | C69: Thủ kho | E69: 1 | F69: 1 | G69: 1 | H69: 1 | I69: 1 | J69: 1 | K69: 1 | L69: 1 | M69: 1 | N69: 1 | O69: 1 | P69: 1 | Q69: 1 | R69: =Q69 -> 1 | T69: Nhân viên xử lý nắp, cổ chai,…
B70: 15.2 | C70: Tổ Trưởng Kho - Xuất nhập | R70: =Q70 -> 0
B71: 15.3 | C71: Nhân viên Nhập - Xuất hàng | E71: 1 | F71: 1 | G71: 1 | H71: 1 | I71: 1 | J71: 1 | K71: 1 | L71: 1 | M71: 1 | N71: 1 | O71: 1 | P71: 1 | Q71: 1 | R71: =Q71 -> 1
B72: 15.4 | C72: Nhân Viên Lái Xe Nâng | E72: 2 | F72: 2 | G72: 2 | H72: 2 | I72: 2 | J72: 2 | K72: 2 | L72: 2 | M72: 2 | N72: 2 | O72: 2 | P72: 2 | Q72: 2 | R72: =Q72 -> 2
B73: 15.5 | C73: Lao động thuê ngoài | E73: 2 | F73: 2 | G73: 2 | H73: 2 | I73: 2 | J73: 2 | K73: 2 | L73: 2 | M73: 2 | N73: 2 | O73: 2 | P73: 2 | Q73: 2 | R73: =Q73 -> 2
B74: 16 | C74: Trạm cấp 2 - Kiên Giang | D74: 642 | E74: =E75 -> 0 | F74: =F75 -> 0 | G74: =G75 -> 0 | H74: =H75 -> 0 | I74: =I75 -> 0 | J74: =J75 -> 0 | K74: =K75 -> 0 | L74: =L75 -> 0 | ... Q74: =Q75 -> 0
B75: 16.1 | C75: Nhân viên
B76: 17 | C76: Trạm cấp 2 - Cà Mau | D76: 642 | E76: =E77 -> 0 | F76: =F77 -> 0 | G76: =G77 -> 0 | H76: =H77 -> 0 | I76: =I77 -> 0 | J76: =J77 -> 0 | K76: =K77 -> 0 | L76: =L77 -> 0 | ... Q76: =Q77 -> 0
B77: 17.1 | C77: Nhân viên
B78: 18 | C78: Trạm cấp 2 - Gia Lai | D78: 642 | E78: =E79 -> 0 | F78: =F79 -> 0 | G78: =G79 -> 0 | H78: =H79 -> 0 | I78: =I79 -> 0 | J78: =J79 -> 0 | K78: =K79 -> 0 | L78: =L79 -> 0 | ... Q78: =Q79 -> 0
B79: 18.1 | C79: Nhân viên
C80: TỔNG NHÂN SỰ | E80: =E5+E8+E16+E21+E23+E25+E27+E31+E33+E35+E37+E39+E43+E51+E68+E74+E76+E78 -> 102 | F80: =F5+F8+F16+F21+F23+F25+F27+F31+F33+F35+F37+F39+F43+F51+F68+F74+F76+F78 -> 93 | G80: =G5+G8+G16+G21+G23+G25+G27+G31+G33+G35+G37+G39+G43+G51+G68+G74+G76+G78 -> 93 | H80: =H5+H8+H16+H21+H23+H25+H27+H31+H33+H35+H37+H39+H43+H51+H68+H74+H76+H78 -> 93 | I80: =I5+I8+I16+I21+I23+I25+I27+I31+I33+I35+I37+I39+I43+I51+I68+I74+I76+I78 -> 93 | J80: =J5+J8+J16+J21+J23+J25+J27+J31+J33+J35+J37+J39+J43+J51+J68+J74+J76+J78 -> 93 | K80: =K5+K8+K16+K21+K23+K25+K27+K31+K33+K35+K37+K39+K43+K51+K68+K74+K76+K78 -> 93 | L80: =L5+L8+L16+L21+L23+L25+L27+L31+L33+L35+L37+L39+L43+L51+L68+L74+L76+L78 -> 93 | ... R80: =R5+R8+R16+R21+R23+R25+R27+R31+R33+R35+R37+R39+R43+R51+R68+R74+R76+R78 -> 93
C81: Nhân sự thuộc ĐỊNH BIÊN | E81: =E80-E82 -> 48 | F81: =F80-F82 -> 48 | G81: =G80-G82 -> 48 | H81: =H80-H82 -> 48 | I81: =I80-I82 -> 48 | J81: =J80-J82 -> 48 | K81: =K80-K82 -> 48 | L81: =L80-L82 -> 48 | ... Q81: =Q80-Q82 -> 48 | R81: =Q81 -> 48
C82: Lao động thuê ngoài | E82: =E73+E67+E30+E62 -> 54 | F82: =F73+F67+F30+F62 -> 45 | G82: =G73+G67+G30+G62 -> 45 | H82: =H73+H67+H30+H62 -> 45 | I82: =I73+I67+I30+I62 -> 45 | J82: =J73+J67+J30+J62 -> 45 | K82: =K73+K67+K30+K62 -> 45 | L82: =L73+L67+L30+L62 -> 45 | ... R82: =R73+R67+R30+R62 -> 45
B84: II - ĐỊNH BIÊN - HD
B85: 19 | C85: XƯỞNG SẢN XUẤT | D85: =D4 -> Tài khoản | E85: =E4 -> KQKD 2025 | F85: =F4 -> T1 | G85: =G4 -> T2 | H85: =H4 -> T3 | I85: =I4 -> T4 | J85: =J4 -> T5 | K85: =K4 -> T6 | ... R85: =R4 -> KH 2026
B86: 19.1 | C86: Quản lý sản xuất | D86: 627
B87: 19.1.1 | C87: Trưởng ca sản xuất (theo ca sx)
B88: 19.2 | C88: Công nhân trực tiếp sản xuất | D88: 622
C89: TỔNG: | F89: =F87+F88 -> 0 | G89: =G87+G88 -> 0 | H89: =H87+H88 -> 0 | I89: =I87+I88 -> 0 | J89: =J87+J88 -> 0 | K89: =K87+K88 -> 0 | L89: =L87+L88 -> 0 | M89: =M87+M88 -> 0 | ... R89: =R87+R88 -> 0
F91: ='KQKD PET'!G5/'Dinh bien_HCNS'!F80/1000 -> 8.2717742 | G91: ='KQKD PET'!H5/'Dinh bien_HCNS'!G80/1000 -> 6.4336022 | H91: ='KQKD PET'!I5/'Dinh bien_HCNS'!H80/1000 -> 9.1908602 | I91: ='KQKD PET'!J5/'Dinh bien_HCNS'!I80/1000 -> 10.109946 | J91: ='KQKD PET'!K5/'Dinh bien_HCNS'!J80/1000 -> 10.097527 | K91: ='KQKD PET'!L5/'Dinh bien_HCNS'!K80/1000 -> 3.7867204 | L91: ='KQKD PET'!M5/'Dinh bien_HCNS'!L80/1000 -> 3.7867204 | M91: ='KQKD PET'!N5/'Dinh bien_HCNS'!M80/1000 -> 3.7867204 | ... Q91: ='KQKD PET'!R5/'Dinh bien_HCNS'!Q80/1000 -> 3.7867204

Sheet LUONG
B3: BẢNG LƯƠNG TỪ HCNS - SẢN XUẤT PET | F3: 1 | G3: 2 | H3: 3 | I3: 4 | J3: 5 | K3: 6 | L3: 7 | M3: 8 | N3: 9 | O3: 10 | P3: 11 | Q3: 12
B4: Phòng ban | C4: Mã tài khoản (Mã Chi phí_L4) | D4: Tên tài khoản (Cost elements 2) | E4: Chi Phí_L5 (Cost Group 2) | F4: T1 | G4: T2 | H4: T3 | I4: T4 | J4: T5 | K4: T6 | L4: T7 | M4: T8 | N4: T9 | O4: T10 | P4: T11 | Q4: T12 | R4: Mục tiêu 2026
B5: Ban giám đốc | D5: Số lượng nhân sự | F5: ='Dinh bien_HCNS'!F5 -> 2 | G5: ='Dinh bien_HCNS'!G5 -> 2 | H5: ='Dinh bien_HCNS'!H5 -> 2 | I5: ='Dinh bien_HCNS'!I5 -> 2 | J5: ='Dinh bien_HCNS'!J5 -> 2 | K5: ='Dinh bien_HCNS'!K5 -> 2 | L5: ='Dinh bien_HCNS'!L5 -> 2 | M5: ='Dinh bien_HCNS'!M5 -> 2 | ... Q5: ='Dinh bien_HCNS'!Q5 -> 2 | R5: 2
B6: Ban giám đốc | D6: ADM_Lương Khối Quản Lý | F6: =SUM(F8:F16) -> 122904333 | G6: =SUM(G8:G16) -> 124845948 | H6: =SUM(H8:H16) -> 117254102 | I6: =SUM(I8:I16) -> 125250948 | J6: =SUM(J8:J16) -> 120476718 | K6: =SUM(K8:K16) -> 125250948 | L6: =SUM(L8:L16) -> 122585333 | M6: =SUM(M8:M16) -> 122585333 | ... R6: =SUM(R8:R16) -> 1474398610
B7: Ban giám đốc | D7: Chi phí lương TB/1 Người | F7: =IFERROR(SUM(F8:F15)/F5,0) -> 61452166 | G7: =IFERROR(SUM(G8:G15)/G5,0) -> 62422974 | H7: =IFERROR(SUM(H8:H15)/H5,0) -> 58627051 | I7: =IFERROR(SUM(I8:I15)/I5,0) -> 62625474 | J7: =IFERROR(SUM(J8:J15)/J5,0) -> 60238359 | K7: =IFERROR(SUM(K8:K15)/K5,0) -> 62625474 | L7: =IFERROR(SUM(L8:L15)/L5,0) -> 61292666 | M7: =IFERROR(SUM(M8:M15)/M5,0) -> 61292666 | ... Q7: =IFERROR(SUM(Q8:Q15)/Q5,0) -> 61292666
B8: Ban giám đốc | C8: 6421002604 | D8: Chi phí lương chính - Gián tiếp | E8: Salary and Wages - Direct | F8: 87200000 | G8: 89784615 | H8: 82030769 | I8: 89784615 | J8: 84615385 | K8: 89784615 | L8: 87200000 | M8: 87200000 | N8: 89784615 | O8: 84615385 | P8: 89784615 | Q8: 87200000 | R8: =SUM(F8:Q8) -> 1048984614
B9: Ban giám đốc | C9: 6421002605 | D9: Chi phí lương T13, phép năm - Gián tiếp | E9: Salary and Wages - Support | F9: 6903333 | G9: 6903333 | H9: 6903333 | I9: 6903333 | J9: 6903333 | K9: 6903333 | L9: 6903333 | M9: 6903333 | N9: 6903333 | O9: 6903333 | P9: 6903333 | Q9: 6903333 | R9: =SUM(F9:Q9) -> 82839996
B10: Ban giám đốc | C10: 6421002802 | D10: Chi phí khen thưởng - Gián tiếp | E10: Employee Welfare | F10: 1500000 | G10: 1100000 | H10: 1100000 | I10: 1100000 | J10: 1900000 | K10: 1100000 | L10: 1100000 | M10: 1100000 | N10: 1500000 | O10: 1100000 | P10: 1100000 | Q10: 1100000 | R10: =SUM(F10:Q10) -> 14800000
B11: Ban giám đốc | C11: 6421002806 | D11: Thưởng danh hiệu | E11: Salary and Wages - Support | F11: 9374000 | G11: 9374000 | H11: 9374000 | I11: 9374000 | J11: 9374000 | K11: 9374000 | L11: 9374000 | M11: 9374000 | N11: 9374000 | O11: 9374000 | P11: 9374000 | Q11: 9374000 | R11: =SUM(F11:Q11) -> 112488000
B12: Ban giám đốc | C12: 6421007202 | D12: Chi phí khen thưởng, bồi dưỡng khác | E12: Employee Welfare | F12: 0 | G12: 0 | H12: 0 | I12: 0 | J12: 0 | K12: 0 | L12: 0 | M12: 0 | N12: 0 | O12: 0 | P12: 0 | Q12: 0 | R12: =SUM(F12:Q12) -> 0
B13: Ban giám đốc | C13: 6421003202 | D13: Tiền ăn giữa ca - Gián tiếp | E13: Employee Welfare | F13: 2025000 | G13: 1782000 | H13: 1944000 | I13: 2187000 | J13: 1782000 | K13: 2187000 | L13: 2106000 | M13: 2106000 | N13: 2025000 | O13: 2025000 | P13: 2187000 | Q13: 2106000 | R13: =SUM(F13:Q13) -> 24462000
B14: Ban giám đốc | C14: 6421002603 | D14: Phụ cấp ca đêm - Gián tiếp | E14: Salary and Wages - Support | F14: 0 | G14: 0 | H14: 0 | I14: 0 | J14: 0 | K14: 0 | L14: 0 | M14: 0 | N14: 0 | O14: 0 | P14: 0 | Q14: 0 | R14: =SUM(F14:Q14) -> 0
B15: Ban giám đốc | C15: 6421003401 | D15: BHXH, BHYT, KPCĐ, BHTN - Gián tiếp | E15: Employee Welfare | F15: 15902000 | G15: 15902000 | H15: 15902000 | I15: 15902000 | J15: 15902000 | K15: 15902000 | L15: 15902000 | M15: 15902000 | N15: 15902000 | O15: 15902000 | P15: 15902000 | Q15: 15902000 | R15: =SUM(F15:Q15) -> 190824000
B16: Ban giám đốc | C16: 6421002703 | D16: Chi phí lương ngoài giờ - Gián tiếp | E16: Salary and Wages - Support | F16: 0 | G16: 0 | H16: 0 | I16: 0 | J16: 0 | K16: 0 | L16: 0 | M16: 0 | N16: 0 | O16: 0 | P16: 0 | Q16: 0 | R16: =SUM(F16:Q16) -> 0
B17: Phòng Hành chánh nhân sự | D17: Số lượng nhân sự | F17: ='Dinh bien_HCNS'!F8 -> 2 | G17: ='Dinh bien_HCNS'!G8 -> 2 | H17: ='Dinh bien_HCNS'!H8 -> 2 | I17: ='Dinh bien_HCNS'!I8 -> 2 | J17: ='Dinh bien_HCNS'!J8 -> 2 | K17: ='Dinh bien_HCNS'!K8 -> 2 | L17: ='Dinh bien_HCNS'!L8 -> 2 | M17: ='Dinh bien_HCNS'!M8 -> 2 | ... Q17: ='Dinh bien_HCNS'!Q8 -> 2 | R17: =Q17 -> 2
B18: Phòng Hành chánh nhân sự | D18: ADM_Lương Khối Quản Lý | F18: =SUM(F20:F28) -> 36609307 | G18: =SUM(G20:G28) -> 36976461 | H18: =SUM(H20:H28) -> 34282999 | I18: =SUM(I20:I28) -> 37256461 | J18: =SUM(J20:J28) -> 35906153 | K18: =SUM(K20:K28) -> 37256461 | L18: =SUM(L20:L28) -> 36265307 | M18: =SUM(M20:M28) -> 36265307 | ... R18: =SUM(R20:R28) -> 437158838
B19: Phòng Hành chánh nhân sự | D19: Chi phí lương TB/1 Người | F19: =IFERROR(SUM(F20:F27)/F17,0) -> 18304654 | G19: =IFERROR(SUM(G20:G27)/G17,0) -> 18488230 | H19: =IFERROR(SUM(H20:H27)/H17,0) -> 17141500 | I19: =IFERROR(SUM(I20:I27)/I17,0) -> 18628230 | J19: =IFERROR(SUM(J20:J27)/J17,0) -> 17953076 | K19: =IFERROR(SUM(K20:K27)/K17,0) -> 18628230 | L19: =IFERROR(SUM(L20:L27)/L17,0) -> 18132654 | M19: =IFERROR(SUM(M20:M27)/M17,0) -> 18132654 | ... Q19: =IFERROR(SUM(Q20:Q27)/Q17,0) -> 18132654
B20: Phòng Hành chánh nhân sự | C20: 6421002604 | D20: Chi phí lương chính - Gián tiếp | E20: Salary and Wages - Direct | F20: 24314000 | G20: 25249154 | H20: 22443692 | I20: 25249154 | J20: 23378846 | K20: 25249154 | L20: 24314000 | M20: 24314000 | N20: 25249154 | O20: 23378846 | P20: 25249154 | Q20: 24314000 | R20: =SUM(F20:Q20) -> 292703154
B21: Phòng Hành chánh nhân sự | C21: 6421002605 | D21: Chi phí lương T13, phép năm - Gián tiếp | E21: Salary and Wages - Support | F21: 1924859 | G21: 1924859 | H21: 1924859 | I21: 1924859 | J21: 1924859 | K21: 1924859 | L21: 1924859 | M21: 1924859 | N21: 1924859 | O21: 1924859 | P21: 1924859 | Q21: 1924859 | R21: =SUM(F21:Q21) -> 23098308
B22: Phòng Hành chánh nhân sự | C22: 6421002802 | D22: Chi phí khen thưởng - Gián tiếp | E22: Employee Welfare | F22: 1150000 | G22: 750000 | H22: 750000 | I22: 750000 | J22: 1550000 | K22: 750000 | L22: 750000 | M22: 750000 | N22: 1150000 | O22: 750000 | P22: 750000 | Q22: 750000 | R22: =SUM(F22:Q22) -> 10600000
B23: Phòng Hành chánh nhân sự | C23: 6421002806 | D23: Thưởng danh hiệu | E23: Salary and Wages - Support | F23: 2007924 | G23: 2007924 | H23: 2007924 | I23: 2007924 | J23: 2007924 | K23: 2007924 | L23: 2007924 | M23: 2007924 | N23: 2007924 | O23: 2007924 | P23: 2007924 | Q23: 2007924 | R23: =SUM(F23:Q23) -> 24095088
B24: Phòng Hành chánh nhân sự | C24: 6421007202 | D24: Chi phí khen thưởng, bồi dưỡng khác | E24: Employee Welfare | F24: 98734 | G24: 98734 | H24: 98734 | I24: 98734 | J24: 98734 | K24: 98734 | L24: 98734 | M24: 98734 | N24: 98734 | O24: 98734 | P24: 98734 | Q24: 98734 | R24: =SUM(F24:Q24) -> 1184808
B25: Phòng Hành chánh nhân sự | C25: 6421003202 | D25: Tiền ăn giữa ca - Gián tiếp | E25: Employee Welfare | F25: 1400000 | G25: 1232000 | H25: 1344000 | I25: 1512000 | J25: 1232000 | K25: 1512000 | L25: 1456000 | M25: 1456000 | N25: 1400000 | O25: 1400000 | P25: 1512000 | Q25: 1456000 | R25: =SUM(F25:Q25) -> 16912000
B26: Phòng Hành chánh nhân sự | C26: 6421002603 | D26: Phụ cấp ca đêm - Gián tiếp | E26: Salary and Wages - Support | F26: 0 | G26: 0 | H26: 0 | I26: 0 | J26: 0 | K26: 0 | L26: 0 | M26: 0 | N26: 0 | O26: 0 | P26: 0 | Q26: 0 | R26: =SUM(F26:Q26) -> 0
B27: Phòng Hành chánh nhân sự | C27: 6421003401 | D27: BHXH, BHYT, KPCĐ, BHTN - Gián tiếp | E27: Employee Welfare | F27: 5713790 | G27: 5713790 | H27: 5713790 | I27: 5713790 | J27: 5713790 | K27: 5713790 | L27: 5713790 | M27: 5713790 | N27: 5713790 | O27: 5713790 | P27: 5713790 | Q27: 5713790 | R27: =SUM(F27:Q27) -> 68565480
B28: Phòng Hành chánh nhân sự | C28: 6421002703 | D28: Chi phí lương ngoài giờ - Gián tiếp | E28: Salary and Wages - Support | F28: 0 | G28: 0 | H28: 0 | I28: 0 | J28: 0 | K28: 0 | L28: 0 | M28: 0 | N28: 0 | O28: 0 | P28: 0 | Q28: 0 | R28: =SUM(F28:Q28) -> 0
B29: Phòng Kế toán | D29: Số lượng nhân sự | F29: 3 | G29: ='Dinh bien_HCNS'!F16 -> 3 | H29: ='Dinh bien_HCNS'!G16 -> 3 | I29: ='Dinh bien_HCNS'!H16 -> 3 | J29: ='Dinh bien_HCNS'!I16 -> 3 | K29: ='Dinh bien_HCNS'!J16 -> 3 | L29: ='Dinh bien_HCNS'!K16 -> 3 | M29: ='Dinh bien_HCNS'!L16 -> 3 | N29: ='Dinh bien_HCNS'!M16 -> 3 | ... Q29: ='Dinh bien_HCNS'!P16 -> 3 | R29: =Q29 -> 3
B30: Phòng Kế toán | D30: ADM_Lương Khối Quản Lý | F30: =SUM(F32:F40) -> 72145573 | G30: =SUM(G32:G40) -> 73172343 | H30: =SUM(H32:H40) -> 67704034 | I30: =SUM(I32:I40) -> 73592343 | J30: =SUM(J32:J40) -> 70614803 | K30: =SUM(K32:K40) -> 73592343 | L30: =SUM(L32:L40) -> 71629573 | M30: =SUM(M32:M40) -> 71629573 | ... R30: =SUM(R32:R40) -> 862993647
B31: Phòng Kế toán | D31: Chi phí lương TB/1 Người | F31: =IFERROR(SUM(F32:F39)/F29,0) -> 24048524 | G31: =IFERROR(SUM(G32:G39)/G29,0) -> 24390781 | H31: =IFERROR(SUM(H32:H39)/H29,0) -> 22568011 | I31: =IFERROR(SUM(I32:I39)/I29,0) -> 24530781 | J31: =IFERROR(SUM(J32:J39)/J29,0) -> 23538268 | K31: =IFERROR(SUM(K32:K39)/K29,0) -> 24530781 | L31: =IFERROR(SUM(L32:L39)/L29,0) -> 23876524 | M31: =IFERROR(SUM(M32:M39)/M29,0) -> 23876524 | ... Q31: =IFERROR(SUM(Q32:Q39)/Q29,0) -> 23876524
B32: Phòng Kế toán | C32: 6421002604 | D32: Chi phí lương chính - Gián tiếp | E32: Salary and Wages - Direct | F32: 48848000 | G32: 50726770 | H32: 45090461 | I32: 50726770 | J32: 46969230 | K32: 50726770 | L32: 48848000 | M32: 48848000 | N32: 50726770 | O32: 46969230 | P32: 50726770 | Q32: 48848000 | R32: =SUM(F32:Q32) -> 588054771
B33: Phòng Kế toán | C33: 6421002605 | D33: Chi phí lương T13, phép năm - Gián tiếp | E33: Salary and Wages - Support | F33: 3867133 | G33: 3867133 | H33: 3867133 | I33: 3867133 | J33: 3867133 | K33: 3867133 | L33: 3867133 | M33: 3867133 | N33: 3867133 | O33: 3867133 | P33: 3867133 | Q33: 3867133 | R33: =SUM(F33:Q33) -> 46405596
B34: Phòng Kế toán | C34: 6421002802 | D34: Chi phí khen thưởng - Gián tiếp | E34: Employee Welfare | F34: 600000 | G34: 0 | H34: 0 | I34: 0 | J34: 1200000 | K34: 0 | L34: 0 | M34: 0 | N34: 600000 | O34: 0 | P34: 0 | Q34: 0 | R34: =SUM(F34:Q34) -> 2400000
B35: Phòng Kế toán | C35: 6421002806 | D35: Thưởng danh hiệu | E35: Salary and Wages - Support | F35: 5251160 | G35: 5251160 | H35: 5251160 | I35: 5251160 | J35: 5251160 | K35: 5251160 | L35: 5251160 | M35: 5251160 | N35: 5251160 | O35: 5251160 | P35: 5251160 | Q35: 5251160 | R35: =SUM(F35:Q35) -> 63013920
B36: Phòng Kế toán | C36: 6421007202 | D36: Chi phí khen thưởng, bồi dưỡng khác | E36: Employee Welfare | F36: 0 | G36: 0 | H36: 0 | I36: 0 | J36: 0 | K36: 0 | L36: 0 | M36: 0 | N36: 0 | O36: 0 | P36: 0 | Q36: 0 | R36: =SUM(F36:Q36) -> 0
B37: Phòng Kế toán | C37: 6421003202 | D37: Tiền ăn giữa ca - Gián tiếp | E37: Employee Welfare | F37: 2100000 | G37: 1848000 | H37: 2016000 | I37: 2268000 | J37: 1848000 | K37: 2268000 | L37: 2184000 | M37: 2184000 | N37: 2100000 | O37: 2100000 | P37: 2268000 | Q37: 2184000 | R37: =SUM(F37:Q37) -> 25368000
B38: Phòng Kế toán | C38: 6421002603 | D38: Phụ cấp ca đêm - Gián tiếp | E38: Salary and Wages - Support | F38: 0 | G38: 0 | H38: 0 | I38: 0 | J38: 0 | K38: 0 | L38: 0 | M38: 0 | N38: 0 | O38: 0 | P38: 0 | Q38: 0 | R38: =SUM(F38:Q38) -> 0
B39: Phòng Kế toán | C39: 6421003401 | D39: BHXH, BHYT, KPCĐ, BHTN - Gián tiếp | E39: Employee Welfare | F39: 11479280 | G39: 11479280 | H39: 11479280 | I39: 11479280 | J39: 11479280 | K39: 11479280 | L39: 11479280 | M39: 11479280 | N39: 11479280 | O39: 11479280 | P39: 11479280 | Q39: 11479280 | R39: =SUM(F39:Q39) -> 137751360
B40: Phòng Kế toán | C40: 6421002703 | D40: Chi phí lương ngoài giờ - Gián tiếp | E40: Salary and Wages - Support | F40: 0 | G40: 0 | H40: 0 | I40: 0 | J40: 0 | K40: 0 | L40: 0 | M40: 0 | N40: 0 | O40: 0 | P40: 0 | Q40: 0 | R40: =SUM(F40:Q40) -> 0
B41: Phòng Mua hàng | D41: Số lượng nhân sự | F41: 1 | G41: ='Dinh bien_HCNS'!F21 -> 1 | H41: ='Dinh bien_HCNS'!G21 -> 1 | I41: ='Dinh bien_HCNS'!H21 -> 1 | J41: ='Dinh bien_HCNS'!I21 -> 1 | K41: ='Dinh bien_HCNS'!J21 -> 1 | L41: ='Dinh bien_HCNS'!K21 -> 1 | M41: ='Dinh bien_HCNS'!L21 -> 1 | N41: ='Dinh bien_HCNS'!M21 -> 1 | ... Q41: ='Dinh bien_HCNS'!P21 -> 1 | R41: 1
B42: Phòng Mua hàng | D42: ADM_Lương Khối Quản Lý | F42: =SUM(F44:F52) -> 15462700 | G42: =SUM(G44:G52) -> 15545623 | H42: =SUM(H44:H52) -> 14500854 | I42: =SUM(I44:I52) -> 15685623 | J42: =SUM(J44:J52) -> 15211777 | K42: =SUM(K44:K52) -> 15685623 | L42: =SUM(L44:L52) -> 15290700 | M42: =SUM(M44:M52) -> 15290700 | ... R42: =SUM(R44:R52) -> 184375323
B43: Phòng Mua hàng | D43: Chi phí lương TB/1 Người | F43: =IFERROR(SUM(F44:F51)/F41,0) -> 15462700 | G43: =IFERROR(SUM(G44:G51)/G41,0) -> 15545623 | H43: =IFERROR(SUM(H44:H51)/H41,0) -> 14500854 | I43: =IFERROR(SUM(I44:I51)/I41,0) -> 15685623 | J43: =IFERROR(SUM(J44:J51)/J41,0) -> 15211777 | K43: =IFERROR(SUM(K44:K51)/K41,0) -> 15685623 | L43: =IFERROR(SUM(L44:L51)/L41,0) -> 15290700 | M43: =IFERROR(SUM(M44:M51)/M41,0) -> 15290700 | ... Q43: =IFERROR(SUM(Q44:Q51)/Q41,0) -> 15290700
B44: Phòng Mua hàng | C44: 6421002604 | D44: Chi phí lương chính - Gián tiếp | E44: Salary and Wages - Direct | F44: 9540000 | G44: 9906923 | H44: 8806154 | I44: 9906923 | J44: 9173077 | K44: 9906923 | L44: 9540000 | M44: 9540000 | N44: 9906923 | O44: 9173077 | P44: 9906923 | Q44: 9540000 | R44: =SUM(F44:Q44) -> 114846923
B45: Phòng Mua hàng | C45: 6421002605 | D45: Chi phí lương T13, phép năm - Gián tiếp | E45: Salary and Wages - Support | F45: 755250 | G45: 755250 | H45: 755250 | I45: 755250 | J45: 755250 | K45: 755250 | L45: 755250 | M45: 755250 | N45: 755250 | O45: 755250 | P45: 755250 | Q45: 755250 | R45: =SUM(F45:Q45) -> 9063000
B46: Phòng Mua hàng | C46: 6421002802 | D46: Chi phí khen thưởng - Gián tiếp | E46: Employee Welfare | F46: 1200000 | G46: 1000000 | H46: 1000000 | I46: 1000000 | J46: 1400000 | K46: 1000000 | L46: 1000000 | M46: 1000000 | N46: 1200000 | O46: 1000000 | P46: 1000000 | Q46: 1000000 | R46: =SUM(F46:Q46) -> 12800000
B47: Phòng Mua hàng | C47: 6421002806 | D47: Thưởng danh hiệu | E47: Salary and Wages - Support | F47: 1025550 | G47: 1025550 | H47: 1025550 | I47: 1025550 | J47: 1025550 | K47: 1025550 | L47: 1025550 | M47: 1025550 | N47: 1025550 | O47: 1025550 | P47: 1025550 | Q47: 1025550 | R47: =SUM(F47:Q47) -> 12306600
B48: Phòng Mua hàng | C48: 6421007202 | D48: Chi phí khen thưởng, bồi dưỡng khác | E48: Employee Welfare | F48: 0 | G48: 0 | H48: 0 | I48: 0 | J48: 0 | K48: 0 | L48: 0 | M48: 0 | N48: 0 | O48: 0 | P48: 0 | Q48: 0 | R48: =SUM(F48:Q48) -> 0
B49: Phòng Mua hàng | C49: 6421003202 | D49: Tiền ăn giữa ca - Gián tiếp | E49: Employee Welfare | F49: 700000 | G49: 616000 | H49: 672000 | I49: 756000 | J49: 616000 | K49: 756000 | L49: 728000 | M49: 728000 | N49: 700000 | O49: 700000 | P49: 756000 | Q49: 728000 | R49: =SUM(F49:Q49) -> 8456000
B50: Phòng Mua hàng | C50: 6421002603 | D50: Phụ cấp ca đêm - Gián tiếp | E50: Salary and Wages - Support | F50: 0 | G50: 0 | H50: 0 | I50: 0 | J50: 0 | K50: 0 | L50: 0 | M50: 0 | N50: 0 | O50: 0 | P50: 0 | Q50: 0 | R50: =SUM(F50:Q50) -> 0
B51: Phòng Mua hàng | C51: 6421003401 | D51: BHXH, BHYT, KPCĐ, BHTN - Gián tiếp | E51: Employee Welfare | F51: 2241900 | G51: 2241900 | H51: 2241900 | I51: 2241900 | J51: 2241900 | K51: 2241900 | L51: 2241900 | M51: 2241900 | N51: 2241900 | O51: 2241900 | P51: 2241900 | Q51: 2241900 | R51: =SUM(F51:Q51) -> 26902800
B52: Phòng Mua hàng | C52: 6421002703 | D52: Chi phí lương ngoài giờ - Gián tiếp | E52: Salary and Wages - Support | F52: 0 | G52: 0 | H52: 0 | I52: 0 | J52: 0 | K52: 0 | L52: 0 | M52: 0 | N52: 0 | O52: 0 | P52: 0 | Q52: 0 | R52: =SUM(F52:Q52) -> 0
B53: Ban dự án XDCB | D53: Số lượng nhân sự
B54: Ban dự án XDCB | D54: ADM_Lương Khối Quản Lý | F54: =SUM(F56:F63) -> 0 | G54: =SUM(G56:G63) -> 0 | H54: =SUM(H56:H63) -> 0 | I54: =SUM(I56:I63) -> 0 | J54: =SUM(J56:J63) -> 0 | K54: =SUM(K56:K63) -> 0 | L54: =SUM(L56:L63) -> 0 | M54: =SUM(M56:M63) -> 0 | ... Q54: =SUM(Q56:Q63) -> 0 | R54: =SUM(F54:Q54) -> 0
B55: Ban dự án XDCB | D55: Chi phí lương TB/1 Người | F55: =IFERROR(SUM(F56:F63)/F53,0) -> 0 | G55: =IFERROR(SUM(G56:G63)/G53,0) -> 0 | H55: =IFERROR(SUM(H56:H63)/H53,0) -> 0 | I55: =IFERROR(SUM(I56:I63)/I53,0) -> 0 | J55: =IFERROR(SUM(J56:J63)/J53,0) -> 0 | K55: =IFERROR(SUM(K56:K63)/K53,0) -> 0 | L55: =IFERROR(SUM(L56:L63)/L53,0) -> 0 | M55: =IFERROR(SUM(M56:M63)/M53,0) -> 0 | ... Q55: =IFERROR(SUM(Q56:Q63)/Q53,0) -> 0
B56: Ban dự án XDCB | C56: 6421002604 | D56: Chi phí lương chính - Gián tiếp | E56: Salary and Wages - Direct | F56: 0 | G56: 0 | H56: 0 | I56: 0 | J56: 0 | K56: 0 | L56: 0 | M56: 0 | N56: 0 | O56: 0 | P56: 0 | Q56: 0 | R56: =SUM(F56:Q56) -> 0
B57: Ban dự án XDCB | C57: 6421002605 | D57: Chi phí lương T13, phép năm - Gián tiếp | E57: Salary and Wages - Support | F57: 0 | G57: 0 | H57: 0 | I57: 0 | J57: 0 | K57: 0 | L57: 0 | M57: 0 | N57: 0 | O57: 0 | P57: 0 | Q57: 0 | R57: =SUM(F57:Q57) -> 0
B58: Ban dự án XDCB | C58: 6421002802 | D58: Chi phí khen thưởng - Gián tiếp | E58: Employee Welfare | F58: 0 | G58: 0 | H58: 0 | I58: 0 | J58: 0 | K58: 0 | L58: 0 | M58: 0 | N58: 0 | O58: 0 | P58: 0 | Q58: 0 | R58: =SUM(F58:Q58) -> 0
B59: Ban dự án XDCB | C59: 6421002806 | D59: Thưởng danh hiệu | E59: Salary and Wages - Support | F59: 0 | G59: 0 | H59: 0 | I59: 0 | J59: 0 | K59: 0 | L59: 0 | M59: 0 | N59: 0 | O59: 0 | P59: 0 | Q59: 0 | R59: =SUM(F59:Q59) -> 0
B60: Ban dự án XDCB | C60: 6421007202 | D60: Chi phí khen thưởng, bồi dưỡng khác | E60: Employee Welfare | F60: 0 | G60: 0 | H60: 0 | I60: 0 | J60: 0 | K60: 0 | L60: 0 | M60: 0 | N60: 0 | O60: 0 | P60: 0 | Q60: 0 | R60: =SUM(F60:Q60) -> 0
B61: Ban dự án XDCB | C61: 6421003202 | D61: Tiền ăn giữa ca - Gián tiếp | E61: Employee Welfare | F61: 0 | G61: 0 | H61: 0 | I61: 0 | J61: 0 | K61: 0 | L61: 0 | M61: 0 | N61: 0 | O61: 0 | P61: 0 | Q61: 0 | R61: =SUM(F61:Q61) -> 0
B62: Ban dự án XDCB | C62: 6421002603 | D62: Phụ cấp ca đêm - Gián tiếp | E62: Salary and Wages - Support | F62: 0 | G62: 0 | H62: 0 | I62: 0 | J62: 0 | K62: 0 | L62: 0 | M62: 0 | N62: 0 | O62: 0 | P62: 0 | Q62: 0 | R62: =SUM(F62:Q62) -> 0
B63: Ban dự án XDCB | C63: 6421003401 | D63: BHXH, BHYT, KPCĐ, BHTN - Gián tiếp | E63: Employee Welfare | F63: 0 | G63: 0 | H63: 0 | I63: 0 | J63: 0 | K63: 0 | L63: 0 | M63: 0 | N63: 0 | O63: 0 | P63: 0 | Q63: 0 | R63: =SUM(F63:Q63) -> 0
B64: Ban dự án XDCB | C64: 6421002703 | D64: Chi phí lương ngoài giờ - Gián tiếp | E64: Salary and Wages - Support | F64: 0 | G64: 0 | H64: 0 | I64: 0 | J64: 0 | K64: 0 | L64: 0 | M64: 0 | N64: 0 | O64: 0 | P64: 0 | Q64: 0 | R64: =SUM(F64:Q64) -> 0
B65: Phòng Quản Trị Hệ Thống | D65: Số lượng nhân sự
B66: Phòng Quản Trị Hệ Thống | D66: ADM_Lương Khối Quản Lý | F66: =SUM(F68:F75) -> 0 | G66: =SUM(G68:G75) -> 0 | H66: =SUM(H68:H75) -> 0 | I66: =SUM(I68:I75) -> 0 | J66: =SUM(J68:J75) -> 0 | K66: =SUM(K68:K75) -> 0 | L66: =SUM(L68:L75) -> 0 | M66: =SUM(M68:M75) -> 0 | ... Q66: =SUM(Q68:Q75) -> 0 | R66: =SUM(F66:Q66) -> 0
B67: Phòng Quản Trị Hệ Thống | D67: Chi phí lương TB/1 Người | F67: =IFERROR(SUM(F68:F75)/F65,0) -> 0 | G67: =IFERROR(SUM(G68:G75)/G65,0) -> 0 | H67: =IFERROR(SUM(H68:H75)/H65,0) -> 0 | I67: =IFERROR(SUM(I68:I75)/I65,0) -> 0 | J67: =IFERROR(SUM(J68:J75)/J65,0) -> 0 | K67: =IFERROR(SUM(K68:K75)/K65,0) -> 0 | L67: =IFERROR(SUM(L68:L75)/L65,0) -> 0 | M67: =IFERROR(SUM(M68:M75)/M65,0) -> 0 | ... Q67: =IFERROR(SUM(Q68:Q75)/Q65,0) -> 0
B68: Phòng Quản Trị Hệ Thống | C68: 6421002604 | D68: Chi phí lương chính - Gián tiếp | E68: Salary and Wages - Direct | F68: 0 | G68: 0 | H68: 0 | I68: 0 | J68: 0 | K68: 0 | L68: 0 | M68: 0 | N68: 0 | O68: 0 | P68: 0 | Q68: 0 | R68: =SUM(F68:Q68) -> 0
B69: Phòng Quản Trị Hệ Thống | C69: 6421002605 | D69: Chi phí lương T13, phép năm - Gián tiếp | E69: Salary and Wages - Support | F69: 0 | G69: 0 | H69: 0 | I69: 0 | J69: 0 | K69: 0 | L69: 0 | M69: 0 | N69: 0 | O69: 0 | P69: 0 | Q69: 0 | R69: =SUM(F69:Q69) -> 0
B70: Phòng Quản Trị Hệ Thống | C70: 6421002802 | D70: Chi phí khen thưởng - Gián tiếp | E70: Employee Welfare | F70: 0 | G70: 0 | H70: 0 | I70: 0 | J70: 0 | K70: 0 | L70: 0 | M70: 0 | N70: 0 | O70: 0 | P70: 0 | Q70: 0 | R70: =SUM(F70:Q70) -> 0
B71: Phòng Quản Trị Hệ Thống | C71: 6421002806 | D71: Thưởng danh hiệu | E71: Salary and Wages - Support | F71: 0 | G71: 0 | H71: 0 | I71: 0 | J71: 0 | K71: 0 | L71: 0 | M71: 0 | N71: 0 | O71: 0 | P71: 0 | Q71: 0 | R71: =SUM(F71:Q71) -> 0
B72: Phòng Quản Trị Hệ Thống | C72: 6421007202 | D72: Chi phí khen thưởng, bồi dưỡng khác | E72: Employee Welfare | F72: 0 | G72: 0 | H72: 0 | I72: 0 | J72: 0 | K72: 0 | L72: 0 | M72: 0 | N72: 0 | O72: 0 | P72: 0 | Q72: 0 | R72: =SUM(F72:Q72) -> 0
B73: Phòng Quản Trị Hệ Thống | C73: 6421003202 | D73: Tiền ăn giữa ca - Gián tiếp | E73: Employee Welfare | F73: 0 | G73: 0 | H73: 0 | I73: 0 | J73: 0 | K73: 0 | L73: 0 | M73: 0 | N73: 0 | O73: 0 | P73: 0 | Q73: 0 | R73: =SUM(F73:Q73) -> 0
B74: Phòng Quản Trị Hệ Thống | C74: 6421002603 | D74: Phụ cấp ca đêm - Gián tiếp | E74: Salary and Wages - Support | F74: 0 | G74: 0 | H74: 0 | I74: 0 | J74: 0 | K74: 0 | L74: 0 | M74: 0 | N74: 0 | O74: 0 | P74: 0 | Q74: 0 | R74: =SUM(F74:Q74) -> 0
B75: Phòng Quản Trị Hệ Thống | C75: 6421003401 | D75: BHXH, BHYT, KPCĐ, BHTN - Gián tiếp | E75: Employee Welfare | F75: 0 | G75: 0 | H75: 0 | I75: 0 | J75: 0 | K75: 0 | L75: 0 | M75: 0 | N75: 0 | O75: 0 | P75: 0 | Q75: 0 | R75: =SUM(F75:Q75) -> 0
B76: Phòng Quản Trị Hệ Thống | C76: 6421002703 | D76: Chi phí lương ngoài giờ - Gián tiếp | E76: Salary and Wages - Support | F76: 0 | G76: 0 | H76: 0 | I76: 0 | J76: 0 | K76: 0 | L76: 0 | M76: 0 | N76: 0 | O76: 0 | P76: 0 | Q76: 0 | R76: =SUM(F76:Q76) -> 0
B77: Phòng 5S & an toàn | D77: Số lượng nhân sự | F77: ='Dinh bien_HCNS'!F27 -> 5 | G77: ='Dinh bien_HCNS'!G27 -> 5 | H77: ='Dinh bien_HCNS'!H27 -> 5 | I77: ='Dinh bien_HCNS'!I27 -> 5 | J77: ='Dinh bien_HCNS'!J27 -> 5 | K77: ='Dinh bien_HCNS'!K27 -> 5 | L77: ='Dinh bien_HCNS'!L27 -> 5 | M77: ='Dinh bien_HCNS'!M27 -> 5 | ... Q77: ='Dinh bien_HCNS'!Q27 -> 5 | R77: 5
B78: Phòng 5S & an toàn | D78: ADM_Lương Khối Quản Lý | F78: =SUM(F80:F87) -> 70169394 | G78: =SUM(G80:G87) -> 66415548 | H78: =SUM(H80:H87) -> 66473086 | I78: =SUM(I80:I87) -> 70525548 | J78: =SUM(J80:J87) -> 68991240 | K78: =SUM(K80:K87) -> 70830548 | L78: =SUM(L80:L87) -> 69886394 | M78: =SUM(M80:M87) -> 69886394 | ... Q78: =SUM(Q80:Q87) -> 69581394 | R78: =SUM(F78:Q78) -> 832823882
B79: Phòng 5S & an toàn | D79: Chi phí lương TB/1 Người | F79: =IFERROR(SUM(F80:F87)/F77,0) -> 14033879 | G79: =IFERROR(SUM(G80:G87)/G77,0) -> 13283110 | H79: =IFERROR(SUM(H80:H87)/H77,0) -> 13294617 | I79: =IFERROR(SUM(I80:I87)/I77,0) -> 14105110 | J79: =IFERROR(SUM(J80:J87)/J77,0) -> 13798248 | K79: =IFERROR(SUM(K80:K87)/K77,0) -> 14166110 | L79: =IFERROR(SUM(L80:L87)/L77,0) -> 13977279 | M79: =IFERROR(SUM(M80:M87)/M77,0) -> 13977279 | ... Q79: =IFERROR(SUM(Q80:Q87)/Q77,0) -> 13916279
B80: Phòng 5S & an toàn | C80: 6421002604 | D80: Chi phí lương chính - Gián tiếp | E80: Salary and Wages - Direct | F80: 42176000 | G80: 40158154 | H80: 39491692 | I80: 42958154 | J80: 40833846 | K80: 43238154 | L80: 42456000 | M80: 42456000 | N80: 42678154 | O80: 41113846 | P80: 43518154 | Q80: 42176000 | R80: =SUM(F80:Q80) -> 503254154
B81: Phòng 5S & an toàn | C81: 6421002605 | D81: Chi phí lương T13, phép năm - Gián tiếp | E81: Salary and Wages - Support | F81: 2762601 | G81: 2762601 | H81: 2762601 | I81: 2762601 | J81: 2762601 | K81: 2762601 | L81: 2762601 | M81: 2762601 | N81: 2762601 | O81: 2762601 | P81: 2762601 | Q81: 2762601 | R81: =SUM(F81:Q81) -> 33151212
B82: Phòng 5S & an toàn | C82: 6421002802 | D82: Chi phí khen thưởng - Gián tiếp | E82: Employee Welfare | F82: 4975000 | G82: 4175000 | H82: 4175000 | I82: 4175000 | J82: 5775000 | K82: 4175000 | L82: 4175000 | M82: 4175000 | N82: 4975000 | O82: 4175000 | P82: 4175000 | Q82: 4175000 | R82: =SUM(F82:Q82) -> 53300000
B83: Phòng 5S & an toàn | C83: 6421002806 | D83: Thưởng danh hiệu | E83: Salary and Wages - Support | F83: 3751321 | G83: 3751321 | H83: 3751321 | I83: 3751321 | J83: 3751321 | K83: 3751321 | L83: 3751321 | M83: 3751321 | N83: 3751321 | O83: 3751321 | P83: 3751321 | Q83: 3751321 | R83: =SUM(F83:Q83) -> 45015852
B84: Phòng 5S & an toàn | C84: 6421007202 | D84: Chi phí khen thưởng, bồi dưỡng khác | E84: Employee Welfare | F84: 227212 | G84: 227212 | H84: 227212 | I84: 227212 | J84: 227212 | K84: 227212 | L84: 227212 | M84: 227212 | N84: 227212 | O84: 227212 | P84: 227212 | Q84: 227212 | R84: =SUM(F84:Q84) -> 2726544
B85: Phòng 5S & an toàn | C85: 6421003202 | D85: Tiền ăn giữa ca - Gián tiếp | E85: Employee Welfare | F85: 5950000 | G85: 5014000 | H85: 5738000 | I85: 6324000 | J85: 5314000 | K85: 6349000 | L85: 6187000 | M85: 6187000 | N85: 5875000 | O85: 5975000 | P85: 6374000 | Q85: 6162000 | R85: =SUM(F85:Q85) -> 71449000
B86: Phòng 5S & an toàn | C86: 6421002603 | D86: Phụ cấp ca đêm - Gián tiếp | E86: Salary and Wages - Support | F86: 2126700 | G86: 2126700 | H86: 2126700 | I86: 2126700 | J86: 2126700 | K86: 2126700 | L86: 2126700 | M86: 2126700 | N86: 2126700 | O86: 2126700 | P86: 2126700 | Q86: 2126700 | R86: =SUM(F86:Q86) -> 25520400
B87: Phòng 5S & an toàn | C87: 6421003401 | D87: BHXH, BHYT, KPCĐ, BHTN - Gián tiếp | E87: Employee Welfare | F87: 8200560 | G87: 8200560 | H87: 8200560 | I87: 8200560 | J87: 8200560 | K87: 8200560 | L87: 8200560 | M87: 8200560 | N87: 8200560 | O87: 8200560 | P87: 8200560 | Q87: 8200560 | R87: =SUM(F87:Q87) -> 98406720
B88: Phòng 5S & an toàn | C88: 6421002703 | D88: Chi phí lương ngoài giờ - Gián tiếp | E88: Salary and Wages - Support | F88: 7380923 | G88: 6408185 | H88: 7112677 | I88: 8085415 | J88: 6408185 | K88: 8085415 | L88: 7817169 | M88: 7817169 | N88: 7599045 | O88: 7380923 | P88: 8085415 | Q88: 7817169 | R88: =SUM(F88:Q88) -> 89997690
B89: Phòng Cung ứng | D89: Số lượng nhân sự
B90: Phòng Cung ứng | D90: ADM_Lương Khối Quản Lý | F90: =SUM(F92:F99) -> 0 | G90: =SUM(G92:G99) -> 0 | H90: =SUM(H92:H99) -> 0 | I90: =SUM(I92:I99) -> 0 | J90: =SUM(J92:J99) -> 0 | K90: =SUM(K92:K99) -> 0 | L90: =SUM(L92:L99) -> 0 | M90: =SUM(M92:M99) -> 0 | ... Q90: =SUM(Q92:Q99) -> 0 | R90: =SUM(F90:Q90) -> 0
B91: Phòng Cung ứng | D91: Chi phí lương TB/1 Người | F91: =IFERROR(SUM(F92:F99)/F89,0) -> 0 | G91: =IFERROR(SUM(G92:G99)/G89,0) -> 0 | H91: =IFERROR(SUM(H92:H99)/H89,0) -> 0 | I91: =IFERROR(SUM(I92:I99)/I89,0) -> 0 | J91: =IFERROR(SUM(J92:J99)/J89,0) -> 0 | K91: =IFERROR(SUM(K92:K99)/K89,0) -> 0 | L91: =IFERROR(SUM(L92:L99)/L89,0) -> 0 | M91: =IFERROR(SUM(M92:M99)/M89,0) -> 0 | ... Q91: =IFERROR(SUM(Q92:Q99)/Q89,0) -> 0
B92: Phòng Cung ứng | C92: 6421002604 | D92: Chi phí lương chính - Gián tiếp | E92: Salary and Wages - Direct | F92: 0 | G92: 0 | H92: 0 | I92: 0 | J92: 0 | K92: 0 | L92: 0 | M92: 0 | N92: 0 | O92: 0 | P92: 0 | Q92: 0 | R92: =SUM(F92:Q92) -> 0
B93: Phòng Cung ứng | C93: 6421002605 | D93: Chi phí lương T13, phép năm - Gián tiếp | E93: Salary and Wages - Support | F93: 0 | G93: 0 | H93: 0 | I93: 0 | J93: 0 | K93: 0 | L93: 0 | M93: 0 | N93: 0 | O93: 0 | P93: 0 | Q93: 0 | R93: =SUM(F93:Q93) -> 0
B94: Phòng Cung ứng | C94: 6421002802 | D94: Chi phí khen thưởng - Gián tiếp | E94: Employee Welfare | F94: 0 | G94: 0 | H94: 0 | I94: 0 | J94: 0 | K94: 0 | L94: 0 | M94: 0 | N94: 0 | O94: 0 | P94: 0 | Q94: 0 | R94: =SUM(F94:Q94) -> 0
B95: Phòng Cung ứng | C95: 6421002806 | D95: Thưởng danh hiệu | E95: Salary and Wages - Support | F95: 0 | G95: 0 | H95: 0 | I95: 0 | J95: 0 | K95: 0 | L95: 0 | M95: 0 | N95: 0 | O95: 0 | P95: 0 | Q95: 0 | R95: =SUM(F95:Q95) -> 0
B96: Phòng Cung ứng | C96: 6421007202 | D96: Chi phí khen thưởng, bồi dưỡng khác | E96: Employee Welfare | F96: 0 | G96: 0 | H96: 0 | I96: 0 | J96: 0 | K96: 0 | L96: 0 | M96: 0 | N96: 0 | O96: 0 | P96: 0 | Q96: 0 | R96: =SUM(F96:Q96) -> 0
B97: Phòng Cung ứng | C97: 6421003202 | D97: Tiền ăn giữa ca - Gián tiếp | E97: Employee Welfare | F97: 0 | G97: 0 | H97: 0 | I97: 0 | J97: 0 | K97: 0 | L97: 0 | M97: 0 | N97: 0 | O97: 0 | P97: 0 | Q97: 0 | R97: =SUM(F97:Q97) -> 0
B98: Phòng Cung ứng | C98: 6421002603 | D98: Phụ cấp ca đêm - Gián tiếp | E98: Salary and Wages - Support | F98: 0 | G98: 0 | H98: 0 | I98: 0 | J98: 0 | K98: 0 | L98: 0 | M98: 0 | N98: 0 | O98: 0 | P98: 0 | Q98: 0 | R98: =SUM(F98:Q98) -> 0
B99: Phòng Cung ứng | C99: 6421003401 | D99: BHXH, BHYT, KPCĐ, BHTN - Gián tiếp | E99: Employee Welfare | F99: 0 | G99: 0 | H99: 0 | I99: 0 | J99: 0 | K99: 0 | L99: 0 | M99: 0 | N99: 0 | O99: 0 | P99: 0 | Q99: 0 | R99: =SUM(F99:Q99) -> 0
B100: Phòng Cung ứng | C100: 6421002703 | D100: Chi phí lương ngoài giờ - Gián tiếp | E100: Salary and Wages - Support | F100: 0 | G100: 0 | H100: 0 | I100: 0 | J100: 0 | K100: 0 | L100: 0 | M100: 0 | N100: 0 | O100: 0 | P100: 0 | Q100: 0 | R100: =SUM(F100:Q100) -> 0
B101: Phòng mua XNK | D101: Số lượng nhân sự
B102: Phòng mua XNK | D102: ADM_Lương Khối Quản Lý | F102: =SUM(F104:F111) -> 0 | G102: =SUM(G104:G111) -> 0 | H102: =SUM(H104:H111) -> 0 | I102: =SUM(I104:I111) -> 0 | J102: =SUM(J104:J111) -> 0 | K102: =SUM(K104:K111) -> 0 | L102: =SUM(L104:L111) -> 0 | M102: =SUM(M104:M111) -> 0 | ... Q102: =SUM(Q104:Q111) -> 0 | R102: =SUM(F102:Q102) -> 0
...

Sheet GB
A6: STT | B6: Thành phẩm (chai sau phân loại) | C6: ĐVT | D6: T1 | E6: T2 | F6: T3 | G6: T4 | H6: T5 | I6: T6 | J6: T7 | K6: T8 | L6: T9 | M6: T10 | N6: T11 | O6: T12 | P6: Giả định giá bán KHNS ngày 07/01/2026 | Q6: Giả định giá bán chốt ngày 19/01/26 | R6: Chênh lệch | S6: Ghi chú | T6: T1 | U6: T2 | V6: T3 | W6: T4 | X6: T5 | Y6: T6 | Z6: T7 | AA6: T8 | AB6: T9 | AC6: T10 | AD6: T11 | AE6: T12 | AF6: KQKD 2025 | AG6: Chốt
A7: 1 | B7: Chai PET B1 | C7: Đồng/kg | D7: ='4.Doanh thu'!F26 -> 15000 | E7: ='4.Doanh thu'!G26 -> 15000 | F7: ='4.Doanh thu'!H26 -> 15000 | G7: ='4.Doanh thu'!I26 -> 15000 | H7: ='4.Doanh thu'!J26 -> 15000 | I7: ='4.Doanh thu'!K26 -> 15000 | J7: ='4.Doanh thu'!L26 -> 15000 | K7: ='4.Doanh thu'!M26 -> 15000 | ... O7: ='4.Doanh thu'!Q26 -> 15000 | P7: =AVERAGE(D7:O7) -> 15000 | Q7: 16500 | R7: =Q7-P7 -> 1500 | T7: ='4.Doanh thu'!T26 -> 17866.084 | U7: ='4.Doanh thu'!U26 -> 18501.01 | V7: ='4.Doanh thu'!V26 -> 18423.973 | W7: ='4.Doanh thu'!W26 -> 19181.215 | X7: ='4.Doanh thu'!X26 -> 19067.207 | Y7: ='4.Doanh thu'!Y26 -> 19078.717 | Z7: ='4.Doanh thu'!Z26 -> 0 | AA7: ='4.Doanh thu'!AA26 -> 0 | ... AF7: ='4.Doanh thu'!AF26 -> 18817.739
A8: 2 | B8: Chai PET B1 Không Phân Loại | C8: Đồng/kg | D8: ='4.Doanh thu'!F27 -> 15000 | E8: ='4.Doanh thu'!G27 -> 15000 | F8: ='4.Doanh thu'!H27 -> 15000 | G8: ='4.Doanh thu'!I27 -> 15000 | H8: ='4.Doanh thu'!J27 -> 15000 | I8: ='4.Doanh thu'!K27 -> 15000 | J8: ='4.Doanh thu'!L27 -> 15000 | K8: ='4.Doanh thu'!M27 -> 15000 | ... O8: ='4.Doanh thu'!Q27 -> 15000 | P8: =AVERAGE(D8:O8) -> 15000 | Q8: 16500 | R8: =Q8-P8 -> 1500 | T8: ='4.Doanh thu'!T27 -> 0 | U8: ='4.Doanh thu'!U27 -> 0 | V8: ='4.Doanh thu'!V27 -> 0 | W8: ='4.Doanh thu'!W27 -> 0 | X8: ='4.Doanh thu'!X27 -> 0 | Y8: ='4.Doanh thu'!Y27 -> 19180.665 | Z8: ='4.Doanh thu'!Z27 -> 19335.797 | AA8: ='4.Doanh thu'!AA27 -> 19225.39 | ... AF8: ='4.Doanh thu'!AF27 -> 17305.86
A9: 3 | B9: Chai PET B2.2 | C9: Đồng/kg | D9: ='4.Doanh thu'!F30 -> 13500 | E9: ='4.Doanh thu'!G30 -> 13500 | F9: ='4.Doanh thu'!H30 -> 13500 | G9: ='4.Doanh thu'!I30 -> 13500 | H9: ='4.Doanh thu'!J30 -> 13500 | I9: ='4.Doanh thu'!K30 -> 13500 | J9: ='4.Doanh thu'!L30 -> 13500 | K9: ='4.Doanh thu'!M30 -> 13500 | ... O9: ='4.Doanh thu'!Q30 -> 13500 | P9: =AVERAGE(D9:O9) -> 13500 | Q9: 15000 | R9: =Q9-P9 -> 1500 | T9: ='4.Doanh thu'!T30 -> 15739.156 | U9: ='4.Doanh thu'!U30 -> 17522 | V9: ='4.Doanh thu'!V30 -> 17637.022 | W9: ='4.Doanh thu'!W30 -> 18745.521 | X9: ='4.Doanh thu'!X30 -> 18633.722 | Y9: ='4.Doanh thu'!Y30 -> 18892.799 | Z9: ='4.Doanh thu'!Z30 -> 5861.324 | AA9: ='4.Doanh thu'!AA30 -> 0 | ... AF9: ='4.Doanh thu'!AF30 -> 14569.13
A10: 4 | B10: Chai PET B4 | C10: Đồng/kg | D10: ='4.Doanh thu'!F32 -> 12000 | E10: ='4.Doanh thu'!G32 -> 12000 | F10: ='4.Doanh thu'!H32 -> 12000 | G10: ='4.Doanh thu'!I32 -> 12000 | H10: ='4.Doanh thu'!J32 -> 12000 | I10: ='4.Doanh thu'!K32 -> 12000 | J10: ='4.Doanh thu'!L32 -> 12000 | K10: ='4.Doanh thu'!M32 -> 12000 | ... O10: ='4.Doanh thu'!Q32 -> 12000 | P10: =AVERAGE(D10:O10) -> 12000 | Q10: 13500 | R10: =Q10-P10 -> 1500 | T10: ='4.Doanh thu'!T32 -> 14300 | U10: ='4.Doanh thu'!U32 -> 17522 | V10: ='4.Doanh thu'!V32 -> 17637.432 | W10: ='4.Doanh thu'!W32 -> 18713.885 | X10: ='4.Doanh thu'!X32 -> 18576.481 | Y10: ='4.Doanh thu'!Y32 -> 18944.708 | Z10: ='4.Doanh thu'!Z32 -> 19310.69 | AA10: ='4.Doanh thu'!AA32 -> 19323.388 | ... AF10: ='4.Doanh thu'!AF32 -> 16195.848
A11: 5 | B11: Chai PET B5 | C11: Đồng/kg | D11: ='4.Doanh thu'!F33 -> 12000 | E11: ='4.Doanh thu'!G33 -> 12000 | F11: ='4.Doanh thu'!H33 -> 12000 | G11: ='4.Doanh thu'!I33 -> 12000 | H11: ='4.Doanh thu'!J33 -> 12000 | I11: ='4.Doanh thu'!K33 -> 12000 | J11: ='4.Doanh thu'!L33 -> 12000 | K11: ='4.Doanh thu'!M33 -> 12000 | ... O11: ='4.Doanh thu'!Q33 -> 12000 | P11: =AVERAGE(D11:O11) -> 12000 | Q11: 13500 | R11: =Q11-P11 -> 1500 | T11: ='4.Doanh thu'!T33 -> 15616.628 | U11: ='4.Doanh thu'!U33 -> 17522 | V11: ='4.Doanh thu'!V33 -> 17649.541 | W11: ='4.Doanh thu'!W33 -> 18455.821 | X11: ='4.Doanh thu'!X33 -> 18603.148 | Y11: ='4.Doanh thu'!Y33 -> 18874.172 | Z11: ='4.Doanh thu'!Z33 -> 19288.23 | AA11: ='4.Doanh thu'!AA33 -> 18665.068 | ... AF11: ='4.Doanh thu'!AF33 -> 16235.851
A12: 6 | B12: Chai PET B7.2 | C12: Đồng/kg | D12: ='4.Doanh thu'!F37 -> 12000 | E12: ='4.Doanh thu'!G37 -> 12000 | F12: ='4.Doanh thu'!H37 -> 12000 | G12: ='4.Doanh thu'!I37 -> 12000 | H12: ='4.Doanh thu'!J37 -> 12000 | I12: ='4.Doanh thu'!K37 -> 12000 | J12: ='4.Doanh thu'!L37 -> 12000 | K12: ='4.Doanh thu'!M37 -> 12000 | ... O12: ='4.Doanh thu'!Q37 -> 12000 | P12: =AVERAGE(D12:O12) -> 12000 | Q12: 13500 | R12: =Q12-P12 -> 1500 | T12: ='4.Doanh thu'!T37 -> 0 | U12: ='4.Doanh thu'!U37 -> 0 | V12: ='4.Doanh thu'!V37 -> 0 | W12: ='4.Doanh thu'!W37 -> 8000 | X12: ='4.Doanh thu'!X37 -> 0 | Y12: ='4.Doanh thu'!Y37 -> 0 | Z12: ='4.Doanh thu'!Z37 -> 477.63578 | AA12: ='4.Doanh thu'!AA37 -> 0 | ... AF12: ='4.Doanh thu'!AF37 -> 729.17575
A13: 7 | B13: Cổ Chai PET | C13: Đồng/kg | D13: ='4.Doanh thu'!F38 -> 8100 | E13: ='4.Doanh thu'!G38 -> 8100 | F13: ='4.Doanh thu'!H38 -> 8100 | G13: ='4.Doanh thu'!I38 -> 8100 | H13: ='4.Doanh thu'!J38 -> 8100 | I13: ='4.Doanh thu'!K38 -> 8100 | J13: ='4.Doanh thu'!L38 -> 8100 | K13: ='4.Doanh thu'!M38 -> 8100 | ... O13: ='4.Doanh thu'!Q38 -> 8100 | P13: =AVERAGE(D13:O13) -> 8100 | Q13: 8500 | R13: =Q13-P13 -> 400 | T13: ='4.Doanh thu'!T38 -> 0 | U13: ='4.Doanh thu'!U38 -> 0 | V13: ='4.Doanh thu'!V38 -> 0 | W13: ='4.Doanh thu'!W38 -> 0 | X13: ='4.Doanh thu'!X38 -> 10000 | Y13: ='4.Doanh thu'!Y38 -> 0 | Z13: ='4.Doanh thu'!Z38 -> 0 | AA13: ='4.Doanh thu'!AA38 -> 0 | ... AF13: ='4.Doanh thu'!AF38 -> 12052.033
A14: 8 | B14: Nắp HD ép các màu | C14: Đồng/kg | D14: ='4.Doanh thu'!F39 -> 8100 | E14: ='4.Doanh thu'!G39 -> 8100 | F14: ='4.Doanh thu'!H39 -> 8100 | G14: ='4.Doanh thu'!I39 -> 8100 | H14: ='4.Doanh thu'!J39 -> 8100 | I14: ='4.Doanh thu'!K39 -> 8100 | J14: ='4.Doanh thu'!L39 -> 8100 | K14: ='4.Doanh thu'!M39 -> 8100 | ... O14: ='4.Doanh thu'!Q39 -> 8100 | P14: =AVERAGE(D14:O14) -> 8100 | Q14: 8500 | R14: =Q14-P14 -> 400 | T14: ='4.Doanh thu'!T39 -> 0 | U14: ='4.Doanh thu'!U39 -> 0 | V14: ='4.Doanh thu'!V39 -> 10000 | W14: ='4.Doanh thu'!W39 -> 10000 | X14: ='4.Doanh thu'!X39 -> 10000 | Y14: ='4.Doanh thu'!Y39 -> 10000 | Z14: ='4.Doanh thu'!Z39 -> 10000 | AA14: ='4.Doanh thu'!AA39 -> 10000 | ... AF14: ='4.Doanh thu'!AF39 -> 9413.3871
A15: 9 | B15: Vảy PET B1 | C15: Đồng/kg | D15: ='4.Doanh thu'!F103 -> 16500 | E15: ='4.Doanh thu'!G103 -> 16500 | F15: ='4.Doanh thu'!H103 -> 16500 | G15: ='4.Doanh thu'!I103 -> 16500 | H15: ='4.Doanh thu'!J103 -> 16500 | I15: ='4.Doanh thu'!K103 -> 16500 | J15: ='4.Doanh thu'!L103 -> 16500 | K15: ='4.Doanh thu'!M103 -> 16500 | ... O15: ='4.Doanh thu'!Q103 -> 16500 | P15: =AVERAGE(D15:O15) -> 16500 | Q15: 19000 | R15: =Q15-P15 -> 2500 | T15: ='4.Doanh thu'!T103 -> 0 | U15: ='4.Doanh thu'!U103 -> 0 | V15: ='4.Doanh thu'!V103 -> 0 | W15: ='4.Doanh thu'!W103 -> 20000 | X15: ='4.Doanh thu'!X103 -> 0 | Y15: ='4.Doanh thu'!Y103 -> 0 | Z15: ='4.Doanh thu'!Z103 -> 0 | AA15: ='4.Doanh thu'!AA103 -> 0 | ... AF15: ='4.Doanh thu'!AF103 -> 0 | AG15: =Q15 -> 19000
A16: 10 | B16: Vảy PET B6.2 | C16: Đồng/kg | D16: ='4.Doanh thu'!F112 -> 15500 | E16: ='4.Doanh thu'!G112 -> 15500 | F16: ='4.Doanh thu'!H112 -> 15500 | G16: ='4.Doanh thu'!I112 -> 15500 | H16: ='4.Doanh thu'!J112 -> 15500 | I16: ='4.Doanh thu'!K112 -> 15500 | J16: ='4.Doanh thu'!L112 -> 15500 | K16: ='4.Doanh thu'!M112 -> 15500 | ... O16: ='4.Doanh thu'!Q112 -> 15500 | P16: =AVERAGE(D16:O16) -> 15500 | Q16: 18000 | R16: =Q16-P16 -> 2500 | S16: 2025: A Thạch duyệt giá B6 cho Đại Lộc: B0 + 6.500đ/kg | T16: ='4.Doanh thu'!T112 -> 18250 | U16: ='4.Doanh thu'!U112 -> 0 | V16: ='4.Doanh thu'!V112 -> 19674.73 | W16: ='4.Doanh thu'!W112 -> 19878.838 | X16: ='4.Doanh thu'!X112 -> 19162.807 | Y16: ='4.Doanh thu'!Y112 -> 19780.092 | Z16: ='4.Doanh thu'!Z112 -> 20231.894 | AA16: ='4.Doanh thu'!AA112 -> 20330 | ... AF16: ='4.Doanh thu'!AF112 -> 18660.776 | AG16: 18000
A17: 11 | B17: Vảy Nắp HD ép các màu | C17: Đồng/kg | D17: ='4.Doanh thu'!F116 -> 10000 | E17: ='4.Doanh thu'!G116 -> 10000 | F17: ='4.Doanh thu'!H116 -> 10000 | G17: ='4.Doanh thu'!I116 -> 10000 | H17: ='4.Doanh thu'!J116 -> 10000 | I17: ='4.Doanh thu'!K116 -> 10000 | J17: ='4.Doanh thu'!L116 -> 10000 | K17: ='4.Doanh thu'!M116 -> 10000 | ... O17: ='4.Doanh thu'!Q116 -> 10000 | P17: =AVERAGE(D17:O17) -> 10000 | Q17: 11000 | R17: =Q17-P17 -> 1000 | S17: Giá bán 2025: 11.250đ/kg | T17: ='4.Doanh thu'!T116 -> 18249.803 | U17: ='4.Doanh thu'!U116 -> 18250 | V17: ='4.Doanh thu'!V116 -> 18250 | W17: ='4.Doanh thu'!W116 -> 18426.757 | X17: ='4.Doanh thu'!X116 -> 19816.964 | Y17: ='4.Doanh thu'!Y116 -> 19506.115 | Z17: ='4.Doanh thu'!Z116 -> 20244.772 | AA17: ='4.Doanh thu'!AA116 -> 20330 | ... AF17: ='4.Doanh thu'!AF116 -> 18742.585 | AG17: =Q17 -> 11000

Sheet KQKD PET
H2: 0.153846 | I2: 0.076923 | J2: 0.961538 | K2: 0.153846 | L2: 0.961538 | O2: 0.038462 | P2: 0.038462 | Q2: 0.961538
B3: MỤC TIÊU KẾT QUẢ KINH DOANH NĂM 2026 | S3: ĐVT: Triệu đồng
B4: STT | C4: Mục phí | D4: Thực tế năm 2023 | E4: Thực tế năm 2024 | F4: KQKD 2025 | G4: T1 | H4: T2 | I4: T3 | J4: T4 | K4: T5 | L4: T6 | M4: T7 | N4: T8 | O4: T9 | P4: T10 | Q4: T11 | R4: T12 | S4: KH 2026 | U4: KQKD 2025 | V4: KH 2026 | X4: KQKD 2025 | Y4: KH 2026
B5: 1 | C5: SẢN LƯỢNG BÁN (TẤN) | D5: =D6+D7+D8 -> 0 | E5: =E6+E7+E8 -> 0 | F5: =F6+F7+F8 -> 9499913 | G5: =G6+G7+G8 -> 769275 | H5: =H6+H7+H8 -> 598325 | I5: =I6+I7+I8 -> 854750 | J5: =J6+J7+J8 -> 940225 | K5: =K6+K7+K8 -> 939070 | ... R5: =R6+R7+R8 -> 352165 | S5: =SUM(G5:R5) -> 6566800
B6: 1.1 | C6: Chai PET | F6: ='4.Doanh thu'!AF22 -> 8083894 | G6: ='4.Doanh thu'!F22 -> 534375 | H6: ='4.Doanh thu'!G22 -> 415625 | I6: ='4.Doanh thu'!H22 -> 593750 | J6: ='4.Doanh thu'!I22 -> 653125 | K6: ='4.Doanh thu'!J22 -> 651475 | L6: ='4.Doanh thu'!K22 -> 64075 | M6: ='4.Doanh thu'!L22 -> 64075 | N6: ='4.Doanh thu'!M22 -> 64075 | ... R6: ='4.Doanh thu'!Q22 -> 64075 | S6: =SUM(G6:R6) -> 3296875
B7: 1.2 | C7: Vảy PET | F7: ='4.Doanh thu'!AF80 -> 1416019 | G7: ='4.Doanh thu'!F80 -> 234900 | H7: ='4.Doanh thu'!G80 -> 182700 | I7: ='4.Doanh thu'!H80 -> 261000 | J7: ='4.Doanh thu'!I80 -> 287100 | K7: ='4.Doanh thu'!J80 -> 287595 | L7: ='4.Doanh thu'!K80 -> 288090 | M7: ='4.Doanh thu'!L80 -> 288090 | N7: ='4.Doanh thu'!M80 -> 288090 | ... R7: ='4.Doanh thu'!Q80 -> 288090 | S7: =SUM(G7:R7) -> 3269925
B8: 1.3 | C8: Vảy HD | S8: =SUM(G8:R8) -> 0
B9: 2 | C9: DOANH THU | D9: =D10+D11+D12+D13 -> 0 | E9: =E10+E11+E12+E13 -> 64684339330 | F9: =F10+F11+F12+F13 -> 169375622091 | G9: =G10+G11+G12+G13 -> 11415442500 | H9: =H10+H11+H12+H13 -> 8878677500 | I9: =I10+I11+I12+I13 -> 12683825000 | J9: =J10+J11+J12+J13 -> 13952207500 | K9: =K10+K11+K12+K13 -> 13934978750 | ... R9: =R10+R11+R12+R13 -> 5131500000 | S9: =SUM(G9:R9) -> 96785631250 | U9: =F9/F$9 -> 1 | V9: =S9/S$9 -> 1 | X9: =F9/F5 -> 17829.176 | Y9: =S9/S5 -> 14738.629 | Z9: =Y9-X9 -> -3090.5468
B10: 2.1 | C10: Chai PET | E10: =64684339330 -> 64684339330 | F10: ='4.Doanh thu'!AF60 -> 142921750387 | G10: ='4.Doanh thu'!F60 -> 7846267500 | H10: ='4.Doanh thu'!G60 -> 6102652500 | I10: ='4.Doanh thu'!H60 -> 8718075000 | J10: ='4.Doanh thu'!I60 -> 9589882500 | K10: ='4.Doanh thu'!J60 -> 9565132500 | L10: ='4.Doanh thu'!K60 -> 754132500 | M10: ='4.Doanh thu'!L60 -> 754132500 | N10: ='4.Doanh thu'!M60 -> 754132500 | ... R10: ='4.Doanh thu'!Q60 -> 754132500 | S10: =SUM(G10:R10) -> 47100937500 | U10: =F10/F$9 -> 0.84381535 | V10: =S10/S$9 -> 0.48665217
B11: 2.2 | C11: Vảy PET | F11: ='4.Doanh thu'!AF138 -> 26453871704 | G11: ='4.Doanh thu'!F138 -> 3569175000 | H11: ='4.Doanh thu'!G138 -> 2776025000 | I11: ='4.Doanh thu'!H138 -> 3965750000 | J11: ='4.Doanh thu'!I138 -> 4362325000 | K11: ='4.Doanh thu'!J138 -> 4.3698462e+09 | L11: ='4.Doanh thu'!K138 -> 4377367500 | M11: ='4.Doanh thu'!L138 -> 4377367500 | N11: ='4.Doanh thu'!M138 -> 4377367500 | ... R11: ='4.Doanh thu'!Q138 -> 4377367500 | S11: =SUM(G11:R11) -> 49684693750 | U11: =F11/F$9 -> 0.15618465 | V11: =S11/S$9 -> 0.51334783
B12: 2.3 | C12: Vảy HD | S12: =SUM(G12:R12) -> 0 | U12: =F12/F$9 -> 0 | V12: =S12/S$9 -> 0
B13: 2.4 | C13: Khác | S13: =SUM(G13:R13) -> 0 | U13: =F13/F$9 -> 0 | V13: =S13/S$9 -> 0
B14: 3 | C14: BIẾN PHÍ | D14: =D15+D23 -> 0 | E14: =E15+E23 -> 0 | F14: =F15+F23 -> 1.5172881e+11 | G14: =G15+G23 -> 1.0502036e+10 | H14: =H15+H23 -> 8.1594327e+09 | I14: =I15+I23 -> 1.1570876e+10 | J14: =J15+J23 -> 1.2668823e+10 | K14: =K15+K23 -> 1.2667987e+10 | ... R14: =R15+R23 -> 6.5617902e+09 | S14: =SUM(G14:R14) -> 1.0150769e+11 | U14: =F14/F$9 -> 0.89581257 | V14: =S14/S$9 -> 1.0487888
B15: 3.1 | C15: BIẾN PHÍ SẢN XUẤT | D15: =D16+D20+D21+D22 -> 0 | E15: =E16+E20+E21+E22 -> 0 | F15: =F16+F20+F21+F22 -> 1.4856936e+11 | G15: =G16+G20+G21+G22 -> 1.0236868e+10 | H15: =H16+H20+H21+H22 -> 7.9531909e+09 | I15: =I16+I20+I21+I22 -> 1.1276245e+10 | J15: =J16+J20+J21+J22 -> 1.2344729e+10 | K15: =K16+K20+K21+K22 -> 1.2344321e+10 | ... R15: =R16+R20+R21+R22 -> 6.4468191e+09 | S15: =SUM(G15:R15) -> 9.928909e+10 | U15: =F15/F$9 -> 0.87715903 | V15: =S15/S$9 -> 1.025866
B16: 3.1.1 | C16: Nguyên vật liệu chính (nhựa, gồm hao hụt) | F16: =140444033651-85391049-2000000000 -> 138358642602 | G16: ='1.NVL Chai'!H42-'KQKD HD'!G16 -> 9121500000 | H16: ='1.NVL Chai'!I42-'KQKD HD'!H16 -> 7094500000 | I16: ='1.NVL Chai'!J42-'KQKD HD'!I16 -> 10135000000 | J16: ='1.NVL Chai'!K42-'KQKD HD'!J16 -> 11148500000 | K16: ='1.NVL Chai'!L42-'KQKD HD'!K16 -> 11148500000 | L16: ='1.NVL Chai'!M42-'KQKD HD'!L16 -> 5211923750 | M16: ='1.NVL Chai'!N42-'KQKD HD'!M16 -> 5211923750 | N16: ='1.NVL Chai'!O42-'KQKD HD'!N16 -> 5211923750 | ... R16: ='1.NVL Chai'!S42-'KQKD HD'!R16 -> 5211923750 | S16: =SUM(G16:R16) -> 85131466250 | U16: =F16/F$9 -> 0.81687459 | V16: =S16/S$9 -> 0.87958786
B17: 3.1.2 | C17: Trong đó: i/ Hao hụt CĐ phân loại chai | G17: =SUM('3.Thanh pham'!F$211:F$213)*'1.NVL Chai'!H$34 -> 1060374375 | H17: =SUM('3.Thanh pham'!G$211:G$213)*'1.NVL Chai'!I$34 -> 824735625 | I17: =SUM('3.Thanh pham'!H$211:H$213)*'1.NVL Chai'!J$34 -> 1178193750 | J17: =SUM('3.Thanh pham'!I$211:I$213)*'1.NVL Chai'!K$34 -> 1296013125 | K17: =SUM('3.Thanh pham'!J$211:J$213)*'1.NVL Chai'!L$34 -> 1.3071616e+09 | L17: =SUM('3.Thanh pham'!K$211:K$213)*'1.NVL Chai'!M$34 -> 1318310125 | M17: =SUM('3.Thanh pham'!L$211:L$213)*'1.NVL Chai'!N$34 -> 1318310125 | N17: =SUM('3.Thanh pham'!M$211:M$213)*'1.NVL Chai'!O$34 -> 1318310125 | ... R17: =SUM('3.Thanh pham'!Q$211:Q$213)*'1.NVL Chai'!S$34 -> 1318310125 | S17: =SUM(G17:R17) -> 14894649375 | U17: =F17/F$9 -> 0 | V17: =S17/S$9 -> 0.15389319
C18: ii/ Hao hụt CĐ băm vảy | G18: =('3.Thanh pham'!F$214*'1.NVL Chai'!H$34) -> 264523500 | H18: =('3.Thanh pham'!G$214*'1.NVL Chai'!I$34) -> 205740500 | I18: =('3.Thanh pham'!H$214*'1.NVL Chai'!J$34) -> 293915000 | J18: =('3.Thanh pham'!I$214*'1.NVL Chai'!K$34) -> 323306500 | K18: =('3.Thanh pham'!J$214*'1.NVL Chai'!L$34) -> 3.2386392e+08 | L18: =('3.Thanh pham'!K$214*'1.NVL Chai'!M$34) -> 680615925 | M18: =('3.Thanh pham'!L$214*'1.NVL Chai'!N$34) -> 680615925 | N18: =('3.Thanh pham'!M$214*'1.NVL Chai'!O$34) -> 680615925 | ... R18: =('3.Thanh pham'!Q$214*'1.NVL Chai'!S$34) -> 680615925 | S18: =SUM(G18:R18) -> 6175660900 | U18: =F18/F$9 -> 0 | V18: =S18/S$9 -> 0.063807621
B19: 3.1.3 | C19: % chi phí nguyên liệu/doanh thu | D19: =IFERROR(D16/$F$9,0) -> 0 | E19: =IFERROR(E16/$F$9,0) -> 0 | F19: =IFERROR(F16/$F$9,0) -> 0.81687459 | G19: =G16/G9 -> 0.79904918 | H19: =H16/H9 -> 0.79904918 | I19: =I16/I9 -> 0.79904918 | J19: =J16/J9 -> 0.79904918 | K19: =K16/K9 -> 0.8000371 | L19: =L16/L9 -> 1.0156726 | M19: =M16/M9 -> 1.0156726 | N19: =N16/N9 -> 1.0156726 | ... S19: =S16/S9 -> 0.87958786 | U19: =F19/F$9 -> 4.8228581e-12 | V19: =S19/S$9 -> 9.0880004e-12
B20: 3.1.4 | C20: Nguyên vật liệu phụ | F20: =SUM(CPSX!AK19:AK25) -> 2.2270037e+09 | G20: =SUM(CPSX!K19:K25) -> 3.3872006e+08 | H20: =SUM(CPSX!L19:L25) -> 2.6276782e+08 | I20: =SUM(CPSX!M19:M25) -> 3.7221767e+08 | J20: =SUM(CPSX!N19:N25) -> 4.1027929e+08 | K20: =SUM(CPSX!O19:O25) -> 4.0901892e+08 | L20: =SUM(CPSX!P19:P25) -> 3.7647524e+08 | M20: =SUM(CPSX!Q19:Q25) -> 3.7585191e+08 | N20: =SUM(CPSX!R19:R25) -> 3.7596691e+08 | ... R20: =SUM(CPSX!V19:V25) -> 3.7581691e+08 | S20: =SUM(G20:R20) -> 4.4257605e+09 | U20: =F20/F$9 -> 0.013148313 | V20: =S20/S$9 -> 0.045727454
B21: 3.1.5 | C21: Điện sản xuất | F21: =CPSX!$AK$18 -> 1.3082783e+09 | G21: =CPSX!K$18 -> 1.1475174e+08 | H21: =CPSX!L$18 -> 89251352 | I21: =CPSX!M$18 -> 1.2750193e+08 | J21: =CPSX!N$18 -> 140252125 | K21: =CPSX!O$18 -> 1.4029475e+08 | L21: =CPSX!P$18 -> 1.4033737e+08 | M21: =CPSX!Q$18 -> 1.4033737e+08 | N21: =CPSX!R$18 -> 1.4033737e+08 | ... R21: =CPSX!V$18 -> 1.4033737e+08 | S21: =SUM(G21:R21) -> 1.5944135e+09 | U21: =F21/F$9 -> 0.007724124 | V21: =S21/S$9 -> 0.016473659
B22: 3.1.6 | C22: Nhân công trực tiếp | F22: =SUM(CPSX!AK6:AK16) -> 6675431826 | G22: =SUM(CPSX!K6:K16) -> 6.618961e+08 | H22: =SUM(CPSX!L6:L16) -> 5.0667176e+08 | I22: =SUM(CPSX!M6:M16) -> 6.415256e+08 | J22: =SUM(CPSX!N6:N16) -> 6.4569773e+08 | K22: =SUM(CPSX!O6:O16) -> 6.4650688e+08 | L22: =SUM(CPSX!P6:P16) -> 7.1661761e+08 | M22: =SUM(CPSX!Q6:Q16) -> 730711118 | N22: =SUM(CPSX!R6:R16) -> 730711118 | ... R22: =SUM(CPSX!V6:V16) -> 718741118 | S22: =SUM(G22:R22) -> 8.1374503e+09 | U22: =F22/F$9 -> 0.039411999 | V22: =S22/S$9 -> 0.084077049
B23: 3.2 | C23: BIẾN PHÍ BÁN HÀNG | D23: =D24 -> 0 | E23: =E24 -> 0 | F23: =F24 -> 3.1594552e+09 | G23: =G24 -> 265168000 | H23: =H24 -> 2.0624178e+08 | I23: =I24 -> 2.9463111e+08 | J23: =J24 -> 3.2409422e+08 | K23: =K24 -> 3.2366596e+08 | ... R23: =R24 -> 1.1497102e+08 | S23: =SUM(G23:R23) -> 2.2185982e+09 | U23: =F23/F$9 -> 0.018653542 | V23: =S23/S$9 -> 0.022922806
C24: Chi phí vận chuyển | F24: =CPBH!AK8 -> 3.1594552e+09 | G24: =SUM(CPBH!K5:K6) -> 265168000 | H24: =SUM(CPBH!L5:L6) -> 2.0624178e+08 | I24: =SUM(CPBH!M5:M6) -> 2.9463111e+08 | J24: =SUM(CPBH!N5:N6) -> 3.2409422e+08 | K24: =SUM(CPBH!O5:O6) -> 3.2366596e+08 | L24: =SUM(CPBH!P5:P6) -> 1.1497102e+08 | M24: =SUM(CPBH!Q5:Q6) -> 1.1497102e+08 | N24: =SUM(CPBH!R5:R6) -> 1.1497102e+08 | ... R24: =SUM(CPBH!V5:V6) -> 1.1497102e+08 | S24: =SUM(G24:R24) -> 2.2185982e+09 | U24: =F24/F$9 -> 0.018653542 | V24: =S24/S$9 -> 0.022922806
B25: 4 | C25: LÃI SAU BIẾN PHÍ | D25: =D9-D14 -> 0 | E25: =E9-E14 -> 64684339330 | F25: =F9-F14 -> 1.764681e+10 | G25: =G9-G14 -> 9.1340661e+08 | H25: =H9-H14 -> 7.1924479e+08 | I25: =I9-I14 -> 1.1129487e+09 | J25: =J9-J14 -> 1.2833841e+09 | K25: =K9-K14 -> 1.2669922e+09 | ... R25: =R9-R14 -> -1.4302902e+09 | S25: =SUM(G25:R25) -> -4.7220574e+09 | U25: =F25/F$9 -> 0.10418743 | V25: =S25/S$9 -> -0.048788827
B26: 4.1 | C26: % lãi biến phí/doanh thu | D26: =IFERROR(D23/$F$9,0) -> 0 | E26: =IFERROR(E23/$F$9,0) -> 0 | F26: =IFERROR(F23/$F$9,0) -> 0.018653542 | G26: =G25/G9 -> 0.080014998 | H26: =H25/H9 -> 0.081008099 | I26: =I25/I9 -> 0.08774551 | J26: =J25/J9 -> 0.091984307 | K26: =K25/K9 -> 0.090921721 | L26: =L25/L9 -> -0.27844197 | M26: =M25/M9 -> -0.28106697 | N26: =N25/N9 -> -0.28108938 | ... S26: =S25/S9 -> -0.048788827 | U26: =F26/F$9 -> 1.1013121e-13 | V26: =S26/S$9 -> -5.0409163e-13
B27: 5 | C27: CHI PHÍ SẢN XUẤT CHUNG | D27: =D28+D29+D30 -> 0 | E27: =E28+E29+E30 -> 0 | F27: =F28+F29+F30 -> 11353832700 | G27: =G28+G29+G30 -> 7.5427228e+08 | H27: =H28+H29+H30 -> 7.5157228e+08 | I27: =I28+I29+I30 -> 7.5344147e+08 | J27: =J28+J29+J30 -> 7.5305814e+08 | K27: =K28+K29+K30 -> 7.5222481e+08 | ... R27: =R28+R29+R30 -> 7.436137e+08 | S27: =SUM(G27:R27) -> 8.9880329e+09 | U27: =F27/F$9 -> 0.067033452 | V27: =S27/S$9 -> 0.092865364
B28: 5.1 | C28: Lương gián tiếp Sản xuất | F28: =SUM(CPSX!AK72:AK82) -> 4201558148 | G28: =SUM(CPSX!K$72:K$82) -> 2.9555265e+08 | H28: =SUM(CPSX!L$72:L$82) -> 2.93242e+08 | I28: =SUM(CPSX!M$72:M$82) -> 2.7839308e+08 | J28: =SUM(CPSX!N$72:N$82) -> 3.0256017e+08 | K28: =SUM(CPSX!O$72:O$82) -> 2.8727549e+08 | L28: =SUM(CPSX!P$72:P$82) -> 3.0256017e+08 | M28: =SUM(CPSX!Q$72:Q$82) -> 2.9531527e+08 | N28: =SUM(CPSX!R$72:R$82) -> 2.9531527e+08 | ... R28: =SUM(CPSX!V$72:V$82) -> 2.9531527e+08 | S28: =SUM(G28:R28) -> 3.5377006e+09 | U28: =F28/F$9 -> 0.024806156 | V28: =S28/S$9 -> 0.036551919
B29: 5.2 | C29: Chi phí thuê xưởng | F29: =CPSX!AK88 -> 2815076112 | G29: =CPSX!K$88 -> 230839676 | H29: =CPSX!L$88 -> 230839676 | I29: =CPSX!M$88 -> 230839676 | J29: =CPSX!N$88 -> 230839676 | K29: =CPSX!O$88 -> 230839676 | L29: =CPSX!P$88 -> 230839676 | M29: =CPSX!Q$88 -> 230839676 | N29: =CPSX!R$88 -> 230839676 | ... R29: =CPSX!V$88 -> 230839676 | S29: =SUM(G29:R29) -> 2770076112 | U29: =F29/F$9 -> 0.016620315 | V29: =S29/S$9 -> 0.028620737
B30: 5.3 | C30: Chi phí sản xuất (Ngoài lương, BOM, thuê xưởng, khấu hao) | F30: =SUM(CPSX!AK16:AK17,CPSX!$AK$71)-'KQKD PET'!F28-'KQKD PET'!F29-'KQKD PET'!F31 -> 4337198440 | G30: =SUM(CPSX!K16:K17,CPSX!$K$71)-'KQKD PET'!G28-'KQKD PET'!G29-'KQKD PET'!G31 -> 2.2787996e+08 | H30: =SUM(CPSX!L16:L17,CPSX!$K$71)-'KQKD PET'!H28-'KQKD PET'!H29-'KQKD PET'!H31 -> 2.2749061e+08 | I30: =SUM(CPSX!M16:M17,CPSX!$K$71)-'KQKD PET'!I28-'KQKD PET'!I29-'KQKD PET'!I31 -> 2.4420872e+08 | J30: =SUM(CPSX!N16:N17,CPSX!$K$71)-'KQKD PET'!J28-'KQKD PET'!J29-'KQKD PET'!J31 -> 2.196583e+08 | K30: =SUM(CPSX!O16:O17,CPSX!$K$71)-'KQKD PET'!K28-'KQKD PET'!K29-'KQKD PET'!K31 -> 2.3410964e+08 | L30: =SUM(CPSX!P16:P17,CPSX!$K$71)-'KQKD PET'!L28-'KQKD PET'!L29-'KQKD PET'!L31 -> 2.1563746e+08 | M30: =SUM(CPSX!Q16:Q17,CPSX!$K$71)-'KQKD PET'!M28-'KQKD PET'!M29-'KQKD PET'!M31 -> 2.218532e+08 | N30: =SUM(CPSX!R16:R17,CPSX!$K$71)-'KQKD PET'!N28-'KQKD PET'!N29-'KQKD PET'!N31 -> 2.217032e+08 | ... R30: =SUM(CPSX!V16:V17,CPSX!$K$71)-'KQKD PET'!R28-'KQKD PET'!R29-'KQKD PET'!R31 -> 2.1745875e+08 | S30: =SUM(G30:R30) -> 2.6802562e+09 | U30: =F30/F$9 -> 0.025606982 | V30: =S30/S$9 -> 0.027692708
B31: 6 | C31: CHI PHÍ KHẤU HAO, CCDC | F31: =CPSX!AK99 -> 3687386689 | G31: =CPSX!K$99 -> 1.4644116e+08 | H31: =CPSX!L$99+CPSX!L$97 -> 1.4894116e+08 | I31: =CPSX!M$99+CPSX!M$97 -> 1.4707197e+08 | J31: =CPSX!N$99+CPSX!N$97 -> 1.4707197e+08 | K31: =CPSX!O$99+CPSX!O$97 -> 1.479053e+08 | L31: =CPSX!P$99+CPSX!P$97 -> 1.510928e+08 | M31: =CPSX!Q$99+CPSX!Q$97 -> 1.5192614e+08 | N31: =CPSX!R$99+CPSX!R$97 -> 1.5192614e+08 | O31: =CPSX!S$99+CPSX!S$97 -> 1.5373169e+08 | ... R31: =CPSX!V$99+CPSX!V$97 -> 1.5595391e+08 | S31: =SUM(G31:R31) -> 1.8123034e+09 | U31: =F31/F$9 -> 0.021770469 | V31: =S31/S$9 -> 0.018724922
B32: 7 | C32: LỢI NHUẬN GỘP | D32: =D25-D27-D31 -> 0 | E32: =E25-E27-E31 -> 64684339330 | F32: =F25-F27-F31 -> 2.6055911e+09 | G32: =G25-G27-G31 -> 12693166 | H32: =H25-H27-H31 -> -1.8126865e+08 | I32: =I25-I27-I31 -> 2.1243525e+08 | J32: =J25-J27-J31 -> 3.8325403e+08 | K32: =K25-K27-K31 -> 3.6686214e+08 | ... R32: =R25-R27-R31 -> -2.3298578e+09 | S32: =SUM(G32:R32) -> -1.5522394e+10 | U32: =F32/F$9 -> 0.015383507 | V32: =S32/S$9 -> -0.16037911
B33: 7.1 | C33: % lãi gộp/doanh thu | D33: =IFERROR(D30/$F$9,0) -> 0 | E33: =IFERROR(E30/$F$9,0) -> 0 | F33: =IFERROR(F30/$F$9,0) -> 0.025606982 | G33: =G32/G9 -> 0.0011119294 | H33: =H32/H9 -> -0.020416177 | I33: =I32/I9 -> 0.016748516 | J33: =J32/J9 -> 0.02746906 | K33: =K32/K9 -> 0.026326709 | L33: =L32/L9 -> -0.45385464 | M33: =M32/M9 -> -0.45644148 | N33: =N32/N9 -> -0.45643466 | ... S33: =S32/S9 -> -0.16037911 | U33: =F33/F$9 -> 1.5118458e-13 | V33: =S33/S$9 -> -1.657055e-12
B34: 8 | C34: CHI PHÍ BÁN HÀNG & MKT & R&D | D34: =D35+D36+D37 -> 0 | E34: =E35+E36+E37 -> 0 | F34: =F35+F36+F37 -> 0 | G34: =G35+G36+G37 -> 0 | H34: =H35+H36+H37 -> 0 | I34: =I35+I36+I37 -> 0 | J34: =J35+J36+J37 -> 0 | K34: =K35+K36+K37 -> 0 | ... R34: =R35+R36+R37 -> 0 | S34: =SUM(G34:R34) -> 0 | U34: =F34/F$9 -> 0 | V34: =S34/S$9 -> 0
B35: 8.1 | C35: Lương | S35: =SUM(G35:R35) -> 0 | U35: =F35/F$9 -> 0 | V35: =S35/S$9 -> 0
B36: 8.2 | C36: Chi phí bán hàng (ngoài lương, khấu hao) | S36: =SUM(G36:R36) -> 0 | U36: =F36/F$9 -> 0 | V36: =S36/S$9 -> 0
B37: 8.3 | C37: Khấu hao tài sản | S37: =SUM(G37:R37) -> 0 | U37: =F37/F$9 -> 0 | V37: =S37/S$9 -> 0
B38: 9 | C38: CHI PHÍ QUẢN LÝ | D38: =D39+D40+D41 -> 0 | E38: =E39+E40+E41 -> 0 | F38: =F39+F40+F41 -> 3999101100 | G38: =G39+G40+G41 -> 5.5745033e+08 | H38: =H39+H40+H41 -> 4.9130588e+08 | I38: =I39+I40+I41 -> 5.2052051e+08 | J38: =J39+J40+J41 -> 5.2535235e+08 | K38: =K39+K40+K41 -> 5.0687739e+08 | ... R38: =R39+R40+R41 -> 4.9472248e+08 | S38: =SUM(G38:R38) -> 6.2742277e+09 | U38: =F38/F$9 -> 0.023610842 | V38: =S38/S$9 -> 0.064826024
B39: 9.1 | C39: Lương | F39: =SUM(CPQL!AK5:AK14) -> 2254151653 | G39: =SUM(CPQL!K5:K14) -> 3.2479914e+08 | H39: =SUM(CPQL!L5:L14) -> 3.2569102e+08 | I39: =SUM(CPQL!M5:M14) -> 3.0965466e+08 | J39: =SUM(CPQL!N5:N14) -> 3.3272325e+08 | K39: =SUM(CPQL!O5:O14) -> 3.1993578e+08 | L39: =SUM(CPQL!P5:P14) -> 3.3302825e+08 | M39: =SUM(CPQL!Q5:Q14) -> 3.2580138e+08 | N39: =SUM(CPQL!R5:R14) -> 3.2580138e+08 | ... R39: =SUM(CPQL!V5:V14) -> 3.2549638e+08 | S39: =SUM(G39:R39) -> 3.9074709e+09 | U39: =F39/F$9 -> 0.013308596 | V39: =S39/S$9 -> 0.040372428
B40: 9.2 | C40: Chi phí quản lý (ngoài lương, khấu hao) | F40: =CPQL!AK65-'KQKD PET'!F39-'KQKD PET'!F41 -> 1658847971 | G40: =CPQL!K65-G39-G41 -> 2.2404662e+08 | H40: =CPQL!L65-H39-H41 -> 1.5701029e+08 | I40: =CPQL!M65-I39-I41 -> 2.0226129e+08 | J40: =CPQL!N65-J39-J41 -> 1.8402454e+08 | K40: =CPQL!O65-K39-K41 -> 1.7833704e+08 | L40: =CPQL!P65-L39-L41 -> 3.2803148e+08 | M40: =CPQL!Q65-M39-M41 -> 1.6003148e+08 | N40: =CPQL!R65-N39-N41 -> 1.9040648e+08 | ... R40: =CPQL!V65-R39-R41 -> 1.6062153e+08 | S40: =SUM(G40:R40) -> 2.263502e+09 | U40: =F40/F$9 -> 0.0097939004 | V40: =S40/S$9 -> 0.023386757
B41: 9.3 | C41: Khấu hao tài sản | F41: =CPQL!AK61 -> 86101476 | G41: =CPQL!K61 -> 8604567 | H41: =CPQL!L61 -> 8604567 | I41: =CPQL!M61 -> 8604567 | J41: =CPQL!N61 -> 8604567 | K41: =CPQL!O61 -> 8604567 | L41: =CPQL!P61 -> 8604567 | M41: =CPQL!Q61 -> 8604567 | N41: =CPQL!R61 -> 8604567 | ... R41: =CPQL!V61 -> 8604567 | S41: =SUM(G41:R41) -> 103254804 | U41: =F41/F$9 -> 0.00050834633 | V41: =S41/S$9 -> 0.0010668402
B42: 10 | C42: DOANH THU/CHI PHÍ KHÁC | F42: -14027331 | S42: =SUM(G42:R42) -> 0 | U42: =F42/F$9 -> -8.2817886e-05 | V42: =S42/S$9 -> 0
B43: 11 | C43: LỢI NHUẬN THUẦN TỪ HOẠT ĐỘNG KINH DOANH | D43: =D32-D34-D38+D42 -> 0 | E43: =E32-E34-E38+E42 -> 64684339330 | F43: =F32-F34-F38+F42 -> -1.4075374e+09 | G43: =G32-G34-G38+G42 -> -5.4475716e+08 | H43: =H32-H34-H38+H42 -> -6.7257453e+08 | I43: =I32-I34-I38+I42 -> -3.0808527e+08 | J43: =J32-J34-J38+J42 -> -1.4209833e+08 | K43: =K32-K34-K38+K42 -> -1.4001525e+08 | ... R43: =R32-R34-R38+R42 -> -2.8245803e+09 | S43: =SUM(G43:R43) -> -2.1796621e+10 | U43: =F43/F$9 -> -0.0083101531 | V43: =S43/S$9 -> -0.22520514
B44: 12 | C44: DOANH THU TÀI CHÍNH | S44: =SUM(G44:R44) -> 0 | U44: =F44/F$9 -> 0 | V44: =S44/S$9 -> 0
B45: 13 | C45: CHI PHÍ TÀI CHÍNH | S45: =SUM(G45:R45) -> 0 | U45: =F45/F$9 -> 0 | V45: =S45/S$9 -> 0
B46: 13.1 | C46: Trong đó: chi phí lãi vay | S46: =SUM(G46:R46) -> 0 | U46: =F46/F$9 -> 0 | V46: =S46/S$9 -> 0
B47: 14 | C47: LỢI NHUẬN TRƯỚC THUẾ | D47: =D43+D44-D45 -> 0 | E47: =E43+E44-E45 -> 64684339330 | F47: =F43+F44-F45 -> -1.4075374e+09 | G47: =G43+G44-G45 -> -5.4475716e+08 | H47: =H43+H44-H45 -> -6.7257453e+08 | I47: =I43+I44-I45 -> -3.0808527e+08 | J47: =J43+J44-J45 -> -1.4209833e+08 | K47: =K43+K44-K45 -> -1.4001525e+08 | ... R47: =R43+R44-R45 -> -2.8245803e+09 | S47: =SUM(G47:R47) -> -2.1796621e+10 | T47: 1.2313803e+09 | U47: =F47/F$9 -> -0.0083101531 | V47: =S47/S$9 -> -0.22520514
B48: 15 | C48: THUẾ TNDN | S48: =SUM(G48:R48) -> 0 | T48: =T47-S47 -> 2.3028002e+10 | U48: =F48/F$9 -> 0 | V48: =S48/S$9 -> 0
B49: 16 | C49: LỢI NHUẬN SAU THUẾ | D49: =D47-D48 -> 0 | E49: =E47-E48 -> 64684339330 | F49: =F47-F48 -> -1.4075374e+09 | G49: =G47-G48 -> -5.4475716e+08 | H49: =H47-H48 -> -6.7257453e+08 | I49: =I47-I48 -> -3.0808527e+08 | J49: =J47-J48 -> -1.4209833e+08 | K49: =K47-K48 -> -1.4001525e+08 | ... R49: =R47-R48 -> -2.8245803e+09 | S49: =SUM(G49:R49) -> -2.1796621e+10 | U49: =F49/F$9 -> -0.0083101531 | V49: =S49/S$9 -> -0.22520514
B50: 16.1 | C50: % LNST/doanh thu | D50: =IFERROR(D47/$F$9,0) -> 0 | E50: =IFERROR(E47/$F$9,0) -> 0.38189876 | F50: =IFERROR(F47/$F$9,0) -> -0.0083101531 | G50: =G49/G9 -> -0.047721073 | H50: =H49/H9 -> -0.075751657 | I50: =I49/I9 -> -0.024289618 | J50: =J49/J9 -> -0.010184648 | K50: =K49/K9 -> -0.010047755 | L50: =L49/L9 -> -0.58435533 | M50: =M49/M9 -> -0.55279487 | N50: =N49/N9 -> -0.55870737 | ... S50: =S49/S9 -> -0.22520514 | U50: =F50/F$9 -> -4.9063454e-14 | V50: =S50/S$9 -> -2.3268447e-12
B51: 17 | C51: Khấu hao tài sản | F51: =CPSX!AK99+F41 -> 3773488165 | G51: =SUM(PB_TSCD!AF130:AF131,PB_TSCD!AF134,PB_TSCD!AF135) -> 1.4644116e+08 | H51: =SUM(PB_TSCD!AG130:AG131,PB_TSCD!AG134,PB_TSCD!AG135) -> 1.4644116e+08 | I51: =SUM(PB_TSCD!AH130:AH131,PB_TSCD!AH134,PB_TSCD!AH135) -> 1.4387752e+08 | J51: =SUM(PB_TSCD!AI130:AI131,PB_TSCD!AI134,PB_TSCD!AI135) -> 1.4387752e+08 | K51: =SUM(PB_TSCD!AJ130:AJ131,PB_TSCD!AJ134,PB_TSCD!AJ135) -> 1.4387752e+08 | L51: =SUM(PB_TSCD!AK130:AK131,PB_TSCD!AK134,PB_TSCD!AK135) -> 1.4387752e+08 | M51: =SUM(PB_TSCD!AL130:AL131,PB_TSCD!AL134,PB_TSCD!AL135) -> 1.4387752e+08 | N51: =SUM(PB_TSCD!AM130:AM131,PB_TSCD!AM134,PB_TSCD!AM135) -> 1.4387752e+08 | ... R51: =SUM(PB_TSCD!AQ130:AQ131,PB_TSCD!AQ134,PB_TSCD!AQ135) -> 1.4387752e+08 | S51: =SUM(G51:R51) -> 1.7316576e+09 | T51: ='KQKD HD'!S51 -> 2.9257708e+09 | U51: =F51/F$9 -> 0.022278815 | V51: =S51/S$9 -> 0.01789168
B52: 18 | C52: LỢI NHUẬN KHÔNG BAO GỒM KHẤU HAO, LÃI VAY | D52: =D49+D51 -> 0 | E52: =E49+E51 -> 64684339330 | F52: =F49+F51 -> 2.3659508e+09 | G52: =G49+G51 -> -3.98316e+08 | H52: =H49+H51 -> -5.2613337e+08 | I52: =I49+I51 -> -1.6420774e+08 | J52: =J49+J51 -> 1779196.8 | K52: =K49+K51 -> 3862269.9 | ... R52: =R49+R51 -> -2.6807027e+09 | S52: =SUM(G52:R52) -> -2.0064964e+10 | U52: =F52/F$9 -> 0.013968662 | V52: =S52/S$9 -> -0.20731346
B53: 18.1 | C53: % LN không gồm khấu hao/doanh thu | D53: =IFERROR(D50/$F$9,0) -> 0 | E53: =IFERROR(E50/$F$9,0) -> 2.2547445e-12 | F53: =IFERROR(F50/$F$9,0) -> -4.9063454e-14 | G53: =G52/G9 -> -0.034892734 | H53: =H52/H9 -> -0.059258079 | I53: =I52/I9 -> -0.012946232 | J53: =J52/J9 -> 0.00012752081 | K53: =K52/K9 -> 0.00027716367 | L53: =L52/L9 -> -0.55631723 | M53: =M52/M9 -> -0.52475677 | N53: =N52/N9 -> -0.53066927 | ... S53: =S52/S9 -> -0.20731346
B56: 1. Hòa vốn (Bao gồm khấu hao) | D56: =D4 -> Thực tế năm 2023 | E56: =E4 -> Thực tế năm 2024 | F56: =F4 -> KQKD 2025 | G56: =G4 -> T1 | H56: =H4 -> T2 | I56: =I4 -> T3 | J56: =J4 -> T4 | K56: =K4 -> T5 | ... S56: =S4 -> KH 2026
B57: Sản lượng NVL hòa vốn (tấn) | D57: =IFERROR(D$58*(1+(D$17+D$18)/D$16),0) -> 0 | E57: =IFERROR(E$58*(1+(E$17+E$18)/E$16),0) -> 0 | F57: =IFERROR(F$58*(1+(F$17+F$18)/F$16),0) -> 10250090 | G57: =G$58*(1+(G$17+G$18)/G$16) -> 1406449.3 | H57: =H$58*(1+(H$17+H$18)/H$16) -> 1326000.2 | I57: =I$58*(1+(I$17+I$18)/I$16) -> 1249881.2 | J57: =J$58*(1+(J$17+J$18)/J$16) -> 1196016.9 | K57: =K$58*(1+(K$17+K$18)/K$16) -> 1195415 | L57: =L$58*(1+(L$17+L$18)/L$16) -> -535301.34 | M57: =M$58*(1+(M$17+M$18)/M$16) -> -471041.32 | N57: =N$58*(1+(N$17+N$18)/N$16) -> -481213.44 | ... S57: =S$58*(1+(S$17+S$18)/S$16) -> -29621962
B58: Sản lượng thành phẩm hòa vốn (tấn) | D58: =IFERROR((D$27+D$31+D$34+D$38)/(D$25/D$5),0) -> 0 | E58: =IFERROR((E$27+E$31+E$34+E$38)/(E$25/E$5),0) -> 0 | F58: =IFERROR((F$27+F$31+F$34+F$38)/(F$25/F$5),0) -> 10250090 | G58: =(G$27+G$31+G$34+G$38)/(G$25/G$5) -> 1228071.8 | H58: =(H$27+H$31+H$34+H$38)/(H$25/H$5) -> 1157826 | I58: =(I$27+I$31+I$34+I$38)/(I$25/I$5) -> 1091361 | J58: =(J$27+J$31+J$34+J$38)/(J$25/J$5) -> 1044328.2 | K58: =(K$27+K$31+K$34+K$38)/(K$25/K$5) -> 1042846.6 | L58: =(L$27+L$31+L$34+L$38)/(L$25/L$5) -> -386909.98 | M58: =(M$27+M$31+M$34+M$38)/(M$25/M$5) -> -340463.54 | N58: =(N$27+N$31+N$34+N$38)/(N$25/N$5) -> -347815.84 | ... S58: =(S$27+S$31+S$34+S$38)/(S$25/S$5) -> -23744999
B59: Doanh thu hòa vốn (triệu đồng) | D59: =IFERROR(D$58*(D$9/D$5),0) -> 0 | E59: =IFERROR(E$58*(E$9/E$5),0) -> 0 | F59: =IFERROR(F$58*(F$9/F$5),0) -> 1.8275065e+11 | G59: =G$58*(G$9/G$5) -> 1.8223631e+10 | H59: =H$58*(H$9/H$5) -> 1.7181237e+10 | I59: =I$58*(I$9/I$5) -> 1.6194948e+10 | J59: =J$58*(J$9/J$5) -> 1.5497018e+10 | K59: =K$58*(K$9/K$5) -> 1.5474933e+10 | L59: =L$58*(L$9/L$5) -> -5.6377793e+09 | M59: =M$58*(M$9/M$5) -> -4.9609945e+09 | N59: =N$58*(N$9/N$5) -> -5.0681271e+09 | ... S59: =S$58*(S$9/S$5) -> -3.4996873e+11
B60: 2. Hòa vốn (Không bao gồm khấu hao) | D60: =D56 -> Thực tế năm 2023 | E60: =E56 -> Thực tế năm 2024 | F60: =F56 -> KQKD 2025 | G60: =G56 -> T1 | H60: =H56 -> T2 | I60: =I56 -> T3 | J60: =J56 -> T4 | K60: =K56 -> T5 | ... S60: =S56 -> KH 2026
B61: Sản lượng NVL hòa vốn (tấn) | D61: =IFERROR(D$62*(1+(D$17+D$18)/D$16),0) -> 0 | E61: =IFERROR(E$62*(1+(E$17+E$18)/E$16),0) -> 0 | F61: =IFERROR(F$62*(1+(F$17+F$18)/F$16),0) -> 8218685.1 | G61: =G$62*(1+(G$17+G$18)/G$16) -> 1265201.7 | H61: =H$62*(1+(H$17+H$18)/H$16) -> 1186484.2 | I61: =I$62*(1+(I$17+I$18)/I$16) -> 1123332.6 | J61: =J$62*(1+(J$17+J$18)/J$16) -> 1075299.9 | K61: =K$62*(1+(K$17+K$18)/K$16) -> 1073174.5 | L61: =L$62*(1+(L$17+L$18)/L$16) -> -486238.97 | M61: =M$62*(1+(M$17+M$18)/M$16) -> -422437.16 | N61: =N$62*(1+(N$17+N$18)/N$16) -> -432613.16 | ... S61: =S$62*(1+(S$17+S$18)/S$16) -> -26617780
B62: Sản lượng thành phẩm hòa vốn (tấn) | D62: =IFERROR((D$27+D$31+D$34+D$38-D51)/(D$25/D$5),0) -> 0 | E62: =IFERROR((E$27+E$31+E$34+E$38-E51)/(E$25/E$5),0) -> 0 | F62: =IFERROR((F$27+F$31+F$34+F$38-F51)/(F$25/F$5),0) -> 8218685.1 | G62: =(G$27+G$31+G$34+G$38-G51)/(G$25/G$5) -> 1104738.5 | H62: =(H$27+H$31+H$34+H$38-H51)/(H$25/H$5) -> 1036004.6 | I62: =(I$27+I$31+I$34+I$38-I51)/(I$25/I$5) -> 980862.34 | J62: =(J$27+J$31+J$34+J$38-J51)/(J$25/J$5) -> 938921.54 | K62: =(K$27+K$31+K$34+K$38-K51)/(K$25/K$5) -> 936207.36 | L62: =(L$27+L$31+L$34+L$38-L51)/(L$25/L$5) -> -351448.23 | M62: =(M$27+M$31+M$34+M$38-M51)/(M$25/M$5) -> -305332.98 | N62: =(N$27+N$31+N$34+N$38-N51)/(N$25/N$5) -> -312688.08 | ... S62: =(S$27+S$31+S$34+S$38-S51)/(S$25/S$5) -> -21336843
B63: Doanh thu hòa vốn (triệu đồng) | D63: =IFERROR(D$62*(D$9/D$5),0) -> 0 | E63: =IFERROR(E$62*(E$9/E$5),0) -> 0 | F63: =IFERROR(F$62*(F$9/F$5),0) -> 1.4653238e+11 | G63: =G$62*(G$9/G$5) -> 1.6393459e+10 | H63: =H$62*(H$9/H$5) -> 1.5373502e+10 | I63: =I$62*(I$9/I$5) -> 1.4555234e+10 | J63: =J$62*(J$9/J$5) -> 1.3932865e+10 | K63: =K$62*(K$9/K$5) -> 1.38925e+10 | L63: =L$62*(L$9/L$5) -> -5.1210558e+09 | M63: =M$62*(M$9/M$5) -> -4.4490969e+09 | N63: =N$62*(N$9/N$5) -> -4.5562702e+09 | ... S63: =S$62*(S$9/S$5) -> -3.1447582e+11
B65: Tỷ lệ Hao hụt | F65: =(F17+F18)/F9 -> 0 | G65: =(G17+G18)/G9 -> 0.11606189 | H65: =(H17+H18)/H9 -> 0.11606189 | I65: =(I17+I18)/I9 -> 0.11606189 | J65: =(J17+J18)/J9 -> 0.11606189 | K65: =(K17+K18)/K9 -> 0.11704543 | L65: =(L17+L18)/L9 -> 0.3895403 | M65: =(M17+M18)/M9 -> 0.3895403 | ... S65: =(S17+S18)/S9 -> 0.21770081
B66: 1.Phân loại | F66: =(F17)/F9 -> 0 | G66: =(G17)/G9 -> 0.092889467 | H66: =(H17)/H9 -> 0.092889467 | I66: =(I17)/I9 -> 0.092889467 | J66: =(J17)/J9 -> 0.092889467 | K66: =(K17)/K9 -> 0.09380435 | L66: =(L17)/L9 -> 0.25690541 | M66: =(M17)/M9 -> 0.25690541 | ... S66: =(S17)/S9 -> 0.15389319
B67: 2. Băm | F67: =(F18)/F9 -> 0 | G67: =(G18)/G9 -> 0.023172426 | H67: =(H18)/H9 -> 0.023172426 | I67: =(I18)/I9 -> 0.023172426 | J67: =(J18)/J9 -> 0.023172426 | K67: =(K18)/K9 -> 0.023241078 | L67: =(L18)/L9 -> 0.13263489 | M67: =(M18)/M9 -> 0.13263489 | ... S67: =(S18)/S9 -> 0.063807621

Sheet KQKD HD
L1: 62610818
B3: MỤC TIÊU KẾT QUẢ KINH DOANH NĂM 2026 | F3: 215.282 | S3: ĐVT: Triệu đồng
B4: STT | C4: Mục phí | D4: Thực tế năm 2023 | E4: Thực tế năm 2024 | F4: KQKD 2025 | G4: T1 | H4: T2 | I4: T3 | J4: T4 | K4: T5 | L4: T6 | M4: T7 | N4: T8 | O4: T9 | P4: T10 | Q4: T11 | R4: T12 | S4: KH 2026 | U4: KQKD 2025 | V4: KH 2026 | X4: KQKD 2025 | Y4: KH 2026
B5: 1 | C5: SẢN LƯỢNG BÁN (TẤN) | F5: =F6+F7+F8 -> 215282 | G5: =G6+G7+G8 -> 0 | H5: =H6+H7+H8 -> 0 | I5: =I6+I7+I8 -> 0 | J5: =J6+J7+J8 -> 0 | K5: =K6+K7+K8 -> 0 | L5: =L6+L7+L8 -> 550605 | M5: =M6+M7+M8 -> 550605 | ... R5: =R6+R7+R8 -> 550605 | S5: =SUM(G5:R5) -> 3854235
B6: 1.1 | C6: Chai PET | F6: ='4.Doanh thu'!E22 -> 0 | S6: =SUM(G6:R6) -> 0
B7: 1.2 | C7: Vảy PET | G7: ='4.Doanh thu'!F99 -> 0 | H7: ='4.Doanh thu'!G99 -> 0 | I7: ='4.Doanh thu'!H99 -> 0 | J7: ='4.Doanh thu'!I99 -> 0 | K7: ='4.Doanh thu'!J99 -> 0 | L7: ='4.Doanh thu'!K99 -> 550605 | M7: ='4.Doanh thu'!L99 -> 550605 | N7: ='4.Doanh thu'!M99 -> 550605 | ... R7: ='4.Doanh thu'!Q99 -> 550605 | S7: =SUM(G7:R7) -> 3854235
B8: 1.3 | C8: Vảy HD | F8: ='4.Doanh thu'!AF161 -> 215282 | G8: ='4.Doanh thu'!F161 -> 0 | H8: ='4.Doanh thu'!G161 -> 0 | I8: ='4.Doanh thu'!H161 -> 0 | J8: ='4.Doanh thu'!I161 -> 0 | K8: ='4.Doanh thu'!J161 -> 0 | L8: ='4.Doanh thu'!K161 -> 0 | M8: ='4.Doanh thu'!L161 -> 0 | N8: ='4.Doanh thu'!M161 -> 0 | ... R8: ='4.Doanh thu'!Q161 -> 0 | S8: =SUM(G8:R8) -> 0
B9: 2 | C9: DOANH THU | F9: =F10+F11+F12+F13 -> 2657864180 | G9: =SUM(G10:G13) -> 0 | H9: =SUM(H10:H13) -> 0 | I9: =SUM(I10:I13) -> 0 | J9: =SUM(J10:J13) -> 0 | K9: =SUM(K10:K13) -> 0 | L9: =SUM(L10:L13) -> 8894613750 | M9: =SUM(M10:M13) -> 8894613750 | N9: =SUM(N10:N13) -> 8894613750 | ... R9: =SUM(R10:R13) -> 8894613750 | S9: =SUM(G9:R9) -> 62262296250 | U9: =F9/F$9 -> 1 | V9: =S9/S$9 -> 1 | X9: =F9/F5 -> 12345.966 | Y9: =S9/S5 -> 16154.255 | Z9: =Y9-X9 -> 3808.2897
B10: 2.1 | C10: Chai PET | F10: ='4.Doanh thu'!E60 -> 0 | S10: =SUM(G10:R10) -> 0 | U10: =F10/F$9 -> 0 | V10: =S10/S$9 -> 0
B11: 2.2 | C11: Vảy PET | G11: ='4.Doanh thu'!F157 -> 0 | H11: ='4.Doanh thu'!G157 -> 0 | I11: ='4.Doanh thu'!H157 -> 0 | J11: ='4.Doanh thu'!I157 -> 0 | K11: ='4.Doanh thu'!J157 -> 0 | L11: ='4.Doanh thu'!K157 -> 8894613750 | M11: ='4.Doanh thu'!L157 -> 8894613750 | N11: ='4.Doanh thu'!M157 -> 8894613750 | ... R11: ='4.Doanh thu'!Q157 -> 8894613750 | S11: =SUM(G11:R11) -> 62262296250 | U11: =F11/F$9 -> 0 | V11: =S11/S$9 -> 1
B12: 2.3 | C12: Vảy HD | F12: ='4.Doanh thu'!AF163 -> 2657864180 | G12: ='4.Doanh thu'!F163 -> 0 | H12: ='4.Doanh thu'!G163 -> 0 | I12: ='4.Doanh thu'!H163 -> 0 | J12: ='4.Doanh thu'!I163 -> 0 | K12: ='4.Doanh thu'!J163 -> 0 | L12: ='4.Doanh thu'!K163 -> 0 | M12: ='4.Doanh thu'!L163 -> 0 | N12: ='4.Doanh thu'!M163 -> 0 | ... R12: ='4.Doanh thu'!Q163 -> 0 | S12: =SUM(G12:R12) -> 0 | U12: =F12/F$9 -> 1 | V12: =S12/S$9 -> 0
B13: 2.4 | C13: Khác | S13: =SUM(G13:R13) -> 0 | U13: =F13/F$9 -> 0 | V13: =S13/S$9 -> 0
B14: 3 | C14: BIẾN PHÍ | F14: =F15+F23 -> 3423596304 | G14: =G15+G23 -> 0 | H14: =H15+H23 -> 0 | I14: =I15+I23 -> 0 | J14: =J15+J23 -> 0 | K14: =K15+K23 -> 0 | L14: =L15+L23 -> 6.5764919e+09 | M14: =M15+M23 -> 6.5764919e+09 | ... R14: =R15+R23 -> 6.5764919e+09 | S14: =SUM(G14:R14) -> 4.6035443e+10 | U14: =F14/F$9 -> 1.2881005 | V14: =S14/S$9 -> 0.73937914
B15: 3.1 | C15: BIẾN PHÍ SẢN XUẤT | F15: =F16+F20+F21+F22 -> 3423596304 | G15: =G16+G20+G21+G22 -> 0 | H15: =H16+H20+H21+H22 -> 0 | I15: =I16+I20+I21+I22 -> 0 | J15: =J16+J20+J21+J22 -> 0 | K15: =K16+K20+K21+K22 -> 0 | L15: =L16+L20+L21+L22 -> 6.4002983e+09 | M15: =M16+M20+M21+M22 -> 6.4002983e+09 | ... R15: =R16+R20+R21+R22 -> 6.4002983e+09 | S15: =SUM(G15:R15) -> 4.4802088e+10 | U15: =F15/F$9 -> 1.2881005 | V15: =S15/S$9 -> 0.71957012
B16: 3.1.1 | C16: Nguyên vật liệu chính (nhựa, gồm hao hụt) | F16: 3293596304 | G16: ='3.Thanh pham'!F102*'1.NVL Chai'!H34 -> 0 | H16: ='3.Thanh pham'!G102*'1.NVL Chai'!I34 -> 0 | I16: ='3.Thanh pham'!H102*'1.NVL Chai'!J34 -> 0 | J16: ='3.Thanh pham'!I102*'1.NVL Chai'!K34 -> 0 | K16: ='3.Thanh pham'!J102*'1.NVL Chai'!L34 -> 0 | L16: ='3.Thanh pham'!K102*'1.NVL Chai'!M34 -> 5936576250 | M16: ='3.Thanh pham'!L102*'1.NVL Chai'!N34 -> 5936576250 | N16: ='3.Thanh pham'!M102*'1.NVL Chai'!O34 -> 5936576250 | ... R16: ='3.Thanh pham'!Q102*'1.NVL Chai'!S34 -> 5936576250 | S16: =SUM(G16:R16) -> 41556033750 | U16: =F16/F$9 -> 1.2391891 | V16: =S16/S$9 -> 0.66743497
B17: 3.1.2 | C17: Trong đó: i/ Hao hụt CĐ phân loại chai | F17: ='1.NVL Chai'!G43 -> 0 | S17: =SUM(G17:R17) -> 0 | U17: =F17/F$9 -> 0 | V17: =S17/S$9 -> 0
C18: ii/ Hao hụt CĐ băm vảy | G18: ='1.NVL Chai'!H34*'3.Thanh pham'!F192 -> 0 | H18: ='1.NVL Chai'!I34*'3.Thanh pham'!G192 -> 0 | I18: ='1.NVL Chai'!J34*'3.Thanh pham'!H192 -> 0 | J18: ='1.NVL Chai'!K34*'3.Thanh pham'!I192 -> 0 | K18: ='1.NVL Chai'!L34*'3.Thanh pham'!J192 -> 0 | L18: ='1.NVL Chai'!M34*'3.Thanh pham'!K192 -> 356194575 | M18: ='1.NVL Chai'!N34*'3.Thanh pham'!L192 -> 356194575 | N18: ='1.NVL Chai'!O34*'3.Thanh pham'!M192 -> 356194575 | ... R18: ='1.NVL Chai'!S34*'3.Thanh pham'!Q192 -> 356194575 | S18: =SUM(G18:R18) -> 2493362025 | U18: =F18/F$9 -> 0 | V18: =S18/S$9 -> 0.040046098
B19: 3.1.3 | C19: % chi phí nguyên liệu/doanh thu | F19: =IFERROR(F16/F$9,0) -> 1.2391891 | G19: =IFERROR(G16/G$9,0) -> 0 | H19: =IFERROR(H16/H$9,0) -> 0 | I19: =IFERROR(I16/I$9,0) -> 0 | J19: =IFERROR(J16/J$9,0) -> 0 | K19: =IFERROR(K16/K$9,0) -> 0 | L19: =IFERROR(L16/L$9,0) -> 0.66743497 | M19: =IFERROR(M16/M$9,0) -> 0.66743497 | ... S19: =IFERROR(S16/S$9,0) -> 0.66743497 | U19: =F19/F$9 -> 4.6623492e-10 | V19: =S19/S$9 -> 1.0719729e-11
B20: 3.1.4 | C20: Nguyên vật liệu phụ | G20: =SUM(CPSX!K119:K125) -> 0 | H20: =SUM(CPSX!L119:L125) -> 0 | I20: =SUM(CPSX!M119:M125) -> 0 | J20: =SUM(CPSX!N119:N125) -> 0 | K20: =SUM(CPSX!O119:O125) -> 0 | L20: =SUM(CPSX!P119:P125) -> 2.5008533e+08 | M20: =SUM(CPSX!Q119:Q125) -> 2.5008533e+08 | N20: =SUM(CPSX!R119:R125) -> 2.5008533e+08 | ... R20: =SUM(CPSX!V119:V125) -> 2.5008533e+08 | S20: =SUM(G20:R20) -> 1750597300 | U20: =F20/F$9 -> 0 | V20: =S20/S$9 -> 0.028116491
B21: 3.1.5 | C21: Điện sản xuất | F21: =SUM(CPSX!AK118) -> 70000000 | G21: =CPSX!K118 -> 0 | H21: =CPSX!L118 -> 0 | I21: =CPSX!M118 -> 0 | J21: =CPSX!N118 -> 0 | K21: =CPSX!O118 -> 0 | L21: =CPSX!P118 -> 151025875 | M21: =CPSX!Q118 -> 151025875 | N21: =CPSX!R118 -> 151025875 | ... R21: =CPSX!V118 -> 151025875 | S21: =SUM(G21:R21) -> 1057181125 | U21: =F21/F$9 -> 0.026336936 | V21: =S21/S$9 -> 0.016979475
B22: 3.1.6 | C22: Nhân công trực tiếp | F22: =SUM(CPSX!AK106:AK116) -> 60000000 | G22: =SUM(CPSX!K106:K115) -> 0 | H22: =SUM(CPSX!L106:L115) -> 0 | I22: =SUM(CPSX!M106:M115) -> 0 | J22: =SUM(CPSX!N106:N115) -> 0 | K22: =SUM(CPSX!O106:O115) -> 0 | L22: =SUM(CPSX!P106:P115) -> 62610818 | M22: =SUM(CPSX!Q106:Q115) -> 62610818 | N22: =SUM(CPSX!R106:R115) -> 62610818 | ... R22: =SUM(CPSX!V106:V115) -> 62610818 | S22: =SUM(G22:R22) -> 4.3827572e+08 | U22: =F22/F$9 -> 0.022574517 | V22: =S22/S$9 -> 0.0070391834
B23: 3.2 | C23: BIẾN PHÍ BÁN HÀNG | F23: =F24 -> 0 | G23: =G24 -> 0 | H23: =H24 -> 0 | I23: =I24 -> 0 | J23: =J24 -> 0 | K23: =K24 -> 0 | L23: =L24 -> 176193600 | M23: =M24 -> 176193600 | ... R23: =R24 -> 176193600 | S23: =SUM(G23:R23) -> 1233355200 | U23: =F23/F$9 -> 0 | V23: =S23/S$9 -> 0.019809022
C24: Chi phí vận chuyển | F24: =SUM(CPBH!AK14) -> 0 | G24: =CPBH!K7 -> 0 | H24: =CPBH!L7 -> 0 | I24: =CPBH!M7 -> 0 | J24: =CPBH!N7 -> 0 | K24: =CPBH!O7 -> 0 | L24: =CPBH!P7 -> 176193600 | M24: =CPBH!Q7 -> 176193600 | N24: =CPBH!R7 -> 176193600 | ... R24: =CPBH!V7 -> 176193600 | S24: =SUM(G24:R24) -> 1233355200 | U24: =F24/F$9 -> 0 | V24: =S24/S$9 -> 0.019809022
B25: 4 | C25: LÃI SAU BIẾN PHÍ | F25: =F9-F14 -> -765732124 | G25: =G9-G14 -> 0 | H25: =H9-H14 -> 0 | I25: =I9-I14 -> 0 | J25: =J9-J14 -> 0 | K25: =K9-K14 -> 0 | L25: =L9-L14 -> 2.3181219e+09 | M25: =M9-M14 -> 2.3181219e+09 | ... R25: =R9-R14 -> 2.3181219e+09 | S25: =SUM(G25:R25) -> 1.6226853e+10 | U25: =F25/F$9 -> -0.28810055 | V25: =S25/S$9 -> 0.26062086
B26: 4.1 | C26: % lãi biến phí/doanh thu | F26: =IFERROR(F25/F$9,0) -> -0.28810055 | G26: =IFERROR(G25/G$9,0) -> 0 | H26: =IFERROR(H25/H$9,0) -> 0 | I26: =IFERROR(I25/I$9,0) -> 0 | J26: =IFERROR(J25/J$9,0) -> 0 | K26: =IFERROR(K25/K$9,0) -> 0 | L26: =IFERROR(L25/L$9,0) -> 0.26062086 | M26: =IFERROR(M25/M$9,0) -> 0.26062086 | ... S26: =IFERROR(S25/S$9,0) -> 0.26062086 | U26: =F26/F$9 -> -1.0839551e-10 | V26: =S26/S$9 -> 4.1858536e-12
B27: 5 | C27: CHI PHÍ SẢN XUẤT CHUNG | F27: =F28+F29+F30 -> 2927437824 | G27: =G28+G29+G30 -> 243953152 | H27: =H28+H29+H30 -> 243953152 | I27: =I28+I29+I30 -> 243953152 | J27: =J28+J29+J30 -> 243953152 | K27: =K28+K29+K30 -> 243953152 | L27: =L28+L29+L30 -> 2.6051886e+08 | M27: =M28+M29+M30 -> 260124222 | ... R27: =R28+R29+R30 -> 260124222 | S27: =SUM(G27:R27) -> 3041526929 | U27: =F27/F$9 -> 1.1014249 | V27: =S27/S$9 -> 0.048850221
B28: 5.1 | C28: Lương gián tiếp Sản xuất | F28: =SUM(CPSX!AK128:AK138) -> 0 | G28: =CPSX!K128 -> 0 | H28: =CPSX!L128 -> 0 | I28: =CPSX!M128 -> 0 | J28: =CPSX!N128 -> 0 | K28: =CPSX!O128 -> 0 | L28: =CPSX!P128 -> 16565711 | M28: =CPSX!Q128 -> 16171070 | N28: =CPSX!R128 -> 16171070 | ... R28: =CPSX!V128 -> 16171070 | S28: =SUM(G28:R28) -> 114089105 | U28: =F28/F$9 -> 0 | V28: =S28/S$9 -> 0.0018323948
B29: 5.2 | C29: Chi phí thuê xưởng | F29: =SUM(CPSX!AK144) -> 2770076112 | G29: =CPSX!K144 -> 230839676 | H29: =CPSX!L144 -> 230839676 | I29: =CPSX!M144 -> 230839676 | J29: =CPSX!N144 -> 230839676 | K29: =CPSX!O144 -> 230839676 | L29: =CPSX!P144 -> 230839676 | M29: =CPSX!Q144 -> 230839676 | N29: =CPSX!R144 -> 230839676 | ... R29: =CPSX!V144 -> 230839676 | S29: =SUM(G29:R29) -> 2770076112 | U29: =F29/F$9 -> 1.0422188 | V29: =S29/S$9 -> 0.044490426
B30: 5.3 | C30: Chi phí sản xuất (Ngoài lương, BOM, thuê xưởng, khấu hao) | F30: =CPSX!AK127-SUM('KQKD HD'!F28,'KQKD HD'!F29,'KQKD HD'!F31) -> 157361712 | G30: =$F$30/12 -> 13113476 | H30: =$F$30/12 -> 13113476 | I30: =$F$30/12 -> 13113476 | J30: =$F$30/12 -> 13113476 | K30: =$F$30/12 -> 13113476 | L30: =$F$30/12 -> 13113476 | M30: =$F$30/12 -> 13113476 | N30: =$F$30/12 -> 13113476 | ... R30: =$F$30/12 -> 13113476 | S30: =SUM(G30:R30) -> 157361712 | U30: =F30/F$9 -> 0.059206077 | V30: =S30/S$9 -> 0.0025273998
B31: 6 | C31: CHI PHÍ KHẤU HAO, CCDC | F31: =CPSX!AK155 -> 3462360432 | G31: =CPSX!K155 -> 2.3368692e+08 | H31: =CPSX!L155 -> 2.3368692e+08 | I31: =CPSX!M155 -> 2.3368692e+08 | J31: =CPSX!N155 -> 2.3368692e+08 | K31: =CPSX!O155 -> 2.3368692e+08 | L31: =CPSX!P155 -> 2.5104803e+08 | M31: =CPSX!Q155 -> 2.5104803e+08 | N31: =CPSX!R155 -> 2.5104803e+08 | ... R31: =CPSX!V155 -> 2.5104803e+08 | S31: =SUM(G31:R31) -> 2.9257708e+09 | U31: =F31/F$9 -> 1.3026852 | V31: =S31/S$9 -> 0.046991052
B32: 7 | C32: LỢI NHUẬN GỘP | F32: =F25-F27-F31 -> -7155530380 | G32: =G25-G27-G31 -> -4.7764007e+08 | H32: =H25-H27-H31 -> -4.7764007e+08 | I32: =I25-I27-I31 -> -4.7764007e+08 | J32: =J25-J27-J31 -> -4.7764007e+08 | K32: =K25-K27-K31 -> -4.7764007e+08 | L32: =L25-L27-L31 -> 1.806555e+09 | M32: =M25-M27-M31 -> 1.8069496e+09 | ... R32: =R25-R27-R31 -> 1.8069496e+09 | S32: =SUM(G32:R32) -> 1.0259555e+10 | U32: =F32/F$9 -> -2.6922107 | V32: =S32/S$9 -> 0.16477959
B33: 7.1 | C33: % lãi gộp/doanh thu | F33: =IFERROR(F32/F$9,0) -> -2.6922107 | G33: =IFERROR(G32/G$9,0) -> 0 | H33: =IFERROR(H32/H$9,0) -> 0 | I33: =IFERROR(I32/I$9,0) -> 0 | J33: =IFERROR(J32/J$9,0) -> 0 | K33: =IFERROR(K32/K$9,0) -> 0 | L33: =IFERROR(L32/L$9,0) -> 0.20310663 | M33: =IFERROR(M32/M$9,0) -> 0.20315099 | ... S33: =IFERROR(S32/S$9,0) -> 0.16477959 | U33: =F33/F$9 -> -1.0129226e-09 | V33: =S33/S$9 -> 2.6465389e-12
B34: 8 | C34: CHI PHÍ BÁN HÀNG & MKT & R&D | F34: =F35+F36+F37 -> 0 | G34: =G35+G36+G37 -> 0 | H34: =H35+H36+H37 -> 0 | I34: =I35+I36+I37 -> 0 | J34: =J35+J36+J37 -> 0 | K34: =K35+K36+K37 -> 0 | L34: =L35+L36+L37 -> 0 | M34: =M35+M36+M37 -> 0 | ... R34: =R35+R36+R37 -> 0 | S34: =SUM(G34:R34) -> 0 | U34: =F34/F$9 -> 0 | V34: =S34/S$9 -> 0
B35: 8.1 | C35: Lương | S35: =SUM(G35:R35) -> 0 | U35: =F35/F$9 -> 0 | V35: =S35/S$9 -> 0
B36: 8.2 | C36: Chi phí bán hàng (ngoài lương, khấu hao) | S36: =SUM(G36:R36) -> 0 | U36: =F36/F$9 -> 0 | V36: =S36/S$9 -> 0
B37: 83 | C37: Khấu hao tài sản | S37: =SUM(G37:R37) -> 0 | U37: =F37/F$9 -> 0 | V37: =S37/S$9 -> 0
B38: 9 | C38: CHI PHÍ QUẢN LÝ | F38: =F39+F40+F41 -> 0 | G38: =G39+G40+G41 -> 0 | H38: =H39+H40+H41 -> 0 | I38: =I39+I40+I41 -> 0 | J38: =J39+J40+J41 -> 0 | K38: =K39+K40+K41 -> 0 | L38: =L39+L40+L41 -> 0 | M38: =M39+M40+M41 -> 0 | ... R38: =R39+R40+R41 -> 0 | S38: =SUM(G38:R38) -> 0 | U38: =F38/F$9 -> 0 | V38: =S38/S$9 -> 0
B39: 9.1 | C39: Lương | S39: =SUM(G39:R39) -> 0 | U39: =F39/F$9 -> 0 | V39: =S39/S$9 -> 0
B40: 9.2 | C40: Chi phí quản lý (ngoài lương, khấu hao) | S40: =SUM(G40:R40) -> 0 | U40: =F40/F$9 -> 0 | V40: =S40/S$9 -> 0
B41: 9.3 | C41: Khấu hao tài sản | S41: =SUM(G41:R41) -> 0 | U41: =F41/F$9 -> 0 | V41: =S41/S$9 -> 0
B42: 10 | C42: DOANH THU/CHI PHÍ KHÁC | S42: =SUM(G42:R42) -> 0 | U42: =F42/F$9 -> 0 | V42: =S42/S$9 -> 0
B43: 11 | C43: LỢI NHUẬN THUẦN TỪ HOẠT ĐỘNG KINH DOANH | F43: =F32-F34-F38+F42 -> -7155530380 | G43: =G32-G34-G38+G42 -> -4.7764007e+08 | H43: =H32-H34-H38+H42 -> -4.7764007e+08 | I43: =I32-I34-I38+I42 -> -4.7764007e+08 | J43: =J32-J34-J38+J42 -> -4.7764007e+08 | K43: =K32-K34-K38+K42 -> -4.7764007e+08 | L43: =L32-L34-L38+L42 -> 1.806555e+09 | M43: =M32-M34-M38+M42 -> 1.8069496e+09 | ... R43: =R32-R34-R38+R42 -> 1.8069496e+09 | S43: =SUM(G43:R43) -> 1.0259555e+10 | U43: =F43/F$9 -> -2.6922107 | V43: =S43/S$9 -> 0.16477959
B44: 12 | C44: DOANH THU TÀI CHÍNH | S44: =SUM(G44:R44) -> 0 | U44: =F44/F$9 -> 0 | V44: =S44/S$9 -> 0
B45: 13 | C45: CHI PHÍ TÀI CHÍNH | S45: =SUM(G45:R45) -> 0 | U45: =F45/F$9 -> 0 | V45: =S45/S$9 -> 0
B46: 13.1 | C46: Trong đó: chi phí lãi vay | S46: =SUM(G46:R46) -> 0 | U46: =F46/F$9 -> 0 | V46: =S46/S$9 -> 0
B47: 14 | C47: LỢI NHUẬN TRƯỚC THUẾ | F47: =F43+F44-F45 -> -7155530380 | G47: =G43+G44-G45 -> -4.7764007e+08 | H47: =H43+H44-H45 -> -4.7764007e+08 | I47: =I43+I44-I45 -> -4.7764007e+08 | J47: =J43+J44-J45 -> -4.7764007e+08 | K47: =K43+K44-K45 -> -4.7764007e+08 | L47: =L43+L44-L45 -> 1.806555e+09 | M47: =M43+M44-M45 -> 1.8069496e+09 | ... R47: =R43+R44-R45 -> 1.8069496e+09 | S47: =SUM(G47:R47) -> 1.0259555e+10 | U47: =F47/F$9 -> -2.6922107 | V47: =S47/S$9 -> 0.16477959
B48: 15 | C48: THUẾ TNDN | S48: =SUM(G48:R48) -> 0 | U48: =F48/F$9 -> 0 | V48: =S48/S$9 -> 0
B49: 16 | C49: LỢI NHUẬN SAU THUẾ | F49: =F47-F48 -> -7155530380 | G49: =G47-G48 -> -4.7764007e+08 | H49: =H47-H48 -> -4.7764007e+08 | I49: =I47-I48 -> -4.7764007e+08 | J49: =J47-J48 -> -4.7764007e+08 | K49: =K47-K48 -> -4.7764007e+08 | L49: =L47-L48 -> 1.806555e+09 | M49: =M47-M48 -> 1.8069496e+09 | ... R49: =R47-R48 -> 1.8069496e+09 | S49: =SUM(G49:R49) -> 1.0259555e+10 | U49: =F49/F$9 -> -2.6922107 | V49: =S49/S$9 -> 0.16477959
B50: 16.1 | C50: % LNST/doanh thu | F50: =IFERROR(F49/F$9,0) -> -2.6922107 | G50: =IFERROR(G49/G$9,0) -> 0 | H50: =IFERROR(H49/H$9,0) -> 0 | I50: =IFERROR(I49/I$9,0) -> 0 | J50: =IFERROR(J49/J$9,0) -> 0 | K50: =IFERROR(K49/K$9,0) -> 0 | L50: =IFERROR(L49/L$9,0) -> 0.20310663 | M50: =IFERROR(M49/M$9,0) -> 0.20315099 | ... S50: =IFERROR(S49/S$9,0) -> 0.16477959 | U50: =F50/F$9 -> -1.0129226e-09 | V50: =S50/S$9 -> 2.6465389e-12
B51: 17 | C51: Khấu hao tài sản | F51: =F31+F37+F41 -> 3462360432 | G51: =G31+G37+G41 -> 2.3368692e+08 | H51: =H31+H37+H41 -> 2.3368692e+08 | I51: =I31+I37+I41 -> 2.3368692e+08 | J51: =J31+J37+J41 -> 2.3368692e+08 | K51: =K31+K37+K41 -> 2.3368692e+08 | L51: =L31+L37+L41 -> 2.5104803e+08 | M51: =M31+M37+M41 -> 2.5104803e+08 | ... R51: =R31+R37+R41 -> 2.5104803e+08 | S51: =SUM(G51:R51) -> 2.9257708e+09 | U51: =F51/F$9 -> 1.3026852 | V51: =S51/S$9 -> 0.046991052 | CL51: ư
B52: 18 | C52: LỢI NHUẬN KHÔNG BAO GỒM KHẤU HAO, LÃI VAY | F52: =F49+F51 -> -3693169948 | G52: =G49+G51 -> -243953152 | H52: =H49+H51 -> -243953152 | I52: =I49+I51 -> -243953152 | J52: =J49+J51 -> -243953152 | K52: =K49+K51 -> -243953152 | L52: =L49+L51 -> 2.057603e+09 | M52: =M49+M51 -> 2.0579977e+09 | ... R52: =R49+R51 -> 2.0579977e+09 | S52: =SUM(G52:R52) -> 1.3185326e+10 | U52: =F52/F$9 -> -1.3895255 | V52: =S52/S$9 -> 0.21177064
B53: 18.1 | C53: % LN không gồm khấu hao/doanh thu | F53: =IFERROR(F52/F$9,0) -> -1.3895255 | G53: =IFERROR(G52/G$9,0) -> 0 | H53: =IFERROR(H52/H$9,0) -> 0 | I53: =IFERROR(I52/I$9,0) -> 0 | J53: =IFERROR(J52/J$9,0) -> 0 | K53: =IFERROR(K52/K$9,0) -> 0 | L53: =IFERROR(L52/L$9,0) -> 0.23133135 | M53: =IFERROR(M52/M$9,0) -> 0.23137572 | ... S53: =IFERROR(S52/S$9,0) -> 0.21177064
B56: Tỷ lệ Hao hụt | F56: =(F17+F18)/F9 -> 0 | G56: =(G17+G18)/G9 -> #DIV/0! | H56: =(H17+H18)/H9 -> #DIV/0! | I56: =(I17+I18)/I9 -> #DIV/0! | J56: =(J17+J18)/J9 -> #DIV/0! | K56: =(K17+K18)/K9 -> #DIV/0! | L56: =(L17+L18)/L9 -> 0.040046098 | M56: =(M17+M18)/M9 -> 0.040046098 | ... S56: =(S17+S18)/S9 -> 0.040046098
B57: 1.Phân loại
B58: 2. Băm

Sheet KQKD Tong hop
R2: =SUM(R24,R30,R41) -> 1.6134987e+10
B3: MỤC TIÊU KẾT QUẢ KINH DOANH NĂM 2026 | F3: ='1.NVL Chai'!H16*11000 -> 9900000000 | G3: ='1.NVL Chai'!I16*11000 -> 7700000000 | H3: ='1.NVL Chai'!J16*11000 -> 11000000000 | I3: ='1.NVL Chai'!K16*11000 -> 12100000000 | J3: ='1.NVL Chai'!L16*11000 -> 12100000000 | K3: ='1.NVL Chai'!M16*11000 -> 12100000000 | L3: ='1.NVL Chai'!N16*11000 -> 12100000000 | M3: ='1.NVL Chai'!O16*11000 -> 12100000000 | ... Q3: ='1.NVL Chai'!S16*11000 -> 12100000000 | R3: ĐVT: Triệu đồng
B4: STT | C4: Mục phí | D4: Thực tế năm 2024 | E4: KQKD 2025 | F4: T1 | G4: T2 | H4: T3 | I4: T4 | J4: T5 | K4: T6 | L4: T7 | M4: T8 | N4: T9 | O4: T10 | P4: T11 | Q4: T12 | R4: KH 2026 | U4: KQKD 2025 | V4: KH 2026 | X4: KQKD 2025 | Y4: KH 2026
B5: 1 | C5: SẢN LƯỢNG BÁN (TẤN) | D5: ='KQKD PET'!E5 -> 0 | E5: ='KQKD PET'!F5 -> 9499913 | F5: =F6+F7+F8 -> 769275 | G5: =G6+G7+G8 -> 598325 | H5: =H6+H7+H8 -> 854750 | I5: =I6+I7+I8 -> 940225 | J5: =J6+J7+J8 -> 939070 | K5: =K6+K7+K8 -> 902770 | L5: =L6+L7+L8 -> 902770 | M5: =M6+M7+M8 -> 902770 | ... Q5: =Q6+Q7+Q8 -> 902770 | R5: =SUM(F5:Q5) -> 10421035 | S5: =R5/E5 -> 1.0969611
B6: 1.1 | C6: Chai PET | D6: ='KQKD PET'!E6 -> 0 | E6: ='KQKD PET'!F6 -> 8083894 | F6: ='KQKD PET'!G6+'KQKD HD'!G6 -> 534375 | G6: ='KQKD PET'!H6+'KQKD HD'!H6 -> 415625 | H6: ='KQKD PET'!I6+'KQKD HD'!I6 -> 593750 | I6: ='KQKD PET'!J6+'KQKD HD'!J6 -> 653125 | J6: ='KQKD PET'!K6+'KQKD HD'!K6 -> 651475 | K6: ='KQKD PET'!L6+'KQKD HD'!L6 -> 64075 | L6: ='KQKD PET'!M6+'KQKD HD'!M6 -> 64075 | M6: ='KQKD PET'!N6+'KQKD HD'!N6 -> 64075 | ... Q6: ='KQKD PET'!R6+'KQKD HD'!R6 -> 64075 | R6: =SUM(F6:Q6) -> 3296875 | S6: =R6/E6 -> 0.40783254
B7: 1.2 | C7: Vảy PET | D7: ='KQKD PET'!E7 -> 0 | E7: ='KQKD PET'!F7 -> 1416019 | F7: ='KQKD PET'!G7+'KQKD HD'!G7 -> 234900 | G7: ='KQKD PET'!H7+'KQKD HD'!H7 -> 182700 | H7: ='KQKD PET'!I7+'KQKD HD'!I7 -> 261000 | I7: ='KQKD PET'!J7+'KQKD HD'!J7 -> 287100 | J7: ='KQKD PET'!K7+'KQKD HD'!K7 -> 287595 | K7: ='KQKD PET'!L7+'KQKD HD'!L7 -> 838695 | L7: ='KQKD PET'!M7+'KQKD HD'!M7 -> 838695 | M7: ='KQKD PET'!N7+'KQKD HD'!N7 -> 838695 | ... Q7: ='KQKD PET'!R7+'KQKD HD'!R7 -> 838695 | R7: =SUM(F7:Q7) -> 7124160 | S7: =R7/E7 -> 5.0311189
B8: 1.3 | C8: Vảy HD | D8: ='KQKD PET'!E8 -> 0 | E8: ='KQKD HD'!F5 -> 215282 | F8: ='KQKD PET'!G8+'KQKD HD'!G8 -> 0 | G8: ='KQKD PET'!H8+'KQKD HD'!H8 -> 0 | H8: ='KQKD PET'!I8+'KQKD HD'!I8 -> 0 | I8: ='KQKD PET'!J8+'KQKD HD'!J8 -> 0 | J8: ='KQKD PET'!K8+'KQKD HD'!K8 -> 0 | K8: ='KQKD PET'!L8+'KQKD HD'!L8 -> 0 | L8: ='KQKD PET'!M8+'KQKD HD'!M8 -> 0 | M8: ='KQKD PET'!N8+'KQKD HD'!N8 -> 0 | ... Q8: ='KQKD PET'!R8+'KQKD HD'!R8 -> 0 | R8: =SUM(F8:Q8) -> 0 | S8: =R8/E8 -> 0
B9: 1.4 | C9: Dây Đai PET | F9: ='KDKD DAY DAI'!G6 -> 0 | G9: ='KDKD DAY DAI'!H6 -> 0 | H9: ='KDKD DAY DAI'!I6 -> 0 | I9: ='KDKD DAY DAI'!J6 -> 0 | J9: ='KDKD DAY DAI'!K6 -> 0 | K9: ='KDKD DAY DAI'!L6 -> 0 | L9: ='KDKD DAY DAI'!M6 -> 0 | M9: ='KDKD DAY DAI'!N6 -> 0 | ... Q9: ='KDKD DAY DAI'!R6 -> 0 | R9: =SUM(F9:Q9) -> 0 | S9: =R9/E9 -> #DIV/0!
B10: 2 | C10: DOANH THU | D10: ='KQKD PET'!E9 -> 64684339330 | E10: ='KQKD PET'!F9+'KQKD HD'!F9 -> 172033486271 | F10: =SUM(F11:F14) -> 11415442500 | G10: =SUM(G11:G14) -> 8878677500 | H10: =SUM(H11:H14) -> 12683825000 | I10: =SUM(I11:I14) -> 13952207500 | J10: =SUM(J11:J14) -> 13934978750 | K10: =SUM(K11:K14) -> 14026113750 | L10: =SUM(L11:L14) -> 14026113750 | M10: =SUM(M11:M14) -> 14026113750 | ... Q10: =SUM(Q11:Q14) -> 14026113750 | R10: =SUM(F10:Q10) -> 159047927500 | S10: =R10/E10 -> 0.92451726 | U10: =E10/E$10 -> 1 | V10: =R10/R$10 -> 1 | X10: =E10/E5 -> 18108.954 | Y10: =R10/R5 -> 15262.201 | Z10: =Y10-X10 -> -2846.7532
B11: 2.1 | C11: Chai PET | D11: ='KQKD PET'!E10 -> 64684339330 | E11: ='KQKD PET'!F10+'KQKD HD'!F10 -> 142921750387 | F11: ='KQKD PET'!G10+'KQKD HD'!G10 -> 7846267500 | G11: ='KQKD PET'!H10+'KQKD HD'!H10 -> 6102652500 | H11: ='KQKD PET'!I10+'KQKD HD'!I10 -> 8718075000 | I11: ='KQKD PET'!J10+'KQKD HD'!J10 -> 9589882500 | J11: ='KQKD PET'!K10+'KQKD HD'!K10 -> 9565132500 | K11: ='KQKD PET'!L10+'KQKD HD'!L10 -> 754132500 | L11: ='KQKD PET'!M10+'KQKD HD'!M10 -> 754132500 | ... Q11: ='KQKD PET'!R10+'KQKD HD'!R10 -> 754132500 | R11: =SUM(F11:Q11) -> 47100937500 | S11: =R11/E11 -> 0.32955752 | U11: =E11/E$10 -> 0.83077867 | V11: =R11/R$10 -> 0.29614304
B12: 2.2 | C12: Vảy PET | D12: ='KQKD PET'!E11 -> 0 | E12: ='KQKD PET'!F11+'KQKD HD'!F11 -> 26453871704 | F12: ='KQKD PET'!G11+'KQKD HD'!G11 -> 3569175000 | G12: ='KQKD PET'!H11+'KQKD HD'!H11 -> 2776025000 | H12: ='KQKD PET'!I11+'KQKD HD'!I11 -> 3965750000 | I12: ='KQKD PET'!J11+'KQKD HD'!J11 -> 4362325000 | J12: ='KQKD PET'!K11+'KQKD HD'!K11 -> 4.3698462e+09 | K12: ='KQKD PET'!L11+'KQKD HD'!L11 -> 13271981250 | L12: ='KQKD PET'!M11+'KQKD HD'!M11 -> 13271981250 | ... Q12: ='KQKD PET'!R11+'KQKD HD'!R11 -> 13271981250 | R12: =SUM(F12:Q12) -> 111946990000 | S12: =R12/E12 -> 4.2317809 | U12: =E12/E$10 -> 0.15377164 | V12: =R12/R$10 -> 0.70385696
B13: 2.3 | C13: Vảy HD | D13: ='KQKD PET'!E12 -> 0 | E13: ='KQKD PET'!F12+'KQKD HD'!F12 -> 2657864180 | F13: ='KQKD PET'!G12+'KQKD HD'!G12 -> 0 | G13: ='KQKD PET'!H12+'KQKD HD'!H12 -> 0 | H13: ='KQKD PET'!I12+'KQKD HD'!I12 -> 0 | I13: ='KQKD PET'!J12+'KQKD HD'!J12 -> 0 | J13: ='KQKD PET'!K12+'KQKD HD'!K12 -> 0 | K13: ='KQKD PET'!L12+'KQKD HD'!L12 -> 0 | L13: ='KQKD PET'!M12+'KQKD HD'!M12 -> 0 | ... Q13: ='KQKD PET'!R12+'KQKD HD'!R12 -> 0 | R13: =SUM(F13:Q13) -> 0 | S13: =R13/E13 -> 0 | U13: =E13/E$10 -> 0.015449691 | V13: =R13/R$10 -> 0
B14: 2.4 | C14: Dây Đai PET | F14: ='KDKD DAY DAI'!G10 -> 0 | G14: ='KDKD DAY DAI'!H10 -> 0 | H14: ='KDKD DAY DAI'!I10 -> 0 | I14: ='KDKD DAY DAI'!J10 -> 0 | J14: ='KDKD DAY DAI'!K10 -> 0 | K14: ='KDKD DAY DAI'!L10 -> 0 | L14: ='KDKD DAY DAI'!M10 -> 0 | M14: ='KDKD DAY DAI'!N10 -> 0 | ... Q14: ='KDKD DAY DAI'!R10 -> 0 | R14: =SUM(F14:Q14) -> 0 | S14: =R14/E14 -> #DIV/0! | U14: =E14/E$10 -> 0 | V14: =R14/R$10 -> 0
B15: 2.4 | C15: Khác | D15: ='KQKD PET'!E13 -> 0 | E15: ='KQKD PET'!F13+'KQKD HD'!F13 -> 0 | F15: ='KQKD PET'!G13+'KQKD HD'!G13 -> 0 | G15: ='KQKD PET'!H13+'KQKD HD'!H13 -> 0 | H15: ='KQKD PET'!I13+'KQKD HD'!I13 -> 0 | I15: ='KQKD PET'!J13+'KQKD HD'!J13 -> 0 | J15: ='KQKD PET'!K13+'KQKD HD'!K13 -> 0 | K15: ='KQKD PET'!L13+'KQKD HD'!L13 -> 0 | L15: ='KQKD PET'!M13+'KQKD HD'!M13 -> 0 | ... Q15: ='KQKD PET'!R13+'KQKD HD'!R13 -> 0 | R15: =SUM(F15:Q15) -> 0 | S15: =R15/E15 -> #DIV/0! | U15: =E15/E$10 -> 0 | V15: =R15/R$10 -> 0
B16: 3 | C16: BIẾN PHÍ | D16: ='KQKD PET'!E14 -> 0 | E16: ='KQKD PET'!F14+'KQKD HD'!F14 -> 1.5515241e+11 | F16: =F17+F25 -> 1.0502036e+10 | G16: =G17+G25 -> 8.1594327e+09 | H16: =H17+H25 -> 1.1570876e+10 | I16: =I17+I25 -> 1.2668823e+10 | J16: =J17+J25 -> 1.2667987e+10 | K16: =K17+K25 -> 1.3136817e+10 | L16: =L17+L25 -> 1.3150287e+10 | M16: =M17+M25 -> 1.3150402e+10 | ... Q16: =Q17+Q25 -> 1.3138282e+10 | R16: =SUM(F16:Q16) -> 1.4754313e+11 | S16: =R16/E16 -> 0.95095612 | U16: =E16/E$10 -> 0.9018733 | V16: =R16/R$10 -> 0.9276646
B17: 3.1 | C17: BIẾN PHÍ SẢN XUẤT | D17: ='KQKD PET'!E15 -> 0 | E17: ='KQKD PET'!F15+'KQKD HD'!F15 -> 1.5199295e+11 | F17: =F18+F22+F23+F24 -> 1.0236868e+10 | G17: =G18+G22+G23+G24 -> 7.9531909e+09 | H17: =H18+H22+H23+H24 -> 1.1276245e+10 | I17: =I18+I22+I23+I24 -> 1.2344729e+10 | J17: =J18+J22+J23+J24 -> 1.2344321e+10 | K17: =K18+K22+K23+K24 -> 1.2845652e+10 | L17: =L18+L22+L23+L24 -> 1.2859122e+10 | M17: =M18+M22+M23+M24 -> 1.2859237e+10 | ... Q17: =Q18+Q22+Q23+Q24 -> 1.2847117e+10 | R17: =SUM(F17:Q17) -> 1.4409118e+11 | S17: =R17/E17 -> 0.94801223 | U17: =E17/E$10 -> 0.88350795 | V17: =R17/R$10 -> 0.90596074
B18: 3.1.1 | C18: Nguyên vật liệu chính (nhựa, gồm hao hụt) | D18: ='KQKD PET'!E16 -> 0 | E18: ='KQKD PET'!F16+'KQKD HD'!F16 -> 141652238906 | F18: ='KQKD PET'!G16+'KQKD HD'!G16+'KDKD DAY DAI'!G16 -> 9121500000 | G18: ='KQKD PET'!H16+'KQKD HD'!H16+'KDKD DAY DAI'!H16 -> 7094500000 | H18: ='KQKD PET'!I16+'KQKD HD'!I16+'KDKD DAY DAI'!I16 -> 10135000000 | I18: ='KQKD PET'!J16+'KQKD HD'!J16+'KDKD DAY DAI'!J16 -> 11148500000 | J18: ='KQKD PET'!K16+'KQKD HD'!K16+'KDKD DAY DAI'!K16 -> 11148500000 | K18: ='KQKD PET'!L16+'KQKD HD'!L16+'KDKD DAY DAI'!L16 -> 11148500000 | L18: ='KQKD PET'!M16+'KQKD HD'!M16+'KDKD DAY DAI'!M16 -> 11148500000 | M18: ='KQKD PET'!N16+'KQKD HD'!N16+'KDKD DAY DAI'!N16 -> 11148500000 | ... Q18: ='KQKD PET'!R16+'KQKD HD'!R16+'KDKD DAY DAI'!R16 -> 11148500000 | R18: =SUM(F18:Q18) -> 126687500000 | S18: =R18/E18 -> 0.89435579 | U18: =E18/E$10 -> 0.82339922 | V18: =R18/R$10 -> 0.79653663
B19: 3.1.2 | C19: Trong đó: i/ Hao hụt CĐ phân loại chai | D19: ='KQKD PET'!E17 -> 0 | E19: ='KQKD PET'!F17 -> 0 | F19: ='KQKD PET'!G17+'KQKD HD'!G17 -> 1060374375 | G19: ='KQKD PET'!H17+'KQKD HD'!H17 -> 824735625 | H19: ='KQKD PET'!I17+'KQKD HD'!I17 -> 1178193750 | I19: ='KQKD PET'!J17+'KQKD HD'!J17 -> 1296013125 | J19: ='KQKD PET'!K17+'KQKD HD'!K17 -> 1.3071616e+09 | K19: ='KQKD PET'!L17+'KQKD HD'!L17 -> 1318310125 | L19: ='KQKD PET'!M17+'KQKD HD'!M17 -> 1318310125 | M19: ='KQKD PET'!N17+'KQKD HD'!N17 -> 1318310125 | ... Q19: ='KQKD PET'!R17+'KQKD HD'!R17 -> 1318310125 | R19: =SUM(F19:Q19) -> 14894649375 | S19: =R19/E19 -> #DIV/0! | U19: =E19/E$10 -> 0 | V19: =R19/R$10 -> 0.093648811
C20: ii/ Hao hụt CĐ băm vảy | D20: ='KQKD PET'!E18 -> 0 | E20: ='KQKD PET'!F18 -> 0 | F20: ='KQKD PET'!G18+'KQKD HD'!G18 -> 264523500 | G20: ='KQKD PET'!H18+'KQKD HD'!H18 -> 205740500 | H20: ='KQKD PET'!I18+'KQKD HD'!I18 -> 293915000 | I20: ='KQKD PET'!J18+'KQKD HD'!J18 -> 323306500 | J20: ='KQKD PET'!K18+'KQKD HD'!K18 -> 3.2386392e+08 | K20: ='KQKD PET'!L18+'KQKD HD'!L18 -> 1036810500 | L20: ='KQKD PET'!M18+'KQKD HD'!M18 -> 1036810500 | M20: ='KQKD PET'!N18+'KQKD HD'!N18 -> 1036810500 | ... Q20: ='KQKD PET'!R18+'KQKD HD'!R18 -> 1036810500 | R20: =SUM(F20:Q20) -> 8669022925 | S20: =R20/E20 -> #DIV/0! | U20: =E20/E$10 -> 0 | V20: =R20/R$10 -> 0.054505727
B21: 3.1.3 | C21: % chi phí nguyên liệu/doanh thu | D21: ='KQKD PET'!E19 -> 0 | E21: =E18/E10 -> 0.82339922 | F21: =F18/F10 -> 0.79904918 | G21: =G18/G10 -> 0.79904918 | H21: =H18/H10 -> 0.79904918 | I21: =I18/I10 -> 0.79904918 | J21: =J18/J10 -> 0.8000371 | K21: =K18/K10 -> 0.79483884 | L21: =L18/L10 -> 0.79483884 | ... R21: =R18/R10 -> 0.79653663 | S21: =R21/E21 -> 0.96737598 | U21: =E21/E$10 -> 4.786273e-12 | V21: =R21/R$10 -> 5.0081547e-12
B22: 3.1.4 | C22: Nguyên vật liệu phụ | D22: ='KQKD PET'!E20 -> 0 | E22: ='KQKD PET'!F20+'KQKD HD'!F20 -> 2.2270037e+09 | F22: ='KQKD PET'!G20+'KQKD HD'!G20+'KDKD DAY DAI'!G20 -> 3.3872006e+08 | G22: ='KQKD PET'!H20+'KQKD HD'!H20+'KDKD DAY DAI'!H20 -> 2.6276782e+08 | H22: ='KQKD PET'!I20+'KQKD HD'!I20+'KDKD DAY DAI'!I20 -> 3.7221767e+08 | I22: ='KQKD PET'!J20+'KQKD HD'!J20+'KDKD DAY DAI'!J20 -> 4.1027929e+08 | J22: ='KQKD PET'!K20+'KQKD HD'!K20+'KDKD DAY DAI'!K20 -> 4.0901892e+08 | K22: ='KQKD PET'!L20+'KQKD HD'!L20+'KDKD DAY DAI'!L20 -> 6.2656057e+08 | L22: ='KQKD PET'!M20+'KQKD HD'!M20+'KDKD DAY DAI'!M20 -> 6.2593724e+08 | M22: ='KQKD PET'!N20+'KQKD HD'!N20+'KDKD DAY DAI'!N20 -> 6.2605224e+08 | ... Q22: ='KQKD PET'!R20+'KQKD HD'!R20+'KDKD DAY DAI'!R20 -> 6.2590224e+08 | R22: =SUM(F22:Q22) -> 6.1763578e+09 | S22: =R22/E22 -> 2.7733936 | U22: =E22/E$10 -> 0.012945176 | V22: =R22/R$10 -> 0.038833312
B23: 3.1.5 | C23: Điện sản xuất | D23: ='KQKD PET'!E21 -> 0 | E23: ='KQKD PET'!F21+'KQKD HD'!F21 -> 1.3782783e+09 | F23: ='KQKD PET'!G21+'KQKD HD'!G21+'KDKD DAY DAI'!G21 -> 1.1475174e+08 | G23: ='KQKD PET'!H21+'KQKD HD'!H21+'KDKD DAY DAI'!H21 -> 89251352 | H23: ='KQKD PET'!I21+'KQKD HD'!I21+'KDKD DAY DAI'!I21 -> 1.2750193e+08 | I23: ='KQKD PET'!J21+'KQKD HD'!J21+'KDKD DAY DAI'!J21 -> 140252125 | J23: ='KQKD PET'!K21+'KQKD HD'!K21+'KDKD DAY DAI'!K21 -> 1.4029475e+08 | K23: ='KQKD PET'!L21+'KQKD HD'!L21+'KDKD DAY DAI'!L21 -> 2.9136324e+08 | L23: ='KQKD PET'!M21+'KQKD HD'!M21+'KDKD DAY DAI'!M21 -> 2.9136324e+08 | M23: ='KQKD PET'!N21+'KQKD HD'!N21+'KDKD DAY DAI'!N21 -> 2.9136324e+08 | ... Q23: ='KQKD PET'!R21+'KQKD HD'!R21+'KDKD DAY DAI'!R21 -> 2.9136324e+08 | R23: =SUM(F23:Q23) -> 2.6515946e+09 | S23: =R23/E23 -> 1.9238456 | U23: =E23/E$10 -> 0.0080116862 | V23: =R23/R$10 -> 0.01667167
B24: 3.1.6 | C24: Nhân công trực tiếp | D24: ='KQKD PET'!E22 -> 0 | E24: ='KQKD PET'!F22+'KQKD HD'!F22 -> 6735431826 | F24: ='KQKD PET'!G22+'KQKD HD'!G22+'KDKD DAY DAI'!G22 -> 6.618961e+08 | G24: ='KQKD PET'!H22+'KQKD HD'!H22+'KDKD DAY DAI'!H22 -> 5.0667176e+08 | H24: ='KQKD PET'!I22+'KQKD HD'!I22+'KDKD DAY DAI'!I22 -> 6.415256e+08 | I24: ='KQKD PET'!J22+'KQKD HD'!J22+'KDKD DAY DAI'!J22 -> 6.4569773e+08 | J24: ='KQKD PET'!K22+'KQKD HD'!K22+'KDKD DAY DAI'!K22 -> 6.4650688e+08 | K24: ='KQKD PET'!L22+'KQKD HD'!L22+'KDKD DAY DAI'!L22 -> 7.7922842e+08 | L24: ='KQKD PET'!M22+'KQKD HD'!M22+'KDKD DAY DAI'!M22 -> 7.9332194e+08 | M24: ='KQKD PET'!N22+'KQKD HD'!N22+'KDKD DAY DAI'!N22 -> 7.9332194e+08 | ... Q24: ='KQKD PET'!R22+'KQKD HD'!R22+'KDKD DAY DAI'!R22 -> 7.8135194e+08 | R24: =SUM(F24:Q24) -> 8.575726e+09 | S24: =R24/E24 -> 1.2732259 | U24: =E24/E$10 -> 0.039151865 | V24: =R24/R$10 -> 0.053919131
B25: 3.2 | C25: BIẾN PHÍ BÁN HÀNG | D25: ='KQKD PET'!E23 -> 0 | E25: ='KQKD PET'!F23+'KQKD HD'!F23 -> 3.1594552e+09 | F25: =F26 -> 265168000 | G25: =G26 -> 2.0624178e+08 | H25: =H26 -> 2.9463111e+08 | I25: =I26 -> 3.2409422e+08 | J25: =J26 -> 3.2366596e+08 | K25: =K26 -> 2.9116462e+08 | L25: =L26 -> 2.9116462e+08 | M25: =M26 -> 2.9116462e+08 | ... Q25: =Q26 -> 2.9116462e+08 | R25: =SUM(F25:Q25) -> 3.4519534e+09 | S25: =R25/E25 -> 1.0925787 | U25: =E25/E$10 -> 0.01836535 | V25: =R25/R$10 -> 0.021703857
C26: Chi phí vận chuyển | D26: ='KQKD PET'!E24 -> 0 | E26: ='KQKD PET'!F24+'KQKD HD'!F24 -> 3.1594552e+09 | F26: ='KQKD PET'!G24+'KQKD HD'!G24+'KDKD DAY DAI'!G24 -> 265168000 | G26: ='KQKD PET'!H24+'KQKD HD'!H24+'KDKD DAY DAI'!H24 -> 2.0624178e+08 | H26: ='KQKD PET'!I24+'KQKD HD'!I24+'KDKD DAY DAI'!I24 -> 2.9463111e+08 | I26: ='KQKD PET'!J24+'KQKD HD'!J24+'KDKD DAY DAI'!J24 -> 3.2409422e+08 | J26: ='KQKD PET'!K24+'KQKD HD'!K24+'KDKD DAY DAI'!K24 -> 3.2366596e+08 | K26: ='KQKD PET'!L24+'KQKD HD'!L24+'KDKD DAY DAI'!L24 -> 2.9116462e+08 | L26: ='KQKD PET'!M24+'KQKD HD'!M24+'KDKD DAY DAI'!M24 -> 2.9116462e+08 | M26: ='KQKD PET'!N24+'KQKD HD'!N24+'KDKD DAY DAI'!N24 -> 2.9116462e+08 | ... Q26: ='KQKD PET'!R24+'KQKD HD'!R24+'KDKD DAY DAI'!R24 -> 2.9116462e+08 | R26: =SUM(F26:Q26) -> 3.4519534e+09 | S26: =R26/E26 -> 1.0925787 | U26: =E26/E$10 -> 0.01836535 | V26: =R26/R$10 -> 0.021703857
B27: 4 | C27: LÃI SAU BIẾN PHÍ | D27: ='KQKD PET'!E25 -> 64684339330 | E27: ='KQKD PET'!F25+'KQKD HD'!F25 -> 1.6881078e+10 | F27: =F10-F16 -> 9.1340661e+08 | G27: =G10-G16 -> 7.1924479e+08 | H27: =H10-H16 -> 1.1129487e+09 | I27: =I10-I16 -> 1.2833841e+09 | J27: =J10-J16 -> 1.2669922e+09 | K27: =K10-K16 -> 8.8929689e+08 | L27: =L10-L16 -> 8.7582671e+08 | M27: =M10-M16 -> 8.7571171e+08 | ... Q27: =Q10-Q16 -> 8.8783171e+08 | R27: =SUM(F27:Q27) -> 1.1504796e+10 | S27: =R27/E27 -> 0.68152019 | U27: =E27/E$10 -> 0.0981267 | V27: =R27/R$10 -> 0.072335402
B28: 4.1 | C28: % lãi biến phí/doanh thu | D28: ='KQKD PET'!E26 -> 0 | E28: =E27/E10 -> 0.0981267 | F28: =F27/F10 -> 0.080014998 | G28: =G27/G10 -> 0.081008099 | H28: =H27/H10 -> 0.08774551 | I28: =I27/I10 -> 0.091984307 | J28: =J27/J10 -> 0.090921721 | K28: =K27/K10 -> 0.063402943 | L28: =L27/L10 -> 0.062442579 | ... R28: =R27/R10 -> 0.072335402 | S28: =R28/E28 -> 0.7371633 | U28: =E28/E$10 -> 5.7039302e-13 | V28: =R28/R$10 -> 4.5480254e-13
B29: 5 | C29: CHI PHÍ SẢN XUẤT CHUNG | D29: ='KQKD PET'!E27 -> 0 | E29: ='KQKD PET'!F27+'KQKD HD'!F27 -> 14281270524 | F29: =F30+F31+F32 -> 9.9822543e+08 | G29: =G30+G31+G32 -> 9.9552543e+08 | H29: =H30+H31+H32 -> 9.9739463e+08 | I29: =I30+I31+I32 -> 9.9701129e+08 | J29: =J30+J31+J32 -> 9.9617796e+08 | K29: =K30+K31+K32 -> 1.0095562e+09 | L29: =L30+L31+L32 -> 1.0081324e+09 | M29: =M30+M31+M32 -> 1.0079824e+09 | ... Q29: =Q30+Q31+Q32 -> 1.0037379e+09 | R29: =SUM(F29:Q29) -> 1.202956e+10 | S29: =R29/E29 -> 0.84233121 | U29: =E29/E$10 -> 0.083014481 | V29: =R29/R$10 -> 0.07563481
B30: 5.1 | C30: Lương gián tiếp Sản xuất | D30: ='KQKD PET'!E28 -> 0 | E30: ='KQKD PET'!F28+'KQKD HD'!F28 -> 4201558148 | F30: ='KQKD PET'!G28+'KQKD HD'!G28+'KDKD DAY DAI'!G28 -> 2.9555265e+08 | G30: ='KQKD PET'!H28+'KQKD HD'!H28+'KDKD DAY DAI'!H28 -> 2.93242e+08 | H30: ='KQKD PET'!I28+'KQKD HD'!I28+'KDKD DAY DAI'!I28 -> 2.7839308e+08 | I30: ='KQKD PET'!J28+'KQKD HD'!J28+'KDKD DAY DAI'!J28 -> 3.0256017e+08 | J30: ='KQKD PET'!K28+'KQKD HD'!K28+'KDKD DAY DAI'!K28 -> 2.8727549e+08 | K30: ='KQKD PET'!L28+'KQKD HD'!L28+'KDKD DAY DAI'!L28 -> 3.1912588e+08 | L30: ='KQKD PET'!M28+'KQKD HD'!M28+'KDKD DAY DAI'!M28 -> 3.1148634e+08 | M30: ='KQKD PET'!N28+'KQKD HD'!N28+'KDKD DAY DAI'!N28 -> 3.1148634e+08 | ... Q30: ='KQKD PET'!R28+'KQKD HD'!R28+'KDKD DAY DAI'!R28 -> 3.1148634e+08 | R30: =SUM(F30:Q30) -> 3.6517897e+09 | S30: =R30/E30 -> 0.86915129 | U30: =E30/E$10 -> 0.024422909 | V30: =R30/R$10 -> 0.02296031
B31: 5.2 | C31: Chi phí thuê xưởng | D31: ='KQKD PET'!E29 -> 0 | E31: ='KQKD PET'!F29+'KQKD HD'!F29 -> 5585152224 | F31: ='KQKD PET'!G29+'KQKD HD'!G29 -> 461679352 | G31: ='KQKD PET'!H29+'KQKD HD'!H29 -> 461679352 | H31: ='KQKD PET'!I29+'KQKD HD'!I29 -> 461679352 | I31: ='KQKD PET'!J29+'KQKD HD'!J29 -> 461679352 | J31: ='KQKD PET'!K29+'KQKD HD'!K29 -> 461679352 | K31: ='KQKD PET'!L29+'KQKD HD'!L29 -> 461679352 | L31: ='KQKD PET'!M29+'KQKD HD'!M29 -> 461679352 | ... Q31: ='KQKD PET'!R29+'KQKD HD'!R29 -> 461679352 | R31: =SUM(F31:Q31) -> 5540152224 | S31: =R31/E31 -> 0.99194292 | U31: =E31/E$10 -> 0.032465495 | V31: =R31/R$10 -> 0.034833225
B32: 5.3 | C32: Chi phí sản xuất (Ngoài lương, BOM, thuê xưởng, khấu hao) | D32: ='KQKD PET'!E30 -> 0 | E32: ='KQKD PET'!F30+'KQKD HD'!F30 -> 4494560152 | F32: ='KQKD PET'!G30+'KQKD HD'!G30+'KDKD DAY DAI'!G30 -> 2.4099343e+08 | G32: ='KQKD PET'!H30+'KQKD HD'!H30+'KDKD DAY DAI'!H30 -> 2.4060409e+08 | H32: ='KQKD PET'!I30+'KQKD HD'!I30+'KDKD DAY DAI'!I30 -> 2.5732219e+08 | I32: ='KQKD PET'!J30+'KQKD HD'!J30+'KDKD DAY DAI'!J30 -> 2.3277177e+08 | J32: ='KQKD PET'!K30+'KQKD HD'!K30+'KDKD DAY DAI'!K30 -> 2.4722312e+08 | K32: ='KQKD PET'!L30+'KQKD HD'!L30+'KDKD DAY DAI'!L30 -> 2.2875094e+08 | L32: ='KQKD PET'!M30+'KQKD HD'!M30+'KDKD DAY DAI'!M30 -> 2.3496668e+08 | M32: ='KQKD PET'!N30+'KQKD HD'!N30+'KDKD DAY DAI'!N30 -> 2.3481668e+08 | ... Q32: ='KQKD PET'!R30+'KQKD HD'!R30+'KDKD DAY DAI'!R30 -> 2.3057223e+08 | R32: =SUM(F32:Q32) -> 2.8376179e+09 | S32: =R32/E32 -> 0.63134496 | U32: =E32/E$10 -> 0.026126077 | V32: =R32/R$10 -> 0.017841276
B33: 6 | C33: CHI PHÍ KHẤU HAO, CCDC | D33: ='KQKD PET'!E31 -> 0 | E33: ='KQKD PET'!F31+'KQKD HD'!F31 -> 7149747121 | F33: ='KQKD PET'!G31+'KQKD HD'!G31 -> 3.8012808e+08 | G33: ='KQKD PET'!H31+'KQKD HD'!H31 -> 3.8262808e+08 | H33: ='KQKD PET'!I31+'KQKD HD'!I31 -> 3.8075889e+08 | I33: ='KQKD PET'!J31+'KQKD HD'!J31 -> 3.8075889e+08 | J33: ='KQKD PET'!K31+'KQKD HD'!K31 -> 3.8159222e+08 | K33: ='KQKD PET'!L31+'KQKD HD'!L31 -> 4.0214083e+08 | L33: ='KQKD PET'!M31+'KQKD HD'!M31 -> 4.0297416e+08 | ... Q33: ='KQKD PET'!R31+'KQKD HD'!R31 -> 4.0700194e+08 | R33: =SUM(F33:Q33) -> 4.7380742e+09 | S33: =R33/E33 -> 0.66269116 | U33: =E33/E$10 -> 0.041560206 | V33: =R33/R$10 -> 0.029790229
B34: 7 | C34: LỢI NHUẬN GỘP | D34: ='KQKD PET'!E32 -> 64684339330 | E34: ='KQKD PET'!F32+'KQKD HD'!F32 -> -4.5499393e+09 | F34: =F27-F29-F33 -> -4.649469e+08 | G34: =G27-G29-G33 -> -6.5890872e+08 | H34: =H27-H29-H33 -> -2.6520482e+08 | I34: =I27-I29-I33 -> -94386044 | J34: =J27-J29-J33 -> -1.1077793e+08 | K34: =K27-K29-K33 -> -5.2240011e+08 | L34: =L27-L29-L33 -> -5.3527982e+08 | M34: =M27-M29-M33 -> -5.3524482e+08 | ... Q34: =Q27-Q29-Q33 -> -5.2290815e+08 | R34: =SUM(F34:Q34) -> -5.2628383e+09 | S34: =R34/E34 -> 1.1566832 | U34: =E34/E$10 -> -0.026447986 | V34: =R34/R$10 -> -0.033089638
B35: 7.1 | C35: % lãi gộp/doanh thu | D35: ='KQKD PET'!E33 -> 0 | E35: =E34/E10 -> -0.026447986 | F35: =F34/F10 -> -0.040729644 | G35: =G34/G10 -> -0.074212485 | H35: =H34/H10 -> -0.0209089 | I35: =I34/I10 -> -0.0067649541 | J35: =J34/J10 -> -0.0079496306 | K35: =K34/K10 -> -0.037244822 | L35: =L34/L10 -> -0.038163088 | ... R35: =R34/R10 -> -0.033089638 | S35: =R35/E35 -> 1.2511212 | U35: =E35/E$10 -> -1.5373743e-13 | V35: =R35/R$10 -> -2.0804822e-13
B36: 8 | C36: CHI PHÍ BÁN HÀNG & MKT & R&D | D36: ='KQKD PET'!E34 -> 0 | E36: ='KQKD PET'!F34+'KQKD HD'!F34 -> 0 | F36: =F37+F38+F39 -> 0 | G36: =G37+G38+G39 -> 0 | H36: =H37+H38+H39 -> 0 | I36: =I37+I38+I39 -> 0 | J36: =J37+J38+J39 -> 0 | K36: =K37+K38+K39 -> 0 | L36: =L37+L38+L39 -> 0 | M36: =M37+M38+M39 -> 0 | ... Q36: =Q37+Q38+Q39 -> 0 | R36: =SUM(F36:Q36) -> 0 | S36: =R36/E36 -> #DIV/0! | U36: =E36/E$10 -> 0 | V36: =R36/R$10 -> 0
B37: 8.1 | C37: Lương | D37: ='KQKD PET'!E35 -> 0 | E37: ='KQKD PET'!F35+'KQKD HD'!F35 -> 0 | F37: ='KQKD PET'!G35+'KQKD HD'!G35+'KDKD DAY DAI'!G35 -> 0 | G37: ='KQKD PET'!H35+'KQKD HD'!H35+'KDKD DAY DAI'!H35 -> 0 | H37: ='KQKD PET'!I35+'KQKD HD'!I35+'KDKD DAY DAI'!I35 -> 0 | I37: ='KQKD PET'!J35+'KQKD HD'!J35+'KDKD DAY DAI'!J35 -> 0 | J37: ='KQKD PET'!K35+'KQKD HD'!K35+'KDKD DAY DAI'!K35 -> 0 | K37: ='KQKD PET'!L35+'KQKD HD'!L35+'KDKD DAY DAI'!L35 -> 0 | L37: ='KQKD PET'!M35+'KQKD HD'!M35+'KDKD DAY DAI'!M35 -> 0 | M37: ='KQKD PET'!N35+'KQKD HD'!N35+'KDKD DAY DAI'!N35 -> 0 | ... Q37: ='KQKD PET'!R35+'KQKD HD'!R35+'KDKD DAY DAI'!R35 -> 0 | R37: =SUM(F37:Q37) -> 0 | S37: =R37/E37 -> #DIV/0! | U37: =E37/E$10 -> 0 | V37: =R37/R$10 -> 0
B38: 8.2 | C38: Chi phí bán hàng (ngoài lương, khấu hao) | D38: ='KQKD PET'!E36 -> 0 | E38: ='KQKD PET'!F36+'KQKD HD'!F36 -> 0 | F38: ='KQKD PET'!G36+'KQKD HD'!G36+'KDKD DAY DAI'!G36 -> 0 | G38: ='KQKD PET'!H36+'KQKD HD'!H36+'KDKD DAY DAI'!H36 -> 0 | H38: ='KQKD PET'!I36+'KQKD HD'!I36+'KDKD DAY DAI'!I36 -> 0 | I38: ='KQKD PET'!J36+'KQKD HD'!J36+'KDKD DAY DAI'!J36 -> 0 | J38: ='KQKD PET'!K36+'KQKD HD'!K36+'KDKD DAY DAI'!K36 -> 0 | K38: ='KQKD PET'!L36+'KQKD HD'!L36+'KDKD DAY DAI'!L36 -> 0 | L38: ='KQKD PET'!M36+'KQKD HD'!M36+'KDKD DAY DAI'!M36 -> 0 | M38: ='KQKD PET'!N36+'KQKD HD'!N36+'KDKD DAY DAI'!N36 -> 0 | ... Q38: ='KQKD PET'!R36+'KQKD HD'!R36+'KDKD DAY DAI'!R36 -> 0 | R38: =SUM(F38:Q38) -> 0 | S38: =R38/E38 -> #DIV/0! | U38: =E38/E$10 -> 0 | V38: =R38/R$10 -> 0
B39: 83 | C39: Khấu hao tài sản | D39: ='KQKD PET'!E37 -> 0 | E39: ='KQKD PET'!F37+'KQKD HD'!F37 -> 0 | F39: ='KQKD PET'!G37+'KQKD HD'!G37+'KDKD DAY DAI'!G37 -> 0 | G39: ='KQKD PET'!H37+'KQKD HD'!H37+'KDKD DAY DAI'!H37 -> 0 | H39: ='KQKD PET'!I37+'KQKD HD'!I37+'KDKD DAY DAI'!I37 -> 0 | I39: ='KQKD PET'!J37+'KQKD HD'!J37+'KDKD DAY DAI'!J37 -> 0 | J39: ='KQKD PET'!K37+'KQKD HD'!K37+'KDKD DAY DAI'!K37 -> 0 | K39: ='KQKD PET'!L37+'KQKD HD'!L37+'KDKD DAY DAI'!L37 -> 0 | L39: ='KQKD PET'!M37+'KQKD HD'!M37+'KDKD DAY DAI'!M37 -> 0 | M39: ='KQKD PET'!N37+'KQKD HD'!N37+'KDKD DAY DAI'!N37 -> 0 | ... Q39: ='KQKD PET'!R37+'KQKD HD'!R37+'KDKD DAY DAI'!R37 -> 0 | R39: =SUM(F39:Q39) -> 0 | S39: =R39/E39 -> #DIV/0! | U39: =E39/E$10 -> 0 | V39: =R39/R$10 -> 0
B40: 9 | C40: CHI PHÍ QUẢN LÝ | D40: ='KQKD PET'!E38 -> 0 | E40: ='KQKD PET'!F38+'KQKD HD'!F38 -> 3999101100 | F40: =F41+F42+F43 -> 5.5745033e+08 | G40: =G41+G42+G43 -> 4.9130588e+08 | H40: =H41+H42+H43 -> 5.2052051e+08 | I40: =I41+I42+I43 -> 5.2535235e+08 | J40: =J41+J42+J43 -> 5.0687739e+08 | K40: =K41+K42+K43 -> 6.696643e+08 | L40: =L41+L42+L43 -> 4.9443744e+08 | M40: =M41+M42+M43 -> 5.2481244e+08 | ... Q40: =Q41+Q42+Q43 -> 4.9472248e+08 | R40: =SUM(F40:Q40) -> 6.2742277e+09 | S40: =R40/E40 -> 1.5689095 | U40: =E40/E$10 -> 0.023246062 | V40: =R40/R$10 -> 0.039448661
B41: 9.1 | C41: Lương | D41: ='KQKD PET'!E39 -> 0 | E41: ='KQKD PET'!F39+'KQKD HD'!F39 -> 2254151653 | F41: ='KQKD PET'!G39+'KQKD HD'!G39 -> 3.2479914e+08 | G41: ='KQKD PET'!H39+'KQKD HD'!H39 -> 3.2569102e+08 | H41: ='KQKD PET'!I39+'KQKD HD'!I39 -> 3.0965466e+08 | I41: ='KQKD PET'!J39+'KQKD HD'!J39 -> 3.3272325e+08 | J41: ='KQKD PET'!K39+'KQKD HD'!K39 -> 3.1993578e+08 | K41: ='KQKD PET'!L39+'KQKD HD'!L39 -> 3.3302825e+08 | L41: ='KQKD PET'!M39+'KQKD HD'!M39 -> 3.2580138e+08 | ... Q41: ='KQKD PET'!R39+'KQKD HD'!R39 -> 3.2549638e+08 | R41: =SUM(F41:Q41) -> 3.9074709e+09 | S41: Chuyển CP lương Bp MH + An toàn: 627 -> 642 | U41: =E41/E$10 -> 0.013102982 | V41: =R41/R$10 -> 0.024567883
B42: 9.2 | C42: Chi phí quản lý (ngoài lương, khấu hao) | D42: ='KQKD PET'!E40 -> 0 | E42: ='KQKD PET'!F40+'KQKD HD'!F40 -> 1658847971 | F42: ='KQKD PET'!G40+'KQKD HD'!G40 -> 2.2404662e+08 | G42: ='KQKD PET'!H40+'KQKD HD'!H40 -> 1.5701029e+08 | H42: ='KQKD PET'!I40+'KQKD HD'!I40 -> 2.0226129e+08 | I42: ='KQKD PET'!J40+'KQKD HD'!J40 -> 1.8402454e+08 | J42: ='KQKD PET'!K40+'KQKD HD'!K40 -> 1.7833704e+08 | K42: ='KQKD PET'!L40+'KQKD HD'!L40 -> 3.2803148e+08 | L42: ='KQKD PET'!M40+'KQKD HD'!M40 -> 1.6003148e+08 | ... Q42: ='KQKD PET'!R40+'KQKD HD'!R40 -> 1.6062153e+08 | R42: =SUM(F42:Q42) -> 2.263502e+09 | S42: PS: lương GĐ | U42: =E42/E$10 -> 0.0096425877 | V42: =R42/R$10 -> 0.014231572
B43: 9.3 | C43: Khấu hao tài sản | D43: ='KQKD PET'!E41 -> 0 | E43: ='KQKD PET'!F41+'KQKD HD'!F41 -> 86101476 | F43: ='KQKD PET'!G41+'KQKD HD'!G41 -> 8604567 | G43: ='KQKD PET'!H41+'KQKD HD'!H41 -> 8604567 | H43: ='KQKD PET'!I41+'KQKD HD'!I41 -> 8604567 | I43: ='KQKD PET'!J41+'KQKD HD'!J41 -> 8604567 | J43: ='KQKD PET'!K41+'KQKD HD'!K41 -> 8604567 | K43: ='KQKD PET'!L41+'KQKD HD'!L41 -> 8604567 | L43: ='KQKD PET'!M41+'KQKD HD'!M41 -> 8604567 | ... Q43: ='KQKD PET'!R41+'KQKD HD'!R41 -> 8604567 | R43: =SUM(F43:Q43) -> 103254804 | S43: =R43/E43 -> 1.1992222 | U43: =E43/E$10 -> 0.00050049254 | V43: =R43/R$10 -> 0.00064920559
B44: 10 | C44: DOANH THU/CHI PHÍ KHÁC | D44: ='KQKD PET'!E42 -> 0 | E44: ='KQKD PET'!F42+'KQKD HD'!F42 -> -14027331 | F44: ='KQKD PET'!G42+'KQKD HD'!G42 -> 0 | G44: ='KQKD PET'!H42+'KQKD HD'!H42 -> 0 | H44: ='KQKD PET'!I42+'KQKD HD'!I42 -> 0 | I44: ='KQKD PET'!J42+'KQKD HD'!J42 -> 0 | J44: ='KQKD PET'!K42+'KQKD HD'!K42 -> 0 | K44: ='KQKD PET'!L42+'KQKD HD'!L42 -> 0 | L44: ='KQKD PET'!M42+'KQKD HD'!M42 -> 0 | ... Q44: ='KQKD PET'!R42+'KQKD HD'!R42 -> 0 | R44: =SUM(F44:Q44) -> 0 | S44: =R44/E44 -> 0 | U44: =E44/E$10 -> -8.1538375e-05 | V44: =R44/R$10 -> 0
B45: 11 | C45: LỢI NHUẬN THUẦN TỪ HOẠT ĐỘNG KINH DOANH | D45: ='KQKD PET'!E43 -> 64684339330 | E45: ='KQKD PET'!F43+'KQKD HD'!F43 -> -8.5630677e+09 | F45: =F34-F36-F40+F44 -> -1.0223972e+09 | G45: =G34-G36-G40+G44 -> -1.1502146e+09 | H45: =H34-H36-H40+H44 -> -7.8572534e+08 | I45: =I34-I36-I40+I44 -> -6.197384e+08 | J45: =J34-J36-J40+J44 -> -6.1765532e+08 | K45: =K34-K36-K40+K44 -> -1.1920644e+09 | L45: =L34-L36-L40+L44 -> -1.0297173e+09 | M45: =M34-M36-M40+M44 -> -1.0600573e+09 | ... Q45: =Q34-Q36-Q40+Q44 -> -1.0176306e+09 | R45: =SUM(F45:Q45) -> -1.1537066e+10 | S45: =R45/E45 -> 1.3473052 | U45: =E45/E$10 -> -0.049775587 | V45: =R45/R$10 -> -0.072538298
B46: 12 | C46: DOANH THU TÀI CHÍNH | D46: ='KQKD PET'!E44 -> 0 | E46: ='KQKD PET'!F44+'KQKD HD'!F44 -> 0 | F46: ='KQKD PET'!G44+'KQKD HD'!G44 -> 0 | G46: ='KQKD PET'!H44+'KQKD HD'!H44 -> 0 | H46: ='KQKD PET'!I44+'KQKD HD'!I44 -> 0 | I46: ='KQKD PET'!J44+'KQKD HD'!J44 -> 0 | J46: ='KQKD PET'!K44+'KQKD HD'!K44 -> 0 | K46: ='KQKD PET'!L44+'KQKD HD'!L44 -> 0 | L46: ='KQKD PET'!M44+'KQKD HD'!M44 -> 0 | ... Q46: ='KQKD PET'!R44+'KQKD HD'!R44 -> 0 | R46: =SUM(F46:Q46) -> 0 | S46: =R46/E46 -> #DIV/0! | U46: =E46/E$10 -> 0 | V46: =R46/R$10 -> 0
B47: 13 | C47: CHI PHÍ TÀI CHÍNH | D47: ='KQKD PET'!E45 -> 0 | E47: ='KQKD PET'!F45+'KQKD HD'!F45 -> 0 | F47: ='KQKD PET'!G45+'KQKD HD'!G45 -> 0 | G47: ='KQKD PET'!H45+'KQKD HD'!H45 -> 0 | H47: ='KQKD PET'!I45+'KQKD HD'!I45 -> 0 | I47: ='KQKD PET'!J45+'KQKD HD'!J45 -> 0 | J47: ='KQKD PET'!K45+'KQKD HD'!K45 -> 0 | K47: ='KQKD PET'!L45+'KQKD HD'!L45 -> 0 | L47: ='KQKD PET'!M45+'KQKD HD'!M45 -> 0 | ... Q47: ='KQKD PET'!R45+'KQKD HD'!R45 -> 0 | R47: =SUM(F47:Q47) -> 0 | S47: =R47/E47 -> #DIV/0! | U47: =E47/E$10 -> 0 | V47: =R47/R$10 -> 0
B48: 13.1 | C48: Trong đó: chi phí lãi vay | D48: ='KQKD PET'!E46 -> 0 | E48: ='KQKD PET'!F46+'KQKD HD'!F46 -> 0 | F48: ='KQKD PET'!G46+'KQKD HD'!G46 -> 0 | G48: ='KQKD PET'!H46+'KQKD HD'!H46 -> 0 | H48: ='KQKD PET'!I46+'KQKD HD'!I46 -> 0 | I48: ='KQKD PET'!J46+'KQKD HD'!J46 -> 0 | J48: ='KQKD PET'!K46+'KQKD HD'!K46 -> 0 | K48: ='KQKD PET'!L46+'KQKD HD'!L46 -> 0 | L48: ='KQKD PET'!M46+'KQKD HD'!M46 -> 0 | ... Q48: ='KQKD PET'!R46+'KQKD HD'!R46 -> 0 | R48: =SUM(F48:Q48) -> 0 | S48: =R48/E48 -> #DIV/0! | U48: =E48/E$10 -> 0 | V48: =R48/R$10 -> 0
B49: 14 | C49: LỢI NHUẬN TRƯỚC THUẾ | D49: ='KQKD PET'!E47 -> 64684339330 | E49: ='KQKD PET'!F47+'KQKD HD'!F47 -> -8.5630677e+09 | F49: =F45+F46-F47 -> -1.0223972e+09 | G49: =G45+G46-G47 -> -1.1502146e+09 | H49: =H45+H46-H47 -> -7.8572534e+08 | I49: =I45+I46-I47 -> -6.197384e+08 | J49: =J45+J46-J47 -> -6.1765532e+08 | K49: =K45+K46-K47 -> -1.1920644e+09 | L49: =L45+L46-L47 -> -1.0297173e+09 | M49: =M45+M46-M47 -> -1.0600573e+09 | ... Q49: =Q45+Q46-Q47 -> -1.0176306e+09 | R49: =SUM(F49:Q49) -> -1.1537066e+10 | S49: =R49/E49 -> 1.3473052 | U49: =E49/E$10 -> -0.049775587 | V49: =R49/R$10 -> -0.072538298
B50: 15 | C50: THUẾ TNDN | D50: ='KQKD PET'!E48 -> 0 | E50: ='KQKD PET'!F48+'KQKD HD'!F48 -> 0 | R50: =SUM(F50:Q50) -> 0 | S50: =R50/E50 -> #DIV/0! | U50: =E50/E$10 -> 0 | V50: =R50/R$10 -> 0
B51: 16 | C51: LỢI NHUẬN SAU THUẾ | D51: ='KQKD PET'!E49 -> 64684339330 | E51: ='KQKD PET'!F49+'KQKD HD'!F49 -> -8.5630677e+09 | F51: =F49-F50 -> -1.0223972e+09 | G51: =G49-G50 -> -1.1502146e+09 | H51: =H49-H50 -> -7.8572534e+08 | I51: =I49-I50 -> -6.197384e+08 | J51: =J49-J50 -> -6.1765532e+08 | K51: =K49-K50 -> -1.1920644e+09 | L51: =L49-L50 -> -1.0297173e+09 | M51: =M49-M50 -> -1.0600573e+09 | ... Q51: =Q49-Q50 -> -1.0176306e+09 | R51: =SUM(F51:Q51) -> -1.1537066e+10 | S51: =R51/E51 -> 1.3473052 | U51: =E51/E$10 -> -0.049775587 | V51: =R51/R$10 -> -0.072538298
B52: 16.1 | C52: % LNST/doanh thu | D52: ='KQKD PET'!E50 -> 0.38189876 | E52: =E51/E10 -> -0.049775587 | F52: =F51/F10 -> -0.089562646 | G52: =G51/G10 -> -0.12954796 | H52: =H51/H10 -> -0.061947034 | I52: =I51/I10 -> -0.044418663 | J52: =J51/J10 -> -0.044324095 | K52: =K51/K10 -> -0.084988931 | L52: =L51/L10 -> -0.073414295 | ... R52: =R51/R10 -> -0.072538298 | S52: =R52/E52 -> 1.4573067 | U52: =E52/E$10 -> -2.8933662e-13 | V52: =R52/R$10 -> -4.5607824e-13
B53: 17 | C53: Khấu hao tài sản | D53: ='KQKD PET'!E51 -> 0 | E53: ='KQKD PET'!F51+'KQKD HD'!F51 -> 7235848597 | F53: ='KQKD PET'!G51+'KQKD HD'!G51 -> 3.8012808e+08 | G53: ='KQKD PET'!H51+'KQKD HD'!H51 -> 3.8012808e+08 | H53: ='KQKD PET'!I51+'KQKD HD'!I51 -> 3.7756444e+08 | I53: ='KQKD PET'!J51+'KQKD HD'!J51 -> 3.7756444e+08 | J53: ='KQKD PET'!K51+'KQKD HD'!K51 -> 3.7756444e+08 | K53: ='KQKD PET'!L51+'KQKD HD'!L51 -> 3.9492555e+08 | L53: ='KQKD PET'!M51+'KQKD HD'!M51 -> 3.9492555e+08 | ... Q53: ='KQKD PET'!R51+'KQKD HD'!R51 -> 3.9492555e+08 | R53: =SUM(F53:Q53) -> 4.6574284e+09 | S53: =R53/E53 -> 0.64366028 | U53: =E53/E$10 -> 0.042060698 | V53: =R53/R$10 -> 0.029283175
B54: 18 | C54: LỢI NHUẬN KHÔNG BAO GỒM KHẤU HAO, LÃI VAY | D54: ='KQKD PET'!E52 -> 64684339330 | E54: ='KQKD PET'!F52+'KQKD HD'!F52 -> -1.3272191e+09 | F54: =F51+F53 -> -6.4226915e+08 | G54: =G51+G53 -> -7.7008652e+08 | H54: =H51+H53 -> -4.081609e+08 | I54: =I51+I53 -> -2.4217396e+08 | J54: =J51+J53 -> -2.4009088e+08 | K54: =K51+K53 -> -7.9713885e+08 | L54: =L51+L53 -> -6.347917e+08 | M54: =M51+M53 -> -6.651317e+08 | ... Q54: =Q51+Q53 -> -6.2270507e+08 | R54: =SUM(F54:Q54) -> -6.8796376e+09 | S54: =R54/E54 -> 5.1834979 | U54: =E54/E$10 -> -0.0077148883 | V54: =R54/R$10 -> -0.043255123
B55: 18.1 | C55: % LN không gồm khấu hao/doanh thu | D55: ='KQKD PET'!E53 -> 2.2547445e-12 | E55: =E54/E10 -> -0.0077148883 | F55: =F54/F10 -> -0.056263185 | G55: =G54/G10 -> -0.086734372 | H55: =H54/H10 -> -0.032179638 | I55: =I54/I10 -> -0.017357393 | J55: =J54/J10 -> -0.017229368 | K55: =K54/K10 -> -0.056832482 | L55: =L54/L10 -> -0.045257846 | ... R55: =R54/R10 -> -0.043255123 | S55: =R55/E55 -> 5.6067076 | U55: =E55/E$10 -> -4.4845271e-14 | V55: =R55/R$10 -> -2.7196282e-13
S56: =R56/E56 -> #DIV/0!
B58: 1. Hòa vốn (Bao gồm khấu hao) | D58: =D4 -> Thực tế năm 2024 | E58: =E4 -> KQKD 2025 | F58: =F4 -> T1 | G58: =G4 -> T2 | H58: =H4 -> T3 | I58: =I4 -> T4 | J58: =J4 -> T5 | K58: =K4 -> T6 | ... R58: =R4 -> KH 2026
B59: Sản lượng NVL hòa vốn (tấn) | D59: =IFERROR(D$60*(1+(D$19+D$20)/D$18),0) -> 0 | E59: =IFERROR(E$60*(1+(E$19+E$20)/E$18),0) -> 14310929 | F59: =F$60*(1+(F$19+F$20)/F$18) -> 1867149.6 | G59: =G$60*(1+(G$19+G$20)/G$18) -> 1781052.7 | H59: =H$60*(1+(H$19+H$20)/H$18) -> 1669993.1 | I59: =I$60*(1+(I$19+I$20)/I$18) -> 1596769.3 | J59: =J$60*(1+(J$19+J$20)/J$18) -> 1601225.3 | K59: =K$60*(1+(K$19+K$20)/K$18) -> 2559243.5 | L59: =L$60*(1+(L$19+L$20)/L$18) -> 2379094.5 | M59: =M$60*(1+(M$19+M$20)/M$18) -> 2417148.2 | ... R59: =R$60*(1+(R$19+R$20)/R$18) -> 24753329
B60: Sản lượng thành phẩm hòa vốn (tấn) | D60: =IFERROR((D$29+D$33+D$36+D$40)/(D$27/D$5),0) -> 0 | E60: =IFERROR((E$29+E$33+E$36+E$40)/(E$27/E$5),0) -> 14310929 | F60: =(F$29+F$33+F$36+F$40)/(F$27/F$5) -> 1630342.4 | G60: =(G$29+G$33+G$36+G$40)/(G$27/G$5) -> 1555165 | H60: =(H$29+H$33+H$36+H$40)/(H$27/H$5) -> 1458190.9 | I60: =(I$29+I$33+I$36+I$40)/(I$27/I$5) -> 1394253.9 | J60: =(J$29+J$33+J$36+J$40)/(J$27/J$5) -> 1396864.1 | K60: =(K$29+K$33+K$36+K$40)/(K$27/K$5) -> 2112894.5 | L60: =(L$29+L$33+L$36+L$40)/(L$27/L$5) -> 1964164.7 | M60: =(M$29+M$33+M$36+M$40)/(M$27/M$5) -> 1995581.6 | ... R60: =(R$29+R$33+R$36+R$40)/(R$27/R$5) -> 20871300
B61: Doanh thu hòa vốn (triệu đồng) | D61: =IFERROR(D$60*(D$10/D$5),0) -> 0 | E61: =IFERROR(E$60*(E$10/E$5),0) -> 2.5915596e+11 | F61: =F$60*(F$10/F$5) -> 2.4193012e+10 | G61: =G$60*(G$10/G$5) -> 2.3077438e+10 | H61: =H$60*(H$10/H$5) -> 2.1638418e+10 | I61: =I$60*(I$10/I$5) -> 2.0689644e+10 | J61: =J$60*(J$10/J$5) -> 2.0728244e+10 | K61: =K$60*(K$10/K$5) -> 3.2827519e+10 | L61: =L$60*(L$10/L$5) -> 3.051674e+10 | M61: =M$60*(M$10/M$5) -> 3.1004856e+10 | ... R61: =R$60*(R$10/R$5) -> 3.1854198e+11
B62: 2. Hòa vốn (Không bao gồm khấu hao) | D62: =D58 -> Thực tế năm 2024 | E62: =E58 -> KQKD 2025 | F62: =F58 -> T1 | G62: =G58 -> T2 | H62: =H58 -> T3 | I62: =I58 -> T4 | J62: =J58 -> T5 | K62: =K58 -> T6 | ... R62: =R58 -> KH 2026
B63: Sản lượng NVL hòa vốn (tấn) | D63: =IFERROR(D$64*(1+(D$19+D$20)/D$18),0) -> 0 | E63: =IFERROR(E$64*(1+(E$19+E$20)/E$18),0) -> 10238918 | F63: =F$64*(1+(F$19+F$20)/F$18) -> 1500503 | G63: =G$64*(1+(G$19+G$20)/G$18) -> 1418900.8 | H63: =H$64*(1+(H$19+H$20)/H$18) -> 1337903.4 | I63: =I$64*(1+(I$19+I$20)/I$18) -> 1279982.9 | J63: =J$64*(1+(J$19+J$20)/J$18) -> 1280440.8 | K63: =K$64*(1+(K$19+K$20)/K$18) -> 2073642.7 | L63: =L$64*(1+(L$19+L$20)/L$18) -> 1886025.2 | M63: =M$64*(1+(M$19+M$20)/M$18) -> 1924014.1 | ... R63: =R$64*(1+(R$19+R$20)/R$18) -> 19749963
B64: Sản lượng thành phẩm hòa vốn (tấn) | D64: =IFERROR((D$29+D$33+D$36+D$40-D53)/(D$27/D$5),0) -> 0 | E64: =IFERROR((E$29+E$33+E$36+E$40-E53)/(E$27/E$5),0) -> 10238918 | F64: =(F$29+F$33+F$36+F$40-F53)/(F$27/F$5) -> 1310196.9 | G64: =(G$29+G$33+G$36+G$40-G53)/(G$27/G$5) -> 1238944.2 | H64: =(H$29+H$33+H$36+H$40-H53)/(H$27/H$5) -> 1168219.6 | I64: =(I$29+I$33+I$36+I$40-I53)/(I$27/I$5) -> 1117645 | J64: =(J$29+J$33+J$36+J$40-J53)/(J$27/J$5) -> 1117020.7 | K64: =(K$29+K$33+K$36+K$40-K53)/(K$27/K$5) -> 1711985.7 | L64: =(L$29+L$33+L$36+L$40-L53)/(L$27/L$5) -> 1557090 | M64: =(M$29+M$33+M$36+M$40-M53)/(M$27/M$5) -> 1588453.4 | ... R64: =(R$29+R$33+R$36+R$40-R53)/(R$27/R$5) -> 16652605
B65: Doanh thu hòa vốn (triệu đồng) | D65: =IFERROR(D$64*(D$10/D$5),0) -> 0 | E65: =IFERROR(E$64*(E$10/E$5),0) -> 1.854161e+11 | F65: =F$64*(F$10/F$5) -> 1.9442302e+10 | G65: =G$64*(G$10/G$5) -> 1.8384968e+10 | H65: =H$64*(H$10/H$5) -> 1.7335469e+10 | I65: =I$64*(I$10/I$5) -> 1.6584982e+10 | J65: =J$64*(J$10/J$5) -> 1.6575612e+10 | K65: =K$64*(K$10/K$5) -> 2.6598698e+10 | L65: =L$64*(L$10/L$5) -> 2.4192121e+10 | M65: =M$64*(M$10/M$5) -> 2.4679406e+10 | ... R65: =R$64*(R$10/R$5) -> 2.5415541e+11

Sheet 1.NVL Chai
B1: Logo CTY
B3: NHU CẦU MUA NGUYÊN VẬT LIỆU CHAI
B4: 1. Số lượng | H4: =SUM(H13:H14)/1000 -> 855 | I4: =SUM(I13:I14)/1000 -> 665 | J4: =SUM(J13:J14)/1000 -> 950 | K4: =SUM(K13:K14)/1000 -> 1045 | L4: =SUM(L13:L14)/1000 -> 1045 | M4: =SUM(M13:M14)/1000 -> 1045 | N4: =SUM(N13:N14)/1000 -> 1045 | O4: =SUM(O13:O14)/1000 -> 1045 | ... S4: =SUM(S13:S14)/1000 -> 1045
B5: STT | C5: Loại chai nguyên liệu | D5: ĐVT | E5: Thực tế năm 2023 | F5: Thực tế năm 2024 | G5: KQKD 2025 | H5: T1 | I5: T2 | J5: T3 | K5: T4 | L5: T5 | M5: T6 | N5: T7 | O5: T8 | P5: T9 | Q5: T10 | R5: T11 | S5: T12 | T5: KH 2026
B6: i. Tỷ lệ chai
B7: 1 | C7: Chai B0 - Xá tròn | D7: % | G7: =G13/$G$16 -> 0.24307792 | H7: 0.45 | I7: 0.45 | J7: 0.45 | K7: 0.45 | L7: 0.4 | M7: 0.35 | N7: 0.35 | O7: 0.35 | P7: 0.35 | Q7: 0.35 | R7: 0.35 | S7: 0.35 | T7: 0.45
B8: 2 | C8: Chai B0 - Ép kiện | D8: % | G8: =G14/$G$16 -> 0.53610583 | H8: =H10-H7-H9 -> 0.5 | I8: =I10-I7-I9 -> 0.5 | J8: =J10-J7-J9 -> 0.5 | K8: =K10-K7-K9 -> 0.5 | L8: =L10-L7-L9 -> 0.55 | M8: =M10-M7-M9 -> 0.6 | N8: =N10-N7-N9 -> 0.6 | O8: =O10-O7-O9 -> 0.6 | ... T8: =T10-T7-T9 -> 0.5
B9: 3 | C9: Chai B1.4 (xô tuyển -> ép kiện) | D9: % | G9: =G15/$G$16 -> 0.22081626 | H9: 0.05 | I9: 0.05 | J9: 0.05 | K9: 0.05 | L9: 0.05 | M9: 0.05 | N9: 0.05 | O9: 0.05 | P9: 0.05 | Q9: 0.05 | R9: 0.05 | S9: 0.05 | T9: 0.05
C10: Tổng: | E10: =E7+E8+E9 -> 0 | F10: =F7+F8+F9 -> 0 | G10: =G7+G8+G9 -> 1 | H10: 1 | I10: 1 | J10: 1 | K10: 1 | L10: 1 | M10: 1 | N10: 1 | O10: 1 | P10: 1 | Q10: 1 | R10: 1 | S10: 1 | T10: 1
B12: ii Số lượng chai | V12: Trạm | W12: Tổng mua / Năm | X12: Tổng mua / Tháng
B13: 1 | C13: Chai B0 - Xá tròn | D13: Tấn | G13: 2584077 | H13: =H7*H$16 -> 405000 | I13: =I7*I$16 -> 315000 | J13: =J7*J$16 -> 450000 | K13: =K7*K$16 -> 495000 | L13: =L7*L$16 -> 440000 | M13: =M7*M$16 -> 385000 | N13: =N7*N$16 -> 385000 | O13: =O7*O$16 -> 385000 | ... S13: =S7*S$16 -> 385000 | T13: =SUM(H13:S13) -> 4800000 | V13: Đại Lộc | W13: 13200000 | X13: =W13/12 -> 1100000
B14: 2 | C14: Chai B0 - Ép kiện | D14: Tấn | G14: 5699155 | H14: =H8*H$16 -> 450000 | I14: =I8*I$16 -> 350000 | J14: =J8*J$16 -> 500000 | K14: =K8*K$16 -> 550000 | L14: =L8*L$16 -> 605000 | M14: =M8*M$16 -> 660000 | N14: =N8*N$16 -> 660000 | O14: =O8*O$16 -> 660000 | ... S14: =S8*S$16 -> 660000 | T14: =SUM(H14:S14) -> 7075000 | V14: Khánh Nga | W14: 7800000 | X14: =W14/12 -> 650000
B15: 3 | C15: Chai B1.4 (xô tuyển -> ép kiện) | D15: Tấn | G15: 2347421 | H15: =H9*H$16 -> 45000 | I15: =I9*I$16 -> 35000 | J15: =J9*J$16 -> 50000 | K15: =K9*K$16 -> 55000 | L15: =L9*L$16 -> 55000 | M15: =M9*M$16 -> 55000 | N15: =N9*N$16 -> 55000 | O15: =O9*O$16 -> 55000 | ... S15: =S9*S$16 -> 55000 | T15: =SUM(H15:S15) -> 625000 | V15: Đồng Lâm | W15: 9000000 | X15: =W15/12 -> 750000
C16: Tổng: | D16: Tấn | G16: 10630653 | H16: 900000 | I16: 700000 | J16: 1000000 | K16: 1100000 | L16: 1100000 | M16: 1100000 | N16: 1100000 | O16: 1100000 | P16: 1100000 | Q16: 1100000 | R16: 1100000 | S16: 1100000 | T16: =SUM(H16:S16) -> 12500000 | U16: <= Nhập sản lượng | V16: TỔNG CỘNG | W16: =SUM(W13:W15) -> 30000000 | X16: =SUM(X13:X15) -> 2500000
H17: =H16/1000 -> 900 | I17: =I16/1000 -> 700 | J17: =J16/1000 -> 1000 | K17: =K16/1000 -> 1100 | L17: =L16/1000 -> 1100 | M17: =M16/1000 -> 1100 | N17: =N16/1000 -> 1100 | O17: =O16/1000 -> 1100 | ... S17: =S16/1000 -> 1100
B18: iii Số lượng và giá trị mua vảy HD
B19: 1 | C19: Lượng mua NVL vảy HD | D19: Tấn | T19: =SUM(H19:S19) -> 0
B20: 2 | C20: Giá mua vảy HD | D20: Đồng/kg
B21: 3 | C21: Tổng giá trị HD | D21: Triệu đ | E21: =E19*E20 -> 0 | F21: =F19*F20 -> 0 | G21: =G19*G20 -> 0 | H21: =H19*H20 -> 0 | I21: =I19*I20 -> 0 | J21: =J19*J20 -> 0 | K21: =K19*K20 -> 0 | L21: =L19*L20 -> 0 | ... S21: =S19*S20 -> 0 | T21: =SUM(H21:S21) -> 0
B23: 2. Giá mua
B24: STT | C24: Loại chai nguyên liệu | D24: ĐVT | E24: Thực tế năm 2023 | F24: Thực tế năm 2024 | G24: KQKD 2025 | H24: T1 | I24: T2 | J24: T3 | K24: T4 | L24: T5 | M24: T6 | N24: T7 | O24: T8 | P24: T9 | Q24: T10 | R24: T11 | S24: T12 | T24: KH 2026
B25: 1 | C25: Chai B0 - Xá tròn | D25: Đồng/kg | H25: =H26+H27 -> 10000 | I25: =I26+I27 -> 10000 | J25: =J26+J27 -> 10000 | K25: =K26+K27 -> 10000 | L25: =L26+L27 -> 10000 | M25: =M26+M27 -> 10000 | N25: =N26+N27 -> 10000 | O25: =O26+O27 -> 10000 | ... T25: =T26+T27 -> 0
B26: a | C26: Giá chai | H26: 10000 | I26: =H26 -> 10000 | J26: =I26 -> 10000 | K26: =J26 -> 10000 | L26: =K26 -> 10000 | M26: =L26 -> 10000 | N26: =M26 -> 10000 | O26: =N26 -> 10000 | P26: =O26 -> 10000 | ... S26: =R26 -> 10000
B27: b | C27: Chi phí mua (các chính sách mua hàng)
B28: 2 | C28: Chai B0 - Ép kiện | D28: Đồng/kg | H28: =H29+H30 -> 10000 | I28: =I29+I30 -> 10000 | J28: =J29+J30 -> 10000 | K28: =K29+K30 -> 10000 | L28: =L29+L30 -> 10000 | M28: =M29+M30 -> 10000 | N28: =N29+N30 -> 10000 | O28: =O29+O30 -> 10000 | ... T28: =T29+T30 -> 0
B29: a | C29: Giá chai | H29: =H26 -> 10000 | I29: =I26 -> 10000 | J29: =J26 -> 10000 | K29: =K26 -> 10000 | L29: =L26 -> 10000 | M29: =M26 -> 10000 | N29: =N26 -> 10000 | O29: =O26 -> 10000 | ... S29: =S26 -> 10000
B30: b | C30: Chi phí mua (các chính sách mua hàng)
B31: 3 | C31: Chai B1.4 (xô tuyển) | D31: Đồng/kg | E31: =E32+E33 -> 0 | F31: =F32+F33 -> 0 | G31: =G32+G33 -> 0 | H31: =H32+H33 -> 12700 | I31: =I32+I33 -> 12700 | J31: =J32+J33 -> 12700 | K31: =K32+K33 -> 12700 | L31: =L32+L33 -> 12700 | ... T31: =T32+T33 -> 0
B32: a | C32: Giá chai | H32: 12700 | I32: =H32 -> 12700 | J32: =I32 -> 12700 | K32: =J32 -> 12700 | L32: =K32 -> 12700 | M32: =L32 -> 12700 | N32: =M32 -> 12700 | O32: =N32 -> 12700 | P32: =O32 -> 12700 | ... S32: =R32 -> 12700
B33: b | C33: Chi phí mua (các chính sách mua hàng)
C34: Giá mua bình quân | D34: Đồng/kg | H34: =H42/H16 -> 10135 | I34: =I42/I16 -> 10135 | J34: =J42/J16 -> 10135 | K34: =K42/K16 -> 10135 | L34: =L42/L16 -> 10135 | M34: =M42/M16 -> 10135 | N34: =N42/N16 -> 10135 | O34: =O42/O16 -> 10135 | ... S34: =S42/S16 -> 10135
B36: 3. Tổng giá trị mua
B37: STT | C37: Loại chai nguyên liệu | D37: ĐVT | E37: Thực tế năm 2023 | F37: Thực tế năm 2024 | G37: KQKD 2025 | H37: T1 | I37: T2 | J37: T3 | K37: T4 | L37: T5 | M37: T6 | N37: T7 | O37: T8 | P37: T9 | Q37: T10 | R37: T11 | S37: T12 | T37: KH 2026
B38: 1 | C38: Chai B0 - Xá tròn | D38: Triệu đ | H38: =H$13*H$25 -> 4050000000 | I38: =I$13*I$25 -> 3150000000 | J38: =J$13*J$25 -> 4500000000 | K38: =K$13*K$25 -> 4950000000 | L38: =L$13*L$25 -> 4400000000 | M38: =M$13*M$25 -> 3850000000 | N38: =N$13*N$25 -> 3850000000 | O38: =O$13*O$25 -> 3850000000 | ... S38: =S$13*S$25 -> 3850000000 | T38: =SUM(H38:S38) -> 48000000000
B39: 2 | C39: Chai B0 - Ép kiện | D39: Triệu đ | H39: =H$14*H$28 -> 4500000000 | I39: =I$14*I$28 -> 3500000000 | J39: =J$14*J$28 -> 5000000000 | K39: =K$14*K$28 -> 5500000000 | L39: =L$14*L$28 -> 6.05e+09 | M39: =M$14*M$28 -> 6600000000 | N39: =N$14*N$28 -> 6600000000 | O39: =O$14*O$28 -> 6600000000 | ... S39: =S$14*S$28 -> 6600000000 | T39: =SUM(H39:S39) -> 70750000000
B40: 3 | C40: Chai B1.4 (xô tuyển -> ép kiện) | D40: Triệu đ | H40: =H$15*H$31 -> 571500000 | I40: =I$15*I$31 -> 444500000 | J40: =J$15*J$31 -> 635000000 | K40: =K$15*K$31 -> 698500000 | L40: =L$15*L$31 -> 698500000 | M40: =M$15*M$31 -> 698500000 | N40: =N$15*N$31 -> 698500000 | O40: =O$15*O$31 -> 698500000 | ... S40: =S$15*S$31 -> 698500000 | T40: =SUM(H40:S40) -> 7937500000
T41: =SUM(H41:S41) -> 0
C42: Tổng: | D42: Triệu đ | E42: =SUM(E38:E41) -> 0 | F42: =SUM(F38:F41) -> 0 | G42: =SUM(G38:G41) -> 0 | H42: =SUM(H38:H41) -> 9121500000 | I42: =SUM(I38:I41) -> 7094500000 | J42: =SUM(J38:J41) -> 10135000000 | K42: =SUM(K38:K41) -> 11148500000 | L42: =SUM(L38:L41) -> 11148500000 | ... S42: =SUM(S38:S41) -> 11148500000 | T42: =SUM(H42:S42) -> 126687500000
B44: 4. Hiệu suất máy (1ca 8giờ x 4ca 1 ngày x 30 ngày 1 tháng)
B45: STT | C45: Loại chai nguyên liệu | D45: ĐVT | E45: Thực tế năm 2023 | F45: Thực tế năm 2024 | G45: KQKD 2025 | H45: T1 | I45: T2 | J45: T3 | K45: T4 | L45: T5 | M45: T6 | N45: T7 | O45: T8 | P45: T9 | Q45: T10 | R45: T11 | S45: T12 | T45: KH 2026
B46: i | C46: Hiệu suất máy - Tính trên NVL đầu vào | H46: =H47/H48 -> 0.75719334 | I46: =I47/I48 -> 0.58892815 | J46: =J47/J48 -> 0.84132593 | K46: =K47/K48 -> 0.92545852 | L46: =L47/L48 -> 0.92545852 | M46: =M47/M48 -> 0.92545852 | N46: =N47/N48 -> 0.92545852 | O46: =O47/O48 -> 0.92545852 | ... T46: =T47/T48 -> 0.87638118
B47: 1 | C47: Tổng sản lượng chai mua vào | D47: Tấn | H47: =H16 -> 900000 | I47: =I16 -> 700000 | J47: =J16 -> 1000000 | K47: =K16 -> 1100000 | L47: =L16 -> 1100000 | M47: =M16 -> 1100000 | N47: =N16 -> 1100000 | O47: =O16 -> 1100000 | ... S47: =S16 -> 1100000 | T47: =SUM(H47:S47) -> 12500000
