Workbook
Name _1: #REF!
Name _1: #REF!
Name _2: #REF!
Name _2: #REF!
Name _3: #REF!
Name _3: #REF!
Name _4: #REF!
Name _4: #REF!
Name _5: #REF!
Name _5: #REF!
Name a: #REF!
Name a: #REF!
Name Accounts: #REF!
Name Accounts: #REF!
Name Activity_Reports: #REF!
Name Activity_Reports: #REF!
Name ADM: #REF!
Name ADM: #REF!
Name Application: #REF!
Name B: #REF!
Name B: #REF!
Name back: #REF!
Name back: #REF!
Name Calendar: #REF!
Name Calendar: #REF!
Name Catalogue_xls: #REF!
Name Catalogue_xls: #REF!
Name CompanyCode: [10]CompanyCode!$A$2:$A$5
Name Contractingdiv: #REF!
Name Contractingdiv: #REF!
Name corporate_affairs: #REF!
Name corporate_affairs: #REF!
Name CTY: '[11]0.CTY'!$D$1:$D$65536
Name Data_Values: '[15]Single Measure Analysis'!$B$29:$M$30
Name DATA13: '[16]2.1Raw material_details'!#REF!
Name DATA13: '[16]2.1Raw material_details'!#REF!
Name DATA14: '[16]2.1Raw material_details'!#REF!
Name DATA14: '[16]2.1Raw material_details'!#REF!
Name DATA15: '[16]2.1Raw material_details'!#REF!
Name DATA15: '[16]2.1Raw material_details'!#REF!
Name DATA16: '[16]2.1Raw material_details'!#REF!
Name DATA16: '[16]2.1Raw material_details'!#REF!
Name DATA17: '[16]2.1Raw material_details'!#REF!
Name DATA17: '[16]2.1Raw material_details'!#REF!
Name DATA18: '[16]2.1Raw material_details'!#REF!
Name DATA18: '[16]2.1Raw material_details'!#REF!
Name DATA19: '[16]2.1Raw material_details'!#REF!
Name DATA19: '[16]2.1Raw material_details'!#REF!
Name DATA20: '[16]2.1Raw material_details'!#REF!
Name DATA20: '[16]2.1Raw material_details'!#REF!
Name DATA21: '[16]2.1Raw material_details'!#REF!
Name DATA21: '[16]2.1Raw material_details'!#REF!
Name DATA22: '[16]2.1Raw material_details'!#REF!
Name DATA22: '[16]2.1Raw material_details'!#REF!
Name DATA23: '[16]2.1Raw material_details'!#REF!
Name DATA23: '[16]2.1Raw material_details'!#REF!
Name DATA24: '[16]2.1Raw material_details'!#REF!
Name DATA24: '[16]2.1Raw material_details'!#REF!
Name DATA25: '[16]2.1Raw material_details'!#REF!
Name DATA25: '[16]2.1Raw material_details'!#REF!

Sheet Timeline & PIC
B1: DUY TAN GROUP
B2: =IF(B3="EN","Schedule Annual Plan 2025","Lịch lập NGÂN SÁCH năm 2026") -> Lịch lập NGÂN SÁCH năm 2026 | D2: =IF(B3="EN","Start:","Bắt đầu:") -> Bắt đầu: | E2: 45915
B3: VN | D3: =IF(B3="EN","Finish:","Kết thúc:") -> Kết thúc: | E3: =G22 -> 45990 | G3: =E3-E2 -> 75
D4: =IF(B3="en","SENDER","Đơn vị gửi") -> Đơn vị gửi | E4: =IF(B3="EN","RECEIVER","Đơn vị nhận") -> Đơn vị nhận | G4: Deadline | H4: THÁNG 09 | AM4: THÁNG 10 | BR4: THÁNG 11
B5: No. | C5: =IF(B3="EN","PROCESS","TRÌNH TỰ THỰC HIỆN") -> TRÌNH TỰ THỰC HIỆN | F5: Thời gian | H5: 1 | I5: 2 | J5: 3 | K5: 4 | L5: 5 | M5: 6 | N5: 7 | O5: 8 | P5: 9 | Q5: 10 | R5: 11 | S5: 12 | T5: 13 | U5: 14 | V5: 15 | W5: 16 | X5: 17 | Y5: 18 | Z5: 19 | AA5: 20 | AB5: 21 | AC5: 22 | AD5: 23 | AE5: 24 | AF5: 25 | AG5: 26 | AH5: 27 | AI5: 28 | AJ5: 29 | AK5: 30 | AL5: 31 | AM5: 1 | AN5: 2 | AO5: 3 | AP5: 4 | AQ5: 5 | AR5: 6 | AS5: 7 | AT5: 8 | AU5: 9 | AV5: 10 | AW5: 11 | AX5: 12 | AY5: 13 | AZ5: 14 | BA5: 15 | BB5: 16 | BC5: 17 | BD5: 18 | BE5: 19 | BF5: 20 | BG5: 21 | BH5: 22 | BI5: 23 | BJ5: 24 | BK5: 25 | BL5: 26 | BM5: 27 | BN5: 28 | BO5: 29 | BP5: 30 | BQ5: 31 | BR5: 1 | BS5: =BR5+1 -> 2 | BT5: =BS5+1 -> 3 | BU5: =BT5+1 -> 4 | BV5: =BU5+1 -> 5 | BW5: =BV5+1 -> 6 | BX5: =BW5+1 -> 7 | BY5: =BX5+1 -> 8 | BZ5: =BY5+1 -> 9 | ... CT5: =CS5+1 -> 29 | CU5: 30
F6: (Ngày) | H6: M | I6: T | J6: W | K6: TH | L6: F | M6: Sa | N6: Su | O6: M | P6: T | Q6: W | R6: TH | S6: F | T6: Sa | U6: Su | V6: M | W6: T | X6: W | Y6: TH | Z6: F | AA6: Sa | AB6: Su | AC6: M | AD6: T | AE6: W | AF6: TH | AG6: F | AH6: Sa | AI6: Su | AJ6: M | AK6: T | AL6: W | AM6: TH | AN6: F | AO6: Sa | AP6: Su | AQ6: M | AR6: T | AS6: W | AT6: TH | AU6: F | AV6: Sa | AW6: Su | AX6: M | AY6: T | AZ6: W | BA6: TH | BB6: F | BC6: Sa | BD6: Su | BE6: M | BF6: T | BG6: W | BH6: TH | BI6: F | BJ6: Sa | BK6: Su | BL6: M | BM6: T | BN6: W | BO6: TH | BP6: F | BQ6: Sa | BR6: Su | BS6: M | BT6: T | BU6: W | BV6: TH | BW6: F | BX6: Sa | BY6: Su | BZ6: M | CA6: T | CB6: W | CC6: TH | CD6: F | CE6: Sa | CF6: Su | CG6: M | CH6: T | CI6: W | CJ6: TH | CK6: F | CL6: Sa | CM6: Su | CN6: M | CO6: T | CP6: W | CQ6: TH | CR6: F | CS6: Sa | CT6: Su | CU6: M
B7: 1 | C7: Khởi động | D7: GĐTC holding | E7: =IF(B3="EN","All","Tất cả") -> Tất cả | G7: =E2 -> 45915
B8: 2 | C8: Kế hoạch Doanh thu / Sản lượng | D8: =IF(B3="EN","Sales team","Phòng kinh doanh") -> Phòng kinh doanh | E8: =IF(B3="EN","Acct.","Kế toán") -> Kế toán | F8: 15 | G8: =F8+$G$7 -> 45930
B9: 3 | C9: Kế hoạch giá cả nguyên vật liệu | D9: =IF(B2="EN","Supply chain","Chuỗi cung ứng") -> Chuỗi cung ứng | E9: =E8 -> Kế toán | F9: 15 | G9: =F9+$G$7 -> 45930
B10: =B9+1 -> 4 | C10: Kế hoạch chi phí vận chuyển, cước xuất khẩu,... | D10: =IF(B3="EN","Supply chain","Chuổi cung ứng") -> Chuổi cung ứng | E10: =E9 -> Kế toán | F10: 15 | G10: =F10+$G$7 -> 45930
B11: =B10+1 -> 5 | C11: Kế hoạch sản xuất | D11: =IF(B3="EN","Production","Bộ phận sản xuất") -> Bộ phận sản xuất | E11: =E10 -> Kế toán | F11: 20 | G11: =F11+$G$7 -> 45935
B12: =B11+1 -> 6 | C12: Kế hoạch biến phí sản xuất | D12: =E12 -> Kế toán | E12: =E11 -> Kế toán | F12: 20 | G12: =F12+$G$7 -> 45935
B13: =B12+1 -> 7 | C13: Kế hoạch nhân sự (số lượng nhân sự, quỹ lương, chi phí đào tạo,...) | D13: =IF(B3="EN","HR","Phòng nhân sự") -> Phòng nhân sự | E13: =E12 -> Kế toán | F13: 30 | G13: =F13+$G$7 -> 45945
B14: =B13+1 -> 8 | C14: Ngân sách đầu tư | D14: =E7 -> Tất cả | E14: =E13 -> Kế toán | F14: 30 | G14: =F14+$G$7 -> 45945
B15: =B14+1 -> 9 | C15: Ngân sách chi phí sản xuất (không bao gồm lương) | D15: =D11 -> Bộ phận sản xuất | E15: =E14 -> Kế toán | F15: 30 | G15: =F15+$G$7 -> 45945
B16: =B15+1 -> 10 | C16: Ngân sách chi phí bán hàng & chí phí quản lý (không bao gồm lương) | D16: =D14 -> Tất cả | E16: =E15 -> Kế toán | F16: 30 | G16: =F16+$G$7 -> 45945
B17: =B16+1 -> 11 | C17: Tổng hợp kết quả ngân sách mỗi công ty | D17: Kế toán quản trị | E17: KTT/GĐTC | F17: 45 | G17: =F17+$G$7 -> 45960
B18: 12 | C18: Trình bày kết quả ngân sách của mỗi công ty đến TGĐ (Bottom up) | D18: KTT/GĐTC | E18: TGĐ | F18: 50 | G18: =F18+$G$7 -> 45965
B19: 13 | C19: Trình bày kết quả ngân sách của mỗi công ty đến TGĐ (Top down) | D19: KTT/GĐTC | E19: TGĐ | F19: 55 | G19: =F19+$G$7 -> 45970
B20: 14 | C20: Trình bày kết quả ngân sách của mỗi công ty đến TGĐ (Chính thức) | D20: KTT/GĐTC | E20: TGĐ | F20: 62 | G20: =F20+$G$7 -> 45977
B21: 15 | C21: Hợp nhất ngân sách cho toàn bộ DT Group | D21: KTQT holding | E21: GĐTC holding | F21: 70 | G21: =F21+$G$7 -> 45985
B22: 16 | C22: Trình bày kết quả ngân sách hợp nhất cho toàn bộ DT Group | D22: GĐTC holding | E22: TGĐ | F22: 75 | G22: =F22+$G$7 -> 45990

Sheet Thongtin
B2: STT | C2: Nội dung | D2: Nguồn cung cấp dữ liệu | E2: Nguồn thông tin liên quan | F2: Thời gian cần dữ liệu | H2: STT | I2: Màu sheet | J2: Thông tin
B3: 1 | C3: Ban hành Nhóm-Loại NVL Trạm thu mua | D3: GĐĐH Trạm - DTR | E3: 1. BGĐ DTR 2. Phòng cung ứng DTR | F3: 45940 | H3: 1 | J3: Kết quả kinh doanh tổng hợp
B4: 2 | C4: Ban hành Sản lượng Trạm thu mua | D4: GĐĐH Trạm - DTR | E4: 1. BGĐ DTR 2. Phòng cung ứng DTR | F4: 45940 | H4: 2 | J4: Kết quả kinh doanh PET và HD
B5: 3 | C5: Ban hành đơn giá MUA từng loại NVL | D5: GĐĐH Trạm - DTR | E5: 1. Phòng cung ứng DTR đề xuất KH năm 2026 (Dữ liệu theo từng tháng) 2. KTT các trạm cung cấp đơn giá bình quân thực tế mua theo từng tháng ( Dữ liệu năm 2023-2024-2025) 3. Đơn giá BGĐ-DTR duyệt mua trong năm 2025 (Dữ liệu theo từng tháng) | F5: 45940 | H5: 3 | J5: Kết quả kinh doanh PET và HD
B6: 4 | C6: Ban hành đơn giá BÁN từng loại thành phẩm | D6: GĐĐH Trạm - DTR | E6: 1. BGĐ DTR 2. Phòng cung ứng DTR | F6: 45940 | H6: 4 | J6: Ban hành Định mức về Công suất MMTB - Định mức về CP phục vụ sản xuất - Định biên Nhân sự
B7: 5 | C7: Kế hoạch đầu tư CAPEX tại Trạm => Ảnh hưởng đến Sản phẩm và TCKT Trạm cung cấp đến DTR | D7: GĐĐH Trạm - DTR | E7: 1. BGĐ DTR 2. Phòng kỹ thuật DTR 3. Phòng mua hàng DTR | F7: 45940 | H7: 5 | J7: Ban hành sản lượng - đơn giá - Cơ cấu về: NVL - Thành phẩm - Hao hụt - Bán hàng
H8: 6 | J8: Nhóm Chi phí:CP Sản xuất - CP Bán hàng - CP Quản lý (Công thức từ: Định mức - Lương - PB_TSCD - PB_CPTT - nhóm NVL - Phát sinh trực tiếp)
H9: 7 | J9: Cập nhật TSCĐ - CPTT năm trước chuyển sang và Capex 2026
H10: 8 | I10: … | J10: Thông tin khác

Sheet KH hanh dong
A3: KẾ HOẠCH KINH DOANH 2026
A4: Nguồn yêu cầu: GĐTC-DTR
A5: STT | B5: Nhóm công việc | C5: Kế hoạch hành động | D5: Người thực hiện | E5: Thời gian hoàn thành tính toán và xác lập mục tiêu 2026 | F5: Hiện trạng / vướng mắt / giải pháp (tại thời điểm tháng 10/2025) | G5: Mục tiêu 2026 (rolling hàng tháng) | U5: KHNS 2026 | V5: Thực hiện 2025 | W5: Tăng/giảm vs KHNS 2026
G6: Đánh giá KQ đạt được (cập nhật đến thời điểm báo cáo) | H6: Mục tiêu T1 | I6: Mục tiêu T2 | J6: Mục tiêu T3 | K6: Mục tiêu T4 | L6: Mục tiêu T5 | M6: Mục tiêu T6 | N6: Mục tiêu T7 | O6: Mục tiêu T8 | P6: Mục tiêu T9 | Q6: Mục tiêu T10 | R6: Mục tiêu T11 | S6: Mục tiêu T12 | T6: Dự báo KQ 2026 | W6: Theo số tiền phát sinh | X6: Theo mức độ hoạt động | Y6: %
A7: A | B7: HOẠT ĐỘNG MUA HÀNG
A8: 1 | B8: Đáp ứng sản lượng mua cho Trạm | C8: Lập mục tiêu sản lượng mua để Trạm đạt hòa vốn và có lãi.
C9: Xây dựng các trạm vệ tinh để tăng lượng chai về Trạm.
C10: Phát triển thêm các NCC liên kết ở tỉnh.
C11: Đàm phán tăng sản lượng mua từ các NCC đang giao dịch.
A12: 2 | B12: Cải thiện dịch vụ khách hàng | C12: Cải thiện thời gian nhận hàng
C13: Thanh toán trong ngày và cuối tuần
A14: B | B14: HOẠT ĐỘNG BÁN HÀNG
A15: 1 | B15: Giá bán về DTR | C15: Áp dụng cơ cấu giá mới từ Tháng 9/2025
A16: 2 | B16: Kiểm soát tồn kho thành phẩm | C16: Lập KH giao hàng về DTR hàng ngày, ngày cuối tháng không để tồn kho và xuất hóa đơn 100%
A17: 3 | B17: Chi phí thuê xe vận chuyển | C17: - Đàm phán giảm giá, đề nghị NCC sử dụng phương tiện vận chuyển hiệu quả. - Tìm NCC mới cạnh tranh.
A18: C | B18: HOẠT ĐỘNG CẢI TIẾN CHI PHÍ
A19: I | B19: Chi phí nguyên vật liệu
A20: 1 | B20: Kiểm soát lượng mua, giá mua | C20: - Lập mục tiêu tồn kho tối thiểu 10 ngày sản xuất và phối hợp P.Cung ứng lập KH mua hàng theo tuần. - Kiểm soát giá mua tương ứng với từng mức chất lượng chai.
A21: 2 | B21: Kiểm soát chất lượng NVL, hao hụt | C21: Kiểm soát chất lượng chai (tỷ lệ chai nguyên liệu - Chai xá/xô tuyển, thành phần chai sau phân loại, tỷ lệ tạp chất).
A22: 3 | B22: Kiểm soát định mức vật tư sản xuất (hóa chất, dây đai, vật tư kỹ thuật …) | C22: - Thống kê và thực hiện cải tiến tiêu hao. - Mua tập trung tại P.Mua hàng DTR.
A23: 4 | B23: Xử lý phế liệu, phó sản thu hồi | C23: Phân loại phế liệu thành 2 nhóm: - Nhóm hàng hóa (nhãn, bao jumbo, kim loại,…): tìm đơn vị thu mua giá cao - Nhóm rác thải công nghiệp (bùn, hỗn hợp tạp chất): thuê thu gom
A24: II | B24: Chi phí nhân công
A25: 1 | B25: Định mức NCTT | C25: - Kiểm soát định mức NCTT theo chuyền/công đoạn. - Thực hiện tiêu chuẩn hóa/tự động hóa MMTB để giảm nhân công, tăng năng suất. - Tăng số lượng lao động thời vụ. - Tính toán phương án trả lương/ thưởng theo sản lượng.
A26: 2 | B26: Năng suất lao động | C26: - Lập mục tiêu tăng thời gian sản xuất từ 8 giờ/ngày -> 12 giờ -> 16 giờ -> 24 giờ.
A27: III | B27: Chi phí sản xuất chung
A28: 1 | B28: Chi phí điện | C28: - Phối hợp kỹ thuật bảo trì MMTB đảm bảo hoạt động liên tục -> tăng hiệu quả sử dụng điện và tăng năng suất lao động.
A29: 2 | B29: Chi phí xe nâng | C29: - Chuyển dần xe nâng dầu từ DTR về các Trạm (các xe của trạm sửa chữa nhiều sẽ thanh lý)
A30: 3 | B30: Chi phí khấu hao TSCĐ, CCDC, chi phí phân bổ khác | C30: - Thống kê, đánh giá lại hiệu quả sử dụng tất cả TS. - Tách chi phí khấu hao/phân bổ không phục vụ trực tiếp hoạt động để đánh giá hiệu quả KD thực của trạm.
A31: 4 | B31: Chi phí thuê xưởng | C31: - Tìm vị trí và đề xuất phương án di dời nhà máy để giảm tiền thu, tăng hiệu quả thu mua.
A32: IV | B32: Chi phí quản lý
A33: 1 | B33: Chi phí lương (gồm gián tiếp SX) | C33: Soát xét định biên và kế hoạch tuyển dụng, lập mục tiêu giảm định biên đến cuối 2026
A34: 2 | B34: Chi phí theo mục phí (ngoài chi phí lương) | C34: - Lập danh mục chi phí dịch vụ thuê/mua trả tiền định kỳ (nhóm dịch vụ/phòng ban quản lý, tên NCC, hợp đồng mới nhất, tiền trả định kỳ tháng/quý/năm, thời hạn công nợ) -> đàm phán từng NC giảm giá và tìm NCC mới cạnh tranh - XD định mức chi phí cho các khoản mục có thể xác lập định mức - Phân tích chi phí, nguyên nhân tăng/giảm và giải pháp cải tiến.
A35: V | B35: Mục tiêu lợi nhuận
A36: 1 | B36: Lợi nhuận kế hoạch đến cuối năm 2026 | C36: Sau khi đánh giá, xác lập các mục tiêu bên trên, tính toán lợi nhuận kế hoạch đến cuối năm 2026

Sheet KQKD Tong hop
E1: =E29+E33+E40 -> 22617107745 | R1: =R29+R33+R40 -> 2.3161896e+10
R2: =SUM(R24,R30,R41) -> 1.6873505e+10
B3: MỤC TIÊU KẾT QUẢ KINH DOANH NĂM 2026 | F3: =F17/F5 -> 13307.439 | G3: =G17/G5 -> 13277.288 | H3: =H17/H5 -> 13317.825 | I3: =I17/I5 -> 13140.123 | J3: =J17/J5 -> 13150.499 | K3: =K17/K5 -> 13155.331 | L3: =L17/L5 -> 13178.937 | M3: =M17/M5 -> 13179.046 | N3: =N17/N5 -> 13117.508 | O3: ='1.NVL Chai'!Q16*11000 -> 14300000000 | P3: ='1.NVL Chai'!R16*11000 -> 14300000000 | Q3: ='1.NVL Chai'!S16*11000 -> 14300000000 | R3: ĐVT: Triệu đồng
B4: STT | C4: Mục phí | D4: Thực tế năm 2024 | E4: KQKD 2025 | F4: T1 | G4: T2 | H4: T3 | I4: T4 | J4: T5 | K4: T6 | L4: T7 | M4: T8 | N4: T9 | O4: T10 | P4: T11 | Q4: T12 | R4: KH 2026
B5: 1 | C5: SẢN LƯỢNG BÁN (TẤN) | D5: ='KQKD PET'!E5 -> 0 | E5: ='KQKD PET'!F5+'KQKD HD'!F5 -> 9805731 | F5: =F6+F7+F8 -> 760725 | G5: =G6+G7+G8 -> 591675 | H5: =H6+H7+H8 -> 845250 | I5: =I6+I7+I8 -> 1055250 | J5: =J6+J7+J8 -> 1055250 | K5: =K6+K7+K8 -> 1055250 | L5: =L6+L7+L8 -> 1055250 | M5: =M6+M7+M8 -> 1055250 | ... Q5: =Q6+Q7+Q8 -> 1057212 | R5: =SUM(F5:Q5) -> 11700786
B6: 1.1 | C6: Chai PET | D6: ='KQKD PET'!E6 -> 0 | E6: ='KQKD PET'!F6 -> 7883386 | F6: ='KQKD PET'!G6+'KQKD HD'!G6 -> 519750 | G6: ='KQKD PET'!H6+'KQKD HD'!H6 -> 404250 | H6: ='KQKD PET'!I6+'KQKD HD'!I6 -> 577500 | I6: ='KQKD PET'!J6+'KQKD HD'!J6 -> 720000 | J6: ='KQKD PET'!K6+'KQKD HD'!K6 -> 720000 | K6: ='KQKD PET'!L6+'KQKD HD'!L6 -> 720000 | L6: ='KQKD PET'!M6+'KQKD HD'!M6 -> 720000 | M6: ='KQKD PET'!N6+'KQKD HD'!N6 -> 720000 | ... Q6: ='KQKD PET'!R6+'KQKD HD'!R6 -> 78000 | R6: =SUM(F6:Q6) -> 6055500
B7: 1.2 | C7: Vảy PET | D7: ='KQKD PET'!E7 -> 0 | E7: ='KQKD PET'!F7 -> 1688932 | F7: ='KQKD PET'!G7+'KQKD HD'!G7 -> 240975 | G7: ='KQKD PET'!H7+'KQKD HD'!H7 -> 187425 | H7: ='KQKD PET'!I7+'KQKD HD'!I7 -> 267750 | I7: ='KQKD PET'!J7+'KQKD HD'!J7 -> 335250 | J7: ='KQKD PET'!K7+'KQKD HD'!K7 -> 335250 | K7: ='KQKD PET'!L7+'KQKD HD'!L7 -> 335250 | L7: ='KQKD PET'!M7+'KQKD HD'!M7 -> 335250 | M7: ='KQKD PET'!N7+'KQKD HD'!N7 -> 335250 | ... Q7: ='KQKD PET'!R7+'KQKD HD'!R7 -> 979212 | R7: =SUM(F7:Q7) -> 5645286
B8: 1.3 | C8: Vảy HD | D8: ='KQKD PET'!E8 -> 0 | E8: ='KQKD HD'!F5 -> 233413 | F8: ='KQKD PET'!G8+'KQKD HD'!G8 -> 0 | G8: ='KQKD PET'!H8+'KQKD HD'!H8 -> 0 | H8: ='KQKD PET'!I8+'KQKD HD'!I8 -> 0 | I8: ='KQKD PET'!J8+'KQKD HD'!J8 -> 0 | J8: ='KQKD PET'!K8+'KQKD HD'!K8 -> 0 | K8: ='KQKD PET'!L8+'KQKD HD'!L8 -> 0 | L8: ='KQKD PET'!M8+'KQKD HD'!M8 -> 0 | M8: ='KQKD PET'!N8+'KQKD HD'!N8 -> 0 | ... Q8: ='KQKD PET'!R8+'KQKD HD'!R8 -> 0 | R8: =SUM(F8:Q8) -> 0
B9: 1.4 | C9: Dây Đai PET | F9: ='KDKD DAY DAI'!G6 -> 0 | G9: ='KDKD DAY DAI'!H6 -> 0 | H9: ='KDKD DAY DAI'!I6 -> 0 | I9: ='KDKD DAY DAI'!J6 -> 0 | J9: ='KDKD DAY DAI'!K6 -> 0 | K9: ='KDKD DAY DAI'!L6 -> 0 | L9: ='KDKD DAY DAI'!M6 -> 0 | M9: ='KDKD DAY DAI'!N6 -> 0 | ... Q9: ='KDKD DAY DAI'!R6 -> 0 | R9: =SUM(F9:Q9) -> 0
B10: 2 | C10: DOANH THU | D10: ='KQKD PET'!E9 -> 64684339330 | E10: ='KQKD PET'!F9+'KQKD HD'!F9+126341842 -> 173927684403 | F10: =SUM(F11:F14) -> 11515218750 | G10: =SUM(G11:G14) -> 8956281250 | H10: =SUM(H11:H14) -> 12794687500 | I10: =SUM(I11:I14) -> 15974312500 | J10: =SUM(J11:J14) -> 15974312500 | K10: =SUM(K11:K14) -> 15974312500 | L10: =SUM(L11:L14) -> 15974312500 | M10: =SUM(M11:M14) -> 15974312500 | ... Q10: =SUM(Q11:Q14) -> 17334395000 | R10: =SUM(F10:Q10) -> 181115247500
B11: 2.1 | C11: Chai PET | D11: ='KQKD PET'!E10 -> 64684339330 | E11: ='KQKD PET'!F10+'KQKD HD'!F10+126341842 -> 140227158729 | F11: ='KQKD PET'!G10+'KQKD HD'!G10 -> 7626150000 | G11: ='KQKD PET'!H10+'KQKD HD'!H10 -> 5931450000 | H11: ='KQKD PET'!I10+'KQKD HD'!I10 -> 8473500000 | I11: ='KQKD PET'!J10+'KQKD HD'!J10 -> 10563750000 | J11: ='KQKD PET'!K10+'KQKD HD'!K10 -> 10563750000 | K11: ='KQKD PET'!L10+'KQKD HD'!L10 -> 10563750000 | L11: ='KQKD PET'!M10+'KQKD HD'!M10 -> 10563750000 | M11: ='KQKD PET'!N10+'KQKD HD'!N10 -> 10563750000 | ... Q11: ='KQKD PET'!R10+'KQKD HD'!R10 -> 924300000 | R11: =SUM(F11:Q11) -> 88186500000
B12: 2.2 | C12: Vảy PET | D12: ='KQKD PET'!E11 -> 0 | E12: ='KQKD PET'!F11+'KQKD HD'!F11 -> 30731028704 | F12: ='KQKD PET'!G11+'KQKD HD'!G11 -> 3889068750 | G12: ='KQKD PET'!H11+'KQKD HD'!H11 -> 3024831250 | H12: ='KQKD PET'!I11+'KQKD HD'!I11 -> 4321187500 | I12: ='KQKD PET'!J11+'KQKD HD'!J11 -> 5410562500 | J12: ='KQKD PET'!K11+'KQKD HD'!K11 -> 5410562500 | K12: ='KQKD PET'!L11+'KQKD HD'!L11 -> 5410562500 | L12: ='KQKD PET'!M11+'KQKD HD'!M11 -> 5410562500 | ... Q12: ='KQKD PET'!R11+'KQKD HD'!R11 -> 16410095000 | R12: =SUM(F12:Q12) -> 92928747500
B13: 2.3 | C13: Vảy HD | D13: ='KQKD PET'!E12 -> 0 | E13: ='KQKD PET'!F12+'KQKD HD'!F12 -> 2969496970 | F13: ='KQKD PET'!G12+'KQKD HD'!G12 -> 0 | G13: ='KQKD PET'!H12+'KQKD HD'!H12 -> 0 | H13: ='KQKD PET'!I12+'KQKD HD'!I12 -> 0 | I13: ='KQKD PET'!J12+'KQKD HD'!J12 -> 0 | J13: ='KQKD PET'!K12+'KQKD HD'!K12 -> 0 | K13: ='KQKD PET'!L12+'KQKD HD'!L12 -> 0 | L13: ='KQKD PET'!M12+'KQKD HD'!M12 -> 0 | ... Q13: ='KQKD PET'!R12+'KQKD HD'!R12 -> 0 | R13: =SUM(F13:Q13) -> 0
B14: 2.4 | C14: Dây Đai PET | F14: ='KDKD DAY DAI'!G10 -> 0 | G14: ='KDKD DAY DAI'!H10 -> 0 | H14: ='KDKD DAY DAI'!I10 -> 0 | I14: ='KDKD DAY DAI'!J10 -> 0 | J14: ='KDKD DAY DAI'!K10 -> 0 | K14: ='KDKD DAY DAI'!L10 -> 0 | L14: ='KDKD DAY DAI'!M10 -> 0 | M14: ='KDKD DAY DAI'!N10 -> 0 | ... Q14: ='KDKD DAY DAI'!R10 -> 0 | R14: =SUM(F14:Q14) -> 0
B15: 2.4 | C15: Khác | D15: ='KQKD PET'!E13 -> 0 | E15: ='KQKD PET'!F13+'KQKD HD'!F13 -> 0 | F15: ='KQKD PET'!G13+'KQKD HD'!G13 -> 0 | G15: ='KQKD PET'!H13+'KQKD HD'!H13 -> 0 | H15: ='KQKD PET'!I13+'KQKD HD'!I13 -> 0 | I15: ='KQKD PET'!J13+'KQKD HD'!J13 -> 0 | J15: ='KQKD PET'!K13+'KQKD HD'!K13 -> 0 | K15: ='KQKD PET'!L13+'KQKD HD'!L13 -> 0 | L15: ='KQKD PET'!M13+'KQKD HD'!M13 -> 0 | ... Q15: ='KQKD PET'!R13+'KQKD HD'!R13 -> 0 | R15: =SUM(F15:Q15) -> 0
B16: 3 | C16: BIẾN PHÍ | D16: ='KQKD PET'!E14 -> 0 | E16: ='KQKD PET'!F14+'KQKD HD'!F14 -> 1.5804639e+11 | F16: =F17+F25 -> 1.0382402e+10 | G16: =G17+G25 -> 8.057362e+09 | H16: =H17+H25 -> 1.1544781e+10 | I16: =I17+I25 -> 1.4225483e+10 | J16: =J17+J25 -> 1.4236432e+10 | K16: =K17+K25 -> 1.4241531e+10 | L16: =L17+L25 -> 1.4266442e+10 | M16: =M17+M25 -> 1.4266557e+10 | ... Q16: =Q17+Q25 -> 1.5196076e+10 | R16: =SUM(F16:Q16) -> 1.6103167e+11
B17: 3.1 | C17: BIẾN PHÍ SẢN XUẤT | D17: ='KQKD PET'!E15 -> 0 | E17: ='KQKD PET'!F15+'KQKD HD'!F15 -> 1.5491849e+11 | F17: =F18+F22+F23+F24 -> 1.0123301e+10 | G17: =G18+G22+G23+G24 -> 7.8558393e+09 | H17: =H18+H22+H23+H24 -> 1.1256891e+10 | I17: =I18+I22+I23+I24 -> 1.3866114e+10 | J17: =J18+J22+J23+J24 -> 1.3877064e+10 | K17: =K18+K22+K23+K24 -> 1.3882163e+10 | L17: =L18+L22+L23+L24 -> 1.3907073e+10 | M17: =M18+M22+M23+M24 -> 1.3907188e+10 | ... Q17: =Q18+Q22+Q23+Q24 -> 1.4866419e+10 | R17: =SUM(F17:Q17) -> 1.5713797e+11
B18: 3.1.1 | C18: Nguyên vật liệu chính (nhựa, gồm hao hụt) | D18: ='KQKD PET'!E16 -> 0 | E18: ='KQKD PET'!F16+'KQKD HD'!F16 -> 1.4456918e+11 | F18: ='KQKD PET'!G16+'KQKD HD'!G16+'KDKD DAY DAI'!G16 -> 9000000000 | G18: ='KQKD PET'!H16+'KQKD HD'!H16+'KDKD DAY DAI'!H16 -> 7000000000 | H18: ='KQKD PET'!I16+'KQKD HD'!I16+'KDKD DAY DAI'!I16 -> 10000000000 | I18: ='KQKD PET'!J16+'KQKD HD'!J16+'KDKD DAY DAI'!J16 -> 12500000000 | J18: ='KQKD PET'!K16+'KQKD HD'!K16+'KDKD DAY DAI'!K16 -> 12500000000 | K18: ='KQKD PET'!L16+'KQKD HD'!L16+'KDKD DAY DAI'!L16 -> 12500000000 | L18: ='KQKD PET'!M16+'KQKD HD'!M16+'KDKD DAY DAI'!M16 -> 12500000000 | M18: ='KQKD PET'!N16+'KQKD HD'!N16+'KDKD DAY DAI'!N16 -> 12500000000 | ... Q18: ='KQKD PET'!R16+'KQKD HD'!R16+'KDKD DAY DAI'!R16 -> 13000000000 | R18: =SUM(F18:Q18) -> 140000000000
B19: 3.1.2 | C19: Trong đó: i/ Hao hụt CĐ phân loại chai | D19: ='KQKD PET'!E17 -> 0 | E19: ='KQKD PET'!F17 -> 1.3748236e+10 | F19: ='KQKD PET'!G17+'KQKD HD'!G17 -> 1125000000 | G19: ='KQKD PET'!H17+'KQKD HD'!H17 -> 875000000 | H19: ='KQKD PET'!I17+'KQKD HD'!I17 -> 1250000000 | I19: ='KQKD PET'!J17+'KQKD HD'!J17 -> 1575000000 | J19: ='KQKD PET'!K17+'KQKD HD'!K17 -> 1575000000 | K19: ='KQKD PET'!L17+'KQKD HD'!L17 -> 1575000000 | L19: ='KQKD PET'!M17+'KQKD HD'!M17 -> 1575000000 | M19: ='KQKD PET'!N17+'KQKD HD'!N17 -> 1575000000 | ... Q19: ='KQKD PET'!R17+'KQKD HD'!R17 -> 1638000000 | R19: =SUM(F19:Q19) -> 17614000000
C20: ii/ Hao hụt CĐ băm vảy | D20: ='KQKD PET'!E18 -> 0 | E20: ='KQKD PET'!F18 -> 1.715399e+09 | F20: ='KQKD PET'!G18+'KQKD HD'!G18 -> 267750000 | G20: ='KQKD PET'!H18+'KQKD HD'!H18 -> 208250000 | H20: ='KQKD PET'!I18+'KQKD HD'!I18 -> 297500000 | I20: ='KQKD PET'!J18+'KQKD HD'!J18 -> 372500000 | J20: ='KQKD PET'!K18+'KQKD HD'!K18 -> 372500000 | K20: ='KQKD PET'!L18+'KQKD HD'!L18 -> 372500000 | L20: ='KQKD PET'!M18+'KQKD HD'!M18 -> 372500000 | M20: ='KQKD PET'!N18+'KQKD HD'!N18 -> 372500000 | ... Q20: ='KQKD PET'!R18+'KQKD HD'!R18 -> 1192360000 | R20: =SUM(F20:Q20) -> 6585580000
B21: 3.1.3 | C21: % chi phí nguyên liệu/doanh thu | D21: ='KQKD PET'!E19 -> 0 | E21: =E18/E10 -> 0.83120281 | F21: =F18/F10 -> 0.78157438 | G21: =G18/G10 -> 0.78157438 | H21: =H18/H10 -> 0.78157438 | I21: =I18/I10 -> 0.78250629 | J21: =J18/J10 -> 0.78250629 | K21: =K18/K10 -> 0.78250629 | L21: =L18/L10 -> 0.78250629 | ... R21: =R18/R10 -> 0.77298848
B22: 3.1.4 | C22: Vật tư tiêu hao(dao băm, dao tách nhãn, bùn, nhãn, dao jumbo, dây đai) | D22: ='KQKD PET'!E20 -> 0 | E22: ='KQKD PET'!F20+'KQKD HD'!F20 -> 2.7789895e+09 | F22: ='KQKD PET'!G20+'KQKD HD'!G20+'KDKD DAY DAI'!G20 -> 3.0802692e+08 | G22: ='KQKD PET'!H20+'KQKD HD'!H20+'KDKD DAY DAI'!H20 -> 2.3889538e+08 | H22: ='KQKD PET'!I20+'KQKD HD'!I20+'KDKD DAY DAI'!I20 -> 3.3811419e+08 | I22: ='KQKD PET'!J20+'KQKD HD'!J20+'KDKD DAY DAI'!J20 -> 4.2242376e+08 | J22: ='KQKD PET'!K20+'KQKD HD'!K20+'KDKD DAY DAI'!K20 -> 4.2112376e+08 | K22: ='KQKD PET'!L20+'KQKD HD'!L20+'KDKD DAY DAI'!L20 -> 4.2078209e+08 | L22: ='KQKD PET'!M20+'KQKD HD'!M20+'KDKD DAY DAI'!M20 -> 4.2015876e+08 | M22: ='KQKD PET'!N20+'KQKD HD'!N20+'KDKD DAY DAI'!N20 -> 4.2027376e+08 | ... Q22: ='KQKD PET'!R20+'KQKD HD'!R20+'KDKD DAY DAI'!R20 -> 6.7023156e+08 | R22: =SUM(F22:Q22) -> 5.4218121e+09
B23: 3.1.5 | C23: Điện sản xuất | D23: ='KQKD PET'!E21 -> 0 | E23: ='KQKD PET'!F21+'KQKD HD'!F21 -> 1409501660 | F23: ='KQKD PET'!G21+'KQKD HD'!G21+'KDKD DAY DAI'!G21 -> 1.1567843e+08 | G23: ='KQKD PET'!H21+'KQKD HD'!H21+'KDKD DAY DAI'!H21 -> 89972114 | H23: ='KQKD PET'!I21+'KQKD HD'!I21+'KDKD DAY DAI'!I21 -> 1.2853159e+08 | I23: ='KQKD PET'!J21+'KQKD HD'!J21+'KDKD DAY DAI'!J21 -> 1.6071292e+08 | J23: ='KQKD PET'!K21+'KQKD HD'!K21+'KDKD DAY DAI'!K21 -> 1.6071292e+08 | K23: ='KQKD PET'!L21+'KQKD HD'!L21+'KDKD DAY DAI'!L21 -> 1.6071292e+08 | L23: ='KQKD PET'!M21+'KQKD HD'!M21+'KDKD DAY DAI'!M21 -> 1.6071292e+08 | M23: ='KQKD PET'!N21+'KQKD HD'!N21+'KDKD DAY DAI'!N21 -> 1.6071292e+08 | ... Q23: ='KQKD PET'!R21+'KQKD HD'!R21+'KDKD DAY DAI'!R21 -> 3.4009604e+08 | R23: =SUM(F23:Q23) -> 2.3187478e+09
B24: 3.1.6 | C24: Nhân công trực tiếp | D24: ='KQKD PET'!E22 -> 0 | E24: ='KQKD PET'!F22+'KQKD HD'!F22 -> 6160821040 | F24: ='KQKD PET'!G22+'KQKD HD'!G22+'KDKD DAY DAI'!G22 -> 6.995961e+08 | G24: ='KQKD PET'!H22+'KQKD HD'!H22+'KDKD DAY DAI'!H22 -> 5.2697176e+08 | H24: ='KQKD PET'!I22+'KQKD HD'!I22+'KDKD DAY DAI'!I22 -> 7.902456e+08 | I24: ='KQKD PET'!J22+'KQKD HD'!J22+'KDKD DAY DAI'!J22 -> 7.8297773e+08 | J24: ='KQKD PET'!K22+'KQKD HD'!K22+'KDKD DAY DAI'!K22 -> 7.9522688e+08 | K24: ='KQKD PET'!L22+'KQKD HD'!L22+'KDKD DAY DAI'!L22 -> 8.0066773e+08 | L24: ='KQKD PET'!M22+'KQKD HD'!M22+'KDKD DAY DAI'!M22 -> 826201238 | M24: ='KQKD PET'!N22+'KQKD HD'!N22+'KDKD DAY DAI'!N22 -> 826201238 | ... Q24: ='KQKD PET'!R22+'KQKD HD'!R22+'KDKD DAY DAI'!R22 -> 8.5609124e+08 | R24: =SUM(F24:Q24) -> 9.3974111e+09 | S24: 9050781100
B25: 3.2 | C25: BIẾN PHÍ BÁN HÀNG | D25: ='KQKD PET'!E23 -> 0 | E25: ='KQKD PET'!F23+'KQKD HD'!F23 -> 3127900000 | F25: =F26 -> 259100625 | G25: =G26 -> 2.0152271e+08 | H25: =H26 -> 2.8788958e+08 | I25: =I26 -> 359368750 | J25: =J26 -> 359368750 | K25: =K26 -> 359368750 | L25: =L26 -> 359368750 | M25: =M26 -> 359368750 | ... Q25: =Q26 -> 3.2965703e+08 | R25: =SUM(F25:Q25) -> 3.8936965e+09 | S25: =S24-R24 -> -3.4663001e+08
C26: Chi phí vận chuyển | D26: ='KQKD PET'!E24 -> 0 | E26: ='KQKD PET'!F24+'KQKD HD'!F24 -> 3127900000 | F26: ='KQKD PET'!G24+'KQKD HD'!G24+'KDKD DAY DAI'!G24 -> 259100625 | G26: ='KQKD PET'!H24+'KQKD HD'!H24+'KDKD DAY DAI'!H24 -> 2.0152271e+08 | H26: ='KQKD PET'!I24+'KQKD HD'!I24+'KDKD DAY DAI'!I24 -> 2.8788958e+08 | I26: ='KQKD PET'!J24+'KQKD HD'!J24+'KDKD DAY DAI'!J24 -> 359368750 | J26: ='KQKD PET'!K24+'KQKD HD'!K24+'KDKD DAY DAI'!K24 -> 359368750 | K26: ='KQKD PET'!L24+'KQKD HD'!L24+'KDKD DAY DAI'!L24 -> 359368750 | L26: ='KQKD PET'!M24+'KQKD HD'!M24+'KDKD DAY DAI'!M24 -> 359368750 | M26: ='KQKD PET'!N24+'KQKD HD'!N24+'KDKD DAY DAI'!N24 -> 359368750 | ... Q26: ='KQKD PET'!R24+'KQKD HD'!R24+'KDKD DAY DAI'!R24 -> 3.2965703e+08 | R26: =SUM(F26:Q26) -> 3.8936965e+09
B27: 4 | C27: LÃI SAU BIẾN PHÍ | D27: ='KQKD PET'!E25 -> 64684339330 | E27: ='KQKD PET'!F25+'KQKD HD'!F25+126341842 -> 1.5881292e+10 | F27: =F10-F16 -> 1.1328167e+09 | G27: =G10-G16 -> 8.9891929e+08 | H27: =H10-H16 -> 1.2499065e+09 | I27: =I10-I16 -> 1.7488293e+09 | J27: =J10-J16 -> 1.7378802e+09 | K27: =K10-K16 -> 1.732781e+09 | L27: =L10-L16 -> 1.7078708e+09 | M27: =M10-M16 -> 1.7077558e+09 | ... Q27: =Q10-Q16 -> 2.1383191e+09 | R27: =SUM(F27:Q27) -> 2.008358e+10 | S27: =(R29+R33+R40)/R28 -> 2.0887573e+11 | T27: =S27/T10 -> #DIV/0!
B28: 4.1 | C28: % lãi biến phí/doanh thu | D28: ='KQKD PET'!E26 -> 0 | E28: =E27/E10 -> 0.091309744 | F28: =F27/F10 -> 0.09837561 | G28: =G27/G10 -> 0.10036747 | H28: =H27/H10 -> 0.097689493 | I28: =I27/I10 -> 0.1094776 | J28: =J27/J10 -> 0.10879217 | K28: =K27/K10 -> 0.10847296 | L28: =L27/L10 -> 0.10691357 | ... R28: =R27/R10 -> 0.1108884 | S28: =S27/12 -> 1.7406311e+10 | T28: =T27/0.85 -> #DIV/0!
B29: 5 | C29: CHI PHÍ SẢN XUẤT CHUNG | D29: ='KQKD PET'!E27 -> 0 | E29: ='KQKD PET'!F27+'KQKD HD'!F27 -> 11547786451 | F29: =F30+F31+F32 -> 9.8327029e+08 | G29: =G30+G31+G32 -> 9.7009247e+08 | H29: =H30+H31+H32 -> 9.4610202e+08 | I29: =I30+I31+I32 -> 9.8519882e+08 | J29: =J30+J31+J32 -> 9.9516998e+08 | K29: =K30+K31+K32 -> 1.0293843e+09 | L29: =L30+L31+L32 -> 1.031294e+09 | M29: =M30+M31+M32 -> 1.0384301e+09 | ... Q29: =Q30+Q31+Q32 -> 1.120583e+09 | R29: =SUM(F29:Q29) -> 1.2401078e+10 | S29: =R29+R33 -> 1.695734e+10 | T29: =T28/12 -> #DIV/0!
B30: 5.1 | C30: Lương gián tiếp Sản xuất | D30: ='KQKD PET'!E28 -> 0 | E30: ='KQKD PET'!F28+'KQKD HD'!F28 -> 3749845944 | F30: ='KQKD PET'!G28+'KQKD HD'!G28+'KDKD DAY DAI'!G28 -> 2.9691432e+08 | G30: ='KQKD PET'!H28+'KQKD HD'!H28+'KDKD DAY DAI'!H28 -> 2.9460366e+08 | H30: ='KQKD PET'!I28+'KQKD HD'!I28+'KDKD DAY DAI'!I28 -> 2.8225475e+08 | I30: ='KQKD PET'!J28+'KQKD HD'!J28+'KDKD DAY DAI'!J28 -> 3.0506017e+08 | J30: ='KQKD PET'!K28+'KQKD HD'!K28+'KDKD DAY DAI'!K28 -> 2.8977549e+08 | K30: ='KQKD PET'!L28+'KQKD HD'!L28+'KDKD DAY DAI'!L28 -> 3.0532267e+08 | L30: ='KQKD PET'!M28+'KQKD HD'!M28+'KDKD DAY DAI'!M28 -> 2.9807777e+08 | M30: ='KQKD PET'!N28+'KQKD HD'!N28+'KDKD DAY DAI'!N28 -> 2.9807777e+08 | ... Q30: ='KQKD PET'!R28+'KQKD HD'!R28+'KDKD DAY DAI'!R28 -> 2.9807777e+08 | R30: =SUM(F30:Q30) -> 3.5686231e+09
B31: 5.2 | C31: Chi phí thuê xưởng | D31: ='KQKD PET'!E29 -> 0 | E31: ='KQKD PET'!F29+'KQKD HD'!F29 -> 5585152224 | F31: ='KQKD PET'!G29+'KQKD HD'!G29 -> 461679352 | G31: ='KQKD PET'!H29+'KQKD HD'!H29 -> 461679352 | H31: ='KQKD PET'!I29+'KQKD HD'!I29 -> 461679352 | I31: ='KQKD PET'!J29+'KQKD HD'!J29 -> 461679352 | J31: ='KQKD PET'!K29+'KQKD HD'!K29 -> 461679352 | K31: ='KQKD PET'!L29+'KQKD HD'!L29 -> 461679352 | L31: ='KQKD PET'!M29+'KQKD HD'!M29 -> 461679352 | ... Q31: ='KQKD PET'!R29+'KQKD HD'!R29 -> 461679352 | R31: =SUM(F31:Q31) -> 5540152224
B32: 5.3 | C32: Chi phí sản xuất (Ngoài lương, BOM, thuê xưởng, khấu hao) | D32: ='KQKD PET'!E30 -> 0 | E32: ='KQKD PET'!F30+'KQKD HD'!F30 -> 2212788283 | F32: ='KQKD PET'!G30+'KQKD HD'!G30+'KDKD DAY DAI'!G30 -> 2.2467662e+08 | G32: ='KQKD PET'!H30+'KQKD HD'!H30+'KDKD DAY DAI'!H30 -> 2.1380946e+08 | H32: ='KQKD PET'!I30+'KQKD HD'!I30+'KDKD DAY DAI'!I30 -> 2.0216791e+08 | I32: ='KQKD PET'!J30+'KQKD HD'!J30+'KDKD DAY DAI'!J30 -> 2.184593e+08 | J32: ='KQKD PET'!K30+'KQKD HD'!K30+'KDKD DAY DAI'!K30 -> 2.4371514e+08 | K32: ='KQKD PET'!L30+'KQKD HD'!L30+'KDKD DAY DAI'!L30 -> 2.6238226e+08 | L32: ='KQKD PET'!M30+'KQKD HD'!M30+'KDKD DAY DAI'!M30 -> 2.7153692e+08 | M32: ='KQKD PET'!N30+'KQKD HD'!N30+'KDKD DAY DAI'!N30 -> 2.7867294e+08 | ... Q32: ='KQKD PET'!R30+'KQKD HD'!R30+'KDKD DAY DAI'!R30 -> 3.6082585e+08 | R32: =SUM(F32:Q32) -> 3.2923026e+09
B33: 6 | C33: CHI PHÍ KHẤU HAO, CCDC | D33: ='KQKD PET'!E31 -> 0 | E33: ='KQKD PET'!F31+'KQKD HD'!F31 -> 7149747131 | F33: ='KQKD PET'!G31+'KQKD HD'!G31 -> 3.7748461e+08 | G33: ='KQKD PET'!H31+'KQKD HD'!H31 -> 3.7748461e+08 | H33: ='KQKD PET'!I31+'KQKD HD'!I31 -> 3.7492098e+08 | I33: ='KQKD PET'!J31+'KQKD HD'!J31 -> 3.7492098e+08 | J33: ='KQKD PET'!K31+'KQKD HD'!K31 -> 3.7492098e+08 | K33: ='KQKD PET'!L31+'KQKD HD'!L31 -> 3.7492098e+08 | L33: ='KQKD PET'!M31+'KQKD HD'!M31 -> 3.7492098e+08 | ... Q33: ='KQKD PET'!R31+'KQKD HD'!R31 -> 3.9228209e+08 | R33: =SUM(F33:Q33) -> 4.5562623e+09
B34: 7 | C34: LỢI NHUẬN GỘP | D34: ='KQKD PET'!E32 -> 64684339330 | E34: ='KQKD PET'!F32+'KQKD HD'!F32+126341842 -> -2.8162412e+09 | F34: =F27-F29-F33 -> -2.2793823e+08 | G34: =G27-G29-G33 -> -4.486578e+08 | H34: =H27-H29-H33 -> -71116452 | I34: =I27-I29-I33 -> 3.8870955e+08 | J34: =J27-J29-J33 -> 3.6778923e+08 | K34: =K27-K29-K33 -> 3.2847575e+08 | L34: =L27-L29-L33 -> 3.0165582e+08 | M34: =M27-M29-M33 -> 2.944048e+08 | ... Q34: =Q27-Q29-Q33 -> 6.2545408e+08 | R34: =SUM(F34:Q34) -> 3.1262398e+09
B35: 7.1 | C35: % lãi gộp/doanh thu | D35: ='KQKD PET'!E33 -> 0 | E35: =E34/E10 -> -0.016192024 | F35: =F34/F10 -> -0.01979452 | G35: =G34/G10 -> -0.050094206 | H35: =H34/H10 -> -0.0055582798 | I35: =I34/I10 -> 0.024333413 | J35: =J34/J10 -> 0.023023791 | K35: =K34/K10 -> 0.020562747 | L35: =L34/L10 -> 0.018883806 | ... R35: =R34/R10 -> 0.017261053
B36: 8 | C36: CHI PHÍ BÁN HÀNG & MKT & R&D | D36: ='KQKD PET'!E34 -> 0 | E36: ='KQKD PET'!F34+'KQKD HD'!F34 -> 0 | F36: =F37+F38+F39 -> 0 | G36: =G37+G38+G39 -> 0 | H36: =H37+H38+H39 -> 0 | I36: =I37+I38+I39 -> 0 | J36: =J37+J38+J39 -> 0 | K36: =K37+K38+K39 -> 0 | L36: =L37+L38+L39 -> 0 | M36: =M37+M38+M39 -> 0 | ... Q36: =Q37+Q38+Q39 -> 0 | R36: =SUM(F36:Q36) -> 0
B37: 8.1 | C37: Lương | D37: ='KQKD PET'!E35 -> 0 | E37: ='KQKD PET'!F35+'KQKD HD'!F35 -> 0 | F37: ='KQKD PET'!G35+'KQKD HD'!G35+'KDKD DAY DAI'!G35 -> 0 | G37: ='KQKD PET'!H35+'KQKD HD'!H35+'KDKD DAY DAI'!H35 -> 0 | H37: ='KQKD PET'!I35+'KQKD HD'!I35+'KDKD DAY DAI'!I35 -> 0 | I37: ='KQKD PET'!J35+'KQKD HD'!J35+'KDKD DAY DAI'!J35 -> 0 | J37: ='KQKD PET'!K35+'KQKD HD'!K35+'KDKD DAY DAI'!K35 -> 0 | K37: ='KQKD PET'!L35+'KQKD HD'!L35+'KDKD DAY DAI'!L35 -> 0 | L37: ='KQKD PET'!M35+'KQKD HD'!M35+'KDKD DAY DAI'!M35 -> 0 | M37: ='KQKD PET'!N35+'KQKD HD'!N35+'KDKD DAY DAI'!N35 -> 0 | ... Q37: ='KQKD PET'!R35+'KQKD HD'!R35+'KDKD DAY DAI'!R35 -> 0 | R37: =SUM(F37:Q37) -> 0
B38: 8.2 | C38: Chi phí bán hàng (ngoài lương, khấu hao) | D38: ='KQKD PET'!E36 -> 0 | E38: ='KQKD PET'!F36+'KQKD HD'!F36 -> 0 | F38: ='KQKD PET'!G36+'KQKD HD'!G36+'KDKD DAY DAI'!G36 -> 0 | G38: ='KQKD PET'!H36+'KQKD HD'!H36+'KDKD DAY DAI'!H36 -> 0 | H38: ='KQKD PET'!I36+'KQKD HD'!I36+'KDKD DAY DAI'!I36 -> 0 | I38: ='KQKD PET'!J36+'KQKD HD'!J36+'KDKD DAY DAI'!J36 -> 0 | J38: ='KQKD PET'!K36+'KQKD HD'!K36+'KDKD DAY DAI'!K36 -> 0 | K38: ='KQKD PET'!L36+'KQKD HD'!L36+'KDKD DAY DAI'!L36 -> 0 | L38: ='KQKD PET'!M36+'KQKD HD'!M36+'KDKD DAY DAI'!M36 -> 0 | M38: ='KQKD PET'!N36+'KQKD HD'!N36+'KDKD DAY DAI'!N36 -> 0 | ... Q38: ='KQKD PET'!R36+'KQKD HD'!R36+'KDKD DAY DAI'!R36 -> 0 | R38: =SUM(F38:Q38) -> 0
B39: 83 | C39: Khấu hao tài sản | D39: ='KQKD PET'!E37 -> 0 | E39: ='KQKD PET'!F37+'KQKD HD'!F37 -> 0 | F39: ='KQKD PET'!G37+'KQKD HD'!G37+'KDKD DAY DAI'!G37 -> 0 | G39: ='KQKD PET'!H37+'KQKD HD'!H37+'KDKD DAY DAI'!H37 -> 0 | H39: ='KQKD PET'!I37+'KQKD HD'!I37+'KDKD DAY DAI'!I37 -> 0 | I39: ='KQKD PET'!J37+'KQKD HD'!J37+'KDKD DAY DAI'!J37 -> 0 | J39: ='KQKD PET'!K37+'KQKD HD'!K37+'KDKD DAY DAI'!K37 -> 0 | K39: ='KQKD PET'!L37+'KQKD HD'!L37+'KDKD DAY DAI'!L37 -> 0 | L39: ='KQKD PET'!M37+'KQKD HD'!M37+'KDKD DAY DAI'!M37 -> 0 | M39: ='KQKD PET'!N37+'KQKD HD'!N37+'KDKD DAY DAI'!N37 -> 0 | ... Q39: ='KQKD PET'!R37+'KQKD HD'!R37+'KDKD DAY DAI'!R37 -> 0 | R39: =SUM(F39:Q39) -> 0
B40: 9 | C40: CHI PHÍ QUẢN LÝ | D40: ='KQKD PET'!E38 -> 0 | E40: ='KQKD PET'!F38+'KQKD HD'!F38 -> 3919574163 | F40: =F41+F42+F43 -> 5.5148923e+08 | G40: =G41+G42+G43 -> 4.8534478e+08 | H40: =H41+H42+H43 -> 5.1455941e+08 | I40: =I41+I42+I43 -> 5.1939125e+08 | J40: =J41+J42+J43 -> 5.0091629e+08 | K40: =K41+K42+K43 -> 6.637032e+08 | L40: =L41+L42+L43 -> 4.8847633e+08 | M40: =M41+M42+M43 -> 5.1885133e+08 | ... Q40: =Q41+Q42+Q43 -> 4.9062235e+08 | R40: =SUM(F40:Q40) -> 6.2045555e+09 | S40: 6.2045555e+09
B41: 9.1 | C41: Lương | D41: ='KQKD PET'!E39 -> 0 | E41: ='KQKD PET'!F39+'KQKD HD'!F39 -> 2289784061 | F41: ='KQKD PET'!G39+'KQKD HD'!G39 -> 3.2479914e+08 | G41: ='KQKD PET'!H39+'KQKD HD'!H39 -> 3.2569102e+08 | H41: ='KQKD PET'!I39+'KQKD HD'!I39 -> 3.0965466e+08 | I41: ='KQKD PET'!J39+'KQKD HD'!J39 -> 3.3272325e+08 | J41: ='KQKD PET'!K39+'KQKD HD'!K39 -> 3.1993578e+08 | K41: ='KQKD PET'!L39+'KQKD HD'!L39 -> 3.3302825e+08 | L41: ='KQKD PET'!M39+'KQKD HD'!M39 -> 3.2580138e+08 | ... Q41: ='KQKD PET'!R39+'KQKD HD'!R39 -> 3.2549638e+08 | R41: =SUM(F41:Q41) -> 3.9074709e+09 | S41: Chuyển CP lương Bp MH + An toàn: 627 -> 642
B42: 9.2 | C42: Chi phí quản lý (ngoài lương, khấu hao) | D42: ='KQKD PET'!E40 -> 0 | E42: ='KQKD PET'!F40+'KQKD HD'!F40 -> 1543688629 | F42: ='KQKD PET'!G40+'KQKD HD'!G40 -> 2.2404662e+08 | G42: ='KQKD PET'!H40+'KQKD HD'!H40 -> 1.5701029e+08 | H42: ='KQKD PET'!I40+'KQKD HD'!I40 -> 2.0226129e+08 | I42: ='KQKD PET'!J40+'KQKD HD'!J40 -> 1.8402454e+08 | J42: ='KQKD PET'!K40+'KQKD HD'!K40 -> 1.7833704e+08 | K42: ='KQKD PET'!L40+'KQKD HD'!L40 -> 3.2803148e+08 | L42: ='KQKD PET'!M40+'KQKD HD'!M40 -> 1.6003148e+08 | ... Q42: ='KQKD PET'!R40+'KQKD HD'!R40 -> 1.624825e+08 | R42: =SUM(F42:Q42) -> 2.265363e+09 | S42: PS: lương GĐ
B43: 9.3 | C43: Khấu hao tài sản | D43: ='KQKD PET'!E41 -> 0 | E43: ='KQKD PET'!F41+'KQKD HD'!F41 -> 86101473 | F43: ='KQKD PET'!G41+'KQKD HD'!G41 -> 2643466 | G43: ='KQKD PET'!H41+'KQKD HD'!H41 -> 2643466 | H43: ='KQKD PET'!I41+'KQKD HD'!I41 -> 2643466 | I43: ='KQKD PET'!J41+'KQKD HD'!J41 -> 2643466 | J43: ='KQKD PET'!K41+'KQKD HD'!K41 -> 2643466 | K43: ='KQKD PET'!L41+'KQKD HD'!L41 -> 2643466 | L43: ='KQKD PET'!M41+'KQKD HD'!M41 -> 2643466 | ... Q43: ='KQKD PET'!R41+'KQKD HD'!R41 -> 2643466 | R43: =SUM(F43:Q43) -> 31721592
B44: 10 | C44: DOANH THU/CHI PHÍ KHÁC | D44: ='KQKD PET'!E42 -> 0 | E44: ='KQKD PET'!F42+'KQKD HD'!F42 -> 82396393 | F44: ='KQKD PET'!G42+'KQKD HD'!G42 -> 0 | G44: ='KQKD PET'!H42+'KQKD HD'!H42 -> 0 | H44: ='KQKD PET'!I42+'KQKD HD'!I42 -> 0 | I44: ='KQKD PET'!J42+'KQKD HD'!J42 -> 0 | J44: ='KQKD PET'!K42+'KQKD HD'!K42 -> 0 | K44: ='KQKD PET'!L42+'KQKD HD'!L42 -> 0 | L44: ='KQKD PET'!M42+'KQKD HD'!M42 -> 0 | ... Q44: ='KQKD PET'!R42+'KQKD HD'!R42 -> 0 | R44: =SUM(F44:Q44) -> 0
B45: 11 | C45: LỢI NHUẬN THUẦN TỪ HOẠT ĐỘNG KINH DOANH | D45: ='KQKD PET'!E43 -> 64684339330 | E45: ='KQKD PET'!F43+'KQKD HD'!F43+126341842 -> -6.653419e+09 | F45: =F34-F36-F40+F44 -> -7.7942746e+08 | G45: =G34-G36-G40+G44 -> -9.3400257e+08 | H45: =H34-H36-H40+H44 -> -5.8567586e+08 | I45: =I34-I36-I40+I44 -> -1.3068171e+08 | J45: =J34-J36-J40+J44 -> -1.3312706e+08 | K45: =K34-K36-K40+K44 -> -3.3522744e+08 | L45: =L34-L36-L40+L44 -> -1.8682051e+08 | M45: =M34-M36-M40+M44 -> -2.2444654e+08 | ... Q45: =Q34-Q36-Q40+Q44 -> 1.3483173e+08 | R45: =SUM(F45:Q45) -> -3.0783157e+09
B46: 12 | C46: DOANH THU TÀI CHÍNH | D46: ='KQKD PET'!E44 -> 0 | E46: ='KQKD PET'!F44+'KQKD HD'!F44 -> 0 | F46: ='KQKD PET'!G44+'KQKD HD'!G44 -> 0 | G46: ='KQKD PET'!H44+'KQKD HD'!H44 -> 0 | H46: ='KQKD PET'!I44+'KQKD HD'!I44 -> 0 | I46: ='KQKD PET'!J44+'KQKD HD'!J44 -> 0 | J46: ='KQKD PET'!K44+'KQKD HD'!K44 -> 0 | K46: ='KQKD PET'!L44+'KQKD HD'!L44 -> 0 | L46: ='KQKD PET'!M44+'KQKD HD'!M44 -> 0 | ... Q46: ='KQKD PET'!R44+'KQKD HD'!R44 -> 0 | R46: =SUM(F46:Q46) -> 0
B47: 13 | C47: CHI PHÍ TÀI CHÍNH | D47: ='KQKD PET'!E45 -> 0 | E47: ='KQKD PET'!F45+'KQKD HD'!F45 -> 0 | F47: ='KQKD PET'!G45+'KQKD HD'!G45 -> 0 | G47: ='KQKD PET'!H45+'KQKD HD'!H45 -> 0 | H47: ='KQKD PET'!I45+'KQKD HD'!I45 -> 0 | I47: ='KQKD PET'!J45+'KQKD HD'!J45 -> 0 | J47: ='KQKD PET'!K45+'KQKD HD'!K45 -> 0 | K47: ='KQKD PET'!L45+'KQKD HD'!L45 -> 0 | L47: ='KQKD PET'!M45+'KQKD HD'!M45 -> 0 | ... Q47: ='KQKD PET'!R45+'KQKD HD'!R45 -> 0 | R47: =SUM(F47:Q47) -> 0
B48: 13.1 | C48: Trong đó: chi phí lãi vay | D48: ='KQKD PET'!E46 -> 0 | E48: ='KQKD PET'!F46+'KQKD HD'!F46 -> 0 | F48: ='KQKD PET'!G46+'KQKD HD'!G46 -> 0 | G48: ='KQKD PET'!H46+'KQKD HD'!H46 -> 0 | H48: ='KQKD PET'!I46+'KQKD HD'!I46 -> 0 | I48: ='KQKD PET'!J46+'KQKD HD'!J46 -> 0 | J48: ='KQKD PET'!K46+'KQKD HD'!K46 -> 0 | K48: ='KQKD PET'!L46+'KQKD HD'!L46 -> 0 | L48: ='KQKD PET'!M46+'KQKD HD'!M46 -> 0 | ... Q48: ='KQKD PET'!R46+'KQKD HD'!R46 -> 0 | R48: =SUM(F48:Q48) -> 0
B49: 14 | C49: LỢI NHUẬN TRƯỚC THUẾ | D49: ='KQKD PET'!E47 -> 64684339330 | E49: ='KQKD PET'!F47+'KQKD HD'!F47+126341842 -> -6.653419e+09 | F49: =F45+F46-F47 -> -7.7942746e+08 | G49: =G45+G46-G47 -> -9.3400257e+08 | H49: =H45+H46-H47 -> -5.8567586e+08 | I49: =I45+I46-I47 -> -1.3068171e+08 | J49: =J45+J46-J47 -> -1.3312706e+08 | K49: =K45+K46-K47 -> -3.3522744e+08 | L49: =L45+L46-L47 -> -1.8682051e+08 | M49: =M45+M46-M47 -> -2.2444654e+08 | ... Q49: =Q45+Q46-Q47 -> 1.3483173e+08 | R49: =SUM(F49:Q49) -> -3.0783157e+09
B50: 15 | C50: THUẾ TNDN | D50: ='KQKD PET'!E48 -> 0 | E50: ='KQKD PET'!F48+'KQKD HD'!F48 -> 0 | R50: =SUM(F50:Q50) -> 0
B51: 16 | C51: LỢI NHUẬN SAU THUẾ | D51: ='KQKD PET'!E49 -> 64684339330 | E51: ='KQKD PET'!F49+'KQKD HD'!F49 -> -6.7797608e+09 | F51: =F49-F50 -> -7.7942746e+08 | G51: =G49-G50 -> -9.3400257e+08 | H51: =H49-H50 -> -5.8567586e+08 | I51: =I49-I50 -> -1.3068171e+08 | J51: =J49-J50 -> -1.3312706e+08 | K51: =K49-K50 -> -3.3522744e+08 | L51: =L49-L50 -> -1.8682051e+08 | M51: =M49-M50 -> -2.2444654e+08 | ... Q51: =Q49-Q50 -> 1.3483173e+08 | R51: =SUM(F51:Q51) -> -3.0783157e+09
B52: 16.1 | C52: % LNST/doanh thu | D52: ='KQKD PET'!E50 -> 0.37864333 | E52: =E51/E10 -> -0.038980343 | F52: =F51/F10 -> -0.067686726 | G52: =G51/G10 -> -0.10428464 | H52: =H51/H10 -> -0.045774925 | I52: =I51/I10 -> -0.0081807406 | J52: =J51/J10 -> -0.0083338208 | K52: =K51/K10 -> -0.020985407 | L52: =L51/L10 -> -0.011695058 | ... R52: =R51/R10 -> -0.016996447
B53: 17 | C53: Khấu hao tài sản | D53: ='KQKD PET'!E51 -> 0 | E53: ='KQKD PET'!F51+'KQKD HD'!F51 -> 7235848604 | F53: ='KQKD PET'!G51+'KQKD HD'!G51 -> 3.8012808e+08 | G53: ='KQKD PET'!H51+'KQKD HD'!H51 -> 3.8012808e+08 | H53: ='KQKD PET'!I51+'KQKD HD'!I51 -> 3.7756444e+08 | I53: ='KQKD PET'!J51+'KQKD HD'!J51 -> 3.7756444e+08 | J53: ='KQKD PET'!K51+'KQKD HD'!K51 -> 3.7756444e+08 | K53: ='KQKD PET'!L51+'KQKD HD'!L51 -> 3.7756444e+08 | L53: ='KQKD PET'!M51+'KQKD HD'!M51 -> 3.7756444e+08 | ... Q53: ='KQKD PET'!R51+'KQKD HD'!R51 -> 3.9492555e+08 | R53: =SUM(F53:Q53) -> 4.5879839e+09
B54: 18 | C54: LỢI NHUẬN KHÔNG BAO GỒM KHẤU HAO, LÃI VAY | D54: ='KQKD PET'!E52 -> 64684339330 | E54: ='KQKD PET'!F52+'KQKD HD'!F52+126341842 -> 5.8242961e+08 | F54: =F51+F53 -> -3.9929938e+08 | G54: =G51+G53 -> -5.5387449e+08 | H54: =H51+H53 -> -2.0811142e+08 | I54: =I51+I53 -> 2.4688273e+08 | J54: =J51+J53 -> 2.4443738e+08 | K54: =K51+K53 -> 42336998 | L54: =L51+L53 -> 1.9074393e+08 | M54: =M51+M53 -> 1.5311791e+08 | ... Q54: =Q51+Q53 -> 5.2975728e+08 | R54: =SUM(F54:Q54) -> 1.5096683e+09
B55: 18.1 | C55: % LN không gồm khấu hao/doanh thu | D55: ='KQKD PET'!E53 -> 2.2164681e-12 | E55: =E54/E10 -> 0.0033486883 | F55: =F54/F10 -> -0.034675796 | G55: =G54/G10 -> -0.061842017 | H55: =H54/H10 -> -0.016265456 | I55: =I54/I10 -> 0.015454983 | J55: =J54/J10 -> 0.015301903 | K55: =K54/K10 -> 0.0026503174 | L55: =L54/L10 -> 0.011940666 | ... R55: =R54/R10 -> 0.0083354012
B58: 1. Hòa vốn (Bao gồm khấu hao) | D58: =D4 -> Thực tế năm 2024 | E58: =E4 -> KQKD 2025 | F58: =F4 -> T1 | G58: =G4 -> T2 | H58: =H4 -> T3 | I58: =I4 -> T4 | J58: =J4 -> T5 | K58: =K4 -> T6 | ... R58: =R4 -> KH 2026
B59: Sản lượng NVL hòa vốn (tấn) | D59: =IFERROR(D$60*(1+(D$19+D$20)/D$18),0) -> 0 | E59: =IFERROR(E$60*(1+(E$19+E$20)/E$18),0) -> 15458400 | F59: =F$60*(1+(F$19+F$20)/F$18) -> 1482857.3 | G59: =G$60*(1+(G$19+G$20)/G$18) -> 1393139 | H59: =H$60*(1+(H$19+H$20)/H$18) -> 1433406.9 | I59: =I$60*(1+(I$19+I$20)/I$18) -> 1310797.2 | J59: =J$60*(1+(J$19+J$20)/J$18) -> 1313087.6 | K59: =K$60*(1+(K$19+K$20)/K$18) -> 1455615.5 | L59: =L$60*(1+(L$19+L$20)/L$18) -> 1353073.9 | M59: =M$60*(1+(M$19+M$20)/M$18) -> 1379954.9 | ... R59: =R$60*(1+(R$19+R$20)/R$18) -> 15826760
B60: Sản lượng thành phẩm hòa vốn (tấn) | D60: =IFERROR((D$29+D$33+D$36+D$40)/(D$27/D$5),0) -> 0 | E60: =IFERROR((E$29+E$33+E$36+E$40)/(E$27/E$5),0) -> 13964687 | F60: =(F$29+F$33+F$36+F$40)/(F$27/F$5) -> 1284137.1 | G60: =(G$29+G$33+G$36+G$40)/(G$27/G$5) -> 1206442.1 | H60: =(H$29+H$33+H$36+H$40)/(H$27/H$5) -> 1241313.6 | I60: =(I$29+I$33+I$36+I$40)/(I$27/I$5) -> 1134103.8 | J60: =(J$29+J$33+J$36+J$40)/(J$27/J$5) -> 1136085.5 | K60: =(K$29+K$33+K$36+K$40)/(K$27/K$5) -> 1259400.9 | L60: =(L$29+L$33+L$36+L$40)/(L$27/L$5) -> 1170681.6 | M60: =(M$29+M$33+M$36+M$40)/(M$27/M$5) -> 1193939.2 | ... R60: =(R$29+R$33+R$36+R$40)/(R$27/R$5) -> 13494227
B61: Doanh thu hòa vốn (triệu đồng) | D61: =IFERROR(D$60*(D$10/D$5),0) -> 0 | E61: =IFERROR(E$60*(E$10/E$5),0) -> 2.4769654e+11 | F61: =F$60*(F$10/F$5) -> 1.9438193e+10 | G61: =G$60*(G$10/G$5) -> 1.8262111e+10 | H61: =H$60*(H$10/H$5) -> 1.8789967e+10 | I61: =I$60*(I$10/I$5) -> 1.7167997e+10 | J61: =J$60*(J$10/J$5) -> 1.7197995e+10 | K61: =K$60*(K$10/K$5) -> 1.9064736e+10 | L61: =L$60*(L$10/L$5) -> 1.772171e+10 | M61: =M$60*(M$10/M$5) -> 1.8073781e+10 | ... R61: =R$60*(R$10/R$5) -> 2.0887573e+11
B62: 2. Hòa vốn (Không bao gồm khấu hao) | D62: =D58 -> Thực tế năm 2024 | E62: =E58 -> KQKD 2025 | F62: =F58 -> T1 | G62: =G58 -> T2 | H62: =H58 -> T3 | I62: =I58 -> T4 | J62: =J58 -> T5 | K62: =K58 -> T6 | ... R62: =R58 -> KH 2026
B63: Sản lượng NVL hòa vốn (tấn) | D63: =IFERROR(D$64*(1+(D$19+D$20)/D$18),0) -> 0 | E63: =IFERROR(E$64*(1+(E$19+E$20)/E$18),0) -> 10512823 | F63: =F$64*(1+(F$19+F$20)/F$18) -> 1188085.5 | G63: =G$64*(1+(G$19+G$20)/G$18) -> 1104217.1 | H63: =H$64*(1+(H$19+H$20)/H$18) -> 1138566.7 | I63: =I$64*(1+(I$19+I$20)/I$18) -> 1047478.5 | J63: =J$64*(1+(J$19+J$20)/J$18) -> 1048109.9 | K63: =K$64*(1+(K$19+K$20)/K$18) -> 1189858.1 | L63: =L$64*(1+(L$19+L$20)/L$18) -> 1083440.2 | M63: =M$64*(1+(M$19+M$20)/M$18) -> 1110303 | ... R63: =R$64*(1+(R$19+R$20)/R$18) -> 12691744
B64: Sản lượng thành phẩm hòa vốn (tấn) | D64: =IFERROR((D$29+D$33+D$36+D$40-D53)/(D$27/D$5),0) -> 0 | E64: =IFERROR((E$29+E$33+E$36+E$40-E53)/(E$27/E$5),0) -> 9496990.9 | F64: =(F$29+F$33+F$36+F$40-F53)/(F$27/F$5) -> 1028868.1 | G64: =(G$29+G$33+G$36+G$40-G53)/(G$27/G$5) -> 956239.09 | H64: =(H$29+H$33+H$36+H$40-H53)/(H$27/H$5) -> 985985.47 | I64: =(I$29+I$33+I$36+I$40-I53)/(I$27/I$5) -> 906280.06 | J64: =(J$29+J$33+J$36+J$40-J53)/(J$27/J$5) -> 906826.33 | K64: =(K$29+K$33+K$36+K$40-K53)/(K$27/K$5) -> 1029467.1 | L64: =(L$29+L$33+L$36+L$40-L53)/(L$27/L$5) -> 937394.17 | M64: =(M$29+M$33+M$36+M$40-M53)/(M$27/M$5) -> 960635.96 | ... R64: =(R$29+R$33+R$36+R$40-R53)/(R$27/R$5) -> 10821246
B65: Doanh thu hòa vốn (triệu đồng) | D65: =IFERROR(D$64*(D$10/D$5),0) -> 0 | E65: =IFERROR(E$64*(E$10/E$5),0) -> 1.6845145e+11 | F65: =F$64*(F$10/F$5) -> 1.5574145e+10 | G65: =G$64*(G$10/G$5) -> 1.4474748e+10 | H65: =H$64*(H$10/H$5) -> 1.4925023e+10 | I65: =I$64*(I$10/I$5) -> 1.3719214e+10 | J65: =J$64*(J$10/J$5) -> 1.3727484e+10 | K65: =K$64*(K$10/K$5) -> 1.5584012e+10 | L65: =L$64*(L$10/L$5) -> 1.4190218e+10 | M65: =M$64*(M$10/M$5) -> 1.4542051e+10 | ... R65: =R$64*(R$10/R$5) -> 1.6750094e+11

Sheet KQKD PET
H2: 0.153846 | I2: 0.076923 | J2: 0.961538 | K2: 0.153846 | L2: 0.961538 | O2: 0.038462 | P2: 0.038462 | Q2: 0.961538
B3: MỤC TIÊU KẾT QUẢ KINH DOANH NĂM 2026 | G3: ='1.NVL Chai'!H16 -> 900000 | H3: ='1.NVL Chai'!I16 -> 700000 | I3: ='1.NVL Chai'!J16 -> 1000000 | J3: ='1.NVL Chai'!K16 -> 1250000 | K3: ='1.NVL Chai'!L16 -> 1250000 | L3: ='1.NVL Chai'!M16 -> 1250000 | M3: ='1.NVL Chai'!N16 -> 1250000 | N3: ='1.NVL Chai'!O16 -> 1250000 | ... R3: ='1.NVL Chai'!S16 -> 1300000 | S3: ĐVT: Triệu đồng
B4: STT | C4: Mục phí | D4: Thực tế năm 2023 | E4: Thực tế năm 2024 | F4: KQKD 2025 | G4: T1 | H4: T2 | I4: T3 | J4: T4 | K4: T5 | L4: T6 | M4: T7 | N4: T8 | O4: T9 | P4: T10 | Q4: T11 | R4: T12 | S4: KH 2026 | U4: Kiểm tra lại các sheet chi phí
B5: 1 | C5: SẢN LƯỢNG BÁN (TẤN) | D5: =D6+D7+D8 -> 0 | E5: =E6+E7+E8 -> 0 | F5: =F6+F7+F8 -> 9572318 | G5: =G6+G7+G8 -> 760725 | H5: =H6+H7+H8 -> 591675 | I5: =I6+I7+I8 -> 845250 | J5: =J6+J7+J8 -> 1055250 | K5: =K6+K7+K8 -> 1055250 | ... R5: =R6+R7+R8 -> 426660 | S5: =SUM(G5:R5) -> 9809130
B6: 1.1 | C6: Chai PET | F6: ='4.Doanh thu'!AF22 -> 7883386 | G6: ='4.Doanh thu'!F22 -> 519750 | H6: ='4.Doanh thu'!G22 -> 404250 | I6: ='4.Doanh thu'!H22 -> 577500 | J6: ='4.Doanh thu'!I22 -> 720000 | K6: ='4.Doanh thu'!J22 -> 720000 | L6: ='4.Doanh thu'!K22 -> 720000 | M6: ='4.Doanh thu'!L22 -> 720000 | N6: ='4.Doanh thu'!M22 -> 720000 | ... R6: ='4.Doanh thu'!Q22 -> 78000 | S6: =SUM(G6:R6) -> 6055500
B7: 1.2 | C7: Vảy PET | F7: ='4.Doanh thu'!AF80 -> 1688932 | G7: ='4.Doanh thu'!F80 -> 240975 | H7: ='4.Doanh thu'!G80 -> 187425 | I7: ='4.Doanh thu'!H80 -> 267750 | J7: ='4.Doanh thu'!I80 -> 335250 | K7: ='4.Doanh thu'!J80 -> 335250 | L7: ='4.Doanh thu'!K80 -> 335250 | M7: ='4.Doanh thu'!L80 -> 335250 | N7: ='4.Doanh thu'!M80 -> 335250 | ... R7: ='4.Doanh thu'!Q80 -> 348660 | S7: =SUM(G7:R7) -> 3753630
B8: 1.3 | C8: Vảy HD | S8: =SUM(G8:R8) -> 0
B9: 2 | C9: DOANH THU | D9: =D10+D11+D12+D13 -> 0 | E9: =E10+E11+E12+E13 -> 64684339330 | F9: =F10+F11+F12+F13 -> 170831845591 | G9: =G10+G11+G12+G13 -> 11515218750 | H9: =H10+H11+H12+H13 -> 8956281250 | I9: =I10+I11+I12+I13 -> 12794687500 | J9: =J10+J11+J12+J13 -> 15974312500 | K9: =K10+K11+K12+K13 -> 15974312500 | ... R9: =R10+R11+R12+R13 -> 6551285000 | S9: =SUM(G9:R9) -> 148765917500
B10: 2.1 | C10: Chai PET | E10: =64684339330 -> 64684339330 | F10: ='4.Doanh thu'!AF60 -> 140100816887 | G10: ='4.Doanh thu'!F60 -> 7626150000 | H10: ='4.Doanh thu'!G60 -> 5931450000 | I10: ='4.Doanh thu'!H60 -> 8473500000 | J10: ='4.Doanh thu'!I60 -> 10563750000 | K10: ='4.Doanh thu'!J60 -> 10563750000 | L10: ='4.Doanh thu'!K60 -> 10563750000 | M10: ='4.Doanh thu'!L60 -> 10563750000 | N10: ='4.Doanh thu'!M60 -> 10563750000 | ... R10: ='4.Doanh thu'!Q60 -> 924300000 | S10: =SUM(G10:R10) -> 88186500000
B11: 2.2 | C11: Vảy PET | F11: ='4.Doanh thu'!AF138 -> 30731028704 | G11: ='4.Doanh thu'!F138 -> 3889068750 | H11: ='4.Doanh thu'!G138 -> 3024831250 | I11: ='4.Doanh thu'!H138 -> 4321187500 | J11: ='4.Doanh thu'!I138 -> 5410562500 | K11: ='4.Doanh thu'!J138 -> 5410562500 | L11: ='4.Doanh thu'!K138 -> 5410562500 | M11: ='4.Doanh thu'!L138 -> 5410562500 | N11: ='4.Doanh thu'!M138 -> 5410562500 | ... R11: ='4.Doanh thu'!Q138 -> 5626985000 | S11: =SUM(G11:R11) -> 60579417500
B12: 2.3 | C12: Vảy HD | S12: =SUM(G12:R12) -> 0
B13: 2.4 | C13: Khác | S13: =SUM(G13:R13) -> 0
B14: 3 | C14: BIẾN PHÍ | D14: =D15+D23 -> 0 | E14: =E15+E23 -> 0 | F14: =F15+F23 -> 1.5431149e+11 | G14: =G15+G23 -> 1.0382402e+10 | H14: =H15+H23 -> 8.057362e+09 | I14: =I15+I23 -> 1.1544781e+10 | J14: =J15+J23 -> 1.4225483e+10 | K14: =K15+K23 -> 1.4236432e+10 | ... R14: =R15+R23 -> 7.778246e+09 | S14: =SUM(G14:R14) -> 1.3877818e+11
B15: 3.1 | C15: BIẾN PHÍ SẢN XUẤT | D15: =D16+D20+D21+D22 -> 0 | E15: =E16+E20+E21+E22 -> 0 | F15: =F16+F20+F21+F22 -> 1.5121452e+11 | G15: =G16+G20+G21+G22 -> 1.0123301e+10 | H15: =H16+H20+H21+H22 -> 7.8558393e+09 | I15: =I16+I20+I21+I22 -> 1.1256891e+10 | J15: =J16+J20+J21+J22 -> 1.3866114e+10 | K15: =K16+K20+K21+K22 -> 1.3877064e+10 | ... R15: =R16+R20+R21+R22 -> 7.6430092e+09 | S15: =SUM(G15:R15) -> 1.3546774e+11
B16: 3.1.1 | C16: Nguyên vật liệu chính (nhựa, gồm hao hụt) | F16: 1.4101136e+11 | G16: ='1.NVL Chai'!H42-'KQKD HD'!G16 -> 9000000000 | H16: ='1.NVL Chai'!I42-'KQKD HD'!H16 -> 7000000000 | I16: ='1.NVL Chai'!J42-'KQKD HD'!I16 -> 10000000000 | J16: ='1.NVL Chai'!K42-'KQKD HD'!J16 -> 12500000000 | K16: ='1.NVL Chai'!L42-'KQKD HD'!K16 -> 12500000000 | L16: ='1.NVL Chai'!M42-'KQKD HD'!L16 -> 12500000000 | M16: ='1.NVL Chai'!N42-'KQKD HD'!M16 -> 12500000000 | N16: ='1.NVL Chai'!O42-'KQKD HD'!N16 -> 12500000000 | ... R16: ='1.NVL Chai'!S42-'KQKD HD'!R16 -> 6292000000 | S16: =SUM(G16:R16) -> 119876000000
B17: 3.1.2 | C17: Trong đó: i/ Hao hụt CĐ phân loại chai | F17: 1.3748236e+10 | G17: =SUM('3.Thanh pham'!F$211:F$213)*'1.NVL Chai'!H$34 -> 1125000000 | H17: =SUM('3.Thanh pham'!G$211:G$213)*'1.NVL Chai'!I$34 -> 875000000 | I17: =SUM('3.Thanh pham'!H$211:H$213)*'1.NVL Chai'!J$34 -> 1250000000 | J17: =SUM('3.Thanh pham'!I$211:I$213)*'1.NVL Chai'!K$34 -> 1575000000 | K17: =SUM('3.Thanh pham'!J$211:J$213)*'1.NVL Chai'!L$34 -> 1575000000 | L17: =SUM('3.Thanh pham'!K$211:K$213)*'1.NVL Chai'!M$34 -> 1575000000 | M17: =SUM('3.Thanh pham'!L$211:L$213)*'1.NVL Chai'!N$34 -> 1575000000 | N17: =SUM('3.Thanh pham'!M$211:M$213)*'1.NVL Chai'!O$34 -> 1575000000 | ... R17: =SUM('3.Thanh pham'!Q$211:Q$213)*'1.NVL Chai'!S$34 -> 1638000000 | S17: =SUM(G17:R17) -> 17614000000
C18: ii/ Hao hụt CĐ băm vảy | F18: 1.715399e+09 | G18: =('3.Thanh pham'!F$214*'1.NVL Chai'!H$34) -> 267750000 | H18: =('3.Thanh pham'!G$214*'1.NVL Chai'!I$34) -> 208250000 | I18: =('3.Thanh pham'!H$214*'1.NVL Chai'!J$34) -> 297500000 | J18: =('3.Thanh pham'!I$214*'1.NVL Chai'!K$34) -> 372500000 | K18: =('3.Thanh pham'!J$214*'1.NVL Chai'!L$34) -> 372500000 | L18: =('3.Thanh pham'!K$214*'1.NVL Chai'!M$34) -> 372500000 | M18: =('3.Thanh pham'!L$214*'1.NVL Chai'!N$34) -> 372500000 | N18: =('3.Thanh pham'!M$214*'1.NVL Chai'!O$34) -> 372500000 | ... R18: =('3.Thanh pham'!Q$214*'1.NVL Chai'!S$34) -> 789880000 | S18: =SUM(G18:R18) -> 5378140000
B19: 3.1.3 | C19: % chi phí nguyên liệu/doanh thu | D19: =IFERROR(D16/$F$9,0) -> 0 | E19: =IFERROR(E16/$F$9,0) -> 0 | F19: =IFERROR(F16/$F$9,0) -> 0.82543955 | G19: =G16/G9 -> 0.78157438 | H19: =H16/H9 -> 0.78157438 | I19: =I16/I9 -> 0.78157438 | J19: =J16/J9 -> 0.78250629 | K19: =K16/K9 -> 0.78250629 | L19: =L16/L9 -> 0.78250629 | M19: =M16/M9 -> 0.78250629 | N19: =N16/N9 -> 0.78250629 | ... S19: =S16/S9 -> 0.80580285
B20: 3.1.4 | C20: Nguyên vật liệu phụ | F20: =SUM(CPSX!AK19:AK25) -> 2.7789895e+09 | G20: =SUM(CPSX!K19:K25) -> 3.0802692e+08 | H20: =SUM(CPSX!L19:L25) -> 2.3889538e+08 | I20: =SUM(CPSX!M19:M25) -> 3.3811419e+08 | J20: =SUM(CPSX!N19:N25) -> 4.2242376e+08 | K20: =SUM(CPSX!O19:O25) -> 4.2112376e+08 | L20: =SUM(CPSX!P19:P25) -> 4.2078209e+08 | M20: =SUM(CPSX!Q19:Q25) -> 4.2015876e+08 | N20: =SUM(CPSX!R19:R25) -> 4.2027376e+08 | ... R20: =SUM(CPSX!V19:V25) -> 3.9947829e+08 | S20: =SUM(G20:R20) -> 4.6095523e+09
B21: 3.1.5 | C21: Điện sản xuất | F21: =CPSX!$AK$18 -> 1323352660 | G21: =CPSX!K$18 -> 1.1567843e+08 | H21: =CPSX!L$18 -> 89972114 | I21: =CPSX!M$18 -> 1.2853159e+08 | J21: =CPSX!N$18 -> 1.6071292e+08 | K21: =CPSX!O$18 -> 1.6071292e+08 | L21: =CPSX!P$18 -> 1.6071292e+08 | M21: =CPSX!Q$18 -> 1.6071292e+08 | N21: =CPSX!R$18 -> 1.6071292e+08 | ... R21: =CPSX!V$18 -> 1.6714144e+08 | S21: =SUM(G21:R21) -> 1.799884e+09
B22: 3.1.6 | C22: Nhân công trực tiếp | F22: =SUM(CPSX!AK6:AK16) -> 6100821040 | G22: =SUM(CPSX!K6:K16) -> 6.995961e+08 | H22: =SUM(CPSX!L6:L16) -> 5.2697176e+08 | I22: =SUM(CPSX!M6:M16) -> 7.902456e+08 | J22: =SUM(CPSX!N6:N16) -> 7.8297773e+08 | K22: =SUM(CPSX!O6:O16) -> 7.9522688e+08 | L22: =SUM(CPSX!P6:P16) -> 8.0066773e+08 | M22: =SUM(CPSX!Q6:Q16) -> 826201238 | N22: =SUM(CPSX!R6:R16) -> 826201238 | ... R22: =SUM(CPSX!V6:V16) -> 7.8438943e+08 | S22: =SUM(G22:R22) -> 9.1823057e+09
B23: 3.2 | C23: BIẾN PHÍ BÁN HÀNG | D23: =D24 -> 0 | E23: =E24 -> 0 | F23: =F24 -> 3.0969688e+09 | G23: =G24 -> 259100625 | H23: =H24 -> 2.0152271e+08 | I23: =I24 -> 2.8788958e+08 | J23: =J24 -> 359368750 | K23: =K24 -> 359368750 | ... R23: =R24 -> 1.3523683e+08 | S23: =SUM(G23:R23) -> 3.3104359e+09
C24: Chi phí vận chuyển | F24: =CPBH!AK8 -> 3.0969688e+09 | G24: =SUM(CPBH!K5:K6) -> 259100625 | H24: =SUM(CPBH!L5:L6) -> 2.0152271e+08 | I24: =SUM(CPBH!M5:M6) -> 2.8788958e+08 | J24: =SUM(CPBH!N5:N6) -> 359368750 | K24: =SUM(CPBH!O5:O6) -> 359368750 | L24: =SUM(CPBH!P5:P6) -> 359368750 | M24: =SUM(CPBH!Q5:Q6) -> 359368750 | N24: =SUM(CPBH!R5:R6) -> 359368750 | ... R24: =SUM(CPBH!V5:V6) -> 1.3523683e+08 | S24: =SUM(G24:R24) -> 3.3104359e+09
B25: 4 | C25: LÃI SAU BIẾN PHÍ | D25: =D9-D14 -> 0 | E25: =E9-E14 -> 64684339330 | F25: =F9-F14 -> 1.6520352e+10 | G25: =G9-G14 -> 1.1328167e+09 | H25: =H9-H14 -> 8.9891929e+08 | I25: =I9-I14 -> 1.2499065e+09 | J25: =J9-J14 -> 1.7488293e+09 | K25: =K9-K14 -> 1.7378802e+09 | ... R25: =R9-R14 -> -1.226961e+09 | S25: =SUM(G25:R25) -> 9.9877397e+09
B26: 4.1 | C26: % lãi biến phí/doanh thu | D26: =IFERROR(D23/$F$9,0) -> 0 | E26: =IFERROR(E23/$F$9,0) -> 0 | F26: =IFERROR(F23/$F$9,0) -> 0.018128756 | G26: =G25/G9 -> 0.09837561 | H26: =H25/H9 -> 0.10036747 | I26: =I25/I9 -> 0.097689493 | J26: =J25/J9 -> 0.1094776 | K26: =K25/K9 -> 0.10879217 | L26: =L25/L9 -> 0.10847296 | M26: =M25/M9 -> 0.10691357 | N26: =N25/N9 -> 0.10690637 | ... S26: =S25/S9 -> 0.067137284
B27: 5 | C27: CHI PHÍ SẢN XUẤT CHUNG | D27: =D28+D29+D30 -> 0 | E27: =E28+E29+E30 -> 0 | F27: =F28+F29+F30 -> 8620348627 | G27: =G28+G29+G30 -> 7.5243062e+08 | H27: =H28+H29+H30 -> 7.3925279e+08 | I27: =I28+I29+I30 -> 7.1526234e+08 | J27: =J28+J29+J30 -> 7.5435915e+08 | K27: =K28+K29+K30 -> 7.6433031e+08 | ... R27: =R28+R29+R30 -> 8.7431489e+08 | S27: =SUM(G27:R27) -> 9.5847166e+09
B28: 5.1 | C28: Lương gián tiếp Sản xuất | F28: =SUM(CPSX!AK72:AK82) -> 3749845944 | G28: =SUM(CPSX!K$72:K$83) -> 2.9691432e+08 | H28: =SUM(CPSX!L$72:L$83) -> 2.9460366e+08 | I28: =SUM(CPSX!M$72:M$83) -> 2.8225475e+08 | J28: =SUM(CPSX!N$72:N$83) -> 3.0506017e+08 | K28: =SUM(CPSX!O$72:O$83) -> 2.8977549e+08 | L28: =SUM(CPSX!P$72:P$83) -> 3.0532267e+08 | M28: =SUM(CPSX!Q$72:Q$83) -> 2.9807777e+08 | N28: =SUM(CPSX!R$72:R$83) -> 2.9807777e+08 | ... R28: =SUM(CPSX!V$72:V$83) -> 2.9807777e+08 | S28: =SUM(G28:R28) -> 3.5686231e+09
B29: 5.2 | C29: Chi phí thuê xưởng | F29: =CPSX!AK88 -> 2815076112 | G29: =CPSX!K$88 -> 230839676 | H29: =CPSX!L$88 -> 230839676 | I29: =CPSX!M$88 -> 230839676 | J29: =CPSX!N$88 -> 230839676 | K29: =CPSX!O$88 -> 230839676 | L29: =CPSX!P$88 -> 230839676 | M29: =CPSX!Q$88 -> 230839676 | N29: =CPSX!R$88 -> 230839676 | ... R29: =CPSX!V$88 -> 230839676 | S29: =SUM(G29:R29) -> 2770076112
B30: 5.3 | C30: Chi phí sản xuất (Ngoài lương, BOM, thuê xưởng, khấu hao) | F30: =SUM(CPSX!AK16:AK17,CPSX!$AK$71)-'KQKD PET'!F28-'KQKD PET'!F29-'KQKD PET'!F31 -> 2055426571 | G30: =SUM(CPSX!K$71)-'KQKD PET'!G28-'KQKD PET'!G29-'KQKD PET'!G31 -> 2.2467662e+08 | H30: =SUM(CPSX!L$71)-'KQKD PET'!H28-'KQKD PET'!H29-'KQKD PET'!H31 -> 2.1380946e+08 | I30: =SUM(CPSX!M$71)-'KQKD PET'!I28-'KQKD PET'!I29-'KQKD PET'!I31 -> 2.0216791e+08 | J30: =SUM(CPSX!N$71)-'KQKD PET'!J28-'KQKD PET'!J29-'KQKD PET'!J31 -> 2.184593e+08 | K30: =SUM(CPSX!O$71)-'KQKD PET'!K28-'KQKD PET'!K29-'KQKD PET'!K31 -> 2.4371514e+08 | L30: =SUM(CPSX!P$71)-'KQKD PET'!L28-'KQKD PET'!L29-'KQKD PET'!L31 -> 2.6238226e+08 | M30: =SUM(CPSX!Q$71)-'KQKD PET'!M28-'KQKD PET'!M29-'KQKD PET'!M31 -> 2.7153692e+08 | N30: =SUM(CPSX!R$71)-'KQKD PET'!N28-'KQKD PET'!N29-'KQKD PET'!N31 -> 2.7867294e+08 | ... R30: =SUM(CPSX!V$71)-'KQKD PET'!R28-'KQKD PET'!R29-'KQKD PET'!R31 -> 3.4539745e+08 | S30: =SUM(G30:R30) -> 3.2460174e+09
B31: 6 | C31: CHI PHÍ KHẤU HAO, CCDC | F31: =CPSX!AK99 -> 3687386699 | G31: =CPSX!K$99 -> 1.4379769e+08 | H31: =CPSX!L$99 -> 1.4379769e+08 | I31: =CPSX!M$99 -> 1.4123406e+08 | J31: =CPSX!N$99 -> 1.4123406e+08 | K31: =CPSX!O$99 -> 1.4123406e+08 | L31: =CPSX!P$99 -> 1.4123406e+08 | M31: =CPSX!Q$99 -> 1.4123406e+08 | N31: =CPSX!R$99 -> 1.4123406e+08 | ... R31: =CPSX!V$99 -> 1.4123406e+08 | S31: =SUM(G31:R31) -> 1.699936e+09
B32: 7 | C32: LỢI NHUẬN GỘP | D32: =D25-D27-D31 -> 0 | E32: =E25-E27-E31 -> 64684339330 | F32: =F25-F27-F31 -> 4.2126165e+09 | G32: =G25-G27-G31 -> 2.3658836e+08 | H32: =H25-H27-H31 -> 15868797 | I32: =I25-I27-I31 -> 3.9341014e+08 | J32: =J25-J27-J31 -> 8.5323614e+08 | K32: =K25-K27-K31 -> 8.3231583e+08 | ... R32: =R25-R27-R31 -> -2.2425099e+09 | S32: =SUM(G32:R32) -> -1.2969129e+09
B33: 7.1 | C33: % lãi gộp/doanh thu | D33: =IFERROR(D30/$F$9,0) -> 0 | E33: =IFERROR(E30/$F$9,0) -> 0 | F33: =IFERROR(F30/$F$9,0) -> 0.01203187 | G33: =G32/G9 -> 0.020545712 | H33: =H32/H9 -> 0.0017718065 | I33: =I32/I9 -> 0.030747929 | J33: =J32/J9 -> 0.053413012 | K33: =K32/K9 -> 0.05210339 | L33: =L32/L9 -> 0.049642346 | M33: =M32/M9 -> 0.047963405 | N33: =N32/N9 -> 0.047509487 | ... S33: =S32/S9 -> -0.0087178094
B34: 8 | C34: CHI PHÍ BÁN HÀNG & MKT & R&D | D34: =D35+D36+D37 -> 0 | E34: =E35+E36+E37 -> 0 | F34: =F35+F36+F37 -> 0 | G34: =G35+G36+G37 -> 0 | H34: =H35+H36+H37 -> 0 | I34: =I35+I36+I37 -> 0 | J34: =J35+J36+J37 -> 0 | K34: =K35+K36+K37 -> 0 | ... R34: =R35+R36+R37 -> 0 | S34: =SUM(G34:R34) -> 0
B35: 8.1 | C35: Lương | S35: =SUM(G35:R35) -> 0
B36: 8.2 | C36: Chi phí bán hàng (ngoài lương, khấu hao) | S36: =SUM(G36:R36) -> 0
B37: 8.3 | C37: Khấu hao tài sản | S37: =SUM(G37:R37) -> 0
B38: 9 | C38: CHI PHÍ QUẢN LÝ | D38: =D39+D40+D41 -> 0 | E38: =E39+E40+E41 -> 0 | F38: =F39+F40+F41 -> 3919574163 | G38: =G39+G40+G41 -> 5.5148923e+08 | H38: =H39+H40+H41 -> 4.8534478e+08 | I38: =I39+I40+I41 -> 5.1455941e+08 | J38: =J39+J40+J41 -> 5.1939125e+08 | K38: =K39+K40+K41 -> 5.0091629e+08 | ... R38: =R39+R40+R41 -> 4.9062235e+08 | S38: =SUM(G38:R38) -> 6.2045555e+09
B39: 9.1 | C39: Lương | F39: =SUM(CPQL!AK5:AK14) -> 2289784061 | G39: =SUM(CPQL!K5:K14) -> 3.2479914e+08 | H39: =SUM(CPQL!L5:L14) -> 3.2569102e+08 | I39: =SUM(CPQL!M5:M14) -> 3.0965466e+08 | J39: =SUM(CPQL!N5:N14) -> 3.3272325e+08 | K39: =SUM(CPQL!O5:O14) -> 3.1993578e+08 | L39: =SUM(CPQL!P5:P14) -> 3.3302825e+08 | M39: =SUM(CPQL!Q5:Q14) -> 3.2580138e+08 | N39: =SUM(CPQL!R5:R14) -> 3.2580138e+08 | ... R39: =SUM(CPQL!V5:V14) -> 3.2549638e+08 | S39: =SUM(G39:R39) -> 3.9074709e+09
B40: 9.2 | C40: Chi phí quản lý (ngoài lương, khấu hao) | F40: =CPQL!AK65-'KQKD PET'!F39-'KQKD PET'!F41 -> 1543688629 | G40: =CPQL!K65-G39-G41 -> 2.2404662e+08 | H40: =CPQL!L65-H39-H41 -> 1.5701029e+08 | I40: =CPQL!M65-I39-I41 -> 2.0226129e+08 | J40: =CPQL!N65-J39-J41 -> 1.8402454e+08 | K40: =CPQL!O65-K39-K41 -> 1.7833704e+08 | L40: =CPQL!P65-L39-L41 -> 3.2803148e+08 | M40: =CPQL!Q65-M39-M41 -> 1.6003148e+08 | N40: =CPQL!R65-N39-N41 -> 1.9040648e+08 | ... R40: =CPQL!V65-R39-R41 -> 1.624825e+08 | S40: =SUM(G40:R40) -> 2.265363e+09
B41: 9.3 | C41: Khấu hao tài sản | F41: =CPQL!AK61 -> 86101473 | G41: =CPQL!K61 -> 2643466 | H41: =CPQL!L61 -> 2643466 | I41: =CPQL!M61 -> 2643466 | J41: =CPQL!N61 -> 2643466 | K41: =CPQL!O61 -> 2643466 | L41: =CPQL!P61 -> 2643466 | M41: =CPQL!Q61 -> 2643466 | N41: =CPQL!R61 -> 2643466 | ... R41: =CPQL!V61 -> 2643466 | S41: =SUM(G41:R41) -> 31721592
B42: 10 | C42: DOANH THU/CHI PHÍ KHÁC | F42: 82396393 | S42: =SUM(G42:R42) -> 0 | U42: <= Nhập số liệu
B43: 11 | C43: LỢI NHUẬN THUẦN TỪ HOẠT ĐỘNG KINH DOANH | D43: =D32-D34-D38+D42 -> 0 | E43: =E32-E34-E38+E42 -> 64684339330 | F43: =F32-F34-F38+F42 -> 3.7543874e+08 | G43: =G32-G34-G38+G42 -> -3.1490086e+08 | H43: =H32-H34-H38+H42 -> -4.6947598e+08 | I43: =I32-I34-I38+I42 -> -1.2114927e+08 | J43: =J32-J34-J38+J42 -> 3.3384489e+08 | K43: =K32-K34-K38+K42 -> 3.3139954e+08 | ... R43: =R32-R34-R38+R42 -> -2.7331323e+09 | S43: =SUM(G43:R43) -> -7.5014684e+09
B44: 12 | C44: DOANH THU TÀI CHÍNH | S44: =SUM(G44:R44) -> 0 | U44: <= Nhập số liệu
B45: 13 | C45: CHI PHÍ TÀI CHÍNH | S45: =SUM(G45:R45) -> 0 | U45: <= Nhập số liệu
B46: 13.1 | C46: Trong đó: chi phí lãi vay | S46: =SUM(G46:R46) -> 0
B47: 14 | C47: LỢI NHUẬN TRƯỚC THUẾ | D47: =D43+D44-D45 -> 0 | E47: =E43+E44-E45 -> 64684339330 | F47: =F43+F44-F45 -> 3.7543874e+08 | G47: =G43+G44-G45 -> -3.1490086e+08 | H47: =H43+H44-H45 -> -4.6947598e+08 | I47: =I43+I44-I45 -> -1.2114927e+08 | J47: =J43+J44-J45 -> 3.3384489e+08 | K47: =K43+K44-K45 -> 3.3139954e+08 | ... R47: =R43+R44-R45 -> -2.7331323e+09 | S47: =SUM(G47:R47) -> -7.5014684e+09 | T47: 1.2313803e+09
B48: 15 | C48: THUẾ TNDN | S48: =SUM(G48:R48) -> 0 | T48: =T47-S47 -> 8.7328487e+09 | U48: <= Nhập số liệu
B49: 16 | C49: LỢI NHUẬN SAU THUẾ | D49: =D47-D48 -> 0 | E49: =E47-E48 -> 64684339330 | F49: =F47-F48 -> 3.7543874e+08 | G49: =G47-G48 -> -3.1490086e+08 | H49: =H47-H48 -> -4.6947598e+08 | I49: =I47-I48 -> -1.2114927e+08 | J49: =J47-J48 -> 3.3384489e+08 | K49: =K47-K48 -> 3.3139954e+08 | ... R49: =R47-R48 -> -2.7331323e+09 | S49: =SUM(G49:R49) -> -7.5014684e+09
B50: 16.1 | C50: % LNST/doanh thu | D50: =IFERROR(D47/$F$9,0) -> 0 | E50: =IFERROR(E47/$F$9,0) -> 0.37864333 | F50: =IFERROR(F47/$F$9,0) -> 0.0021977093 | G50: =G49/G9 -> -0.027346494 | H50: =H49/H9 -> -0.052418628 | I50: =I49/I9 -> -0.0094687167 | J50: =J49/J9 -> 0.020898858 | K50: =K49/K9 -> 0.020745778 | L50: =L49/L9 -> 0.0080941918 | M50: =M49/M9 -> 0.01738454 | N50: =N49/N9 -> 0.015029132 | ... S50: =S49/S9 -> -0.050424644
B51: 17 | C51: Khấu hao tài sản | F51: =CPSX!AK99+F41 -> 3773488172 | G51: =SUM(PB_TSCD!AF130:AF131,PB_TSCD!AF134,PB_TSCD!AF135) -> 1.4644116e+08 | H51: =SUM(PB_TSCD!AG130:AG131,PB_TSCD!AG134,PB_TSCD!AG135) -> 1.4644116e+08 | I51: =SUM(PB_TSCD!AH130:AH131,PB_TSCD!AH134,PB_TSCD!AH135) -> 1.4387752e+08 | J51: =SUM(PB_TSCD!AI130:AI131,PB_TSCD!AI134,PB_TSCD!AI135) -> 1.4387752e+08 | K51: =SUM(PB_TSCD!AJ130:AJ131,PB_TSCD!AJ134,PB_TSCD!AJ135) -> 1.4387752e+08 | L51: =SUM(PB_TSCD!AK130:AK131,PB_TSCD!AK134,PB_TSCD!AK135) -> 1.4387752e+08 | M51: =SUM(PB_TSCD!AL130:AL131,PB_TSCD!AL134,PB_TSCD!AL135) -> 1.4387752e+08 | N51: =SUM(PB_TSCD!AM130:AM131,PB_TSCD!AM134,PB_TSCD!AM135) -> 1.4387752e+08 | ... R51: =SUM(PB_TSCD!AQ130:AQ131,PB_TSCD!AQ134,PB_TSCD!AQ135) -> 1.4387752e+08 | S51: =SUM(G51:R51) -> 1.7316576e+09 | T51: ='KQKD HD'!S51 -> 2.8563264e+09 | U51: =T51+S51 -> 4.5879839e+09
B52: 18 | C52: LỢI NHUẬN KHÔNG BAO GỒM KHẤU HAO, LÃI VAY | D52: =D49+D51 -> 0 | E52: =E49+E51 -> 64684339330 | F52: =F49+F51 -> 4.1489269e+09 | G52: =G49+G51 -> -1.684597e+08 | H52: =H49+H51 -> -3.2303482e+08 | I52: =I49+I51 -> 22728253 | J52: =J49+J51 -> 4.7772241e+08 | K52: =K49+K51 -> 4.7527706e+08 | ... R52: =R49+R51 -> -2.5892548e+09 | S52: =SUM(G52:R52) -> -5.7698108e+09
B53: 18.1 | C53: % LN không gồm khấu hao/doanh thu | D53: =IFERROR(D50/$F$9,0) -> 0 | E53: =IFERROR(E50/$F$9,0) -> 2.2164681e-12 | F53: =IFERROR(F50/$F$9,0) -> 1.2864752e-14 | G53: =G52/G9 -> -0.01462931 | H53: =H52/H9 -> -0.036067963 | I53: =I52/I9 -> 0.0017763821 | J53: =J52/J9 -> 0.029905663 | K53: =K52/K9 -> 0.029752583 | L53: =L52/L9 -> 0.017100997 | M53: =M52/M9 -> 0.026391346 | N53: =N52/N9 -> 0.024035938 | ... S53: =S52/S9 -> -0.038784494
B56: 1. Hòa vốn (Bao gồm khấu hao) | D56: =D4 -> Thực tế năm 2023 | E56: =E4 -> Thực tế năm 2024 | F56: =F4 -> KQKD 2025 | G56: =G4 -> T1 | H56: =H4 -> T2 | I56: =I4 -> T3 | J56: =J4 -> T4 | K56: =K4 -> T5 | ... S56: =S4 -> KH 2026
B57: Sản lượng NVL hòa vốn (tấn) | D57: =IFERROR(D$58*(1+(D$17+D$18)/D$16),0) -> 0 | E57: =IFERROR(E$58*(1+(E$17+E$18)/E$16),0) -> 0 | F57: =IFERROR(F$58*(1+(F$17+F$18)/F$16),0) -> 10433624 | G57: =G$58*(1+(G$17+G$18)/G$16) -> 1122638.3 | H57: =H$58*(1+(H$17+H$18)/H$16) -> 1040068.8 | I57: =I$58*(1+(I$17+I$18)/I$16) -> 1070657.9 | J57: =J$58*(1+(J$17+J$18)/J$16) -> 986829.87 | K57: =K$58*(1+(K$17+K$18)/K$16) -> 987079.16 | L57: =L$58*(1+(L$17+L$18)/L$16) -> 1128647.8 | M57: =M$58*(1+(M$17+M$18)/M$16) -> 1021337.1 | N57: =N$58*(1+(N$17+N$18)/N$16) -> 1048195.8 | ... S57: =S$58*(1+(S$17+S$18)/S$16) -> 20470883
B58: Sản lượng thành phẩm hòa vốn (tấn) | D58: =IFERROR((D$27+D$31+D$34+D$38)/(D$25/D$5),0) -> 0 | E58: =IFERROR((E$27+E$31+E$34+E$38)/(E$25/E$5),0) -> 0 | F58: =IFERROR((F$27+F$31+F$34+F$38)/(F$25/F$5),0) -> 9402521.7 | G58: =(G$27+G$31+G$34+G$38)/(G$25/G$5) -> 972191.66 | H58: =(H$27+H$31+H$34+H$38)/(H$25/H$5) -> 900687.39 | I58: =(I$27+I$31+I$34+I$38)/(I$25/I$5) -> 927177.26 | J58: =(J$27+J$31+J$34+J$38)/(J$25/J$5) -> 853806.78 | K58: =(K$27+K$31+K$34+K$38)/(K$25/K$5) -> 854022.46 | L58: =(L$27+L$31+L$34+L$38)/(L$25/L$5) -> 976507.84 | M58: =(M$27+M$31+M$34+M$38)/(M$25/M$5) -> 883662.47 | N58: =(N$27+N$31+N$34+N$38)/(N$25/N$5) -> 906900.64 | ... S58: =(S$27+S$31+S$34+S$38)/(S$25/S$5) -> 17176450
B59: Doanh thu hòa vốn (triệu đồng) | D59: =IFERROR(D$58*(D$9/D$5),0) -> 0 | E59: =IFERROR(E$58*(E$9/E$5),0) -> 0 | F59: =IFERROR(F$58*(F$9/F$5),0) -> 1.6780159e+11 | G59: =G$58*(G$9/G$5) -> 1.4716224e+10 | H59: =H$58*(H$9/H$5) -> 1.3633852e+10 | I59: =I$58*(I$9/I$5) -> 1.4034834e+10 | J59: =J$58*(J$9/J$5) -> 1.2924877e+10 | K59: =K$58*(K$9/K$5) -> 1.2928142e+10 | L59: =L$58*(L$9/L$5) -> 1.4782318e+10 | M59: =M$58*(M$9/M$5) -> 1.3376831e+10 | N59: =N$58*(N$9/N$5) -> 1.3728609e+10 | ... S59: =S$58*(S$9/S$5) -> 2.6049919e+11
B60: 2. Hòa vốn (Không bao gồm khấu hao) | D60: =D56 -> Thực tế năm 2023 | E60: =E56 -> Thực tế năm 2024 | F60: =F56 -> KQKD 2025 | G60: =G56 -> T1 | H60: =H56 -> T2 | I60: =I56 -> T3 | J60: =J56 -> T4 | K60: =K56 -> T5 | ... S60: =S56 -> KH 2026
B61: Sản lượng NVL hòa vốn (tấn) | D61: =IFERROR(D$62*(1+(D$17+D$18)/D$16),0) -> 0 | E61: =IFERROR(E$62*(1+(E$17+E$18)/E$16),0) -> 0 | F61: =IFERROR(F$62*(1+(F$17+F$18)/F$16),0) -> 8007395.9 | G61: =G$62*(1+(G$17+G$18)/G$16) -> 1009079.9 | H61: =H$62*(1+(H$17+H$18)/H$16) -> 928764.03 | I61: =I$62*(1+(I$17+I$18)/I$16) -> 958303.94 | J61: =J$62*(1+(J$17+J$18)/J$16) -> 886487.68 | K61: =K$62*(1+(K$17+K$18)/K$16) -> 886104.78 | L61: =L$62*(1+(L$17+L$18)/L$16) -> 1027376.2 | M61: =M$62*(1+(M$17+M$18)/M$16) -> 918588.46 | N61: =N$62*(1+(N$17+N$18)/N$16) -> 945440.23 | ... S61: =S$62*(1+(S$17+S$18)/S$16) -> 18444001
B62: Sản lượng thành phẩm hòa vốn (tấn) | D62: =IFERROR((D$27+D$31+D$34+D$38-D51)/(D$25/D$5),0) -> 0 | E62: =IFERROR((E$27+E$31+E$34+E$38-E51)/(E$25/E$5),0) -> 0 | F62: =IFERROR((F$27+F$31+F$34+F$38-F51)/(F$25/F$5),0) -> 7216065.3 | G62: =(G$27+G$31+G$34+G$38-G51)/(G$25/G$5) -> 873851.43 | H62: =(H$27+H$31+H$34+H$38-H51)/(H$25/H$5) -> 804298.79 | I62: =(I$27+I$31+I$34+I$38-I51)/(I$25/I$5) -> 829880.01 | J62: =(J$27+J$31+J$34+J$38-J51)/(J$25/J$5) -> 766990.56 | K62: =(K$27+K$31+K$34+K$38-K51)/(K$25/K$5) -> 766659.27 | L62: =(L$27+L$31+L$34+L$38-L51)/(L$25/L$5) -> 888887.56 | M62: =(M$27+M$31+M$34+M$38-M51)/(M$25/M$5) -> 794764.2 | N62: =(N$27+N$31+N$34+N$38-N51)/(N$25/N$5) -> 817996.39 | ... S62: =(S$27+S$31+S$34+S$38-S51)/(S$25/S$5) -> 15475760
B63: Doanh thu hòa vốn (triệu đồng) | D63: =IFERROR(D$62*(D$9/D$5),0) -> 0 | E63: =IFERROR(E$62*(E$9/E$5),0) -> 0 | F63: =IFERROR(F$62*(F$9/F$5),0) -> 1.2878111e+11 | G63: =G$62*(G$9/G$5) -> 1.3227632e+10 | H63: =H$62*(H$9/H$5) -> 1.2174802e+10 | I63: =I$62*(I$9/I$5) -> 1.2562029e+10 | J63: =J$62*(J$9/J$5) -> 1.1610658e+10 | K63: =K$62*(K$9/K$5) -> 1.1605643e+10 | L63: =L$62*(L$9/L$5) -> 1.3455928e+10 | M63: =M$62*(M$9/M$5) -> 1.2031094e+10 | N63: =N$62*(N$9/N$5) -> 1.2382781e+10 | ... S63: =S$62*(S$9/S$5) -> 2.347064e+11

Sheet KDKD DAY DAI
B3: MỤC TIÊU KẾT QUẢ KINH DOANH NĂM 2026 | S3: ĐVT: Triệu đồng
B4: STT | C4: Mục phí | D4: Thực tế năm 2023 | E4: Thực tế năm 2024 | F4: KQKD 2025 | G4: T1 | H4: T2 | I4: T3 | J4: T4 | K4: T5 | L4: T6 | M4: T7 | N4: T8 | O4: T9 | P4: T10 | Q4: T11 | R4: T12 | S4: KH 2026 | U4: Kiểm tra lại các sheet chi phí
B5: 1 | C5: SẢN LƯỢNG BÁN (TẤN) | D5: =D6+D7+D8 -> 0 | E5: =E6+E7+E8 -> 0 | F5: =F6+F7+F8 -> 0 | G5: =G6+G7+G8 -> 0 | H5: =H6+H7+H8 -> 0 | I5: =I6+I7+I8 -> 0 | J5: =J6+J7+J8 -> 0 | K5: =K6+K7+K8 -> 0 | ... R5: =R6+R7+R8 -> 0 | S5: =SUM(G5:R5) -> 0
B6: 1.1 | C6: Dây Đai PET | G6: ='KH DAY DAI'!E23 -> 0 | H6: ='KH DAY DAI'!F23 -> 0 | I6: ='KH DAY DAI'!G23 -> 0 | J6: ='KH DAY DAI'!H23 -> 0 | K6: ='KH DAY DAI'!I23 -> 0 | L6: ='KH DAY DAI'!J23 -> 0 | M6: ='KH DAY DAI'!K23 -> 0 | N6: ='KH DAY DAI'!L23 -> 0 | ... R6: ='KH DAY DAI'!P23 -> 0 | S6: =SUM(G6:R6) -> 0
B7: 1.2 | S7: =SUM(G7:R7) -> 0
B8: 1.3 | S8: =SUM(G8:R8) -> 0
B9: 2 | C9: DOANH THU | D9: =D10+D11+D12+D13 -> 0 | E9: =E10+E11+E12+E13 -> 0 | F9: =F10+F11+F12+F13 -> 0 | G9: =G10+G11+G12+G13 -> 0 | H9: =H10+H11+H12+H13 -> 0 | I9: =I10+I11+I12+I13 -> 0 | J9: =J10+J11+J12+J13 -> 0 | K9: =K10+K11+K12+K13 -> 0 | ... R9: =R10+R11+R12+R13 -> 0 | S9: =SUM(G9:R9) -> 0
B10: 2.1 | C10: Dây Đai PET | G10: ='KH DAY DAI'!E24 -> 0 | H10: ='KH DAY DAI'!F24 -> 0 | I10: ='KH DAY DAI'!G24 -> 0 | J10: ='KH DAY DAI'!H24 -> 0 | K10: ='KH DAY DAI'!I24 -> 0 | L10: ='KH DAY DAI'!J24 -> 0 | M10: ='KH DAY DAI'!K24 -> 0 | N10: ='KH DAY DAI'!L24 -> 0 | ... R10: ='KH DAY DAI'!P24 -> 0 | S10: =SUM(G10:R10) -> 0
B11: 2.2
B12: 2.3
B13: 2.4 | C13: Khác | S13: =SUM(G13:R13) -> 0
B14: 3 | C14: BIẾN PHÍ | D14: =D15+D23 -> 0 | E14: =E15+E23 -> 0 | G14: =G15+G23 -> 0 | H14: =H15+H23 -> 0 | I14: =I15+I23 -> 0 | J14: =J15+J23 -> 0 | K14: =K15+K23 -> 0 | L14: =L15+L23 -> 0 | M14: =M15+M23 -> 0 | N14: =N15+N23 -> 0 | ... R14: =R15+R23 -> 0 | S14: =SUM(G14:R14) -> 0
B15: 3.1 | C15: BIẾN PHÍ SẢN XUẤT | D15: =D16+D20+D21+D22 -> 0 | E15: =E16+E20+E21+E22 -> 0 | G15: =G16+G20+G21+G22 -> 0 | H15: =H16+H20+H21+H22 -> 0 | I15: =I16+I20+I21+I22 -> 0 | J15: =J16+J20+J21+J22 -> 0 | K15: =K16+K20+K21+K22 -> 0 | L15: =L16+L20+L21+L22 -> 0 | M15: =M16+M20+M21+M22 -> 0 | N15: =N16+N20+N21+N22 -> 0 | ... R15: =R16+R20+R21+R22 -> 0 | S15: =SUM(G15:R15) -> 0
B16: 3.1.1 | C16: Nguyên vật liệu chính (nhựa, gồm hao hụt) | G16: =SUM('KH DAY DAI'!E25:E26,'KH DAY DAI'!E33) -> 0 | H16: =SUM('KH DAY DAI'!F25:F26,'KH DAY DAI'!F33) -> 0 | I16: =SUM('KH DAY DAI'!G25:G26,'KH DAY DAI'!G33) -> 0 | J16: =SUM('KH DAY DAI'!H25:H26,'KH DAY DAI'!H33) -> 0 | K16: =SUM('KH DAY DAI'!I25:I26,'KH DAY DAI'!I33) -> 0 | L16: =SUM('KH DAY DAI'!J25:J26,'KH DAY DAI'!J33) -> 0 | M16: =SUM('KH DAY DAI'!K25:K26,'KH DAY DAI'!K33) -> 0 | N16: =SUM('KH DAY DAI'!L25:L26,'KH DAY DAI'!L33) -> 0 | ... R16: =SUM('KH DAY DAI'!P25:P26,'KH DAY DAI'!P33) -> 0 | S16: =SUM(G16:R16) -> 0
B17: 3.1.2 | C17: Trong đó: i/ Hao hụt CĐ phân loại chai | G17: =SUM('KH DAY DAI'!E26,'KH DAY DAI'!E33) -> 0 | H17: =SUM('KH DAY DAI'!F26,'KH DAY DAI'!F33) -> 0 | I17: =SUM('KH DAY DAI'!G26,'KH DAY DAI'!G33) -> 0 | J17: =SUM('KH DAY DAI'!H26,'KH DAY DAI'!H33) -> 0 | K17: =SUM('KH DAY DAI'!I26,'KH DAY DAI'!I33) -> 0 | L17: =SUM('KH DAY DAI'!J26,'KH DAY DAI'!J33) -> 0 | M17: =SUM('KH DAY DAI'!K26,'KH DAY DAI'!K33) -> 0 | N17: =SUM('KH DAY DAI'!L26,'KH DAY DAI'!L33) -> 0 | ... R17: =SUM('KH DAY DAI'!P26,'KH DAY DAI'!P33) -> 0 | S17: =SUM(G17:R17) -> 0
C18: ii/ Hao hụt CĐ băm vảy | S18: =SUM(G18:R18) -> 0
B19: 3.1.3 | C19: % chi phí nguyên liệu/doanh thu | D19: =IFERROR(D16/$F$9,0) -> 0 | E19: =IFERROR(E16/$F$9,0) -> 0 | F19: =IFERROR(F16/$F$9,0) -> 0 | G19: =G16/G9 -> #DIV/0! | H19: =H16/H9 -> #DIV/0! | I19: =I16/I9 -> #DIV/0! | J19: =J16/J9 -> #DIV/0! | K19: =K16/K9 -> #DIV/0! | L19: =L16/L9 -> #DIV/0! | M19: =M16/M9 -> #DIV/0! | N19: =N16/N9 -> #DIV/0! | ... S19: =S16/S9 -> #DIV/0!
B20: 3.1.4 | C20: Nguyên vật liệu phụ | G20: ='KH DAY DAI'!E27 -> 0 | H20: ='KH DAY DAI'!F27 -> 0 | I20: ='KH DAY DAI'!G27 -> 0 | J20: ='KH DAY DAI'!H27 -> 0 | K20: ='KH DAY DAI'!I27 -> 0 | L20: ='KH DAY DAI'!J27 -> 0 | M20: ='KH DAY DAI'!K27 -> 0 | N20: ='KH DAY DAI'!L27 -> 0 | ... R20: ='KH DAY DAI'!P27 -> 0 | S20: =SUM(G20:R20) -> 0
B21: 3.1.5 | C21: Điện sản xuất | G21: ='KH DAY DAI'!E28 -> 0 | H21: ='KH DAY DAI'!F28 -> 0 | I21: ='KH DAY DAI'!G28 -> 0 | J21: ='KH DAY DAI'!H28 -> 0 | K21: ='KH DAY DAI'!I28 -> 0 | L21: ='KH DAY DAI'!J28 -> 0 | M21: ='KH DAY DAI'!K28 -> 0 | N21: ='KH DAY DAI'!L28 -> 0 | ... R21: ='KH DAY DAI'!P28 -> 0 | S21: =SUM(G21:R21) -> 0
B22: 3.1.6 | C22: Nhân công trực tiếp | G22: ='KH DAY DAI'!E29 -> 0 | H22: ='KH DAY DAI'!F29 -> 0 | I22: ='KH DAY DAI'!G29 -> 0 | J22: ='KH DAY DAI'!H29 -> 0 | K22: ='KH DAY DAI'!I29 -> 0 | L22: ='KH DAY DAI'!J29 -> 0 | M22: ='KH DAY DAI'!K29 -> 0 | N22: ='KH DAY DAI'!L29 -> 0 | ... R22: ='KH DAY DAI'!P29 -> 0 | S22: =SUM(G22:R22) -> 0
B23: 3.2 | C23: BIẾN PHÍ BÁN HÀNG | D23: =D24 -> 0 | E23: =E24 -> 0 | F23: =F24 -> 0 | G23: =G24 -> 0 | H23: =H24 -> 0 | I23: =I24 -> 0 | J23: =J24 -> 0 | K23: =K24 -> 0 | ... R23: =R24 -> 0 | S23: =SUM(G23:R23) -> 0
C24: Chi phí vận chuyển | G24: ='KH DAY DAI'!E36 -> 0 | H24: ='KH DAY DAI'!F36 -> 0 | I24: ='KH DAY DAI'!G36 -> 0 | J24: ='KH DAY DAI'!H36 -> 0 | K24: ='KH DAY DAI'!I36 -> 0 | L24: ='KH DAY DAI'!J36 -> 0 | M24: ='KH DAY DAI'!K36 -> 0 | N24: ='KH DAY DAI'!L36 -> 0 | ... R24: ='KH DAY DAI'!P36 -> 0 | S24: =SUM(G24:R24) -> 0
B25: 4 | C25: LÃI SAU BIẾN PHÍ | D25: =D9-D14 -> 0 | E25: =E9-E14 -> 0 | F25: =F9-F14 -> 0 | G25: =G9-G14 -> 0 | H25: =H9-H14 -> 0 | I25: =I9-I14 -> 0 | J25: =J9-J14 -> 0 | K25: =K9-K14 -> 0 | ... R25: =R9-R14 -> 0 | S25: =SUM(G25:R25) -> 0
B26: 4.1 | C26: % lãi biến phí/doanh thu | D26: =IFERROR(D23/$F$9,0) -> 0 | E26: =IFERROR(E23/$F$9,0) -> 0 | F26: =IFERROR(F23/$F$9,0) -> 0 | G26: =G25/G9 -> #DIV/0! | H26: =H25/H9 -> #DIV/0! | I26: =I25/I9 -> #DIV/0! | J26: =J25/J9 -> #DIV/0! | K26: =K25/K9 -> #DIV/0! | L26: =L25/L9 -> #DIV/0! | M26: =M25/M9 -> #DIV/0! | N26: =N25/N9 -> #DIV/0! | ... S26: =S25/S9 -> #DIV/0!
B27: 5 | C27: CHI PHÍ SẢN XUẤT CHUNG | D27: =D28+D29+D30 -> 0 | E27: =E28+E29+E30 -> 0 | F27: =F28+F29+F30 -> 0 | G27: =G28+G29+G30 -> 0 | H27: =H28+H29+H30 -> 0 | I27: =I28+I29+I30 -> 0 | J27: =J28+J29+J30 -> 0 | K27: =K28+K29+K30 -> 0 | ... R27: =R28+R29+R30 -> 0 | S27: =SUM(G27:R27) -> 0
B28: 5.1 | C28: Lương gián tiếp Sản xuất | G28: ='KH DAY DAI'!E31 -> 0 | H28: ='KH DAY DAI'!F31 -> 0 | I28: ='KH DAY DAI'!G31 -> 0 | J28: ='KH DAY DAI'!H31 -> 0 | K28: ='KH DAY DAI'!I31 -> 0 | L28: ='KH DAY DAI'!J31 -> 0 | M28: ='KH DAY DAI'!K31 -> 0 | N28: ='KH DAY DAI'!L31 -> 0 | ... R28: ='KH DAY DAI'!P31 -> 0 | S28: =SUM(G28:R28) -> 0
B29: 5.2 | C29: Chi phí thuê xưởng | S29: =SUM(G29:R29) -> 0
B30: 5.3 | C30: Chi phí sản xuất (Ngoài lương, BOM, thuê xưởng, khấu hao) | G30: =SUM('KH DAY DAI'!E30) -> 0 | H30: =SUM('KH DAY DAI'!F30) -> 0 | I30: =SUM('KH DAY DAI'!G30) -> 0 | J30: =SUM('KH DAY DAI'!H30) -> 0 | K30: =SUM('KH DAY DAI'!I30) -> 0 | L30: =SUM('KH DAY DAI'!J30) -> 0 | M30: =SUM('KH DAY DAI'!K30) -> 0 | N30: =SUM('KH DAY DAI'!L30) -> 0 | ... R30: =SUM('KH DAY DAI'!P30) -> 0 | S30: =SUM(G30:R30) -> 0
B31: 6 | C31: CHI PHÍ KHẤU HAO, CCDC | G31: ='KH DAY DAI'!E32 -> 0 | H31: ='KH DAY DAI'!F32 -> 0 | I31: ='KH DAY DAI'!G32 -> 0 | J31: ='KH DAY DAI'!H32 -> 0 | K31: ='KH DAY DAI'!I32 -> 0 | L31: ='KH DAY DAI'!J32 -> 0 | M31: ='KH DAY DAI'!K32 -> 0 | N31: ='KH DAY DAI'!L32 -> 0 | ... R31: ='KH DAY DAI'!P32 -> 0 | S31: =SUM(G31:R31) -> 0
B32: 7 | C32: LỢI NHUẬN GỘP | D32: =D25-D27-D31 -> 0 | E32: =E25-E27-E31 -> 0 | F32: =F25-F27-F31 -> 0 | G32: =G25-G27-G31 -> 0 | H32: =H25-H27-H31 -> 0 | I32: =I25-I27-I31 -> 0 | J32: =J25-J27-J31 -> 0 | K32: =K25-K27-K31 -> 0 | ... R32: =R25-R27-R31 -> 0 | S32: =SUM(G32:R32) -> 0
B33: 7.1 | C33: % lãi gộp/doanh thu | D33: =IFERROR(D30/$F$9,0) -> 0 | E33: =IFERROR(E30/$F$9,0) -> 0 | F33: =IFERROR(F30/$F$9,0) -> 0 | G33: =G32/G9 -> #DIV/0! | H33: =H32/H9 -> #DIV/0! | I33: =I32/I9 -> #DIV/0! | J33: =J32/J9 -> #DIV/0! | K33: =K32/K9 -> #DIV/0! | L33: =L32/L9 -> #DIV/0! | M33: =M32/M9 -> #DIV/0! | N33: =N32/N9 -> #DIV/0! | ... S33: =S32/S9 -> #DIV/0!
B34: 8 | C34: CHI PHÍ BÁN HÀNG & MKT & R&D | D34: =D35+D36+D37 -> 0 | E34: =E35+E36+E37 -> 0 | F34: =F35+F36+F37 -> 0 | G34: =G35+G36+G37 -> 0 | H34: =H35+H36+H37 -> 0 | I34: =I35+I36+I37 -> 0 | J34: =J35+J36+J37 -> 0 | K34: =K35+K36+K37 -> 0 | ... R34: =R35+R36+R37 -> 0 | S34: =SUM(G34:R34) -> 0
B35: 8.1 | C35: Lương | S35: =SUM(G35:R35) -> 0
B36: 8.2 | C36: Chi phí bán hàng (ngoài lương, khấu hao) | G36: =SUM('KH DAY DAI'!E34:E35) -> 0 | H36: =SUM('KH DAY DAI'!F34:F35) -> 0 | I36: =SUM('KH DAY DAI'!G34:G35) -> 0 | J36: =SUM('KH DAY DAI'!H34:H35) -> 0 | K36: =SUM('KH DAY DAI'!I34:I35) -> 0 | L36: =SUM('KH DAY DAI'!J34:J35) -> 0 | M36: =SUM('KH DAY DAI'!K34:K35) -> 0 | N36: =SUM('KH DAY DAI'!L34:L35) -> 0 | ... R36: =SUM('KH DAY DAI'!P34:P35) -> 0 | S36: =SUM(G36:R36) -> 0
B37: 8.3 | C37: Khấu hao tài sản | S37: =SUM(G37:R37) -> 0
B38: 9 | C38: CHI PHÍ QUẢN LÝ | D38: =D39+D40+D41 -> 0 | E38: =E39+E40+E41 -> 0 | F38: =F39+F40+F41 -> 0 | G38: =G39+G40+G41 -> 0 | H38: =H39+H40+H41 -> 0 | I38: =I39+I40+I41 -> 0 | J38: =J39+J40+J41 -> 0 | K38: =K39+K40+K41 -> 0 | ... R38: =R39+R40+R41 -> 0 | S38: =SUM(G38:R38) -> 0
B39: 9.1 | C39: Lương | S39: =SUM(G39:R39) -> 0
B40: 9.2 | C40: Chi phí quản lý (ngoài lương, khấu hao) | S40: =SUM(G40:R40) -> 0
B41: 9.3 | C41: Khấu hao tài sản | S41: =SUM(G41:R41) -> 0
B42: 10 | C42: DOANH THU/CHI PHÍ KHÁC | S42: =SUM(G42:R42) -> 0 | U42: <= Nhập số liệu
B43: 11 | C43: LỢI NHUẬN THUẦN TỪ HOẠT ĐỘNG KINH DOANH | D43: =D32-D34-D38+D42 -> 0 | E43: =E32-E34-E38+E42 -> 0 | F43: =F32-F34-F38+F42 -> 0 | G43: =G32-G34-G38+G42 -> 0 | H43: =H32-H34-H38+H42 -> 0 | I43: =I32-I34-I38+I42 -> 0 | J43: =J32-J34-J38+J42 -> 0 | K43: =K32-K34-K38+K42 -> 0 | ... R43: =R32-R34-R38+R42 -> 0 | S43: =SUM(G43:R43) -> 0 | T43: =S9-S14-S27-S34-S31 -> 0
B44: 12 | C44: DOANH THU TÀI CHÍNH | S44: =SUM(G44:R44) -> 0 | U44: <= Nhập số liệu
B45: 13 | C45: CHI PHÍ TÀI CHÍNH | S45: =SUM(G45:R45) -> 0 | U45: <= Nhập số liệu
B46: 13.1 | C46: Trong đó: chi phí lãi vay | S46: =SUM(G46:R46) -> 0
B47: 14 | C47: LỢI NHUẬN TRƯỚC THUẾ | D47: =D43+D44-D45 -> 0 | E47: =E43+E44-E45 -> 0 | F47: =F43+F44-F45 -> 0 | G47: =G43+G44-G45 -> 0 | H47: =H43+H44-H45 -> 0 | I47: =I43+I44-I45 -> 0 | J47: =J43+J44-J45 -> 0 | K47: =K43+K44-K45 -> 0 | ... R47: =R43+R44-R45 -> 0 | S47: =SUM(G47:R47) -> 0
B48: 15 | C48: THUẾ TNDN | S48: =SUM(G48:R48) -> 0 | U48: <= Nhập số liệu
B49: 16 | C49: LỢI NHUẬN SAU THUẾ | D49: =D47-D48 -> 0 | E49: =E47-E48 -> 0 | F49: =F47-F48 -> 0 | G49: =G47-G48 -> 0 | H49: =H47-H48 -> 0 | I49: =I47-I48 -> 0 | J49: =J47-J48 -> 0 | K49: =K47-K48 -> 0 | ... R49: =R47-R48 -> 0 | S49: =SUM(G49:R49) -> 0
B50: 16.1 | C50: % LNST/doanh thu | D50: =IFERROR(D47/$F$9,0) -> 0 | E50: =IFERROR(E47/$F$9,0) -> 0 | F50: =IFERROR(F47/$F$9,0) -> 0 | G50: =G49/G9 -> #DIV/0! | H50: =H49/H9 -> #DIV/0! | I50: =I49/I9 -> #DIV/0! | J50: =J49/J9 -> #DIV/0! | K50: =K49/K9 -> #DIV/0! | L50: =L49/L9 -> #DIV/0! | M50: =M49/M9 -> #DIV/0! | N50: =N49/N9 -> #DIV/0! | ... S50: =S49/S9 -> #DIV/0!
B51: 17 | C51: Khấu hao tài sản | G51: =G31 -> 0 | H51: =H31 -> 0 | I51: =I31 -> 0 | J51: =J31 -> 0 | K51: =K31 -> 0 | L51: =L31 -> 0 | M51: =M31 -> 0 | N51: =N31 -> 0 | ... R51: =R31 -> 0 | S51: =SUM(G51:R51) -> 0
B52: 18 | C52: LỢI NHUẬN KHÔNG BAO GỒM KHẤU HAO, LÃI VAY | D52: =D49+D51 -> 0 | E52: =E49+E51 -> 0 | F52: =F49+F51 -> 0 | G52: =G49+G51 -> 0 | H52: =H49+H51 -> 0 | I52: =I49+I51 -> 0 | J52: =J49+J51 -> 0 | K52: =K49+K51 -> 0 | ... R52: =R49+R51 -> 0 | S52: =SUM(G52:R52) -> 0
B53: 18.1 | C53: % LN không gồm khấu hao/doanh thu | D53: =IFERROR(D50/$F$9,0) -> 0 | E53: =IFERROR(E50/$F$9,0) -> 0 | F53: =IFERROR(F50/$F$9,0) -> 0 | G53: =G52/G9 -> #DIV/0! | H53: =H52/H9 -> #DIV/0! | I53: =I52/I9 -> #DIV/0! | J53: =J52/J9 -> #DIV/0! | K53: =K52/K9 -> #DIV/0! | L53: =L52/L9 -> #DIV/0! | M53: =M52/M9 -> #DIV/0! | N53: =N52/N9 -> #DIV/0! | ... S53: =S52/S9 -> #DIV/0!
B56: 1. Hòa vốn (Bao gồm khấu hao) | D56: =D4 -> Thực tế năm 2023 | E56: =E4 -> Thực tế năm 2024 | F56: =F4 -> KQKD 2025 | G56: =G4 -> T1 | H56: =H4 -> T2 | I56: =I4 -> T3 | J56: =J4 -> T4 | K56: =K4 -> T5 | ... S56: =S4 -> KH 2026
B57: Sản lượng NVL hòa vốn (tấn) | D57: =IFERROR(D$58*(1+(D$17+D$18)/D$16),0) -> 0 | E57: =IFERROR(E$58*(1+(E$17+E$18)/E$16),0) -> 0 | F57: =IFERROR(F$58*(1+(F$17+F$18)/F$16),0) -> 0 | G57: =G$58*(1+(G$17+G$18)/G$16) -> #DIV/0! | H57: =H$58*(1+(H$17+H$18)/H$16) -> #DIV/0! | I57: =I$58*(1+(I$17+I$18)/I$16) -> #DIV/0! | J57: =J$58*(1+(J$17+J$18)/J$16) -> #DIV/0! | K57: =K$58*(1+(K$17+K$18)/K$16) -> #DIV/0! | L57: =L$58*(1+(L$17+L$18)/L$16) -> #DIV/0! | M57: =M$58*(1+(M$17+M$18)/M$16) -> #DIV/0! | N57: =N$58*(1+(N$17+N$18)/N$16) -> #DIV/0! | ... S57: =S$58*(1+(S$17+S$18)/S$16) -> #DIV/0!
B58: Sản lượng thành phẩm hòa vốn (tấn) | D58: =IFERROR((D$27+D$31+D$34+D$38)/(D$25/D$5),0) -> 0 | E58: =IFERROR((E$27+E$31+E$34+E$38)/(E$25/E$5),0) -> 0 | F58: =IFERROR((F$27+F$31+F$34+F$38)/(F$25/F$5),0) -> 0 | G58: =(G$27+G$31+G$34+G$38)/(G$25/G$5) -> #DIV/0! | H58: =(H$27+H$31+H$34+H$38)/(H$25/H$5) -> #DIV/0! | I58: =(I$27+I$31+I$34+I$38)/(I$25/I$5) -> #DIV/0! | J58: =(J$27+J$31+J$34+J$38)/(J$25/J$5) -> #DIV/0! | K58: =(K$27+K$31+K$34+K$38)/(K$25/K$5) -> #DIV/0! | L58: =(L$27+L$31+L$34+L$38)/(L$25/L$5) -> #DIV/0! | M58: =(M$27+M$31+M$34+M$38)/(M$25/M$5) -> #DIV/0! | N58: =(N$27+N$31+N$34+N$38)/(N$25/N$5) -> #DIV/0! | ... S58: =(S$27+S$31+S$34+S$38)/(S$25/S$5) -> #DIV/0!
B59: Doanh thu hòa vốn (triệu đồng) | D59: =IFERROR(D$58*(D$9/D$5),0) -> 0 | E59: =IFERROR(E$58*(E$9/E$5),0) -> 0 | F59: =IFERROR(F$58*(F$9/F$5),0) -> 0 | G59: =G$58*(G$9/G$5) -> #DIV/0! | H59: =H$58*(H$9/H$5) -> #DIV/0! | I59: =I$58*(I$9/I$5) -> #DIV/0! | J59: =J$58*(J$9/J$5) -> #DIV/0! | K59: =K$58*(K$9/K$5) -> #DIV/0! | L59: =L$58*(L$9/L$5) -> #DIV/0! | M59: =M$58*(M$9/M$5) -> #DIV/0! | N59: =N$58*(N$9/N$5) -> #DIV/0! | ... S59: =S$58*(S$9/S$5) -> #DIV/0!
B60: 2. Hòa vốn (Không bao gồm khấu hao) | D60: =D56 -> Thực tế năm 2023 | E60: =E56 -> Thực tế năm 2024 | F60: =F56 -> KQKD 2025 | G60: =G56 -> T1 | H60: =H56 -> T2 | I60: =I56 -> T3 | J60: =J56 -> T4 | K60: =K56 -> T5 | ... S60: =S56 -> KH 2026
B61: Sản lượng NVL hòa vốn (tấn) | D61: =IFERROR(D$62*(1+(D$17+D$18)/D$16),0) -> 0 | E61: =IFERROR(E$62*(1+(E$17+E$18)/E$16),0) -> 0 | F61: =IFERROR(F$62*(1+(F$17+F$18)/F$16),0) -> 0 | G61: =G$62*(1+(G$17+G$18)/G$16) -> #DIV/0! | H61: =H$62*(1+(H$17+H$18)/H$16) -> #DIV/0! | I61: =I$62*(1+(I$17+I$18)/I$16) -> #DIV/0! | J61: =J$62*(1+(J$17+J$18)/J$16) -> #DIV/0! | K61: =K$62*(1+(K$17+K$18)/K$16) -> #DIV/0! | L61: =L$62*(1+(L$17+L$18)/L$16) -> #DIV/0! | M61: =M$62*(1+(M$17+M$18)/M$16) -> #DIV/0! | N61: =N$62*(1+(N$17+N$18)/N$16) -> #DIV/0! | ... S61: =S$62*(1+(S$17+S$18)/S$16) -> #DIV/0!
B62: Sản lượng thành phẩm hòa vốn (tấn) | D62: =IFERROR((D$27+D$31+D$34+D$38-D51)/(D$25/D$5),0) -> 0 | E62: =IFERROR((E$27+E$31+E$34+E$38-E51)/(E$25/E$5),0) -> 0 | F62: =IFERROR((F$27+F$31+F$34+F$38-F51)/(F$25/F$5),0) -> 0 | G62: =(G$27+G$31+G$34+G$38-G51)/(G$25/G$5) -> #DIV/0! | H62: =(H$27+H$31+H$34+H$38-H51)/(H$25/H$5) -> #DIV/0! | I62: =(I$27+I$31+I$34+I$38-I51)/(I$25/I$5) -> #DIV/0! | J62: =(J$27+J$31+J$34+J$38-J51)/(J$25/J$5) -> #DIV/0! | K62: =(K$27+K$31+K$34+K$38-K51)/(K$25/K$5) -> #DIV/0! | L62: =(L$27+L$31+L$34+L$38-L51)/(L$25/L$5) -> #DIV/0! | M62: =(M$27+M$31+M$34+M$38-M51)/(M$25/M$5) -> #DIV/0! | N62: =(N$27+N$31+N$34+N$38-N51)/(N$25/N$5) -> #DIV/0! | ... S62: =(S$27+S$31+S$34+S$38-S51)/(S$25/S$5) -> #DIV/0!
B63: Doanh thu hòa vốn (triệu đồng) | D63: =IFERROR(D$62*(D$9/D$5),0) -> 0 | E63: =IFERROR(E$62*(E$9/E$5),0) -> 0 | F63: =IFERROR(F$62*(F$9/F$5),0) -> 0 | G63: =G$62*(G$9/G$5) -> #DIV/0! | H63: =H$62*(H$9/H$5) -> #DIV/0! | I63: =I$62*(I$9/I$5) -> #DIV/0! | J63: =J$62*(J$9/J$5) -> #DIV/0! | K63: =K$62*(K$9/K$5) -> #DIV/0! | L63: =L$62*(L$9/L$5) -> #DIV/0! | M63: =M$62*(M$9/M$5) -> #DIV/0! | N63: =N$62*(N$9/N$5) -> #DIV/0! | ... S63: =S$62*(S$9/S$5) -> #DIV/0!

Sheet KH DAY DAI
B2: 1. Dây đai
B4: STT | C4: Nội dung | D4: Tỷ lệ | E4: 1 | F4: =+E4+1 -> 2 | G4: =+F4+1 -> 3 | H4: =+G4+1 -> 4 | I4: =+H4+1 -> 5 | J4: =+I4+1 -> 6 | K4: =+J4+1 -> 7 | L4: =+K4+1 -> 8 | M4: =+L4+1 -> 9 | ... P4: =+O4+1 -> 12
B5: 1 | C5: Sản lượng sản xuất (tấn) | E5: =300*16*30/10^3 -> 144 | F5: =300*16*30/10^3 -> 144 | G5: =300*16*30/10^3 -> 144 | H5: =300*16*30/10^3 -> 144 | I5: =300*16*30/10^3 -> 144 | J5: =300*16*30/10^3 -> 144 | K5: =300*16*30/10^3 -> 144 | L5: =300*16*30/10^3 -> 144 | ... P5: =300*16*30/10^3 -> 144 | Q5: =400 -> 400
B6: 2 | C6: Giá bán | E6: 19000 | F6: 19000 | G6: 19000 | H6: 19000 | I6: 19000 | J6: 19000 | K6: 19000 | L6: 19000 | M6: 19000 | N6: 19000 | O6: 19000 | P6: 19000
B7: 3 | C7: Giá vốn (bao gồm CP hoa hồng) | E7: =SUM(E8,E12:E21) -> 17207.846 | F7: =SUM(F8,F12:F21) -> 17207.846 | G7: =SUM(G8,G12:G21) -> 17207.846 | H7: =SUM(H8,H12:H21) -> 17207.846 | I7: =SUM(I8,I12:I21) -> 17207.846 | J7: =SUM(J8,J12:J21) -> 17207.846 | K7: =SUM(K8,K12:K21) -> 17207.846 | L7: =SUM(L8,L12:L21) -> 17207.846 | ... P7: =SUM(P8,P12:P21) -> 17207.846
B8: 3.1 | C8: Chi phí nguyên vật liệu | E8: =+SUM(E9:E11) -> 8840 | F8: =+SUM(F9:F11) -> 8840 | G8: =+SUM(G9:G11) -> 8840 | H8: =+SUM(H9:H11) -> 8840 | I8: =+SUM(I9:I11) -> 8840 | J8: =+SUM(J9:J11) -> 8840 | K8: =+SUM(K9:K11) -> 8840 | L8: =+SUM(L9:L11) -> 8840 | ... P8: =+SUM(P9:P11) -> 8840
C9: Phó Sản PET GC Dây Đai | D9: 0.5 | E9: =8000*$D9 -> 4000 | F9: =8000*$D9 -> 4000 | G9: =8000*$D9 -> 4000 | H9: =8000*$D9 -> 4000 | I9: =8000*$D9 -> 4000 | J9: =8000*$D9 -> 4000 | K9: =8000*$D9 -> 4000 | L9: =8000*$D9 -> 4000 | ... P9: =8000*$D9 -> 4000
C10: Phó Sản PET Đầu Keo | D10: 0.35 | E10: 2800 | F10: 2800 | G10: 2800 | H10: 2800 | I10: 2800 | J10: 2800 | K10: 2800 | L10: 2800 | M10: 2800 | N10: 2800 | O10: 2800 | P10: 2800
C11: Vảy PET B4_A3 | D11: 0.15 | E11: 2040 | F11: 2040 | G11: 2040 | H11: 2040 | I11: 2040 | J11: 2040 | K11: 2040 | L11: 2040 | M11: 2040 | N11: 2040 | O11: 2040 | P11: 2040
B12: 3.2 | C12: Phó sản, hao hụt | E12: 365.39084 | F12: 365.39084 | G12: 365.39084 | H12: 365.39084 | I12: 365.39084 | J12: 365.39084 | K12: 365.39084 | L12: 365.39084 | M12: 365.39084 | N12: 365.39084 | O12: 365.39084 | P12: 365.39084
B13: 3.3 | C13: Hóa chất rửa vảy | E13: 36.24378 | F13: 36.24378 | G13: 36.24378 | H13: 36.24378 | I13: 36.24378 | J13: 36.24378 | K13: 36.24378 | L13: 36.24378 | M13: 36.24378 | N13: 36.24378 | O13: 36.24378 | P13: 36.24378
B14: 3.4 | C14: Điện, nước | E14: 212.12234 | F14: 212.12234 | G14: 212.12234 | H14: 212.12234 | I14: 212.12234 | J14: 212.12234 | K14: 212.12234 | L14: 212.12234 | M14: 212.12234 | N14: 212.12234 | O14: 212.12234 | P14: 212.12234
B15: 3.5 | C15: Nhân công trực tiếp | E15: 240.68287 | F15: 240.68287 | G15: 240.68287 | H15: 240.68287 | I15: 240.68287 | J15: 240.68287 | K15: 240.68287 | L15: 240.68287 | M15: 240.68287 | N15: 240.68287 | O15: 240.68287 | P15: 240.68287 | Q15: =48000*2 -> 96000 | R15: =Q15/Q5 -> 240
B16: 3.6 | C16: Vật tư phân xưởng | E16: 58.638979 | F16: 58.638979 | G16: 58.638979 | H16: 58.638979 | I16: 58.638979 | J16: 58.638979 | K16: 58.638979 | L16: 58.638979 | M16: 58.638979 | N16: 58.638979 | O16: 58.638979 | P16: 58.638979
B17: 3.7 | C17: Lương gián tiếp sx | E17: 217.51578 | F17: 217.51578 | G17: 217.51578 | H17: 217.51578 | I17: 217.51578 | J17: 217.51578 | K17: 217.51578 | L17: 217.51578 | M17: 217.51578 | N17: 217.51578 | O17: 217.51578 | P17: 217.51578
B18: 3.8 | C18: Khấu hao | E18: 421.56543 | F18: 421.56543 | G18: 421.56543 | H18: 421.56543 | I18: 421.56543 | J18: 421.56543 | K18: 421.56543 | L18: 421.56543 | M18: 421.56543 | N18: 421.56543 | O18: 421.56543 | P18: 421.56543 | Q18: =6200000000/12/12 -> 43055556 | R18: =Q18/E5 -> 298996.91
C19: Tỷ lệ hao hụt nguyên liệu gia công | D19: 0.04 | E19: =+SUM(E9:E18)*$D19 -> 415.6864 | F19: =+SUM(F9:F18)*$D19 -> 415.6864 | G19: =+SUM(G9:G18)*$D19 -> 415.6864 | H19: =+SUM(H9:H18)*$D19 -> 415.6864 | I19: =+SUM(I9:I18)*$D19 -> 415.6864 | J19: =+SUM(J9:J18)*$D19 -> 415.6864 | K19: =+SUM(K9:K18)*$D19 -> 415.6864 | L19: =+SUM(L9:L18)*$D19 -> 415.6864 | ... P19: =+SUM(P9:P18)*$D19 -> 415.6864
C20: Chi phí gia công | E20: 5000 | F20: 5000 | G20: 5000 | H20: 5000 | I20: 5000 | J20: 5000 | K20: 5000 | L20: 5000 | M20: 5000 | N20: 5000 | O20: 5000 | P20: 5000
C21: Chi phí hoa hồng | D21: =E21/E$6 -> 0.073684211 | E21: =(E6-5000)*10% -> 1400 | F21: =(F6-5000)*10% -> 1400 | G21: =(G6-5000)*10% -> 1400 | H21: =(H6-5000)*10% -> 1400 | I21: =(I6-5000)*10% -> 1400 | J21: =(J6-5000)*10% -> 1400 | K21: =(K6-5000)*10% -> 1400 | L21: =(L6-5000)*10% -> 1400 | ... P21: =(P6-5000)*10% -> 1400
C23: Thành Phẩm Bán
C24: Doanh thu
C25: CP NVL
C26: Hao hụt
C27: Hóa chất
C28: Điện, nước
C29: Nhân công trực tiếp
C30: Vật tư phân xưởng
C31: Lương gián tiếp sx
C32: Khấu hao
C33: Tỷ lệ hao hụt nguyên liệu gia công
C34: Chi phí gia công
... C42: Vảy B4_A3
C43: Phó Sản PET Đầu Keo | D43: 0.15
C44: HH 4%

Sheet KQKD HD
L1: 62610818
B3: MỤC TIÊU KẾT QUẢ KINH DOANH NĂM 2026 | F3: 215.282 | S3: ĐVT: Triệu đồng
B4: STT | C4: Mục phí | D4: Thực tế năm 2023 | E4: Thực tế năm 2024 | F4: KQKD 2025 | G4: T1 | H4: T2 | I4: T3 | J4: T4 | K4: T5 | L4: T6 | M4: T7 | N4: T8 | O4: T9 | P4: T10 | Q4: T11 | R4: T12 | S4: KH 2026
B5: 1 | C5: SẢN LƯỢNG BÁN (TẤN) | F5: =F6+F7+F8 -> 233413 | G5: =G6+G7+G8 -> 0 | H5: =H6+H7+H8 -> 0 | I5: =I6+I7+I8 -> 0 | J5: =J6+J7+J8 -> 0 | K5: =K6+K7+K8 -> 0 | L5: =L6+L7+L8 -> 0 | M5: =M6+M7+M8 -> 0 | ... R5: =R6+R7+R8 -> 630552 | S5: =SUM(G5:R5) -> 1891656
B6: 1.1 | C6: Chai PET | F6: ='4.Doanh thu'!E22 -> 0 | S6: =SUM(G6:R6) -> 0
B7: 1.2 | C7: Vảy PET | G7: ='4.Doanh thu'!F99 -> 0 | H7: ='4.Doanh thu'!G99 -> 0 | I7: ='4.Doanh thu'!H99 -> 0 | J7: ='4.Doanh thu'!I99 -> 0 | K7: ='4.Doanh thu'!J99 -> 0 | L7: ='4.Doanh thu'!K99 -> 0 | M7: ='4.Doanh thu'!L99 -> 0 | N7: ='4.Doanh thu'!M99 -> 0 | ... R7: ='4.Doanh thu'!Q99 -> 630552 | S7: =SUM(G7:R7) -> 1891656
B8: 1.3 | C8: Vảy HD | F8: ='4.Doanh thu'!AF161 -> 233413 | G8: ='4.Doanh thu'!F161 -> 0 | H8: ='4.Doanh thu'!G161 -> 0 | I8: ='4.Doanh thu'!H161 -> 0 | J8: ='4.Doanh thu'!I161 -> 0 | K8: ='4.Doanh thu'!J161 -> 0 | L8: ='4.Doanh thu'!K161 -> 0 | M8: ='4.Doanh thu'!L161 -> 0 | N8: ='4.Doanh thu'!M161 -> 0 | ... R8: ='4.Doanh thu'!Q161 -> 0 | S8: =SUM(G8:R8) -> 0
B9: 2 | C9: DOANH THU | F9: =F10+F11+F12+F13 -> 2969496970 | G9: =SUM(G10:G13) -> 0 | H9: =SUM(H10:H13) -> 0 | I9: =SUM(I10:I13) -> 0 | J9: =SUM(J10:J13) -> 0 | K9: =SUM(K10:K13) -> 0 | L9: =SUM(L10:L13) -> 0 | M9: =SUM(M10:M13) -> 0 | N9: =SUM(N10:N13) -> 0 | ... R9: =SUM(R10:R13) -> 10783110000 | S9: =SUM(G9:R9) -> 32349330000
B10: 2.1 | C10: Chai PET | F10: ='4.Doanh thu'!E60 -> 0 | S10: =SUM(G10:R10) -> 0
B11: 2.2 | C11: Vảy PET | G11: ='4.Doanh thu'!F157 -> 0 | H11: ='4.Doanh thu'!G157 -> 0 | I11: ='4.Doanh thu'!H157 -> 0 | J11: ='4.Doanh thu'!I157 -> 0 | K11: ='4.Doanh thu'!J157 -> 0 | L11: ='4.Doanh thu'!K157 -> 0 | M11: ='4.Doanh thu'!L157 -> 0 | N11: ='4.Doanh thu'!M157 -> 0 | ... R11: ='4.Doanh thu'!Q157 -> 10783110000 | S11: =SUM(G11:R11) -> 32349330000
B12: 2.3 | C12: Vảy HD | F12: ='4.Doanh thu'!AF163 -> 2969496970 | G12: ='4.Doanh thu'!F163 -> 0 | H12: ='4.Doanh thu'!G163 -> 0 | I12: ='4.Doanh thu'!H163 -> 0 | J12: ='4.Doanh thu'!I163 -> 0 | K12: ='4.Doanh thu'!J163 -> 0 | L12: ='4.Doanh thu'!K163 -> 0 | M12: ='4.Doanh thu'!L163 -> 0 | N12: ='4.Doanh thu'!M163 -> 0 | ... R12: ='4.Doanh thu'!Q163 -> 0 | S12: =SUM(G12:R12) -> 0
B13: 2.4 | C13: Khác | S13: =SUM(G13:R13) -> 0
B14: 3 | C14: BIẾN PHÍ | F14: =F15+F23 -> 3.7348983e+09 | G14: =G15+G23 -> 0 | H14: =H15+H23 -> 0 | I14: =I15+I23 -> 0 | J14: =J15+J23 -> 0 | K14: =K15+K23 -> 0 | L14: =L15+L23 -> 0 | M14: =M15+M23 -> 0 | ... R14: =R15+R23 -> 7.4178299e+09 | S14: =SUM(G14:R14) -> 2.225349e+10
B15: 3.1 | C15: BIẾN PHÍ SẢN XUẤT | F15: =F16+F20+F21+F22 -> 3703967057 | G15: =G16+G20+G21+G22 -> 0 | H15: =H16+H20+H21+H22 -> 0 | I15: =I16+I20+I21+I22 -> 0 | J15: =J16+J20+J21+J22 -> 0 | K15: =K16+K20+K21+K22 -> 0 | L15: =L16+L20+L21+L22 -> 0 | M15: =M16+M20+M21+M22 -> 0 | ... R15: =R16+R20+R21+R22 -> 7.2234097e+09 | S15: =SUM(G15:R15) -> 2.1670229e+10
B16: 3.1.1 | C16: Nguyên vật liệu chính (nhựa, gồm hao hụt) | F16: 3557818057 | G16: ='3.Thanh pham'!F102*'1.NVL Chai'!H34 -> 0 | H16: ='3.Thanh pham'!G102*'1.NVL Chai'!I34 -> 0 | I16: ='3.Thanh pham'!H102*'1.NVL Chai'!J34 -> 0 | J16: ='3.Thanh pham'!I102*'1.NVL Chai'!K34 -> 0 | K16: ='3.Thanh pham'!J102*'1.NVL Chai'!L34 -> 0 | L16: ='3.Thanh pham'!K102*'1.NVL Chai'!M34 -> 0 | M16: ='3.Thanh pham'!L102*'1.NVL Chai'!N34 -> 0 | N16: ='3.Thanh pham'!M102*'1.NVL Chai'!O34 -> 0 | ... R16: ='3.Thanh pham'!Q102*'1.NVL Chai'!S34 -> 6708000000 | S16: =SUM(G16:R16) -> 20124000000
B17: 3.1.2 | C17: Trong đó: i/ Hao hụt CĐ phân loại chai | F17: ='1.NVL Chai'!G43 -> 0 | S17: =SUM(G17:R17) -> 0
C18: ii/ Hao hụt CĐ băm vảy | G18: ='1.NVL Chai'!H34*'3.Thanh pham'!F192 -> 0 | H18: ='1.NVL Chai'!I34*'3.Thanh pham'!G192 -> 0 | I18: ='1.NVL Chai'!J34*'3.Thanh pham'!H192 -> 0 | J18: ='1.NVL Chai'!K34*'3.Thanh pham'!I192 -> 0 | K18: ='1.NVL Chai'!L34*'3.Thanh pham'!J192 -> 0 | L18: ='1.NVL Chai'!M34*'3.Thanh pham'!K192 -> 0 | M18: ='1.NVL Chai'!N34*'3.Thanh pham'!L192 -> 0 | N18: ='1.NVL Chai'!O34*'3.Thanh pham'!M192 -> 0 | ... R18: ='1.NVL Chai'!S34*'3.Thanh pham'!Q192 -> 402480000 | S18: =SUM(G18:R18) -> 1207440000
B19: 3.1.3 | C19: % chi phí nguyên liệu/doanh thu | F19: =IFERROR(F18/F$9,0) -> 0 | G19: =IFERROR(G18/G$9,0) -> 0 | H19: =IFERROR(H18/H$9,0) -> 0 | I19: =IFERROR(I18/I$9,0) -> 0 | J19: =IFERROR(J18/J$9,0) -> 0 | K19: =IFERROR(K18/K$9,0) -> 0 | L19: =IFERROR(L18/L$9,0) -> 0 | M19: =IFERROR(M18/M$9,0) -> 0 | ... S19: =IFERROR(S18/S$9,0) -> 0.037325039
B20: 3.1.4 | C20: Nguyên vật liệu phụ | G20: =SUM(CPSX!K119:K125) -> 0 | H20: =SUM(CPSX!L119:L125) -> 0 | I20: =SUM(CPSX!M119:M125) -> 0 | J20: =SUM(CPSX!N119:N125) -> 0 | K20: =SUM(CPSX!O119:O125) -> 0 | L20: =SUM(CPSX!P119:P125) -> 0 | M20: =SUM(CPSX!Q119:Q125) -> 0 | N20: =SUM(CPSX!R119:R125) -> 0 | ... R20: =SUM(CPSX!V119:V125) -> 2.7075326e+08 | S20: =SUM(G20:R20) -> 8.1225979e+08
B21: 3.1.5 | C21: Điện sản xuất | F21: =SUM(CPSX!AK118) -> 86149000 | G21: =CPSX!K118 -> 0 | H21: =CPSX!L118 -> 0 | I21: =CPSX!M118 -> 0 | J21: =CPSX!N118 -> 0 | K21: =CPSX!O118 -> 0 | L21: =CPSX!P118 -> 0 | M21: =CPSX!Q118 -> 0 | N21: =CPSX!R118 -> 0 | ... R21: =CPSX!V118 -> 172954600 | S21: =SUM(G21:R21) -> 518863800
B22: 3.1.6 | C22: Nhân công trực tiếp | F22: =SUM(CPSX!AK106:AK116) -> 60000000 | G22: =SUM(CPSX!K106:K115) -> 0 | H22: =SUM(CPSX!L106:L115) -> 0 | I22: =SUM(CPSX!M106:M115) -> 0 | J22: =SUM(CPSX!N106:N115) -> 0 | K22: =SUM(CPSX!O106:O115) -> 0 | L22: =SUM(CPSX!P106:P115) -> 0 | M22: =SUM(CPSX!Q106:Q115) -> 0 | N22: =SUM(CPSX!R106:R115) -> 0 | ... R22: =SUM(CPSX!V106:V115) -> 71701812 | S22: =SUM(G22:R22) -> 215105436
B23: 3.2 | C23: BIẾN PHÍ BÁN HÀNG | F23: =F24 -> 30931233 | G23: =G24 -> 0 | H23: =H24 -> 0 | I23: =I24 -> 0 | J23: =J24 -> 0 | K23: =K24 -> 0 | L23: =L24 -> 0 | M23: =M24 -> 0 | ... R23: =R24 -> 194420200 | S23: =SUM(G23:R23) -> 583260600
C24: Chi phí vận chuyển | F24: =SUM(CPBH!AK14) -> 30931233 | G24: =CPBH!K7 -> 0 | H24: =CPBH!L7 -> 0 | I24: =CPBH!M7 -> 0 | J24: =CPBH!N7 -> 0 | K24: =CPBH!O7 -> 0 | L24: =CPBH!P7 -> 0 | M24: =CPBH!Q7 -> 0 | N24: =CPBH!R7 -> 0 | ... R24: =CPBH!V7 -> 194420200 | S24: =SUM(G24:R24) -> 583260600
B25: 4 | C25: LÃI SAU BIẾN PHÍ | F25: =F9-F14 -> -7.6540132e+08 | G25: =G9-G14 -> 0 | H25: =H9-H14 -> 0 | I25: =I9-I14 -> 0 | J25: =J9-J14 -> 0 | K25: =K9-K14 -> 0 | L25: =L9-L14 -> 0 | M25: =M9-M14 -> 0 | ... R25: =R9-R14 -> 3.3652801e+09 | S25: =SUM(G25:R25) -> 1.009584e+10
B26: 4.1 | C26: % lãi biến phí/doanh thu | F26: =IFERROR(F25/F$9,0) -> -0.25775454 | G26: =IFERROR(G25/G$9,0) -> 0 | H26: =IFERROR(H25/H$9,0) -> 0 | I26: =IFERROR(I25/I$9,0) -> 0 | J26: =IFERROR(J25/J$9,0) -> 0 | K26: =IFERROR(K25/K$9,0) -> 0 | L26: =IFERROR(L25/L$9,0) -> 0 | M26: =IFERROR(M25/M$9,0) -> 0 | ... S26: =IFERROR(S25/S$9,0) -> 0.31208808
B27: 5 | C27: CHI PHÍ SẢN XUẤT CHUNG | F27: =F28+F29+F30 -> 2927437824 | G27: =G28+G29+G30 -> 230839676 | H27: =H28+H29+H30 -> 230839676 | I27: =I28+I29+I30 -> 230839676 | J27: =J28+J29+J30 -> 230839676 | K27: =K28+K29+K30 -> 230839676 | L27: =L28+L29+L30 -> 230839676 | M27: =M28+M29+M30 -> 230839676 | ... R27: =R28+R29+R30 -> 246268076 | S27: =SUM(G27:R27) -> 2816361312
B28: 5.1 | C28: Lương gián tiếp Sản xuất | F28: =SUM(CPSX!AK128:AK138) -> 0 | G28: =CPSX!K128 -> 0 | H28: =CPSX!L128 -> 0 | I28: =CPSX!M128 -> 0 | J28: =CPSX!N128 -> 0 | K28: =CPSX!O128 -> 0 | L28: =CPSX!P128 -> 0 | M28: =CPSX!Q128 -> 0 | N28: =CPSX!R128 -> 0 | ... R28: =CPSX!V128 -> 0 | S28: =SUM(G28:R28) -> 0
B29: 5.2 | C29: Chi phí thuê xưởng | F29: =SUM(CPSX!AK144) -> 2770076112 | G29: =CPSX!K144 -> 230839676 | H29: =CPSX!L144 -> 230839676 | I29: =CPSX!M144 -> 230839676 | J29: =CPSX!N144 -> 230839676 | K29: =CPSX!O144 -> 230839676 | L29: =CPSX!P144 -> 230839676 | M29: =CPSX!Q144 -> 230839676 | N29: =CPSX!R144 -> 230839676 | ... R29: =CPSX!V144 -> 230839676 | S29: =SUM(G29:R29) -> 2770076112
B30: 5.3 | C30: Chi phí sản xuất (Ngoài lương, BOM, thuê xưởng, khấu hao) | F30: =CPSX!AK127-SUM('KQKD HD'!F28,'KQKD HD'!F29,'KQKD HD'!F31) -> 157361712 | G30: =CPSX!K127-'KQKD HD'!G28-'KQKD HD'!G29-G31 -> 0 | H30: =CPSX!L127-'KQKD HD'!H28-'KQKD HD'!H29-H31 -> 0 | I30: =CPSX!M127-'KQKD HD'!I28-'KQKD HD'!I29-I31 -> 0 | J30: =CPSX!N127-'KQKD HD'!J28-'KQKD HD'!J29-J31 -> 0 | K30: =CPSX!O127-'KQKD HD'!K28-'KQKD HD'!K29-K31 -> 0 | L30: =CPSX!P127-'KQKD HD'!L28-'KQKD HD'!L29-L31 -> 0 | M30: =CPSX!Q127-'KQKD HD'!M28-'KQKD HD'!M29-M31 -> 0 | N30: =CPSX!R127-'KQKD HD'!N28-'KQKD HD'!N29-N31 -> 0 | ... R30: =CPSX!V127-'KQKD HD'!R28-'KQKD HD'!R29-R31 -> 15428400 | S30: =SUM(G30:R30) -> 46285200
B31: 6 | C31: CHI PHÍ KHẤU HAO, CCDC | F31: =CPSX!AK155 -> 3462360432 | G31: =CPSX!K155 -> 2.3368692e+08 | H31: =CPSX!L155 -> 2.3368692e+08 | I31: =CPSX!M155 -> 2.3368692e+08 | J31: =CPSX!N155 -> 2.3368692e+08 | K31: =CPSX!O155 -> 2.3368692e+08 | L31: =CPSX!P155 -> 2.3368692e+08 | M31: =CPSX!Q155 -> 2.3368692e+08 | N31: =CPSX!R155 -> 2.3368692e+08 | ... R31: =CPSX!V155 -> 2.5104803e+08 | S31: =SUM(G31:R31) -> 2.8563264e+09
B32: 7 | C32: LỢI NHUẬN GỘP | F32: =F25-F27-F31 -> -7.1551996e+09 | G32: =G25-G27-G31 -> -4.6452659e+08 | H32: =H25-H27-H31 -> -4.6452659e+08 | I32: =I25-I27-I31 -> -4.6452659e+08 | J32: =J25-J27-J31 -> -4.6452659e+08 | K32: =K25-K27-K31 -> -4.6452659e+08 | L32: =L25-L27-L31 -> -4.6452659e+08 | M32: =M25-M27-M31 -> -4.6452659e+08 | ... R32: =R25-R27-R31 -> 2.867964e+09 | S32: =SUM(G32:R32) -> 4.4231527e+09
B33: 7.1 | C33: % lãi gộp/doanh thu | F33: =IFERROR(F32/F$9,0) -> -2.4095662 | G33: =IFERROR(G32/G$9,0) -> 0 | H33: =IFERROR(H32/H$9,0) -> 0 | I33: =IFERROR(I32/I$9,0) -> 0 | J33: =IFERROR(J32/J$9,0) -> 0 | K33: =IFERROR(K32/K$9,0) -> 0 | L33: =IFERROR(L32/L$9,0) -> 0 | M33: =IFERROR(M32/M$9,0) -> 0 | ... S33: =IFERROR(S32/S$9,0) -> 0.13673089
B34: 8 | C34: CHI PHÍ BÁN HÀNG & MKT & R&D | F34: =F35+F36+F37 -> 0 | G34: =G35+G36+G37 -> 0 | H34: =H35+H36+H37 -> 0 | I34: =I35+I36+I37 -> 0 | J34: =J35+J36+J37 -> 0 | K34: =K35+K36+K37 -> 0 | L34: =L35+L36+L37 -> 0 | M34: =M35+M36+M37 -> 0 | ... R34: =R35+R36+R37 -> 0 | S34: =SUM(G34:R34) -> 0
B35: 8.1 | C35: Lương | S35: =SUM(G35:R35) -> 0
B36: 8.2 | C36: Chi phí bán hàng (ngoài lương, khấu hao) | S36: =SUM(G36:R36) -> 0
B37: 83 | C37: Khấu hao tài sản | S37: =SUM(G37:R37) -> 0
B38: 9 | C38: CHI PHÍ QUẢN LÝ | F38: =F39+F40+F41 -> 0 | G38: =G39+G40+G41 -> 0 | H38: =H39+H40+H41 -> 0 | I38: =I39+I40+I41 -> 0 | J38: =J39+J40+J41 -> 0 | K38: =K39+K40+K41 -> 0 | L38: =L39+L40+L41 -> 0 | M38: =M39+M40+M41 -> 0 | ... R38: =R39+R40+R41 -> 0 | S38: =SUM(G38:R38) -> 0
B39: 9.1 | C39: Lương | S39: =SUM(G39:R39) -> 0
B40: 9.2 | C40: Chi phí quản lý (ngoài lương, khấu hao) | S40: =SUM(G40:R40) -> 0
B41: 9.3 | C41: Khấu hao tài sản | S41: =SUM(G41:R41) -> 0
B42: 10 | C42: DOANH THU/CHI PHÍ KHÁC | S42: =SUM(G42:R42) -> 0
B43: 11 | C43: LỢI NHUẬN THUẦN TỪ HOẠT ĐỘNG KINH DOANH | F43: =F32-F34-F38+F42 -> -7.1551996e+09 | G43: =G32-G34-G38+G42 -> -4.6452659e+08 | H43: =H32-H34-H38+H42 -> -4.6452659e+08 | I43: =I32-I34-I38+I42 -> -4.6452659e+08 | J43: =J32-J34-J38+J42 -> -4.6452659e+08 | K43: =K32-K34-K38+K42 -> -4.6452659e+08 | L43: =L32-L34-L38+L42 -> -4.6452659e+08 | M43: =M32-M34-M38+M42 -> -4.6452659e+08 | ... R43: =R32-R34-R38+R42 -> 2.867964e+09 | S43: =SUM(G43:R43) -> 4.4231527e+09
B44: 12 | C44: DOANH THU TÀI CHÍNH | S44: =SUM(G44:R44) -> 0
B45: 13 | C45: CHI PHÍ TÀI CHÍNH | S45: =SUM(G45:R45) -> 0
B46: 13.1 | C46: Trong đó: chi phí lãi vay | S46: =SUM(G46:R46) -> 0
B47: 14 | C47: LỢI NHUẬN TRƯỚC THUẾ | F47: =F43+F44-F45 -> -7.1551996e+09 | G47: =G43+G44-G45 -> -4.6452659e+08 | H47: =H43+H44-H45 -> -4.6452659e+08 | I47: =I43+I44-I45 -> -4.6452659e+08 | J47: =J43+J44-J45 -> -4.6452659e+08 | K47: =K43+K44-K45 -> -4.6452659e+08 | L47: =L43+L44-L45 -> -4.6452659e+08 | M47: =M43+M44-M45 -> -4.6452659e+08 | ... R47: =R43+R44-R45 -> 2.867964e+09 | S47: =SUM(G47:R47) -> 4.4231527e+09
B48: 15 | C48: THUẾ TNDN | S48: =SUM(G48:R48) -> 0
B49: 16 | C49: LỢI NHUẬN SAU THUẾ | F49: =F47-F48 -> -7.1551996e+09 | G49: =G47-G48 -> -4.6452659e+08 | H49: =H47-H48 -> -4.6452659e+08 | I49: =I47-I48 -> -4.6452659e+08 | J49: =J47-J48 -> -4.6452659e+08 | K49: =K47-K48 -> -4.6452659e+08 | L49: =L47-L48 -> -4.6452659e+08 | M49: =M47-M48 -> -4.6452659e+08 | ... R49: =R47-R48 -> 2.867964e+09 | S49: =SUM(G49:R49) -> 4.4231527e+09
B50: 16.1 | C50: % LNST/doanh thu | F50: =IFERROR(F49/F$9,0) -> -2.4095662 | G50: =IFERROR(G49/G$9,0) -> 0 | H50: =IFERROR(H49/H$9,0) -> 0 | I50: =IFERROR(I49/I$9,0) -> 0 | J50: =IFERROR(J49/J$9,0) -> 0 | K50: =IFERROR(K49/K$9,0) -> 0 | L50: =IFERROR(L49/L$9,0) -> 0 | M50: =IFERROR(M49/M$9,0) -> 0 | ... S50: =IFERROR(S49/S$9,0) -> 0.13673089
B51: 17 | C51: Khấu hao tài sản | F51: =F31+F37+F41 -> 3462360432 | G51: =G31+G37+G41 -> 2.3368692e+08 | H51: =H31+H37+H41 -> 2.3368692e+08 | I51: =I31+I37+I41 -> 2.3368692e+08 | J51: =J31+J37+J41 -> 2.3368692e+08 | K51: =K31+K37+K41 -> 2.3368692e+08 | L51: =L31+L37+L41 -> 2.3368692e+08 | M51: =M31+M37+M41 -> 2.3368692e+08 | ... R51: =R31+R37+R41 -> 2.5104803e+08 | S51: =SUM(G51:R51) -> 2.8563264e+09 | CL51: ư
B52: 18 | C52: LỢI NHUẬN KHÔNG BAO GỒM KHẤU HAO, LÃI VAY | F52: =F49+F51 -> -3.6928391e+09 | G52: =G49+G51 -> -230839676 | H52: =H49+H51 -> -230839676 | I52: =I49+I51 -> -230839676 | J52: =J49+J51 -> -230839676 | K52: =K49+K51 -> -230839676 | L52: =L49+L51 -> -230839676 | M52: =M49+M51 -> -230839676 | ... R52: =R49+R51 -> 3.119012e+09 | S52: =SUM(G52:R52) -> 7.2794791e+09
B53: 18.1 | C53: % LN không gồm khấu hao/doanh thu | F53: =IFERROR(F52/F$9,0) -> -1.2435908 | G53: =IFERROR(G52/G$9,0) -> 0 | H53: =IFERROR(H52/H$9,0) -> 0 | I53: =IFERROR(I52/I$9,0) -> 0 | J53: =IFERROR(J52/J$9,0) -> 0 | K53: =IFERROR(K52/K$9,0) -> 0 | L53: =IFERROR(L52/L$9,0) -> 0 | M53: =IFERROR(M52/M$9,0) -> 0 | ... S53: =IFERROR(S52/S$9,0) -> 0.2250272

Sheet Cong suat
B3: CÔNG SUẤT
B4: I - CÔNG SUẤT CHUYỀN LỰA CHAI - CHAI XÁ TRÒN | E4: SX Chai B1.1 | F4: Loại B2.2, B4, B5, B6.2 | H4: Loại kim loại, chai còn nhãn
B5: STT | C5: Công đoạn sản xuất | D5: Cấp liệu | E5: Lồng tách tạp chất | F5: Lựa phân loại chai | G5: Tách nhãn | H5: Lựa phân loại chai sau tách nhãn | I5: Ép kiện | J5: Xử lý phó sản, nắp, cổ chai | K5: Công suất thành phẩm cả chuyền
B6: 1 | C6: Năng suất THIẾT KẾ (Kg NVL đầu vào / giờ) | D6: 1500 | E6: 1500 | F6: 1500 | G6: 1.100-1.500 | H6: 1100 | I6: 1400 | K6: =D6*(100%-$D$14) -> 1335
B7: 2 | C7: Năng suất ĐỊNH MỨC (Kg NVL đầu vào / giờ) | D7: 1400 | E7: 1200 | F7: 1200 | G7: =D7*95% -> 1330 | H7: =D7*90% -> 1260 | I7: 1300 | K7: =E15 -> 1246
B8: 3 | C8: Định mức nhân công (Số NV / Ca8) | D8: 2 | E8: 2 | F8: =4+1 -> 5 | G8: 1 | H8: =5 -> 5 | I8: =1 -> 1 | J8: 2 | K8: =SUM(D8:J8) -> 18
C9: Diễn giải
B11: STT | C11: Chỉ tiêu định mức | D11: ĐVT | E11: ĐM 1 giờ | F11: ĐM 1 Ca8 | G11: ĐM 1 Ca12 | H11: ĐM 2 Ca8 | I11: ĐM 2 Ca12
B12: 1 | C12: Tổng nhân sự: | D12: Người | E12: =K8 -> 18 | F12: =$E12 -> 18 | G12: =$F12*1.5 -> 27 | H12: =$F12*2 -> 36 | I12: =$G12*2 -> 54
B13: 2 | C13: Định mức NVL đầu vào: | D13: kg/giờ | E13: =D7 -> 1400 | F13: =$E13*8 -> 11200 | G13: =$F13*1.5 -> 16800 | H13: =$F13*2 -> 22400 | I13: =$G13*2 -> 33600
B14: 3 | C14: Hao hụt: | D14: ='2.Hao hut & % chai '!$N$8 -> 0.11 | E14: =E13*$D$14 -> 154 | F14: =$E14*8 -> 1232 | G14: =$E14*12 -> 1848 | H14: =$F14*2 -> 2464 | I14: =$G14*2 -> 3696
B15: 4 | C15: Định mức thành phẩm: | D15: kg/giờ | E15: =E13-E14 -> 1246 | F15: =$E15*8 -> 9968 | G15: =$F15*1.5 -> 14952 | H15: =$F15*2 -> 19936 | I15: =$G15*2 -> 29904
B16: 5 | C16: Định mức thành phẩm/người: | D16: kg/giờ/người | E16: =E15/K8 -> 69.222222 | F16: =$E16*8 -> 553.77778 | G16: =$F16*1.5 -> 830.66667 | H16: =$F16*2 -> 1107.5556 | I16: =$G16*2 -> 1661.3333
B18: II - CÔNG SUẤT CHUYỀN LỰA CHAI - CHAI ÉP KIỆN
B19: STT | C19: Công đoạn sản xuất | D19: Cấp liệu | E19: Phá kiện (thủ công bằng tay) | F19: Lựa phân loại chai | G19: Tách nhãn | H19: Lựa phân loại chai sau tách nhãn | I19: Ép kiện | J19: Xử lý phó sản, nắp, cổ chai | K19: Công suất thành phẩm cả chuyền
B20: 1 | C20: Năng suất THIẾT KẾ (Kg NVL đầu vào / giờ) | D20: 1500 | F20: 1500 | G20: 1.100-1.500 | H20: 1100 | I20: 1400 | K20: =D20*(100%-$D$14) -> 1335
B21: 2 | C21: Năng suất ĐỊNH MỨC (Kg NVL đầu vào / giờ) | D21: 1400 | E21: =D21 -> 1400 | F21: =E21 -> 1400 | G21: =F21 -> 1400 | H21: =G21 -> 1400 | I21: 1300 | K21: =E29 -> 1218
B22: 3 | C22: Định mức nhân công (Số NV / Ca8) | D22: 2 | E22: 2 | F22: =3+1+1 -> 5 | G22: 1 | H22: 6 | I22: =1+1 -> 2 | J22: 2 | K22: =SUM(D22:J22) -> 20
C23: Diễn giải
B25: STT | C25: Chỉ tiêu định mức | D25: ĐVT | E25: ĐM 1 giờ | F25: ĐM 1 Ca8 | G25: ĐM 1 Ca12 | H25: ĐM 2 Ca8 | I25: ĐM 2 Ca12
B26: 1 | C26: Tổng nhân sự: | D26: Người | E26: =K22 -> 20 | F26: =$E26 -> 20 | G26: =$F26*1.5 -> 30 | H26: =$F26*2 -> 40 | I26: =$G26*2 -> 60
B27: 2 | C27: Định mức NVL đầu vào: | D27: kg/giờ | E27: =G21 -> 1400 | F27: =$E27*8 -> 11200 | G27: =$F27*1.5 -> 16800 | H27: =$F27*2 -> 22400 | I27: =$G27*2 -> 33600
B28: 3 | C28: Hao hụt: | D28: ='2.Hao hut & % chai '!$N$14 -> 0.13 | E28: =E27*$D$28 -> 182 | F28: =$E28*8 -> 1456 | G28: =$F28*1.5 -> 2184 | H28: =$F28*2 -> 2912 | I28: =$G28*2 -> 4368
B29: 4 | C29: Định mức thành phẩm: | D29: kg/giờ | E29: =E27-E28 -> 1218 | F29: =$E29*8 -> 9744 | G29: =$F29*1.5 -> 14616 | H29: =$F29*2 -> 19488 | I29: =$G29*2 -> 29232
B30: 5 | C30: Định mức thành phẩm/người: | D30: kg/giờ/người | E30: =E29/K22 -> 60.9 | F30: =$E30*8 -> 487.2 | G30: =$F30*1.5 -> 730.8 | H30: =$F30*2 -> 974.4 | I30: =$G30*2 -> 1461.6
B32: III - CÔNG SUẤT CHUYỀN LỰA CHAI - CHAI TUYỂN XÔ
B33: STT | C33: Công đoạn sản xuất | D33: Cấp liệu | E33: Lồng tách tạp chất | F33: Lựa phân loại chai | G33: Tách nhãn | H33: Lựa phân loại chai sau tách nhãn | I33: Ép kiện | J33: Xử lý phó sản, nắp, cổ chai | K33: Công suất thành phẩm cả chuyền
B34: 1 | C34: Năng suất THIẾT KẾ (Kg NVL đầu vào / giờ) | D34: 2000 | E34: 2000 | F34: 1500 | G34: 1.000-1.500 | H34: 1000 | I34: 1400 | K34: 1300
B35: 2 | C35: Năng suất ĐỊNH MỨC (Kg NVL đầu vào / giờ) | D35: 2000 | E35: 2000 | F35: 1500 | G35: 1000 | H35: 900 | I35: 1300 | K35: =E43 -> 1926
B36: 3 | C36: Định mức nhân công (Số NV / Ca8) | D36: 2 | F36: 2 | G36: 1 | H36: 2 | I36: 2 | J36: 2 | K36: =SUM(D36:J36) -> 11
C37: Diễn giải
B39: STT | C39: Chỉ tiêu định mức | D39: ĐVT | E39: ĐM 1 giờ | F39: ĐM 1 Ca8 | G39: ĐM 1 Ca12 | H39: ĐM 2 Ca8 | I39: ĐM 2 Ca12
B40: 1 | C40: Tổng nhân sự: | D40: Người | E40: =K36 -> 11 | F40: =$E40 -> 11 | G40: =$F40*1.5 -> 16.5 | H40: =$F40*2 -> 22 | I40: =$G40*2 -> 33
B41: 2 | C41: Định mức NVL đầu vào: | D41: kg/giờ | E41: =$E$35 -> 2000 | F41: =$E41*8 -> 16000 | G41: =$F41*1.5 -> 24000 | H41: =$F41*2 -> 32000 | I41: =$G41*2 -> 48000
B42: 3 | C42: Hao hụt: | D42: ='2.Hao hut & % chai '!$G$20 -> 0.037 | E42: =E41*$D$42 -> 74 | F42: =$E42*8 -> 592 | G42: =$E42*12 -> 888 | H42: =$F42*2 -> 1184 | I42: =$G42*2 -> 1776
B43: 4 | C43: Định mức thành phẩm: | D43: kg/giờ | E43: =E41-E42 -> 1926 | F43: =$E43*8 -> 15408 | G43: =$F43*1.5 -> 23112 | H43: =$F43*2 -> 30816 | I43: =$G43*2 -> 46224
B44: 5 | C44: Định mức thành phẩm/người: | D44: kg/giờ/người | E44: =E43/K36 -> 175.09091 | F44: =$E44*8 -> 1400.7273 | G44: =$F44*1.5 -> 2101.0909 | H44: =$F44*2 -> 2801.4545 | I44: =$G44*2 -> 4202.1818
B46: VI - CÔNG SUẤT MÁY VÀ NĂNG SUẤT LAO ĐỘNG MỤC TIÊU
B47: 1 | C47: CHUYỀN LỰA CHAI - CHAI XÁ TRÒN | E47: Định mức | F47: T1 | G47: T2 | H47: T3 | I47: T4 | J47: T5 | K47: T6 | L47: T7 | M47: T8 | N47: T9 | O47: T10 | P47: T11 | Q47: T12 | R47: Mục tiêu 2026
B48: a | C48: Số nhân sự/ chuyền/ ca | D48: Người | E48: =E12 -> 18 | F48: =E48 -> 18 | G48: =F48 -> 18 | H48: =G48 -> 18 | I48: =H48 -> 18 | J48: =E48 -> 18 | K48: =J48 -> 18 | L48: =K48 -> 18 | M48: =L48 -> 18 | N48: =M48 -> 18 | O48: =N48 -> 18 | P48: =O48 -> 18 | Q48: =P48 -> 18
B49: b | C49: Công suất/ chuyền | D49: kg/giờ | E49: =E15 -> 1246 | F49: =E49 -> 1246 | G49: =F49 -> 1246 | H49: =G49 -> 1246 | I49: =H49 -> 1246 | J49: =E49 -> 1246 | K49: =J49 -> 1246 | L49: =K49 -> 1246 | M49: =L49 -> 1246 | N49: =M49 -> 1246 | O49: =N49 -> 1246 | P49: =O49 -> 1246 | Q49: =P49 -> 1246
B50: c | C50: Năng suất lao động | D50: kg/giờ/người | E50: =E49/E48 -> 69.222222 | F50: =E50 -> 69.222222 | G50: =F50 -> 69.222222 | H50: =G50 -> 69.222222 | I50: =H50 -> 69.222222 | J50: =J49/J48 -> 69.222222 | K50: =K49/K48 -> 69.222222 | L50: =L49/L48 -> 69.222222 | M50: =M49/M48 -> 69.222222 | N50: =N49/N48 -> 69.222222 | O50: =O49/O48 -> 69.222222 | P50: =P49/P48 -> 69.222222 | Q50: =Q49/Q48 -> 69.222222
B51: 2 | C51: CHUYỀN LỰA CHAI - CHAI ÉP KIỆN | F51: =E51 -> 0 | G51: =F51 -> 0 | H51: =G51 -> 0 | I51: =H51 -> 0
B52: a | C52: Số nhân sự/ chuyền/ ca | D52: Người | E52: =E26 -> 20 | F52: =E52 -> 20 | G52: =F52 -> 20 | H52: =G52 -> 20 | I52: =H52 -> 20 | J52: =E52 -> 20 | K52: =J52 -> 20 | L52: =K52 -> 20 | M52: =L52 -> 20 | N52: =M52 -> 20 | O52: =N52 -> 20 | P52: =O52 -> 20 | Q52: =P52 -> 20
B53: b | C53: Công suất/chuyền (kg thành phẩm/ giờ) | D53: kg/giờ | E53: =E29 -> 1218 | F53: =E53 -> 1218 | G53: =F53 -> 1218 | H53: =G53 -> 1218 | I53: =H53 -> 1218 | J53: =E53 -> 1218 | K53: =J53 -> 1218 | L53: =K53 -> 1218 | M53: =L53 -> 1218 | N53: =M53 -> 1218 | O53: =N53 -> 1218 | P53: =O53 -> 1218 | Q53: =P53 -> 1218
B54: c | C54: Năng suất lao động (kg thành phẩm/ người/ giờ): | D54: kg/giờ/người | E54: =E53/E52 -> 60.9 | F54: =E54 -> 60.9 | G54: =F54 -> 60.9 | H54: =G54 -> 60.9 | I54: =H54 -> 60.9 | J54: =J53/J52 -> 60.9 | K54: =K53/K52 -> 60.9 | L54: =L53/L52 -> 60.9 | M54: =M53/M52 -> 60.9 | N54: =N53/N52 -> 60.9 | O54: =O53/O52 -> 60.9 | P54: =P53/P52 -> 60.9 | Q54: =Q53/Q52 -> 60.9
B55: 3 | C55: CHUYỀN LỰA CHAI - CHAI TUYỂN XÔ (có thể xử lý chạy trên chuyền chai tròn hoặc ép kiện) | F55: =E55 -> 0 | G55: =F55 -> 0 | H55: =G55 -> 0 | I55: =H55 -> 0
B56: a | C56: Số nhân sự/ chuyền/ ca | D56: Người | E56: =E40 -> 11 | F56: =E56 -> 11 | G56: =F56 -> 11 | H56: =G56 -> 11 | I56: =H56 -> 11 | J56: =E56 -> 11 | K56: =J56 -> 11 | L56: =K56 -> 11 | M56: =L56 -> 11 | N56: =M56 -> 11 | O56: =N56 -> 11 | P56: =O56 -> 11 | Q56: =P56 -> 11
B57: b | C57: Công suất/chuyền (kg thành phẩm/ giờ) | D57: kg/giờ | E57: =E43 -> 1926 | F57: =E57 -> 1926 | G57: =F57 -> 1926 | H57: =G57 -> 1926 | I57: =H57 -> 1926 | J57: =E57 -> 1926 | K57: =J57 -> 1926 | L57: =K57 -> 1926 | M57: =L57 -> 1926 | N57: =M57 -> 1926 | O57: =N57 -> 1926 | P57: =O57 -> 1926 | Q57: =P57 -> 1926
B58: c | C58: Năng suất lao động (kg thành phẩm/ người/ giờ): | D58: kg/giờ/người | E58: =E57/E56 -> 175.09091 | F58: =E58 -> 175.09091 | G58: =F58 -> 175.09091 | H58: =G58 -> 175.09091 | I58: =H58 -> 175.09091 | J58: =J57/J56 -> 175.09091 | K58: =K57/K56 -> 175.09091 | L58: =L57/L56 -> 175.09091 | M58: =M57/M56 -> 175.09091 | N58: =N57/N56 -> 175.09091 | O58: =O57/O56 -> 175.09091 | P58: =P57/P56 -> 175.09091 | Q58: =Q57/Q56 -> 175.09091
B60: VII - TỔNG CÔNG SUẤT MÁY PET và NĂNG SUẤT LAO ĐỘNG
B61: i | C61: Tổng công suất PET/giờ | D61: kg/giờ | E61: Định mức | F61: T1 | G61: T2 | H61: T3 | I61: T4 | J61: T5 | K61: T6 | L61: T7 | M61: T8 | N61: T9 | O61: T10 | P61: T11 | Q61: T12 | R61: Mục tiêu 2026
B62: 1 | C62: Công suất máy - Tính trên NVL đầu vào | D62: Tấn/giờ | E62: =$E$13+$E$27*90%+$E$41*10% -> 2860 | F62: =$E$13+$E$27*95%+$E$41*5% -> 2830 | G62: =$E$13+$E$27*95%+$E$41*5% -> 2830 | H62: =$E$13+$E$27*95%+$E$41*5% -> 2830 | I62: =$E$13+$E$27*95%+$E$41*5% -> 2830 | J62: =$E$13+$E$27*95%+$E$41*5% -> 2830 | K62: =$E$13+$E$27*95%+$E$41*5% -> 2830 | L62: =$E$13+$E$27*95%+$E$41*5% -> 2830 | M62: =$E$13+$E$27*95%+$E$41*5% -> 2830 | ... Q62: =$E$13+$E$27*95%+$E$41*5% -> 2830
B63: 2 | C63: Công suất máy - Tính trên Thành phẩm SX | D63: Tấn/giờ | E63: =$E$49+$E$53*80%+$E$57*20% -> 2605.6 | F63: =$E$49+$E$53*80%+$E$57*20% -> 2605.6 | G63: =$E$49+$E$53*80%+$E$57*20% -> 2605.6 | H63: =$E$49+$E$53*80%+$E$57*20% -> 2605.6 | I63: =$E$49+$E$53*80%+$E$57*20% -> 2605.6 | J63: =$E$49+$E$53*80%+$E$57*20% -> 2605.6 | K63: =$E$49+$E$53*80%+$E$57*20% -> 2605.6 | L63: =$E$49+$E$53*80%+$E$57*20% -> 2605.6 | ... Q63: =$E$49+$E$53*80%+$E$57*20% -> 2605.6
B64: ii | C64: Tổng công suất PET/tháng (8hx4cax30 ngày) | D64: kg/tháng | E64: Định mức | J64: T5 | K64: T6 | L64: T7 | M64: T8 | N64: T9 | O64: T10 | P64: T11 | Q64: T12
B65: 1 | C65: Công suất máy - Tính trên NVL đầu vào | D65: Tấn/tháng | E65: =E62*7*2*30 -> 1201200 | F65: =F62*7*2*30 -> 1188600 | G65: =G62*7*2*30 -> 1188600 | H65: =H62*7*2*30 -> 1188600 | I65: =I62*7*2*30 -> 1188600 | J65: =J62*7*2*30 -> 1188600 | K65: =K62*7*2*30 -> 1188600 | L65: =L62*7*2*30 -> 1188600 | ... Q65: =Q62*7*2*30 -> 1188600
B66: 2 | C66: Công suất máy - Tính trên Thành phẩm SX | D66: Tấn/tháng | E66: =E63*7*2*30 -> 1094352 | F66: =F63*7*2*30 -> 1094352 | G66: =G63*7*2*30 -> 1094352 | H66: =H63*7*2*30 -> 1094352 | I66: =I63*7*2*30 -> 1094352 | J66: =J63*7*2*30 -> 1094352 | K66: =K63*7*2*30 -> 1094352 | L66: =L63*7*2*30 -> 1094352 | ... Q66: =Q63*7*2*30 -> 1094352
B67: iii | C67: Năng suất lao động (CNTT) | E67: Định mức | J67: T5 | K67: T6 | L67: T7 | M67: T8 | N67: T9 | O67: T10 | P67: T11 | Q67: T12
B68: 1 | C68: Năng suất lao động - Tấn/người/ngày | D68: Tấn/người/ngày | E68: =E69/30 -> 251.92265 | F68: =F69/30 -> 251.92265 | G68: =G69/30 -> 251.92265 | H68: =H69/30 -> 251.92265 | I68: =I69/30 -> 251.92265 | J68: =J69/30 -> 251.92265 | K68: =K69/30 -> 251.92265 | L68: =L69/30 -> 251.92265 | ... Q68: =Q69/30 -> 251.92265
B69: 2 | C69: Năng suất lao động - Tấn/người/tháng | D69: Tấn/người/tháng | E69: =E66/(E48+E52*80%+E56*20%)/4 -> 7557.6796 | F69: =F66/(F48+F52*80%+F56*20%)/4 -> 7557.6796 | G69: =G66/(G48+G52*80%+G56*20%)/4 -> 7557.6796 | H69: =H66/(H48+H52*80%+H56*20%)/4 -> 7557.6796 | I69: =I66/(I48+I52*80%+I56*20%)/4 -> 7557.6796 | J69: =J66/(J48+J52*80%+J56*20%)/4 -> 7557.6796 | K69: =K66/(K48+K52*80%+K56*20%)/4 -> 7557.6796 | L69: =L66/(L48+L52*80%+L56*20%)/4 -> 7557.6796 | ... Q69: =Q66/(Q48+Q52*80%+Q56*20%)/4 -> 7557.6796
B71: IX - CÔNG SUẤT CHUYỀN BĂM PET FS (B6.2)
B72: STT | C72: Công đoạn sản xuất | D72: Cấp liệu | E72: XXX | F72: XXX | G72: XXX | H72: XXX | I72: Đóng gói, cân TP | J72: XXX | K72: Công suất thành phẩm cả chuyền
B73: 1 | C73: Năng suất THIẾT KẾ (Kg NVL đầu vào / giờ) | D73: 7000 | K73: =D73*(100%-$D$97) -> 6580
B74: 2 | C74: Năng suất ĐỊNH MỨC (Kg NVL đầu vào / giờ) | D74: 700 | E74: =D74 -> 700 | F74: =E74 -> 700 | G74: =F74 -> 700 | H74: =G74 -> 700 | I74: 1300 | K74: =D74*(100%-$D$81) -> 630
B75: 3 | C75: Định mức nhân công (Số NV / Ca8) | D75: 1 | F75: 1 | I75: 1 | K75: =SUM(D75:J75) -> 3
C76: Diễn giải
B78: STT | C78: Chỉ tiêu định mức | D78: ĐVT | E78: ĐM 1 giờ | F78: ĐM 1 Ca8 | G78: ĐM 1 Ca12 | H78: ĐM 2 Ca8 | I78: ĐM 2 Ca12
B79: 1 | C79: Tổng nhân sự: | D79: Người | E79: =K75 -> 3 | F79: =$E79 -> 3 | G79: =$F79*1.5 -> 4.5 | H79: =$F79*2 -> 6 | I79: =$G79*2 -> 9
B80: 2 | C80: Định mức NVL đầu vào: | D80: kg/giờ | E80: =D74 -> 700 | F80: =$E80*8 -> 5600 | G80: =$F80*1.5 -> 8400 | H80: =$F80*2 -> 11200 | I80: =$G80*2 -> 16800
B81: 3 | C81: Hao hụt: | D81: ='2.Hao hut & % chai '!H43 -> 0.1 | E81: =E80*D81 -> 70 | F81: =$E81*8 -> 560 | G81: =$F81*1.5 -> 840 | H81: =$F81*2 -> 1120 | I81: =$G81*2 -> 1680
B82: 4 | C82: Định mức thành phẩm: | D82: kg/giờ | E82: =E80-E81 -> 630 | F82: =$E82*8 -> 5040 | G82: =$F82*1.5 -> 7560 | H82: =$F82*2 -> 10080 | I82: =$G82*2 -> 15120
B83: 5 | C83: Định mức thành phẩm/người: | D83: kg/giờ/người | E83: =E82/K75 -> 210 | F83: =$E83*8 -> 1680 | G83: =$F83*1.5 -> 2520 | H83: =$F83*2 -> 3360 | I83: =$G83*2 -> 5040
B87: IX - CÔNG SUẤT CHUYỀN BĂM HDPE
B88: STT | C88: Công đoạn sản xuất | D88: Cấp liệu | E88: XXX | F88: XXX | G88: XXX | H88: XXX | I88: Đóng gói, cân TP | J88: XXX | K88: Công suất thành phẩm cả chuyền
B89: 1 | C89: Năng suất THIẾT KẾ (Kg NVL đầu vào / giờ) | D89: 1500 | K89: =D89*(100%-$D$97) -> 1410
B90: 2 | C90: Năng suất ĐỊNH MỨC (Kg NVL đầu vào / giờ) | D90: 1500 | E90: =D90 -> 1500 | F90: =E90 -> 1500 | G90: =F90 -> 1500 | H90: =G90 -> 1500 | I90: 1300 | K90: =D90*(100%-$D$97) -> 1410
B91: 3 | C91: Định mức nhân công (Số NV / Ca8) | D91: 1 | F91: 1 | I91: 1 | K91: =SUM(D91:J91) -> 3
C92: Diễn giải
B94: STT | C94: Chỉ tiêu định mức | D94: ĐVT | E94: ĐM 1 giờ | F94: ĐM 1 Ca8 | G94: ĐM 1 Ca12 | H94: ĐM 2 Ca8 | I94: ĐM 2 Ca12
B95: 1 | C95: Tổng nhân sự: | D95: Người | E95: =K91 -> 3 | F95: =$E95 -> 3 | G95: =$F95*1.5 -> 4.5 | H95: =$F95*2 -> 6 | I95: =$G95*2 -> 9
B96: 2 | C96: Định mức NVL đầu vào: | D96: kg/giờ | E96: =D90 -> 1500 | F96: =$E96*8 -> 12000 | G96: =$F96*1.5 -> 18000 | H96: =$F96*2 -> 24000 | I96: =$G96*2 -> 36000
B97: 3 | C97: Hao hụt: | D97: ='2.Hao hut & % chai '!H27 -> 0.06 | E97: =E96*D97 -> 90 | F97: =$E97*8 -> 720 | G97: =$F97*1.5 -> 1080 | H97: =$F97*2 -> 1440 | I97: =$G97*2 -> 2160
B98: 4 | C98: Định mức thành phẩm: | D98: kg/giờ | E98: =E96-E97 -> 1410 | F98: =$E98*8 -> 11280 | G98: =$F98*1.5 -> 16920 | H98: =$F98*2 -> 22560 | I98: =$G98*2 -> 33840
B99: 5 | C99: Định mức thành phẩm/người: | D99: kg/giờ/người | E99: =E98/K91 -> 470 | F99: =$E99*8 -> 3760 | G99: =$F99*1.5 -> 5640 | H99: =$F99*2 -> 7520 | I99: =$G99*2 -> 11280
B102: IX - CÔNG SUẤT CHUYỀN DÂY ĐAI
B103: STT | C103: Công đoạn sản xuất | D103: Cấp liệu | E103: XXX | F103: XXX | G103: XXX | H103: XXX | I103: Đóng gói, cân TP | J103: XXX | K103: Công suất thành phẩm cả chuyền
B104: 1 | C104: Năng suất THIẾT KẾ (Kg NVL đầu vào / giờ) | D104: 300 | K104: =D104*(100%-$D$97) -> 282
B105: 2 | C105: Năng suất ĐỊNH MỨC (Kg NVL đầu vào / giờ) | D105: 300 | K105: =D105*(100%-$D$97) -> 282
C106: Định mức Kỹ thuật vận hành (Số NV / Ca12) | D106: 1 | K106: =SUM(D106:J106) -> 1
B107: 3 | C107: Định mức nhân công (Số NV / Ca12) | D107: 2 | K107: =SUM(D107:J107) -> 2
C108: Diễn giải
B110: STT | C110: Chỉ tiêu định mức | D110: ĐVT | E110: ĐM 1 giờ | F110: ĐM 1 Ca8 | G110: ĐM 1 Ca12 | H110: ĐM 2 Ca8 | I110: ĐM 2 Ca12
B111: 1 | C111: Tổng nhân sự: | D111: Người | E111: 3 | F111: =$E111 -> 3 | G111: =$F111*1.5 -> 4.5 | H111: =$F111*2 -> 6 | I111: =$G111*2 -> 9
B112: 2 | C112: Định mức NVL đầu vào: | D112: kg/giờ | E112: =D105 -> 300 | F112: =$E112*8 -> 2400 | G112: =$F112*1.5 -> 3600 | H112: =$F112*2 -> 4800 | I112: =$G112*2 -> 7200
B113: 3 | C113: Hao hụt: | D113: ='2.Hao hut & % chai '!T172 -> 0.04 | E113: =E112*$D$28 -> 39 | F113: =$E113*8 -> 312 | G113: =$F113*1.5 -> 468 | H113: =$F113*2 -> 624 | I113: =$G113*2 -> 936
B114: 4 | C114: Định mức thành phẩm: | D114: kg/giờ | E114: =E112-E113 -> 261 | F114: =$E114*8 -> 2088 | G114: =$F114*1.5 -> 3132 | H114: =$F114*2 -> 4176 | I114: =$G114*2 -> 6264
B115: 5 | C115: Định mức thành phẩm/người: | D115: kg/giờ/người | E115: =E114/K107 -> 130.5 | F115: =$E115*8 -> 1044 | G115: =$F115*1.5 -> 1566 | H115: =$F115*2 -> 2088 | I115: =$G115*2 -> 3132
B117: VIII - CÔNG SUẤT CHUYỀN BĂM VẢY PET
B118: STT | C118: Công đoạn sản xuất | D118: Cấp liệu | E118: XXX | F118: XXX | G118: XXX | H118: XXX | I118: Đóng gói, cân TP | J118: XXX | K118: Công suất thành phẩm cả chuyền
B119: 1 | C119: Năng suất THIẾT KẾ (Kg NVL đầu vào / giờ) | D119: 2000 | F119: 1500 | G119: 1.100-1.500 | K119: =D119*(100%-$D$97) -> 1880
...

Sheet Dinh muc
B3: ĐỊNH MỨC CHI PHÍ
B4: I - ĐỊNH MỨC TIÊU HAO VẬT TƯ - PHÂN LOẠI CHAI PET
B5: STT | C5: Mục phí | D5: ĐVT | E5: Định mức | F5: Đơn giá | G5: Chi phí/1kg thành phẩm | H5: Diễn giải
C6: Công suất lựa chai | E6: =('Cong suat'!E29+'Cong suat'!E15)/2 -> 1232
B7: 1 | C7: Chi phí nhân công trực tiếp (giờ công lao động) | E7: =E8+E9 -> 128
B8: a | C8: LĐ định biên | D8: Giờ công/ca 8 | E8: =7*8 -> 56 | G8: =E8*F8/E6 -> 0
B9: b | C9: LĐ thời vụ | D9: Giờ công/ca 8 | E9: =9*8 -> 72 | F9: =260000/8 -> 32500 | G9: =E9*F9/E6 -> 1899.3506
B10: c | C10: Tiền ăn giữa Ca | D10: Đồng/người/ngày công | E10: =E7/8 -> 16 | F10: =25000 -> 25000 | G10: =(E10*F10)/($E$6*8) -> 40.584416
B11: 2 | C11: Điện sản xuất | D11: Kw/1chuyền/1giờ hoạt động | E11: 40 | F11: =ROUND(2100*1.05,-1) -> 2210 | G11: =E11*F11/E6 -> 71.753247
B12: 3 | C12: Dao tách nhãn chai PET | D12: Tấn/Bộ | E12: 1 | F12: 165000000 | G12: =F12/(1800000*87%) -> 105.36398 | H12: Anh Quân chốt định mức băm: 1500 tấn chai PET-B0 nâng lên 1800 tấn | I12: 1 bộ băm được 1700 tấn => Tỷ lệ TP: 87%
B13: 4 | C13: Dây đai | D13: Kg/tấn | E13: =1.1 -> 1.1 | F13: 51000 | G13: =E13*F13/(1000*87%)+1 -> 65.482759
B14: 5 | C14: Bao jumbo | D14: Cái
B15: 6 | C15: Hóa chất
B16: 7 | C16: Chi phí xử lý nhãn chai PET | D16: Kg | E16: 1 | F16: 300 | G16: =(6.5%*1000)*F16/870 -> 22.413793
B17: 8 | C17: Dầu xe nâng | D17: Lít/h | E17: =2.5*85% -> 2.125 | F17: 18000 | G17: =E17*F17/1100 -> 34.772727 | H17: Bình quân 1 h: 2.5 lít, hiệu suất sử dụng: 85%
B18: 9 | C18: Chi phí vận chuyển | D18: Chuyến/9 tấn | E18: 1 | F18: =3200000 -> 3200000 | G18: =F18/9000 -> 355.55556 | H18: 1 chuyến chở được 9 tấn
B20: II - ĐỊNH MỨC TIÊU HAO VẬT TƯ - BĂM VẢY PET - CHUYỀN FS (B6.2)
B21: STT | C21: Mục phí | D21: ĐVT | E21: ĐM 1 giờ | F21: Đơn giá | G21: Chi phí/1kg thành phẩm | H21: Diễn giải
C22: Công suất băm PET | E22: ='Cong suat'!E82 -> 630
B23: 1 | C23: Chi phí nhân công trực tiếp | E23: =SUM(E24:E25) -> 24
B24: a | C24: LĐ định biên | D24: Giờ công/ca 8 | E24: =3*8 -> 24
B25: b | C25: LĐ thời vụ | D25: Giờ công/ca 8
B26: c | C26: Tiền ăn giữa Ca | D26: Đồng/người/ngày công | E26: =E23/8 -> 3 | F26: =25000 -> 25000 | G26: =(E26*F26)/($E$22*8) -> 14.880952
B27: 2 | C27: Điện sản xuất | D27: Kw/h | E27: 70 | F27: =ROUND(2100*1.05,-1) -> 2210 | G27: =E27*F27/$E$22 -> 245.55556
B28: 3 | C28: Dao băm vảy PET | D28: Tấn/Bộ | E28: 1 | F28: 44000000 | G28: =F28/(250000*90%) -> 195.55556 | H28: Công suất thiết kế: 250 tấn | I28: 1 bộ băm 200 tấn, Tỷ lệ TP 90%
B29: 4 | C29: Dây đai
B30: 5 | C30: Bao jumbo | D30: Cái/Kg | E30: 1 | F30: 75000 | G30: =(E30*F30)/350/2 -> 107.14286 | H30: 1 cái chứa được: 350 kg, tái sử dụng được 2 lần
B31: 6 | C31: Hóa chất
B32: 7 | C32: Chi phí xử lý bùn, nước thải | G32: =SUM(G33:G35) -> 218.96 | H32: Xử lý: nhãn, bùn, nước thải, hóa chất xử lý hồ XLNT
B33: 7.1 | C33: Chi phí nước sản xuất | D33: m3/h | E33: 3 | F33: 11500 | G33: =E33*F33/$E$22 -> 54.761905
C34: Chi phí xử lý nước thải | D34: m3/h | E34: =E33*80% -> 2.4 | F34: 11852 | G34: =E34*F34/$E$22 -> 45.150476
C35: Chi phí xử lý bùn | D35: Kg/h | E35: ='Cong suat'!D90*5% -> 75 | F35: 1000 | G35: =E35*F35/$E$22 -> 119.04762
B36: 8 | C36: Dầu xe nâng | D36: Lít/h | E36: =2.5*60% -> 1.5 | F36: 18000 | G36: =E36*F36/1100 -> 24.545455 | H36: Bình quân 1 h: 2.5 lít, hiệu suất sử dụng: 70%
B37: 9 | C37: Chi phí vận chuyển | D37: Chuyến/12 tấn | E37: 1 | F37: 3700000 | G37: =F37/12000 -> 308.33333 | H37: 1 chuyến chở được 12 tấn
B39: III - ĐỊNH MỨC TIÊU HAO VẬT TƯ - BĂM VẢY PET Tu chuyen HD
B40: STT | C40: Mục phí | D40: ĐVT | E40: Định mức | F40: Đơn giá | G40: Chi phí/1kg thành phẩm | H40: Diễn giải
C41: Công suất băm HD | E41: ='Cong suat'!K90 -> 1410
B42: 1 | C42: Chi phí nhân công trực tiếp | E42: 3 | F42: 50320
B43: a | C43: LĐ định biên | D43: h | E43: =3*8 -> 24 | F43: 50320 | G43: =(E43*F43)/($E$41*8) -> 107.06383
B44: b | C44: LĐ thời vụ | D44: h
B45: c | C45: Tiền ăn giữa Ca | D45: Đồng/người/ngày công | E45: 3 | F45: =25000 -> 25000 | G45: =E45*F45/($E$41*8) -> 6.6489362
B46: 2 | C46: Điện sản xuất | D46: Kw/h | E46: =250*70% -> 175 | F46: =ROUND(2100*1.05,-1) -> 2210 | G46: =E46*F46/$E$41 -> 274.29078
B47: 3 | C47: Dao băm vảy HD | D47: Tấn/Bộ | E47: 1 | F47: 70000000 | G47: =(E47*F47)/(300000*95%) -> 245.61404
B48: 4 | C48: Dây đai
B49: 5 | C49: Bao jumbo | D49: Cái/Kg | E49: 1 | F49: 75000 | G49: =E49*F49/350/2 -> 107.14286 | H49: 1 cái sử dụng được 2 lần
B50: 6 | C50: Hóa chất
B51: 7.1 | C51: Chi phí nước sản xuất | D51: m3/h | E51: 3 | F51: 11500 | G51: =E51*F51/$E$41 -> 24.468085
B52: 7 | C52: Chi phí xử lý nước thải, môi trường | D52: m3/h | E52: =E51*80% -> 2.4 | F52: 11852 | G52: =E52*F52/$E$41 -> 20.173617
C53: Chi phí xử lý bùn | D53: Kg/h | E53: ='Cong suat'!D90*3% -> 45 | F53: 1000 | G53: =E53*F53/$E$41 -> 31.914894 | H53: bùn đất: 3%
B54: 8 | C54: Dầu xe nâng | D54: Lít/h | E54: =2.5*60% -> 1.5 | F54: 18000 | G54: =E54*F54/1100 -> 24.545455
B55: 9 | C55: Chi phí vận chuyển | D55: Chuyến/12 tấn | E55: 1 | F55: 3700000 | G55: =F55/12000 -> 308.33333 | H55: 1 chuyến chở được 12 tấn
H59: Ngày …
C60: Duyệt | D60: Xem xét | E60: Xem xét | G60: Xem xét | H60: Người lập
C61: GĐĐH DTR | D61: GĐTC DTR | E61: GĐ các trạm | G61: Trưởng Trạm | H61: Kế toán trưởng

Sheet Dinh muc (2)
B3: ĐỊNH MỨC CHI PHÍ
B4: I - ĐỊNH MỨC TIÊU HAO VẬT TƯ - PHÂN LOẠI CHAI PET
B5: STT | C5: Mục phí | D5: ĐVT | E5: Định mức | F5: Đơn giá | G5: Chi phí/1kg thành phẩm | H5: Diễn giải
C6: Công suất lựa chai | E6: =('Cong suat'!E29+'Cong suat'!E15)/2 -> 1232
B7: 1 | C7: Chi phí nhân công trực tiếp (giờ công lao động) | E7: =E8+E9 -> 16 | F7: =(E8*F8+E9*F9)/E7 -> 18281.25 | G7: =G8+G9 -> 237.41883
B8: a | C8: LĐ định biên | D8: Giờ công/ca 8 | E8: 7 | G8: =E8*F8/E6 -> 0
B9: b | C9: LĐ thời vụ | D9: Giờ công/ca 8 | E9: 9 | F9: =260000/8 -> 32500 | G9: =E9*F9/E6 -> 237.41883
B10: c | C10: Tiền ăn giữa Ca | D10: Đồng/người/ngày công | E10: =E7 -> 16 | F10: =25000/8 -> 3125 | G10: =E10*F10/$E$6 -> 40.584416
B11: 2 | C11: Điện sản xuất | D11: Kw/1chuyền/1giờ hoạt động | E11: 40 | F11: =ROUND(2100*1.05,-1) -> 2210 | G11: =E11*F11/E6 -> 71.753247
B12: 3 | C12: Dao tách nhãn chai PET | D12: Tấn/Bộ | E12: =1/1700000*(('Cong suat'!$E$13+'Cong suat'!$E$21)/2) -> 0.00082352941 | F12: 165000000 | G12: =E12*F12/$E$6 -> 110.29412 | H12: Anh Quân chốt định mức băm: 1500 tấn chai PET-B0 | I12: Tăng Dm dao tách nhãn 1500 -> 1700
B13: 4 | C13: Dây đai | E13: =0.3*50% -> 0.15 | F13: 51000 | G13: =E13*F13/230 -> 33.26087 | H13: Chuyển Băm 80%, CP dây đai tái sử dụng lại được 2 lần
B14: 5 | C14: Bao jumbo
B15: 6 | C15: Hóa chất
B16: 7 | C16: Chi phí xử lý nhãn chai PET | D16: Kg | E16: =SUM('Cong suat'!E13,'Cong suat'!E27)/2*6.5% -> 91 | F16: 300 | G16: =E16*F16/$E$6 -> 22.159091
B17: 8 | C17: Dầu xe nâng | D17: Lít/giờ hoạt động | E17: =2.5*85% -> 2.125 | F17: 18000 | G17: =E17*F17/1100 -> 34.772727 | H17: Bình quân 1 h: 2.5 lít, hiệu suất sử dụng: 85%
B18: 9 | C18: Chi phí vận chuyển | D18: Chuyến/9 tấn | E18: 1 | F18: 3200000 | G18: =F18/9000 -> 355.55556
B20: II - ĐỊNH MỨC TIÊU HAO VẬT TƯ - BĂM VẢY PET
B21: STT | C21: Mục phí | D21: ĐVT | E21: ĐM 1 giờ | F21: Đơn giá | G21: Chi phí/1kg thành phẩm | H21: Diễn giải
C22: Công suất băm PET | E22: ='Cong suat'!$E$98 -> 1410
B23: 1 | C23: Chi phí nhân công trực tiếp
B24: a | C24: LĐ định biên | D24: Giờ công/ca 8 | E24: 3
B25: b | C25: LĐ thời vụ | D25: Giờ công/ca 8
B26: c | C26: Tiền ăn giữa Ca | D26: Đồng/người | E26: =E23 -> 0 | F26: =25000/8 -> 3125 | G26: =E26*F26/$E$22 -> 0
B27: 2 | C27: Điện sản xuất | D27: Kw/1chuyền/1giờ hoạt động | E27: 70 | F27: =ROUND(2100*1.05,-1) -> 2210 | G27: =E27*F27/$E$22 -> 109.71631
B28: 3 | C28: Dao băm vảy PET | E28: =1/200000*'Cong suat'!$E$96 -> 0.0075 | F28: 44000000 | G28: =E28*F28/$E$22 -> 234.04255 | H28: Công suất thiết kế: 200 tấn
B29: 4 | C29: Dây đai
B30: 5 | C30: Bao jumbo | E30: =E22/350*50% -> 2.0142857 | F30: 71000 | G30: =E30*F30/$E$22 -> 101.42857
B31: 6 | C31: Hóa chất
B32: 7 | C32: Chi phí xử lý bùn, nước thải | G32: =SUM(G33:G35) -> 120.42553 | H32: Xử lý: nhãn, bùn, nước thải, hóa chất xử lý hồ XLNT
B33: 7.1 | C33: Chi phí nước sản xuất | E33: 3 | F33: 11500 | G33: =E33*F33/$E$22 -> 24.468085
C34: Chi phí xử lý nước thải | E34: =E33*80% -> 2.4 | F34: 9500 | G34: =E34*F34/$E$22 -> 16.170213
C35: Chi phí xử lý bùn | E35: ='Cong suat'!D90*5% -> 75 | F35: 1500 | G35: =E35*F35/$E$22 -> 79.787234
B36: 8 | C36: Dầu xe nâng | E36: =2.5*60% -> 1.5 | F36: 18000 | G36: =E36*F36/1100 -> 24.545455 | H36: Bình quân 1 h: 2.5 lít, hiệu suất sử dụng: 60%
B37: 9 | C37: Chi phí vận chuyển | D37: Chuyến | E37: 10000 | F37: 3200000 | G37: =F37/E37 -> 320
B39: III - ĐỊNH MỨC TIÊU HAO VẬT TƯ - BĂM VẢY PET Tu chuyen HD
B40: STT | C40: Mục phí | D40: ĐVT | E40: Định mức | F40: Đơn giá | G40: Chi phí/1kg thành phẩm | H40: Diễn giải
C41: Công suất băm HD | E41: ='Cong suat'!K90 -> 1410
B42: 1 | C42: Chi phí nhân công trực tiếp | E42: 3 | F42: 50320
B43: a | C43: LĐ định biên | E43: 3 | F43: 50320 | G43: =E43*F43/$E$41 -> 107.06383
B44: b | C44: LĐ thời vụ
B45: c | C45: Tiền ăn giữa Ca | E45: 3 | F45: =25000/8 -> 3125 | G45: =E45*F45/$E$41 -> 6.6489362
B46: 2 | C46: Điện sản xuất | E46: =250*75% -> 187.5 | F46: =ROUND(2100*1.05,-1) -> 2210 | G46: =E46*F46/$E$41 -> 293.88298
B47: 3 | C47: Dao băm vảy HD | E47: =1/300000*'Cong suat'!D89 -> 0.005 | F47: 70000000 | G47: =E47*F47/$E$41 -> 248.22695
B48: 4 | C48: Dây đai
B49: 5 | C49: Bao jumbo | E49: =1/350*E41*50% -> 2.0142857 | F49: 75000 | G49: =E49*F49/$E$41 -> 107.14286
B50: 6 | C50: Hóa chất
B51: 7.1 | C51: Chi phí nước sản xuất | E51: 3 | F51: 11500 | G51: =E51*F51/$E$41 -> 24.468085
B52: 7 | C52: Chi phí xử lý nước thải, môi trường | E52: =E51*80% -> 2.4 | F52: 11500 | G52: =E52*F52/$E$41 -> 19.574468
C53: Chi phí xử lý bùn | E53: ='Cong suat'!D90*3% -> 45 | F53: 1500 | G53: =E53*F53/$E$41 -> 47.87234
B54: 8 | C54: Dầu xe nâng | E54: =2.5*60% -> 1.5 | F54: 18000 | G54: =E54*F54/1100 -> 24.545455
B55: 9 | C55: Chi phí vận chuyển | D55: Chuyến | E55: 10000 | F55: 3200000 | G55: =F55/E55 -> 320
H59: Ngày …
C60: Duyệt | D60: Xem xét | E60: Xem xét | G60: Xem xét | H60: Người lập
C61: GĐĐH DTR | D61: GĐTC DTR | E61: GĐ các trạm | G61: Trưởng Trạm | H61: Kế toán trưởng

Sheet Dinh bien_HCNS
B1: #VALUE!
B3: I - ĐINH BIÊN NHÂN SỰ - PET | R3: ĐVT: người
B4: STT | C4: Phòng ban | D4: Tài khoản | E4: KQKD 2025 | F4: T1 | G4: T2 | H4: T3 | I4: T4 | J4: T5 | K4: T6 | L4: T7 | M4: T8 | N4: T9 | O4: T10 | P4: T11 | Q4: T12 | R4: KH 2026
B5: 1 | C5: Ban giám đốc | D5: 642 | E5: =E6+E7 -> 2 | F5: =SUM(F6:F7) -> 2 | G5: =SUM(G6:G7) -> 2 | H5: =SUM(H6:H7) -> 2 | I5: =SUM(I6:I7) -> 2 | J5: =SUM(J6:J7) -> 2 | K5: =SUM(K6:K7) -> 2 | L5: =SUM(L6:L7) -> 2 | M5: =SUM(M6:M7) -> 2 | ... Q5: =SUM(Q6:Q7) -> 2 | R5: =R6+R7 -> 2
B6: 1.1 | C6: Giám đốc Trạm | E6: 1 | F6: 1 | G6: 1 | H6: 1 | I6: 1 | J6: 1 | K6: 1 | L6: 1 | M6: 1 | N6: 1 | O6: 1 | P6: 1 | Q6: 1 | R6: =Q6 -> 1
B7: 1.2 | C7: Trưởng trạm thu mua | E7: 1 | F7: 1 | G7: 1 | H7: 1 | I7: 1 | J7: 1 | K7: 1 | L7: 1 | M7: 1 | N7: 1 | O7: 1 | P7: 1 | Q7: 1 | R7: =Q7 -> 1
B8: 2 | C8: Phòng Hành chánh nhân sự | D8: 642 | E8: =E9+E11+E12+E13+E14+E15 -> 2 | F8: =SUM(F9:F15) -> 2 | G8: =SUM(G9:G15) -> 2 | H8: =SUM(H9:H15) -> 2 | I8: =SUM(I9:I15) -> 2 | J8: =SUM(J9:J15) -> 2 | K8: =SUM(K9:K15) -> 2 | L8: =SUM(L9:L15) -> 2 | M8: =SUM(M9:M15) -> 2 | ... R8: =SUM(R9:R15) -> 2
B9: 2.1 | C9: Trưởng phòng nhân sự | E9: 1 | F9: 1 | G9: 1 | H9: 1 | I9: 1 | J9: 1 | K9: 1 | L9: 1 | M9: 1 | N9: 1 | O9: 1 | P9: 1 | Q9: 1 | R9: =Q9 -> 1
B10: 2.1 | C10: Nhân viên hành chính | R10: =Q10 -> 0
B11: 2.2 | C11: Nhân viên nhân sự | R11: =Q11 -> 0
B12: 2.3 | C12: Tuyển dụng | R12: =Q12 -> 0
B13: 2.4 | C13: Nhân viên tạp vụ | E13: 1 | F13: 1 | G13: 1 | H13: 1 | I13: 1 | J13: 1 | K13: 1 | L13: 1 | M13: 1 | N13: 1 | O13: 1 | P13: 1 | Q13: 1 | R13: =Q13 -> 1
B14: 2.5 | C14: Bảo vệ | R14: =Q14 -> 0
B15: 2.6 | C15: Nhân viên chăm sóc cây xanh | R15: =Q15 -> 0
B16: 3 | C16: Phòng Kế toán | D16: 642 | E16: =SUM(E17:E20) -> 3 | F16: =SUM(F17:F20) -> 3 | G16: =SUM(G17:G20) -> 3 | H16: =SUM(H17:H20) -> 3 | I16: =SUM(I17:I20) -> 3 | J16: =SUM(J17:J20) -> 3 | K16: =SUM(K17:K20) -> 3 | L16: =SUM(L17:L20) -> 3 | ... R16: =SUM(R17:R20) -> 3
B17: 3.1 | C17: Kế toán trưởng | E17: 1 | F17: 1 | G17: 1 | H17: 1 | I17: 1 | J17: 1 | K17: 1 | L17: 1 | M17: 1 | N17: 1 | O17: 1 | P17: 1 | Q17: 1 | R17: =Q17 -> 1
B18: 3.2 | C18: Kế toán tổng hợp | E18: 1 | F18: 1 | G18: 1 | H18: 1 | I18: 1 | J18: 1 | K18: 1 | L18: 1 | M18: 1 | N18: 1 | O18: 1 | P18: 1 | Q18: 1 | R18: =Q18 -> 1
B19: 3.3 | C19: Kế toán kho | R19: =Q19 -> 0
B20: 3.4 | C20: Kế toán viên | E20: 1 | F20: 1 | G20: 1 | H20: 1 | I20: 1 | J20: 1 | K20: 1 | L20: 1 | M20: 1 | N20: 1 | O20: 1 | P20: 1 | Q20: 1 | R20: =Q20 -> 1
B21: 4 | C21: Phòng Mua hàng | D21: 642 | E21: =E22 -> 1 | F21: =F22 -> 1 | G21: =G22 -> 1 | H21: =H22 -> 1 | I21: =I22 -> 1 | J21: =J22 -> 1 | K21: =K22 -> 1 | L21: =L22 -> 1 | ... R21: =R22 -> 1
B22: 4.1 | C22: Nhân viên mua hàng | E22: 1 | F22: 1 | G22: 1 | H22: 1 | I22: 1 | J22: 1 | K22: 1 | L22: 1 | M22: 1 | N22: 1 | O22: 1 | P22: 1 | Q22: 1 | R22: =Q22 -> 1
B23: 5 | C23: Ban dự án XDCB | D23: 642 | E23: =E24 -> 0 | F23: =F24 -> 0 | G23: =G24 -> 0 | H23: =H24 -> 0 | I23: =I24 -> 0 | J23: =J24 -> 0 | K23: =K24 -> 0 | L23: =L24 -> 0 | ... Q23: =Q24 -> 0
B24: 5.1 | C24: Nhân viên
B25: 6 | C25: Phòng Quản Trị Hệ Thống | D25: 642 | E25: =E26 -> 0 | F25: =F26 -> 0 | G25: =G26 -> 0 | H25: =H26 -> 0 | I25: =I26 -> 0 | J25: =J26 -> 0 | K25: =K26 -> 0 | L25: =L26 -> 0 | ... Q25: =Q26 -> 0
B26: 6.1 | C26: Nhân viên quản trị hệ thống
B27: 7 | C27: Phòng 5S & an toàn | D27: 642 | E27: =SUM(E28:E30) -> 5 | F27: =SUM(F28:F30) -> 5 | G27: =SUM(G28:G30) -> 5 | H27: =SUM(H28:H30) -> 5 | I27: =SUM(I28:I30) -> 5 | J27: =SUM(J28:J30) -> 5 | K27: =SUM(K28:K30) -> 5 | L27: =SUM(L28:L30) -> 5 | ... R27: =SUM(R28:R30) -> 5
B28: 7.1 | C28: Nhân viên 5S & an toàn | E28: 1 | F28: 1 | G28: 1 | H28: 1 | I28: 1 | J28: 1 | K28: 1 | L28: 1 | M28: 1 | N28: 1 | O28: 1 | P28: 1 | Q28: 1 | R28: =Q28 -> 1
B29: 7.2 | C29: Nhân viên XLNT | E29: 3 | F29: 3 | G29: 3 | H29: 3 | I29: 3 | J29: 3 | K29: 3 | L29: 3 | M29: 3 | N29: 3 | O29: 3 | P29: 3 | Q29: 3 | R29: 3
B30: 7.3 | C30: Lao động thuê ngoài: 5S 2 xưởng | E30: 1 | F30: 1 | G30: 1 | H30: 1 | I30: 1 | J30: 1 | K30: 1 | L30: 1 | M30: 1 | N30: 1 | O30: 1 | P30: 1 | Q30: 1 | R30: 1
B31: 8 | C31: Phòng Cung ứng | D31: 642 | E31: =E32 -> 0 | F31: =F32 -> 0 | G31: =G32 -> 0 | H31: =H32 -> 0 | I31: =I32 -> 0 | J31: =J32 -> 0 | K31: =K32 -> 0 | L31: =L32 -> 0 | ... Q31: =Q32 -> 0 | R31: =Q31 -> 0
B32: 8.1 | C32: Nhân viên | R32: =Q32 -> 0
B33: 9 | C33: Phòng mua XNK | D33: 642 | E33: =E34 -> 0 | F33: =F34 -> 0 | G33: =G34 -> 0 | H33: =H34 -> 0 | I33: =I34 -> 0 | J33: =J34 -> 0 | K33: =K34 -> 0 | L33: =L34 -> 0 | ... Q33: =Q34 -> 0 | R33: =Q33 -> 0
B34: 9.1 | C34: Nhân viên mua hàng | R34: =Q34 -> 0
B35: 10 | C35: Tư Vấn Dịch Vụ | D35: 642 | E35: =E36 -> 0 | F35: =F36 -> 0 | G35: =G36 -> 0 | H35: =H36 -> 0 | I35: =I36 -> 0 | J35: =J36 -> 0 | K35: =K36 -> 0 | L35: =L36 -> 0 | ... Q35: =Q36 -> 0 | R35: =Q35 -> 0
B36: 10.1 | C36: Nhân viên | R36: =Q36 -> 0
B37: 11 | C37: Phòng Nghiên Cứu & Phát Triển | D37: 627 | E37: =E38 -> 0 | F37: =F38 -> 0 | G37: =G38 -> 0 | H37: =H38 -> 0 | I37: =I38 -> 0 | J37: =J38 -> 0 | K37: =K38 -> 0 | L37: =L38 -> 0 | ... Q37: =Q38 -> 0 | R37: =Q37 -> 0
B38: 11.1 | C38: Nhân viên | R38: =Q38 -> 0
B39: 12 | C39: Phòng Kiểm soát chất lượng | D39: 627 | E39: =E41+E42 -> 2 | F39: =SUM(F40:F42) -> 2 | G39: =SUM(G40:G42) -> 2 | H39: =SUM(H40:H42) -> 2 | I39: =SUM(I40:I42) -> 2 | J39: =SUM(J40:J42) -> 2 | K39: =SUM(K40:K42) -> 2 | L39: =SUM(L40:L42) -> 2 | M39: =SUM(M40:M42) -> 2 | ... R39: =SUM(R40:R42) -> 2
B40: 12.1 | C40: Tổ trưởng Kiểm soát chất lượng
B41: 12.2 | C41: Kiểm soát NVL | E41: 1 | F41: 1 | G41: 1 | H41: 1 | I41: 1 | J41: 1 | K41: 1 | L41: 1 | M41: 1 | N41: 1 | O41: 1 | P41: 1 | Q41: 1 | R41: 1
B42: 12.3 | C42: Kiểm soát thành phẩm | E42: 1 | F42: 1 | G42: 1 | H42: 1 | I42: 1 | J42: 1 | K42: 1 | L42: 1 | M42: 1 | N42: 1 | O42: 1 | P42: 1 | Q42: 1 | R42: 1
B43: 13 | C43: Phòng Kỹ thuật | D43: 627 | E43: =SUM(E44:E50) -> 6 | F43: =SUM(F44:F50) -> 6 | G43: =SUM(G44:G50) -> 6 | H43: =SUM(H44:H50) -> 6 | I43: =SUM(I44:I50) -> 6 | J43: =SUM(J44:J50) -> 6 | K43: =SUM(K44:K50) -> 6 | L43: =SUM(L44:L50) -> 6 | ... R43: =SUM(R44:R50) -> 6
B44: 13.1 | C44: Quản lý kỹ thuật | R44: =Q44 -> 0
B45: 13.2 | C45: Tổ trưởng vận hành máy | E45: 1 | F45: 1 | G45: 1 | H45: 1 | I45: 1 | J45: 1 | K45: 1 | L45: 1 | M45: 1 | N45: 1 | O45: 1 | P45: 1 | Q45: 1 | R45: 1
B46: 13.3 | C46: Tổ trưởng kỹ thuật nước và môi trường
B47: 13.3 | C47: Nhân viên vận hành máy | E47: 3 | F47: 3 | G47: 3 | H47: 3 | I47: 3 | J47: 3 | K47: 3 | L47: 3 | M47: 3 | N47: 3 | O47: 3 | P47: 3 | Q47: 3 | R47: 3
B48: 13.4 | C48: Nhân viên bảo trì | E48: 2 | F48: 2 | G48: 2 | H48: 2 | I48: 2 | J48: 2 | K48: 2 | L48: 2 | M48: 2 | N48: 2 | O48: 2 | P48: 2 | Q48: 2 | R48: 2
B49: 13.5 | C49: Nhân viên xử lý nước thải (24/24)
B50: 13.6 | C50: Nhân viên thống kê kỹ thuật | R50: =Q50 -> 0
B51: 14 | C51: Phòng Sản xuất | E51: =E52+E57+E63 -> 75 | F51: =F52+F57+F63 -> 66 | G51: =G52+G57+G63 -> 66 | H51: =H52+H57+H63 -> 66 | I51: =I52+I57+I63 -> 66 | J51: =J52+J57+J63 -> 66 | K51: =K52+K57+K63 -> 66 | L51: =L52+L57+L63 -> 66 | ... R51: =R52+R57+R63 -> 66
B52: 14.1 | C52: Bộ phận quản lý sản xuất | D52: 627 | E52: =E53+E54+E55+E56 -> 2 | F52: =SUM(F53:F56) -> 2 | G52: =SUM(G53:G56) -> 2 | H52: =SUM(H53:H56) -> 2 | I52: =SUM(I53:I56) -> 2 | J52: =SUM(J53:J56) -> 2 | K52: =SUM(K53:K56) -> 2 | L52: =SUM(L53:L56) -> 2 | M52: =SUM(M53:M56) -> 2 | ... R52: =SUM(R53:R56) -> 2
B53: 14.1.1 | C53: Trưởng phòng sản xuất | E53: 1 | F53: 1 | G53: 1 | H53: 1 | I53: 1 | J53: 1 | K53: 1 | L53: 1 | M53: 1 | N53: 1 | O53: 1 | P53: 1 | Q53: 1 | R53: =Q53 -> 1
B54: 14.1.2 | C54: Giám sát sản xuất | R54: =Q54 -> 0
B55: 14.1.3 | C55: Tổ trưởng sản xuất | R55: =Q55 -> 0
B56: 14.1.4 | C56: Nhân viên thống kê sản xuất | E56: 1 | F56: 1 | G56: 1 | H56: 1 | I56: 1 | J56: 1 | K56: 1 | L56: 1 | M56: 1 | N56: 1 | O56: 1 | P56: 1 | Q56: 1 | R56: =Q56 -> 1 | T56: Chi tiết phân bổ Công nhân trực tiếp SX
B57: 14.2 | C57: Công nhân trực tiếp sản xuất - Phân loại | D57: 622 | E57: =SUM(E58:E62) -> 70 | F57: =SUM(F58:F62) -> 58 | G57: =SUM(G58:G62) -> 58 | H57: =SUM(H58:H62) -> 58 | I57: =SUM(I58:I62) -> 58 | J57: =SUM(J58:J62) -> 58 | K57: =SUM(K58:K62) -> 58 | L57: =SUM(L58:L62) -> 58 | ... R57: =SUM(R58:R62) -> 58 | T57: Công nhân trực tiếp sản xuất - Phân loại
B58: 14.2.1 | C58: Nhân viên phân loại | E58: 16 | F58: =22-F64-F60-F61 -> 13 | G58: =22-G64-G60-G61 -> 13 | H58: =22-H64-H60-H61 -> 13 | I58: =22-I64-I60-I61 -> 13 | J58: =22-J64-J60-J61 -> 13 | K58: =22-K64-K60-K61 -> 13 | L58: =22-L64-L60-L61 -> 13 | M58: =22-M64-M60-M61 -> 13 | ... Q58: =22-Q64-Q60-Q61 -> 13 | R58: =Q58 -> 13 | T58: SX chai PET - Chuyền phân loại
B59: 14.2.2 | C59: Nhân viên sản xuất chung | T59: Công đoạn 1: Cấp liệu
B60: 14.2.3 | C60: Nhân viên ép kiện | E60: 2 | F60: 2 | G60: 2 | H60: 2 | I60: 2 | J60: 2 | K60: 2 | L60: 2 | M60: 2 | N60: 2 | O60: 2 | P60: 2 | Q60: 2 | R60: =Q60 -> 2 | T60: Công đoạn 2: Phân loại chai
B61: 14.2.4 | C61: Nhân viên lái xe nâng | E61: 1 | F61: 1 | G61: 1 | H61: 1 | I61: 1 | J61: 1 | K61: 1 | L61: 1 | M61: 1 | N61: 1 | O61: 1 | P61: 1 | Q61: 1 | R61: =Q61 -> 1 | T61: Công đoạn 3: Tách nhãn
B62: 14.2.4 | C62: Lao động thuê ngoài | E62: =54-E73-E30 -> 51 | F62: 42 | G62: 42 | H62: 42 | I62: 42 | J62: 42 | K62: 42 | L62: 42 | M62: 42 | N62: 42 | O62: 42 | P62: 42 | Q62: 42 | R62: 42 | T62: Công đoạn 4: Rework (B6.2+chai còn nhãn)
B63: 14.3 | C63: Công nhân trực tiếp sản xuất - Băm vảy PET | D63: 622 | E63: =E64+E67 -> 3 | F63: =F64+F67 -> 6 | G63: =G64+G67 -> 6 | H63: =H64+H67 -> 6 | I63: =I64+I67 -> 6 | J63: =J64+J67 -> 6 | K63: =K64+K67 -> 6 | L63: =L64+L67 -> 6 | ... Q63: =Q64+Q67 -> 6 | R63: =Q63 -> 6 | T63: Công đoạn 5: Ép kiện
B64: 14.3.1 | C64: Nhân viên băm vảy | E64: 3 | F64: 6 | G64: 6 | H64: 6 | I64: 6 | J64: 6 | K64: 6 | L64: 6 | M64: 6 | N64: 6 | O64: 6 | P64: 6 | Q64: 6 | R64: =Q64 -> 6 | T64: Sản xuất chung
B65: 14.3.2 | T65: Nhân viên lái xe nâng
B66: 14.3.3 | T66: Nhân viên kéo bao, bì tạp
B67: 14.3.4 | C67: Lao động thuê ngoài | T67: Nhân viên ghi số liệu
B68: 15 | C68: Phòng Kho vận | D68: 627 | E68: =SUM(E69:E73) -> 6 | F68: =SUM(F69:F73) -> 6 | G68: =SUM(G69:G73) -> 6 | H68: =SUM(H69:H73) -> 6 | I68: =SUM(I69:I73) -> 6 | J68: =SUM(J69:J73) -> 6 | K68: =SUM(K69:K73) -> 6 | L68: =SUM(L69:L73) -> 6 | ... R68: =SUM(R69:R73) -> 6 | T68: Xử lý phó sản
B69: 15.1 | C69: Thủ kho | E69: 1 | F69: 1 | G69: 1 | H69: 1 | I69: 1 | J69: 1 | K69: 1 | L69: 1 | M69: 1 | N69: 1 | O69: 1 | P69: 1 | Q69: 1 | R69: =Q69 -> 1 | T69: Nhân viên xử lý nắp, cổ chai,…
B70: 15.2 | C70: Tổ Trưởng Kho - Xuất nhập | R70: =Q70 -> 0
B71: 15.3 | C71: Nhân viên Nhập - Xuất hàng | E71: 1 | F71: 1 | G71: 1 | H71: 1 | I71: 1 | J71: 1 | K71: 1 | L71: 1 | M71: 1 | N71: 1 | O71: 1 | P71: 1 | Q71: 1 | R71: =Q71 -> 1
B72: 15.4 | C72: Nhân Viên Lái Xe Nâng | E72: 2 | F72: 2 | G72: 2 | H72: 2 | I72: 2 | J72: 2 | K72: 2 | L72: 2 | M72: 2 | N72: 2 | O72: 2 | P72: 2 | Q72: 2 | R72: =Q72 -> 2
B73: 15.5 | C73: Lao động thuê ngoài | E73: 2 | F73: 2 | G73: 2 | H73: 2 | I73: 2 | J73: 2 | K73: 2 | L73: 2 | M73: 2 | N73: 2 | O73: 2 | P73: 2 | Q73: 2 | R73: =Q73 -> 2
B74: 16 | C74: Trạm cấp 2 - Kiên Giang | D74: 642 | E74: =E75 -> 0 | F74: =F75 -> 0 | G74: =G75 -> 0 | H74: =H75 -> 0 | I74: =I75 -> 0 | J74: =J75 -> 0 | K74: =K75 -> 0 | L74: =L75 -> 0 | ... Q74: =Q75 -> 0
B75: 16.1 | C75: Nhân viên
B76: 17 | C76: Trạm cấp 2 - Cà Mau | D76: 642 | E76: =E77 -> 0 | F76: =F77 -> 0 | G76: =G77 -> 0 | H76: =H77 -> 0 | I76: =I77 -> 0 | J76: =J77 -> 0 | K76: =K77 -> 0 | L76: =L77 -> 0 | ... Q76: =Q77 -> 0
B77: 17.1 | C77: Nhân viên
B78: 18 | C78: Trạm cấp 2 - Gia Lai | D78: 642 | E78: =E79 -> 0 | F78: =F79 -> 0 | G78: =G79 -> 0 | H78: =H79 -> 0 | I78: =I79 -> 0 | J78: =J79 -> 0 | K78: =K79 -> 0 | L78: =L79 -> 0 | ... Q78: =Q79 -> 0
B79: 18.1 | C79: Nhân viên
C80: TỔNG NHÂN SỰ | E80: =E5+E8+E16+E21+E23+E25+E27+E31+E33+E35+E37+E39+E43+E51+E68+E74+E76+E78 -> 102 | F80: =F5+F8+F16+F21+F23+F25+F27+F31+F33+F35+F37+F39+F43+F51+F68+F74+F76+F78 -> 93 | G80: =G5+G8+G16+G21+G23+G25+G27+G31+G33+G35+G37+G39+G43+G51+G68+G74+G76+G78 -> 93 | H80: =H5+H8+H16+H21+H23+H25+H27+H31+H33+H35+H37+H39+H43+H51+H68+H74+H76+H78 -> 93 | I80: =I5+I8+I16+I21+I23+I25+I27+I31+I33+I35+I37+I39+I43+I51+I68+I74+I76+I78 -> 93 | J80: =J5+J8+J16+J21+J23+J25+J27+J31+J33+J35+J37+J39+J43+J51+J68+J74+J76+J78 -> 93 | K80: =K5+K8+K16+K21+K23+K25+K27+K31+K33+K35+K37+K39+K43+K51+K68+K74+K76+K78 -> 93 | L80: =L5+L8+L16+L21+L23+L25+L27+L31+L33+L35+L37+L39+L43+L51+L68+L74+L76+L78 -> 93 | ... R80: =R5+R8+R16+R21+R23+R25+R27+R31+R33+R35+R37+R39+R43+R51+R68+R74+R76+R78 -> 93
C81: Nhân sự thuộc ĐỊNH BIÊN | E81: =E80-E82 -> 48 | F81: =F80-F82 -> 48 | G81: =G80-G82 -> 48 | H81: =H80-H82 -> 48 | I81: =I80-I82 -> 48 | J81: =J80-J82 -> 48 | K81: =K80-K82 -> 48 | L81: =L80-L82 -> 48 | ... Q81: =Q80-Q82 -> 48 | R81: =Q81 -> 48
C82: Lao động thuê ngoài | E82: =E73+E67+E30+E62 -> 54 | F82: =F73+F67+F30+F62 -> 45 | G82: =G73+G67+G30+G62 -> 45 | H82: =H73+H67+H30+H62 -> 45 | I82: =I73+I67+I30+I62 -> 45 | J82: =J73+J67+J30+J62 -> 45 | K82: =K73+K67+K30+K62 -> 45 | L82: =L73+L67+L30+L62 -> 45 | ... R82: =R73+R67+R30+R62 -> 45
B84: II - ĐỊNH BIÊN - HD
B85: 19 | C85: XƯỞNG SẢN XUẤT | D85: =D4 -> Tài khoản | E85: =E4 -> KQKD 2025 | F85: =F4 -> T1 | G85: =G4 -> T2 | H85: =H4 -> T3 | I85: =I4 -> T4 | J85: =J4 -> T5 | K85: =K4 -> T6 | ... R85: =R4 -> KH 2026
B86: 19.1 | C86: Quản lý sản xuất | D86: 627
B87: 19.1.1 | C87: Trưởng ca sản xuất (theo ca sx)
B88: 19.2 | C88: Công nhân trực tiếp sản xuất | D88: 622
C89: TỔNG: | F89: =F87+F88 -> 0 | G89: =G87+G88 -> 0 | H89: =H87+H88 -> 0 | I89: =I87+I88 -> 0 | J89: =J87+J88 -> 0 | K89: =K87+K88 -> 0 | L89: =L87+L88 -> 0 | M89: =M87+M88 -> 0 | ... R89: =R87+R88 -> 0
F91: ='KQKD PET'!G5/'Dinh bien_HCNS'!F80/1000 -> 8.1798387 | G91: ='KQKD PET'!H5/'Dinh bien_HCNS'!G80/1000 -> 6.3620968 | H91: ='KQKD PET'!I5/'Dinh bien_HCNS'!H80/1000 -> 9.0887097 | I91: ='KQKD PET'!J5/'Dinh bien_HCNS'!I80/1000 -> 11.346774 | J91: ='KQKD PET'!K5/'Dinh bien_HCNS'!J80/1000 -> 11.346774 | K91: ='KQKD PET'!L5/'Dinh bien_HCNS'!K80/1000 -> 11.346774 | L91: ='KQKD PET'!M5/'Dinh bien_HCNS'!L80/1000 -> 11.346774 | M91: ='KQKD PET'!N5/'Dinh bien_HCNS'!M80/1000 -> 11.346774 | ... Q91: ='KQKD PET'!R5/'Dinh bien_HCNS'!Q80/1000 -> 4.5877419

Sheet LUONG
B3: BẢNG LƯƠNG TỪ HCNS - SẢN XUẤT PET | F3: 1 | G3: 2 | H3: 3 | I3: 4 | J3: 5 | K3: 6 | L3: 7 | M3: 8 | N3: 9 | O3: 10 | P3: 11 | Q3: 12
B4: Phòng ban | C4: Mã tài khoản (Mã Chi phí_L4) | D4: Tên tài khoản (Cost elements 2) | E4: Chi Phí_L5 (Cost Group 2) | F4: T1 | G4: T2 | H4: T3 | I4: T4 | J4: T5 | K4: T6 | L4: T7 | M4: T8 | N4: T9 | O4: T10 | P4: T11 | Q4: T12 | R4: Mục tiêu 2026
B5: Ban giám đốc | D5: Số lượng nhân sự | F5: ='[27]Dinh bien_HCNS'!F5 -> 2 | G5: ='[27]Dinh bien_HCNS'!G5 -> 2 | H5: ='[27]Dinh bien_HCNS'!H5 -> 2 | I5: ='[27]Dinh bien_HCNS'!I5 -> 2 | J5: ='[27]Dinh bien_HCNS'!J5 -> 2 | K5: ='[27]Dinh bien_HCNS'!K5 -> 2 | L5: ='[27]Dinh bien_HCNS'!L5 -> 2 | M5: ='[27]Dinh bien_HCNS'!M5 -> 2 | ... Q5: ='[27]Dinh bien_HCNS'!Q5 -> 2 | R5: 2
B6: Ban giám đốc | D6: ADM_Lương Khối Quản Lý | F6: =SUM(F8:F16) -> 122904333 | G6: =SUM(G8:G16) -> 124845948 | H6: =SUM(H8:H16) -> 117254102 | I6: =SUM(I8:I16) -> 125250948 | J6: =SUM(J8:J16) -> 120476718 | K6: =SUM(K8:K16) -> 125250948 | L6: =SUM(L8:L16) -> 122585333 | M6: =SUM(M8:M16) -> 122585333 | ... R6: =SUM(R8:R16) -> 1474398610
B7: Ban giám đốc | D7: Chi phí lương TB/1 Người | F7: =IFERROR(SUM(F8:F15)/F5,0) -> 61452166 | G7: =IFERROR(SUM(G8:G15)/G5,0) -> 62422974 | H7: =IFERROR(SUM(H8:H15)/H5,0) -> 58627051 | I7: =IFERROR(SUM(I8:I15)/I5,0) -> 62625474 | J7: =IFERROR(SUM(J8:J15)/J5,0) -> 60238359 | K7: =IFERROR(SUM(K8:K15)/K5,0) -> 62625474 | L7: =IFERROR(SUM(L8:L15)/L5,0) -> 61292666 | M7: =IFERROR(SUM(M8:M15)/M5,0) -> 61292666 | ... Q7: =IFERROR(SUM(Q8:Q15)/Q5,0) -> 61292666
B8: Ban giám đốc | C8: 6421002604 | D8: Chi phí lương chính - Gián tiếp | E8: Salary and Wages - Direct | F8: 87200000 | G8: 89784615 | H8: 82030769 | I8: 89784615 | J8: 84615385 | K8: 89784615 | L8: 87200000 | M8: 87200000 | N8: 89784615 | O8: 84615385 | P8: 89784615 | Q8: 87200000 | R8: =SUM(F8:Q8) -> 1048984614
B9: Ban giám đốc | C9: 6421002605 | D9: Chi phí lương T13, phép năm - Gián tiếp | E9: Salary and Wages - Support | F9: 6903333 | G9: 6903333 | H9: 6903333 | I9: 6903333 | J9: 6903333 | K9: 6903333 | L9: 6903333 | M9: 6903333 | N9: 6903333 | O9: 6903333 | P9: 6903333 | Q9: 6903333 | R9: =SUM(F9:Q9) -> 82839996
B10: Ban giám đốc | C10: 6421002802 | D10: Chi phí khen thưởng - Gián tiếp | E10: Employee Welfare | F10: 1500000 | G10: 1100000 | H10: 1100000 | I10: 1100000 | J10: 1900000 | K10: 1100000 | L10: 1100000 | M10: 1100000 | N10: 1500000 | O10: 1100000 | P10: 1100000 | Q10: 1100000 | R10: =SUM(F10:Q10) -> 14800000
B11: Ban giám đốc | C11: 6421002806 | D11: Thưởng danh hiệu | E11: Salary and Wages - Support | F11: 9374000 | G11: 9374000 | H11: 9374000 | I11: 9374000 | J11: 9374000 | K11: 9374000 | L11: 9374000 | M11: 9374000 | N11: 9374000 | O11: 9374000 | P11: 9374000 | Q11: 9374000 | R11: =SUM(F11:Q11) -> 112488000
B12: Ban giám đốc | C12: 6421007202 | D12: Chi phí khen thưởng, bồi dưỡng khác | E12: Employee Welfare | F12: 0 | G12: 0 | H12: 0 | I12: 0 | J12: 0 | K12: 0 | L12: 0 | M12: 0 | N12: 0 | O12: 0 | P12: 0 | Q12: 0 | R12: =SUM(F12:Q12) -> 0
B13: Ban giám đốc | C13: 6421003202 | D13: Tiền ăn giữa ca - Gián tiếp | E13: Employee Welfare | F13: 2025000 | G13: 1782000 | H13: 1944000 | I13: 2187000 | J13: 1782000 | K13: 2187000 | L13: 2106000 | M13: 2106000 | N13: 2025000 | O13: 2025000 | P13: 2187000 | Q13: 2106000 | R13: =SUM(F13:Q13) -> 24462000
B14: Ban giám đốc | C14: 6421002603 | D14: Phụ cấp ca đêm - Gián tiếp | E14: Salary and Wages - Support | F14: 0 | G14: 0 | H14: 0 | I14: 0 | J14: 0 | K14: 0 | L14: 0 | M14: 0 | N14: 0 | O14: 0 | P14: 0 | Q14: 0 | R14: =SUM(F14:Q14) -> 0
B15: Ban giám đốc | C15: 6421003401 | D15: BHXH, BHYT, KPCĐ, BHTN - Gián tiếp | E15: Employee Welfare | F15: 15902000 | G15: 15902000 | H15: 15902000 | I15: 15902000 | J15: 15902000 | K15: 15902000 | L15: 15902000 | M15: 15902000 | N15: 15902000 | O15: 15902000 | P15: 15902000 | Q15: 15902000 | R15: =SUM(F15:Q15) -> 190824000
B16: Ban giám đốc | C16: 6421002703 | D16: Chi phí lương ngoài giờ - Gián tiếp | E16: Salary and Wages - Support | F16: 0 | G16: 0 | H16: 0 | I16: 0 | J16: 0 | K16: 0 | L16: 0 | M16: 0 | N16: 0 | O16: 0 | P16: 0 | Q16: 0 | R16: =SUM(F16:Q16) -> 0
B17: Phòng Hành chánh nhân sự | D17: Số lượng nhân sự | F17: ='[27]Dinh bien_HCNS'!F8 -> 2 | G17: ='[27]Dinh bien_HCNS'!G8 -> 2 | H17: ='[27]Dinh bien_HCNS'!H8 -> 2 | I17: ='[27]Dinh bien_HCNS'!I8 -> 2 | J17: ='[27]Dinh bien_HCNS'!J8 -> 2 | K17: ='[27]Dinh bien_HCNS'!K8 -> 2 | L17: ='[27]Dinh bien_HCNS'!L8 -> 2 | M17: ='[27]Dinh bien_HCNS'!M8 -> 2 | ... Q17: ='[27]Dinh bien_HCNS'!Q8 -> 2 | R17: =Q17 -> 2
B18: Phòng Hành chánh nhân sự | D18: ADM_Lương Khối Quản Lý | F18: =SUM(F20:F28) -> 36609307 | G18: =SUM(G20:G28) -> 36976461 | H18: =SUM(H20:H28) -> 34282999 | I18: =SUM(I20:I28) -> 37256461 | J18: =SUM(J20:J28) -> 35906153 | K18: =SUM(K20:K28) -> 37256461 | L18: =SUM(L20:L28) -> 36265307 | M18: =SUM(M20:M28) -> 36265307 | ... R18: =SUM(R20:R28) -> 437158838
B19: Phòng Hành chánh nhân sự | D19: Chi phí lương TB/1 Người | F19: =IFERROR(SUM(F20:F27)/F17,0) -> 18304654 | G19: =IFERROR(SUM(G20:G27)/G17,0) -> 18488230 | H19: =IFERROR(SUM(H20:H27)/H17,0) -> 17141500 | I19: =IFERROR(SUM(I20:I27)/I17,0) -> 18628230 | J19: =IFERROR(SUM(J20:J27)/J17,0) -> 17953076 | K19: =IFERROR(SUM(K20:K27)/K17,0) -> 18628230 | L19: =IFERROR(SUM(L20:L27)/L17,0) -> 18132654 | M19: =IFERROR(SUM(M20:M27)/M17,0) -> 18132654 | ... Q19: =IFERROR(SUM(Q20:Q27)/Q17,0) -> 18132654
B20: Phòng Hành chánh nhân sự | C20: 6421002604 | D20: Chi phí lương chính - Gián tiếp | E20: Salary and Wages - Direct | F20: 24314000 | G20: 25249154 | H20: 22443692 | I20: 25249154 | J20: 23378846 | K20: 25249154 | L20: 24314000 | M20: 24314000 | N20: 25249154 | O20: 23378846 | P20: 25249154 | Q20: 24314000 | R20: =SUM(F20:Q20) -> 292703154
B21: Phòng Hành chánh nhân sự | C21: 6421002605 | D21: Chi phí lương T13, phép năm - Gián tiếp | E21: Salary and Wages - Support | F21: 1924859 | G21: 1924859 | H21: 1924859 | I21: 1924859 | J21: 1924859 | K21: 1924859 | L21: 1924859 | M21: 1924859 | N21: 1924859 | O21: 1924859 | P21: 1924859 | Q21: 1924859 | R21: =SUM(F21:Q21) -> 23098308
B22: Phòng Hành chánh nhân sự | C22: 6421002802 | D22: Chi phí khen thưởng - Gián tiếp | E22: Employee Welfare | F22: 1150000 | G22: 750000 | H22: 750000 | I22: 750000 | J22: 1550000 | K22: 750000 | L22: 750000 | M22: 750000 | N22: 1150000 | O22: 750000 | P22: 750000 | Q22: 750000 | R22: =SUM(F22:Q22) -> 10600000
B23: Phòng Hành chánh nhân sự | C23: 6421002806 | D23: Thưởng danh hiệu | E23: Salary and Wages - Support | F23: 2007924 | G23: 2007924 | H23: 2007924 | I23: 2007924 | J23: 2007924 | K23: 2007924 | L23: 2007924 | M23: 2007924 | N23: 2007924 | O23: 2007924 | P23: 2007924 | Q23: 2007924 | R23: =SUM(F23:Q23) -> 24095088
B24: Phòng Hành chánh nhân sự | C24: 6421007202 | D24: Chi phí khen thưởng, bồi dưỡng khác | E24: Employee Welfare | F24: 98734 | G24: 98734 | H24: 98734 | I24: 98734 | J24: 98734 | K24: 98734 | L24: 98734 | M24: 98734 | N24: 98734 | O24: 98734 | P24: 98734 | Q24: 98734 | R24: =SUM(F24:Q24) -> 1184808
B25: Phòng Hành chánh nhân sự | C25: 6421003202 | D25: Tiền ăn giữa ca - Gián tiếp | E25: Employee Welfare | F25: 1400000 | G25: 1232000 | H25: 1344000 | I25: 1512000 | J25: 1232000 | K25: 1512000 | L25: 1456000 | M25: 1456000 | N25: 1400000 | O25: 1400000 | P25: 1512000 | Q25: 1456000 | R25: =SUM(F25:Q25) -> 16912000
B26: Phòng Hành chánh nhân sự | C26: 6421002603 | D26: Phụ cấp ca đêm - Gián tiếp | E26: Salary and Wages - Support | F26: 0 | G26: 0 | H26: 0 | I26: 0 | J26: 0 | K26: 0 | L26: 0 | M26: 0 | N26: 0 | O26: 0 | P26: 0 | Q26: 0 | R26: =SUM(F26:Q26) -> 0
B27: Phòng Hành chánh nhân sự | C27: 6421003401 | D27: BHXH, BHYT, KPCĐ, BHTN - Gián tiếp | E27: Employee Welfare | F27: 5713790 | G27: 5713790 | H27: 5713790 | I27: 5713790 | J27: 5713790 | K27: 5713790 | L27: 5713790 | M27: 5713790 | N27: 5713790 | O27: 5713790 | P27: 5713790 | Q27: 5713790 | R27: =SUM(F27:Q27) -> 68565480
B28: Phòng Hành chánh nhân sự | C28: 6421002703 | D28: Chi phí lương ngoài giờ - Gián tiếp | E28: Salary and Wages - Support | F28: 0 | G28: 0 | H28: 0 | I28: 0 | J28: 0 | K28: 0 | L28: 0 | M28: 0 | N28: 0 | O28: 0 | P28: 0 | Q28: 0 | R28: =SUM(F28:Q28) -> 0
B29: Phòng Kế toán | D29: Số lượng nhân sự | F29: 3 | G29: ='[27]Dinh bien_HCNS'!F16 -> 3 | H29: ='[27]Dinh bien_HCNS'!G16 -> 3 | I29: ='[27]Dinh bien_HCNS'!H16 -> 3 | J29: ='[27]Dinh bien_HCNS'!I16 -> 3 | K29: ='[27]Dinh bien_HCNS'!J16 -> 3 | L29: ='[27]Dinh bien_HCNS'!K16 -> 3 | M29: ='[27]Dinh bien_HCNS'!L16 -> 3 | N29: ='[27]Dinh bien_HCNS'!M16 -> 3 | ... Q29: ='[27]Dinh bien_HCNS'!P16 -> 3 | R29: =Q29 -> 3
B30: Phòng Kế toán | D30: ADM_Lương Khối Quản Lý | F30: =SUM(F32:F40) -> 72145573 | G30: =SUM(G32:G40) -> 73172343 | H30: =SUM(H32:H40) -> 67704034 | I30: =SUM(I32:I40) -> 73592343 | J30: =SUM(J32:J40) -> 70614803 | K30: =SUM(K32:K40) -> 73592343 | L30: =SUM(L32:L40) -> 71629573 | M30: =SUM(M32:M40) -> 71629573 | ... R30: =SUM(R32:R40) -> 862993647
B31: Phòng Kế toán | D31: Chi phí lương TB/1 Người | F31: =IFERROR(SUM(F32:F39)/F29,0) -> 24048524 | G31: =IFERROR(SUM(G32:G39)/G29,0) -> 24390781 | H31: =IFERROR(SUM(H32:H39)/H29,0) -> 22568011 | I31: =IFERROR(SUM(I32:I39)/I29,0) -> 24530781 | J31: =IFERROR(SUM(J32:J39)/J29,0) -> 23538268 | K31: =IFERROR(SUM(K32:K39)/K29,0) -> 24530781 | L31: =IFERROR(SUM(L32:L39)/L29,0) -> 23876524 | M31: =IFERROR(SUM(M32:M39)/M29,0) -> 23876524 | ... Q31: =IFERROR(SUM(Q32:Q39)/Q29,0) -> 23876524
B32: Phòng Kế toán | C32: 6421002604 | D32: Chi phí lương chính - Gián tiếp | E32: Salary and Wages - Direct | F32: 48848000 | G32: 50726770 | H32: 45090461 | I32: 50726770 | J32: 46969230 | K32: 50726770 | L32: 48848000 | M32: 48848000 | N32: 50726770 | O32: 46969230 | P32: 50726770 | Q32: 48848000 | R32: =SUM(F32:Q32) -> 588054771
B33: Phòng Kế toán | C33: 6421002605 | D33: Chi phí lương T13, phép năm - Gián tiếp | E33: Salary and Wages - Support | F33: 3867133 | G33: 3867133 | H33: 3867133 | I33: 3867133 | J33: 3867133 | K33: 3867133 | L33: 3867133 | M33: 3867133 | N33: 3867133 | O33: 3867133 | P33: 3867133 | Q33: 3867133 | R33: =SUM(F33:Q33) -> 46405596
B34: Phòng Kế toán | C34: 6421002802 | D34: Chi phí khen thưởng - Gián tiếp | E34: Employee Welfare | F34: 600000 | G34: 0 | H34: 0 | I34: 0 | J34: 1200000 | K34: 0 | L34: 0 | M34: 0 | N34: 600000 | O34: 0 | P34: 0 | Q34: 0 | R34: =SUM(F34:Q34) -> 2400000
B35: Phòng Kế toán | C35: 6421002806 | D35: Thưởng danh hiệu | E35: Salary and Wages - Support | F35: 5251160 | G35: 5251160 | H35: 5251160 | I35: 5251160 | J35: 5251160 | K35: 5251160 | L35: 5251160 | M35: 5251160 | N35: 5251160 | O35: 5251160 | P35: 5251160 | Q35: 5251160 | R35: =SUM(F35:Q35) -> 63013920
B36: Phòng Kế toán | C36: 6421007202 | D36: Chi phí khen thưởng, bồi dưỡng khác | E36: Employee Welfare | F36: 0 | G36: 0 | H36: 0 | I36: 0 | J36: 0 | K36: 0 | L36: 0 | M36: 0 | N36: 0 | O36: 0 | P36: 0 | Q36: 0 | R36: =SUM(F36:Q36) -> 0
B37: Phòng Kế toán | C37: 6421003202 | D37: Tiền ăn giữa ca - Gián tiếp | E37: Employee Welfare | F37: 2100000 | G37: 1848000 | H37: 2016000 | I37: 2268000 | J37: 1848000 | K37: 2268000 | L37: 2184000 | M37: 2184000 | N37: 2100000 | O37: 2100000 | P37: 2268000 | Q37: 2184000 | R37: =SUM(F37:Q37) -> 25368000
B38: Phòng Kế toán | C38: 6421002603 | D38: Phụ cấp ca đêm - Gián tiếp | E38: Salary and Wages - Support | F38: 0 | G38: 0 | H38: 0 | I38: 0 | J38: 0 | K38: 0 | L38: 0 | M38: 0 | N38: 0 | O38: 0 | P38: 0 | Q38: 0 | R38: =SUM(F38:Q38) -> 0
B39: Phòng Kế toán | C39: 6421003401 | D39: BHXH, BHYT, KPCĐ, BHTN - Gián tiếp | E39: Employee Welfare | F39: 11479280 | G39: 11479280 | H39: 11479280 | I39: 11479280 | J39: 11479280 | K39: 11479280 | L39: 11479280 | M39: 11479280 | N39: 11479280 | O39: 11479280 | P39: 11479280 | Q39: 11479280 | R39: =SUM(F39:Q39) -> 137751360
B40: Phòng Kế toán | C40: 6421002703 | D40: Chi phí lương ngoài giờ - Gián tiếp | E40: Salary and Wages - Support | F40: 0 | G40: 0 | H40: 0 | I40: 0 | J40: 0 | K40: 0 | L40: 0 | M40: 0 | N40: 0 | O40: 0 | P40: 0 | Q40: 0 | R40: =SUM(F40:Q40) -> 0
B41: Phòng Mua hàng | D41: Số lượng nhân sự | F41: 1 | G41: ='[27]Dinh bien_HCNS'!F21 -> 1 | H41: ='[27]Dinh bien_HCNS'!G21 -> 1 | I41: ='[27]Dinh bien_HCNS'!H21 -> 1 | J41: ='[27]Dinh bien_HCNS'!I21 -> 1 | K41: ='[27]Dinh bien_HCNS'!J21 -> 1 | L41: ='[27]Dinh bien_HCNS'!K21 -> 1 | M41: ='[27]Dinh bien_HCNS'!L21 -> 1 | N41: ='[27]Dinh bien_HCNS'!M21 -> 1 | ... Q41: ='[27]Dinh bien_HCNS'!P21 -> 1 | R41: 1
B42: Phòng Mua hàng | D42: ADM_Lương Khối Quản Lý | F42: =SUM(F44:F52) -> 15462700 | G42: =SUM(G44:G52) -> 15545623 | H42: =SUM(H44:H52) -> 14500854 | I42: =SUM(I44:I52) -> 15685623 | J42: =SUM(J44:J52) -> 15211777 | K42: =SUM(K44:K52) -> 15685623 | L42: =SUM(L44:L52) -> 15290700 | M42: =SUM(M44:M52) -> 15290700 | ... R42: =SUM(R44:R52) -> 184375323
B43: Phòng Mua hàng | D43: Chi phí lương TB/1 Người | F43: =IFERROR(SUM(F44:F51)/F41,0) -> 15462700 | G43: =IFERROR(SUM(G44:G51)/G41,0) -> 15545623 | H43: =IFERROR(SUM(H44:H51)/H41,0) -> 14500854 | I43: =IFERROR(SUM(I44:I51)/I41,0) -> 15685623 | J43: =IFERROR(SUM(J44:J51)/J41,0) -> 15211777 | K43: =IFERROR(SUM(K44:K51)/K41,0) -> 15685623 | L43: =IFERROR(SUM(L44:L51)/L41,0) -> 15290700 | M43: =IFERROR(SUM(M44:M51)/M41,0) -> 15290700 | ... Q43: =IFERROR(SUM(Q44:Q51)/Q41,0) -> 15290700
B44: Phòng Mua hàng | C44: 6421002604 | D44: Chi phí lương chính - Gián tiếp | E44: Salary and Wages - Direct | F44: 9540000 | G44: 9906923 | H44: 8806154 | I44: 9906923 | J44: 9173077 | K44: 9906923 | L44: 9540000 | M44: 9540000 | N44: 9906923 | O44: 9173077 | P44: 9906923 | Q44: 9540000 | R44: =SUM(F44:Q44) -> 114846923
B45: Phòng Mua hàng | C45: 6421002605 | D45: Chi phí lương T13, phép năm - Gián tiếp | E45: Salary and Wages - Support | F45: 755250 | G45: 755250 | H45: 755250 | I45: 755250 | J45: 755250 | K45: 755250 | L45: 755250 | M45: 755250 | N45: 755250 | O45: 755250 | P45: 755250 | Q45: 755250 | R45: =SUM(F45:Q45) -> 9063000
B46: Phòng Mua hàng | C46: 6421002802 | D46: Chi phí khen thưởng - Gián tiếp | E46: Employee Welfare | F46: 1200000 | G46: 1000000 | H46: 1000000 | I46: 1000000 | J46: 1400000 | K46: 1000000 | L46: 1000000 | M46: 1000000 | N46: 1200000 | O46: 1000000 | P46: 1000000 | Q46: 1000000 | R46: =SUM(F46:Q46) -> 12800000
B47: Phòng Mua hàng | C47: 6421002806 | D47: Thưởng danh hiệu | E47: Salary and Wages - Support | F47: 1025550 | G47: 1025550 | H47: 1025550 | I47: 1025550 | J47: 1025550 | K47: 1025550 | L47: 1025550 | M47: 1025550 | N47: 1025550 | O47: 1025550 | P47: 1025550 | Q47: 1025550 | R47: =SUM(F47:Q47) -> 12306600
B48: Phòng Mua hàng | C48: 6421007202 | D48: Chi phí khen thưởng, bồi dưỡng khác | E48: Employee Welfare | F48: 0 | G48: 0 | H48: 0 | I48: 0 | J48: 0 | K48: 0 | L48: 0 | M48: 0 | N48: 0 | O48: 0 | P48: 0 | Q48: 0 | R48: =SUM(F48:Q48) -> 0
B49: Phòng Mua hàng | C49: 6421003202 | D49: Tiền ăn giữa ca - Gián tiếp | E49: Employee Welfare | F49: 700000 | G49: 616000 | H49: 672000 | I49: 756000 | J49: 616000 | K49: 756000 | L49: 728000 | M49: 728000 | N49: 700000 | O49: 700000 | P49: 756000 | Q49: 728000 | R49: =SUM(F49:Q49) -> 8456000
B50: Phòng Mua hàng | C50: 6421002603 | D50: Phụ cấp ca đêm - Gián tiếp | E50: Salary and Wages - Support | F50: 0 | G50: 0 | H50: 0 | I50: 0 | J50: 0 | K50: 0 | L50: 0 | M50: 0 | N50: 0 | O50: 0 | P50: 0 | Q50: 0 | R50: =SUM(F50:Q50) -> 0
B51: Phòng Mua hàng | C51: 6421003401 | D51: BHXH, BHYT, KPCĐ, BHTN - Gián tiếp | E51: Employee Welfare | F51: 2241900 | G51: 2241900 | H51: 2241900 | I51: 2241900 | J51: 2241900 | K51: 2241900 | L51: 2241900 | M51: 2241900 | N51: 2241900 | O51: 2241900 | P51: 2241900 | Q51: 2241900 | R51: =SUM(F51:Q51) -> 26902800
B52: Phòng Mua hàng | C52: 6421002703 | D52: Chi phí lương ngoài giờ - Gián tiếp | E52: Salary and Wages - Support | F52: 0 | G52: 0 | H52: 0 | I52: 0 | J52: 0 | K52: 0 | L52: 0 | M52: 0 | N52: 0 | O52: 0 | P52: 0 | Q52: 0 | R52: =SUM(F52:Q52) -> 0
B53: Ban dự án XDCB | D53: Số lượng nhân sự
B54: Ban dự án XDCB | D54: ADM_Lương Khối Quản Lý | F54: =SUM(F56:F63) -> 0 | G54: =SUM(G56:G63) -> 0 | H54: =SUM(H56:H63) -> 0 | I54: =SUM(I56:I63) -> 0 | J54: =SUM(J56:J63) -> 0 | K54: =SUM(K56:K63) -> 0 | L54: =SUM(L56:L63) -> 0 | M54: =SUM(M56:M63) -> 0 | ... Q54: =SUM(Q56:Q63) -> 0 | R54: =SUM(F54:Q54) -> 0
B55: Ban dự án XDCB | D55: Chi phí lương TB/1 Người | F55: =IFERROR(SUM(F56:F63)/F53,0) -> 0 | G55: =IFERROR(SUM(G56:G63)/G53,0) -> 0 | H55: =IFERROR(SUM(H56:H63)/H53,0) -> 0 | I55: =IFERROR(SUM(I56:I63)/I53,0) -> 0 | J55: =IFERROR(SUM(J56:J63)/J53,0) -> 0 | K55: =IFERROR(SUM(K56:K63)/K53,0) -> 0 | L55: =IFERROR(SUM(L56:L63)/L53,0) -> 0 | M55: =IFERROR(SUM(M56:M63)/M53,0) -> 0 | ... Q55: =IFERROR(SUM(Q56:Q63)/Q53,0) -> 0
B56: Ban dự án XDCB | C56: 6421002604 | D56: Chi phí lương chính - Gián tiếp | E56: Salary and Wages - Direct | R56: =SUM(F56:Q56) -> 0
B57: Ban dự án XDCB | C57: 6421002605 | D57: Chi phí lương T13, phép năm - Gián tiếp | E57: Salary and Wages - Support | R57: =SUM(F57:Q57) -> 0
B58: Ban dự án XDCB | C58: 6421002802 | D58: Chi phí khen thưởng - Gián tiếp | E58: Employee Welfare | R58: =SUM(F58:Q58) -> 0
B59: Ban dự án XDCB | C59: 6421002806 | D59: Thưởng danh hiệu | E59: Salary and Wages - Support | R59: =SUM(F59:Q59) -> 0
B60: Ban dự án XDCB | C60: 6421007202 | D60: Chi phí khen thưởng, bồi dưỡng khác | E60: Employee Welfare | R60: =SUM(F60:Q60) -> 0
B61: Ban dự án XDCB | C61: 6421003202 | D61: Tiền ăn giữa ca - Gián tiếp | E61: Employee Welfare | R61: =SUM(F61:Q61) -> 0
B62: Ban dự án XDCB | C62: 6421002603 | D62: Phụ cấp ca đêm - Gián tiếp | E62: Salary and Wages - Support | R62: =SUM(F62:Q62) -> 0
B63: Ban dự án XDCB | C63: 6421003401 | D63: BHXH, BHYT, KPCĐ, BHTN - Gián tiếp | E63: Employee Welfare | R63: =SUM(F63:Q63) -> 0
B64: Ban dự án XDCB | C64: 6421002703 | D64: Chi phí lương ngoài giờ - Gián tiếp | E64: Salary and Wages - Support | R64: =SUM(F64:Q64) -> 0
B65: Phòng Quản Trị Hệ Thống | D65: Số lượng nhân sự
B66: Phòng Quản Trị Hệ Thống | D66: ADM_Lương Khối Quản Lý | F66: =SUM(F68:F75) -> 0 | G66: =SUM(G68:G75) -> 0 | H66: =SUM(H68:H75) -> 0 | I66: =SUM(I68:I75) -> 0 | J66: =SUM(J68:J75) -> 0 | K66: =SUM(K68:K75) -> 0 | L66: =SUM(L68:L75) -> 0 | M66: =SUM(M68:M75) -> 0 | ... Q66: =SUM(Q68:Q75) -> 0 | R66: =SUM(F66:Q66) -> 0
B67: Phòng Quản Trị Hệ Thống | D67: Chi phí lương TB/1 Người | F67: =IFERROR(SUM(F68:F75)/F65,0) -> 0 | G67: =IFERROR(SUM(G68:G75)/G65,0) -> 0 | H67: =IFERROR(SUM(H68:H75)/H65,0) -> 0 | I67: =IFERROR(SUM(I68:I75)/I65,0) -> 0 | J67: =IFERROR(SUM(J68:J75)/J65,0) -> 0 | K67: =IFERROR(SUM(K68:K75)/K65,0) -> 0 | L67: =IFERROR(SUM(L68:L75)/L65,0) -> 0 | M67: =IFERROR(SUM(M68:M75)/M65,0) -> 0 | ... Q67: =IFERROR(SUM(Q68:Q75)/Q65,0) -> 0
B68: Phòng Quản Trị Hệ Thống | C68: 6421002604 | D68: Chi phí lương chính - Gián tiếp | E68: Salary and Wages - Direct | R68: =SUM(F68:Q68) -> 0
B69: Phòng Quản Trị Hệ Thống | C69: 6421002605 | D69: Chi phí lương T13, phép năm - Gián tiếp | E69: Salary and Wages - Support | R69: =SUM(F69:Q69) -> 0
B70: Phòng Quản Trị Hệ Thống | C70: 6421002802 | D70: Chi phí khen thưởng - Gián tiếp | E70: Employee Welfare | R70: =SUM(F70:Q70) -> 0
B71: Phòng Quản Trị Hệ Thống | C71: 6421002806 | D71: Thưởng danh hiệu | E71: Salary and Wages - Support | R71: =SUM(F71:Q71) -> 0
B72: Phòng Quản Trị Hệ Thống | C72: 6421007202 | D72: Chi phí khen thưởng, bồi dưỡng khác | E72: Employee Welfare | R72: =SUM(F72:Q72) -> 0
B73: Phòng Quản Trị Hệ Thống | C73: 6421003202 | D73: Tiền ăn giữa ca - Gián tiếp | E73: Employee Welfare | R73: =SUM(F73:Q73) -> 0
B74: Phòng Quản Trị Hệ Thống | C74: 6421002603 | D74: Phụ cấp ca đêm - Gián tiếp | E74: Salary and Wages - Support | R74: =SUM(F74:Q74) -> 0
B75: Phòng Quản Trị Hệ Thống | C75: 6421003401 | D75: BHXH, BHYT, KPCĐ, BHTN - Gián tiếp | E75: Employee Welfare | R75: =SUM(F75:Q75) -> 0
B76: Phòng Quản Trị Hệ Thống | C76: 6421002703 | D76: Chi phí lương ngoài giờ - Gián tiếp | E76: Salary and Wages - Support | R76: =SUM(F76:Q76) -> 0
B77: Phòng 5S & an toàn | D77: Số lượng nhân sự | F77: ='[27]Dinh bien_HCNS'!F27 -> 5 | G77: ='[27]Dinh bien_HCNS'!G27 -> 5 | H77: ='[27]Dinh bien_HCNS'!H27 -> 5 | I77: ='[27]Dinh bien_HCNS'!I27 -> 5 | J77: ='[27]Dinh bien_HCNS'!J27 -> 5 | K77: ='[27]Dinh bien_HCNS'!K27 -> 5 | L77: ='[27]Dinh bien_HCNS'!L27 -> 5 | M77: ='[27]Dinh bien_HCNS'!M27 -> 5 | ... Q77: ='[27]Dinh bien_HCNS'!Q27 -> 5
B78: Phòng 5S & an toàn | D78: ADM_Lương Khối Quản Lý | F78: =SUM(F80:F87) -> 70169394 | G78: =SUM(G80:G87) -> 66415548 | H78: =SUM(H80:H87) -> 66473086 | I78: =SUM(I80:I87) -> 70525548 | J78: =SUM(J80:J87) -> 68991240 | K78: =SUM(K80:K87) -> 70830548 | L78: =SUM(L80:L87) -> 69886394 | M78: =SUM(M80:M87) -> 69886394 | ... Q78: =SUM(Q80:Q87) -> 69581394 | R78: =SUM(F78:Q78) -> 832823882
B79: Phòng 5S & an toàn | D79: Chi phí lương TB/1 Người | F79: =IFERROR(SUM(F80:F87)/F77,0) -> 14033879 | G79: =IFERROR(SUM(G80:G87)/G77,0) -> 13283110 | H79: =IFERROR(SUM(H80:H87)/H77,0) -> 13294617 | I79: =IFERROR(SUM(I80:I87)/I77,0) -> 14105110 | J79: =IFERROR(SUM(J80:J87)/J77,0) -> 13798248 | K79: =IFERROR(SUM(K80:K87)/K77,0) -> 14166110 | L79: =IFERROR(SUM(L80:L87)/L77,0) -> 13977279 | M79: =IFERROR(SUM(M80:M87)/M77,0) -> 13977279 | ... Q79: =IFERROR(SUM(Q80:Q87)/Q77,0) -> 13916279
B80: Phòng 5S & an toàn | C80: 6421002604 | D80: Chi phí lương chính - Gián tiếp | E80: Salary and Wages - Direct | F80: 42176000 | G80: 40158154 | H80: 39491692 | I80: 42958154 | J80: 40833846 | K80: 43238154 | L80: 42456000 | M80: 42456000 | N80: 42678154 | O80: 41113846 | P80: 43518154 | Q80: 42176000 | R80: =SUM(F80:Q80) -> 503254154
B81: Phòng 5S & an toàn | C81: 6421002605 | D81: Chi phí lương T13, phép năm - Gián tiếp | E81: Salary and Wages - Support | F81: 2762601 | G81: 2762601 | H81: 2762601 | I81: 2762601 | J81: 2762601 | K81: 2762601 | L81: 2762601 | M81: 2762601 | N81: 2762601 | O81: 2762601 | P81: 2762601 | Q81: 2762601 | R81: =SUM(F81:Q81) -> 33151212
B82: Phòng 5S & an toàn | C82: 6421002802 | D82: Chi phí khen thưởng - Gián tiếp | E82: Employee Welfare | F82: 4975000 | G82: 4175000 | H82: 4175000 | I82: 4175000 | J82: 5775000 | K82: 4175000 | L82: 4175000 | M82: 4175000 | N82: 4975000 | O82: 4175000 | P82: 4175000 | Q82: 4175000 | R82: =SUM(F82:Q82) -> 53300000
B83: Phòng 5S & an toàn | C83: 6421002806 | D83: Thưởng danh hiệu | E83: Salary and Wages - Support | F83: 3751321 | G83: 3751321 | H83: 3751321 | I83: 3751321 | J83: 3751321 | K83: 3751321 | L83: 3751321 | M83: 3751321 | N83: 3751321 | O83: 3751321 | P83: 3751321 | Q83: 3751321 | R83: =SUM(F83:Q83) -> 45015852
B84: Phòng 5S & an toàn | C84: 6421007202 | D84: Chi phí khen thưởng, bồi dưỡng khác | E84: Employee Welfare | F84: 227212 | G84: 227212 | H84: 227212 | I84: 227212 | J84: 227212 | K84: 227212 | L84: 227212 | M84: 227212 | N84: 227212 | O84: 227212 | P84: 227212 | Q84: 227212 | R84: =SUM(F84:Q84) -> 2726544
B85: Phòng 5S & an toàn | C85: 6421003202 | D85: Tiền ăn giữa ca - Gián tiếp | E85: Employee Welfare | F85: 5950000 | G85: 5014000 | H85: 5738000 | I85: 6324000 | J85: 5314000 | K85: 6349000 | L85: 6187000 | M85: 6187000 | N85: 5875000 | O85: 5975000 | P85: 6374000 | Q85: 6162000 | R85: =SUM(F85:Q85) -> 71449000
B86: Phòng 5S & an toàn | C86: 6421002603 | D86: Phụ cấp ca đêm - Gián tiếp | E86: Salary and Wages - Support | F86: 2126700 | G86: 2126700 | H86: 2126700 | I86: 2126700 | J86: 2126700 | K86: 2126700 | L86: 2126700 | M86: 2126700 | N86: 2126700 | O86: 2126700 | P86: 2126700 | Q86: 2126700 | R86: =SUM(F86:Q86) -> 25520400
B87: Phòng 5S & an toàn | C87: 6421003401 | D87: BHXH, BHYT, KPCĐ, BHTN - Gián tiếp | E87: Employee Welfare | F87: 8200560 | G87: 8200560 | H87: 8200560 | I87: 8200560 | J87: 8200560 | K87: 8200560 | L87: 8200560 | M87: 8200560 | N87: 8200560 | O87: 8200560 | P87: 8200560 | Q87: 8200560 | R87: =SUM(F87:Q87) -> 98406720
B88: Phòng 5S & an toàn | C88: 6421002703 | D88: Chi phí lương ngoài giờ - Gián tiếp | E88: Salary and Wages - Support | F88: 7380923 | G88: 6408185 | H88: 7112677 | I88: 8085415 | J88: 6408185 | K88: 8085415 | L88: 7817169 | M88: 7817169 | N88: 7599045 | O88: 7380923 | P88: 8085415 | Q88: 7817169 | R88: =SUM(F88:Q88) -> 89997690
B89: Phòng Cung ứng | D89: Số lượng nhân sự
B90: Phòng Cung ứng | D90: ADM_Lương Khối Quản Lý | F90: =SUM(F92:F99) -> 0 | G90: =SUM(G92:G99) -> 0 | H90: =SUM(H92:H99) -> 0 | I90: =SUM(I92:I99) -> 0 | J90: =SUM(J92:J99) -> 0 | K90: =SUM(K92:K99) -> 0 | L90: =SUM(L92:L99) -> 0 | M90: =SUM(M92:M99) -> 0 | ... Q90: =SUM(Q92:Q99) -> 0 | R90: =SUM(F90:Q90) -> 0
B91: Phòng Cung ứng | D91: Chi phí lương TB/1 Người | F91: =IFERROR(SUM(F92:F99)/F89,0) -> 0 | G91: =IFERROR(SUM(G92:G99)/G89,0) -> 0 | H91: =IFERROR(SUM(H92:H99)/H89,0) -> 0 | I91: =IFERROR(SUM(I92:I99)/I89,0) -> 0 | J91: =IFERROR(SUM(J92:J99)/J89,0) -> 0 | K91: =IFERROR(SUM(K92:K99)/K89,0) -> 0 | L91: =IFERROR(SUM(L92:L99)/L89,0) -> 0 | M91: =IFERROR(SUM(M92:M99)/M89,0) -> 0 | ... Q91: =IFERROR(SUM(Q92:Q99)/Q89,0) -> 0
B92: Phòng Cung ứng | C92: 6421002604 | D92: Chi phí lương chính - Gián tiếp | E92: Salary and Wages - Direct | R92: =SUM(F92:Q92) -> 0
B93: Phòng Cung ứng | C93: 6421002605 | D93: Chi phí lương T13, phép năm - Gián tiếp | E93: Salary and Wages - Support | R93: =SUM(F93:Q93) -> 0
B94: Phòng Cung ứng | C94: 6421002802 | D94: Chi phí khen thưởng - Gián tiếp | E94: Employee Welfare | R94: =SUM(F94:Q94) -> 0
B95: Phòng Cung ứng | C95: 6421002806 | D95: Thưởng danh hiệu | E95: Salary and Wages - Support | R95: =SUM(F95:Q95) -> 0
B96: Phòng Cung ứng | C96: 6421007202 | D96: Chi phí khen thưởng, bồi dưỡng khác | E96: Employee Welfare | R96: =SUM(F96:Q96) -> 0
B97: Phòng Cung ứng | C97: 6421003202 | D97: Tiền ăn giữa ca - Gián tiếp | E97: Employee Welfare | R97: =SUM(F97:Q97) -> 0
B98: Phòng Cung ứng | C98: 6421002603 | D98: Phụ cấp ca đêm - Gián tiếp | E98: Salary and Wages - Support | R98: =SUM(F98:Q98) -> 0
B99: Phòng Cung ứng | C99: 6421003401 | D99: BHXH, BHYT, KPCĐ, BHTN - Gián tiếp | E99: Employee Welfare | R99: =SUM(F99:Q99) -> 0
B100: Phòng Cung ứng | C100: 6421002703 | D100: Chi phí lương ngoài giờ - Gián tiếp | E100: Salary and Wages - Support | R100: =SUM(F100:Q100) -> 0
B101: Phòng mua XNK | D101: Số lượng nhân sự
B102: Phòng mua XNK | D102: ADM_Lương Khối Quản Lý | F102: =SUM(F104:F111) -> 0 | G102: =SUM(G104:G111) -> 0 | H102: =SUM(H104:H111) -> 0 | I102: =SUM(I104:I111) -> 0 | J102: =SUM(J104:J111) -> 0 | K102: =SUM(K104:K111) -> 0 | L102: =SUM(L104:L111) -> 0 | M102: =SUM(M104:M111) -> 0 | ... Q102: =SUM(Q104:Q111) -> 0 | R102: =SUM(F102:Q102) -> 0
...

Sheet 4.Doanh thu
B3: DOANH THU
B4: I - DOANH THU CHAI PET
B5: 1. Sản lượng bán chai | T5: 1 | U5: 2 | V5: 3 | W5: 4 | X5: 5 | Y5: 6 | Z5: 7 | AA5: 8 | AB5: 9 | AC5: 10 | AD5: 11 | AE5: 12
B6: STT | C6: Thành phẩm (chai sau phân loại) | D6: ĐVT | E6: Tỷ lệ | F6: T1 | G6: T2 | H6: T3 | I6: T4 | J6: T5 | K6: T6 | L6: T7 | M6: T8 | N6: T9 | O6: T10 | P6: T11 | Q6: T12 | R6: KH 2026 | T6: T1 | U6: T2 | V6: T3 | W6: T4 | X6: T5 | Y6: T6 | Z6: T7 | AA6: T8 | AB6: T9 | AC6: T10 | AD6: T11 | AE6: T12 | AF6: KQKD 2025 | AH6: KQKD 2024 | AJ6: KQKD 2023 | AL6: +/- 2026 sv 2025 | AM6: +/- %
B7: 1 | C7: Chai PET B1 | D7: Tấn | F7: ='3.Thanh pham'!F82 -> 465750 | G7: ='3.Thanh pham'!G82 -> 362250 | H7: ='3.Thanh pham'!H82 -> 517500 | I7: ='3.Thanh pham'!I82 -> 645000 | J7: ='3.Thanh pham'!J82 -> 645000 | K7: ='3.Thanh pham'!K82 -> 645000 | L7: ='3.Thanh pham'!L82 -> 645000 | M7: ='3.Thanh pham'!M82 -> 645000 | ... Q7: ='3.Thanh pham'!Q82 -> 0 | R7: =SUM(F7:Q7) -> 5215500 | T7: 95215 | U7: 258158 | V7: 538935 | W7: 507551 | X7: 557652 | Y7: 233713 | AC7: 713747 | AD7: 299880 | AE7: 352996 | AF7: =SUM(T7:AE7) -> 3557847 | AL7: =IFERROR(R7-AF7,0) -> 1657653 | AM7: =IFERROR((R7/AF7)-1,0) -> 0.46591464
B8: 2 | C8: Chai PET B1 Không Phân Loại | D8: Tấn | F8: ='3.Thanh pham'!F83 -> 0 | G8: ='3.Thanh pham'!G83 -> 0 | H8: ='3.Thanh pham'!H83 -> 0 | I8: ='3.Thanh pham'!I83 -> 0 | J8: ='3.Thanh pham'!J83 -> 0 | K8: ='3.Thanh pham'!K83 -> 0 | L8: ='3.Thanh pham'!L83 -> 0 | M8: ='3.Thanh pham'!M83 -> 0 | ... Q8: ='3.Thanh pham'!Q83 -> 0 | R8: =SUM(F8:Q8) -> 0 | Y8: 482670 | Z8: 900335 | AA8: 847972 | AB8: 780422 | AF8: =SUM(T8:AE8) -> 3011399 | AL8: =IFERROR(R8-AF8,0) -> -3011399 | AM8: =IFERROR((R8/AF8)-1,0) -> -1
B9: 3 | C9: Chai PET B1.3 | D9: Tấn | F9: ='3.Thanh pham'!F84 -> 0 | G9: ='3.Thanh pham'!G84 -> 0 | H9: ='3.Thanh pham'!H84 -> 0 | I9: ='3.Thanh pham'!I84 -> 0 | J9: ='3.Thanh pham'!J84 -> 0 | K9: ='3.Thanh pham'!K84 -> 0 | L9: ='3.Thanh pham'!L84 -> 0 | M9: ='3.Thanh pham'!M84 -> 0 | ... Q9: ='3.Thanh pham'!Q84 -> 0 | R9: =SUM(F9:Q9) -> 0 | X9: 80328 | Y9: 49992 | AF9: =SUM(T9:AE9) -> 130320 | AL9: =IFERROR(R9-AF9,0) -> -130320 | AM9: =IFERROR((R9/AF9)-1,0) -> -1
B10: 4 | C10: Chai PET B2.1 | D10: Tấn | F10: ='3.Thanh pham'!F85 -> 0 | G10: ='3.Thanh pham'!G85 -> 0 | H10: ='3.Thanh pham'!H85 -> 0 | I10: ='3.Thanh pham'!I85 -> 0 | J10: ='3.Thanh pham'!J85 -> 0 | K10: ='3.Thanh pham'!K85 -> 0 | L10: ='3.Thanh pham'!L85 -> 0 | M10: ='3.Thanh pham'!M85 -> 0 | ... Q10: ='3.Thanh pham'!Q85 -> 0 | R10: =SUM(F10:Q10) -> 0 | AF10: =SUM(T10:AE10) -> 0 | AL10: =IFERROR(R10-AF10,0) -> 0 | AM10: =IFERROR((R10/AF10)-1,0) -> 0
B11: 5 | C11: Chai PET B2.2 | D11: Tấn | F11: ='3.Thanh pham'!F86 -> 18000 | G11: ='3.Thanh pham'!G86 -> 14000 | H11: ='3.Thanh pham'!H86 -> 20000 | I11: ='3.Thanh pham'!I86 -> 25000 | J11: ='3.Thanh pham'!J86 -> 25000 | K11: ='3.Thanh pham'!K86 -> 25000 | L11: ='3.Thanh pham'!L86 -> 25000 | M11: ='3.Thanh pham'!M86 -> 25000 | ... Q11: ='3.Thanh pham'!Q86 -> 26000 | R11: =SUM(F11:Q11) -> 280000 | T11: 5203 | U11: 5344 | V11: 11596 | W11: 7094 | X11: 8782 | Y11: 8738 | Z11: 18437 | AD11: 5017 | AE11: 13267 | AF11: =SUM(T11:AE11) -> 83478 | AL11: =IFERROR(R11-AF11,0) -> 196522 | AM11: =IFERROR((R11/AF11)-1,0) -> 2.3541771
B12: 6 | C12: Chai PET B3 | D12: Tấn | F12: ='3.Thanh pham'!F87 -> 0 | G12: ='3.Thanh pham'!G87 -> 0 | H12: ='3.Thanh pham'!H87 -> 0 | I12: ='3.Thanh pham'!I87 -> 0 | J12: ='3.Thanh pham'!J87 -> 0 | K12: ='3.Thanh pham'!K87 -> 0 | L12: ='3.Thanh pham'!L87 -> 0 | M12: ='3.Thanh pham'!M87 -> 0 | ... Q12: ='3.Thanh pham'!Q87 -> 0 | R12: =SUM(F12:Q12) -> 0 | AF12: =SUM(T12:AE12) -> 0 | AL12: =IFERROR(R12-AF12,0) -> 0 | AM12: =IFERROR((R12/AF12)-1,0) -> 0
B13: 7 | C13: Chai PET B4 | D13: Tấn | F13: ='3.Thanh pham'!F88 -> 11250 | G13: ='3.Thanh pham'!G88 -> 8750 | H13: ='3.Thanh pham'!H88 -> 12500 | I13: ='3.Thanh pham'!I88 -> 15000 | J13: ='3.Thanh pham'!J88 -> 15000 | K13: ='3.Thanh pham'!K88 -> 15000 | L13: ='3.Thanh pham'!L88 -> 15000 | M13: ='3.Thanh pham'!M88 -> 15000 | ... Q13: ='3.Thanh pham'!Q88 -> 15600 | R13: =SUM(F13:Q13) -> 169300 | T13: 2549 | U13: 5479 | V13: 7960 | W13: 8266 | X13: 12120 | Y13: 12690 | Z13: 18437 | AA13: 16543 | AB13: 17306 | AC13: 20804 | AD13: 10513 | AE13: 10784 | AF13: =SUM(T13:AE13) -> 143451 | AL13: =IFERROR(R13-AF13,0) -> 25849 | AM13: =IFERROR((R13/AF13)-1,0) -> 0.18019393
B14: 8 | C14: Chai PET B5 | D14: Tấn | F14: ='3.Thanh pham'!F89 -> 15750 | G14: ='3.Thanh pham'!G89 -> 12250 | H14: ='3.Thanh pham'!H89 -> 17500 | I14: ='3.Thanh pham'!I89 -> 22500 | J14: ='3.Thanh pham'!J89 -> 22500 | K14: ='3.Thanh pham'!K89 -> 22500 | L14: ='3.Thanh pham'!L89 -> 22500 | M14: ='3.Thanh pham'!M89 -> 22500 | ... Q14: ='3.Thanh pham'!Q89 -> 23400 | R14: =SUM(F14:Q14) -> 250700 | T14: 3705 | U14: 4465 | V14: 6777 | W14: 7726 | X14: 7663 | Y14: 10724 | Z14: 22576 | AA14: 18134 | AB14: 16133 | AC14: 18930 | AD14: 7740 | AE14: 11341 | AF14: =SUM(T14:AE14) -> 135914 | AL14: =IFERROR(R14-AF14,0) -> 114786 | AM14: =IFERROR((R14/AF14)-1,0) -> 0.84454876
B15: 9 | C15: Chai PET B6.1 | D15: Tấn | F15: ='3.Thanh pham'!F90 -> 0 | G15: ='3.Thanh pham'!G90 -> 0 | H15: ='3.Thanh pham'!H90 -> 0 | I15: ='3.Thanh pham'!I90 -> 0 | J15: ='3.Thanh pham'!J90 -> 0 | K15: ='3.Thanh pham'!K90 -> 0 | L15: ='3.Thanh pham'!L90 -> 0 | M15: ='3.Thanh pham'!M90 -> 0 | ... Q15: ='3.Thanh pham'!Q90 -> 0 | R15: =SUM(F15:Q15) -> 0 | AC15: 0 | AD15: 0 | AE15: 0 | AF15: =SUM(T15:AE15) -> 0 | AL15: =IFERROR(R15-AF15,0) -> 0 | AM15: =IFERROR((R15/AF15)-1,0) -> 0
B16: 10 | C16: Chai PET B6.2 | D16: Tấn | F16: ='3.Thanh pham'!F91 -> 0 | G16: ='3.Thanh pham'!G91 -> 0 | H16: ='3.Thanh pham'!H91 -> 0 | I16: ='3.Thanh pham'!I91 -> 0 | J16: ='3.Thanh pham'!J91 -> 0 | K16: ='3.Thanh pham'!K91 -> 0 | L16: ='3.Thanh pham'!L91 -> 0 | M16: ='3.Thanh pham'!M91 -> 0 | ... Q16: ='3.Thanh pham'!Q91 -> 0 | R16: =SUM(F16:Q16) -> 0 | U16: 81842 | V16: 200774 | W16: 77058 | X16: 77833 | Y16: 103518 | Z16: 31459 | AA16: 21348 | AC16: 0 | AD16: 21008 | AE16: 0 | AF16: =SUM(T16:AE16) -> 614840 | AL16: =IFERROR(R16-AF16,0) -> -614840 | AM16: =IFERROR((R16/AF16)-1,0) -> -1
B17: 11 | C17: Chai PET B7.1 | D17: Tấn | F17: ='3.Thanh pham'!F92 -> 0 | G17: ='3.Thanh pham'!G92 -> 0 | H17: ='3.Thanh pham'!H92 -> 0 | I17: ='3.Thanh pham'!I92 -> 0 | J17: ='3.Thanh pham'!J92 -> 0 | K17: ='3.Thanh pham'!K92 -> 0 | L17: ='3.Thanh pham'!L92 -> 0 | M17: ='3.Thanh pham'!M92 -> 0 | ... Q17: ='3.Thanh pham'!Q92 -> 0 | R17: =SUM(F17:Q17) -> 0 | W17: 461 | X17: 215 | Z17: 299 | AB17: 3363 | AF17: =SUM(T17:AE17) -> 4338 | AL17: =IFERROR(R17-AF17,0) -> -4338 | AM17: =IFERROR((R17/AF17)-1,0) -> -1
B18: 12 | C18: Chai PET B7.2 | D18: Tấn | F18: ='3.Thanh pham'!F93 -> 0 | G18: ='3.Thanh pham'!G93 -> 0 | H18: ='3.Thanh pham'!H93 -> 0 | I18: ='3.Thanh pham'!I93 -> 0 | J18: ='3.Thanh pham'!J93 -> 0 | K18: ='3.Thanh pham'!K93 -> 0 | L18: ='3.Thanh pham'!L93 -> 0 | M18: ='3.Thanh pham'!M93 -> 0 | ... Q18: ='3.Thanh pham'!Q93 -> 0 | R18: =SUM(F18:Q18) -> 0 | W18: 955 | Z18: 5008 | AA18: 5111 | AB18: 2684 | AC18: 4628 | AF18: =SUM(T18:AE18) -> 18386 | AL18: =IFERROR(R18-AF18,0) -> -18386 | AM18: =IFERROR((R18/AF18)-1,0) -> -1
B19: 13 | C19: Cổ Chai PET | D19: Tấn | F19: ='3.Thanh pham'!F94 -> 0 | G19: ='3.Thanh pham'!G94 -> 0 | H19: ='3.Thanh pham'!H94 -> 0 | I19: ='3.Thanh pham'!I94 -> 0 | J19: ='3.Thanh pham'!J94 -> 0 | K19: ='3.Thanh pham'!K94 -> 0 | L19: ='3.Thanh pham'!L94 -> 0 | M19: ='3.Thanh pham'!M94 -> 0 | ... Q19: ='3.Thanh pham'!Q94 -> 0 | R19: =SUM(F19:Q19) -> 0 | X19: 5230 | AB19: 7608 | AC19: 15188 | AD19: 5469 | AE19: 5320 | AF19: =SUM(T19:AE19) -> 38815 | AL19: =IFERROR(R19-AF19,0) -> -38815 | AM19: =IFERROR((R19/AF19)-1,0) -> -1
B20: 14 | C20: Nắp HD ép các màu | D20: Tấn | F20: ='3.Thanh pham'!F95 -> 9000 | G20: ='3.Thanh pham'!G95 -> 7000 | H20: ='3.Thanh pham'!H95 -> 10000 | I20: ='3.Thanh pham'!I95 -> 12500 | J20: ='3.Thanh pham'!J95 -> 12500 | K20: ='3.Thanh pham'!K95 -> 12500 | L20: ='3.Thanh pham'!L95 -> 12500 | M20: ='3.Thanh pham'!M95 -> 12500 | ... Q20: ='3.Thanh pham'!Q95 -> 13000 | R20: =SUM(F20:Q20) -> 140000 | V20: 31930 | W20: 30806 | X20: 18818 | Y20: 25900 | Z20: 2980 | AA20: 8367 | AE20: 3660 | AF20: =SUM(T20:AE20) -> 122461 | AL20: =IFERROR(R20-AF20,0) -> 17539 | AM20: =IFERROR((R20/AF20)-1,0) -> 0.14322111
B21: 15 | C21: Khác | D21: Tấn | F21: ='3.Thanh pham'!F96 -> 0 | G21: ='3.Thanh pham'!G96 -> 0 | H21: ='3.Thanh pham'!H96 -> 0 | I21: ='3.Thanh pham'!I96 -> 0 | J21: ='3.Thanh pham'!J96 -> 0 | K21: ='3.Thanh pham'!K96 -> 0 | L21: ='3.Thanh pham'!L96 -> 0 | M21: ='3.Thanh pham'!M96 -> 0 | ... Q21: ='3.Thanh pham'!Q96 -> 0 | R21: =SUM(F21:Q21) -> 0 | W21: 22137 | AF21: =SUM(T21:AE21) -> 22137 | AL21: =IFERROR(R21-AF21,0) -> -22137 | AM21: =IFERROR((R21/AF21)-1,0) -> -1
C22: TỔNG: | E22: =SUM(E7:E21) -> 0 | F22: =SUM(F7:F21) -> 519750 | G22: =SUM(G7:G21) -> 404250 | H22: =SUM(H7:H21) -> 577500 | I22: =SUM(I7:I21) -> 720000 | J22: =SUM(J7:J21) -> 720000 | K22: =SUM(K7:K21) -> 720000 | L22: =SUM(L7:L21) -> 720000 | ... Q22: =SUM(Q7:Q21) -> 78000 | R22: =SUM(F22:Q22) -> 6055500 | T22: =SUM(T7:T21) -> 106672 | U22: =SUM(U7:U21) -> 355288 | V22: =SUM(V7:V21) -> 797972 | W22: =SUM(W7:W21) -> 662054 | X22: =SUM(X7:X21) -> 768641 | Y22: =SUM(Y7:Y21) -> 927945 | Z22: =SUM(Z7:Z21) -> 999531 | AA22: =SUM(AA7:AA21) -> 917475 | ... AE22: =SUM(AE7:AE21) -> 397368 | AF22: =SUM(T22:AE22) -> 7883386 | AH22: =SUM(V22:AG22) -> 15304812 | AJ22: =SUM(X22:AI22) -> 29149598 | AL22: =IFERROR(R22-AF22,0) -> -1827886 | AM22: =IFERROR((R22/AF22)-1,0) -> -0.2318656
B24: 2. Giá bán chai
B25: STT | C25: Thành phẩm (chai sau phân loại) | D25: ĐVT | E25: Tỷ lệ | F25: T1 | G25: T2 | H25: T3 | I25: T4 | J25: T5 | K25: T6 | L25: T7 | M25: T8 | N25: T9 | O25: T10 | P25: T11 | Q25: T12 | R25: KH 2026 | T25: T1 | U25: T2 | V25: T3 | W25: T4 | X25: T5 | Y25: T6 | Z25: T7 | AA25: T8 | AB25: T9 | AC25: T10 | AD25: T11 | AE25: T12 | AF25: KQKD 2025 | AH25: KQKD 2024 | AJ25: KQKD 2023 | AL25: +/- 2026 sv 2025 | AM25: +/- % | AO25: Nhóm chai PET | AP25: Thành phần chai PET sau phân loại | AQ25: Đơn giá PET-B0 | AR25: Hao hụt | AT25: GAP (đảm bảo chi phí và lợi nhuận) | AU25: Đơn giá bán theo công thức
B26: 1 | C26: Chai PET B1 | D26: Đồng/kg | F26: =$AU$27 -> 15000 | G26: =$AU$27 -> 15000 | H26: =$AU$27 -> 15000 | I26: =$AU$27 -> 15000 | J26: =$AU$27 -> 15000 | K26: =$AU$27 -> 15000 | L26: =$AU$27 -> 15000 | M26: =$AU$27 -> 15000 | ... Q26: =$AU$27 -> 15000 | R26: =AVERAGE(F26:Q26) -> 15000 | T26: =IFERROR(T45/T7,0) -> 17866.084 | U26: =IFERROR(U45/U7,0) -> 18501.01 | V26: =IFERROR(V45/V7,0) -> 18423.973 | W26: =IFERROR(W45/W7,0) -> 19181.215 | X26: =IFERROR(X45/X7,0) -> 19067.207 | Y26: =IFERROR(Y45/Y7,0) -> 19078.717 | Z26: =IFERROR(Z45/Z7,0) -> 0 | AA26: =IFERROR(AA45/AA7,0) -> 0 | ... AF26: =IFERROR(AF45/AF7,0) -> 17351.288 | AL26: =IFERROR(R26-AF26,0) -> -2351.2877 | AM26: =IFERROR((R26/AF26)-1,0) -> -0.13551085 | AR26: Tỷ lệ | AS26: Quy ra tiền
B27: 2 | C27: Chai PET B1 Không Phân Loại | D27: Đồng/kg | F27: =$AU$27 -> 15000 | G27: =$AU$27 -> 15000 | H27: =$AU$27 -> 15000 | I27: =$AU$27 -> 15000 | J27: =$AU$27 -> 15000 | K27: =$AU$27 -> 15000 | L27: =$AU$27 -> 15000 | M27: =$AU$27 -> 15000 | ... Q27: =$AU$27 -> 15000 | R27: =AVERAGE(F27:Q27) -> 15000 | T27: =IFERROR(T46/T8,0) -> 0 | U27: =IFERROR(U46/U8,0) -> 0 | V27: =IFERROR(V46/V8,0) -> 0 | W27: =IFERROR(W46/W8,0) -> 0 | X27: =IFERROR(X46/X8,0) -> 0 | Y27: =IFERROR(Y46/Y8,0) -> 19180.665 | Z27: =IFERROR(Z46/Z8,0) -> 19335.797 | AA27: =IFERROR(AA46/AA8,0) -> 19225.39 | ... AF27: =IFERROR(AF46/AF8,0) -> 18580.933 | AL27: =IFERROR(R27-AF27,0) -> -3580.9331 | AM27: =IFERROR((R27/AF27)-1,0) -> -0.19272084 | AO27: Chai PET nhóm 1 | AP27: B1.1 + B1.2 + B1.3 + B2.1 + B3 | AQ27: ='1.NVL Chai'!H25 -> 10000 | AR27: =14% -> 0.14 | AS27: =AQ27*AR27 -> 1400 | AT27: =3500+100 -> 3600 | AU27: =ROUND(AQ27+AS27+AT27,-2) -> 15000
B28: 3 | C28: Chai PET B1.3 | D28: Đồng/kg | F28: =$AU$27 -> 15000 | G28: =$AU$27 -> 15000 | H28: =$AU$27 -> 15000 | I28: =$AU$27 -> 15000 | J28: =$AU$27 -> 15000 | K28: =$AU$27 -> 15000 | L28: =$AU$27 -> 15000 | M28: =$AU$27 -> 15000 | ... Q28: =$AU$27 -> 15000 | R28: =AVERAGE(F28:Q28) -> 15000 | T28: =IFERROR(T47/T9,0) -> 0 | U28: =IFERROR(U47/U9,0) -> 0 | V28: =IFERROR(V47/V9,0) -> 0 | W28: =IFERROR(W47/W9,0) -> 0 | X28: =IFERROR(X47/X9,0) -> 18529.069 | Y28: =IFERROR(Y47/Y9,0) -> 19016.201 | Z28: =IFERROR(Z47/Z9,0) -> 0 | AA28: =IFERROR(AA47/AA9,0) -> 0 | ... AF28: =IFERROR(AF47/AF9,0) -> 18715.938 | AL28: =IFERROR(R28-AF28,0) -> -3715.9375 | AM28: =IFERROR((R28/AF28)-1,0) -> -0.19854402 | AO28: Chai PET nhóm 2 | AP28: B4 + B5 | AQ28: =$AQ$27 -> 10000 | AR28: =14% -> 0.14 | AS28: =AQ28*AR28 -> 1400 | AT28: =500+100 -> 600 | AU28: =ROUND(AQ28+AS28+AT28,-2) -> 12000
B29: 4 | C29: Chai PET B2.1 | D29: Đồng/kg | F29: =$AU$27 -> 15000 | G29: =$AU$27 -> 15000 | H29: =$AU$27 -> 15000 | I29: =$AU$27 -> 15000 | J29: =$AU$27 -> 15000 | K29: =$AU$27 -> 15000 | L29: =$AU$27 -> 15000 | M29: =$AU$27 -> 15000 | ... Q29: =$AU$27 -> 15000 | R29: =AVERAGE(F29:Q29) -> 15000 | T29: =IFERROR(T48/T10,0) -> 0 | U29: =IFERROR(U48/U10,0) -> 0 | V29: =IFERROR(V48/V10,0) -> 0 | W29: =IFERROR(W48/W10,0) -> 0 | X29: =IFERROR(X48/X10,0) -> 0 | Y29: =IFERROR(Y48/Y10,0) -> 0 | Z29: =IFERROR(Z48/Z10,0) -> 0 | AA29: =IFERROR(AA48/AA10,0) -> 0 | ... AF29: =IFERROR(AF48/AF10,0) -> 0 | AL29: =IFERROR(R29-AF29,0) -> 15000 | AM29: =IFERROR((R29/AF29)-1,0) -> 0 | AO29: Chai PET nhóm 3 | AP29: B2.2 + B6.1 + B6.2 | AQ29: =$AQ$27 -> 10000 | AR29: =14% -> 0.14 | AS29: =AQ29*AR29 -> 1400 | AT29: =2000+100 -> 2100 | AU29: =ROUND(AQ29+AS29+AT29,-2) -> 13500
B30: 5 | C30: Chai PET B2.2 | D30: Đồng/kg | F30: =$AU$29 -> 13500 | G30: =$AU$29 -> 13500 | H30: =$AU$29 -> 13500 | I30: =$AU$29 -> 13500 | J30: =$AU$29 -> 13500 | K30: =$AU$29 -> 13500 | L30: =$AU$29 -> 13500 | M30: =$AU$29 -> 13500 | ... Q30: =$AU$29 -> 13500 | R30: =AVERAGE(F30:Q30) -> 13500 | T30: =IFERROR(T49/T11,0) -> 15739.156 | U30: =IFERROR(U49/U11,0) -> 17522 | V30: =IFERROR(V49/V11,0) -> 17637.022 | W30: =IFERROR(W49/W11,0) -> 18745.521 | X30: =IFERROR(X49/X11,0) -> 18633.722 | Y30: =IFERROR(Y49/Y11,0) -> 18892.799 | Z30: =IFERROR(Z49/Z11,0) -> 5861.324 | AA30: =IFERROR(AA49/AA11,0) -> 0 | ... AF30: =IFERROR(AF49/AF11,0) -> 14334.961 | AL30: =IFERROR(R30-AF30,0) -> -834.96116 | AM30: =IFERROR((R30/AF30)-1,0) -> -0.058246489 | AO30: Chai PET nhóm 4 | AP30: Nắp HD ép, cổ chai, PP (Quai) | AQ30: =$AQ$27 -> 10000 | AR30: =14% -> 0.14 | AS30: =AQ30*AR30 -> 1400 | AT30: =-4000+500+200 -> -3300 | AU30: =ROUND(AQ30+AS30+AT30,-2) -> 8100
B31: 6 | C31: Chai PET B3 | D31: Đồng/kg | F31: =$AU$27 -> 15000 | G31: =$AU$27 -> 15000 | H31: =$AU$27 -> 15000 | I31: =$AU$27 -> 15000 | J31: =$AU$27 -> 15000 | K31: =$AU$27 -> 15000 | L31: =$AU$27 -> 15000 | M31: =$AU$27 -> 15000 | ... Q31: =$AU$27 -> 15000 | R31: =AVERAGE(F31:Q31) -> 15000 | T31: =IFERROR(T50/T12,0) -> 0 | U31: =IFERROR(U50/U12,0) -> 0 | V31: =IFERROR(V50/V12,0) -> 0 | W31: =IFERROR(W50/W12,0) -> 0 | X31: =IFERROR(X50/X12,0) -> 0 | Y31: =IFERROR(Y50/Y12,0) -> 0 | Z31: =IFERROR(Z50/Z12,0) -> 0 | AA31: =IFERROR(AA50/AA12,0) -> 0 | ... AF31: =IFERROR(AF50/AF12,0) -> 0 | AL31: =IFERROR(R31-AF31,0) -> 15000 | AM31: =IFERROR((R31/AF31)-1,0) -> 0
B32: 7 | C32: Chai PET B4 | D32: Đồng/kg | F32: =$AU$28 -> 12000 | G32: =$AU$28 -> 12000 | H32: =$AU$28 -> 12000 | I32: =$AU$28 -> 12000 | J32: =$AU$28 -> 12000 | K32: =$AU$28 -> 12000 | L32: =$AU$28 -> 12000 | M32: =$AU$28 -> 12000 | ... Q32: =$AU$28 -> 12000 | R32: =AVERAGE(F32:Q32) -> 12000 | T32: =IFERROR(T51/T13,0) -> 14300 | U32: =IFERROR(U51/U13,0) -> 17522 | V32: =IFERROR(V51/V13,0) -> 17637.432 | W32: =IFERROR(W51/W13,0) -> 18713.885 | X32: =IFERROR(X51/X13,0) -> 18576.481 | Y32: =IFERROR(Y51/Y13,0) -> 18944.708 | Z32: =IFERROR(Z51/Z13,0) -> 19310.69 | AA32: =IFERROR(AA51/AA13,0) -> 19323.388 | ... AF32: =IFERROR(AF51/AF13,0) -> 16294.043 | AL32: =IFERROR(R32-AF32,0) -> -4294.0432 | AM32: =IFERROR((R32/AF32)-1,0) -> -0.26353454
B33: 8 | C33: Chai PET B5 | D33: Đồng/kg | F33: =$AU$28 -> 12000 | G33: =$AU$28 -> 12000 | H33: =$AU$28 -> 12000 | I33: =$AU$28 -> 12000 | J33: =$AU$28 -> 12000 | K33: =$AU$28 -> 12000 | L33: =$AU$28 -> 12000 | M33: =$AU$28 -> 12000 | ... Q33: =$AU$28 -> 12000 | R33: =AVERAGE(F33:Q33) -> 12000 | T33: =IFERROR(T52/T14,0) -> 15616.628 | U33: =IFERROR(U52/U14,0) -> 17522 | V33: =IFERROR(V52/V14,0) -> 17649.541 | W33: =IFERROR(W52/W14,0) -> 18455.821 | X33: =IFERROR(X52/X14,0) -> 18603.148 | Y33: =IFERROR(Y52/Y14,0) -> 18874.172 | Z33: =IFERROR(Z52/Z14,0) -> 19288.23 | AA33: =IFERROR(AA52/AA14,0) -> 18665.068 | ... AF33: =IFERROR(AF52/AF14,0) -> 16314.509 | AL33: =IFERROR(R33-AF33,0) -> -4314.509 | AM33: =IFERROR((R33/AF33)-1,0) -> -0.2644584
B34: 9 | C34: Chai PET B6.1 | D34: Đồng/kg | F34: =$AU$29 -> 13500 | G34: =$AU$29 -> 13500 | H34: =$AU$29 -> 13500 | I34: =$AU$29 -> 13500 | J34: =$AU$29 -> 13500 | K34: =$AU$29 -> 13500 | L34: =$AU$29 -> 13500 | M34: =$AU$29 -> 13500 | ... Q34: =$AU$29 -> 13500 | R34: =AVERAGE(F34:Q34) -> 13500 | T34: =IFERROR(T53/T15,0) -> 0 | U34: =IFERROR(U53/U15,0) -> 0 | V34: =IFERROR(V53/V15,0) -> 0 | W34: =IFERROR(W53/W15,0) -> 0 | X34: =IFERROR(X53/X15,0) -> 0 | Y34: =IFERROR(Y53/Y15,0) -> 0 | Z34: =IFERROR(Z53/Z15,0) -> 0 | AA34: =IFERROR(AA53/AA15,0) -> 0 | ... AF34: =IFERROR(AF53/AF15,0) -> 0 | AL34: =IFERROR(R34-AF34,0) -> 13500 | AM34: =IFERROR((R34/AF34)-1,0) -> 0
B35: 10 | C35: Chai PET B6.2 | D35: Đồng/kg | F35: =$AU$29 -> 13500 | G35: =$AU$29 -> 13500 | H35: =$AU$29 -> 13500 | I35: =$AU$29 -> 13500 | J35: =$AU$29 -> 13500 | K35: =$AU$29 -> 13500 | L35: =$AU$29 -> 13500 | M35: =$AU$29 -> 13500 | ... Q35: =$AU$29 -> 13500 | R35: =AVERAGE(F35:Q35) -> 13500 | T35: =IFERROR(T54/T16,0) -> 0 | U35: =IFERROR(U54/U16,0) -> 18235.568 | V35: =IFERROR(V54/V16,0) -> 0 | W35: =IFERROR(W54/W16,0) -> 19425.512 | X35: =IFERROR(X54/X16,0) -> 19460 | Y35: =IFERROR(Y54/Y16,0) -> 19193.273 | Z35: =IFERROR(Z54/Z16,0) -> 19363.428 | AA35: =IFERROR(AA54/AA16,0) -> 19479.381 | ... AF35: =IFERROR(AF54/AF16,0) -> 12676.756 | AL35: =IFERROR(R35-AF35,0) -> 823.24388 | AM35: =IFERROR((R35/AF35)-1,0) -> 0.06494121
B36: 11 | C36: Chai PET B7.1 | D36: Đồng/kg | F36: =$AU$28 -> 12000 | G36: =$AU$28 -> 12000 | H36: =$AU$28 -> 12000 | I36: =$AU$28 -> 12000 | J36: =$AU$28 -> 12000 | K36: =$AU$28 -> 12000 | L36: =$AU$28 -> 12000 | M36: =$AU$28 -> 12000 | ... Q36: =$AU$28 -> 12000 | R36: =AVERAGE(F36:Q36) -> 12000 | T36: =IFERROR(T55/T17,0) -> 0 | U36: =IFERROR(U55/U17,0) -> 0 | V36: =IFERROR(V55/V17,0) -> 0 | W36: =IFERROR(W55/W17,0) -> 8000 | X36: =IFERROR(X55/X17,0) -> 8000 | Y36: =IFERROR(Y55/Y17,0) -> 0 | Z36: =IFERROR(Z55/Z17,0) -> 0 | AA36: =IFERROR(AA55/AA17,0) -> 0 | ... AF36: =IFERROR(AF55/AF17,0) -> 7448.5938 | AL36: =IFERROR(R36-AF36,0) -> 4551.4062 | AM36: =IFERROR((R36/AF36)-1,0) -> 0.61104234
B37: 12 | C37: Chai PET B7.2 | D37: Đồng/kg | F37: =$AU$28 -> 12000 | G37: =$AU$28 -> 12000 | H37: =$AU$28 -> 12000 | I37: =$AU$28 -> 12000 | J37: =$AU$28 -> 12000 | K37: =$AU$28 -> 12000 | L37: =$AU$28 -> 12000 | M37: =$AU$28 -> 12000 | ... Q37: =$AU$28 -> 12000 | R37: =AVERAGE(F37:Q37) -> 12000 | T37: =IFERROR(T56/T18,0) -> 0 | U37: =IFERROR(U56/U18,0) -> 0 | V37: =IFERROR(V56/V18,0) -> 0 | W37: =IFERROR(W56/W18,0) -> 8000 | X37: =IFERROR(X56/X18,0) -> 0 | Y37: =IFERROR(Y56/Y18,0) -> 0 | Z37: =IFERROR(Z56/Z18,0) -> 477.63578 | AA37: =IFERROR(AA56/AA18,0) -> 0 | ... AF37: =IFERROR(AF56/AF18,0) -> 2811.0519 | AL37: =IFERROR(R37-AF37,0) -> 9188.9481 | AM37: =IFERROR((R37/AF37)-1,0) -> 3.2688646
B38: 13 | C38: Cổ Chai PET | D38: Đồng/kg | F38: =$AU$30 -> 8100 | G38: =$AU$30 -> 8100 | H38: =$AU$30 -> 8100 | I38: =$AU$30 -> 8100 | J38: =$AU$30 -> 8100 | K38: =$AU$30 -> 8100 | L38: =$AU$30 -> 8100 | M38: =$AU$30 -> 8100 | ... Q38: =$AU$30 -> 8100 | R38: =AVERAGE(F38:Q38) -> 8100 | T38: =IFERROR(T57/T19,0) -> 0 | U38: =IFERROR(U57/U19,0) -> 0 | V38: =IFERROR(V57/V19,0) -> 0 | W38: =IFERROR(W57/W19,0) -> 0 | X38: =IFERROR(X57/X19,0) -> 10000 | Y38: =IFERROR(Y57/Y19,0) -> 0 | Z38: =IFERROR(Z57/Z19,0) -> 0 | AA38: =IFERROR(AA57/AA19,0) -> 0 | ... AF38: =IFERROR(AF57/AF19,0) -> 8336.3262 | AL38: =IFERROR(R38-AF38,0) -> -236.32616 | AM38: =IFERROR((R38/AF38)-1,0) -> -0.028348958
B39: 14 | C39: Nắp HD ép các màu | D39: Đồng/kg | F39: =$AU$30 -> 8100 | G39: =$AU$30 -> 8100 | H39: =$AU$30 -> 8100 | I39: =$AU$30 -> 8100 | J39: =$AU$30 -> 8100 | K39: =$AU$30 -> 8100 | L39: =$AU$30 -> 8100 | M39: =$AU$30 -> 8100 | ... Q39: =$AU$30 -> 8100 | R39: =AVERAGE(F39:Q39) -> 8100 | T39: =IFERROR(T58/T20,0) -> 0 | U39: =IFERROR(U58/U20,0) -> 0 | V39: =IFERROR(V58/V20,0) -> 10000 | W39: =IFERROR(W58/W20,0) -> 10000 | X39: =IFERROR(X58/X20,0) -> 10000 | Y39: =IFERROR(Y58/Y20,0) -> 10000 | Z39: =IFERROR(Z58/Z20,0) -> 10000 | AA39: =IFERROR(AA58/AA20,0) -> 10000 | ... AF39: =IFERROR(AF58/AF20,0) -> 10330.277 | AL39: =IFERROR(R39-AF39,0) -> -2230.2766 | AM39: =IFERROR((R39/AF39)-1,0) -> -0.21589708
B40: 15 | C40: Khác | D40: Đồng/kg | F40: =$AU$30 -> 8100 | G40: =$AU$30 -> 8100 | H40: =$AU$30 -> 8100 | I40: =$AU$30 -> 8100 | J40: =$AU$30 -> 8100 | K40: =$AU$30 -> 8100 | L40: =$AU$30 -> 8100 | M40: =$AU$30 -> 8100 | ... Q40: =$AU$30 -> 8100 | R40: =AVERAGE(F40:Q40) -> 8100 | T40: =IFERROR(T59/T21,0) -> 0 | U40: =IFERROR(U59/U21,0) -> 0 | V40: =IFERROR(V59/V21,0) -> 0 | W40: =IFERROR(W59/W21,0) -> 2037 | X40: =IFERROR(X59/X21,0) -> 0 | Y40: =IFERROR(Y59/Y21,0) -> 0 | Z40: =IFERROR(Z59/Z21,0) -> 0 | AA40: =IFERROR(AA59/AA21,0) -> 0 | ... AF40: =IFERROR(AF59/AF21,0) -> 44493.528 | AL40: =IFERROR(R40-AF40,0) -> -36393.528 | AM40: =IFERROR((R40/AF40)-1,0) -> -0.81795105
C41: Giá bán Trung bình | F41: =F60/F22 -> 14672.727 | G41: =G60/G22 -> 14672.727 | H41: =H60/H22 -> 14672.727 | I41: =I60/I22 -> 14671.875 | J41: =J60/J22 -> 14671.875 | K41: =K60/K22 -> 14671.875 | L41: =L60/L22 -> 14671.875 | M41: =M60/M22 -> 14671.875 | ... Q41: =Q60/Q22 -> 11850 | R41: =AVERAGE(F41:Q41) -> 13966.619 | AL41: =IFERROR(R41-AF41,0) -> 13966.619 | AM41: =IFERROR((R41/AF41)-1,0) -> 0
B43: 3. Doanh thu chai
B44: STT | C44: Thành phẩm (chai sau phân loại) | D44: ĐVT | E44: Tỷ lệ | F44: T1 | G44: T2 | H44: T3 | I44: T4 | J44: T5 | K44: T6 | L44: T7 | M44: T8 | N44: T9 | O44: T10 | P44: T11 | Q44: T12 | R44: KH 2026 | T44: T1 | U44: T2 | V44: T3 | W44: T4 | X44: T5 | Y44: T6 | Z44: T7 | AA44: T8 | AB44: T9 | AC44: T10 | AD44: T11 | AE44: T12 | AF44: KQKD 2025 | AH44: KQKD 2024 | AJ44: KQKD 2023 | AL44: +/- 2026 sv 2025 | AM44: +/- %
B45: 1 | C45: Chai PET B1 | D45: Triệu đ | F45: =F7*F26 -> 6986250000 | G45: =G7*G26 -> 5433750000 | H45: =H7*H26 -> 7762500000 | I45: =I7*I26 -> 9675000000 | J45: =J7*J26 -> 9675000000 | K45: =K7*K26 -> 9675000000 | L45: =L7*L26 -> 9675000000 | M45: =M7*M26 -> 9675000000 | ... Q45: =Q7*Q26 -> 0 | R45: =SUM(F45:Q45) -> 78232500000 | T45: =1694108524+7010684 -> 1701119208 | U45: =4688625112+87558560 -> 4776183672 | V45: =10039243858-109919970 -> 9929323888 | W45: =9740096000-4651119 -> 9735444881 | X45: 10632866005 | Y45: 4458944080 | AC45: 10706205000 | AD45: 4498200000 | AE45: 5294940000 | AF45: =SUM(T45:AE45) -> 61733226734 | AL45: =IFERROR(R45-AF45,0) -> 16499273266 | AM45: =IFERROR((R45/AF45)-1,0) -> 0.26726731
B46: 2 | C46: Chai PET B1 Không Phân Loại | D46: Triệu đ | F46: =F8*F27 -> 0 | G46: =G8*G27 -> 0 | H46: =H8*H27 -> 0 | I46: =I8*I27 -> 0 | J46: =J8*J27 -> 0 | K46: =K8*K27 -> 0 | L46: =L8*L27 -> 0 | M46: =M8*M27 -> 0 | ... Q46: =Q8*Q27 -> 0 | R46: =SUM(F46:Q46) -> 0 | Y46: 9257931690 | Z46: 17408694963 | AA46: =16327675670-25082920 -> 16302592750 | AB46: =12966349000+19034856 -> 12985383856 | AF46: =SUM(T46:AE46) -> 55954603259 | AL46: =IFERROR(R46-AF46,0) -> -55954603259 | AM46: =IFERROR((R46/AF46)-1,0) -> -1
B47: 3 | C47: Chai PET B1.3 | D47: Triệu đ | F47: =F9*F28 -> 0 | G47: =G9*G28 -> 0 | H47: =H9*H28 -> 0 | I47: =I9*I28 -> 0 | J47: =J9*J28 -> 0 | K47: =K9*K28 -> 0 | L47: =L9*L28 -> 0 | M47: =M9*M28 -> 0 | ... Q47: =Q9*Q28 -> 0 | R47: =SUM(F47:Q47) -> 0 | X47: 1488403050 | Y47: 950657925 | AF47: =SUM(T47:AE47) -> 2439060975 | AL47: =IFERROR(R47-AF47,0) -> -2439060975 | AM47: =IFERROR((R47/AF47)-1,0) -> -1
B48: 4 | C48: Chai PET B2.1 | D48: Triệu đ | F48: =F10*F29 -> 0 | G48: =G10*G29 -> 0 | H48: =H10*H29 -> 0 | I48: =I10*I29 -> 0 | J48: =J10*J29 -> 0 | K48: =K10*K29 -> 0 | L48: =L10*L29 -> 0 | M48: =M10*M29 -> 0 | ... Q48: =Q10*Q29 -> 0 | R48: =SUM(F48:Q48) -> 0 | AF48: =SUM(T48:AE48) -> 0 | AL48: =IFERROR(R48-AF48,0) -> 0 | AM48: =IFERROR((R48/AF48)-1,0) -> 0
B49: 5 | C49: Chai PET B2.2 | D49: Triệu đ | F49: =F11*F30 -> 243000000 | G49: =G11*G30 -> 189000000 | H49: =H11*H30 -> 270000000 | I49: =I11*I30 -> 337500000 | J49: =J11*J30 -> 337500000 | K49: =K11*K30 -> 337500000 | L49: =L11*L30 -> 337500000 | M49: =M11*M30 -> 337500000 | ... Q49: =Q11*Q30 -> 351000000 | R49: =SUM(F49:Q49) -> 3780000000 | T49: 81890828 | U49: 93637568 | V49: 204518912 | W49: 132980725 | X49: 163641350 | Y49: 165085275 | Z49: 108065230 | AD49: 67729500 | AE49: 179104500 | AF49: =SUM(T49:AE49) -> 1196653888 | AL49: =IFERROR(R49-AF49,0) -> 2583346112 | AM49: =IFERROR((R49/AF49)-1,0) -> 2.1588081
B50: 6 | C50: Chai PET B3 | D50: Triệu đ | F50: =F12*F31 -> 0 | G50: =G12*G31 -> 0 | H50: =H12*H31 -> 0 | I50: =I12*I31 -> 0 | J50: =J12*J31 -> 0 | K50: =K12*K31 -> 0 | L50: =L12*L31 -> 0 | M50: =M12*M31 -> 0 | ... Q50: =Q12*Q31 -> 0 | R50: =SUM(F50:Q50) -> 0 | AF50: =SUM(T50:AE50) -> 0 | AL50: =IFERROR(R50-AF50,0) -> 0 | AM50: =IFERROR((R50/AF50)-1,0) -> 0
B51: 7 | C51: Chai PET B4 | D51: Triệu đ | F51: =F13*F32 -> 135000000 | G51: =G13*G32 -> 105000000 | H51: =H13*H32 -> 150000000 | I51: =I13*I32 -> 180000000 | J51: =J13*J32 -> 180000000 | K51: =K13*K32 -> 180000000 | L51: =L13*L32 -> 180000000 | M51: =M13*M32 -> 180000000 | ... Q51: =Q13*Q32 -> 187200000 | R51: =SUM(F51:Q51) -> 2031600000 | T51: 36450700 | U51: 96003038 | V51: 140393960 | W51: 154688975 | X51: 225146950 | Y51: 240408350 | Z51: 356031194 | AA51: 319666810 | AB51: 263394820 | AC51: 249648000 | AD51: 126156000 | AE51: 129408000 | AF51: =SUM(T51:AE51) -> 2337396797 | AL51: =IFERROR(R51-AF51,0) -> -305796797 | AM51: =IFERROR((R51/AF51)-1,0) -> -0.13082794
B52: 8 | C52: Chai PET B5 | D52: Triệu đ | F52: =F14*F33 -> 189000000 | G52: =G14*G33 -> 147000000 | H52: =H14*H33 -> 210000000 | I52: =I14*I33 -> 270000000 | J52: =J14*J33 -> 270000000 | K52: =K14*K33 -> 270000000 | L52: =L14*L33 -> 270000000 | M52: =M14*M33 -> 270000000 | ... Q52: =Q14*Q33 -> 280800000 | R52: =SUM(F52:Q52) -> 3008400000 | T52: 57859608 | U52: 78235730 | V52: 119610942 | W52: 142589675 | X52: 142555925 | Y52: 202406625 | Z52: 435451071 | AA52: 338472350 | AB52: 244056250 | AC52: 227160000 | AD52: 92880000 | AE52: 136092000 | AF52: =SUM(T52:AE52) -> 2217370176 | AL52: =IFERROR(R52-AF52,0) -> 791029824 | AM52: =IFERROR((R52/AF52)-1,0) -> 0.35674234
B53: 9 | C53: Chai PET B6.1 | D53: Triệu đ | F53: =F15*F34 -> 0 | G53: =G15*G34 -> 0 | H53: =H15*H34 -> 0 | I53: =I15*I34 -> 0 | J53: =J15*J34 -> 0 | K53: =K15*K34 -> 0 | L53: =L15*L34 -> 0 | M53: =M15*M34 -> 0 | ... Q53: =Q15*Q34 -> 0 | R53: =SUM(F53:Q53) -> 0 | V53: 3770748604 | AF53: =SUM(T53:AE53) -> 3770748604 | AL53: =IFERROR(R53-AF53,0) -> -3770748604 | AM53: =IFERROR((R53/AF53)-1,0) -> -1
B54: 10 | C54: Chai PET B6.2 | D54: Triệu đ | F54: =F16*F35 -> 0 | G54: =G16*G35 -> 0 | H54: =H16*H35 -> 0 | I54: =I16*I35 -> 0 | J54: =J16*J35 -> 0 | K54: =K16*K35 -> 0 | L54: =L16*L35 -> 0 | M54: =M16*M35 -> 0 | ... Q54: =Q16*Q35 -> 0 | R54: =SUM(F54:Q54) -> 0 | U54: 1492435320 | W54: 1496891080 | X54: 1514630180 | Y54: 1986849230 | Z54: 609154092 | AA54: 415845830 | AD54: 278371000 | AF54: =SUM(T54:AE54) -> 7794176732 | AL54: =IFERROR(R54-AF54,0) -> -7794176732 | AM54: =IFERROR((R54/AF54)-1,0) -> -1
B55: 11 | C55: Chai PET B7.1 | D55: Triệu đ | F55: =F17*F36 -> 0 | G55: =G17*G36 -> 0 | H55: =H17*H36 -> 0 | I55: =I17*I36 -> 0 | J55: =J17*J36 -> 0 | K55: =K17*K36 -> 0 | L55: =L17*L36 -> 0 | M55: =M17*M36 -> 0 | ... Q55: =Q17*Q36 -> 0 | R55: =SUM(F55:Q55) -> 0 | W55: 3688000 | X55: 1720000 | AB55: 26904000 | AF55: =SUM(T55:AE55) -> 32312000 | AL55: =IFERROR(R55-AF55,0) -> -32312000 | AM55: =IFERROR((R55/AF55)-1,0) -> -1
